Instruction context:
   
 L. 241        90  POP_BLOCK        
                  92  POP_EXCEPT       
->                94  CALL_FINALLY        100  'to 100'
                  96  LOAD_CONST               None
                  98  RETURN_VALUE     
               100_0  COME_FROM            94  '94'
               100_1  COME_FROM_FINALLY    76  '76'
                 100  LOAD_CONST               None
                 102  STORE_FAST               'exc'
                 104  DELETE_FAST              'exc'
                 106  END_FINALLY      
                 108  POP_EXCEPT       
                 110  JUMP_FORWARD        114  'to 114'
               112_0  COME_FROM            68  '68'
                 112  END_FINALLY      
               114_0  COME_FROM           110  '110'
               114_1  COME_FROM            60  '60'
               114_2  COME_FROM            36  '36'
Instruction context:
   
 L. 267       132  POP_BLOCK        
                 134  POP_EXCEPT       
->               136  CALL_FINALLY        142  'to 142'
                 138  LOAD_CONST               None
                 140  RETURN_VALUE     
               142_0  COME_FROM           136  '136'
               142_1  COME_FROM_FINALLY   118  '118'
                 142  LOAD_CONST               None
                 144  STORE_FAST               'exc'
                 146  DELETE_FAST              'exc'
                 148  END_FINALLY      
                 150  POP_EXCEPT       
                 152  JUMP_ABSOLUTE       170  'to 170'
               154_0  COME_FROM           110  '110'
                 154  END_FINALLY      
                 156  JUMP_FORWARD        170  'to 170'
               158_0  COME_FROM            58  '58'
Instruction context:
   
 L. 288        90  POP_BLOCK        
->                92  POP_BLOCK        
               94_96  CALL_FINALLY        378  'to 378'
                  98  LOAD_CONST               None
                 100  RETURN_VALUE     
               102_0  COME_FROM            84  '84'
Instruction context:
   
 L. 374        28  POP_BLOCK        
->                30  LOAD_CONST               None
                  32  RETURN_VALUE     
                34_0  COME_FROM            26  '26'
                34_1  COME_FROM            20  '20'
                34_2  COME_FROM            10  '10'
Instruction context:
   
 L. 507         8  POP_BLOCK        
->                10  LOAD_CONST               None
                  12  RETURN_VALUE     
                14_0  COME_FROM             6  '6'
Instruction context:
   
 L. 541        16  POP_BLOCK        
->                18  POP_BLOCK        
               20_22  CALL_FINALLY        316  'to 316'
                  24  LOAD_CONST               None
                  26  RETURN_VALUE     
                28_0  COME_FROM            14  '14'
Instruction context:
   
 L. 728       216  LOAD_FAST                'total_sent'
                 218  POP_BLOCK        
->               220  CALL_FINALLY        270  'to 270'
                 222  RETURN_VALUE     
               224_0  COME_FROM           214  '214'
Instruction context:
   
 L. 816       118  POP_BLOCK        
->               120  LOAD_CONST               None
                 122  RETURN_VALUE     
               124_0  COME_FROM           116  '116'

test/397.pyc -- 
# decompile failed

# file test/397.pyc
# Deparsing stopped due to parse error
