Instruction context:
   
 L. 218        14  LOAD_CLOSURE             'fields'
                  16  BUILD_TUPLE_1         1 
->                18  LOAD_DICTCOMP            '<code_object <dictcomp>>'
                  20  LOAD_STR                 'sort_attributes.<locals>.<dictcomp>'
                  22  MAKE_FUNCTION_8          'closure'
                  24  LOAD_GLOBAL              enumerate
                  26  LOAD_DEREF               'fields'
                  28  CALL_FUNCTION_1       1  ''
                  30  GET_ITER         
                  32  CALL_FUNCTION_1       1  ''
                  34  STORE_DEREF              'field_order'
                  36  POP_BLOCK        
                  38  JUMP_FORWARD         64  'to 64'
                40_0  COME_FROM_FINALLY    12  '12'
Instruction context:
   
 L. 283       230  POP_EXCEPT       
->               232  LOAD_CONST               None
                 234  RETURN_VALUE     
                 236  END_FINALLY      
               238_0  COME_FROM           222  '222'
Instruction context:
   
 L. 316       150  LOAD_GLOBAL              ErrorDuringImport
                 152  LOAD_FAST                'path'
                 154  LOAD_GLOBAL              sys
                 156  LOAD_METHOD              exc_info
                 158  CALL_METHOD_0         0  ''
                 160  CALL_FUNCTION_2       2  ''
->               162  RAISE_VARARGS_1       1  'exception instance'
                 164  POP_EXCEPT       
                 166  JUMP_FORWARD        170  'to 170'
                 168  END_FINALLY      
Instruction context:
   
 L. 355       192  POP_EXCEPT       
->               194  LOAD_CONST               None
                 196  RETURN_VALUE     
               198_0  COME_FROM           190  '190'
               198_1  COME_FROM           180  '180'
Instruction context:
   
 L. 871   432_434  JUMP_BACK           348  'to 348'
->               436  JUMP_FORWARD        472  'to 472'
               438_0  COME_FROM           424  '424'
               438_1  COME_FROM           412  '412'
Instruction context:
   
 L.1337   616_618  JUMP_BACK           532  'to 532'
->               620  JUMP_FORWARD        654  'to 654'
               622_0  COME_FROM           608  '608'
               622_1  COME_FROM           596  '596'
Instruction context:
   
 L.1496       280  LOAD_LAMBDA              '<code_object <lambda>>'
                 282  LOAD_STR                 'getpager.<locals>.<lambda>'
                 284  MAKE_FUNCTION_0          'Neither defaults, keyword-only args, annotations, nor closures'
                 286  POP_BLOCK        
->               288  CALL_FINALLY        304  'to 304'
                 290  RETURN_VALUE     
               292_0  COME_FROM           276  '276'
               292_1  COME_FROM           256  '256'
Instruction context:
   
 L.1637       164  LOAD_FAST                'object'
->               166  RETURN_VALUE     
Instruction context:
   
 L.2030        40  POP_EXCEPT       
->                42  LOAD_CONST               None
                  44  RETURN_VALUE     
                46_0  COME_FROM            20  '20'
                  46  END_FINALLY      
                48_0  COME_FROM            12  '12'
Instruction context:
   
 L.2138       172  POP_TOP          
             174_176  JUMP_ABSOLUTE       506  'to 506'
->             178_0  COME_FROM           170  '170'
Instruction context:
   
 L.2591       238  LOAD_STR                 ''
                 240  LOAD_METHOD              join
                 242  LOAD_FAST                'fp'
                 244  LOAD_METHOD              readlines
                 246  CALL_METHOD_0         0  ''
                 248  CALL_METHOD_1         1  ''
                 250  POP_BLOCK        
->               252  ROT_TWO          
                 254  BEGIN_FINALLY    
                 256  WITH_CLEANUP_START
                 258  WITH_CLEANUP_FINISH
                 260  POP_FINALLY           0  ''
                 262  RETURN_VALUE     
               264_0  COME_FROM_WITH      234  '234'
                 264  WITH_CLEANUP_START
                 266  WITH_CLEANUP_FINISH
                 268  END_FINALLY      
                 270  JUMP_FORWARD        290  'to 290'
               272_0  COME_FROM           190  '190'
Instruction context:
   
 L.2696       124  POP_TOP          
->               126  POP_BLOCK        
                 128  LOAD_CONST               None
                 130  RETURN_VALUE     
               132_0  COME_FROM           114  '114'

test/504.pyc -- 
# decompile failed

# file test/504.pyc
# Deparsing stopped due to parse error
