Instruction context:
   
 L. 294        52  LOAD_GLOBAL              DoneAndNotDoneFutures
                  54  LOAD_FAST                'done'
                  56  LOAD_FAST                'not_done'
                  58  CALL_FUNCTION_2       2  ''
                  60  POP_BLOCK        
->                62  ROT_TWO          
                  64  BEGIN_FINALLY    
                  66  WITH_CLEANUP_START
                  68  WITH_CLEANUP_FINISH
                  70  POP_FINALLY           0  ''
                  72  RETURN_VALUE     
                74_0  COME_FROM            50  '50'
                74_1  COME_FROM            46  '46'
Instruction context:
   
 L. 336        54  BUILD_TUPLE_4         4 
                  56  BINARY_MODULO    
                  58  POP_BLOCK        
->                60  ROT_TWO          
                  62  BEGIN_FINALLY    
                  64  WITH_CLEANUP_START
                  66  WITH_CLEANUP_FINISH
                  68  POP_FINALLY           0  ''
                  70  RETURN_VALUE     
                72_0  COME_FROM            22  '22'
Instruction context:
   
 L. 360        22  POP_BLOCK        
->                24  BEGIN_FINALLY    
                  26  WITH_CLEANUP_START
                  28  WITH_CLEANUP_FINISH
                  30  POP_FINALLY           0  ''
                  32  LOAD_CONST               False
                  34  RETURN_VALUE     
                36_0  COME_FROM            20  '20'
Instruction context:
   
 L. 374         8  LOAD_FAST                'self'
                  10  LOAD_ATTR                _state
                  12  LOAD_GLOBAL              CANCELLED
                  14  LOAD_GLOBAL              CANCELLED_AND_NOTIFIED
                  16  BUILD_TUPLE_2         2 
                  18  COMPARE_OP               in
                  20  POP_BLOCK        
->                22  ROT_TWO          
                  24  BEGIN_FINALLY    
                  26  WITH_CLEANUP_START
                  28  WITH_CLEANUP_FINISH
                  30  POP_FINALLY           0  ''
                  32  RETURN_VALUE     
                34_0  COME_FROM_WITH        4  '4'
                  34  WITH_CLEANUP_START
                  36  WITH_CLEANUP_FINISH
Instruction context:
   
 L. 379         8  LOAD_FAST                'self'
                  10  LOAD_ATTR                _state
                  12  LOAD_GLOBAL              RUNNING
                  14  COMPARE_OP               ==
                  16  POP_BLOCK        
->                18  ROT_TWO          
                  20  BEGIN_FINALLY    
                  22  WITH_CLEANUP_START
                  24  WITH_CLEANUP_FINISH
                  26  POP_FINALLY           0  ''
                  28  RETURN_VALUE     
                30_0  COME_FROM_WITH        4  '4'
                  30  WITH_CLEANUP_START
                  32  WITH_CLEANUP_FINISH
Instruction context:
   
 L. 384         8  LOAD_FAST                'self'
                  10  LOAD_ATTR                _state
                  12  LOAD_GLOBAL              CANCELLED
                  14  LOAD_GLOBAL              CANCELLED_AND_NOTIFIED
                  16  LOAD_GLOBAL              FINISHED
                  18  BUILD_TUPLE_3         3 
                  20  COMPARE_OP               in
                  22  POP_BLOCK        
->                24  ROT_TWO          
                  26  BEGIN_FINALLY    
                  28  WITH_CLEANUP_START
                  30  WITH_CLEANUP_FINISH
                  32  POP_FINALLY           0  ''
                  34  RETURN_VALUE     
                36_0  COME_FROM_WITH        4  '4'
                  36  WITH_CLEANUP_START
                  38  WITH_CLEANUP_FINISH
Instruction context:
   
 L. 406        36  POP_BLOCK        
->                38  BEGIN_FINALLY    
                  40  WITH_CLEANUP_START
                  42  WITH_CLEANUP_FINISH
                  44  POP_FINALLY           0  ''
                  46  LOAD_CONST               None
                  48  RETURN_VALUE     
                50_0  COME_FROM            22  '22'
                  50  POP_BLOCK        
                  52  BEGIN_FINALLY    
                54_0  COME_FROM_WITH        4  '4'
                  54  WITH_CLEANUP_START
                  56  WITH_CLEANUP_FINISH
                  58  END_FINALLY      
Instruction context:
   
 L. 432        40  LOAD_FAST                'self'
                  42  LOAD_METHOD              _Future__get_result
                  44  CALL_METHOD_0         0  ''
                  46  POP_BLOCK        
->                48  ROT_TWO          
                  50  BEGIN_FINALLY    
                  52  WITH_CLEANUP_START
                  54  WITH_CLEANUP_FINISH
                  56  POP_FINALLY           0  ''
                  58  RETURN_VALUE     
                60_0  COME_FROM            38  '38'
                60_1  COME_FROM            28  '28'
Instruction context:
   
 L. 465        40  LOAD_FAST                'self'
                  42  LOAD_ATTR                _exception
                  44  POP_BLOCK        
->                46  ROT_TWO          
                  48  BEGIN_FINALLY    
                  50  WITH_CLEANUP_START
                  52  WITH_CLEANUP_FINISH
                  54  POP_FINALLY           0  ''
                  56  RETURN_VALUE     
                58_0  COME_FROM            38  '38'
                58_1  COME_FROM            28  '28'
Instruction context:
   
 L. 507        46  POP_BLOCK        
->                48  BEGIN_FINALLY    
                  50  WITH_CLEANUP_START
                  52  WITH_CLEANUP_FINISH
                  54  POP_FINALLY           0  ''
                  56  LOAD_CONST               False
                  58  RETURN_VALUE     
                60_0  COME_FROM            16  '16'

test/518.pyc -- 
# decompile failed

# file test/518.pyc
# Deparsing stopped due to parse error
