# uncompyle6 version 3.7.4
# Python bytecode 3.8 (3413)
# Decompiled from: Python 3.8.11 (default, Aug 17 2021, 15:56:41) 
# [GCC 10.2.1 20210110]
# Embedded file name: site-packages\requests\api.py
"""
requests.api
~~~~~~~~~~~~

This module implements the Requests API.

:copyright: (c) 2012 by Kenneth Reitz.
:license: Apache2, see LICENSE for more details.
"""
from . import sessions

def request--- This code section failed: ---

 L.  60         0  LOAD_GLOBAL              sessions
                2  LOAD_METHOD              Session
                4  CALL_METHOD_0         0  ''
                6  SETUP_WITH           44  'to 44'
                8  STORE_FAST               'session'

 L.  61        10  LOAD_FAST                'session'
               12  LOAD_ATTR                request
               14  BUILD_TUPLE_0         0 
               16  LOAD_FAST                'method'
               18  LOAD_FAST                'url'
               20  LOAD_CONST               ('method', 'url')
               22  BUILD_CONST_KEY_MAP_2     2 
               24  LOAD_FAST                'kwargs'
               26  BUILD_MAP_UNPACK_WITH_CALL_2     2 
               28  CALL_FUNCTION_EX_KW     1  'keyword and positional arguments'
               30  POP_BLOCK        
               32  ROT_TWO          
               34  BEGIN_FINALLY    
               36  WITH_CLEANUP_START
               38  WITH_CLEANUP_FINISH
               40  POP_FINALLY           0  ''
               42  RETURN_VALUE     
             44_0  COME_FROM_WITH        6  '6'
               44  WITH_CLEANUP_START
               46  WITH_CLEANUP_FINISH
               48  END_FINALLY      

Parse error at or near `ROT_TWO' instruction at offset 32


def get(url, params=None, **kwargs):
    r"""Sends a GET request.

    :param url: URL for the new :class:`Request` object.
    :param params: (optional) Dictionary, list of tuples or bytes to send
        in the query string for the :class:`Request`.
    :param \*\*kwargs: Optional arguments that ``request`` takes.
    :return: :class:`Response <Response>` object
    :rtype: requests.Response
    """
    kwargs.setdefault('allow_redirects', True)
    return request('get', url, params=params, **kwargs)


def options(url, **kwargs):
    r"""Sends an OPTIONS request.

    :param url: URL for the new :class:`Request` object.
    :param \*\*kwargs: Optional arguments that ``request`` takes.
    :return: :class:`Response <Response>` object
    :rtype: requests.Response
    """
    kwargs.setdefault('allow_redirects', True)
    return request('options', url, **kwargs)


def head(url, **kwargs):
    r"""Sends a HEAD request.

    :param url: URL for the new :class:`Request` object.
    :param \*\*kwargs: Optional arguments that ``request`` takes. If
        `allow_redirects` is not provided, it will be set to `False` (as
        opposed to the default :meth:`request` behavior).
    :return: :class:`Response <Response>` object
    :rtype: requests.Response
    """
    kwargs.setdefault('allow_redirects', False)
    return request('head', url, **kwargs)


def post(url, data=None, json=None, **kwargs):
    r"""Sends a POST request.

    :param url: URL for the new :class:`Request` object.
    :param data: (optional) Dictionary, list of tuples, bytes, or file-like
        object to send in the body of the :class:`Request`.
    :param json: (optional) json data to send in the body of the :class:`Request`.
    :param \*\*kwargs: Optional arguments that ``request`` takes.
    :return: :class:`Response <Response>` object
    :rtype: requests.Response
    """
    return request('post', url, data=data, json=json, **kwargs)


def put(url, data=None, **kwargs):
    r"""Sends a PUT request.

    :param url: URL for the new :class:`Request` object.
    :param data: (optional) Dictionary, list of tuples, bytes, or file-like
        object to send in the body of the :class:`Request`.
    :param json: (optional) json data to send in the body of the :class:`Request`.
    :param \*\*kwargs: Optional arguments that ``request`` takes.
    :return: :class:`Response <Response>` object
    :rtype: requests.Response
    """
    return request('put', url, data=data, **kwargs)


def patch(url, data=None, **kwargs):
    r"""Sends a PATCH request.

    :param url: URL for the new :class:`Request` object.
    :param data: (optional) Dictionary, list of tuples, bytes, or file-like
        object to send in the body of the :class:`Request`.
    :param json: (optional) json data to send in the body of the :class:`Request`.
    :param \*\*kwargs: Optional arguments that ``request`` takes.
    :return: :class:`Response <Response>` object
    :rtype: requests.Response
    """
    return request('patch', url, data=data, **kwargs)


def delete(url, **kwargs):
    r"""Sends a DELETE request.

    :param url: URL for the new :class:`Request` object.
    :param \*\*kwargs: Optional arguments that ``request`` takes.
    :return: :class:`Response <Response>` object
    :rtype: requests.Response
    """
    return request('delete', url, **kwargs)