# uncompyle6 version 3.7.4
# Python bytecode 2.7 (62211)
# Decompiled from: Python 3.6.15 (default, Sep 28 2021, 20:18:52) 
# [GCC 10.2.1 20210110]
# Embedded file name: template_meter\build\pyi.win32\template_meter\outPYZ1.pyz/threading
"""Thread module emulating a subset of Java's threading model."""
import sys as _sys
try:
    import thread
except ImportError:
    del _sys.modules[__name__]
    raise

import warnings
from time import time as _time, sleep as _sleep
from traceback import format_exc as _format_exc
from collections import deque
__all__ = [
 'activeCount', 'active_count', 'Condition', 'currentThread',
 'current_thread', 'enumerate', 'Event',
 'Lock', 'RLock', 'Semaphore', 'BoundedSemaphore', 'Thread',
 'Timer', 'setprofile', 'settrace', 'local', 'stack_size']
_start_new_thread = thread.start_new_thread
_allocate_lock = thread.allocate_lock
_get_ident = thread.get_ident
ThreadError = thread.error
del thread
warnings.filterwarnings('ignore', category=DeprecationWarning, module='threading', message='sys.exc_clear')
_VERBOSE = False

class _Verbose(object):

    def __init__(self, verbose=None):
        if verbose is None:
            verbose = _VERBOSE
        self.__verbose = verbose
        return

    def _note(self, format, *args):
        if self.__verbose:
            format = format % args
            format = '%s: %s\n' % (
             current_thread().name, format)
            _sys.stderr.write(format)


_profile_hook = None
_trace_hook = None

def setprofile(func):
    global _profile_hook
    _profile_hook = func


def settrace(func):
    global _trace_hook
    _trace_hook = func


Lock = _allocate_lock

def RLock(*args, **kwargs):
    return _RLock(*args, **kwargs)


class _RLock(_Verbose):

    def __init__(self, verbose=None):
        _Verbose.__init__(self, verbose)
        self.__block = _allocate_lock()
        self.__owner = None
        self.__count = 0
        return

    def __repr__(self):
        owner = self.__owner
        try:
            owner = _active[owner].name
        except KeyError:
            pass

        return '<%s owner=%r count=%d>' % (
         self.__class__.__name__, owner, self.__count)

    def acquire(self, blocking=1):
        me = _get_ident()
        if self.__owner == me:
            self.__count = self.__count + 1
            self._note('%s.acquire(%s): recursive success', self, blocking)
            return 1
        rc = self.__block.acquire(blocking)
        if rc:
            self.__owner = me
            self.__count = 1
            self._note('%s.acquire(%s): initial success', self, blocking)
        else:
            self._note('%s.acquire(%s): failure', self, blocking)
        return rc

    __enter__ = acquire

    def release(self):
        if self.__owner != _get_ident():
            raise RuntimeError('cannot release un-acquired lock')
        self.__count = count = self.__count - 1
        if not count:
            self.__owner = None
            self.__block.release()
            self._note('%s.release(): final release', self)
        else:
            self._note('%s.release(): non-final release', self)
        return

    def __exit__(self, t, v, tb):
        self.release()

    def _acquire_restore(self, count_owner):
        count, owner = count_owner
        self.__block.acquire()
        self.__count = count
        self.__owner = owner
        self._note('%s._acquire_restore()', self)

    def _release_save(self):
        self._note('%s._release_save()', self)
        count = self.__count
        self.__count = 0
        owner = self.__owner
        self.__owner = None
        self.__block.release()
        return (count, owner)

    def _is_owned(self):
        return self.__owner == _get_ident()


def Condition(*args, **kwargs):
    return _Condition(*args, **kwargs)


class _Condition(_Verbose):

    def __init__(self, lock=None, verbose=None):
        _Verbose.__init__(self, verbose)
        if lock is None:
            lock = RLock()
        self.__lock = lock
        self.acquire = lock.acquire
        self.release = lock.release
        try:
            self._release_save = lock._release_save
        except AttributeError:
            pass

        try:
            self._acquire_restore = lock._acquire_restore
        except AttributeError:
            pass

        try:
            self._is_owned = lock._is_owned
        except AttributeError:
            pass

        self.__waiters = []
        return

    def __enter__(self):
        return self.__lock.__enter__()

    def __exit__(self, *args):
        return self.__lock.__exit__(*args)

    def __repr__(self):
        return '<Condition(%s, %d)>' % (self.__lock, len(self.__waiters))

    def _release_save(self):
        self.__lock.release()

    def _acquire_restore(self, x):
        self.__lock.acquire()

    def _is_owned(self):
        if self.__lock.acquire(0):
            self.__lock.release()
            return False
        else:
            return True

    def wait(self, timeout=None):
        if not self._is_owned():
            raise RuntimeError('cannot wait on un-acquired lock')
        waiter = _allocate_lock()
        waiter.acquire()
        self.__waiters.append(waiter)
        saved_state = self._release_save()
        try:
            if timeout is None:
                waiter.acquire()
                self._note('%s.wait(): got it', self)
            else:
                endtime = _time() + timeout
                delay = 0.0005
                while True:
                    gotit = waiter.acquire(0)
                    if gotit:
                        break
                    remaining = endtime - _time()
                    if remaining <= 0:
                        break
                    delay = min(delay * 2, remaining, 0.05)
                    _sleep(delay)

                if not gotit:
                    self._note('%s.wait(%s): timed out', self, timeout)
                    try:
                        self.__waiters.remove(waiter)
                    except ValueError:
                        pass

                else:
                    self._note('%s.wait(%s): got it', self, timeout)
        finally:
            self._acquire_restore(saved_state)

        return

    def notify(self, n=1):
        if not self._is_owned():
            raise RuntimeError('cannot notify on un-acquired lock')
        __waiters = self.__waiters
        waiters = __waiters[:n]
        if not waiters:
            self._note('%s.notify(): no waiters', self)
            return
        self._note('%s.notify(): notifying %d waiter%s', self, n, n != 1 and 's' or '')
        for waiter in waiters:
            waiter.release()
            try:
                __waiters.remove(waiter)
            except ValueError:
                pass

    def notifyAll(self):
        self.notify(len(self.__waiters))

    notify_all = notifyAll


def Semaphore(*args, **kwargs):
    return _Semaphore(*args, **kwargs)


class _Semaphore(_Verbose):

    def __init__(self, value=1, verbose=None):
        if value < 0:
            raise ValueError('semaphore initial value must be >= 0')
        _Verbose.__init__(self, verbose)
        self.__cond = Condition(Lock())
        self.__value = value

    def acquire(self, blocking=1):
        rc = False
        self.__cond.acquire()
        while 1:
            if self.__value == 0:
                if not blocking:
                    break
                self._note('%s.acquire(%s): blocked waiting, value=%s', self, blocking, self.__value)
                self.__cond.wait()
        else:
            self.__value = self.__value - 1
            self._note('%s.acquire: success, value=%s', self, self.__value)
            rc = True

        self.__cond.release()
        return rc

    __enter__ = acquire

    def release(self):
        self.__cond.acquire()
        self.__value = self.__value + 1
        self._note('%s.release: success, value=%s', self, self.__value)
        self.__cond.notify()
        self.__cond.release()

    def __exit__(self, t, v, tb):
        self.release()


def BoundedSemaphore(*args, **kwargs):
    return _BoundedSemaphore(*args, **kwargs)


class _BoundedSemaphore(_Semaphore):
    """Semaphore that checks that # releases is <= # acquires"""

    def __init__(self, value=1, verbose=None):
        _Semaphore.__init__(self, value, verbose)
        self._initial_value = value

    def release(self):
        if self._Semaphore__value >= self._initial_value:
            raise ValueError, 'Semaphore released too many times'
        return _Semaphore.release(self)


def Event(*args, **kwargs):
    return _Event(*args, **kwargs)


class _Event(_Verbose):

    def __init__(self, verbose=None):
        _Verbose.__init__(self, verbose)
        self.__cond = Condition(Lock())
        self.__flag = False

    def isSet(self):
        return self.__flag

    is_set = isSet

    def set(self):
        self.__cond.acquire()
        try:
            self.__flag = True
            self.__cond.notify_all()
        finally:
            self.__cond.release()

    def clear(self):
        self.__cond.acquire()
        try:
            self.__flag = False
        finally:
            self.__cond.release()

    def wait(self, timeout=None):
        self.__cond.acquire()
        try:
            if not self.__flag:
                self.__cond.wait(timeout)
            return self.__flag
        finally:
            self.__cond.release()


_counter = 0

def _newname(template='Thread-%d'):
    global _counter
    _counter = _counter + 1
    return template % _counter


_active_limbo_lock = _allocate_lock()
_active = {}
_limbo = {}

class Thread(_Verbose):
    __initialized = False
    __exc_info = _sys.exc_info
    __exc_clear = _sys.exc_clear

    def __init__--- This code section failed: ---

 L. 428         0  LOAD_FAST             1  'group'
                3  LOAD_CONST               None
                6  COMPARE_OP            8  is
                9  POP_JUMP_IF_TRUE     21  'to 21'
               12  LOAD_ASSERT              AssertionError
               15  LOAD_CONST               'group argument must be None for now'
               18  RAISE_VARARGS_2       2  None

 L. 429        21  LOAD_GLOBAL           2  '_Verbose'
               24  LOAD_ATTR             3  '__init__'
               27  LOAD_FAST             0  'self'
               30  LOAD_FAST             6  'verbose'
               33  CALL_FUNCTION_2       2  None
               36  POP_TOP          

 L. 430        37  LOAD_FAST             5  'kwargs'
               40  LOAD_CONST               None
               43  COMPARE_OP            8  is
               46  POP_JUMP_IF_FALSE    58  'to 58'

 L. 431        49  BUILD_MAP_0           0  None
               52  STORE_FAST            5  'kwargs'
               55  JUMP_FORWARD          0  'to 58'
             58_0  COME_FROM            55  '55'

 L. 432        58  LOAD_FAST             2  'target'
               61  LOAD_FAST             0  'self'
               64  STORE_ATTR            4  '__target'

 L. 433        67  LOAD_GLOBAL           5  'str'
               70  LOAD_FAST             3  'name'
               73  JUMP_IF_TRUE_OR_POP    82  'to 82'
               76  LOAD_GLOBAL           6  '_newname'
               79  CALL_FUNCTION_0       0  None
             82_0  COME_FROM            73  '73'
               82  CALL_FUNCTION_1       1  None
               85  LOAD_FAST             0  'self'
               88  STORE_ATTR            7  '__name'

 L. 434        91  LOAD_FAST             4  'args'
               94  LOAD_FAST             0  'self'
               97  STORE_ATTR            8  '__args'

 L. 435       100  LOAD_FAST             5  'kwargs'
              103  LOAD_FAST             0  'self'
              106  STORE_ATTR            9  '__kwargs'

 L. 436       109  LOAD_FAST             0  'self'
              112  LOAD_ATTR            10  '_set_daemon'
              115  CALL_FUNCTION_0       0  None
              118  LOAD_FAST             0  'self'
              121  STORE_ATTR           11  '__daemonic'

 L. 437       124  LOAD_CONST               None
              127  LOAD_FAST             0  'self'
              130  STORE_ATTR           12  '__ident'

 L. 438       133  LOAD_GLOBAL          13  'Event'
              136  CALL_FUNCTION_0       0  None
              139  LOAD_FAST             0  'self'
              142  STORE_ATTR           14  '__started'

 L. 439       145  LOAD_GLOBAL          15  'False'
              148  LOAD_FAST             0  'self'
              151  STORE_ATTR           16  '__stopped'

 L. 440       154  LOAD_GLOBAL          17  'Condition'
              157  LOAD_GLOBAL          18  'Lock'
              160  CALL_FUNCTION_0       0  None
              163  CALL_FUNCTION_1       1  None
              166  LOAD_FAST             0  'self'
              169  STORE_ATTR           19  '__block'

 L. 441       172  LOAD_GLOBAL          20  'True'
              175  LOAD_FAST             0  'self'
              178  STORE_ATTR           21  '__initialized'

 L. 444       181  LOAD_GLOBAL          22  '_sys'
              184  LOAD_ATTR            23  'stderr'
              187  LOAD_FAST             0  'self'
              190  STORE_ATTR           24  '__stderr'
              193  LOAD_CONST               None
              196  RETURN_VALUE     

Parse error at or near `LOAD_CONST' instruction at offset 193

    def _set_daemon(self):
        return current_thread().daemon

    def __repr__--- This code section failed: ---

 L. 451         0  LOAD_FAST             0  'self'
                3  LOAD_ATTR             0  '__initialized'
                6  POP_JUMP_IF_TRUE     18  'to 18'
                9  LOAD_ASSERT              AssertionError
               12  LOAD_CONST               'Thread.__init__() was not called'
               15  RAISE_VARARGS_2       2  None

 L. 452        18  LOAD_CONST               'initial'
               21  STORE_FAST            1  'status'

 L. 453        24  LOAD_FAST             0  'self'
               27  LOAD_ATTR             2  '__started'
               30  LOAD_ATTR             3  'is_set'
               33  CALL_FUNCTION_0       0  None
               36  POP_JUMP_IF_FALSE    48  'to 48'

 L. 454        39  LOAD_CONST               'started'
               42  STORE_FAST            1  'status'
               45  JUMP_FORWARD          0  'to 48'
             48_0  COME_FROM            45  '45'

 L. 455        48  LOAD_FAST             0  'self'
               51  LOAD_ATTR             4  '__stopped'
               54  POP_JUMP_IF_FALSE    66  'to 66'

 L. 456        57  LOAD_CONST               'stopped'
               60  STORE_FAST            1  'status'
               63  JUMP_FORWARD          0  'to 66'
             66_0  COME_FROM            63  '63'

 L. 457        66  LOAD_FAST             0  'self'
               69  LOAD_ATTR             5  '__daemonic'
               72  POP_JUMP_IF_FALSE    88  'to 88'

 L. 458        75  LOAD_FAST             1  'status'
               78  LOAD_CONST               ' daemon'
               81  INPLACE_ADD      
               82  STORE_FAST            1  'status'
               85  JUMP_FORWARD          0  'to 88'
             88_0  COME_FROM            85  '85'

 L. 459        88  LOAD_FAST             0  'self'
               91  LOAD_ATTR             6  '__ident'
               94  LOAD_CONST               None
               97  COMPARE_OP            9  is-not
              100  POP_JUMP_IF_FALSE   123  'to 123'

 L. 460       103  LOAD_FAST             1  'status'
              106  LOAD_CONST               ' %s'
              109  LOAD_FAST             0  'self'
              112  LOAD_ATTR             6  '__ident'
              115  BINARY_MODULO    
              116  INPLACE_ADD      
              117  STORE_FAST            1  'status'
              120  JUMP_FORWARD          0  'to 123'
            123_0  COME_FROM           120  '120'

 L. 461       123  LOAD_CONST               '<%s(%s, %s)>'
              126  LOAD_FAST             0  'self'
              129  LOAD_ATTR             8  '__class__'
              132  LOAD_ATTR             9  '__name__'
              135  LOAD_FAST             0  'self'
              138  LOAD_ATTR            10  '__name'
              141  LOAD_FAST             1  'status'
              144  BUILD_TUPLE_3         3 
              147  BINARY_MODULO    
              148  RETURN_VALUE     

Parse error at or near `BINARY_MODULO' instruction at offset 147

    def start(self):
        global _active_limbo_lock
        if not self.__initialized:
            raise RuntimeError('thread.__init__() not called')
        if self.__started.is_set():
            raise RuntimeError('threads can only be started once')
        self._note('%s.start(): starting thread', self)
        with _active_limbo_lock:
            _limbo[self] = self
        try:
            _start_new_thread(self.__bootstrap, ())
        except Exception:
            with _active_limbo_lock:
                del _limbo[self]
            raise

        self.__started.wait()

    def run(self):
        try:
            if self.__target:
                self.__target(*self.__args, **self.__kwargs)
        finally:
            del self.__target
            del self.__args
            del self.__kwargs

    def __bootstrap(self):
        try:
            self.__bootstrap_inner()
        except:
            if self.__daemonic and _sys is None:
                return
            raise

        return

    def _set_ident(self):
        self.__ident = _get_ident()

    def __bootstrap_inner(self):
        try:
            self._set_ident()
            self.__started.set()
            with _active_limbo_lock:
                _active[self.__ident] = self
                del _limbo[self]
            self._note('%s.__bootstrap(): thread started', self)
            if _trace_hook:
                self._note('%s.__bootstrap(): registering trace hook', self)
                _sys.settrace(_trace_hook)
            if _profile_hook:
                self._note('%s.__bootstrap(): registering profile hook', self)
                _sys.setprofile(_profile_hook)
            try:
                try:
                    self.run()
                except SystemExit:
                    self._note('%s.__bootstrap(): raised SystemExit', self)
                except:
                    self._note('%s.__bootstrap(): unhandled exception', self)
                    if _sys:
                        _sys.stderr.write('Exception in thread %s:\n%s\n' % (
                         self.name, _format_exc()))
                    else:
                        exc_type, exc_value, exc_tb = self.__exc_info()
                        try:
                            print >> self.__stderr, 'Exception in thread ' + self.name + ' (most likely raised during interpreter shutdown):'
                            print >> self.__stderr, 'Traceback (most recent call last):'
                            while exc_tb:
                                print >> self.__stderr, '  File "%s", line %s, in %s' % (
                                 exc_tb.tb_frame.f_code.co_filename,
                                 exc_tb.tb_lineno,
                                 exc_tb.tb_frame.f_code.co_name)
                                exc_tb = exc_tb.tb_next

                            print >> self.__stderr, '%s: %s' % (exc_type, exc_value)
                        finally:
                            del exc_type
                            del exc_value
                            del exc_tb

                else:
                    self._note('%s.__bootstrap(): normal return', self)

            finally:
                self.__exc_clear()

        finally:
            with _active_limbo_lock:
                self.__stop()
                try:
                    del _active[_get_ident()]
                except:
                    pass

    def __stop(self):
        self.__block.acquire()
        self.__stopped = True
        self.__block.notify_all()
        self.__block.release()

    def __delete(self):
        """Remove current thread from the dict of currently running threads."""
        try:
            with _active_limbo_lock:
                del _active[_get_ident()]
        except KeyError:
            if 'dummy_threading' not in _sys.modules:
                raise

    def join(self, timeout=None):
        if not self.__initialized:
            raise RuntimeError('Thread.__init__() not called')
        if not self.__started.is_set():
            raise RuntimeError('cannot join thread before it is started')
        if self is current_thread():
            raise RuntimeError('cannot join current thread')
        if not self.__stopped:
            self._note('%s.join(): waiting until thread stops', self)
        self.__block.acquire()
        try:
            if timeout is None:
                while not self.__stopped:
                    self.__block.wait()

                self._note('%s.join(): thread stopped', self)
            else:
                deadline = _time() + timeout
                while not self.__stopped:
                    delay = deadline - _time()
                    if delay <= 0:
                        self._note('%s.join(): timed out', self)
                        break
                    self.__block.wait(delay)
                else:
                    self._note('%s.join(): thread stopped', self)

        finally:
            self.__block.release()

        return

    @property
    def name--- This code section failed: ---

 L. 662         0  LOAD_FAST             0  'self'
                3  LOAD_ATTR             0  '__initialized'
                6  POP_JUMP_IF_TRUE     18  'to 18'
                9  LOAD_ASSERT              AssertionError
               12  LOAD_CONST               'Thread.__init__() not called'
               15  RAISE_VARARGS_2       2  None

 L. 663        18  LOAD_FAST             0  'self'
               21  LOAD_ATTR             2  '__name'
               24  RETURN_VALUE     
               -1  RETURN_LAST      

Parse error at or near `RETURN_VALUE' instruction at offset 24

    @name.setter
    def name--- This code section failed: ---

 L. 667         0  LOAD_FAST             0  'self'
                3  LOAD_ATTR             0  '__initialized'
                6  POP_JUMP_IF_TRUE     18  'to 18'
                9  LOAD_ASSERT              AssertionError
               12  LOAD_CONST               'Thread.__init__() not called'
               15  RAISE_VARARGS_2       2  None

 L. 668        18  LOAD_GLOBAL           2  'str'
               21  LOAD_FAST             1  'name'
               24  CALL_FUNCTION_1       1  None
               27  LOAD_FAST             0  'self'
               30  STORE_ATTR            3  '__name'

Parse error at or near `LOAD_FAST' instruction at offset 27

    @property
    def ident--- This code section failed: ---

 L. 672         0  LOAD_FAST             0  'self'
                3  LOAD_ATTR             0  '__initialized'
                6  POP_JUMP_IF_TRUE     18  'to 18'
                9  LOAD_ASSERT              AssertionError
               12  LOAD_CONST               'Thread.__init__() not called'
               15  RAISE_VARARGS_2       2  None

 L. 673        18  LOAD_FAST             0  'self'
               21  LOAD_ATTR             2  '__ident'
               24  RETURN_VALUE     
               -1  RETURN_LAST      

Parse error at or near `RETURN_VALUE' instruction at offset 24

    def isAlive--- This code section failed: ---

 L. 676         0  LOAD_FAST             0  'self'
                3  LOAD_ATTR             0  '__initialized'
                6  POP_JUMP_IF_TRUE     18  'to 18'
                9  LOAD_ASSERT              AssertionError
               12  LOAD_CONST               'Thread.__init__() not called'
               15  RAISE_VARARGS_2       2  None

 L. 677        18  LOAD_FAST             0  'self'
               21  LOAD_ATTR             2  '__started'
               24  LOAD_ATTR             3  'is_set'
               27  CALL_FUNCTION_0       0  None
               30  JUMP_IF_FALSE_OR_POP    40  'to 40'
               33  LOAD_FAST             0  'self'
               36  LOAD_ATTR             4  '__stopped'
               39  UNARY_NOT        
             40_0  COME_FROM            30  '30'
               40  RETURN_VALUE     
               -1  RETURN_LAST      

Parse error at or near `RETURN_VALUE' instruction at offset 40

    is_alive = isAlive

    @property
    def daemon--- This code section failed: ---

 L. 683         0  LOAD_FAST             0  'self'
                3  LOAD_ATTR             0  '__initialized'
                6  POP_JUMP_IF_TRUE     18  'to 18'
                9  LOAD_ASSERT              AssertionError
               12  LOAD_CONST               'Thread.__init__() not called'
               15  RAISE_VARARGS_2       2  None

 L. 684        18  LOAD_FAST             0  'self'
               21  LOAD_ATTR             2  '__daemonic'
               24  RETURN_VALUE     
               -1  RETURN_LAST      

Parse error at or near `RETURN_VALUE' instruction at offset 24

    @daemon.setter
    def daemon(self, daemonic):
        if not self.__initialized:
            raise RuntimeError('Thread.__init__() not called')
        if self.__started.is_set():
            raise RuntimeError('cannot set daemon status of active thread')
        self.__daemonic = daemonic

    def isDaemon(self):
        return self.daemon

    def setDaemon(self, daemonic):
        self.daemon = daemonic

    def getName(self):
        return self.name

    def setName(self, name):
        self.name = name


def Timer(*args, **kwargs):
    return _Timer(*args, **kwargs)


class _Timer(Thread):
    """Call a function after a specified number of seconds:

    t = Timer(30.0, f, args=[], kwargs={})
    t.start()
    t.cancel() # stop the timer's action if it's still waiting
    """

    def __init__(self, interval, function, args=[], kwargs={}):
        Thread.__init__(self)
        self.interval = interval
        self.function = function
        self.args = args
        self.kwargs = kwargs
        self.finished = Event()

    def cancel(self):
        """Stop the timer if it hasn't finished yet"""
        self.finished.set()

    def run(self):
        self.finished.wait(self.interval)
        if not self.finished.is_set():
            self.function(*self.args, **self.kwargs)
        self.finished.set()


class _MainThread(Thread):

    def __init__(self):
        Thread.__init__(self, name='MainThread')
        self._Thread__started.set()
        self._set_ident()
        with _active_limbo_lock:
            _active[_get_ident()] = self

    def _set_daemon(self):
        return False

    def _exitfunc(self):
        self._Thread__stop()
        t = _pickSomeNonDaemonThread()
        if t:
            self._note('%s: waiting for other threads', self)
        while t:
            t.join()
            t = _pickSomeNonDaemonThread()

        self._note('%s: exiting', self)
        self._Thread__delete()


def _pickSomeNonDaemonThread():
    for t in enumerate():
        if not t.daemon and t.is_alive():
            return t

    return


class _DummyThread(Thread):

    def __init__(self):
        Thread.__init__(self, name=_newname('Dummy-%d'))
        del self._Thread__block
        self._Thread__started.set()
        self._set_ident()
        with _active_limbo_lock:
            _active[_get_ident()] = self

    def _set_daemon(self):
        return True

    def join--- This code section failed: ---

 L. 799         0  LOAD_GLOBAL           0  'False'
                3  POP_JUMP_IF_TRUE     15  'to 15'
                6  LOAD_ASSERT              AssertionError
                9  LOAD_CONST               'cannot join a dummy thread'
               12  RAISE_VARARGS_2       2  None

Parse error at or near `None' instruction at offset -1


def currentThread():
    try:
        return _active[_get_ident()]
    except KeyError:
        return _DummyThread()


current_thread = currentThread

def activeCount():
    with _active_limbo_lock:
        return len(_active) + len(_limbo)


active_count = activeCount

def _enumerate():
    return _active.values() + _limbo.values()


def enumerate():
    with _active_limbo_lock:
        return _active.values() + _limbo.values()


from thread import stack_size
_shutdown = _MainThread()._exitfunc
try:
    from thread import _local as local
except ImportError:
    from _threading_local import local

def _after_fork():
    global _active_limbo_lock
    _active_limbo_lock = _allocate_lock()
    new_active = {}
    current = current_thread()
    with _active_limbo_lock:
        for thread in _active.itervalues():
            if thread is current:
                ident = _get_ident()
                thread._Thread__ident = ident
                new_active[ident] = thread
            else:
                thread._Thread__stopped = True

        _limbo.clear()
        _active.clear()
        _active.update(new_active)
        assert len(_active) == 1


def _test():

    class BoundedQueue(_Verbose):

        def __init__(self, limit):
            _Verbose.__init__(self)
            self.mon = RLock()
            self.rc = Condition(self.mon)
            self.wc = Condition(self.mon)
            self.limit = limit
            self.queue = deque()

        def put(self, item):
            self.mon.acquire()
            while len(self.queue) >= self.limit:
                self._note('put(%s): queue full', item)
                self.wc.wait()

            self.queue.append(item)
            self._note('put(%s): appended, length now %d', item, len(self.queue))
            self.rc.notify()
            self.mon.release()

        def get(self):
            self.mon.acquire()
            while not self.queue:
                self._note('get(): queue empty')
                self.rc.wait()

            item = self.queue.popleft()
            self._note('get(): got %s, %d left', item, len(self.queue))
            self.wc.notify()
            self.mon.release()
            return item

    class ProducerThread(Thread):

        def __init__(self, queue, quota):
            Thread.__init__(self, name='Producer')
            self.queue = queue
            self.quota = quota

        def run(self):
            from random import random
            counter = 0
            while counter < self.quota:
                counter = counter + 1
                self.queue.put('%s.%d' % (self.name, counter))
                _sleep(random() * 1e-05)

    class ConsumerThread(Thread):

        def __init__(self, queue, count):
            Thread.__init__(self, name='Consumer')
            self.queue = queue
            self.count = count

        def run(self):
            while self.count > 0:
                item = self.queue.get()
                print item
                self.count = self.count - 1

    NP = 3
    QL = 4
    NI = 5
    Q = BoundedQueue(QL)
    P = []
    for i in range(NP):
        t = ProducerThread(Q, NI)
        t.name = 'Producer-%d' % (i + 1)
        P.append(t)

    C = ConsumerThread(Q, NI * NP)
    for t in P:
        t.start()
        _sleep(1e-06)

    C.start()
    for t in P:
        t.join()

    C.join()


if __name__ == '__main__':
    _test()