Instruction context:
   
 L. 177        18  LOAD_FAST                'object'
                  20  LOAD_ATTR                __code__
                  22  LOAD_ATTR                co_flags
                  24  LOAD_GLOBAL              CO_GENERATOR
                  26  BINARY_AND       
                28_0  COME_FROM            16  '16'
->                28  CALL_FUNCTION_1       1  '1 positional argument'
                  30  RETURN_VALUE     
Instruction context:
   
 L. 185        18  LOAD_FAST                'object'
                  20  LOAD_ATTR                __code__
                  22  LOAD_ATTR                co_flags
                  24  LOAD_GLOBAL              CO_COROUTINE
                  26  BINARY_AND       
                28_0  COME_FROM            16  '16'
->                28  CALL_FUNCTION_1       1  '1 positional argument'
                  30  RETURN_VALUE     
Instruction context:
   
 L. 194        18  LOAD_FAST                'object'
                  20  LOAD_ATTR                __code__
                  22  LOAD_ATTR                co_flags
                  24  LOAD_GLOBAL              CO_ASYNC_GENERATOR
                  26  BINARY_AND       
                28_0  COME_FROM            16  '16'
->                28  CALL_FUNCTION_1       1  '1 positional argument'
                  30  RETURN_VALUE     
Instruction context:
   
 L.1859       138  LOAD_GLOBAL              isinstance
                 140  LOAD_FAST                'annotations'
                 142  LOAD_GLOBAL              dict
                 144  CALL_FUNCTION_2       2  '2 positional arguments'
               146_0  COME_FROM           136  '136'
               146_1  COME_FROM           118  '118'
->             146_2  COME_FROM           100  '100'
               146_3  COME_FROM            90  '90'
                 146  RETURN_VALUE     

test/129.pyc -- 
# decompile failed

# file test/129.pyc
# Deparsing stopped due to parse error
