
# file test/101041.pyc
# --- This code section failed: ---

 L.   1         0  LOAD_STR                 'Utilities for with-statement contexts.  See PEP 343.'
                2  STORE_NAME               __doc__

 L.   2         4  LOAD_CONST               0
                6  LOAD_CONST               None
                8  IMPORT_NAME              abc
               10  STORE_NAME               abc

 L.   3        12  LOAD_CONST               0
               14  LOAD_CONST               None
               16  IMPORT_NAME              sys
               18  STORE_NAME               sys

 L.   4        20  LOAD_CONST               0
               22  LOAD_CONST               None
               24  IMPORT_NAME              _collections_abc
               26  STORE_NAME               _collections_abc

 L.   5        28  LOAD_CONST               0
               30  LOAD_CONST               ('deque',)
               32  IMPORT_NAME              collections
               34  IMPORT_FROM              deque
               36  STORE_NAME               deque
               38  POP_TOP          

 L.   6        40  LOAD_CONST               0
               42  LOAD_CONST               ('wraps',)
               44  IMPORT_NAME              functools
               46  IMPORT_FROM              wraps
               48  STORE_NAME               wraps
               50  POP_TOP          

 L.   7        52  LOAD_CONST               0
               54  LOAD_CONST               ('MethodType', 'GenericAlias')
               56  IMPORT_NAME              types
               58  IMPORT_FROM              MethodType
               60  STORE_NAME               MethodType
               62  IMPORT_FROM              GenericAlias
               64  STORE_NAME               GenericAlias
               66  POP_TOP          

 L.   9        68  BUILD_LIST_0          0 
               70  LOAD_CONST               ('asynccontextmanager', 'contextmanager', 'closing', 'nullcontext', 'AbstractContextManager', 'AbstractAsyncContextManager', 'AsyncExitStack', 'ContextDecorator', 'ExitStack', 'redirect_stdout', 'redirect_stderr', 'suppress')
               72  CALL_FINALLY         75  'to 75'
               74  STORE_NAME               __all__

 L.  15        76  LOAD_BUILD_CLASS 
               78  LOAD_CODE                <code_object AbstractContextManager>
               80  LOAD_STR                 'AbstractContextManager'
               82  MAKE_FUNCTION_0          'Neither defaults, keyword-only args, annotations, nor closures'
               84  LOAD_STR                 'AbstractContextManager'
               86  LOAD_NAME                abc
               88  LOAD_ATTR                ABC
               90  CALL_FUNCTION_3       3  ''
               92  STORE_NAME               AbstractContextManager

 L.  37        94  LOAD_BUILD_CLASS 
               96  LOAD_CODE                <code_object AbstractAsyncContextManager>
               98  LOAD_STR                 'AbstractAsyncContextManager'
              100  MAKE_FUNCTION_0          'Neither defaults, keyword-only args, annotations, nor closures'
              102  LOAD_STR                 'AbstractAsyncContextManager'
              104  LOAD_NAME                abc
              106  LOAD_ATTR                ABC
              108  CALL_FUNCTION_3       3  ''
              110  STORE_NAME               AbstractAsyncContextManager

 L.  60       112  LOAD_BUILD_CLASS 
              114  LOAD_CODE                <code_object ContextDecorator>
              116  LOAD_STR                 'ContextDecorator'
              118  MAKE_FUNCTION_0          'Neither defaults, keyword-only args, annotations, nor closures'
              120  LOAD_STR                 'ContextDecorator'
              122  LOAD_NAME                object
              124  CALL_FUNCTION_3       3  ''
              126  STORE_NAME               ContextDecorator

 L.  83       128  LOAD_BUILD_CLASS 
              130  LOAD_CODE                <code_object _GeneratorContextManagerBase>
              132  LOAD_STR                 '_GeneratorContextManagerBase'
              134  MAKE_FUNCTION_0          'Neither defaults, keyword-only args, annotations, nor closures'
              136  LOAD_STR                 '_GeneratorContextManagerBase'
              138  CALL_FUNCTION_2       2  ''
              140  STORE_NAME               _GeneratorContextManagerBase

 L. 101       142  LOAD_BUILD_CLASS 
              144  LOAD_CODE                <code_object _GeneratorContextManager>
              146  LOAD_STR                 '_GeneratorContextManager'
              148  MAKE_FUNCTION_0          'Neither defaults, keyword-only args, annotations, nor closures'
              150  LOAD_STR                 '_GeneratorContextManager'
              152  LOAD_NAME                _GeneratorContextManagerBase

 L. 102       154  LOAD_NAME                AbstractContextManager

 L. 103       156  LOAD_NAME                ContextDecorator

 L. 101       158  CALL_FUNCTION_5       5  ''
              160  STORE_NAME               _GeneratorContextManager

 L. 169       162  LOAD_BUILD_CLASS 
              164  LOAD_CODE                <code_object _AsyncGeneratorContextManager>
              166  LOAD_STR                 '_AsyncGeneratorContextManager'
              168  MAKE_FUNCTION_0          'Neither defaults, keyword-only args, annotations, nor closures'
              170  LOAD_STR                 '_AsyncGeneratorContextManager'
              172  LOAD_NAME                _GeneratorContextManagerBase

 L. 170       174  LOAD_NAME                AbstractAsyncContextManager

 L. 169       176  CALL_FUNCTION_4       4  ''
              178  STORE_NAME               _AsyncGeneratorContextManager

 L. 215       180  LOAD_CODE                <code_object contextmanager>
              182  LOAD_STR                 'contextmanager'
              184  MAKE_FUNCTION_0          'Neither defaults, keyword-only args, annotations, nor closures'
              186  STORE_NAME               contextmanager

 L. 248       188  LOAD_CODE                <code_object asynccontextmanager>
              190  LOAD_STR                 'asynccontextmanager'
              192  MAKE_FUNCTION_0          'Neither defaults, keyword-only args, annotations, nor closures'
              194  STORE_NAME               asynccontextmanager

 L. 281       196  LOAD_BUILD_CLASS 
              198  LOAD_CODE                <code_object closing>
              200  LOAD_STR                 'closing'
              202  MAKE_FUNCTION_0          'Neither defaults, keyword-only args, annotations, nor closures'
              204  LOAD_STR                 'closing'
              206  LOAD_NAME                AbstractContextManager
              208  CALL_FUNCTION_3       3  ''
              210  STORE_NAME               closing

 L. 306       212  LOAD_BUILD_CLASS 
              214  LOAD_CODE                <code_object _RedirectStream>
              216  LOAD_STR                 '_RedirectStream'
              218  MAKE_FUNCTION_0          'Neither defaults, keyword-only args, annotations, nor closures'
              220  LOAD_STR                 '_RedirectStream'
              222  LOAD_NAME                AbstractContextManager
              224  CALL_FUNCTION_3       3  ''
              226  STORE_NAME               _RedirectStream

 L. 324       228  LOAD_BUILD_CLASS 
              230  LOAD_CODE                <code_object redirect_stdout>
              232  LOAD_STR                 'redirect_stdout'
              234  MAKE_FUNCTION_0          'Neither defaults, keyword-only args, annotations, nor closures'
              236  LOAD_STR                 'redirect_stdout'
              238  LOAD_NAME                _RedirectStream
              240  CALL_FUNCTION_3       3  ''
              242  STORE_NAME               redirect_stdout

 L. 340       244  LOAD_BUILD_CLASS 
              246  LOAD_CODE                <code_object redirect_stderr>
              248  LOAD_STR                 'redirect_stderr'
              250  MAKE_FUNCTION_0          'Neither defaults, keyword-only args, annotations, nor closures'
              252  LOAD_STR                 'redirect_stderr'
              254  LOAD_NAME                _RedirectStream
              256  CALL_FUNCTION_3       3  ''
              258  STORE_NAME               redirect_stderr

 L. 346       260  LOAD_BUILD_CLASS 
              262  LOAD_CODE                <code_object suppress>
              264  LOAD_STR                 'suppress'
              266  MAKE_FUNCTION_0          'Neither defaults, keyword-only args, annotations, nor closures'
              268  LOAD_STR                 'suppress'
              270  LOAD_NAME                AbstractContextManager
              272  CALL_FUNCTION_3       3  ''
              274  STORE_NAME               suppress

 L. 376       276  LOAD_BUILD_CLASS 
              278  LOAD_CODE                <code_object _BaseExitStack>
              280  LOAD_STR                 '_BaseExitStack'
              282  MAKE_FUNCTION_0          'Neither defaults, keyword-only args, annotations, nor closures'
              284  LOAD_STR                 '_BaseExitStack'
              286  CALL_FUNCTION_2       2  ''
              288  STORE_NAME               _BaseExitStack

 L. 456       290  LOAD_BUILD_CLASS 
              292  LOAD_CODE                <code_object ExitStack>
              294  LOAD_STR                 'ExitStack'
              296  MAKE_FUNCTION_0          'Neither defaults, keyword-only args, annotations, nor closures'
              298  LOAD_STR                 'ExitStack'
              300  LOAD_NAME                _BaseExitStack
              302  LOAD_NAME                AbstractContextManager
              304  CALL_FUNCTION_4       4  ''
              306  STORE_NAME               ExitStack

 L. 525       308  LOAD_BUILD_CLASS 
              310  LOAD_CODE                <code_object AsyncExitStack>
              312  LOAD_STR                 'AsyncExitStack'
              314  MAKE_FUNCTION_0          'Neither defaults, keyword-only args, annotations, nor closures'
              316  LOAD_STR                 'AsyncExitStack'
              318  LOAD_NAME                _BaseExitStack
              320  LOAD_NAME                AbstractAsyncContextManager
              322  CALL_FUNCTION_4       4  ''
              324  STORE_NAME               AsyncExitStack

 L. 658       326  LOAD_BUILD_CLASS 
              328  LOAD_CODE                <code_object nullcontext>
              330  LOAD_STR                 'nullcontext'
              332  MAKE_FUNCTION_0          'Neither defaults, keyword-only args, annotations, nor closures'
              334  LOAD_STR                 'nullcontext'
              336  LOAD_NAME                AbstractContextManager
              338  CALL_FUNCTION_3       3  ''
              340  STORE_NAME               nullcontext

Parse error at or near `CALL_FINALLY' instruction at offset 72

Instruction context:
   
 L.   9        68  BUILD_LIST_0          0 
                  70  LOAD_CONST               ('asynccontextmanager', 'contextmanager', 'closing', 'nullcontext', 'AbstractContextManager', 'AbstractAsyncContextManager', 'AsyncExitStack', 'ContextDecorator', 'ExitStack', 'redirect_stdout', 'redirect_stderr', 'suppress')
->                72  CALL_FINALLY         75  'to 75'
                  74  STORE_NAME               __all__

test/101041.pyc -- 
# decompile failed
