Instruction context:
   
 L.  15        68  BUILD_LIST_0          0 
                  70  LOAD_CONST               ('compile', 'main', 'PyCompileError', 'PycInvalidationMode')
->                72  CALL_FINALLY         75  'to 75'
                  74  STORE_NAME               __all__

test/101081.pyc -- 
# decompile failed

# file test/101081.pyc
# --- This code section failed: ---

 L.   1         0  LOAD_STR                 'Routine to "compile" a .py file to a .pyc file.\n\nThis module has intimate knowledge of the format of .pyc files.\n'
                2  STORE_NAME               __doc__

 L.   6         4  LOAD_CONST               0
                6  LOAD_CONST               None
                8  IMPORT_NAME              enum
               10  STORE_NAME               enum

 L.   7        12  LOAD_CONST               0
               14  LOAD_CONST               None
               16  IMPORT_NAME_ATTR         importlib._bootstrap_external
               18  STORE_NAME               importlib

 L.   8        20  LOAD_CONST               0
               22  LOAD_CONST               None
               24  IMPORT_NAME_ATTR         importlib.machinery
               26  STORE_NAME               importlib

 L.   9        28  LOAD_CONST               0
               30  LOAD_CONST               None
               32  IMPORT_NAME_ATTR         importlib.util
               34  STORE_NAME               importlib

 L.  10        36  LOAD_CONST               0
               38  LOAD_CONST               None
               40  IMPORT_NAME              os
               42  STORE_NAME               os

 L.  11        44  LOAD_CONST               0
               46  LOAD_CONST               None
               48  IMPORT_NAME_ATTR         os.path
               50  STORE_NAME               os

 L.  12        52  LOAD_CONST               0
               54  LOAD_CONST               None
               56  IMPORT_NAME              sys
               58  STORE_NAME               sys

 L.  13        60  LOAD_CONST               0
               62  LOAD_CONST               None
               64  IMPORT_NAME              traceback
               66  STORE_NAME               traceback

 L.  15        68  BUILD_LIST_0          0 
               70  LOAD_CONST               ('compile', 'main', 'PyCompileError', 'PycInvalidationMode')
               72  CALL_FINALLY         75  'to 75'
               74  STORE_NAME               __all__

 L.  18        76  LOAD_BUILD_CLASS 
               78  LOAD_CODE                <code_object PyCompileError>
               80  LOAD_STR                 'PyCompileError'
               82  MAKE_FUNCTION_0          'Neither defaults, keyword-only args, annotations, nor closures'
               84  LOAD_STR                 'PyCompileError'
               86  LOAD_NAME                Exception
               88  CALL_FUNCTION_3       3  ''
               90  STORE_NAME               PyCompileError

 L.  66        92  LOAD_BUILD_CLASS 
               94  LOAD_CODE                <code_object PycInvalidationMode>
               96  LOAD_STR                 'PycInvalidationMode'
               98  MAKE_FUNCTION_0          'Neither defaults, keyword-only args, annotations, nor closures'
              100  LOAD_STR                 'PycInvalidationMode'
              102  LOAD_NAME                enum
              104  LOAD_ATTR                Enum
              106  CALL_FUNCTION_3       3  ''
              108  STORE_NAME               PycInvalidationMode

 L.  72       110  LOAD_CODE                <code_object _get_default_invalidation_mode>
              112  LOAD_STR                 '_get_default_invalidation_mode'
              114  MAKE_FUNCTION_0          'Neither defaults, keyword-only args, annotations, nor closures'
              116  STORE_NAME               _get_default_invalidation_mode

 L.  79       118  LOAD_CONST               (None, None, False, -1, None, 0)
              120  LOAD_CODE                <code_object compile>
              122  LOAD_STR                 'compile'
              124  MAKE_FUNCTION_1          'default'
              126  STORE_NAME               compile

 L. 176       128  LOAD_CONST               (None,)
              130  LOAD_CODE                <code_object main>
              132  LOAD_STR                 'main'
              134  MAKE_FUNCTION_1          'default'
              136  STORE_NAME               main

 L. 214       138  LOAD_NAME                __name__
              140  LOAD_STR                 '__main__'
              142  COMPARE_OP               ==
              144  POP_JUMP_IF_FALSE   158  'to 158'

 L. 215       146  LOAD_NAME                sys
              148  LOAD_METHOD              exit
              150  LOAD_NAME                main
              152  CALL_FUNCTION_0       0  ''
              154  CALL_METHOD_1         1  ''
              156  POP_TOP          
            158_0  COME_FROM           144  '144'

Parse error at or near `CALL_FINALLY' instruction at offset 72

