
# file test/101129.pyc
# --- This code section failed: ---

 L.   1         0  LOAD_STR                 'Event loop and event loop policy.'
                2  STORE_NAME               __doc__

 L.   3         4  LOAD_CONST               ('AbstractEventLoopPolicy', 'AbstractEventLoop', 'AbstractServer', 'Handle', 'TimerHandle', 'get_event_loop_policy', 'set_event_loop_policy', 'get_event_loop', 'set_event_loop', 'new_event_loop', 'get_child_watcher', 'set_child_watcher', '_set_running_loop', 'get_running_loop', '_get_running_loop')
                6  STORE_NAME               __all__

 L.  14         8  LOAD_CONST               0
               10  LOAD_CONST               None
               12  IMPORT_NAME              contextvars
               14  STORE_NAME               contextvars

 L.  15        16  LOAD_CONST               0
               18  LOAD_CONST               None
               20  IMPORT_NAME              os
               22  STORE_NAME               os

 L.  16        24  LOAD_CONST               0
               26  LOAD_CONST               None
               28  IMPORT_NAME              socket
               30  STORE_NAME               socket

 L.  17        32  LOAD_CONST               0
               34  LOAD_CONST               None
               36  IMPORT_NAME              subprocess
               38  STORE_NAME               subprocess

 L.  18        40  LOAD_CONST               0
               42  LOAD_CONST               None
               44  IMPORT_NAME              sys
               46  STORE_NAME               sys

 L.  19        48  LOAD_CONST               0
               50  LOAD_CONST               None
               52  IMPORT_NAME              threading
               54  STORE_NAME               threading

 L.  21        56  LOAD_CONST               1
               58  LOAD_CONST               ('format_helpers',)
               60  IMPORT_NAME              
               62  IMPORT_FROM              format_helpers
               64  STORE_NAME               format_helpers
               66  POP_TOP          

 L.  24        68  LOAD_BUILD_CLASS 
               70  LOAD_CODE                <code_object Handle>
               72  LOAD_STR                 'Handle'
               74  MAKE_FUNCTION_0          'Neither defaults, keyword-only args, annotations, nor closures'
               76  LOAD_STR                 'Handle'
               78  CALL_FUNCTION_2       2  ''
               80  STORE_NAME               Handle

 L.  98        82  LOAD_BUILD_CLASS 
               84  LOAD_CODE                <code_object TimerHandle>
               86  LOAD_STR                 'TimerHandle'
               88  MAKE_FUNCTION_0          'Neither defaults, keyword-only args, annotations, nor closures'
               90  LOAD_STR                 'TimerHandle'
               92  LOAD_NAME                Handle
               94  CALL_FUNCTION_3       3  ''
               96  STORE_NAME               TimerHandle

 L. 162        98  LOAD_BUILD_CLASS 
              100  LOAD_CODE                <code_object AbstractServer>
              102  LOAD_STR                 'AbstractServer'
              104  MAKE_FUNCTION_0          'Neither defaults, keyword-only args, annotations, nor closures'
              106  LOAD_STR                 'AbstractServer'
              108  CALL_FUNCTION_2       2  ''
              110  STORE_NAME               AbstractServer

 L. 204       112  LOAD_BUILD_CLASS 
              114  LOAD_CODE                <code_object AbstractEventLoop>
              116  LOAD_STR                 'AbstractEventLoop'
              118  MAKE_FUNCTION_0          'Neither defaults, keyword-only args, annotations, nor closures'
              120  LOAD_STR                 'AbstractEventLoop'
              122  CALL_FUNCTION_2       2  ''
              124  STORE_NAME               AbstractEventLoop

 L. 575       126  LOAD_BUILD_CLASS 
              128  LOAD_CODE                <code_object AbstractEventLoopPolicy>
              130  LOAD_STR                 'AbstractEventLoopPolicy'
              132  MAKE_FUNCTION_0          'Neither defaults, keyword-only args, annotations, nor closures'
              134  LOAD_STR                 'AbstractEventLoopPolicy'
              136  CALL_FUNCTION_2       2  ''
              138  STORE_NAME               AbstractEventLoopPolicy

 L. 609       140  LOAD_BUILD_CLASS 
              142  LOAD_CODE                <code_object BaseDefaultEventLoopPolicy>
              144  LOAD_STR                 'BaseDefaultEventLoopPolicy'
              146  MAKE_FUNCTION_0          'Neither defaults, keyword-only args, annotations, nor closures'
              148  LOAD_STR                 'BaseDefaultEventLoopPolicy'
              150  LOAD_NAME                AbstractEventLoopPolicy
              152  CALL_FUNCTION_3       3  ''
              154  STORE_NAME               BaseDefaultEventLoopPolicy

 L. 666       156  LOAD_CONST               None
              158  STORE_GLOBAL             _event_loop_policy

 L. 669       160  LOAD_NAME                threading
              162  LOAD_METHOD              Lock
              164  CALL_METHOD_0         0  ''
              166  STORE_NAME               _lock

 L. 673       168  LOAD_BUILD_CLASS 
              170  LOAD_CODE                <code_object _RunningLoop>
              172  LOAD_STR                 '_RunningLoop'
              174  MAKE_FUNCTION_0          'Neither defaults, keyword-only args, annotations, nor closures'
              176  LOAD_STR                 '_RunningLoop'
              178  LOAD_NAME                threading
              180  LOAD_ATTR                local
              182  CALL_FUNCTION_3       3  ''
              184  STORE_NAME               _RunningLoop

 L. 677       186  LOAD_NAME                _RunningLoop
              188  CALL_FUNCTION_0       0  ''
              190  STORE_NAME               _running_loop

 L. 680       192  LOAD_CODE                <code_object get_running_loop>
              194  LOAD_STR                 'get_running_loop'
              196  MAKE_FUNCTION_0          'Neither defaults, keyword-only args, annotations, nor closures'
              198  STORE_NAME               get_running_loop

 L. 692       200  LOAD_CODE                <code_object _get_running_loop>
              202  LOAD_STR                 '_get_running_loop'
              204  MAKE_FUNCTION_0          'Neither defaults, keyword-only args, annotations, nor closures'
              206  STORE_NAME               _get_running_loop

 L. 704       208  LOAD_CODE                <code_object _set_running_loop>
              210  LOAD_STR                 '_set_running_loop'
              212  MAKE_FUNCTION_0          'Neither defaults, keyword-only args, annotations, nor closures'
              214  STORE_NAME               _set_running_loop

 L. 714       216  LOAD_CODE                <code_object _init_event_loop_policy>
              218  LOAD_STR                 '_init_event_loop_policy'
              220  MAKE_FUNCTION_0          'Neither defaults, keyword-only args, annotations, nor closures'
              222  STORE_NAME               _init_event_loop_policy

 L. 722       224  LOAD_CODE                <code_object get_event_loop_policy>
              226  LOAD_STR                 'get_event_loop_policy'
              228  MAKE_FUNCTION_0          'Neither defaults, keyword-only args, annotations, nor closures'
              230  STORE_NAME               get_event_loop_policy

 L. 729       232  LOAD_CODE                <code_object set_event_loop_policy>
              234  LOAD_STR                 'set_event_loop_policy'
              236  MAKE_FUNCTION_0          'Neither defaults, keyword-only args, annotations, nor closures'
              238  STORE_NAME               set_event_loop_policy

 L. 738       240  LOAD_CODE                <code_object get_event_loop>
              242  LOAD_STR                 'get_event_loop'
              244  MAKE_FUNCTION_0          'Neither defaults, keyword-only args, annotations, nor closures'
              246  STORE_NAME               get_event_loop

 L. 754       248  LOAD_CODE                <code_object set_event_loop>
              250  LOAD_STR                 'set_event_loop'
              252  MAKE_FUNCTION_0          'Neither defaults, keyword-only args, annotations, nor closures'
              254  STORE_NAME               set_event_loop

 L. 759       256  LOAD_CODE                <code_object new_event_loop>
              258  LOAD_STR                 'new_event_loop'
              260  MAKE_FUNCTION_0          'Neither defaults, keyword-only args, annotations, nor closures'
              262  STORE_NAME               new_event_loop

 L. 764       264  LOAD_CODE                <code_object get_child_watcher>
              266  LOAD_STR                 'get_child_watcher'
              268  MAKE_FUNCTION_0          'Neither defaults, keyword-only args, annotations, nor closures'
              270  STORE_NAME               get_child_watcher

 L. 769       272  LOAD_CODE                <code_object set_child_watcher>
              274  LOAD_STR                 'set_child_watcher'
              276  MAKE_FUNCTION_0          'Neither defaults, keyword-only args, annotations, nor closures'
              278  STORE_NAME               set_child_watcher

 L. 776       280  LOAD_NAME                _get_running_loop
              282  STORE_NAME               _py__get_running_loop

 L. 777       284  LOAD_NAME                _set_running_loop
              286  STORE_NAME               _py__set_running_loop

 L. 778       288  LOAD_NAME                get_running_loop
              290  STORE_NAME               _py_get_running_loop

 L. 779       292  LOAD_NAME                get_event_loop
              294  STORE_NAME               _py_get_event_loop

 L. 782       296  SETUP_FINALLY       326  'to 326'

 L. 786       298  LOAD_CONST               0
              300  LOAD_CONST               ('_get_running_loop', '_set_running_loop', 'get_running_loop', 'get_event_loop')
              302  IMPORT_NAME              _asyncio
              304  IMPORT_FROM              _get_running_loop
              306  STORE_NAME               _get_running_loop
              308  IMPORT_FROM              _set_running_loop
              310  STORE_NAME               _set_running_loop
              312  IMPORT_FROM              get_running_loop
              314  STORE_NAME               get_running_loop
              316  IMPORT_FROM              get_event_loop
              318  STORE_NAME               get_event_loop
              320  POP_TOP          
              322  POP_BLOCK        
              324  JUMP_FORWARD        346  'to 346'
            326_0  COME_FROM_FINALLY   296  '296'

 L. 788       326  DUP_TOP          
              328  LOAD_NAME                ImportError
          330_332  <121>               344  ''
              334  POP_TOP          
              336  POP_TOP          
              338  POP_TOP          

 L. 789       340  POP_EXCEPT       
              342  JUMP_FORWARD        362  'to 362'
              344  <48>             
            346_0  COME_FROM           324  '324'

 L. 792       346  LOAD_NAME                _get_running_loop
              348  STORE_NAME               _c__get_running_loop

 L. 793       350  LOAD_NAME                _set_running_loop
              352  STORE_NAME               _c__set_running_loop

 L. 794       354  LOAD_NAME                get_running_loop
              356  STORE_NAME               _c_get_running_loop

 L. 795       358  LOAD_NAME                get_event_loop
              360  STORE_NAME               _c_get_event_loop
            362_0  COME_FROM           342  '342'

Parse error at or near `<121>' instruction at offset 330_332

Instruction context:
   
 L. 788       326  DUP_TOP          
                 328  LOAD_NAME                ImportError
->           330_332  <121>               344  ''
                 334  POP_TOP          
                 336  POP_TOP          
                 338  POP_TOP          

test/101129.pyc -- 
# decompile failed
