Instruction context:
   
 L.  76        80  DUP_TOP          
                  82  LOAD_GLOBAL              OSError
                  84  LOAD_GLOBAL              ValueError
                  86  BUILD_TUPLE_2         2 
->                88  <121>               148  ''
                  90  POP_TOP          
                  92  POP_TOP          
                  94  POP_TOP          
Instruction context:
   
 L. 120        10  LOAD_FAST                'mi'
                  12  LOAD_CONST               None
->                14  <117>                 1  ''
                  16  POP_JUMP_IF_FALSE    26  'to 26'
Instruction context:
   
 L. 178        74  DUP_TOP          
                  76  LOAD_GLOBAL              KeyError
->                78  <121>               102  ''
                  80  POP_TOP          
                  82  POP_TOP          
                  84  POP_TOP          
Instruction context:
   
 L. 203        10  LOAD_FAST                'mi'
                  12  LOAD_CONST               None
->                14  <117>                 0  ''
                  16  POP_JUMP_IF_FALSE    36  'to 36'
Instruction context:
   
 L. 228        10  LOAD_FAST                'mi'
                  12  LOAD_CONST               None
->                14  <117>                 0  ''
                  16  POP_JUMP_IF_FALSE    36  'to 36'
Instruction context:
   
 L. 243        28  LOAD_FAST                'mod'
                  30  LOAD_CONST               None
->                32  <117>                 0  ''
                  34  POP_JUMP_IF_TRUE     46  'to 46'
                  36  LOAD_GLOBAL              isinstance
                  38  LOAD_FAST                'mod'
                  40  LOAD_GLOBAL              _module_type
                  42  CALL_FUNCTION_2       2  ''
                  44  POP_JUMP_IF_TRUE     64  'to 64'
                46_0  COME_FROM            34  '34'
Instruction context:
   
 L. 280        12  POP_BLOCK        
->                14  LOAD_CONST               None
                  16  RETURN_VALUE     
                18_0  COME_FROM            10  '10'
                  18  POP_BLOCK        
                  20  JUMP_FORWARD         42  'to 42'
                22_0  COME_FROM_FINALLY     0  '0'
Instruction context:
   
 L. 318         8  LOAD_FAST                'dirpath'
                  10  LOAD_FAST                'self'
                  12  LOAD_ATTR                _files
->                14  <118>                 0  ''
                  16  RETURN_VALUE     
Instruction context:
   
 L. 325        32  LOAD_FAST                'fullpath'
                  34  LOAD_FAST                'self'
                  36  LOAD_ATTR                _files
->                38  <118>                 0  ''
                  40  POP_JUMP_IF_FALSE_BACK    14  'to 14'
Instruction context:
   
 L. 355        16  DUP_TOP          
                  18  LOAD_GLOBAL              OSError
->                20  <121>                50  ''
                  22  POP_TOP          
                  24  POP_TOP          
                  26  POP_TOP          
Instruction context:
   
 L. 521        46  DUP_TOP          
                  48  LOAD_GLOBAL              Exception
->                50  <121>                80  ''
                  52  POP_TOP          
                  54  POP_TOP          
                  56  POP_TOP          
Instruction context:
   
 L. 540        66  DUP_TOP          
                  68  LOAD_GLOBAL              OSError
->                70  <121>               100  ''
                  72  POP_TOP          
                  74  POP_TOP          
                  76  POP_TOP          
Instruction context:
   
 L. 595        30  DUP_TOP          
                  32  LOAD_GLOBAL              ImportError
->                34  <121>                48  ''
                  36  POP_TOP          
                  38  POP_TOP          
                  40  POP_TOP          
Instruction context:
   
 L. 667         2  LOAD_FAST                'path'
                   4  LOAD_CONST               -1
                   6  LOAD_CONST               None
                   8  BUILD_SLICE_2         2 
                  10  BINARY_SUBSCR    
                  12  LOAD_CONST               ('c', 'o')
->                14  <118>                 0  ''
                  16  POP_JUMP_IF_TRUE     22  'to 22'
                  18  <74>             
                  20  RAISE_VARARGS_1       1  'exception instance'
                22_0  COME_FROM            16  '16'
Instruction context:
   
 L. 705        70  DUP_TOP          
                  72  LOAD_GLOBAL              KeyError
->                74  <121>                86  ''
                  76  POP_TOP          
                  78  POP_TOP          
                  80  POP_TOP          
Instruction context:
   
 L. 742        60  DUP_TOP          
                  62  LOAD_GLOBAL              OSError
->                64  <121>                84  ''
                  66  POP_TOP          
                  68  POP_TOP          
                  70  POP_TOP          
Instruction context:
   
 L. 758        46  DUP_TOP          
                  48  LOAD_GLOBAL              OSError
->                50  <121>                64  ''
                  52  POP_TOP          
                  54  POP_TOP          
                  56  POP_TOP          
Instruction context:
   
 L. 775        44  LOAD_FAST                'relative_path'
                  46  LOAD_ATTR                name
                  48  LOAD_STR                 '__init__.py'
                  50  COMPARE_OP               ==
                  52  POP_JUMP_IF_TRUE     58  'to 58'
->                54  <74>             
                  56  RAISE_VARARGS_1       1  'exception instance'
                58_0  COME_FROM            52  '52'

test/101112.pyc -- 
# decompile failed

# file test/101112.pyc
# Deparsing stopped due to parse error
