
test/101257.pyc -- 
# decompile failed

# file test/101257.pyc
# --- This code section failed: ---

 L.  10         0  BUILD_LIST_0          0 
                2  LOAD_CONST               ('Queue', 'SimpleQueue', 'JoinableQueue')
                4  CALL_FINALLY          7  'to 7'
                6  STORE_NAME               __all__

 L.  12         8  LOAD_CONST               0
               10  LOAD_CONST               None
               12  IMPORT_NAME              sys
               14  STORE_NAME               sys

 L.  13        16  LOAD_CONST               0
               18  LOAD_CONST               None
               20  IMPORT_NAME              os
               22  STORE_NAME               os

 L.  14        24  LOAD_CONST               0
               26  LOAD_CONST               None
               28  IMPORT_NAME              threading
               30  STORE_NAME               threading

 L.  15        32  LOAD_CONST               0
               34  LOAD_CONST               None
               36  IMPORT_NAME              collections
               38  STORE_NAME               collections

 L.  16        40  LOAD_CONST               0
               42  LOAD_CONST               None
               44  IMPORT_NAME              time
               46  STORE_NAME               time

 L.  17        48  LOAD_CONST               0
               50  LOAD_CONST               None
               52  IMPORT_NAME              types
               54  STORE_NAME               types

 L.  18        56  LOAD_CONST               0
               58  LOAD_CONST               None
               60  IMPORT_NAME              weakref
               62  STORE_NAME               weakref

 L.  19        64  LOAD_CONST               0
               66  LOAD_CONST               None
               68  IMPORT_NAME              errno
               70  STORE_NAME               errno

 L.  21        72  LOAD_CONST               0
               74  LOAD_CONST               ('Empty', 'Full')
               76  IMPORT_NAME              queue
               78  IMPORT_FROM              Empty
               80  STORE_NAME               Empty
               82  IMPORT_FROM              Full
               84  STORE_NAME               Full
               86  POP_TOP          

 L.  23        88  LOAD_CONST               0
               90  LOAD_CONST               None
               92  IMPORT_NAME              _multiprocessing
               94  STORE_NAME               _multiprocessing

 L.  25        96  LOAD_CONST               1
               98  LOAD_CONST               ('connection',)
              100  IMPORT_NAME              
              102  IMPORT_FROM              connection
              104  STORE_NAME               connection
              106  POP_TOP          

 L.  26       108  LOAD_CONST               1
              110  LOAD_CONST               ('context',)
              112  IMPORT_NAME              
              114  IMPORT_FROM              context
              116  STORE_NAME               context
              118  POP_TOP          

 L.  27       120  LOAD_NAME                context
              122  LOAD_ATTR                reduction
              124  LOAD_ATTR                ForkingPickler
              126  STORE_NAME               _ForkingPickler

 L.  29       128  LOAD_CONST               1
              130  LOAD_CONST               ('debug', 'info', 'Finalize', 'register_after_fork', 'is_exiting')
              132  IMPORT_NAME              util
              134  IMPORT_FROM              debug
              136  STORE_NAME               debug
              138  IMPORT_FROM              info
              140  STORE_NAME               info
              142  IMPORT_FROM              Finalize
              144  STORE_NAME               Finalize
              146  IMPORT_FROM              register_after_fork
              148  STORE_NAME               register_after_fork
              150  IMPORT_FROM              is_exiting
              152  STORE_NAME               is_exiting
              154  POP_TOP          

 L.  35       156  LOAD_BUILD_CLASS 
              158  LOAD_CODE                <code_object Queue>
              160  LOAD_STR                 'Queue'
              162  MAKE_FUNCTION_0          'Neither defaults, keyword-only args, annotations, nor closures'
              164  LOAD_STR                 'Queue'
              166  LOAD_NAME                object
              168  CALL_FUNCTION_3       3  ''
              170  STORE_NAME               Queue

 L. 285       172  LOAD_NAME                object
              174  CALL_FUNCTION_0       0  ''
              176  STORE_NAME               _sentinel

 L. 295       178  LOAD_BUILD_CLASS 
              180  LOAD_CODE                <code_object JoinableQueue>
              182  LOAD_STR                 'JoinableQueue'
              184  MAKE_FUNCTION_0          'Neither defaults, keyword-only args, annotations, nor closures'
              186  LOAD_STR                 'JoinableQueue'
              188  LOAD_NAME                Queue
              190  CALL_FUNCTION_3       3  ''
              192  STORE_NAME               JoinableQueue

 L. 338       194  LOAD_BUILD_CLASS 
              196  LOAD_CODE                <code_object SimpleQueue>
              198  LOAD_STR                 'SimpleQueue'
              200  MAKE_FUNCTION_0          'Neither defaults, keyword-only args, annotations, nor closures'
              202  LOAD_STR                 'SimpleQueue'
              204  LOAD_NAME                object
              206  CALL_FUNCTION_3       3  ''
              208  STORE_NAME               SimpleQueue

Parse error at or near `None' instruction at offset -1

