
# file test/101265.pyc
# --- This code section failed: ---

 L.  10         0  LOAD_CONST               0
                2  LOAD_CONST               None
                4  IMPORT_NAME              os
                6  STORE_NAME               os

 L.  11         8  LOAD_CONST               0
               10  LOAD_CONST               None
               12  IMPORT_NAME              itertools
               14  STORE_NAME               itertools

 L.  12        16  LOAD_CONST               0
               18  LOAD_CONST               None
               20  IMPORT_NAME              sys
               22  STORE_NAME               sys

 L.  13        24  LOAD_CONST               0
               26  LOAD_CONST               None
               28  IMPORT_NAME              weakref
               30  STORE_NAME               weakref

 L.  14        32  LOAD_CONST               0
               34  LOAD_CONST               None
               36  IMPORT_NAME              atexit
               38  STORE_NAME               atexit

 L.  15        40  LOAD_CONST               0
               42  LOAD_CONST               None
               44  IMPORT_NAME              threading
               46  STORE_NAME               threading

 L.  17        48  LOAD_CONST               0
               50  LOAD_CONST               ('_args_from_interpreter_flags',)
               52  IMPORT_NAME              subprocess
               54  IMPORT_FROM              _args_from_interpreter_flags
               56  STORE_NAME               _args_from_interpreter_flags
               58  POP_TOP          

 L.  19        60  LOAD_CONST               1
               62  LOAD_CONST               ('process',)
               64  IMPORT_NAME              
               66  IMPORT_FROM              process
               68  STORE_NAME               process
               70  POP_TOP          

 L.  21        72  BUILD_LIST_0          0 
               74  LOAD_CONST               ('sub_debug', 'debug', 'info', 'sub_warning', 'get_logger', 'log_to_stderr', 'get_temp_dir', 'register_after_fork', 'is_exiting', 'Finalize', 'ForkAwareThreadLock', 'ForkAwareLocal', 'close_all_fds_except', 'SUBDEBUG', 'SUBWARNING')
               76  CALL_FINALLY         79  'to 79'
               78  STORE_NAME               __all__

 L.  32        80  LOAD_CONST               0
               82  STORE_NAME               NOTSET

 L.  33        84  LOAD_CONST               5
               86  STORE_NAME               SUBDEBUG

 L.  34        88  LOAD_CONST               10
               90  STORE_NAME               DEBUG

 L.  35        92  LOAD_CONST               20
               94  STORE_NAME               INFO

 L.  36        96  LOAD_CONST               25
               98  STORE_NAME               SUBWARNING

 L.  38       100  LOAD_STR                 'multiprocessing'
              102  STORE_NAME               LOGGER_NAME

 L.  39       104  LOAD_STR                 '[%(levelname)s/%(processName)s] %(message)s'
              106  STORE_NAME               DEFAULT_LOGGING_FORMAT

 L.  41       108  LOAD_CONST               None
              110  STORE_GLOBAL             _logger

 L.  42       112  LOAD_CONST               False
              114  STORE_GLOBAL             _log_to_stderr

 L.  44       116  LOAD_CODE                <code_object sub_debug>
              118  LOAD_STR                 'sub_debug'
              120  MAKE_FUNCTION_0          'Neither defaults, keyword-only args, annotations, nor closures'
              122  STORE_NAME               sub_debug

 L.  48       124  LOAD_CODE                <code_object debug>
              126  LOAD_STR                 'debug'
              128  MAKE_FUNCTION_0          'Neither defaults, keyword-only args, annotations, nor closures'
              130  STORE_NAME               debug

 L.  52       132  LOAD_CODE                <code_object info>
              134  LOAD_STR                 'info'
              136  MAKE_FUNCTION_0          'Neither defaults, keyword-only args, annotations, nor closures'
              138  STORE_NAME               info

 L.  56       140  LOAD_CODE                <code_object sub_warning>
              142  LOAD_STR                 'sub_warning'
              144  MAKE_FUNCTION_0          'Neither defaults, keyword-only args, annotations, nor closures'
              146  STORE_NAME               sub_warning

 L.  60       148  LOAD_CODE                <code_object get_logger>
              150  LOAD_STR                 'get_logger'
              152  MAKE_FUNCTION_0          'Neither defaults, keyword-only args, annotations, nor closures'
              154  STORE_NAME               get_logger

 L.  87       156  LOAD_CONST               (None,)
              158  LOAD_CODE                <code_object log_to_stderr>
              160  LOAD_STR                 'log_to_stderr'
              162  MAKE_FUNCTION_1          'default'
              164  STORE_NAME               log_to_stderr

 L. 108       166  LOAD_CODE                <code_object _platform_supports_abstract_sockets>
              168  LOAD_STR                 '_platform_supports_abstract_sockets'
              170  MAKE_FUNCTION_0          'Neither defaults, keyword-only args, annotations, nor closures'
              172  STORE_NAME               _platform_supports_abstract_sockets

 L. 116       174  LOAD_CODE                <code_object is_abstract_socket_namespace>
              176  LOAD_STR                 'is_abstract_socket_namespace'
              178  MAKE_FUNCTION_0          'Neither defaults, keyword-only args, annotations, nor closures'
              180  STORE_NAME               is_abstract_socket_namespace

 L. 126       182  LOAD_NAME                _platform_supports_abstract_sockets
              184  CALL_FUNCTION_0       0  ''
              186  STORE_NAME               abstract_sockets_supported

 L. 132       188  LOAD_CODE                <code_object _remove_temp_dir>
              190  LOAD_STR                 '_remove_temp_dir'
              192  MAKE_FUNCTION_0          'Neither defaults, keyword-only args, annotations, nor closures'
              194  STORE_NAME               _remove_temp_dir

 L. 141       196  LOAD_CODE                <code_object get_temp_dir>
              198  LOAD_STR                 'get_temp_dir'
              200  MAKE_FUNCTION_0          'Neither defaults, keyword-only args, annotations, nor closures'
              202  STORE_NAME               get_temp_dir

 L. 159       204  LOAD_NAME                weakref
              206  LOAD_METHOD              WeakValueDictionary
              208  CALL_METHOD_0         0  ''
              210  STORE_NAME               _afterfork_registry

 L. 160       212  LOAD_NAME                itertools
              214  LOAD_METHOD              count
              216  CALL_METHOD_0         0  ''
              218  STORE_NAME               _afterfork_counter

 L. 162       220  LOAD_CODE                <code_object _run_after_forkers>
              222  LOAD_STR                 '_run_after_forkers'
              224  MAKE_FUNCTION_0          'Neither defaults, keyword-only args, annotations, nor closures'
              226  STORE_NAME               _run_after_forkers

 L. 171       228  LOAD_CODE                <code_object register_after_fork>
              230  LOAD_STR                 'register_after_fork'
              232  MAKE_FUNCTION_0          'Neither defaults, keyword-only args, annotations, nor closures'
              234  STORE_NAME               register_after_fork

 L. 178       236  BUILD_MAP_0           0 
              238  STORE_NAME               _finalizer_registry

 L. 179       240  LOAD_NAME                itertools
              242  LOAD_METHOD              count
              244  CALL_METHOD_0         0  ''
              246  STORE_NAME               _finalizer_counter

 L. 182       248  LOAD_BUILD_CLASS 
              250  LOAD_CODE                <code_object Finalize>
              252  LOAD_STR                 'Finalize'
              254  MAKE_FUNCTION_0          'Neither defaults, keyword-only args, annotations, nor closures'
              256  LOAD_STR                 'Finalize'
              258  LOAD_NAME                object
              260  CALL_FUNCTION_3       3  ''
              262  STORE_NAME               Finalize

 L. 268       264  LOAD_CONST               (None,)
              266  LOAD_CODE                <code_object _run_finalizers>
              268  LOAD_STR                 '_run_finalizers'
              270  MAKE_FUNCTION_1          'default'
              272  STORE_NAME               _run_finalizers

 L. 312       274  LOAD_CODE                <code_object is_exiting>
              276  LOAD_STR                 'is_exiting'
              278  MAKE_FUNCTION_0          'Neither defaults, keyword-only args, annotations, nor closures'
              280  STORE_NAME               is_exiting

 L. 318       282  LOAD_CONST               False
              284  STORE_GLOBAL             _exiting

 L. 320       286  LOAD_NAME                info
              288  LOAD_NAME                debug
              290  LOAD_NAME                _run_finalizers

 L. 321       292  LOAD_NAME                process
              294  LOAD_ATTR                active_children

 L. 322       296  LOAD_NAME                process
              298  LOAD_ATTR                current_process

 L. 320       300  BUILD_TUPLE_5         5 
              302  LOAD_CODE                <code_object _exit_function>
              304  LOAD_STR                 '_exit_function'
              306  MAKE_FUNCTION_1          'default'
              308  STORE_NAME               _exit_function

 L. 362       310  LOAD_NAME                atexit
              312  LOAD_METHOD              register
              314  LOAD_NAME                _exit_function
              316  CALL_METHOD_1         1  ''
              318  POP_TOP          

 L. 368       320  LOAD_BUILD_CLASS 
              322  LOAD_CODE                <code_object ForkAwareThreadLock>
              324  LOAD_STR                 'ForkAwareThreadLock'
              326  MAKE_FUNCTION_0          'Neither defaults, keyword-only args, annotations, nor closures'
              328  LOAD_STR                 'ForkAwareThreadLock'
              330  LOAD_NAME                object
              332  CALL_FUNCTION_3       3  ''
              334  STORE_NAME               ForkAwareThreadLock

 L. 385       336  LOAD_BUILD_CLASS 
              338  LOAD_CODE                <code_object ForkAwareLocal>
              340  LOAD_STR                 'ForkAwareLocal'
              342  MAKE_FUNCTION_0          'Neither defaults, keyword-only args, annotations, nor closures'
              344  LOAD_STR                 'ForkAwareLocal'
              346  LOAD_NAME                threading
              348  LOAD_ATTR                local
              350  CALL_FUNCTION_3       3  ''
              352  STORE_NAME               ForkAwareLocal

 L. 395       354  SETUP_FINALLY       370  'to 370'

 L. 396       356  LOAD_NAME                os
              358  LOAD_METHOD              sysconf
              360  LOAD_STR                 'SC_OPEN_MAX'
              362  CALL_METHOD_1         1  ''
              364  STORE_NAME               MAXFD
              366  POP_BLOCK        
              368  JUMP_FORWARD        394  'to 394'
            370_0  COME_FROM_FINALLY   354  '354'

 L. 397       370  DUP_TOP          
              372  LOAD_NAME                Exception
          374_376  <121>               392  ''
              378  POP_TOP          
              380  POP_TOP          
              382  POP_TOP          

 L. 398       384  LOAD_CONST               256
              386  STORE_NAME               MAXFD
              388  POP_EXCEPT       
              390  JUMP_FORWARD        394  'to 394'
              392  <48>             
            394_0  COME_FROM           390  '390'
            394_1  COME_FROM           368  '368'

 L. 400       394  LOAD_CODE                <code_object close_all_fds_except>
              396  LOAD_STR                 'close_all_fds_except'
              398  MAKE_FUNCTION_0          'Neither defaults, keyword-only args, annotations, nor closures'
              400  STORE_NAME               close_all_fds_except

 L. 410       402  LOAD_CODE                <code_object _close_stdin>
              404  LOAD_STR                 '_close_stdin'
              406  MAKE_FUNCTION_0          'Neither defaults, keyword-only args, annotations, nor closures'
              408  STORE_NAME               _close_stdin

 L. 433       410  LOAD_CODE                <code_object _flush_std_streams>
              412  LOAD_STR                 '_flush_std_streams'
              414  MAKE_FUNCTION_0          'Neither defaults, keyword-only args, annotations, nor closures'
              416  STORE_NAME               _flush_std_streams

 L. 447       418  LOAD_CODE                <code_object spawnv_passfds>
              420  LOAD_STR                 'spawnv_passfds'
              422  MAKE_FUNCTION_0          'Neither defaults, keyword-only args, annotations, nor closures'
              424  STORE_NAME               spawnv_passfds

 L. 461       426  LOAD_CODE                <code_object close_fds>
              428  LOAD_STR                 'close_fds'
              430  MAKE_FUNCTION_0          'Neither defaults, keyword-only args, annotations, nor closures'
              432  STORE_NAME               close_fds

 L. 467       434  LOAD_CODE                <code_object _cleanup_tests>
              436  LOAD_STR                 '_cleanup_tests'
              438  MAKE_FUNCTION_0          'Neither defaults, keyword-only args, annotations, nor closures'
              440  STORE_NAME               _cleanup_tests

Parse error at or near `CALL_FINALLY' instruction at offset 76

Instruction context:
   
 L.  21        72  BUILD_LIST_0          0 
                  74  LOAD_CONST               ('sub_debug', 'debug', 'info', 'sub_warning', 'get_logger', 'log_to_stderr', 'get_temp_dir', 'register_after_fork', 'is_exiting', 'Finalize', 'ForkAwareThreadLock', 'ForkAwareLocal', 'close_all_fds_except', 'SUBDEBUG', 'SUBWARNING')
->                76  CALL_FINALLY         79  'to 79'
                  78  STORE_NAME               __all__

test/101265.pyc -- 
# decompile failed
