
# file test/101287.pyc
# --- This code section failed: ---

 L.  18         0  LOAD_CONST               0
                2  LOAD_CONST               None
                4  IMPORT_NAME              io
                6  STORE_NAME               io

 L.  19         8  LOAD_CONST               0
               10  LOAD_CONST               None
               12  IMPORT_NAME              os
               14  STORE_NAME               os

 L.  20        16  LOAD_CONST               0
               18  LOAD_CONST               None
               20  IMPORT_NAME              shutil
               22  STORE_NAME               shutil

 L.  21        24  LOAD_CONST               0
               26  LOAD_CONST               None
               28  IMPORT_NAME              struct
               30  STORE_NAME               struct

 L.  22        32  LOAD_CONST               0
               34  LOAD_CONST               None
               36  IMPORT_NAME              subprocess
               38  STORE_NAME               subprocess

 L.  23        40  LOAD_CONST               0
               42  LOAD_CONST               None
               44  IMPORT_NAME              sys
               46  STORE_NAME               sys

 L.  24        48  LOAD_CONST               0
               50  LOAD_CONST               None
               52  IMPORT_NAME              tempfile
               54  STORE_NAME               tempfile

 L.  26        56  LOAD_CONST               0
               58  LOAD_CONST               ('Image', 'ImageFile', 'PngImagePlugin', 'features')
               60  IMPORT_NAME              PIL
               62  IMPORT_FROM              Image
               64  STORE_NAME               Image
               66  IMPORT_FROM              ImageFile
               68  STORE_NAME               ImageFile
               70  IMPORT_FROM              PngImagePlugin
               72  STORE_NAME               PngImagePlugin
               74  IMPORT_FROM              features
               76  STORE_NAME               features
               78  POP_TOP          

 L.  28        80  LOAD_NAME                features
               82  LOAD_METHOD              check_codec
               84  LOAD_STR                 'jpg_2000'
               86  CALL_METHOD_1         1  ''
               88  STORE_NAME               enable_jpeg2k

 L.  29        90  LOAD_NAME                enable_jpeg2k
               92  POP_JUMP_IF_FALSE   106  'to 106'

 L.  30        94  LOAD_CONST               0
               96  LOAD_CONST               ('Jpeg2KImagePlugin',)
               98  IMPORT_NAME              PIL
              100  IMPORT_FROM              Jpeg2KImagePlugin
              102  STORE_NAME               Jpeg2KImagePlugin
              104  POP_TOP          
            106_0  COME_FROM            92  '92'

 L.  32       106  LOAD_CONST               8
              108  STORE_NAME               HEADERSIZE

 L.  35       110  LOAD_CODE                <code_object nextheader>
              112  LOAD_STR                 'nextheader'
              114  MAKE_FUNCTION_0          'Neither defaults, keyword-only args, annotations, nor closures'
              116  STORE_NAME               nextheader

 L.  39       118  LOAD_CODE                <code_object read_32t>
              120  LOAD_STR                 'read_32t'
              122  MAKE_FUNCTION_0          'Neither defaults, keyword-only args, annotations, nor closures'
              124  STORE_NAME               read_32t

 L.  49       126  LOAD_CODE                <code_object read_32>
              128  LOAD_STR                 'read_32'
              130  MAKE_FUNCTION_0          'Neither defaults, keyword-only args, annotations, nor closures'
              132  STORE_NAME               read_32

 L.  91       134  LOAD_CODE                <code_object read_mk>
              136  LOAD_STR                 'read_mk'
              138  MAKE_FUNCTION_0          'Neither defaults, keyword-only args, annotations, nor closures'
              140  STORE_NAME               read_mk

 L. 101       142  LOAD_CODE                <code_object read_png_or_jpeg2000>
              144  LOAD_STR                 'read_png_or_jpeg2000'
              146  MAKE_FUNCTION_0          'Neither defaults, keyword-only args, annotations, nor closures'
              148  STORE_NAME               read_png_or_jpeg2000

 L. 131       150  LOAD_BUILD_CLASS 
              152  LOAD_CODE                <code_object IcnsFile>
              154  LOAD_STR                 'IcnsFile'
              156  MAKE_FUNCTION_0          'Neither defaults, keyword-only args, annotations, nor closures'
              158  LOAD_STR                 'IcnsFile'
              160  CALL_FUNCTION_2       2  ''
              162  STORE_NAME               IcnsFile

 L. 232       164  LOAD_BUILD_CLASS 
              166  LOAD_CODE                <code_object IcnsImageFile>
              168  LOAD_STR                 'IcnsImageFile'
              170  MAKE_FUNCTION_0          'Neither defaults, keyword-only args, annotations, nor closures'
              172  LOAD_STR                 'IcnsImageFile'
              174  LOAD_NAME                ImageFile
              176  LOAD_ATTR                ImageFile
              178  CALL_FUNCTION_3       3  ''
              180  STORE_NAME               IcnsImageFile

 L. 304       182  LOAD_CODE                <code_object _save>
              184  LOAD_STR                 '_save'
              186  MAKE_FUNCTION_0          'Neither defaults, keyword-only args, annotations, nor closures'
              188  STORE_NAME               _save

 L. 360       190  LOAD_NAME                Image
              192  LOAD_METHOD              register_open
              194  LOAD_NAME                IcnsImageFile
              196  LOAD_ATTR                format
              198  LOAD_NAME                IcnsImageFile
              200  LOAD_LAMBDA              '<code_object <lambda>>'
              202  LOAD_STR                 '<lambda>'
              204  MAKE_FUNCTION_0          'Neither defaults, keyword-only args, annotations, nor closures'
              206  CALL_METHOD_3         3  ''
              208  POP_TOP          

 L. 361       210  LOAD_NAME                Image
              212  LOAD_METHOD              register_extension
              214  LOAD_NAME                IcnsImageFile
              216  LOAD_ATTR                format
              218  LOAD_STR                 '.icns'
              220  CALL_METHOD_2         2  ''
              222  POP_TOP          

 L. 363       224  LOAD_NAME                sys
              226  LOAD_ATTR                platform
              228  LOAD_STR                 'darwin'
              230  COMPARE_OP               ==
          232_234  POP_JUMP_IF_FALSE   264  'to 264'

 L. 364       236  LOAD_NAME                Image
              238  LOAD_METHOD              register_save
              240  LOAD_NAME                IcnsImageFile
              242  LOAD_ATTR                format
              244  LOAD_NAME                _save
              246  CALL_METHOD_2         2  ''
              248  POP_TOP          

 L. 366       250  LOAD_NAME                Image
              252  LOAD_METHOD              register_mime
              254  LOAD_NAME                IcnsImageFile
              256  LOAD_ATTR                format
              258  LOAD_STR                 'image/icns'
              260  CALL_METHOD_2         2  ''
              262  POP_TOP          
            264_0  COME_FROM           232  '232'

 L. 369       264  LOAD_NAME                __name__
              266  LOAD_STR                 '__main__'
              268  COMPARE_OP               ==
          270_272  POP_JUMP_IF_FALSE   484  'to 484'

 L. 371       274  LOAD_NAME                len
              276  LOAD_NAME                sys
              278  LOAD_ATTR                argv
              280  CALL_FUNCTION_1       1  ''
              282  LOAD_CONST               2
              284  COMPARE_OP               <
          286_288  POP_JUMP_IF_FALSE   306  'to 306'

 L. 372       290  LOAD_NAME                print
              292  LOAD_STR                 'Syntax: python IcnsImagePlugin.py [file]'
              294  CALL_FUNCTION_1       1  ''
              296  POP_TOP          

 L. 373       298  LOAD_NAME                sys
              300  LOAD_METHOD              exit
              302  CALL_METHOD_0         0  ''
              304  POP_TOP          
            306_0  COME_FROM           286  '286'

 L. 375       306  LOAD_NAME                open
              308  LOAD_NAME                sys
              310  LOAD_ATTR                argv
              312  LOAD_CONST               1
              314  BINARY_SUBSCR    
              316  LOAD_STR                 'rb'
              318  CALL_FUNCTION_2       2  ''
              320  SETUP_WITH          466  'to 466'
              322  STORE_NAME               fp

 L. 376       324  LOAD_NAME                IcnsImageFile
              326  LOAD_NAME                fp
              328  CALL_FUNCTION_1       1  ''
              330  STORE_NAME               imf

 L. 377       332  LOAD_NAME                imf
              334  LOAD_ATTR                info
              336  LOAD_STR                 'sizes'
              338  BINARY_SUBSCR    
              340  GET_ITER         
            342_0  COME_FROM           366  '366'
              342  FOR_ITER            370  'to 370'
              344  STORE_NAME               size

 L. 378       346  LOAD_NAME                size
              348  LOAD_NAME                imf
              350  STORE_ATTR               size

 L. 379       352  LOAD_NAME                imf
              354  LOAD_METHOD              save
              356  LOAD_STR                 'out-%s-%s-%s.png'
              358  LOAD_NAME                size
              360  BINARY_MODULO    
              362  CALL_METHOD_1         1  ''
              364  POP_TOP          
          366_368  JUMP_BACK           342  'to 342'
            370_0  COME_FROM           342  '342'

 L. 380       370  LOAD_NAME                Image
              372  LOAD_METHOD              open
              374  LOAD_NAME                sys
              376  LOAD_ATTR                argv
              378  LOAD_CONST               1
              380  BINARY_SUBSCR    
              382  CALL_METHOD_1         1  ''
              384  SETUP_WITH          412  'to 412'
              386  STORE_NAME               im

 L. 381       388  LOAD_NAME                im
              390  LOAD_METHOD              save
              392  LOAD_STR                 'out.png'
              394  CALL_METHOD_1         1  ''
              396  POP_TOP          
              398  POP_BLOCK        
              400  LOAD_CONST               None
              402  DUP_TOP          
              404  DUP_TOP          
              406  CALL_FUNCTION_3       3  ''
              408  POP_TOP          
              410  JUMP_FORWARD        430  'to 430'
            412_0  COME_FROM_WITH      384  '384'
              412  <49>             
          414_416  POP_JUMP_IF_TRUE    420  'to 420'
              418  <48>             
            420_0  COME_FROM           414  '414'
              420  POP_TOP          
              422  POP_TOP          
              424  POP_TOP          
              426  POP_EXCEPT       
              428  POP_TOP          
            430_0  COME_FROM           410  '410'

 L. 382       430  LOAD_NAME                sys
              432  LOAD_ATTR                platform
              434  LOAD_STR                 'windows'
              436  COMPARE_OP               ==
          438_440  POP_JUMP_IF_FALSE   452  'to 452'

 L. 383       442  LOAD_NAME                os
              444  LOAD_METHOD              startfile
              446  LOAD_STR                 'out.png'
              448  CALL_METHOD_1         1  ''
              450  POP_TOP          
            452_0  COME_FROM           438  '438'
              452  POP_BLOCK        
              454  LOAD_CONST               None
              456  DUP_TOP          
              458  DUP_TOP          
              460  CALL_FUNCTION_3       3  ''
              462  POP_TOP          
              464  JUMP_FORWARD        484  'to 484'
            466_0  COME_FROM_WITH      320  '320'
              466  <49>             
          468_470  POP_JUMP_IF_TRUE    474  'to 474'
              472  <48>             
            474_0  COME_FROM           468  '468'
              474  POP_TOP          
              476  POP_TOP          
              478  POP_TOP          
              480  POP_EXCEPT       
              482  POP_TOP          
            484_0  COME_FROM           464  '464'
            484_1  COME_FROM           270  '270'

Parse error at or near `DUP_TOP' instruction at offset 402

Instruction context:
   
 L. 381       388  LOAD_NAME                im
                 390  LOAD_METHOD              save
                 392  LOAD_STR                 'out.png'
                 394  CALL_METHOD_1         1  ''
                 396  POP_TOP          
                 398  POP_BLOCK        
                 400  LOAD_CONST               None
->               402  DUP_TOP          
                 404  DUP_TOP          
                 406  CALL_FUNCTION_3       3  ''
                 408  POP_TOP          
                 410  JUMP_FORWARD        430  'to 430'
               412_0  COME_FROM_WITH      384  '384'
                 412  <49>             
             414_416  POP_JUMP_IF_TRUE    420  'to 420'
                 418  <48>             
               420_0  COME_FROM           414  '414'
                 420  POP_TOP          
                 422  POP_TOP          
                 424  POP_TOP          
                 426  POP_EXCEPT       
                 428  POP_TOP          
               430_0  COME_FROM           410  '410'

test/101287.pyc -- 
# decompile failed
