
test/101267.pyc -- 
# decompile failed

# file test/101267.pyc
# --- This code section failed: ---

 L.  10         0  BUILD_LIST_0          0 
                2  LOAD_CONST               ('Client', 'Listener', 'Pipe')
                4  CALL_FINALLY          7  'to 7'
                6  STORE_NAME               __all__

 L.  12         8  LOAD_CONST               0
               10  LOAD_CONST               ('Queue',)
               12  IMPORT_NAME              queue
               14  IMPORT_FROM              Queue
               16  STORE_NAME               Queue
               18  POP_TOP          

 L.  15        20  LOAD_CONST               None
               22  BUILD_LIST_1          1 
               24  STORE_NAME               families

 L.  18        26  LOAD_BUILD_CLASS 
               28  LOAD_CODE                <code_object Listener>
               30  LOAD_STR                 'Listener'
               32  MAKE_FUNCTION_0          'Neither defaults, keyword-only args, annotations, nor closures'
               34  LOAD_STR                 'Listener'
               36  LOAD_NAME                object
               38  CALL_FUNCTION_3       3  ''
               40  STORE_NAME               Listener

 L.  40        42  LOAD_CODE                <code_object Client>
               44  LOAD_STR                 'Client'
               46  MAKE_FUNCTION_0          'Neither defaults, keyword-only args, annotations, nor closures'
               48  STORE_NAME               Client

 L.  46        50  LOAD_CONST               (True,)
               52  LOAD_CODE                <code_object Pipe>
               54  LOAD_STR                 'Pipe'
               56  MAKE_FUNCTION_1          'default'
               58  STORE_NAME               Pipe

 L.  51        60  LOAD_BUILD_CLASS 
               62  LOAD_CODE                <code_object Connection>
               64  LOAD_STR                 'Connection'
               66  MAKE_FUNCTION_0          'Neither defaults, keyword-only args, annotations, nor closures'
               68  LOAD_STR                 'Connection'
               70  LOAD_NAME                object
               72  CALL_FUNCTION_3       3  ''
               74  STORE_NAME               Connection

Parse error at or near `None' instruction at offset -1

