
test/101268.pyc -- 
# decompile failed

# file test/101268.pyc
# --- This code section failed: ---

 L.  10         0  BUILD_LIST_0          0 
                2  LOAD_CONST               ('Process', 'current_process', 'active_children', 'freeze_support', 'Lock', 'RLock', 'Semaphore', 'BoundedSemaphore', 'Condition', 'Event', 'Barrier', 'Queue', 'Manager', 'Pipe', 'Pool', 'JoinableQueue')
                4  CALL_FINALLY          7  'to 7'
                6  STORE_NAME               __all__

 L.  20         8  LOAD_CONST               0
               10  LOAD_CONST               None
               12  IMPORT_NAME              threading
               14  STORE_NAME               threading

 L.  21        16  LOAD_CONST               0
               18  LOAD_CONST               None
               20  IMPORT_NAME              sys
               22  STORE_NAME               sys

 L.  22        24  LOAD_CONST               0
               26  LOAD_CONST               None
               28  IMPORT_NAME              weakref
               30  STORE_NAME               weakref

 L.  23        32  LOAD_CONST               0
               34  LOAD_CONST               None
               36  IMPORT_NAME              array
               38  STORE_NAME               array

 L.  25        40  LOAD_CONST               1
               42  LOAD_CONST               ('Pipe',)
               44  IMPORT_NAME              connection
               46  IMPORT_FROM              Pipe
               48  STORE_NAME               Pipe
               50  POP_TOP          

 L.  26        52  LOAD_CONST               0
               54  LOAD_CONST               ('Lock', 'RLock', 'Semaphore', 'BoundedSemaphore')
               56  IMPORT_NAME              threading
               58  IMPORT_FROM              Lock
               60  STORE_NAME               Lock
               62  IMPORT_FROM              RLock
               64  STORE_NAME               RLock
               66  IMPORT_FROM              Semaphore
               68  STORE_NAME               Semaphore
               70  IMPORT_FROM              BoundedSemaphore
               72  STORE_NAME               BoundedSemaphore
               74  POP_TOP          

 L.  27        76  LOAD_CONST               0
               78  LOAD_CONST               ('Event', 'Condition', 'Barrier')
               80  IMPORT_NAME              threading
               82  IMPORT_FROM              Event
               84  STORE_NAME               Event
               86  IMPORT_FROM              Condition
               88  STORE_NAME               Condition
               90  IMPORT_FROM              Barrier
               92  STORE_NAME               Barrier
               94  POP_TOP          

 L.  28        96  LOAD_CONST               0
               98  LOAD_CONST               ('Queue',)
              100  IMPORT_NAME              queue
              102  IMPORT_FROM              Queue
              104  STORE_NAME               Queue
              106  POP_TOP          

 L.  34       108  LOAD_BUILD_CLASS 
              110  LOAD_CODE                <code_object DummyProcess>
              112  LOAD_STR                 'DummyProcess'
              114  MAKE_FUNCTION_0          'Neither defaults, keyword-only args, annotations, nor closures'
              116  LOAD_STR                 'DummyProcess'
              118  LOAD_NAME                threading
              120  LOAD_ATTR                Thread
              122  CALL_FUNCTION_3       3  ''
              124  STORE_NAME               DummyProcess

 L.  64       126  LOAD_NAME                DummyProcess
              128  STORE_NAME               Process

 L.  65       130  LOAD_NAME                threading
              132  LOAD_ATTR                current_thread
              134  STORE_NAME               current_process

 L.  66       136  LOAD_NAME                weakref
              138  LOAD_METHOD              WeakKeyDictionary
              140  CALL_METHOD_0         0  ''
              142  LOAD_NAME                current_process
              144  CALL_FUNCTION_0       0  ''
              146  STORE_ATTR               _children

 L.  68       148  LOAD_CODE                <code_object active_children>
              150  LOAD_STR                 'active_children'
              152  MAKE_FUNCTION_0          'Neither defaults, keyword-only args, annotations, nor closures'
              154  STORE_NAME               active_children

 L.  75       156  LOAD_CODE                <code_object freeze_support>
              158  LOAD_STR                 'freeze_support'
              160  MAKE_FUNCTION_0          'Neither defaults, keyword-only args, annotations, nor closures'
              162  STORE_NAME               freeze_support

 L.  82       164  LOAD_BUILD_CLASS 
              166  LOAD_CODE                <code_object Namespace>
              168  LOAD_STR                 'Namespace'
              170  MAKE_FUNCTION_0          'Neither defaults, keyword-only args, annotations, nor closures'
              172  LOAD_STR                 'Namespace'
              174  LOAD_NAME                object
              176  CALL_FUNCTION_3       3  ''
              178  STORE_NAME               Namespace

 L.  94       180  LOAD_NAME                dict
              182  STORE_NAME               dict

 L.  95       184  LOAD_NAME                list
              186  STORE_NAME               list

 L.  97       188  LOAD_CONST               (True,)
              190  LOAD_CODE                <code_object Array>
              192  LOAD_STR                 'Array'
              194  MAKE_FUNCTION_1          'default'
              196  STORE_NAME               Array

 L. 100       198  LOAD_BUILD_CLASS 
              200  LOAD_CODE                <code_object Value>
              202  LOAD_STR                 'Value'
              204  MAKE_FUNCTION_0          'Neither defaults, keyword-only args, annotations, nor closures'
              206  LOAD_STR                 'Value'
              208  LOAD_NAME                object
              210  CALL_FUNCTION_3       3  ''
              212  STORE_NAME               Value

 L. 116       214  LOAD_CODE                <code_object Manager>
              216  LOAD_STR                 'Manager'
              218  MAKE_FUNCTION_0          'Neither defaults, keyword-only args, annotations, nor closures'
              220  STORE_NAME               Manager

 L. 119       222  LOAD_CODE                <code_object shutdown>
              224  LOAD_STR                 'shutdown'
              226  MAKE_FUNCTION_0          'Neither defaults, keyword-only args, annotations, nor closures'
              228  STORE_NAME               shutdown

 L. 122       230  LOAD_CONST               (None, None, ())
              232  LOAD_CODE                <code_object Pool>
              234  LOAD_STR                 'Pool'
              236  MAKE_FUNCTION_1          'default'
              238  STORE_NAME               Pool

 L. 126       240  LOAD_NAME                Queue
              242  STORE_NAME               JoinableQueue

Parse error at or near `None' instruction at offset -1

