
# file test/101340.pyc
# --- This code section failed: ---

 L.   1         0  LOAD_STR                 "Ttk wrapper.\n\nThis module provides classes to allow using Tk themed widget set.\n\nTtk is based on a revised and enhanced version of\nTIP #48 (http://tip.tcl.tk/48) specified style engine.\n\nIts basic idea is to separate, to the extent possible, the code\nimplementing a widget's behavior from the code implementing its\nappearance. Widget class bindings are primarily responsible for\nmaintaining the widget state and invoking callbacks, all aspects\nof the widgets appearance lies at Themes.\n"
                2  STORE_NAME               __doc__

 L.  15         4  LOAD_STR                 '0.3.1'
                6  STORE_NAME               __version__

 L.  17         8  LOAD_STR                 'Guilherme Polo <ggpolo@gmail.com>'
               10  STORE_NAME               __author__

 L.  19        12  BUILD_LIST_0          0 
               14  LOAD_CONST               ('Button', 'Checkbutton', 'Combobox', 'Entry', 'Frame', 'Label', 'Labelframe', 'LabelFrame', 'Menubutton', 'Notebook', 'Panedwindow', 'PanedWindow', 'Progressbar', 'Radiobutton', 'Scale', 'Scrollbar', 'Separator', 'Sizegrip', 'Spinbox', 'Style', 'Treeview', 'LabeledScale', 'OptionMenu', 'tclobjs_to_py', 'setup_master')
               16  CALL_FINALLY         19  'to 19'
               18  STORE_NAME               __all__

 L.  28        20  LOAD_CONST               0
               22  LOAD_CONST               None
               24  IMPORT_NAME              tkinter
               26  STORE_NAME               tkinter

 L.  29        28  LOAD_CONST               0
               30  LOAD_CONST               ('_flatten', '_join', '_stringify', '_splitdict')
               32  IMPORT_NAME              tkinter
               34  IMPORT_FROM              _flatten
               36  STORE_NAME               _flatten
               38  IMPORT_FROM              _join
               40  STORE_NAME               _join
               42  IMPORT_FROM              _stringify
               44  STORE_NAME               _stringify
               46  IMPORT_FROM              _splitdict
               48  STORE_NAME               _splitdict
               50  POP_TOP          

 L.  32        52  LOAD_NAME                tkinter
               54  LOAD_ATTR                TkVersion
               56  LOAD_CONST               8.5
               58  COMPARE_OP               <
               60  POP_JUMP_IF_FALSE    66  'to 66'
               62  LOAD_CONST               True
               64  JUMP_FORWARD         68  'to 68'
             66_0  COME_FROM            60  '60'
               66  LOAD_CONST               False
             68_0  COME_FROM            64  '64'
               68  STORE_NAME               _REQUIRE_TILE

 L.  34        70  LOAD_CODE                <code_object _load_tile>
               72  LOAD_STR                 '_load_tile'
               74  MAKE_FUNCTION_0          'Neither defaults, keyword-only args, annotations, nor closures'
               76  STORE_NAME               _load_tile

 L.  49        78  LOAD_CONST               (False,)
               80  LOAD_CODE                <code_object _format_optvalue>
               82  LOAD_STR                 '_format_optvalue'
               84  MAKE_FUNCTION_1          'default'
               86  STORE_NAME               _format_optvalue

 L.  59        88  LOAD_CONST               (False, None)
               90  LOAD_CODE                <code_object _format_optdict>
               92  LOAD_STR                 '_format_optdict'
               94  MAKE_FUNCTION_1          'default'
               96  STORE_NAME               _format_optdict

 L.  75        98  LOAD_CODE                <code_object _mapdict_values>
              100  LOAD_STR                 '_mapdict_values'
              102  MAKE_FUNCTION_0          'Neither defaults, keyword-only args, annotations, nor closures'
              104  STORE_NAME               _mapdict_values

 L.  96       106  LOAD_CONST               (False,)
              108  LOAD_CODE                <code_object _format_mapdict>
              110  LOAD_STR                 '_format_mapdict'
              112  MAKE_FUNCTION_1          'default'
              114  STORE_NAME               _format_mapdict

 L. 113       116  LOAD_CONST               (False,)
              118  LOAD_CODE                <code_object _format_elemcreate>
              120  LOAD_STR                 '_format_elemcreate'
              122  MAKE_FUNCTION_1          'default'
              124  STORE_NAME               _format_elemcreate

 L. 150       126  LOAD_CONST               (0, 2)
              128  LOAD_CODE                <code_object _format_layoutlist>
              130  LOAD_STR                 '_format_layoutlist'
              132  MAKE_FUNCTION_1          'default'
              134  STORE_NAME               _format_layoutlist

 L. 199       136  LOAD_CODE                <code_object _script_from_settings>
              138  LOAD_STR                 '_script_from_settings'
              140  MAKE_FUNCTION_0          'Neither defaults, keyword-only args, annotations, nor closures'
              142  STORE_NAME               _script_from_settings

 L. 241       144  LOAD_CODE                <code_object _list_from_statespec>
              146  LOAD_STR                 '_list_from_statespec'
              148  MAKE_FUNCTION_0          'Neither defaults, keyword-only args, annotations, nor closures'
              150  STORE_NAME               _list_from_statespec

 L. 261       152  LOAD_CODE                <code_object _list_from_layouttuple>
              154  LOAD_STR                 '_list_from_layouttuple'
              156  MAKE_FUNCTION_0          'Neither defaults, keyword-only args, annotations, nor closures'
              158  STORE_NAME               _list_from_layouttuple

 L. 289       160  LOAD_CODE                <code_object _val_or_dict>
              162  LOAD_STR                 '_val_or_dict'
              164  MAKE_FUNCTION_0          'Neither defaults, keyword-only args, annotations, nor closures'
              166  STORE_NAME               _val_or_dict

 L. 305       168  LOAD_CODE                <code_object _convert_stringval>
              170  LOAD_STR                 '_convert_stringval'
              172  MAKE_FUNCTION_0          'Neither defaults, keyword-only args, annotations, nor closures'
              174  STORE_NAME               _convert_stringval

 L. 315       176  LOAD_CODE                <code_object _to_number>
              178  LOAD_STR                 '_to_number'
              180  MAKE_FUNCTION_0          'Neither defaults, keyword-only args, annotations, nor closures'
              182  STORE_NAME               _to_number

 L. 323       184  LOAD_CODE                <code_object _tclobj_to_py>
              186  LOAD_STR                 '_tclobj_to_py'
              188  MAKE_FUNCTION_0          'Neither defaults, keyword-only args, annotations, nor closures'
              190  STORE_NAME               _tclobj_to_py

 L. 336       192  LOAD_CODE                <code_object tclobjs_to_py>
              194  LOAD_STR                 'tclobjs_to_py'
              196  MAKE_FUNCTION_0          'Neither defaults, keyword-only args, annotations, nor closures'
              198  STORE_NAME               tclobjs_to_py

 L. 344       200  LOAD_CONST               (None,)
              202  LOAD_CODE                <code_object setup_master>
              204  LOAD_STR                 'setup_master'
              206  MAKE_FUNCTION_1          'default'
              208  STORE_NAME               setup_master

 L. 361       210  LOAD_BUILD_CLASS 
              212  LOAD_CODE                <code_object Style>
              214  LOAD_STR                 'Style'
              216  MAKE_FUNCTION_0          'Neither defaults, keyword-only args, annotations, nor closures'
              218  LOAD_STR                 'Style'
              220  LOAD_NAME                object
              222  CALL_FUNCTION_3       3  ''
              224  STORE_NAME               Style

 L. 530       226  LOAD_BUILD_CLASS 
              228  LOAD_CODE                <code_object Widget>
              230  LOAD_STR                 'Widget'
              232  MAKE_FUNCTION_0          'Neither defaults, keyword-only args, annotations, nor closures'
              234  LOAD_STR                 'Widget'
              236  LOAD_NAME                tkinter
              238  LOAD_ATTR                Widget
              240  CALL_FUNCTION_3       3  ''
              242  STORE_NAME               Widget

 L. 596       244  LOAD_BUILD_CLASS 
              246  LOAD_CODE                <code_object Button>
              248  LOAD_STR                 'Button'
              250  MAKE_FUNCTION_0          'Neither defaults, keyword-only args, annotations, nor closures'
              252  LOAD_STR                 'Button'
              254  LOAD_NAME                Widget
              256  CALL_FUNCTION_3       3  ''
              258  STORE_NAME               Button

 L. 620       260  LOAD_BUILD_CLASS 
              262  LOAD_CODE                <code_object Checkbutton>
              264  LOAD_STR                 'Checkbutton'
              266  MAKE_FUNCTION_0          'Neither defaults, keyword-only args, annotations, nor closures'
              268  LOAD_STR                 'Checkbutton'
              270  LOAD_NAME                Widget
              272  CALL_FUNCTION_3       3  ''
              274  STORE_NAME               Checkbutton

 L. 649       276  LOAD_BUILD_CLASS 
              278  LOAD_CODE                <code_object Entry>
              280  LOAD_STR                 'Entry'
              282  MAKE_FUNCTION_0          'Neither defaults, keyword-only args, annotations, nor closures'
              284  LOAD_STR                 'Entry'
              286  LOAD_NAME                Widget
              288  LOAD_NAME                tkinter
              290  LOAD_ATTR                Entry
              292  CALL_FUNCTION_4       4  ''
              294  STORE_NAME               Entry

 L. 691       296  LOAD_BUILD_CLASS 
              298  LOAD_CODE                <code_object Combobox>
              300  LOAD_STR                 'Combobox'
              302  MAKE_FUNCTION_0          'Neither defaults, keyword-only args, annotations, nor closures'
              304  LOAD_STR                 'Combobox'
              306  LOAD_NAME                Entry
              308  CALL_FUNCTION_3       3  ''
              310  STORE_NAME               Combobox

 L. 725       312  LOAD_BUILD_CLASS 
              314  LOAD_CODE                <code_object Frame>
              316  LOAD_STR                 'Frame'
              318  MAKE_FUNCTION_0          'Neither defaults, keyword-only args, annotations, nor closures'
              320  LOAD_STR                 'Frame'
              322  LOAD_NAME                Widget
              324  CALL_FUNCTION_3       3  ''
              326  STORE_NAME               Frame

 L. 743       328  LOAD_BUILD_CLASS 
              330  LOAD_CODE                <code_object Label>
              332  LOAD_STR                 'Label'
              334  MAKE_FUNCTION_0          'Neither defaults, keyword-only args, annotations, nor closures'
              336  LOAD_STR                 'Label'
              338  LOAD_NAME                Widget
              340  CALL_FUNCTION_3       3  ''
              342  STORE_NAME               Label

 L. 762       344  LOAD_BUILD_CLASS 
              346  LOAD_CODE                <code_object Labelframe>
              348  LOAD_STR                 'Labelframe'
              350  MAKE_FUNCTION_0          'Neither defaults, keyword-only args, annotations, nor closures'
              352  LOAD_STR                 'Labelframe'
              354  LOAD_NAME                Widget
              356  CALL_FUNCTION_3       3  ''
              358  STORE_NAME               Labelframe

 L. 780       360  LOAD_NAME                Labelframe
              362  STORE_NAME               LabelFrame

 L. 783       364  LOAD_BUILD_CLASS 
              366  LOAD_CODE                <code_object Menubutton>
              368  LOAD_STR                 'Menubutton'
              370  MAKE_FUNCTION_0          'Neither defaults, keyword-only args, annotations, nor closures'
              372  LOAD_STR                 'Menubutton'
              374  LOAD_NAME                Widget
              376  CALL_FUNCTION_3       3  ''
              378  STORE_NAME               Menubutton

 L. 802       380  LOAD_BUILD_CLASS 
              382  LOAD_CODE                <code_object Notebook>
              384  LOAD_STR                 'Notebook'
              386  MAKE_FUNCTION_0          'Neither defaults, keyword-only args, annotations, nor closures'
              388  LOAD_STR                 'Notebook'
              390  LOAD_NAME                Widget
              392  CALL_FUNCTION_3       3  ''
              394  STORE_NAME               Notebook

 L. 935       396  LOAD_BUILD_CLASS 
              398  LOAD_CODE                <code_object Panedwindow>
              400  LOAD_STR                 'Panedwindow'
              402  MAKE_FUNCTION_0          'Neither defaults, keyword-only args, annotations, nor closures'
              404  LOAD_STR                 'Panedwindow'
              406  LOAD_NAME                Widget
              408  LOAD_NAME                tkinter
              410  LOAD_ATTR                PanedWindow
              412  CALL_FUNCTION_4       4  ''
              414  STORE_NAME               Panedwindow

 L. 991       416  LOAD_NAME                Panedwindow
              418  STORE_NAME               PanedWindow

 L. 994       420  LOAD_BUILD_CLASS 
              422  LOAD_CODE                <code_object Progressbar>
              424  LOAD_STR                 'Progressbar'
              426  MAKE_FUNCTION_0          'Neither defaults, keyword-only args, annotations, nor closures'
              428  LOAD_STR                 'Progressbar'
              430  LOAD_NAME                Widget
              432  CALL_FUNCTION_3       3  ''
              434  STORE_NAME               Progressbar

 L.1036       436  LOAD_BUILD_CLASS 
              438  LOAD_CODE                <code_object Radiobutton>
              440  LOAD_STR                 'Radiobutton'
              442  MAKE_FUNCTION_0          'Neither defaults, keyword-only args, annotations, nor closures'
              444  LOAD_STR                 'Radiobutton'
              446  LOAD_NAME                Widget
              448  CALL_FUNCTION_3       3  ''
              450  STORE_NAME               Radiobutton

 L.1064       452  LOAD_BUILD_CLASS 
              454  LOAD_CODE                <code_object Scale>
              456  LOAD_STR                 'Scale'
              458  MAKE_FUNCTION_0          'Neither defaults, keyword-only args, annotations, nor closures'
              460  LOAD_STR                 'Scale'
              462  LOAD_NAME                Widget
              464  LOAD_NAME                tkinter
              466  LOAD_ATTR                Scale
              468  CALL_FUNCTION_4       4  ''
              470  STORE_NAME               Scale

 L.1104       472  LOAD_BUILD_CLASS 
              474  LOAD_CODE                <code_object Scrollbar>
              476  LOAD_STR                 'Scrollbar'
              478  MAKE_FUNCTION_0          'Neither defaults, keyword-only args, annotations, nor closures'
              480  LOAD_STR                 'Scrollbar'
              482  LOAD_NAME                Widget
              484  LOAD_NAME                tkinter
              486  LOAD_ATTR                Scrollbar
              488  CALL_FUNCTION_4       4  ''
              490  STORE_NAME               Scrollbar

 L.1121       492  LOAD_BUILD_CLASS 
              494  LOAD_CODE                <code_object Separator>
              496  LOAD_STR                 'Separator'
              498  MAKE_FUNCTION_0          'Neither defaults, keyword-only args, annotations, nor closures'
              500  LOAD_STR                 'Separator'
              502  LOAD_NAME                Widget
              504  CALL_FUNCTION_3       3  ''
              506  STORE_NAME               Separator

 L.1139       508  LOAD_BUILD_CLASS 
              510  LOAD_CODE                <code_object Sizegrip>
              512  LOAD_STR                 'Sizegrip'
              514  MAKE_FUNCTION_0          'Neither defaults, keyword-only args, annotations, nor closures'
              516  LOAD_STR                 'Sizegrip'
              518  LOAD_NAME                Widget
              520  CALL_FUNCTION_3       3  ''
              522  STORE_NAME               Sizegrip

 L.1153       524  LOAD_BUILD_CLASS 
              526  LOAD_CODE                <code_object Spinbox>
              528  LOAD_STR                 'Spinbox'
              530  MAKE_FUNCTION_0          'Neither defaults, keyword-only args, annotations, nor closures'
              532  LOAD_STR                 'Spinbox'
              534  LOAD_NAME                Entry
              536  CALL_FUNCTION_3       3  ''
              538  STORE_NAME               Spinbox

 L.1180       540  LOAD_BUILD_CLASS 
              542  LOAD_CODE                <code_object Treeview>
              544  LOAD_STR                 'Treeview'
              546  MAKE_FUNCTION_0          'Neither defaults, keyword-only args, annotations, nor closures'
              548  LOAD_STR                 'Treeview'
              550  LOAD_NAME                Widget
              552  LOAD_NAME                tkinter
              554  LOAD_ATTR                XView
              556  LOAD_NAME                tkinter
              558  LOAD_ATTR                YView
              560  CALL_FUNCTION_5       5  ''
              562  STORE_NAME               Treeview

 L.1508       564  LOAD_BUILD_CLASS 
              566  LOAD_CODE                <code_object LabeledScale>
              568  LOAD_STR                 'LabeledScale'
              570  MAKE_FUNCTION_0          'Neither defaults, keyword-only args, annotations, nor closures'
              572  LOAD_STR                 'LabeledScale'
              574  LOAD_NAME                Frame
              576  CALL_FUNCTION_3       3  ''
              578  STORE_NAME               LabeledScale

 L.1601       580  LOAD_BUILD_CLASS 
              582  LOAD_CODE                <code_object OptionMenu>
              584  LOAD_STR                 'OptionMenu'
              586  MAKE_FUNCTION_0          'Neither defaults, keyword-only args, annotations, nor closures'
              588  LOAD_STR                 'OptionMenu'
              590  LOAD_NAME                Menubutton
              592  CALL_FUNCTION_3       3  ''
              594  STORE_NAME               OptionMenu

Parse error at or near `CALL_FINALLY' instruction at offset 16

Instruction context:
   
 L.  19        12  BUILD_LIST_0          0 
                  14  LOAD_CONST               ('Button', 'Checkbutton', 'Combobox', 'Entry', 'Frame', 'Label', 'Labelframe', 'LabelFrame', 'Menubutton', 'Notebook', 'Panedwindow', 'PanedWindow', 'Progressbar', 'Radiobutton', 'Scale', 'Scrollbar', 'Separator', 'Sizegrip', 'Spinbox', 'Style', 'Treeview', 'LabeledScale', 'OptionMenu', 'tclobjs_to_py', 'setup_master')
->                16  CALL_FINALLY         19  'to 19'
                  18  STORE_NAME               __all__

test/101340.pyc -- 
# decompile failed
