
# file test/101352.pyc
# --- This code section failed: ---

 L.   1         0  LOAD_STR                 '\nPython unit testing framework, based on Erich Gamma\'s JUnit and Kent Beck\'s\nSmalltalk testing framework (used with permission).\n\nThis module contains the core framework classes that form the basis of\nspecific test cases and suites (TestCase, TestSuite etc.), and also a\ntext-based utility class for running the tests and reporting the results\n (TextTestRunner).\n\nSimple usage:\n\n    import unittest\n\n    class IntegerArithmeticTestCase(unittest.TestCase):\n        def testAdd(self):  # test method names begin with \'test\'\n            self.assertEqual((1 + 2), 3)\n            self.assertEqual(0 + 1, 1)\n        def testMultiply(self):\n            self.assertEqual((0 * 10), 0)\n            self.assertEqual((5 * 8), 40)\n\n    if __name__ == \'__main__\':\n        unittest.main()\n\nFurther information is available in the bundled documentation, and from\n\n  http://docs.python.org/library/unittest.html\n\nCopyright (c) 1999-2003 Steve Purcell\nCopyright (c) 2003-2010 Python Software Foundation\nThis module is free software, and you may redistribute it and/or modify\nit under the same terms as Python itself, so long as this copyright message\nand disclaimer are retained in their original form.\n\nIN NO EVENT SHALL THE AUTHOR BE LIABLE TO ANY PARTY FOR DIRECT, INDIRECT,\nSPECIAL, INCIDENTAL, OR CONSEQUENTIAL DAMAGES ARISING OUT OF THE USE OF\nTHIS CODE, EVEN IF THE AUTHOR HAS BEEN ADVISED OF THE POSSIBILITY OF SUCH\nDAMAGE.\n\nTHE AUTHOR SPECIFICALLY DISCLAIMS ANY WARRANTIES, INCLUDING, BUT NOT\nLIMITED TO, THE IMPLIED WARRANTIES OF MERCHANTABILITY AND FITNESS FOR A\nPARTICULAR PURPOSE.  THE CODE PROVIDED HEREUNDER IS ON AN "AS IS" BASIS,\nAND THERE IS NO OBLIGATION WHATSOEVER TO PROVIDE MAINTENANCE,\nSUPPORT, UPDATES, ENHANCEMENTS, OR MODIFICATIONS.\n'
                2  STORE_NAME               __doc__

 L.  47         4  BUILD_LIST_0          0 
                6  LOAD_CONST               ('TestResult', 'TestCase', 'IsolatedAsyncioTestCase', 'TestSuite', 'TextTestRunner', 'TestLoader', 'FunctionTestCase', 'main', 'defaultTestLoader', 'SkipTest', 'skip', 'skipIf', 'skipUnless', 'expectedFailure', 'TextTestResult', 'installHandler', 'registerResult', 'removeResult', 'removeHandler', 'addModuleCleanup')
                8  CALL_FINALLY         11  'to 11'
               10  STORE_NAME               __all__

 L.  55        12  LOAD_NAME                __all__
               14  LOAD_METHOD              extend
               16  BUILD_LIST_0          0 
               18  LOAD_CONST               ('getTestCaseNames', 'makeSuite', 'findTestCases')
               20  CALL_FINALLY         23  'to 23'
               22  CALL_METHOD_1         1  ''
               24  POP_TOP          

 L.  57        26  LOAD_CONST               True
               28  STORE_NAME               __unittest

 L.  59        30  LOAD_CONST               1
               32  LOAD_CONST               ('TestResult',)
               34  IMPORT_NAME              result
               36  IMPORT_FROM              TestResult
               38  STORE_NAME               TestResult
               40  POP_TOP          

 L.  60        42  LOAD_CONST               1
               44  LOAD_CONST               ('addModuleCleanup', 'TestCase', 'FunctionTestCase', 'SkipTest', 'skip', 'skipIf', 'skipUnless', 'expectedFailure')
               46  IMPORT_NAME              case
               48  IMPORT_FROM              addModuleCleanup
               50  STORE_NAME               addModuleCleanup
               52  IMPORT_FROM              TestCase
               54  STORE_NAME               TestCase
               56  IMPORT_FROM              FunctionTestCase
               58  STORE_NAME               FunctionTestCase
               60  IMPORT_FROM              SkipTest
               62  STORE_NAME               SkipTest
               64  IMPORT_FROM              skip
               66  STORE_NAME               skip
               68  IMPORT_FROM              skipIf
               70  STORE_NAME               skipIf
               72  IMPORT_FROM              skipUnless
               74  STORE_NAME               skipUnless
               76  IMPORT_FROM              expectedFailure
               78  STORE_NAME               expectedFailure
               80  POP_TOP          

 L.  62        82  LOAD_CONST               1
               84  LOAD_CONST               ('BaseTestSuite', 'TestSuite')
               86  IMPORT_NAME              suite
               88  IMPORT_FROM              BaseTestSuite
               90  STORE_NAME               BaseTestSuite
               92  IMPORT_FROM              TestSuite
               94  STORE_NAME               TestSuite
               96  POP_TOP          

 L.  63        98  LOAD_CONST               1
              100  LOAD_CONST               ('TestLoader', 'defaultTestLoader', 'makeSuite', 'getTestCaseNames', 'findTestCases')
              102  IMPORT_NAME              loader
              104  IMPORT_FROM              TestLoader
              106  STORE_NAME               TestLoader
              108  IMPORT_FROM              defaultTestLoader
              110  STORE_NAME               defaultTestLoader
              112  IMPORT_FROM              makeSuite
              114  STORE_NAME               makeSuite
              116  IMPORT_FROM              getTestCaseNames
              118  STORE_NAME               getTestCaseNames
              120  IMPORT_FROM              findTestCases
              122  STORE_NAME               findTestCases
              124  POP_TOP          

 L.  65       126  LOAD_CONST               1
              128  LOAD_CONST               ('TestProgram', 'main')
              130  IMPORT_NAME              main
              132  IMPORT_FROM              TestProgram
              134  STORE_NAME               TestProgram
              136  IMPORT_FROM              main
              138  STORE_NAME               main
              140  POP_TOP          

 L.  66       142  LOAD_CONST               1
              144  LOAD_CONST               ('TextTestRunner', 'TextTestResult')
              146  IMPORT_NAME              runner
              148  IMPORT_FROM              TextTestRunner
              150  STORE_NAME               TextTestRunner
              152  IMPORT_FROM              TextTestResult
              154  STORE_NAME               TextTestResult
              156  POP_TOP          

 L.  67       158  LOAD_CONST               1
              160  LOAD_CONST               ('installHandler', 'registerResult', 'removeResult', 'removeHandler')
              162  IMPORT_NAME              signals
              164  IMPORT_FROM              installHandler
              166  STORE_NAME               installHandler
              168  IMPORT_FROM              registerResult
              170  STORE_NAME               registerResult
              172  IMPORT_FROM              removeResult
              174  STORE_NAME               removeResult
              176  IMPORT_FROM              removeHandler
              178  STORE_NAME               removeHandler
              180  POP_TOP          

 L.  71       182  LOAD_NAME                TextTestResult
              184  STORE_NAME               _TextTestResult

 L.  76       186  LOAD_CODE                <code_object load_tests>
              188  LOAD_STR                 'load_tests'
              190  MAKE_FUNCTION_0          'Neither defaults, keyword-only args, annotations, nor closures'
              192  STORE_NAME               load_tests

 L.  87       194  LOAD_CODE                <code_object __dir__>
              196  LOAD_STR                 '__dir__'
              198  MAKE_FUNCTION_0          'Neither defaults, keyword-only args, annotations, nor closures'
              200  STORE_NAME               __dir__

 L.  90       202  LOAD_CODE                <code_object __getattr__>
              204  LOAD_STR                 '__getattr__'
              206  MAKE_FUNCTION_0          'Neither defaults, keyword-only args, annotations, nor closures'
              208  STORE_NAME               __getattr__

Parse error at or near `CALL_FINALLY' instruction at offset 8

Instruction context:
   
 L.  47         4  BUILD_LIST_0          0 
                   6  LOAD_CONST               ('TestResult', 'TestCase', 'IsolatedAsyncioTestCase', 'TestSuite', 'TextTestRunner', 'TestLoader', 'FunctionTestCase', 'main', 'defaultTestLoader', 'SkipTest', 'skip', 'skipIf', 'skipUnless', 'expectedFailure', 'TextTestResult', 'installHandler', 'registerResult', 'removeResult', 'removeHandler', 'addModuleCleanup')
->                 8  CALL_FINALLY         11  'to 11'
                  10  STORE_NAME               __all__

test/101352.pyc -- 
# decompile failed
