Instruction context:
   
 L.  67       116  BUILD_SET_0           0 
                 118  LOAD_CONST               frozenset({1, 2, 3, 4, 5, 6, 7, 8, 11, 14, 15, 16, 17, 18, 19, 20, 21, 22, 23, 24, 25, 26, 27, 28, 29, 30, 31, 589823, 1114111, 655358, 589822, 655359, 131071, 1114110, 127, 128, 129, 130, 131, 132, 133, 134, 135, 136, 137, 138, 139, 140, 141, 142, 143, 144, 145, 146, 147, 148, 149, 150, 151, 152, 153, 154, 155, 156, 157, 158, 159, 720895, 196607, 786430, 720894, 262143, 786431, 851966, 851967, 917502, 393215, 917503, 983038, 458751, 983039, 524286, 64976, 64977, 64978, 64979, 64980, 64981, 64982, 64983, 64984, 64985, 64986, 64987, 64988, 64989, 64990, 64991, 64992, 64993, 64994, 64995, 64996, 64997, 64998, 524287, 1048575, 64999, 65000, 65001, 65002, 65003, 65004, 65005, 65006, 65007, 196606, 262142, 327678, 393214, 65534, 327679, 458750, 1048574, 131070, 65535})
->               120  POP_FINALLY           1  ''
                 122  STORE_NAME               _invalid_codepoints

test/101701.pyc -- 
# decompile failed

# file test/101701.pyc
# --- This code section failed: ---

 L.   1         0  LOAD_STR                 '\nGeneral functions for HTML manipulation.\n'
                2  STORE_NAME               __doc__

 L.   5         4  LOAD_CONST               0
                6  LOAD_CONST               None
                8  IMPORT_NAME              re
               10  STORE_NAME               _re

 L.   6        12  LOAD_CONST               0
               14  LOAD_CONST               ('html5',)
               16  IMPORT_NAME_ATTR         html.entities
               18  IMPORT_FROM              html5
               20  STORE_NAME               _html5
               22  POP_TOP          

 L.   9        24  LOAD_STR                 'escape'
               26  LOAD_STR                 'unescape'
               28  BUILD_LIST_2          2 
               30  STORE_NAME               __all__

 L.  12        32  LOAD_CONST               (True,)
               34  LOAD_CODE                <code_object escape>
               36  LOAD_STR                 'escape'
               38  MAKE_FUNCTION_1          'default'
               40  STORE_NAME               escape

 L.  31        42  LOAD_STR                 '�'

 L.  32        44  LOAD_STR                 '\r'

 L.  33        46  LOAD_STR                 '€'

 L.  34        48  LOAD_STR                 '\x81'

 L.  35        50  LOAD_STR                 '‚'

 L.  36        52  LOAD_STR                 'ƒ'

 L.  37        54  LOAD_STR                 '„'

 L.  38        56  LOAD_STR                 '…'

 L.  39        58  LOAD_STR                 '†'

 L.  40        60  LOAD_STR                 '‡'

 L.  41        62  LOAD_STR                 'ˆ'

 L.  42        64  LOAD_STR                 '‰'

 L.  43        66  LOAD_STR                 'Š'

 L.  44        68  LOAD_STR                 '‹'

 L.  45        70  LOAD_STR                 'Œ'

 L.  46        72  LOAD_STR                 '\x8d'

 L.  47        74  LOAD_STR                 'Ž'

 L.  48        76  LOAD_STR                 '\x8f'

 L.  49        78  LOAD_STR                 '\x90'

 L.  50        80  LOAD_STR                 '‘'

 L.  51        82  LOAD_STR                 '’'

 L.  52        84  LOAD_STR                 '“'

 L.  53        86  LOAD_STR                 '”'

 L.  54        88  LOAD_STR                 '•'

 L.  55        90  LOAD_STR                 '–'

 L.  56        92  LOAD_STR                 '—'

 L.  57        94  LOAD_STR                 '˜'

 L.  58        96  LOAD_STR                 '™'

 L.  59        98  LOAD_STR                 'š'

 L.  60       100  LOAD_STR                 '›'

 L.  61       102  LOAD_STR                 'œ'

 L.  62       104  LOAD_STR                 '\x9d'

 L.  63       106  LOAD_STR                 'ž'

 L.  64       108  LOAD_STR                 'Ÿ'

 L.  30       110  LOAD_CONST               (0, 13, 128, 129, 130, 131, 132, 133, 134, 135, 136, 137, 138, 139, 140, 141, 142, 143, 144, 145, 146, 147, 148, 149, 150, 151, 152, 153, 154, 155, 156, 157, 158, 159)
              112  BUILD_CONST_KEY_MAP_34    34 
              114  STORE_NAME               _invalid_charrefs

 L.  67       116  BUILD_SET_0           0 
              118  LOAD_CONST               frozenset({1, 2, 3, 4, 5, 6, 7, 8, 11, 14, 15, 16, 17, 18, 19, 20, 21, 22, 23, 24, 25, 26, 27, 28, 29, 30, 31, 589823, 1114111, 655358, 589822, 655359, 131071, 1114110, 127, 128, 129, 130, 131, 132, 133, 134, 135, 136, 137, 138, 139, 140, 141, 142, 143, 144, 145, 146, 147, 148, 149, 150, 151, 152, 153, 154, 155, 156, 157, 158, 159, 720895, 196607, 786430, 720894, 262143, 786431, 851966, 851967, 917502, 393215, 917503, 983038, 458751, 983039, 524286, 64976, 64977, 64978, 64979, 64980, 64981, 64982, 64983, 64984, 64985, 64986, 64987, 64988, 64989, 64990, 64991, 64992, 64993, 64994, 64995, 64996, 64997, 64998, 524287, 1048575, 64999, 65000, 65001, 65002, 65003, 65004, 65005, 65006, 65007, 196606, 262142, 327678, 393214, 65534, 327679, 458750, 1048574, 131070, 65535})
              120  POP_FINALLY           1  ''
              122  STORE_NAME               _invalid_codepoints

 L.  91       124  LOAD_CODE                <code_object _replace_charref>
              126  LOAD_STR                 '_replace_charref'
              128  MAKE_FUNCTION_0          'Neither defaults, keyword-only args, annotations, nor closures'
              130  STORE_NAME               _replace_charref

 L. 118       132  LOAD_NAME                _re
              134  LOAD_METHOD              compile
              136  LOAD_STR                 '&(#[0-9]+;?|#[xX][0-9a-fA-F]+;?|[^\\t\\n\\f <&#;]{1,32};?)'
              138  CALL_METHOD_1         1  ''
              140  STORE_NAME               _charref

 L. 122       142  LOAD_CODE                <code_object unescape>
              144  LOAD_STR                 'unescape'
              146  MAKE_FUNCTION_0          'Neither defaults, keyword-only args, annotations, nor closures'
              148  STORE_NAME               unescape

Parse error at or near `POP_FINALLY' instruction at offset 120

