Instruction context:
   
 L.  96        68  DUP_TOP          
                  70  LOAD_GLOBAL              ValueError
                  72  LOAD_GLOBAL              OSError
                  74  BUILD_TUPLE_2         2 
->                76  <121>               118  ''
                  78  POP_TOP          
                  80  STORE_FAST               'exc'
                  82  POP_TOP          
                  84  SETUP_FINALLY       110  'to 110'
Instruction context:
   
 L. 126        12  LOAD_FAST                'handle'
                  14  LOAD_CONST               None
->                16  <117>                 0  ''
                  18  POP_JUMP_IF_FALSE    24  'to 24'
Instruction context:
   
 L. 141        24  DUP_TOP          
                  26  LOAD_GLOBAL              KeyError
->                28  <121>                42  ''
                  30  POP_TOP          
                  32  POP_TOP          
                  34  POP_TOP          
Instruction context:
   
 L. 174        24  LOAD_FAST                'sig'
                  26  LOAD_GLOBAL              signal
                  28  LOAD_METHOD              valid_signals
                  30  CALL_METHOD_0         0  ''
->                32  <118>                 1  ''
                  34  POP_JUMP_IF_FALSE    50  'to 50'
Instruction context:
-> 
 L. 197        64  <164>                 1  ''
                  66  CALL_FUNCTION_EX_KW     1  'keyword and positional arguments'
                  68  STORE_FAST               'transp'
Instruction context:
   
 L. 271        18  LOAD_FAST                'ssl_handshake_timeout'
                  20  LOAD_CONST               None
->                22  <117>                 1  ''
                  24  POP_JUMP_IF_FALSE    38  'to 38'
                  26  LOAD_FAST                'ssl'
                  28  POP_JUMP_IF_TRUE     38  'to 38'
Instruction context:
   
 L. 333        12  DUP_TOP          
                  14  LOAD_GLOBAL              AttributeError
->                16  <121>                38  ''
                  18  POP_TOP          
                  20  POP_TOP          
                  22  POP_TOP          
Instruction context:
   
 L. 356         8  LOAD_FAST                'registered_fd'
                  10  LOAD_CONST               None
->                12  <117>                 1  ''
                  14  POP_JUMP_IF_FALSE    26  'to 26'
Instruction context:
   
 L. 465       188  LOAD_FAST                'waiter'
                 190  LOAD_CONST               None
->               192  <117>                 1  ''
                 194  POP_JUMP_IF_FALSE   214  'to 214'
Instruction context:
   
 L. 472        10  LOAD_FAST                'self'
                  12  LOAD_ATTR                _pipe
                  14  LOAD_CONST               None
->                16  <117>                 0  ''
                  18  POP_JUMP_IF_FALSE    32  'to 32'
Instruction context:
   
 L. 494        22  DUP_TOP          
                  24  LOAD_GLOBAL              BlockingIOError
                  26  LOAD_GLOBAL              InterruptedError
                  28  BUILD_TUPLE_2         2 
->                30  <121>                42  ''
                  32  POP_TOP          
                  34  POP_TOP          
                  36  POP_TOP          
Instruction context:
   
 L. 566        16  LOAD_FAST                'self'
                  18  LOAD_ATTR                _pipe
                  20  LOAD_METHOD              close
                  22  CALL_METHOD_0         0  ''
->                24  POP_TOP          
Instruction context:
   
 L. 607       224  LOAD_FAST                'waiter'
                 226  LOAD_CONST               None
->               228  <117>                 1  ''
                 230  POP_JUMP_IF_FALSE   250  'to 250'
Instruction context:
   
 L. 614        10  LOAD_FAST                'self'
                  12  LOAD_ATTR                _pipe
                  14  LOAD_CONST               None
->                16  <117>                 0  ''
                  18  POP_JUMP_IF_FALSE    32  'to 32'
Instruction context:
   
 L. 717        10  LOAD_FAST                'self'
                  12  LOAD_ATTR                _pipe
                  14  POP_JUMP_IF_TRUE     20  'to 20'
->                16  <74>             
                  18  RAISE_VARARGS_1       1  'exception instance'
                20_0  COME_FROM            14  '14'
Instruction context:
   
 L. 771        16  LOAD_FAST                'self'
                  18  LOAD_ATTR                _pipe
                  20  LOAD_METHOD              close
                  22  CALL_METHOD_0         0  ''
->                24  POP_TOP          
Instruction context:
-> 
 L. 789        54  <164>                 1  ''
                  56  CALL_FUNCTION_EX_KW     1  'keyword and positional arguments'
                  58  LOAD_FAST                'self'
                  60  STORE_ATTR               _proc
Instruction context:
   
 L. 923        12  LOAD_FAST                'existing'
                  14  LOAD_CONST               None
->                16  <117>                 1  ''
                  18  POP_JUMP_IF_FALSE    42  'to 42'
Instruction context:
   
 L. 935        52  DUP_TOP          
                  54  LOAD_GLOBAL              ChildProcessError
->                56  <121>                84  ''
                  58  POP_TOP          
                  60  POP_TOP          
                  62  POP_TOP          
Instruction context:
   
 L. 952        24  DUP_TOP          
                  26  LOAD_GLOBAL              KeyError
->                28  <121>                42  ''
                  30  POP_TOP          
                  32  POP_TOP          
                  34  POP_TOP          
Instruction context:
   
 L.1014        14  DUP_TOP          
                  16  LOAD_GLOBAL              SystemExit
                  18  LOAD_GLOBAL              KeyboardInterrupt
                  20  BUILD_TUPLE_2         2 
->                22  <121>                36  ''
                  24  POP_TOP          
                  26  POP_TOP          
                  28  POP_TOP          
Instruction context:
-> 
 L.1057        16  DUP_TOP          
                  18  LOAD_GLOBAL              KeyError
                  20  <121>                34  ''
                  22  POP_TOP          
                  24  POP_TOP          
                  26  POP_TOP          
Instruction context:
   
 L.1125        22  LOAD_FAST                'self'
                  24  POP_BLOCK        
                  26  ROT_TWO          
->                28  LOAD_CONST               None
                  30  DUP_TOP          
                  32  DUP_TOP          
                  34  CALL_FUNCTION_3       3  ''
                  36  POP_TOP          
                  38  RETURN_VALUE     
                40_0  COME_FROM_WITH        4  '4'
                  40  <49>             
                  42  POP_JUMP_IF_TRUE     46  'to 46'
                  44  <48>             
                46_0  COME_FROM            42  '42'
                  46  POP_TOP          
                  48  POP_TOP          
                  50  POP_TOP          
                  52  POP_EXCEPT       
Instruction context:
   
 L.1132        34  POP_BLOCK        
->                36  LOAD_CONST               None
                  38  DUP_TOP          
                  40  DUP_TOP          
                  42  CALL_FUNCTION_3       3  ''
                  44  POP_TOP          
                  46  LOAD_CONST               None
                  48  RETURN_VALUE     
                50_0  COME_FROM            32  '32'
Instruction context:
-> 
 L.1159        16  DUP_TOP          
                  18  LOAD_GLOBAL              KeyError
                  20  <121>                34  ''
                  22  POP_TOP          
                  24  POP_TOP          
                  26  POP_TOP          
Instruction context:
   
 L.1168        24  DUP_TOP          
                  26  LOAD_GLOBAL              ChildProcessError
->                28  <121>                42  ''
                  30  POP_TOP          
                  32  POP_TOP          
                  34  POP_TOP          
Instruction context:
   
 L.1233        10  LOAD_FAST                'self'
                  12  LOAD_ATTR                _saved_sighandler
                  14  LOAD_CONST               None
->                16  <117>                 0  ''
                  18  POP_JUMP_IF_FALSE    24  'to 24'
Instruction context:
-> 
 L.1260        16  DUP_TOP          
                  18  LOAD_GLOBAL              KeyError
                  20  <121>                34  ''
                  22  POP_TOP          
                  24  POP_TOP          
                  26  POP_TOP          
Instruction context:
   
 L.1324        14  DUP_TOP          
                  16  LOAD_GLOBAL              SystemExit
                  18  LOAD_GLOBAL              KeyboardInterrupt
                  20  BUILD_TUPLE_2         2 
->                22  <121>                36  ''
                  24  POP_TOP          
                  26  POP_TOP          
                  28  POP_TOP          
Instruction context:
   
 L.1429         8  LOAD_FAST                'self'
                  10  LOAD_ATTR                _watcher
                  12  LOAD_CONST               None
->                14  <117>                 0  ''
                  16  POP_JUMP_IF_FALSE    58  'to 58'
Instruction context:
   
 L.1444        12  LOAD_FAST                'self'
                  14  LOAD_ATTR                _watcher
                  16  LOAD_CONST               None
->                18  <117>                 1  ''
                  20  POP_JUMP_IF_FALSE    50  'to 50'

test/103777.pyc -- 
# decompile failed

# file test/103777.pyc
# Deparsing stopped due to parse error
