
# file test/103984.pyc
# --- This code section failed: ---

 L.   1         0  LOAD_CONST               0
                2  LOAD_CONST               None
                4  IMPORT_NAME              calendar
                6  STORE_NAME               calendar

 L.   2         8  LOAD_CONST               0
               10  LOAD_CONST               None
               12  IMPORT_NAME              datetime
               14  STORE_NAME               datetime

 L.   4        16  LOAD_CONST               0
               18  LOAD_CONST               ('b16encode',)
               20  IMPORT_NAME              base64
               22  IMPORT_FROM              b16encode
               24  STORE_NAME               b16encode
               26  POP_TOP          

 L.   5        28  LOAD_CONST               0
               30  LOAD_CONST               ('partial',)
               32  IMPORT_NAME              functools
               34  IMPORT_FROM              partial
               36  STORE_NAME               partial
               38  POP_TOP          

 L.   6        40  LOAD_CONST               0
               42  LOAD_CONST               ('__eq__', '__ne__', '__lt__', '__le__', '__gt__', '__ge__')
               44  IMPORT_NAME              operator
               46  IMPORT_FROM              __eq__
               48  STORE_NAME               __eq__
               50  IMPORT_FROM              __ne__
               52  STORE_NAME               __ne__
               54  IMPORT_FROM              __lt__
               56  STORE_NAME               __lt__
               58  IMPORT_FROM              __le__
               60  STORE_NAME               __le__
               62  IMPORT_FROM              __gt__
               64  STORE_NAME               __gt__
               66  IMPORT_FROM              __ge__
               68  STORE_NAME               __ge__
               70  POP_TOP          

 L.   8        72  LOAD_CONST               0
               74  LOAD_CONST               ('integer_types', 'text_type', 'PY2')
               76  IMPORT_NAME              six
               78  IMPORT_FROM              integer_types
               80  STORE_NAME               _integer_types
               82  IMPORT_FROM              text_type
               84  STORE_NAME               _text_type
               86  IMPORT_FROM              PY2
               88  STORE_NAME               _PY2
               90  POP_TOP          

 L.  14        92  LOAD_CONST               0
               94  LOAD_CONST               ('utils', 'x509')
               96  IMPORT_NAME              cryptography
               98  IMPORT_FROM              utils
              100  STORE_NAME               utils
              102  IMPORT_FROM              x509
              104  STORE_NAME               x509
              106  POP_TOP          

 L.  15       108  LOAD_CONST               0
              110  LOAD_CONST               ('dsa', 'rsa')
              112  IMPORT_NAME_ATTR         cryptography.hazmat.primitives.asymmetric
              114  IMPORT_FROM              dsa
              116  STORE_NAME               dsa
              118  IMPORT_FROM              rsa
              120  STORE_NAME               rsa
              122  POP_TOP          

 L.  17       124  LOAD_CONST               0
              126  LOAD_CONST               ('ffi', 'lib', 'exception_from_error_queue', 'byte_string', 'native', 'path_string', 'UNSPECIFIED', 'text_to_bytes_and_warn', 'make_assert')
              128  IMPORT_NAME_ATTR         OpenSSL._util
              130  IMPORT_FROM              ffi
              132  STORE_NAME               _ffi
              134  IMPORT_FROM              lib
              136  STORE_NAME               _lib
              138  IMPORT_FROM              exception_from_error_queue
              140  STORE_NAME               _exception_from_error_queue
              142  IMPORT_FROM              byte_string
              144  STORE_NAME               _byte_string
              146  IMPORT_FROM              native
              148  STORE_NAME               _native
              150  IMPORT_FROM              path_string
              152  STORE_NAME               _path_string
              154  IMPORT_FROM              UNSPECIFIED
              156  STORE_NAME               _UNSPECIFIED
              158  IMPORT_FROM              text_to_bytes_and_warn
              160  STORE_NAME               _text_to_bytes_and_warn
              162  IMPORT_FROM              make_assert
              164  STORE_NAME               _make_assert
              166  POP_TOP          

 L.  29       168  BUILD_LIST_0          0 
              170  LOAD_CONST               ('FILETYPE_PEM', 'FILETYPE_ASN1', 'FILETYPE_TEXT', 'TYPE_RSA', 'TYPE_DSA', 'Error', 'PKey', 'get_elliptic_curves', 'get_elliptic_curve', 'X509Name', 'X509Extension', 'X509Req', 'X509', 'X509StoreFlags', 'X509Store', 'X509StoreContextError', 'X509StoreContext', 'load_certificate', 'dump_certificate', 'dump_publickey', 'dump_privatekey', 'Revoked', 'CRL', 'PKCS7', 'PKCS12', 'NetscapeSPKI', 'load_publickey', 'load_privatekey', 'dump_certificate_request', 'load_certificate_request', 'sign', 'verify', 'dump_crl', 'load_crl', 'load_pkcs7_data', 'load_pkcs12')
              172  CALL_FINALLY        175  'to 175'
              174  STORE_NAME               __all__

 L.  68       176  LOAD_NAME                _lib
              178  LOAD_ATTR                SSL_FILETYPE_PEM
              180  STORE_NAME               FILETYPE_PEM

 L.  69       182  LOAD_NAME                _lib
              184  LOAD_ATTR                SSL_FILETYPE_ASN1
              186  STORE_NAME               FILETYPE_ASN1

 L.  72       188  LOAD_CONST               65535
              190  STORE_NAME               FILETYPE_TEXT

 L.  74       192  LOAD_NAME                _lib
              194  LOAD_ATTR                EVP_PKEY_RSA
              196  STORE_NAME               TYPE_RSA

 L.  75       198  LOAD_NAME                _lib
              200  LOAD_ATTR                EVP_PKEY_DSA
              202  STORE_NAME               TYPE_DSA

 L.  76       204  LOAD_NAME                _lib
              206  LOAD_ATTR                EVP_PKEY_DH
              208  STORE_NAME               TYPE_DH

 L.  77       210  LOAD_NAME                _lib
              212  LOAD_ATTR                EVP_PKEY_EC
              214  STORE_NAME               TYPE_EC

 L.  80       216  LOAD_BUILD_CLASS 
              218  LOAD_CODE                <code_object Error>
              220  LOAD_STR                 'Error'
              222  MAKE_FUNCTION_0          'Neither defaults, keyword-only args, annotations, nor closures'
              224  LOAD_STR                 'Error'
              226  LOAD_NAME                Exception
              228  CALL_FUNCTION_3       3  ''
              230  STORE_NAME               Error

 L.  86       232  LOAD_NAME                partial
              234  LOAD_NAME                _exception_from_error_queue
              236  LOAD_NAME                Error
              238  CALL_FUNCTION_2       2  ''
              240  STORE_NAME               _raise_current_error

 L.  87       242  LOAD_NAME                _make_assert
              244  LOAD_NAME                Error
              246  CALL_FUNCTION_1       1  ''
              248  STORE_NAME               _openssl_assert

 L.  90       250  LOAD_CODE                <code_object _get_backend>
              252  LOAD_STR                 '_get_backend'
              254  MAKE_FUNCTION_0          'Neither defaults, keyword-only args, annotations, nor closures'
              256  STORE_NAME               _get_backend

 L. 103       258  LOAD_CODE                <code_object _untested_error>
              260  LOAD_STR                 '_untested_error'
              262  MAKE_FUNCTION_0          'Neither defaults, keyword-only args, annotations, nor closures'
              264  STORE_NAME               _untested_error

 L. 112       266  LOAD_CONST               (None,)
              268  LOAD_CODE                <code_object _new_mem_buf>
              270  LOAD_STR                 '_new_mem_buf'
              272  MAKE_FUNCTION_1          'default'
              274  STORE_NAME               _new_mem_buf

 L. 138       276  LOAD_CODE                <code_object _bio_to_string>
              278  LOAD_STR                 '_bio_to_string'
              280  MAKE_FUNCTION_0          'Neither defaults, keyword-only args, annotations, nor closures'
              282  STORE_NAME               _bio_to_string

 L. 147       284  LOAD_CODE                <code_object _set_asn1_time>
              286  LOAD_STR                 '_set_asn1_time'
              288  MAKE_FUNCTION_0          'Neither defaults, keyword-only args, annotations, nor closures'
              290  STORE_NAME               _set_asn1_time

 L. 169       292  LOAD_CODE                <code_object _get_asn1_time>
              294  LOAD_STR                 '_get_asn1_time'
              296  MAKE_FUNCTION_0          'Neither defaults, keyword-only args, annotations, nor closures'
              298  STORE_NAME               _get_asn1_time

 L. 210       300  LOAD_BUILD_CLASS 
              302  LOAD_CODE                <code_object _X509NameInvalidator>
              304  LOAD_STR                 '_X509NameInvalidator'
              306  MAKE_FUNCTION_0          'Neither defaults, keyword-only args, annotations, nor closures'
              308  LOAD_STR                 '_X509NameInvalidator'
              310  LOAD_NAME                object
              312  CALL_FUNCTION_3       3  ''
              314  STORE_NAME               _X509NameInvalidator

 L. 223       316  LOAD_BUILD_CLASS 
              318  LOAD_CODE                <code_object PKey>
              320  LOAD_STR                 'PKey'
              322  MAKE_FUNCTION_0          'Neither defaults, keyword-only args, annotations, nor closures'
              324  LOAD_STR                 'PKey'
              326  LOAD_NAME                object
              328  CALL_FUNCTION_3       3  ''
              330  STORE_NAME               PKey

 L. 382       332  LOAD_BUILD_CLASS 
              334  LOAD_CODE                <code_object _EllipticCurve>
              336  LOAD_STR                 '_EllipticCurve'
              338  MAKE_FUNCTION_0          'Neither defaults, keyword-only args, annotations, nor closures'
              340  LOAD_STR                 '_EllipticCurve'
              342  LOAD_NAME                object
              344  CALL_FUNCTION_3       3  ''
              346  STORE_NAME               _EllipticCurve

 L. 487       348  LOAD_CODE                <code_object get_elliptic_curves>
              350  LOAD_STR                 'get_elliptic_curves'
              352  MAKE_FUNCTION_0          'Neither defaults, keyword-only args, annotations, nor closures'
              354  STORE_NAME               get_elliptic_curves

 L. 502       356  LOAD_CODE                <code_object get_elliptic_curve>
              358  LOAD_STR                 'get_elliptic_curve'
              360  MAKE_FUNCTION_0          'Neither defaults, keyword-only args, annotations, nor closures'
              362  STORE_NAME               get_elliptic_curve

 L. 520       364  LOAD_BUILD_CLASS 
              366  LOAD_CODE                <code_object X509Name>
              368  LOAD_STR                 'X509Name'
              370  MAKE_FUNCTION_0          'Neither defaults, keyword-only args, annotations, nor closures'
              372  LOAD_STR                 'X509Name'
              374  LOAD_NAME                object
              376  CALL_FUNCTION_3       3  ''
              378  STORE_NAME               X509Name

 L. 720       380  LOAD_BUILD_CLASS 
              382  LOAD_CODE                <code_object X509Extension>
              384  LOAD_STR                 'X509Extension'
              386  MAKE_FUNCTION_0          'Neither defaults, keyword-only args, annotations, nor closures'
              388  LOAD_STR                 'X509Extension'
              390  LOAD_NAME                object
              392  CALL_FUNCTION_3       3  ''
              394  STORE_NAME               X509Extension

 L. 872       396  LOAD_BUILD_CLASS 
              398  LOAD_CODE                <code_object X509Req>
              400  LOAD_STR                 'X509Req'
              402  MAKE_FUNCTION_0          'Neither defaults, keyword-only args, annotations, nor closures'
              404  LOAD_STR                 'X509Req'
              406  LOAD_NAME                object
              408  CALL_FUNCTION_3       3  ''
              410  STORE_NAME               X509Req

 L.1083       412  LOAD_BUILD_CLASS 
              414  LOAD_CODE                <code_object X509>
              416  LOAD_STR                 'X509'
              418  MAKE_FUNCTION_0          'Neither defaults, keyword-only args, annotations, nor closures'
              420  LOAD_STR                 'X509'
              422  LOAD_NAME                object
              424  CALL_FUNCTION_3       3  ''
              426  STORE_NAME               X509

 L.1556       428  LOAD_BUILD_CLASS 
              430  LOAD_CODE                <code_object X509StoreFlags>
              432  LOAD_STR                 'X509StoreFlags'
              434  MAKE_FUNCTION_0          'Neither defaults, keyword-only args, annotations, nor closures'
              436  LOAD_STR                 'X509StoreFlags'
              438  LOAD_NAME                object
              440  CALL_FUNCTION_3       3  ''
              442  STORE_NAME               X509StoreFlags

 L.1580       444  LOAD_BUILD_CLASS 
              446  LOAD_CODE                <code_object X509Store>
              448  LOAD_STR                 'X509Store'
              450  MAKE_FUNCTION_0          'Neither defaults, keyword-only args, annotations, nor closures'
              452  LOAD_STR                 'X509Store'
              454  LOAD_NAME                object
              456  CALL_FUNCTION_3       3  ''
              458  STORE_NAME               X509Store

 L.1732       460  LOAD_BUILD_CLASS 
              462  LOAD_CODE                <code_object X509StoreContextError>
              464  LOAD_STR                 'X509StoreContextError'
              466  MAKE_FUNCTION_0          'Neither defaults, keyword-only args, annotations, nor closures'
              468  LOAD_STR                 'X509StoreContextError'
              470  LOAD_NAME                Exception
              472  CALL_FUNCTION_3       3  ''
              474  STORE_NAME               X509StoreContextError

 L.1746       476  LOAD_BUILD_CLASS 
              478  LOAD_CODE                <code_object X509StoreContext>
              480  LOAD_STR                 'X509StoreContext'
              482  MAKE_FUNCTION_0          'Neither defaults, keyword-only args, annotations, nor closures'
              484  LOAD_STR                 'X509StoreContext'
              486  LOAD_NAME                object
              488  CALL_FUNCTION_3       3  ''
              490  STORE_NAME               X509StoreContext

 L.1927       492  LOAD_CODE                <code_object load_certificate>
              494  LOAD_STR                 'load_certificate'
              496  MAKE_FUNCTION_0          'Neither defaults, keyword-only args, annotations, nor closures'
              498  STORE_NAME               load_certificate

 L.1956       500  LOAD_CODE                <code_object dump_certificate>
              502  LOAD_STR                 'dump_certificate'
              504  MAKE_FUNCTION_0          'Neither defaults, keyword-only args, annotations, nor closures'
              506  STORE_NAME               dump_certificate

 L.1984       508  LOAD_CODE                <code_object dump_publickey>
              510  LOAD_STR                 'dump_publickey'
              512  MAKE_FUNCTION_0          'Neither defaults, keyword-only args, annotations, nor closures'
              514  STORE_NAME               dump_publickey

 L.2009       516  LOAD_CONST               (None, None)
              518  LOAD_CODE                <code_object dump_privatekey>
              520  LOAD_STR                 'dump_privatekey'
              522  MAKE_FUNCTION_1          'default'
              524  STORE_NAME               dump_privatekey

 L.2073       526  LOAD_BUILD_CLASS 
              528  LOAD_CODE                <code_object Revoked>
              530  LOAD_STR                 'Revoked'
              532  MAKE_FUNCTION_0          'Neither defaults, keyword-only args, annotations, nor closures'
              534  LOAD_STR                 'Revoked'
              536  LOAD_NAME                object
              538  CALL_FUNCTION_3       3  ''
              540  STORE_NAME               Revoked

 L.2246       542  LOAD_BUILD_CLASS 
              544  LOAD_CODE                <code_object CRL>
              546  LOAD_STR                 'CRL'
              548  MAKE_FUNCTION_0          'Neither defaults, keyword-only args, annotations, nor closures'
              550  LOAD_STR                 'CRL'
              552  LOAD_NAME                object
              554  CALL_FUNCTION_3       3  ''
              556  STORE_NAME               CRL

 L.2467       558  LOAD_BUILD_CLASS 
              560  LOAD_CODE                <code_object PKCS7>
              562  LOAD_STR                 'PKCS7'
              564  MAKE_FUNCTION_0          'Neither defaults, keyword-only args, annotations, nor closures'
              566  LOAD_STR                 'PKCS7'
              568  LOAD_NAME                object
              570  CALL_FUNCTION_3       3  ''
              572  STORE_NAME               PKCS7

 L.2511       574  LOAD_BUILD_CLASS 
              576  LOAD_CODE                <code_object PKCS12>
              578  LOAD_STR                 'PKCS12'
              580  MAKE_FUNCTION_0          'Neither defaults, keyword-only args, annotations, nor closures'
              582  LOAD_STR                 'PKCS12'
              584  LOAD_NAME                object
              586  CALL_FUNCTION_3       3  ''
              588  STORE_NAME               PKCS12

 L.2692       590  LOAD_BUILD_CLASS 
              592  LOAD_CODE                <code_object NetscapeSPKI>
              594  LOAD_STR                 'NetscapeSPKI'
              596  MAKE_FUNCTION_0          'Neither defaults, keyword-only args, annotations, nor closures'
              598  LOAD_STR                 'NetscapeSPKI'
              600  LOAD_NAME                object
              602  CALL_FUNCTION_3       3  ''
              604  STORE_NAME               NetscapeSPKI

 L.2782       606  LOAD_BUILD_CLASS 
              608  LOAD_CODE                <code_object _PassphraseHelper>
              610  LOAD_STR                 '_PassphraseHelper'
              612  MAKE_FUNCTION_0          'Neither defaults, keyword-only args, annotations, nor closures'
              614  LOAD_STR                 '_PassphraseHelper'
              616  LOAD_NAME                object
              618  CALL_FUNCTION_3       3  ''
              620  STORE_NAME               _PassphraseHelper

 L.2852       622  LOAD_CODE                <code_object load_publickey>
              624  LOAD_STR                 'load_publickey'
              626  MAKE_FUNCTION_0          'Neither defaults, keyword-only args, annotations, nor closures'
              628  STORE_NAME               load_publickey

 L.2886       630  LOAD_CONST               (None,)
              632  LOAD_CODE                <code_object load_privatekey>
              634  LOAD_STR                 'load_privatekey'
              636  MAKE_FUNCTION_1          'default'
              638  STORE_NAME               load_privatekey

 L.2923       640  LOAD_CODE                <code_object dump_certificate_request>
              642  LOAD_STR                 'dump_certificate_request'
              644  MAKE_FUNCTION_0          'Neither defaults, keyword-only args, annotations, nor closures'
              646  STORE_NAME               dump_certificate_request

 L.2951       648  LOAD_CODE                <code_object load_certificate_request>
              650  LOAD_STR                 'load_certificate_request'
              652  MAKE_FUNCTION_0          'Neither defaults, keyword-only args, annotations, nor closures'
              654  STORE_NAME               load_certificate_request

 L.2979       656  LOAD_CODE                <code_object sign>
              658  LOAD_STR                 'sign'
              660  MAKE_FUNCTION_0          'Neither defaults, keyword-only args, annotations, nor closures'
              662  STORE_NAME               sign

 L.3014       664  LOAD_CODE                <code_object verify>
              666  LOAD_STR                 'verify'
              668  MAKE_FUNCTION_0          'Neither defaults, keyword-only args, annotations, nor closures'
              670  STORE_NAME               verify

 L.3050       672  LOAD_CODE                <code_object dump_crl>
              674  LOAD_STR                 'dump_crl'
              676  MAKE_FUNCTION_0          'Neither defaults, keyword-only args, annotations, nor closures'
              678  STORE_NAME               dump_crl

 L.3079       680  LOAD_CODE                <code_object load_crl>
              682  LOAD_STR                 'load_crl'
              684  MAKE_FUNCTION_0          'Neither defaults, keyword-only args, annotations, nor closures'
              686  STORE_NAME               load_crl

 L.3109       688  LOAD_CODE                <code_object load_pkcs7_data>
              690  LOAD_STR                 'load_pkcs7_data'
              692  MAKE_FUNCTION_0          'Neither defaults, keyword-only args, annotations, nor closures'
              694  STORE_NAME               load_pkcs7_data

 L.3138       696  LOAD_NAME                utils
              698  LOAD_METHOD              deprecated

 L.3139       700  LOAD_NAME                load_pkcs7_data

 L.3140       702  LOAD_NAME                __name__

 L.3142       704  LOAD_STR                 'PKCS#7 support in pyOpenSSL is deprecated. You should use the APIs in cryptography.'

 L.3145       706  LOAD_NAME                DeprecationWarning

 L.3138       708  CALL_METHOD_4         4  ''
              710  STORE_NAME               load_pkcs7_data

 L.3149       712  LOAD_CONST               (None,)
              714  LOAD_CODE                <code_object load_pkcs12>
              716  LOAD_STR                 'load_pkcs12'
              718  MAKE_FUNCTION_1          'default'
              720  STORE_NAME               load_pkcs12

 L.3236       722  LOAD_NAME                utils
              724  LOAD_METHOD              deprecated

 L.3237       726  LOAD_NAME                load_pkcs12

 L.3238       728  LOAD_NAME                __name__

 L.3240       730  LOAD_STR                 'PKCS#12 support in pyOpenSSL is deprecated. You should use the APIs in cryptography.'

 L.3243       732  LOAD_NAME                DeprecationWarning

 L.3236       734  CALL_METHOD_4         4  ''
              736  STORE_NAME               load_pkcs12

 L.3256       738  LOAD_NAME                _lib
              740  LOAD_METHOD              OpenSSL_add_all_algorithms
              742  CALL_METHOD_0         0  ''
              744  POP_TOP          

 L.3260       746  LOAD_NAME                _lib
              748  LOAD_METHOD              SSL_load_error_strings
              750  CALL_METHOD_0         0  ''
              752  POP_TOP          

 L.3265       754  LOAD_NAME                _lib
              756  LOAD_METHOD              ASN1_STRING_set_default_mask_asc
              758  LOAD_CONST               b'utf8only'
              760  CALL_METHOD_1         1  ''
              762  POP_TOP          

Parse error at or near `BUILD_LIST_0' instruction at offset 168

Instruction context:
-> 
 L.  29       168  BUILD_LIST_0          0 
                 170  LOAD_CONST               ('FILETYPE_PEM', 'FILETYPE_ASN1', 'FILETYPE_TEXT', 'TYPE_RSA', 'TYPE_DSA', 'Error', 'PKey', 'get_elliptic_curves', 'get_elliptic_curve', 'X509Name', 'X509Extension', 'X509Req', 'X509', 'X509StoreFlags', 'X509Store', 'X509StoreContextError', 'X509StoreContext', 'load_certificate', 'dump_certificate', 'dump_publickey', 'dump_privatekey', 'Revoked', 'CRL', 'PKCS7', 'PKCS12', 'NetscapeSPKI', 'load_publickey', 'load_privatekey', 'dump_certificate_request', 'load_certificate_request', 'sign', 'verify', 'dump_crl', 'load_crl', 'load_pkcs7_data', 'load_pkcs12')
                 172  CALL_FINALLY        175  'to 175'
                 174  STORE_NAME               __all__

test/103984.pyc -- 
# decompile failed
