Instruction context:
   
 L. 141         8  LOAD_STR                 '\n'
                  10  LOAD_FAST                'repr_str'
->                12  <118>                 0  ''
                  14  POP_JUMP_IF_FALSE    24  'to 24'
Instruction context:
   
 L. 151         8  LOAD_STR                 '\n'
                  10  LOAD_FAST                'repr_str'
->                12  <118>                 0  ''
                  14  POP_JUMP_IF_FALSE    24  'to 24'
Instruction context:
   
 L. 196        38  DUP_TOP          
                  40  LOAD_GLOBAL              NameError
->                42  <121>                54  ''
                  44  POP_TOP          
                  46  POP_TOP          
                  48  POP_TOP          
Instruction context:
   
 L. 373        88  LOAD_FAST                'input'
                  90  LOAD_CONST               None
->                92  <117>                 1  ''
                  94  POP_JUMP_IF_FALSE   106  'to 106'
Instruction context:
   
 L. 717        78  LOAD_FAST                'input'
                  80  LOAD_CONST               None
->                82  <117>                 1  ''
                  84  POP_JUMP_IF_FALSE    96  'to 96'
Instruction context:
   
 L.1023        78  LOAD_FAST                'input'
                  80  LOAD_CONST               None
->                82  <117>                 1  ''
                  84  POP_JUMP_IF_FALSE    96  'to 96'
Instruction context:
   
 L.1328        80  LOAD_FAST                's'
                  82  LOAD_FAST                'self'
                  84  LOAD_ATTR                usyms
->                86  <118>                 1  ''
                  88  POP_JUMP_IF_FALSE_BACK    76  'to 76'
Instruction context:
   
 L.1364        54  DUP_TOP          
                  56  LOAD_GLOBAL              IndexError
                  58  LOAD_GLOBAL              KeyError
                  60  BUILD_TUPLE_2         2 
->                62  <121>                80  ''
                  64  POP_TOP          
                  66  POP_TOP          
                  68  POP_TOP          
Instruction context:
   
 L.1457        20  LOAD_FAST                'symbols'
                  22  LOAD_FAST                'i'
                  24  BINARY_SUBSCR    
                  26  LOAD_FAST                'terminals'
->                28  <118>                 0  ''
                  30  POP_JUMP_IF_FALSE    40  'to 40'
Instruction context:
   
 L.1636        16  LOAD_FAST                'start'
                  18  LOAD_FAST                'self'
                  20  LOAD_ATTR                Nonterminals
->                22  <118>                 1  ''
                  24  POP_JUMP_IF_FALSE    38  'to 38'

test/111987.pyc -- 
# decompile failed

# file test/111987.pyc
# --- This code section failed: ---

 L.1662         0  BUILD_LIST_0          0 
                2  LOAD_FAST                '.0'
              4_0  COME_FROM            20  '20'
              4_1  COME_FROM            14  '14'
                4  FOR_ITER             22  'to 22'
                6  STORE_FAST               's'
                8  LOAD_FAST                's'
               10  LOAD_DEREF               'reachable'
               12  <118>                 1  ''
               14  POP_JUMP_IF_FALSE_BACK     4  'to 4'
               16  LOAD_FAST                's'
               18  LIST_APPEND           2  ''
               20  JUMP_BACK             4  'to 4'
             22_0  COME_FROM             4  '4'
               22  RETURN_VALUE     
               -1  RETURN_LAST      

Parse error at or near `None' instruction at offset -1

