
# file test/115891.pyc
# --- This code section failed: ---

 L.   2         0  LOAD_STR                 '\nPackage resource API\n--------------------\n\nA resource is a logical file contained within a package, or a logical\nsubdirectory thereof.  The package resource API expects resource names\nto have their path parts separated with ``/``, *not* whatever the local\npath separator is.  Do not use os.path operations to manipulate resource\nnames being passed into the API.\n\nThe package resource API is designed to work with normal filesystem packages,\n.egg files, and unpacked .egg files.  It can also work in a limited way with\n.zip files and with custom PEP 302 loaders that support the ``get_data()``\nmethod.\n'
                2  STORE_NAME               __doc__

 L.  18         4  LOAD_CONST               0
                6  LOAD_CONST               ('absolute_import',)
                8  IMPORT_NAME              __future__
               10  IMPORT_FROM              absolute_import
               12  STORE_NAME               absolute_import
               14  POP_TOP          

 L.  20        16  LOAD_CONST               0
               18  LOAD_CONST               None
               20  IMPORT_NAME              sys
               22  STORE_NAME               sys

 L.  21        24  LOAD_CONST               0
               26  LOAD_CONST               None
               28  IMPORT_NAME              os
               30  STORE_NAME               os

 L.  22        32  LOAD_CONST               0
               34  LOAD_CONST               None
               36  IMPORT_NAME              io
               38  STORE_NAME               io

 L.  23        40  LOAD_CONST               0
               42  LOAD_CONST               None
               44  IMPORT_NAME              time
               46  STORE_NAME               time

 L.  24        48  LOAD_CONST               0
               50  LOAD_CONST               None
               52  IMPORT_NAME              re
               54  STORE_NAME               re

 L.  25        56  LOAD_CONST               0
               58  LOAD_CONST               None
               60  IMPORT_NAME              types
               62  STORE_NAME               types

 L.  26        64  LOAD_CONST               0
               66  LOAD_CONST               None
               68  IMPORT_NAME              zipfile
               70  STORE_NAME               zipfile

 L.  27        72  LOAD_CONST               0
               74  LOAD_CONST               None
               76  IMPORT_NAME              zipimport
               78  STORE_NAME               zipimport

 L.  28        80  LOAD_CONST               0
               82  LOAD_CONST               None
               84  IMPORT_NAME              warnings
               86  STORE_NAME               warnings

 L.  29        88  LOAD_CONST               0
               90  LOAD_CONST               None
               92  IMPORT_NAME              stat
               94  STORE_NAME               stat

 L.  30        96  LOAD_CONST               0
               98  LOAD_CONST               None
              100  IMPORT_NAME              functools
              102  STORE_NAME               functools

 L.  31       104  LOAD_CONST               0
              106  LOAD_CONST               None
              108  IMPORT_NAME              pkgutil
              110  STORE_NAME               pkgutil

 L.  32       112  LOAD_CONST               0
              114  LOAD_CONST               None
              116  IMPORT_NAME              operator
              118  STORE_NAME               operator

 L.  33       120  LOAD_CONST               0
              122  LOAD_CONST               None
              124  IMPORT_NAME              platform
              126  STORE_NAME               platform

 L.  34       128  LOAD_CONST               0
              130  LOAD_CONST               None
              132  IMPORT_NAME              collections
              134  STORE_NAME               collections

 L.  35       136  LOAD_CONST               0
              138  LOAD_CONST               None
              140  IMPORT_NAME              plistlib
              142  STORE_NAME               plistlib

 L.  36       144  LOAD_CONST               0
              146  LOAD_CONST               None
              148  IMPORT_NAME_ATTR         email.parser
              150  STORE_NAME               email

 L.  37       152  LOAD_CONST               0
              154  LOAD_CONST               None
              156  IMPORT_NAME              errno
              158  STORE_NAME               errno

 L.  38       160  LOAD_CONST               0
              162  LOAD_CONST               None
              164  IMPORT_NAME              tempfile
              166  STORE_NAME               tempfile

 L.  39       168  LOAD_CONST               0
              170  LOAD_CONST               None
              172  IMPORT_NAME              textwrap
              174  STORE_NAME               textwrap

 L.  40       176  LOAD_CONST               0
              178  LOAD_CONST               None
              180  IMPORT_NAME              itertools
              182  STORE_NAME               itertools

 L.  41       184  LOAD_CONST               0
              186  LOAD_CONST               None
              188  IMPORT_NAME              inspect
              190  STORE_NAME               inspect

 L.  42       192  LOAD_CONST               0
              194  LOAD_CONST               None
              196  IMPORT_NAME              ntpath
              198  STORE_NAME               ntpath

 L.  43       200  LOAD_CONST               0
              202  LOAD_CONST               None
              204  IMPORT_NAME              posixpath
              206  STORE_NAME               posixpath

 L.  44       208  LOAD_CONST               0
              210  LOAD_CONST               ('get_importer',)
              212  IMPORT_NAME              pkgutil
              214  IMPORT_FROM              get_importer
              216  STORE_NAME               get_importer
              218  POP_TOP          

 L.  46       220  SETUP_FINALLY       234  'to 234'

 L.  47       222  LOAD_CONST               0
              224  LOAD_CONST               None
              226  IMPORT_NAME              _imp
              228  STORE_NAME               _imp
              230  POP_BLOCK        
              232  JUMP_FORWARD        262  'to 262'
            234_0  COME_FROM_FINALLY   220  '220'

 L.  48       234  DUP_TOP          
              236  LOAD_NAME                ImportError
          238_240  <121>               260  ''
              242  POP_TOP          
              244  POP_TOP          
              246  POP_TOP          

 L.  50       248  LOAD_CONST               0
              250  LOAD_CONST               None
              252  IMPORT_NAME              imp
              254  STORE_NAME               _imp
              256  POP_EXCEPT       
              258  JUMP_FORWARD        262  'to 262'
              260  <48>             
            262_0  COME_FROM           258  '258'
            262_1  COME_FROM           232  '232'

 L.  52       262  SETUP_FINALLY       272  'to 272'

 L.  53       264  LOAD_NAME                FileExistsError
              266  POP_TOP          
              268  POP_BLOCK        
              270  JUMP_FORWARD        296  'to 296'
            272_0  COME_FROM_FINALLY   262  '262'

 L.  54       272  DUP_TOP          
              274  LOAD_NAME                NameError
          276_278  <121>               294  ''
              280  POP_TOP          
              282  POP_TOP          
              284  POP_TOP          

 L.  55       286  LOAD_NAME                OSError
              288  STORE_NAME               FileExistsError
              290  POP_EXCEPT       
              292  JUMP_FORWARD        296  'to 296'
              294  <48>             
            296_0  COME_FROM           292  '292'
            296_1  COME_FROM           270  '270'

 L.  57       296  LOAD_CONST               0
              298  LOAD_CONST               ('six',)
              300  IMPORT_NAME_ATTR         pkg_resources.extern
              302  IMPORT_FROM              six
              304  STORE_NAME               six
              306  POP_TOP          

 L.  58       308  LOAD_CONST               0
              310  LOAD_CONST               ('map', 'filter')
              312  IMPORT_NAME_ATTR         pkg_resources.extern.six.moves
              314  IMPORT_FROM              map
              316  STORE_NAME               map
              318  IMPORT_FROM              filter
              320  STORE_NAME               filter
              322  POP_TOP          

 L.  61       324  LOAD_CONST               0
              326  LOAD_CONST               ('utime',)
              328  IMPORT_NAME              os
              330  IMPORT_FROM              utime
              332  STORE_NAME               utime
              334  POP_TOP          

 L.  62       336  SETUP_FINALLY       366  'to 366'

 L.  63       338  LOAD_CONST               0
              340  LOAD_CONST               ('mkdir', 'rename', 'unlink')
              342  IMPORT_NAME              os
              344  IMPORT_FROM              mkdir
              346  STORE_NAME               mkdir
              348  IMPORT_FROM              rename
              350  STORE_NAME               rename
              352  IMPORT_FROM              unlink
              354  STORE_NAME               unlink
              356  POP_TOP          

 L.  64       358  LOAD_CONST               True
              360  STORE_NAME               WRITE_SUPPORT
              362  POP_BLOCK        
              364  JUMP_FORWARD        390  'to 390'
            366_0  COME_FROM_FINALLY   336  '336'

 L.  65       366  DUP_TOP          
              368  LOAD_NAME                ImportError
          370_372  <121>               388  ''
              374  POP_TOP          
              376  POP_TOP          
              378  POP_TOP          

 L.  67       380  LOAD_CONST               False
              382  STORE_NAME               WRITE_SUPPORT
              384  POP_EXCEPT       
              386  JUMP_FORWARD        390  'to 390'
              388  <48>             
            390_0  COME_FROM           386  '386'
            390_1  COME_FROM           364  '364'

 L.  69       390  LOAD_CONST               0
              392  LOAD_CONST               ('open',)
              394  IMPORT_NAME              os
              396  IMPORT_FROM              open
              398  STORE_NAME               os_open
              400  POP_TOP          

 L.  70       402  LOAD_CONST               0
              404  LOAD_CONST               ('isdir', 'split')
              406  IMPORT_NAME_ATTR         os.path
              408  IMPORT_FROM              isdir
              410  STORE_NAME               isdir
              412  IMPORT_FROM              split
              414  STORE_NAME               split
              416  POP_TOP          

 L.  72       418  SETUP_FINALLY       442  'to 442'

 L.  73       420  LOAD_CONST               0
              422  LOAD_CONST               None
              424  IMPORT_NAME_ATTR         importlib.machinery
              426  IMPORT_FROM              machinery
              428  STORE_NAME               importlib_machinery
              430  POP_TOP          

 L.  75       432  LOAD_NAME                importlib_machinery
              434  LOAD_ATTR                __name__
              436  POP_TOP          
              438  POP_BLOCK        
              440  JUMP_FORWARD        466  'to 466'
            442_0  COME_FROM_FINALLY   418  '418'

 L.  76       442  DUP_TOP          
              444  LOAD_NAME                ImportError
          446_448  <121>               464  ''
              450  POP_TOP          
              452  POP_TOP          
              454  POP_TOP          

 L.  77       456  LOAD_CONST               None
              458  STORE_NAME               importlib_machinery
              460  POP_EXCEPT       
              462  JUMP_FORWARD        466  'to 466'
              464  <48>             
            466_0  COME_FROM           462  '462'
            466_1  COME_FROM           440  '440'

 L.  79       466  LOAD_CONST               0
              468  LOAD_CONST               ('appdirs',)
              470  IMPORT_NAME_ATTR         pkg_resources.extern
              472  IMPORT_FROM              appdirs
              474  STORE_NAME               appdirs
              476  POP_TOP          

 L.  80       478  LOAD_CONST               0
              480  LOAD_CONST               ('packaging',)
              482  IMPORT_NAME_ATTR         pkg_resources.extern
              484  IMPORT_FROM              packaging
              486  STORE_NAME               packaging
              488  POP_TOP          

 L.  81       490  LOAD_NAME                __import__
              492  LOAD_STR                 'pkg_resources.extern.packaging.version'
              494  CALL_FUNCTION_1       1  ''
              496  POP_TOP          

 L.  82       498  LOAD_NAME                __import__
              500  LOAD_STR                 'pkg_resources.extern.packaging.specifiers'
              502  CALL_FUNCTION_1       1  ''
              504  POP_TOP          

 L.  83       506  LOAD_NAME                __import__
              508  LOAD_STR                 'pkg_resources.extern.packaging.requirements'
              510  CALL_FUNCTION_1       1  ''
              512  POP_TOP          

 L.  84       514  LOAD_NAME                __import__
              516  LOAD_STR                 'pkg_resources.extern.packaging.markers'
              518  CALL_FUNCTION_1       1  ''
              520  POP_TOP          

 L.  87       522  LOAD_NAME                type
              524  STORE_NAME               __metaclass__

 L.  90       526  LOAD_CONST               (3, 0)
              528  LOAD_NAME                sys
              530  LOAD_ATTR                version_info
              532  DUP_TOP          
              534  ROT_THREE        
              536  COMPARE_OP               <
          538_540  POP_JUMP_IF_FALSE   552  'to 552'
              542  LOAD_CONST               (3, 5)
              544  COMPARE_OP               <
          546_548  POP_JUMP_IF_FALSE   564  'to 564'
              550  JUMP_FORWARD        556  'to 556'
            552_0  COME_FROM           538  '538'
              552  POP_TOP          
              554  JUMP_FORWARD        564  'to 564'
            556_0  COME_FROM           550  '550'

 L.  91       556  LOAD_NAME                RuntimeError
              558  LOAD_STR                 'Python 3.5 or later is required'
              560  CALL_FUNCTION_1       1  ''
              562  RAISE_VARARGS_1       1  'exception instance'
            564_0  COME_FROM           554  '554'
            564_1  COME_FROM           546  '546'

 L.  93       564  LOAD_NAME                six
              566  LOAD_ATTR                PY2
          568_570  POP_JUMP_IF_FALSE   580  'to 580'

 L.  95       572  LOAD_CONST               None
              574  STORE_NAME               PermissionError

 L.  96       576  LOAD_CONST               None
              578  STORE_NAME               NotADirectoryError
            580_0  COME_FROM           568  '568'

 L. 100       580  LOAD_CONST               None
              582  STORE_NAME               require

 L. 101       584  LOAD_CONST               None
              586  STORE_NAME               working_set

 L. 102       588  LOAD_CONST               None
              590  STORE_NAME               add_activation_listener

 L. 103       592  LOAD_CONST               None
              594  STORE_NAME               resources_stream

 L. 104       596  LOAD_CONST               None
              598  STORE_NAME               cleanup_resources

 L. 105       600  LOAD_CONST               None
              602  STORE_NAME               resource_dir

 L. 106       604  LOAD_CONST               None
              606  STORE_NAME               resource_stream

 L. 107       608  LOAD_CONST               None
              610  STORE_NAME               set_extraction_path

 L. 108       612  LOAD_CONST               None
              614  STORE_NAME               resource_isdir

 L. 109       616  LOAD_CONST               None
              618  STORE_NAME               resource_string

 L. 110       620  LOAD_CONST               None
              622  STORE_NAME               iter_entry_points

 L. 111       624  LOAD_CONST               None
              626  STORE_NAME               resource_listdir

 L. 112       628  LOAD_CONST               None
              630  STORE_NAME               resource_filename

 L. 113       632  LOAD_CONST               None
              634  STORE_NAME               resource_exists

 L. 114       636  LOAD_CONST               None
              638  STORE_NAME               _distribution_finders

 L. 115       640  LOAD_CONST               None
              642  STORE_NAME               _namespace_handlers

 L. 116       644  LOAD_CONST               None
              646  STORE_NAME               _namespace_packages

 L. 119       648  LOAD_BUILD_CLASS 
              650  LOAD_CODE                <code_object PEP440Warning>
              652  LOAD_STR                 'PEP440Warning'
              654  MAKE_FUNCTION_0          'Neither defaults, keyword-only args, annotations, nor closures'
              656  LOAD_STR                 'PEP440Warning'
              658  LOAD_NAME                RuntimeWarning
              660  CALL_FUNCTION_3       3  ''
              662  STORE_NAME               PEP440Warning

 L. 126       664  LOAD_CODE                <code_object parse_version>
              666  LOAD_STR                 'parse_version'
              668  MAKE_FUNCTION_0          'Neither defaults, keyword-only args, annotations, nor closures'
              670  STORE_NAME               parse_version

 L. 133       672  BUILD_MAP_0           0 
              674  STORE_NAME               _state_vars

 L. 136       676  LOAD_CODE                <code_object _declare_state>
              678  LOAD_STR                 '_declare_state'
              680  MAKE_FUNCTION_0          'Neither defaults, keyword-only args, annotations, nor closures'
              682  STORE_NAME               _declare_state

 L. 141       684  LOAD_CODE                <code_object __getstate__>
              686  LOAD_STR                 '__getstate__'
              688  MAKE_FUNCTION_0          'Neither defaults, keyword-only args, annotations, nor closures'
              690  STORE_NAME               __getstate__

 L. 149       692  LOAD_CODE                <code_object __setstate__>
              694  LOAD_STR                 '__setstate__'
              696  MAKE_FUNCTION_0          'Neither defaults, keyword-only args, annotations, nor closures'
              698  STORE_NAME               __setstate__

 L. 156       700  LOAD_CODE                <code_object _sget_dict>
              702  LOAD_STR                 '_sget_dict'
              704  MAKE_FUNCTION_0          'Neither defaults, keyword-only args, annotations, nor closures'
              706  STORE_NAME               _sget_dict

 L. 160       708  LOAD_CODE                <code_object _sset_dict>
              710  LOAD_STR                 '_sset_dict'
              712  MAKE_FUNCTION_0          'Neither defaults, keyword-only args, annotations, nor closures'
              714  STORE_NAME               _sset_dict

 L. 165       716  LOAD_CODE                <code_object _sget_object>
              718  LOAD_STR                 '_sget_object'
              720  MAKE_FUNCTION_0          'Neither defaults, keyword-only args, annotations, nor closures'
              722  STORE_NAME               _sget_object

 L. 169       724  LOAD_CODE                <code_object _sset_object>
              726  LOAD_STR                 '_sset_object'
              728  MAKE_FUNCTION_0          'Neither defaults, keyword-only args, annotations, nor closures'
              730  STORE_NAME               _sset_object

 L. 173       732  LOAD_LAMBDA              '<code_object <lambda>>'
              734  LOAD_STR                 '<lambda>'
              736  MAKE_FUNCTION_0          'Neither defaults, keyword-only args, annotations, nor closures'
              738  DUP_TOP          
              740  STORE_NAME               _sget_none
              742  STORE_NAME               _sset_none

 L. 176       744  LOAD_CODE                <code_object get_supported_platform>
              746  LOAD_STR                 'get_supported_platform'
              748  MAKE_FUNCTION_0          'Neither defaults, keyword-only args, annotations, nor closures'
              750  STORE_NAME               get_supported_platform

 L. 200       752  BUILD_LIST_0          0 
              754  LOAD_CONST               ('require', 'run_script', 'get_provider', 'get_distribution', 'load_entry_point', 'get_entry_map', 'get_entry_info', 'iter_entry_points', 'resource_string', 'resource_stream', 'resource_filename', 'resource_listdir', 'resource_exists', 'resource_isdir', 'declare_namespace', 'working_set', 'add_activation_listener', 'find_distributions', 'set_extraction_path', 'cleanup_resources', 'get_default_cache', 'Environment', 'WorkingSet', 'ResourceManager', 'Distribution', 'Requirement', 'EntryPoint', 'ResolutionError', 'VersionConflict', 'DistributionNotFound', 'UnknownExtra', 'ExtractionError', 'PEP440Warning', 'parse_requirements', 'parse_version', 'safe_name', 'safe_version', 'get_platform', 'compatible_platforms', 'yield_lines', 'split_sections', 'safe_extra', 'to_filename', 'invalid_marker', 'evaluate_marker', 'ensure_directory', 'normalize_path', 'EGG_DIST', 'BINARY_DIST', 'SOURCE_DIST', 'CHECKOUT_DIST', 'DEVELOP_DIST', 'IMetadataProvider', 'IResourceProvider', 'FileMetadata', 'PathMetadata', 'EggMetadata', 'EmptyProvider', 'empty_provider', 'NullProvider', 'EggProvider', 'DefaultProvider', 'ZipProvider', 'register_finder', 'register_namespace_handler', 'register_loader_type', 'fixup_namespace_packages', 'get_importer', 'PkgResourcesDeprecationWarning', 'run_main', 'AvailableDistributions')
              756  CALL_FINALLY        759  'to 759'
              758  STORE_NAME               __all__

 L. 250       760  LOAD_BUILD_CLASS 
              762  LOAD_CODE                <code_object ResolutionError>
              764  LOAD_STR                 'ResolutionError'
              766  MAKE_FUNCTION_0          'Neither defaults, keyword-only args, annotations, nor closures'
              768  LOAD_STR                 'ResolutionError'
              770  LOAD_NAME                Exception
              772  CALL_FUNCTION_3       3  ''
              774  STORE_NAME               ResolutionError

 L. 257       776  LOAD_BUILD_CLASS 
              778  LOAD_CODE                <code_object VersionConflict>
              780  LOAD_STR                 'VersionConflict'
              782  MAKE_FUNCTION_0          'Neither defaults, keyword-only args, annotations, nor closures'
              784  LOAD_STR                 'VersionConflict'
              786  LOAD_NAME                ResolutionError
              788  CALL_FUNCTION_3       3  ''
              790  STORE_NAME               VersionConflict

 L. 289       792  LOAD_BUILD_CLASS 
              794  LOAD_CODE                <code_object ContextualVersionConflict>
              796  LOAD_STR                 'ContextualVersionConflict'
              798  MAKE_FUNCTION_0          'Neither defaults, keyword-only args, annotations, nor closures'
              800  LOAD_STR                 'ContextualVersionConflict'
              802  LOAD_NAME                VersionConflict
              804  CALL_FUNCTION_3       3  ''
              806  STORE_NAME               ContextualVersionConflict

 L. 302       808  LOAD_BUILD_CLASS 
              810  LOAD_CODE                <code_object DistributionNotFound>
              812  LOAD_STR                 'DistributionNotFound'
              814  MAKE_FUNCTION_0          'Neither defaults, keyword-only args, annotations, nor closures'
              816  LOAD_STR                 'DistributionNotFound'
              818  LOAD_NAME                ResolutionError
              820  CALL_FUNCTION_3       3  ''
              822  STORE_NAME               DistributionNotFound

 L. 329       824  LOAD_BUILD_CLASS 
              826  LOAD_CODE                <code_object UnknownExtra>
              828  LOAD_STR                 'UnknownExtra'
              830  MAKE_FUNCTION_0          'Neither defaults, keyword-only args, annotations, nor closures'
              832  LOAD_STR                 'UnknownExtra'
              834  LOAD_NAME                ResolutionError
              836  CALL_FUNCTION_3       3  ''
              838  STORE_NAME               UnknownExtra

 L. 333       840  BUILD_MAP_0           0 
              842  STORE_NAME               _provider_factories

 L. 335       844  LOAD_STR                 '{}.{}'
              846  LOAD_ATTR                format
              848  LOAD_NAME                sys
              850  LOAD_ATTR                version_info
              852  CALL_FUNCTION_EX      0  'positional arguments only'
              854  STORE_NAME               PY_MAJOR

 L. 336       856  LOAD_CONST               3
              858  STORE_NAME               EGG_DIST

 L. 337       860  LOAD_CONST               2
              862  STORE_NAME               BINARY_DIST

 L. 338       864  LOAD_CONST               1
              866  STORE_NAME               SOURCE_DIST

 L. 339       868  LOAD_CONST               0
              870  STORE_NAME               CHECKOUT_DIST

 L. 340       872  LOAD_CONST               -1
              874  STORE_NAME               DEVELOP_DIST

 L. 343       876  LOAD_CODE                <code_object register_loader_type>
              878  LOAD_STR                 'register_loader_type'
              880  MAKE_FUNCTION_0          'Neither defaults, keyword-only args, annotations, nor closures'
              882  STORE_NAME               register_loader_type

 L. 353       884  LOAD_CODE                <code_object get_provider>
              886  LOAD_STR                 'get_provider'
              888  MAKE_FUNCTION_0          'Neither defaults, keyword-only args, annotations, nor closures'
              890  STORE_NAME               get_provider

 L. 366       892  BUILD_LIST_0          0 
              894  BUILD_TUPLE_1         1 
              896  LOAD_CODE                <code_object _macos_vers>
              898  LOAD_STR                 '_macos_vers'
              900  MAKE_FUNCTION_1          'default'
              902  STORE_NAME               _macos_vers

 L. 382       904  LOAD_CODE                <code_object _macos_arch>
              906  LOAD_STR                 '_macos_arch'
              908  MAKE_FUNCTION_0          'Neither defaults, keyword-only args, annotations, nor closures'
              910  STORE_NAME               _macos_arch

 L. 386       912  LOAD_CODE                <code_object get_build_platform>
              914  LOAD_STR                 'get_build_platform'
              916  MAKE_FUNCTION_0          'Neither defaults, keyword-only args, annotations, nor closures'
              918  STORE_NAME               get_build_platform

 L. 410       920  LOAD_NAME                re
              922  LOAD_METHOD              compile
              924  LOAD_STR                 'macosx-(\\d+)\\.(\\d+)-(.*)'
              926  CALL_METHOD_1         1  ''
              928  STORE_NAME               macosVersionString

 L. 411       930  LOAD_NAME                re
              932  LOAD_METHOD              compile
              934  LOAD_STR                 'darwin-(\\d+)\\.(\\d+)\\.(\\d+)-(.*)'
              936  CALL_METHOD_1         1  ''
              938  STORE_NAME               darwinVersionString

 L. 413       940  LOAD_NAME                get_build_platform
              942  STORE_NAME               get_platform

 L. 416       944  LOAD_CODE                <code_object compatible_platforms>
              946  LOAD_STR                 'compatible_platforms'
              948  MAKE_FUNCTION_0          'Neither defaults, keyword-only args, annotations, nor closures'
              950  STORE_NAME               compatible_platforms

 L. 462       952  LOAD_CODE                <code_object run_script>
              954  LOAD_STR                 'run_script'
              956  MAKE_FUNCTION_0          'Neither defaults, keyword-only args, annotations, nor closures'
              958  STORE_NAME               run_script

 L. 472       960  LOAD_NAME                run_script
              962  STORE_NAME               run_main

 L. 475       964  LOAD_CODE                <code_object get_distribution>
              966  LOAD_STR                 'get_distribution'
              968  MAKE_FUNCTION_0          'Neither defaults, keyword-only args, annotations, nor closures'
              970  STORE_NAME               get_distribution

 L. 486       972  LOAD_CODE                <code_object load_entry_point>
              974  LOAD_STR                 'load_entry_point'
              976  MAKE_FUNCTION_0          'Neither defaults, keyword-only args, annotations, nor closures'
              978  STORE_NAME               load_entry_point

 L. 491       980  LOAD_CONST               (None,)
              982  LOAD_CODE                <code_object get_entry_map>
              984  LOAD_STR                 'get_entry_map'
              986  MAKE_FUNCTION_1          'default'
              988  STORE_NAME               get_entry_map

 L. 496       990  LOAD_CODE                <code_object get_entry_info>
              992  LOAD_STR                 'get_entry_info'
              994  MAKE_FUNCTION_0          'Neither defaults, keyword-only args, annotations, nor closures'
              996  STORE_NAME               get_entry_info

 L. 501       998  LOAD_BUILD_CLASS 
             1000  LOAD_CODE                <code_object IMetadataProvider>
             1002  LOAD_STR                 'IMetadataProvider'
             1004  MAKE_FUNCTION_0          'Neither defaults, keyword-only args, annotations, nor closures'
             1006  LOAD_STR                 'IMetadataProvider'
             1008  CALL_FUNCTION_2       2  ''
             1010  STORE_NAME               IMetadataProvider

 L. 524      1012  LOAD_BUILD_CLASS 
             1014  LOAD_CODE                <code_object IResourceProvider>
             1016  LOAD_STR                 'IResourceProvider'
             1018  MAKE_FUNCTION_0          'Neither defaults, keyword-only args, annotations, nor closures'
             1020  LOAD_STR                 'IResourceProvider'
             1022  LOAD_NAME                IMetadataProvider
             1024  CALL_FUNCTION_3       3  ''
             1026  STORE_NAME               IResourceProvider

 L. 552      1028  LOAD_BUILD_CLASS 
             1030  LOAD_CODE                <code_object WorkingSet>
             1032  LOAD_STR                 'WorkingSet'
             1034  MAKE_FUNCTION_0          'Neither defaults, keyword-only args, annotations, nor closures'
             1036  LOAD_STR                 'WorkingSet'
             1038  CALL_FUNCTION_2       2  ''
             1040  STORE_NAME               WorkingSet

 L. 938      1042  LOAD_BUILD_CLASS 
             1044  LOAD_CODE                <code_object _ReqExtras>
             1046  LOAD_STR                 '_ReqExtras'
             1048  MAKE_FUNCTION_0          'Neither defaults, keyword-only args, annotations, nor closures'
             1050  LOAD_STR                 '_ReqExtras'
             1052  LOAD_NAME                dict
             1054  CALL_FUNCTION_3       3  ''
             1056  STORE_NAME               _ReqExtras

 L. 958      1058  LOAD_BUILD_CLASS 
             1060  LOAD_CODE                <code_object Environment>
             1062  LOAD_STR                 'Environment'
             1064  MAKE_FUNCTION_0          'Neither defaults, keyword-only args, annotations, nor closures'
             1066  LOAD_STR                 'Environment'
             1068  CALL_FUNCTION_2       2  ''
             1070  STORE_NAME               Environment

 L.1105      1072  LOAD_NAME                Environment
             1074  STORE_NAME               AvailableDistributions

 L.1108      1076  LOAD_BUILD_CLASS 
             1078  LOAD_CODE                <code_object ExtractionError>
             1080  LOAD_STR                 'ExtractionError'
             1082  MAKE_FUNCTION_0          'Neither defaults, keyword-only args, annotations, nor closures'
             1084  LOAD_STR                 'ExtractionError'
             1086  LOAD_NAME                RuntimeError
             1088  CALL_FUNCTION_3       3  ''
             1090  STORE_NAME               ExtractionError

 L.1124      1092  LOAD_BUILD_CLASS 
             1094  LOAD_CODE                <code_object ResourceManager>
             1096  LOAD_STR                 'ResourceManager'
             1098  MAKE_FUNCTION_0          'Neither defaults, keyword-only args, annotations, nor closures'
             1100  LOAD_STR                 'ResourceManager'
             1102  CALL_FUNCTION_2       2  ''
             1104  STORE_NAME               ResourceManager

 L.1305      1106  LOAD_CODE                <code_object get_default_cache>
             1108  LOAD_STR                 'get_default_cache'
             1110  MAKE_FUNCTION_0          'Neither defaults, keyword-only args, annotations, nor closures'
             1112  STORE_NAME               get_default_cache

 L.1317      1114  LOAD_CODE                <code_object safe_name>
             1116  LOAD_STR                 'safe_name'
             1118  MAKE_FUNCTION_0          'Neither defaults, keyword-only args, annotations, nor closures'
             1120  STORE_NAME               safe_name

 L.1325      1122  LOAD_CODE                <code_object safe_version>
             1124  LOAD_STR                 'safe_version'
             1126  MAKE_FUNCTION_0          'Neither defaults, keyword-only args, annotations, nor closures'
             1128  STORE_NAME               safe_version

 L.1337      1130  LOAD_CODE                <code_object safe_extra>
             1132  LOAD_STR                 'safe_extra'
             1134  MAKE_FUNCTION_0          'Neither defaults, keyword-only args, annotations, nor closures'
             1136  STORE_NAME               safe_extra

 L.1346      1138  LOAD_CODE                <code_object to_filename>
             1140  LOAD_STR                 'to_filename'
             1142  MAKE_FUNCTION_0          'Neither defaults, keyword-only args, annotations, nor closures'
             1144  STORE_NAME               to_filename

 L.1354      1146  LOAD_CODE                <code_object invalid_marker>
             1148  LOAD_STR                 'invalid_marker'
             1150  MAKE_FUNCTION_0          'Neither defaults, keyword-only args, annotations, nor closures'
             1152  STORE_NAME               invalid_marker

 L.1368      1154  LOAD_CONST               (None,)
             1156  LOAD_CODE                <code_object evaluate_marker>
             1158  LOAD_STR                 'evaluate_marker'
             1160  MAKE_FUNCTION_1          'default'
             1162  STORE_NAME               evaluate_marker

 L.1383      1164  LOAD_BUILD_CLASS 
             1166  LOAD_CODE                <code_object NullProvider>
             1168  LOAD_STR                 'NullProvider'
             1170  MAKE_FUNCTION_0          'Neither defaults, keyword-only args, annotations, nor closures'
             1172  LOAD_STR                 'NullProvider'
             1174  CALL_FUNCTION_2       2  ''
             1176  STORE_NAME               NullProvider

 L.1576      1178  LOAD_NAME                register_loader_type
             1180  LOAD_NAME                object
             1182  LOAD_NAME                NullProvider
             1184  CALL_FUNCTION_2       2  ''
             1186  POP_TOP          

 L.1579      1188  LOAD_CODE                <code_object _parents>
             1190  LOAD_STR                 '_parents'
             1192  MAKE_FUNCTION_0          'Neither defaults, keyword-only args, annotations, nor closures'
             1194  STORE_NAME               _parents

 L.1590      1196  LOAD_BUILD_CLASS 
             1198  LOAD_CODE                <code_object EggProvider>
             1200  LOAD_STR                 'EggProvider'
             1202  MAKE_FUNCTION_0          'Neither defaults, keyword-only args, annotations, nor closures'
             1204  LOAD_STR                 'EggProvider'
             1206  LOAD_NAME                NullProvider
             1208  CALL_FUNCTION_3       3  ''
             1210  STORE_NAME               EggProvider

 L.1610      1212  LOAD_BUILD_CLASS 
             1214  LOAD_CODE                <code_object DefaultProvider>
             1216  LOAD_STR                 'DefaultProvider'
             1218  MAKE_FUNCTION_0          'Neither defaults, keyword-only args, annotations, nor closures'
             1220  LOAD_STR                 'DefaultProvider'
             1222  LOAD_NAME                EggProvider
             1224  CALL_FUNCTION_3       3  ''
             1226  STORE_NAME               DefaultProvider

 L.1637      1228  LOAD_NAME                DefaultProvider
             1230  LOAD_METHOD              _register
             1232  CALL_METHOD_0         0  ''
             1234  POP_TOP          

 L.1640      1236  LOAD_BUILD_CLASS 
             1238  LOAD_CODE                <code_object EmptyProvider>
             1240  LOAD_STR                 'EmptyProvider'
             1242  MAKE_FUNCTION_0          'Neither defaults, keyword-only args, annotations, nor closures'
             1244  LOAD_STR                 'EmptyProvider'
             1246  LOAD_NAME                NullProvider
             1248  CALL_FUNCTION_3       3  ''
             1250  STORE_NAME               EmptyProvider

 L.1657      1252  LOAD_NAME                EmptyProvider
             1254  CALL_FUNCTION_0       0  ''
             1256  STORE_NAME               empty_provider

 L.1660      1258  LOAD_BUILD_CLASS 
             1260  LOAD_CODE                <code_object ZipManifests>
             1262  LOAD_STR                 'ZipManifests'
             1264  MAKE_FUNCTION_0          'Neither defaults, keyword-only args, annotations, nor closures'
             1266  LOAD_STR                 'ZipManifests'
             1268  LOAD_NAME                dict
             1270  CALL_FUNCTION_3       3  ''
             1272  STORE_NAME               ZipManifests

 L.1687      1274  LOAD_BUILD_CLASS 
             1276  LOAD_CODE                <code_object MemoizedZipManifests>
             1278  LOAD_STR                 'MemoizedZipManifests'
             1280  MAKE_FUNCTION_0          'Neither defaults, keyword-only args, annotations, nor closures'
             1282  LOAD_STR                 'MemoizedZipManifests'
             1284  LOAD_NAME                ZipManifests
             1286  CALL_FUNCTION_3       3  ''
             1288  STORE_NAME               MemoizedZipManifests

 L.1707      1290  LOAD_BUILD_CLASS 
             1292  LOAD_CODE                <code_object ZipProvider>
             1294  LOAD_STR                 'ZipProvider'
             1296  MAKE_FUNCTION_0          'Neither defaults, keyword-only args, annotations, nor closures'
             1298  LOAD_STR                 'ZipProvider'
             1300  LOAD_NAME                EggProvider
             1302  CALL_FUNCTION_3       3  ''
             1304  STORE_NAME               ZipProvider

 L.1879      1306  LOAD_NAME                register_loader_type
             1308  LOAD_NAME                zipimport
             1310  LOAD_ATTR                zipimporter
             1312  LOAD_NAME                ZipProvider
             1314  CALL_FUNCTION_2       2  ''
             1316  POP_TOP          

 L.1882      1318  LOAD_BUILD_CLASS 
             1320  LOAD_CODE                <code_object FileMetadata>
             1322  LOAD_STR                 'FileMetadata'
             1324  MAKE_FUNCTION_0          'Neither defaults, keyword-only args, annotations, nor closures'
             1326  LOAD_STR                 'FileMetadata'
             1328  LOAD_NAME                EmptyProvider
             1330  CALL_FUNCTION_3       3  ''
             1332  STORE_NAME               FileMetadata

 L.1924      1334  LOAD_BUILD_CLASS 
             1336  LOAD_CODE                <code_object PathMetadata>
             1338  LOAD_STR                 'PathMetadata'
             1340  MAKE_FUNCTION_0          'Neither defaults, keyword-only args, annotations, nor closures'
             1342  LOAD_STR                 'PathMetadata'
             1344  LOAD_NAME                DefaultProvider
             1346  CALL_FUNCTION_3       3  ''
             1348  STORE_NAME               PathMetadata

 L.1949      1350  LOAD_BUILD_CLASS 
             1352  LOAD_CODE                <code_object EggMetadata>
             1354  LOAD_STR                 'EggMetadata'
             1356  MAKE_FUNCTION_0          'Neither defaults, keyword-only args, annotations, nor closures'
             1358  LOAD_STR                 'EggMetadata'
             1360  LOAD_NAME                ZipProvider
             1362  CALL_FUNCTION_3       3  ''
             1364  STORE_NAME               EggMetadata

 L.1964      1366  LOAD_NAME                _declare_state
             1368  LOAD_STR                 'dict'
             1370  BUILD_MAP_0           0 
             1372  LOAD_CONST               ('_distribution_finders',)
             1374  CALL_FUNCTION_KW_2     2  '2 total positional and keyword args'
             1376  POP_TOP          

 L.1967      1378  LOAD_CODE                <code_object register_finder>
             1380  LOAD_STR                 'register_finder'
             1382  MAKE_FUNCTION_0          'Neither defaults, keyword-only args, annotations, nor closures'
             1384  STORE_NAME               register_finder

 L.1977      1386  LOAD_CONST               (False,)
             1388  LOAD_CODE                <code_object find_distributions>
             1390  LOAD_STR                 'find_distributions'
             1392  MAKE_FUNCTION_1          'default'
             1394  STORE_NAME               find_distributions

 L.1984      1396  LOAD_CONST               (False,)
             1398  LOAD_CODE                <code_object find_eggs_in_zip>
             1400  LOAD_STR                 'find_eggs_in_zip'
             1402  MAKE_FUNCTION_1          'default'
             1404  STORE_NAME               find_eggs_in_zip

 L.2011      1406  LOAD_NAME                register_finder
             1408  LOAD_NAME                zipimport
             1410  LOAD_ATTR                zipimporter
             1412  LOAD_NAME                find_eggs_in_zip
             1414  CALL_FUNCTION_2       2  ''
             1416  POP_TOP          

 L.2014      1418  LOAD_CONST               (False,)
             1420  LOAD_CODE                <code_object find_nothing>
             1422  LOAD_STR                 'find_nothing'
             1424  MAKE_FUNCTION_1          'default'
             1426  STORE_NAME               find_nothing

 L.2018      1428  LOAD_NAME                register_finder
             1430  LOAD_NAME                object
             1432  LOAD_NAME                find_nothing
             1434  CALL_FUNCTION_2       2  ''
             1436  POP_TOP          

 L.2021      1438  LOAD_CODE                <code_object _by_version_descending>
             1440  LOAD_STR                 '_by_version_descending'
             1442  MAKE_FUNCTION_0          'Neither defaults, keyword-only args, annotations, nor closures'
             1444  STORE_NAME               _by_version_descending

 L.2047      1446  LOAD_CONST               (False,)
             1448  LOAD_CODE                <code_object find_on_path>
             1450  LOAD_STR                 'find_on_path'
             1452  MAKE_FUNCTION_1          'default'
             1454  STORE_NAME               find_on_path

 L.2079      1456  LOAD_CODE                <code_object dist_factory>
             1458  LOAD_STR                 'dist_factory'
             1460  MAKE_FUNCTION_0          'Neither defaults, keyword-only args, annotations, nor closures'
             1462  STORE_NAME               dist_factory

 L.2099      1464  LOAD_BUILD_CLASS 
             1466  LOAD_CODE                <code_object NoDists>
             1468  LOAD_STR                 'NoDists'
             1470  MAKE_FUNCTION_0          'Neither defaults, keyword-only args, annotations, nor closures'
             1472  LOAD_STR                 'NoDists'
             1474  CALL_FUNCTION_2       2  ''
             1476  STORE_NAME               NoDists

 L.2116      1478  LOAD_CODE                <code_object safe_listdir>
             1480  LOAD_STR                 'safe_listdir'
             1482  MAKE_FUNCTION_0          'Neither defaults, keyword-only args, annotations, nor closures'
             1484  STORE_NAME               safe_listdir

 L.2137      1486  LOAD_CODE                <code_object distributions_from_metadata>
             1488  LOAD_STR                 'distributions_from_metadata'
             1490  MAKE_FUNCTION_0          'Neither defaults, keyword-only args, annotations, nor closures'
             1492  STORE_NAME               distributions_from_metadata

 L.2152      1494  LOAD_CODE                <code_object non_empty_lines>
             1496  LOAD_STR                 'non_empty_lines'
             1498  MAKE_FUNCTION_0          'Neither defaults, keyword-only args, annotations, nor closures'
             1500  STORE_NAME               non_empty_lines

 L.2163      1502  LOAD_CODE                <code_object resolve_egg_link>
             1504  LOAD_STR                 'resolve_egg_link'
             1506  MAKE_FUNCTION_0          'Neither defaults, keyword-only args, annotations, nor closures'
             1508  STORE_NAME               resolve_egg_link

 L.2177      1510  LOAD_NAME                register_finder
             1512  LOAD_NAME                pkgutil
             1514  LOAD_ATTR                ImpImporter
             1516  LOAD_NAME                find_on_path
             1518  CALL_FUNCTION_2       2  ''
             1520  POP_TOP          

 L.2179      1522  LOAD_NAME                hasattr
             1524  LOAD_NAME                importlib_machinery
             1526  LOAD_STR                 'FileFinder'
             1528  CALL_FUNCTION_2       2  ''
         1530_1532  POP_JUMP_IF_FALSE  1546  'to 1546'

 L.2180      1534  LOAD_NAME                register_finder
             1536  LOAD_NAME                importlib_machinery
             1538  LOAD_ATTR                FileFinder
             1540  LOAD_NAME                find_on_path
             1542  CALL_FUNCTION_2       2  ''
             1544  POP_TOP          
           1546_0  COME_FROM          1530  '1530'

 L.2182      1546  LOAD_NAME                _declare_state
             1548  LOAD_STR                 'dict'
             1550  BUILD_MAP_0           0 
             1552  LOAD_CONST               ('_namespace_handlers',)
             1554  CALL_FUNCTION_KW_2     2  '2 total positional and keyword args'
             1556  POP_TOP          

 L.2183      1558  LOAD_NAME                _declare_state
             1560  LOAD_STR                 'dict'
             1562  BUILD_MAP_0           0 
             1564  LOAD_CONST               ('_namespace_packages',)
             1566  CALL_FUNCTION_KW_2     2  '2 total positional and keyword args'
             1568  POP_TOP          

 L.2186      1570  LOAD_CODE                <code_object register_namespace_handler>
             1572  LOAD_STR                 'register_namespace_handler'
             1574  MAKE_FUNCTION_0          'Neither defaults, keyword-only args, annotations, nor closures'
             1576  STORE_NAME               register_namespace_handler

 L.2204      1578  LOAD_CODE                <code_object _handle_ns>
             1580  LOAD_STR                 '_handle_ns'
             1582  MAKE_FUNCTION_0          'Neither defaults, keyword-only args, annotations, nor closures'
             1584  STORE_NAME               _handle_ns

 L.2239      1586  LOAD_CODE                <code_object _rebuild_mod_path>
             1588  LOAD_STR                 '_rebuild_mod_path'
             1590  MAKE_FUNCTION_0          'Neither defaults, keyword-only args, annotations, nor closures'
             1592  STORE_NAME               _rebuild_mod_path

 L.2273      1594  LOAD_CODE                <code_object declare_namespace>
             1596  LOAD_STR                 'declare_namespace'
             1598  MAKE_FUNCTION_0          'Neither defaults, keyword-only args, annotations, nor closures'
             1600  STORE_NAME               declare_namespace

 L.2307      1602  LOAD_CONST               (None,)
             1604  LOAD_CODE                <code_object fixup_namespace_packages>
             1606  LOAD_STR                 'fixup_namespace_packages'
             1608  MAKE_FUNCTION_1          'default'
             1610  STORE_NAME               fixup_namespace_packages

 L.2319      1612  LOAD_CODE                <code_object file_ns_handler>
             1614  LOAD_STR                 'file_ns_handler'
             1616  MAKE_FUNCTION_0          'Neither defaults, keyword-only args, annotations, nor closures'
             1618  STORE_NAME               file_ns_handler

 L.2332      1620  LOAD_NAME                register_namespace_handler
             1622  LOAD_NAME                pkgutil
             1624  LOAD_ATTR                ImpImporter
             1626  LOAD_NAME                file_ns_handler
             1628  CALL_FUNCTION_2       2  ''
             1630  POP_TOP          

 L.2333      1632  LOAD_NAME                register_namespace_handler
             1634  LOAD_NAME                zipimport
             1636  LOAD_ATTR                zipimporter
             1638  LOAD_NAME                file_ns_handler
             1640  CALL_FUNCTION_2       2  ''
             1642  POP_TOP          

 L.2335      1644  LOAD_NAME                hasattr
             1646  LOAD_NAME                importlib_machinery
             1648  LOAD_STR                 'FileFinder'
             1650  CALL_FUNCTION_2       2  ''
         1652_1654  POP_JUMP_IF_FALSE  1668  'to 1668'

 L.2336      1656  LOAD_NAME                register_namespace_handler
             1658  LOAD_NAME                importlib_machinery
             1660  LOAD_ATTR                FileFinder
             1662  LOAD_NAME                file_ns_handler
             1664  CALL_FUNCTION_2       2  ''
             1666  POP_TOP          
           1668_0  COME_FROM          1652  '1652'

 L.2339      1668  LOAD_CODE                <code_object null_ns_handler>
             1670  LOAD_STR                 'null_ns_handler'
             1672  MAKE_FUNCTION_0          'Neither defaults, keyword-only args, annotations, nor closures'
             1674  STORE_NAME               null_ns_handler

 L.2343      1676  LOAD_NAME                register_namespace_handler
             1678  LOAD_NAME                object
             1680  LOAD_NAME                null_ns_handler
             1682  CALL_FUNCTION_2       2  ''
             1684  POP_TOP          

 L.2346      1686  LOAD_CODE                <code_object normalize_path>
             1688  LOAD_STR                 'normalize_path'
             1690  MAKE_FUNCTION_0          'Neither defaults, keyword-only args, annotations, nor closures'
             1692  STORE_NAME               normalize_path

 L.2352      1694  LOAD_CODE                <code_object _cygwin_patch>
             1696  LOAD_STR                 '_cygwin_patch'
             1698  MAKE_FUNCTION_0          'Neither defaults, keyword-only args, annotations, nor closures'
             1700  STORE_NAME               _cygwin_patch

 L.2363      1702  BUILD_MAP_0           0 
             1704  BUILD_TUPLE_1         1 
             1706  LOAD_CODE                <code_object _normalize_cached>
             1708  LOAD_STR                 '_normalize_cached'
             1710  MAKE_FUNCTION_1          'default'
             1712  STORE_NAME               _normalize_cached

 L.2371      1714  LOAD_CODE                <code_object _is_egg_path>
             1716  LOAD_STR                 '_is_egg_path'
             1718  MAKE_FUNCTION_0          'Neither defaults, keyword-only args, annotations, nor closures'
             1720  STORE_NAME               _is_egg_path

 L.2378      1722  LOAD_CODE                <code_object _is_unpacked_egg>
             1724  LOAD_STR                 '_is_unpacked_egg'
             1726  MAKE_FUNCTION_0          'Neither defaults, keyword-only args, annotations, nor closures'
             1728  STORE_NAME               _is_unpacked_egg

 L.2388      1730  LOAD_CODE                <code_object _set_parent_ns>
             1732  LOAD_STR                 '_set_parent_ns'
             1734  MAKE_FUNCTION_0          'Neither defaults, keyword-only args, annotations, nor closures'
             1736  STORE_NAME               _set_parent_ns

 L.2396      1738  LOAD_CODE                <code_object yield_lines>
             1740  LOAD_STR                 'yield_lines'
             1742  MAKE_FUNCTION_0          'Neither defaults, keyword-only args, annotations, nor closures'
             1744  STORE_NAME               yield_lines

 L.2410      1746  LOAD_NAME                re
             1748  LOAD_METHOD              compile
             1750  LOAD_STR                 '\\w+(\\.\\w+)*$'
             1752  CALL_METHOD_1         1  ''
             1754  LOAD_ATTR                match
             1756  STORE_NAME               MODULE

 L.2411      1758  LOAD_NAME                re
             1760  LOAD_METHOD              compile

 L.2412      1762  LOAD_STR                 '\n    (?P<name>[^-]+) (\n        -(?P<ver>[^-]+) (\n            -py(?P<pyver>[^-]+) (\n                -(?P<plat>.+)\n            )?\n        )?\n    )?\n    '

 L.2421      1764  LOAD_NAME                re
             1766  LOAD_ATTR                VERBOSE
             1768  LOAD_NAME                re
             1770  LOAD_ATTR                IGNORECASE
             1772  BINARY_OR        

 L.2411      1774  CALL_METHOD_2         2  ''
             1776  LOAD_ATTR                match
             1778  STORE_NAME               EGG_NAME

 L.2425      1780  LOAD_BUILD_CLASS 
             1782  LOAD_CODE                <code_object EntryPoint>
             1784  LOAD_STR                 'EntryPoint'
             1786  MAKE_FUNCTION_0          'Neither defaults, keyword-only args, annotations, nor closures'
             1788  LOAD_STR                 'EntryPoint'
             1790  CALL_FUNCTION_2       2  ''
             1792  STORE_NAME               EntryPoint

 L.2557      1794  LOAD_CODE                <code_object _version_from_file>
             1796  LOAD_STR                 '_version_from_file'
             1798  MAKE_FUNCTION_0          'Neither defaults, keyword-only args, annotations, nor closures'
             1800  STORE_NAME               _version_from_file

 L.2570      1802  LOAD_BUILD_CLASS 
             1804  LOAD_CODE                <code_object Distribution>
             1806  LOAD_STR                 'Distribution'
             1808  MAKE_FUNCTION_0          'Neither defaults, keyword-only args, annotations, nor closures'
             1810  LOAD_STR                 'Distribution'
             1812  CALL_FUNCTION_2       2  ''
             1814  STORE_NAME               Distribution

 L.2990      1816  LOAD_BUILD_CLASS 
             1818  LOAD_CODE                <code_object EggInfoDistribution>
             1820  LOAD_STR                 'EggInfoDistribution'
             1822  MAKE_FUNCTION_0          'Neither defaults, keyword-only args, annotations, nor closures'
             1824  LOAD_STR                 'EggInfoDistribution'
             1826  LOAD_NAME                Distribution
             1828  CALL_FUNCTION_3       3  ''
             1830  STORE_NAME               EggInfoDistribution

 L.3009      1832  LOAD_BUILD_CLASS 
             1834  LOAD_CODE                <code_object DistInfoDistribution>
             1836  LOAD_STR                 'DistInfoDistribution'
             1838  MAKE_FUNCTION_0          'Neither defaults, keyword-only args, annotations, nor closures'
             1840  LOAD_STR                 'DistInfoDistribution'
             1842  LOAD_NAME                Distribution
             1844  CALL_FUNCTION_3       3  ''
             1846  STORE_NAME               DistInfoDistribution

 L.3060      1848  LOAD_NAME                Distribution

 L.3061      1850  LOAD_NAME                EggInfoDistribution

 L.3062      1852  LOAD_NAME                DistInfoDistribution

 L.3059      1854  LOAD_CONST               ('.egg', '.egg-info', '.dist-info')
             1856  BUILD_CONST_KEY_MAP_3     3 
             1858  STORE_NAME               _distributionImpl

 L.3066      1860  LOAD_CODE                <code_object issue_warning>
             1862  LOAD_STR                 'issue_warning'
             1864  MAKE_FUNCTION_0          'Neither defaults, keyword-only args, annotations, nor closures'
             1866  STORE_NAME               issue_warning

 L.3079      1868  LOAD_CODE                <code_object parse_requirements>
             1870  LOAD_STR                 'parse_requirements'
             1872  MAKE_FUNCTION_0          'Neither defaults, keyword-only args, annotations, nor closures'
             1874  STORE_NAME               parse_requirements

 L.3101      1876  LOAD_BUILD_CLASS 
             1878  LOAD_CODE                <code_object RequirementParseError>
             1880  LOAD_STR                 'RequirementParseError'
             1882  MAKE_FUNCTION_0          'Neither defaults, keyword-only args, annotations, nor closures'
             1884  LOAD_STR                 'RequirementParseError'
             1886  LOAD_NAME                packaging
             1888  LOAD_ATTR                requirements
             1890  LOAD_ATTR                InvalidRequirement
             1892  CALL_FUNCTION_3       3  ''
             1894  STORE_NAME               RequirementParseError

 L.3105      1896  LOAD_BUILD_CLASS 
             1898  LOAD_CODE                <code_object Requirement>
             1900  LOAD_STR                 'Requirement'
             1902  MAKE_FUNCTION_0          'Neither defaults, keyword-only args, annotations, nor closures'
             1904  LOAD_STR                 'Requirement'
             1906  LOAD_NAME                packaging
             1908  LOAD_ATTR                requirements
             1910  LOAD_ATTR                Requirement
             1912  CALL_FUNCTION_3       3  ''
             1914  STORE_NAME               Requirement

 L.3157      1916  LOAD_CODE                <code_object _always_object>
             1918  LOAD_STR                 '_always_object'
             1920  MAKE_FUNCTION_0          'Neither defaults, keyword-only args, annotations, nor closures'
             1922  STORE_NAME               _always_object

 L.3167      1924  LOAD_CODE                <code_object _find_adapter>
             1926  LOAD_STR                 '_find_adapter'
             1928  MAKE_FUNCTION_0          'Neither defaults, keyword-only args, annotations, nor closures'
             1930  STORE_NAME               _find_adapter

 L.3175      1932  LOAD_CODE                <code_object ensure_directory>
             1934  LOAD_STR                 'ensure_directory'
             1936  MAKE_FUNCTION_0          'Neither defaults, keyword-only args, annotations, nor closures'
             1938  STORE_NAME               ensure_directory

 L.3181      1940  LOAD_CODE                <code_object _bypass_ensure_directory>
             1942  LOAD_STR                 '_bypass_ensure_directory'
             1944  MAKE_FUNCTION_0          'Neither defaults, keyword-only args, annotations, nor closures'
             1946  STORE_NAME               _bypass_ensure_directory

 L.3194      1948  LOAD_CODE                <code_object split_sections>
             1950  LOAD_STR                 'split_sections'
             1952  MAKE_FUNCTION_0          'Neither defaults, keyword-only args, annotations, nor closures'
             1954  STORE_NAME               split_sections

 L.3220      1956  LOAD_CODE                <code_object _mkstemp>
             1958  LOAD_STR                 '_mkstemp'
             1960  MAKE_FUNCTION_0          'Neither defaults, keyword-only args, annotations, nor closures'
             1962  STORE_NAME               _mkstemp

 L.3235      1964  LOAD_NAME                warnings
             1966  LOAD_ATTR                filterwarnings
             1968  LOAD_STR                 'ignore'
             1970  LOAD_NAME                PEP440Warning
             1972  LOAD_CONST               True
             1974  LOAD_CONST               ('category', 'append')
             1976  CALL_FUNCTION_KW_3     3  '3 total positional and keyword args'
             1978  POP_TOP          

 L.3239      1980  LOAD_CODE                <code_object _call_aside>
             1982  LOAD_STR                 '_call_aside'
             1984  MAKE_FUNCTION_0          'Neither defaults, keyword-only args, annotations, nor closures'
             1986  STORE_NAME               _call_aside

 L.3244      1988  LOAD_NAME                _call_aside

 L.3245      1990  LOAD_NAME                globals
             1992  CALL_FUNCTION_0       0  ''
             1994  BUILD_TUPLE_1         1 
             1996  LOAD_CODE                <code_object _initialize>
             1998  LOAD_STR                 '_initialize'
             2000  MAKE_FUNCTION_1          'default'
             2002  CALL_FUNCTION_1       1  ''
             2004  STORE_NAME               _initialize

 L.3256      2006  LOAD_NAME                _call_aside

 L.3257      2008  LOAD_CODE                <code_object _initialize_master_working_set>
             2010  LOAD_STR                 '_initialize_master_working_set'
             2012  MAKE_FUNCTION_0          'Neither defaults, keyword-only args, annotations, nor closures'
             2014  CALL_FUNCTION_1       1  ''
             2016  STORE_NAME               _initialize_master_working_set

 L.3296      2018  LOAD_BUILD_CLASS 
             2020  LOAD_CODE                <code_object PkgResourcesDeprecationWarning>
             2022  LOAD_STR                 'PkgResourcesDeprecationWarning'
             2024  MAKE_FUNCTION_0          'Neither defaults, keyword-only args, annotations, nor closures'
             2026  LOAD_STR                 'PkgResourcesDeprecationWarning'
             2028  LOAD_NAME                Warning
             2030  CALL_FUNCTION_3       3  ''
             2032  STORE_NAME               PkgResourcesDeprecationWarning

Parse error at or near `<121>' instruction at offset 238_240

Instruction context:
   
 L.  48       234  DUP_TOP          
                 236  LOAD_NAME                ImportError
->           238_240  <121>               260  ''
                 242  POP_TOP          
                 244  POP_TOP          
                 246  POP_TOP          

test/115891.pyc -- 
# decompile failed
