Instruction context:
   
 L. 206       102  DUP_TOP          
                 104  LOAD_GLOBAL              struct
                 106  LOAD_ATTR                error
->               108  <121>               160  ''
                 110  POP_TOP          
                 112  STORE_FAST               'e'
                 114  POP_TOP          
                 116  SETUP_FINALLY       152  'to 152'
Instruction context:
   
 L. 226        24  DUP_TOP          
                  26  LOAD_GLOBAL              struct
                  28  LOAD_ATTR                error
->                30  <121>                70  ''
                  32  POP_TOP          
                  34  STORE_FAST               'e'
                  36  POP_TOP          
                  38  SETUP_FINALLY        62  'to 62'
Instruction context:
   
 L. 327        62  DUP_TOP          
                  64  LOAD_GLOBAL              UnicodeError
->                66  <121>                94  ''
                  68  POP_TOP          
                  70  POP_TOP          
                  72  POP_TOP          
Instruction context:
   
 L. 398       118  DUP_TOP          
                 120  LOAD_GLOBAL              ValueError
->               122  <121>               148  ''
                 124  POP_TOP          
                 126  POP_TOP          
                 128  POP_TOP          
Instruction context:
   
 L. 415        70  DUP_TOP          
                  72  LOAD_GLOBAL              Exception
->                74  <121>                86  ''
                  76  POP_TOP          
                  78  POP_TOP          
                  80  POP_TOP          
Instruction context:
   
 L. 464        76  LOAD_FAST                'self'
                  78  LOAD_ATTR                im_mode
                  80  LOAD_CONST               ('1', 'L', 'I')
->                82  <118>                 0  ''
                  84  POP_JUMP_IF_FALSE   102  'to 102'
Instruction context:
   
 L. 515        36  DUP_TOP          
                  38  LOAD_GLOBAL              ValueError
->                40  <121>                60  ''
                  42  POP_TOP          
                  44  POP_TOP          
                  46  POP_TOP          
Instruction context:
   
 L. 535        36  DUP_TOP          
                  38  LOAD_GLOBAL              ValueError
->                40  <121>                60  ''
                  42  POP_TOP          
                  44  POP_TOP          
                  46  POP_TOP          
Instruction context:
   
 L. 569        40  DUP_TOP          
                  42  LOAD_GLOBAL              ValueError
->                44  <121>                60  ''
                  46  POP_TOP          
                  48  POP_TOP          
                  50  POP_TOP          
Instruction context:
   
 L. 612        14  LOAD_FAST                'self'
                  16  LOAD_ATTR                im_n_frames
                  18  LOAD_CONST               None
->                20  <117>                 1  ''
                  22  POP_JUMP_IF_FALSE    44  'to 44'
Instruction context:
   
 L. 628        22  LOAD_FAST                'self'
                  24  LOAD_ATTR                _seq_num
                  26  LOAD_CONST               None
->                28  <117>                 0  ''
                  30  POP_JUMP_IF_FALSE    40  'to 40'
                  32  LOAD_FAST                'seq'
                  34  LOAD_CONST               0
                  36  COMPARE_OP               !=
                  38  POP_JUMP_IF_TRUE     64  'to 64'
                40_0  COME_FROM            30  '30'
Instruction context:
   
 L. 695        94  DUP_TOP          
                  96  LOAD_GLOBAL              EOFError
->                98  <121>               114  ''
                 100  POP_TOP          
                 102  POP_TOP          
                 104  POP_TOP          
Instruction context:
   
 L. 782        82  DUP_TOP          
                  84  LOAD_GLOBAL              EOFError
->                86  <121>               136  ''
                  88  POP_TOP          
                  90  STORE_FAST               'e'
                  92  POP_TOP          
                  94  SETUP_FINALLY       128  'to 128'
Instruction context:
   
 L. 828       318  DUP_TOP          
                 320  LOAD_GLOBAL              struct
                 322  LOAD_ATTR                error
                 324  LOAD_GLOBAL              SyntaxError
                 326  BUILD_TUPLE_2         2 
->           328_330  <121>               348  ''
                 332  POP_TOP          
                 334  POP_TOP          
                 336  POP_TOP          
Instruction context:
   
 L. 898        38  LOAD_FAST                'cid'
                  40  LOAD_CONST               (b'IDAT', b'DDAT', b'fdAT')
->                42  <118>                 1  ''
                  44  POP_JUMP_IF_FALSE    66  'to 66'
Instruction context:
   
 L. 928        34  DUP_TOP          
                  36  LOAD_GLOBAL              struct
                  38  LOAD_ATTR                error
                  40  LOAD_GLOBAL              SyntaxError
                  42  BUILD_TUPLE_2         2 
->                44  <121>                62  ''
                  46  POP_TOP          
                  48  POP_TOP          
                  50  POP_TOP          
Instruction context:
   
 L. 983        30  DUP_TOP          
                  32  LOAD_GLOBAL              AttributeError
->                34  <121>                46  ''
                  36  POP_TOP          
                  38  POP_TOP          
                  40  POP_TOP          
Instruction context:
   
 L.1108       638  LOAD_STR                 'duration'
                 640  LOAD_FAST                'previous'
                 642  LOAD_STR                 'encoderinfo'
                 644  BINARY_SUBSCR    
->               646  <118>                 0  ''
             648_650  POP_JUMP_IF_FALSE   674  'to 674'
Instruction context:
   
 L.1187        14  LOAD_STR                 'bits'
                  16  LOAD_FAST                'im'
                  18  LOAD_ATTR                encoderinfo
->                20  <118>                 0  ''
                  22  POP_JUMP_IF_FALSE    46  'to 46'
Instruction context:
   
 L.1379        52  LOAD_FAST                'im'
->                54  DELETE_ATTR              encoderinfo
                  56  JUMP_FORWARD         64  'to 64'
                58_0  COME_FROM_FINALLY    28  '28'
                  58  LOAD_FAST                'im'
                  60  DELETE_ATTR              encoderinfo
                  62  <48>             
                64_0  COME_FROM            56  '56'

test/130208.pyc -- 
# decompile failed

# file test/130208.pyc
# Deparsing stopped due to parse error
