
# file test/134343.pyc
# --- This code section failed: ---

 L.   1         0  LOAD_CONST               0
                2  LOAD_CONST               None
                4  IMPORT_NAME              asyncio
                6  STORE_NAME               asyncio

 L.   2         8  LOAD_CONST               0
               10  LOAD_CONST               None
               12  IMPORT_NAME              logging
               14  STORE_NAME               logging

 L.   3        16  LOAD_CONST               0
               18  LOAD_CONST               None
               20  IMPORT_NAME              socket
               22  STORE_NAME               socket

 L.   4        24  LOAD_CONST               0
               26  LOAD_CONST               None
               28  IMPORT_NAME              sys
               30  STORE_NAME               sys

 L.   5        32  LOAD_CONST               0
               34  LOAD_CONST               ('ArgumentParser',)
               36  IMPORT_NAME              argparse
               38  IMPORT_FROM              ArgumentParser
               40  STORE_NAME               ArgumentParser
               42  POP_TOP          

 L.   6        44  LOAD_CONST               0
               46  LOAD_CONST               ('Iterable',)
               48  IMPORT_NAME_ATTR         collections.abc
               50  IMPORT_FROM              Iterable
               52  STORE_NAME               Iterable
               54  POP_TOP          

 L.   7        56  LOAD_CONST               0
               58  LOAD_CONST               ('import_module',)
               60  IMPORT_NAME              importlib
               62  IMPORT_FROM              import_module
               64  STORE_NAME               import_module
               66  POP_TOP          

 L.   8        68  LOAD_CONST               0
               70  LOAD_CONST               ('Any', 'Awaitable', 'Callable', 'Iterable', 'List', 'Optional', 'Set', 'Type', 'Union', 'cast')
               72  IMPORT_NAME              typing
               74  IMPORT_FROM              Any
               76  STORE_NAME               Any
               78  IMPORT_FROM              Awaitable
               80  STORE_NAME               Awaitable
               82  IMPORT_FROM              Callable
               84  STORE_NAME               Callable
               86  IMPORT_FROM              Iterable
               88  STORE_NAME               TypingIterable
               90  IMPORT_FROM              List
               92  STORE_NAME               List
               94  IMPORT_FROM              Optional
               96  STORE_NAME               Optional
               98  IMPORT_FROM              Set
              100  STORE_NAME               Set
              102  IMPORT_FROM              Type
              104  STORE_NAME               Type
              106  IMPORT_FROM              Union
              108  STORE_NAME               Union
              110  IMPORT_FROM              cast
              112  STORE_NAME               cast
              114  POP_TOP          

 L.  21       116  LOAD_CONST               1
              118  LOAD_CONST               ('AbstractAccessLogger',)
              120  IMPORT_NAME              abc
              122  IMPORT_FROM              AbstractAccessLogger
              124  STORE_NAME               AbstractAccessLogger
              126  POP_TOP          

 L.  22       128  LOAD_CONST               1
              130  LOAD_CONST               ('all_tasks',)
              132  IMPORT_NAME              helpers
              134  IMPORT_FROM              all_tasks
              136  STORE_NAME               all_tasks
              138  POP_TOP          

 L.  23       140  LOAD_CONST               1
              142  LOAD_CONST               ('access_logger',)
              144  IMPORT_NAME              log
              146  IMPORT_FROM              access_logger
              148  STORE_NAME               access_logger
              150  POP_TOP          

 L.  24       152  LOAD_CONST               1
              154  LOAD_CONST               ('Application', 'CleanupError')
              156  IMPORT_NAME              web_app
              158  IMPORT_FROM              Application
              160  STORE_NAME               Application
              162  IMPORT_FROM              CleanupError
              164  STORE_NAME               CleanupError
              166  POP_TOP          

 L.  25       168  LOAD_CONST               1
              170  LOAD_CONST               ('HTTPAccepted', 'HTTPBadGateway', 'HTTPBadRequest', 'HTTPClientError', 'HTTPConflict', 'HTTPCreated', 'HTTPError', 'HTTPException', 'HTTPExpectationFailed', 'HTTPFailedDependency', 'HTTPForbidden', 'HTTPFound', 'HTTPGatewayTimeout', 'HTTPGone', 'HTTPInsufficientStorage', 'HTTPInternalServerError', 'HTTPLengthRequired', 'HTTPMethodNotAllowed', 'HTTPMisdirectedRequest', 'HTTPMovedPermanently', 'HTTPMultipleChoices', 'HTTPNetworkAuthenticationRequired', 'HTTPNoContent', 'HTTPNonAuthoritativeInformation', 'HTTPNotAcceptable', 'HTTPNotExtended', 'HTTPNotFound', 'HTTPNotImplemented', 'HTTPNotModified', 'HTTPOk', 'HTTPPartialContent', 'HTTPPaymentRequired', 'HTTPPermanentRedirect', 'HTTPPreconditionFailed', 'HTTPPreconditionRequired', 'HTTPProxyAuthenticationRequired', 'HTTPRedirection', 'HTTPRequestEntityTooLarge', 'HTTPRequestHeaderFieldsTooLarge', 'HTTPRequestRangeNotSatisfiable', 'HTTPRequestTimeout', 'HTTPRequestURITooLong', 'HTTPResetContent', 'HTTPSeeOther', 'HTTPServerError', 'HTTPServiceUnavailable', 'HTTPSuccessful', 'HTTPTemporaryRedirect', 'HTTPTooManyRequests', 'HTTPUnauthorized', 'HTTPUnavailableForLegalReasons', 'HTTPUnprocessableEntity', 'HTTPUnsupportedMediaType', 'HTTPUpgradeRequired', 'HTTPUseProxy', 'HTTPVariantAlsoNegotiates', 'HTTPVersionNotSupported')
              172  IMPORT_NAME              web_exceptions
              174  IMPORT_FROM              HTTPAccepted
              176  STORE_NAME               HTTPAccepted
              178  IMPORT_FROM              HTTPBadGateway
              180  STORE_NAME               HTTPBadGateway
              182  IMPORT_FROM              HTTPBadRequest
              184  STORE_NAME               HTTPBadRequest
              186  IMPORT_FROM              HTTPClientError
              188  STORE_NAME               HTTPClientError
              190  IMPORT_FROM              HTTPConflict
              192  STORE_NAME               HTTPConflict
              194  IMPORT_FROM              HTTPCreated
              196  STORE_NAME               HTTPCreated
              198  IMPORT_FROM              HTTPError
              200  STORE_NAME               HTTPError
              202  IMPORT_FROM              HTTPException
              204  STORE_NAME               HTTPException
              206  IMPORT_FROM              HTTPExpectationFailed
              208  STORE_NAME               HTTPExpectationFailed
              210  IMPORT_FROM              HTTPFailedDependency
              212  STORE_NAME               HTTPFailedDependency
              214  IMPORT_FROM              HTTPForbidden
              216  STORE_NAME               HTTPForbidden
              218  IMPORT_FROM              HTTPFound
              220  STORE_NAME               HTTPFound
              222  IMPORT_FROM              HTTPGatewayTimeout
              224  STORE_NAME               HTTPGatewayTimeout
              226  IMPORT_FROM              HTTPGone
              228  STORE_NAME               HTTPGone
              230  IMPORT_FROM              HTTPInsufficientStorage
              232  STORE_NAME               HTTPInsufficientStorage
              234  IMPORT_FROM              HTTPInternalServerError
              236  STORE_NAME               HTTPInternalServerError
              238  IMPORT_FROM              HTTPLengthRequired
              240  STORE_NAME               HTTPLengthRequired
              242  IMPORT_FROM              HTTPMethodNotAllowed
              244  STORE_NAME               HTTPMethodNotAllowed
              246  IMPORT_FROM              HTTPMisdirectedRequest
              248  STORE_NAME               HTTPMisdirectedRequest
              250  IMPORT_FROM              HTTPMovedPermanently
              252  STORE_NAME               HTTPMovedPermanently
              254  IMPORT_FROM              HTTPMultipleChoices
              256  STORE_NAME               HTTPMultipleChoices
              258  IMPORT_FROM              HTTPNetworkAuthenticationRequired
              260  STORE_NAME               HTTPNetworkAuthenticationRequired
              262  IMPORT_FROM              HTTPNoContent
              264  STORE_NAME               HTTPNoContent
              266  IMPORT_FROM              HTTPNonAuthoritativeInformation
              268  STORE_NAME               HTTPNonAuthoritativeInformation
              270  IMPORT_FROM              HTTPNotAcceptable
              272  STORE_NAME               HTTPNotAcceptable
              274  IMPORT_FROM              HTTPNotExtended
              276  STORE_NAME               HTTPNotExtended
              278  IMPORT_FROM              HTTPNotFound
              280  STORE_NAME               HTTPNotFound
              282  IMPORT_FROM              HTTPNotImplemented
              284  STORE_NAME               HTTPNotImplemented
              286  IMPORT_FROM              HTTPNotModified
              288  STORE_NAME               HTTPNotModified
              290  IMPORT_FROM              HTTPOk
              292  STORE_NAME               HTTPOk
              294  IMPORT_FROM              HTTPPartialContent
              296  STORE_NAME               HTTPPartialContent
              298  IMPORT_FROM              HTTPPaymentRequired
              300  STORE_NAME               HTTPPaymentRequired
              302  IMPORT_FROM              HTTPPermanentRedirect
              304  STORE_NAME               HTTPPermanentRedirect
              306  IMPORT_FROM              HTTPPreconditionFailed
              308  STORE_NAME               HTTPPreconditionFailed
              310  IMPORT_FROM              HTTPPreconditionRequired
              312  STORE_NAME               HTTPPreconditionRequired
              314  IMPORT_FROM              HTTPProxyAuthenticationRequired
              316  STORE_NAME               HTTPProxyAuthenticationRequired
              318  IMPORT_FROM              HTTPRedirection
              320  STORE_NAME               HTTPRedirection
              322  IMPORT_FROM              HTTPRequestEntityTooLarge
              324  STORE_NAME               HTTPRequestEntityTooLarge
              326  IMPORT_FROM              HTTPRequestHeaderFieldsTooLarge
              328  STORE_NAME               HTTPRequestHeaderFieldsTooLarge
              330  IMPORT_FROM              HTTPRequestRangeNotSatisfiable
              332  STORE_NAME               HTTPRequestRangeNotSatisfiable
              334  IMPORT_FROM              HTTPRequestTimeout
              336  STORE_NAME               HTTPRequestTimeout
              338  IMPORT_FROM              HTTPRequestURITooLong
              340  STORE_NAME               HTTPRequestURITooLong
              342  IMPORT_FROM              HTTPResetContent
              344  STORE_NAME               HTTPResetContent
              346  IMPORT_FROM              HTTPSeeOther
              348  STORE_NAME               HTTPSeeOther
              350  IMPORT_FROM              HTTPServerError
              352  STORE_NAME               HTTPServerError
              354  IMPORT_FROM              HTTPServiceUnavailable
              356  STORE_NAME               HTTPServiceUnavailable
              358  IMPORT_FROM              HTTPSuccessful
              360  STORE_NAME               HTTPSuccessful
              362  IMPORT_FROM              HTTPTemporaryRedirect
              364  STORE_NAME               HTTPTemporaryRedirect
              366  IMPORT_FROM              HTTPTooManyRequests
              368  STORE_NAME               HTTPTooManyRequests
              370  IMPORT_FROM              HTTPUnauthorized
              372  STORE_NAME               HTTPUnauthorized
              374  IMPORT_FROM              HTTPUnavailableForLegalReasons
              376  STORE_NAME               HTTPUnavailableForLegalReasons
              378  IMPORT_FROM              HTTPUnprocessableEntity
              380  STORE_NAME               HTTPUnprocessableEntity
              382  IMPORT_FROM              HTTPUnsupportedMediaType
              384  STORE_NAME               HTTPUnsupportedMediaType
              386  IMPORT_FROM              HTTPUpgradeRequired
              388  STORE_NAME               HTTPUpgradeRequired
              390  IMPORT_FROM              HTTPUseProxy
              392  STORE_NAME               HTTPUseProxy
              394  IMPORT_FROM              HTTPVariantAlsoNegotiates
              396  STORE_NAME               HTTPVariantAlsoNegotiates
              398  IMPORT_FROM              HTTPVersionNotSupported
              400  STORE_NAME               HTTPVersionNotSupported
              402  POP_TOP          

 L.  84       404  LOAD_CONST               1
              406  LOAD_CONST               ('FileResponse',)
              408  IMPORT_NAME              web_fileresponse
              410  IMPORT_FROM              FileResponse
              412  STORE_NAME               FileResponse
              414  POP_TOP          

 L.  85       416  LOAD_CONST               1
              418  LOAD_CONST               ('AccessLogger',)
              420  IMPORT_NAME              web_log
              422  IMPORT_FROM              AccessLogger
              424  STORE_NAME               AccessLogger
              426  POP_TOP          

 L.  86       428  LOAD_CONST               1
              430  LOAD_CONST               ('middleware', 'normalize_path_middleware')
              432  IMPORT_NAME              web_middlewares
              434  IMPORT_FROM              middleware
              436  STORE_NAME               middleware
              438  IMPORT_FROM              normalize_path_middleware
              440  STORE_NAME               normalize_path_middleware
              442  POP_TOP          

 L.  90       444  LOAD_CONST               1
              446  LOAD_CONST               ('PayloadAccessError', 'RequestHandler', 'RequestPayloadError')
              448  IMPORT_NAME              web_protocol
              450  IMPORT_FROM              PayloadAccessError
              452  STORE_NAME               PayloadAccessError
              454  IMPORT_FROM              RequestHandler
              456  STORE_NAME               RequestHandler
              458  IMPORT_FROM              RequestPayloadError
              460  STORE_NAME               RequestPayloadError
              462  POP_TOP          

 L.  95       464  LOAD_CONST               1
              466  LOAD_CONST               ('BaseRequest', 'FileField', 'Request')
              468  IMPORT_NAME              web_request
              470  IMPORT_FROM              BaseRequest
              472  STORE_NAME               BaseRequest
              474  IMPORT_FROM              FileField
              476  STORE_NAME               FileField
              478  IMPORT_FROM              Request
              480  STORE_NAME               Request
              482  POP_TOP          

 L. 100       484  LOAD_CONST               1
              486  LOAD_CONST               ('ContentCoding', 'Response', 'StreamResponse', 'json_response')
              488  IMPORT_NAME              web_response
              490  IMPORT_FROM              ContentCoding
              492  STORE_NAME               ContentCoding
              494  IMPORT_FROM              Response
              496  STORE_NAME               Response
              498  IMPORT_FROM              StreamResponse
              500  STORE_NAME               StreamResponse
              502  IMPORT_FROM              json_response
              504  STORE_NAME               json_response
              506  POP_TOP          

 L. 106       508  LOAD_CONST               1
              510  LOAD_CONST               ('AbstractRouteDef', 'RouteDef', 'RouteTableDef', 'StaticDef', 'delete', 'get', 'head', 'options', 'patch', 'post', 'put', 'route', 'static', 'view')
              512  IMPORT_NAME              web_routedef
              514  IMPORT_FROM              AbstractRouteDef
              516  STORE_NAME               AbstractRouteDef
              518  IMPORT_FROM              RouteDef
              520  STORE_NAME               RouteDef
              522  IMPORT_FROM              RouteTableDef
              524  STORE_NAME               RouteTableDef
              526  IMPORT_FROM              StaticDef
              528  STORE_NAME               StaticDef
              530  IMPORT_FROM              delete
              532  STORE_NAME               delete
              534  IMPORT_FROM              get
              536  STORE_NAME               get
              538  IMPORT_FROM              head
              540  STORE_NAME               head
              542  IMPORT_FROM              options
              544  STORE_NAME               options
              546  IMPORT_FROM              patch
              548  STORE_NAME               patch
              550  IMPORT_FROM              post
              552  STORE_NAME               post
              554  IMPORT_FROM              put
              556  STORE_NAME               put
              558  IMPORT_FROM              route
              560  STORE_NAME               route
              562  IMPORT_FROM              static
              564  STORE_NAME               static
              566  IMPORT_FROM              view
              568  STORE_NAME               view
              570  POP_TOP          

 L. 122       572  LOAD_CONST               1
              574  LOAD_CONST               ('AppRunner', 'BaseRunner', 'BaseSite', 'GracefulExit', 'NamedPipeSite', 'ServerRunner', 'SockSite', 'TCPSite', 'UnixSite')
              576  IMPORT_NAME              web_runner
              578  IMPORT_FROM              AppRunner
              580  STORE_NAME               AppRunner
              582  IMPORT_FROM              BaseRunner
              584  STORE_NAME               BaseRunner
              586  IMPORT_FROM              BaseSite
              588  STORE_NAME               BaseSite
              590  IMPORT_FROM              GracefulExit
              592  STORE_NAME               GracefulExit
              594  IMPORT_FROM              NamedPipeSite
              596  STORE_NAME               NamedPipeSite
              598  IMPORT_FROM              ServerRunner
              600  STORE_NAME               ServerRunner
              602  IMPORT_FROM              SockSite
              604  STORE_NAME               SockSite
              606  IMPORT_FROM              TCPSite
              608  STORE_NAME               TCPSite
              610  IMPORT_FROM              UnixSite
              612  STORE_NAME               UnixSite
              614  POP_TOP          

 L. 133       616  LOAD_CONST               1
              618  LOAD_CONST               ('Server',)
              620  IMPORT_NAME              web_server
              622  IMPORT_FROM              Server
              624  STORE_NAME               Server
              626  POP_TOP          

 L. 134       628  LOAD_CONST               1
              630  LOAD_CONST               ('AbstractResource', 'AbstractRoute', 'DynamicResource', 'PlainResource', 'Resource', 'ResourceRoute', 'StaticResource', 'UrlDispatcher', 'UrlMappingMatchInfo', 'View')
              632  IMPORT_NAME              web_urldispatcher
              634  IMPORT_FROM              AbstractResource
              636  STORE_NAME               AbstractResource
              638  IMPORT_FROM              AbstractRoute
              640  STORE_NAME               AbstractRoute
              642  IMPORT_FROM              DynamicResource
              644  STORE_NAME               DynamicResource
              646  IMPORT_FROM              PlainResource
              648  STORE_NAME               PlainResource
              650  IMPORT_FROM              Resource
              652  STORE_NAME               Resource
              654  IMPORT_FROM              ResourceRoute
              656  STORE_NAME               ResourceRoute
              658  IMPORT_FROM              StaticResource
              660  STORE_NAME               StaticResource
              662  IMPORT_FROM              UrlDispatcher
              664  STORE_NAME               UrlDispatcher
              666  IMPORT_FROM              UrlMappingMatchInfo
              668  STORE_NAME               UrlMappingMatchInfo
              670  IMPORT_FROM              View
              672  STORE_NAME               View
              674  POP_TOP          

 L. 146       676  LOAD_CONST               1
              678  LOAD_CONST               ('WebSocketReady', 'WebSocketResponse', 'WSMsgType')
              680  IMPORT_NAME              web_ws
              682  IMPORT_FROM              WebSocketReady
              684  STORE_NAME               WebSocketReady
              686  IMPORT_FROM              WebSocketResponse
              688  STORE_NAME               WebSocketResponse
              690  IMPORT_FROM              WSMsgType
              692  STORE_NAME               WSMsgType
              694  POP_TOP          

 L. 152       696  LOAD_CONST               ('Application', 'CleanupError', 'HTTPAccepted', 'HTTPBadGateway', 'HTTPBadRequest', 'HTTPClientError', 'HTTPConflict', 'HTTPCreated', 'HTTPError', 'HTTPException', 'HTTPExpectationFailed', 'HTTPFailedDependency', 'HTTPForbidden', 'HTTPFound', 'HTTPGatewayTimeout', 'HTTPGone', 'HTTPInsufficientStorage', 'HTTPInternalServerError', 'HTTPLengthRequired', 'HTTPMethodNotAllowed', 'HTTPMisdirectedRequest', 'HTTPMovedPermanently', 'HTTPMultipleChoices', 'HTTPNetworkAuthenticationRequired', 'HTTPNoContent', 'HTTPNonAuthoritativeInformation', 'HTTPNotAcceptable', 'HTTPNotExtended', 'HTTPNotFound', 'HTTPNotImplemented', 'HTTPNotModified', 'HTTPOk', 'HTTPPartialContent', 'HTTPPaymentRequired', 'HTTPPermanentRedirect', 'HTTPPreconditionFailed', 'HTTPPreconditionRequired', 'HTTPProxyAuthenticationRequired', 'HTTPRedirection', 'HTTPRequestEntityTooLarge', 'HTTPRequestHeaderFieldsTooLarge', 'HTTPRequestRangeNotSatisfiable', 'HTTPRequestTimeout', 'HTTPRequestURITooLong', 'HTTPResetContent', 'HTTPSeeOther', 'HTTPServerError', 'HTTPServiceUnavailable', 'HTTPSuccessful', 'HTTPTemporaryRedirect', 'HTTPTooManyRequests', 'HTTPUnauthorized', 'HTTPUnavailableForLegalReasons', 'HTTPUnprocessableEntity', 'HTTPUnsupportedMediaType', 'HTTPUpgradeRequired', 'HTTPUseProxy', 'HTTPVariantAlsoNegotiates', 'HTTPVersionNotSupported', 'FileResponse', 'middleware', 'normalize_path_middleware', 'PayloadAccessError', 'RequestHandler', 'RequestPayloadError', 'BaseRequest', 'FileField', 'Request', 'ContentCoding', 'Response', 'StreamResponse', 'json_response', 'AbstractRouteDef', 'RouteDef', 'RouteTableDef', 'StaticDef', 'delete', 'get', 'head', 'options', 'patch', 'post', 'put', 'route', 'static', 'view', 'AppRunner', 'BaseRunner', 'BaseSite', 'GracefulExit', 'ServerRunner', 'SockSite', 'TCPSite', 'UnixSite', 'NamedPipeSite', 'Server', 'AbstractResource', 'AbstractRoute', 'DynamicResource', 'PlainResource', 'Resource', 'ResourceRoute', 'StaticResource', 'UrlDispatcher', 'UrlMappingMatchInfo', 'View', 'WebSocketReady', 'WebSocketResponse', 'WSMsgType', 'run_app')
              698  STORE_NAME               __all__

 L. 279       700  SETUP_FINALLY       718  'to 718'

 L. 280       702  LOAD_CONST               0
              704  LOAD_CONST               ('SSLContext',)
              706  IMPORT_NAME              ssl
              708  IMPORT_FROM              SSLContext
              710  STORE_NAME               SSLContext
              712  POP_TOP          
              714  POP_BLOCK        
              716  JUMP_FORWARD        742  'to 742'
            718_0  COME_FROM_FINALLY   700  '700'

 L. 281       718  DUP_TOP          
              720  LOAD_NAME                ImportError
          722_724  <121>               740  ''
              726  POP_TOP          
              728  POP_TOP          
              730  POP_TOP          

 L. 282       732  LOAD_NAME                Any
              734  STORE_NAME               SSLContext
              736  POP_EXCEPT       
              738  JUMP_FORWARD        742  'to 742'
              740  <48>             
            742_0  COME_FROM           738  '738'
            742_1  COME_FROM           716  '716'

 L. 284       742  LOAD_NAME                TypingIterable
              744  LOAD_NAME                str
              746  BINARY_SUBSCR    
              748  STORE_NAME               HostSequence

 L. 290       750  LOAD_CONST               None

 L. 291       752  LOAD_CONST               None

 L. 292       754  LOAD_CONST               None

 L. 293       756  LOAD_CONST               None

 L. 294       758  LOAD_CONST               60.0

 L. 295       760  LOAD_CONST               None

 L. 296       762  LOAD_NAME                print

 L. 297       764  LOAD_CONST               128

 L. 298       766  LOAD_NAME                AccessLogger

 L. 299       768  LOAD_NAME                AccessLogger
              770  LOAD_ATTR                LOG_FORMAT

 L. 300       772  LOAD_NAME                access_logger

 L. 301       774  LOAD_CONST               True

 L. 302       776  LOAD_CONST               None

 L. 303       778  LOAD_CONST               None

 L. 287       780  LOAD_CONST               ('host', 'port', 'path', 'sock', 'shutdown_timeout', 'ssl_context', 'print', 'backlog', 'access_log_class', 'access_log_format', 'access_log', 'handle_signals', 'reuse_address', 'reuse_port')
              782  BUILD_CONST_KEY_MAP_14    14 

 L. 288       784  LOAD_NAME                Union
              786  LOAD_NAME                Application
              788  LOAD_NAME                Awaitable
              790  LOAD_NAME                Application
              792  BINARY_SUBSCR    
              794  BUILD_TUPLE_2         2 
              796  BINARY_SUBSCR    

 L. 290       798  LOAD_NAME                Optional
              800  LOAD_NAME                Union
              802  LOAD_NAME                str
              804  LOAD_NAME                HostSequence
              806  BUILD_TUPLE_2         2 
              808  BINARY_SUBSCR    
              810  BINARY_SUBSCR    

 L. 291       812  LOAD_NAME                Optional
              814  LOAD_NAME                int
              816  BINARY_SUBSCR    

 L. 292       818  LOAD_NAME                Optional
              820  LOAD_NAME                str
              822  BINARY_SUBSCR    

 L. 293       824  LOAD_NAME                Optional
              826  LOAD_NAME                socket
              828  LOAD_ATTR                socket
              830  BINARY_SUBSCR    

 L. 294       832  LOAD_NAME                float

 L. 295       834  LOAD_NAME                Optional
              836  LOAD_NAME                SSLContext
              838  BINARY_SUBSCR    

 L. 296       840  LOAD_NAME                Callable
              842  LOAD_CONST               (Ellipsis, None)
              844  BINARY_SUBSCR    

 L. 297       846  LOAD_NAME                int

 L. 298       848  LOAD_NAME                Type
              850  LOAD_NAME                AbstractAccessLogger
              852  BINARY_SUBSCR    

 L. 299       854  LOAD_NAME                str

 L. 300       856  LOAD_NAME                Optional
              858  LOAD_NAME                logging
              860  LOAD_ATTR                Logger
              862  BINARY_SUBSCR    

 L. 301       864  LOAD_NAME                bool

 L. 302       866  LOAD_NAME                Optional
              868  LOAD_NAME                bool
              870  BINARY_SUBSCR    

 L. 303       872  LOAD_NAME                Optional
              874  LOAD_NAME                bool
              876  BINARY_SUBSCR    

 L. 304       878  LOAD_CONST               None

 L. 287       880  LOAD_CONST               ('app', 'host', 'port', 'path', 'sock', 'shutdown_timeout', 'ssl_context', 'print', 'backlog', 'access_log_class', 'access_log_format', 'access_log', 'handle_signals', 'reuse_address', 'reuse_port', 'return')
              882  BUILD_CONST_KEY_MAP_16    16 
              884  LOAD_CODE                <code_object _run_app>
              886  LOAD_STR                 '_run_app'
              888  MAKE_FUNCTION_6          'keyword-only, annotation'
              890  STORE_NAME               _run_app

 L. 435       892  LOAD_NAME                Set
              894  LOAD_STR                 'asyncio.Task[Any]'
              896  BINARY_SUBSCR    
              898  LOAD_NAME                asyncio
              900  LOAD_ATTR                AbstractEventLoop

 L. 436       902  LOAD_CONST               None

 L. 434       904  LOAD_CONST               ('to_cancel', 'loop', 'return')
              906  BUILD_CONST_KEY_MAP_3     3 
              908  LOAD_CODE                <code_object _cancel_tasks>
              910  LOAD_STR                 '_cancel_tasks'
              912  MAKE_FUNCTION_4          'annotation'
              914  STORE_NAME               _cancel_tasks

 L. 463       916  LOAD_CONST               None

 L. 464       918  LOAD_CONST               None

 L. 465       920  LOAD_CONST               None

 L. 466       922  LOAD_CONST               None

 L. 467       924  LOAD_CONST               60.0

 L. 468       926  LOAD_CONST               None

 L. 469       928  LOAD_NAME                print

 L. 470       930  LOAD_CONST               128

 L. 471       932  LOAD_NAME                AccessLogger

 L. 472       934  LOAD_NAME                AccessLogger
              936  LOAD_ATTR                LOG_FORMAT

 L. 473       938  LOAD_NAME                access_logger

 L. 474       940  LOAD_CONST               True

 L. 475       942  LOAD_CONST               None

 L. 476       944  LOAD_CONST               None

 L. 460       946  LOAD_CONST               ('host', 'port', 'path', 'sock', 'shutdown_timeout', 'ssl_context', 'print', 'backlog', 'access_log_class', 'access_log_format', 'access_log', 'handle_signals', 'reuse_address', 'reuse_port')
              948  BUILD_CONST_KEY_MAP_14    14 

 L. 461       950  LOAD_NAME                Union
              952  LOAD_NAME                Application
              954  LOAD_NAME                Awaitable
              956  LOAD_NAME                Application
              958  BINARY_SUBSCR    
              960  BUILD_TUPLE_2         2 
              962  BINARY_SUBSCR    

 L. 463       964  LOAD_NAME                Optional
              966  LOAD_NAME                Union
              968  LOAD_NAME                str
              970  LOAD_NAME                HostSequence
              972  BUILD_TUPLE_2         2 
              974  BINARY_SUBSCR    
              976  BINARY_SUBSCR    

 L. 464       978  LOAD_NAME                Optional
              980  LOAD_NAME                int
              982  BINARY_SUBSCR    

 L. 465       984  LOAD_NAME                Optional
              986  LOAD_NAME                str
              988  BINARY_SUBSCR    

 L. 466       990  LOAD_NAME                Optional
              992  LOAD_NAME                socket
              994  LOAD_ATTR                socket
              996  BINARY_SUBSCR    

 L. 467       998  LOAD_NAME                float

 L. 468      1000  LOAD_NAME                Optional
             1002  LOAD_NAME                SSLContext
             1004  BINARY_SUBSCR    

 L. 469      1006  LOAD_NAME                Callable
             1008  LOAD_CONST               (Ellipsis, None)
             1010  BINARY_SUBSCR    

 L. 470      1012  LOAD_NAME                int

 L. 471      1014  LOAD_NAME                Type
             1016  LOAD_NAME                AbstractAccessLogger
             1018  BINARY_SUBSCR    

 L. 472      1020  LOAD_NAME                str

 L. 473      1022  LOAD_NAME                Optional
             1024  LOAD_NAME                logging
             1026  LOAD_ATTR                Logger
             1028  BINARY_SUBSCR    

 L. 474      1030  LOAD_NAME                bool

 L. 475      1032  LOAD_NAME                Optional
             1034  LOAD_NAME                bool
             1036  BINARY_SUBSCR    

 L. 476      1038  LOAD_NAME                Optional
             1040  LOAD_NAME                bool
             1042  BINARY_SUBSCR    

 L. 477      1044  LOAD_CONST               None

 L. 460      1046  LOAD_CONST               ('app', 'host', 'port', 'path', 'sock', 'shutdown_timeout', 'ssl_context', 'print', 'backlog', 'access_log_class', 'access_log_format', 'access_log', 'handle_signals', 'reuse_address', 'reuse_port', 'return')
             1048  BUILD_CONST_KEY_MAP_16    16 
             1050  LOAD_CODE                <code_object run_app>
             1052  LOAD_STR                 'run_app'
             1054  MAKE_FUNCTION_6          'keyword-only, annotation'
             1056  STORE_NAME               run_app

 L. 519      1058  LOAD_NAME                List
             1060  LOAD_NAME                str
             1062  BINARY_SUBSCR    
             1064  LOAD_CONST               None
             1066  LOAD_CONST               ('argv', 'return')
             1068  BUILD_CONST_KEY_MAP_2     2 
             1070  LOAD_CODE                <code_object main>
             1072  LOAD_STR                 'main'
             1074  MAKE_FUNCTION_4          'annotation'
             1076  STORE_NAME               main

 L. 580      1078  LOAD_NAME                __name__
             1080  LOAD_STR                 '__main__'
             1082  COMPARE_OP               ==
         1084_1086  POP_JUMP_IF_FALSE  1106  'to 1106'

 L. 581      1088  LOAD_NAME                main
             1090  LOAD_NAME                sys
             1092  LOAD_ATTR                argv
             1094  LOAD_CONST               1
             1096  LOAD_CONST               None
             1098  BUILD_SLICE_2         2 
             1100  BINARY_SUBSCR    
             1102  CALL_FUNCTION_1       1  ''
             1104  POP_TOP          
           1106_0  COME_FROM          1084  '1084'

Parse error at or near `<121>' instruction at offset 722_724

Instruction context:
   
 L. 281       718  DUP_TOP          
                 720  LOAD_NAME                ImportError
->           722_724  <121>               740  ''
                 726  POP_TOP          
                 728  POP_TOP          
                 730  POP_TOP          

test/134343.pyc -- 
# decompile failed
