
# file test/134316.pyc
# --- This code section failed: ---

 L.   1         0  LOAD_STR                 'HTTP Client for asyncio.'
                2  STORE_NAME               __doc__

 L.   3         4  LOAD_CONST               0
                6  LOAD_CONST               None
                8  IMPORT_NAME              asyncio
               10  STORE_NAME               asyncio

 L.   4        12  LOAD_CONST               0
               14  LOAD_CONST               None
               16  IMPORT_NAME              base64
               18  STORE_NAME               base64

 L.   5        20  LOAD_CONST               0
               22  LOAD_CONST               None
               24  IMPORT_NAME              hashlib
               26  STORE_NAME               hashlib

 L.   6        28  LOAD_CONST               0
               30  LOAD_CONST               None
               32  IMPORT_NAME              json
               34  STORE_NAME               json

 L.   7        36  LOAD_CONST               0
               38  LOAD_CONST               None
               40  IMPORT_NAME              os
               42  STORE_NAME               os

 L.   8        44  LOAD_CONST               0
               46  LOAD_CONST               None
               48  IMPORT_NAME              sys
               50  STORE_NAME               sys

 L.   9        52  LOAD_CONST               0
               54  LOAD_CONST               None
               56  IMPORT_NAME              traceback
               58  STORE_NAME               traceback

 L.  10        60  LOAD_CONST               0
               62  LOAD_CONST               None
               64  IMPORT_NAME              warnings
               66  STORE_NAME               warnings

 L.  11        68  LOAD_CONST               0
               70  LOAD_CONST               ('SimpleNamespace', 'TracebackType')
               72  IMPORT_NAME              types
               74  IMPORT_FROM              SimpleNamespace
               76  STORE_NAME               SimpleNamespace
               78  IMPORT_FROM              TracebackType
               80  STORE_NAME               TracebackType
               82  POP_TOP          

 L.  12        84  LOAD_CONST               0
               86  LOAD_CONST               ('Any', 'Awaitable', 'Callable', 'Coroutine', 'FrozenSet', 'Generator', 'Generic', 'Iterable', 'List', 'Mapping', 'Optional', 'Set', 'Tuple', 'Type', 'TypeVar', 'Union')
               88  IMPORT_NAME              typing
               90  IMPORT_FROM              Any
               92  STORE_NAME               Any
               94  IMPORT_FROM              Awaitable
               96  STORE_NAME               Awaitable
               98  IMPORT_FROM              Callable
              100  STORE_NAME               Callable
              102  IMPORT_FROM              Coroutine
              104  STORE_NAME               Coroutine
              106  IMPORT_FROM              FrozenSet
              108  STORE_NAME               FrozenSet
              110  IMPORT_FROM              Generator
              112  STORE_NAME               Generator
              114  IMPORT_FROM              Generic
              116  STORE_NAME               Generic
              118  IMPORT_FROM              Iterable
              120  STORE_NAME               Iterable
              122  IMPORT_FROM              List
              124  STORE_NAME               List
              126  IMPORT_FROM              Mapping
              128  STORE_NAME               Mapping
              130  IMPORT_FROM              Optional
              132  STORE_NAME               Optional
              134  IMPORT_FROM              Set
              136  STORE_NAME               Set
              138  IMPORT_FROM              Tuple
              140  STORE_NAME               Tuple
              142  IMPORT_FROM              Type
              144  STORE_NAME               Type
              146  IMPORT_FROM              TypeVar
              148  STORE_NAME               TypeVar
              150  IMPORT_FROM              Union
              152  STORE_NAME               Union
              154  POP_TOP          

 L.  31       156  LOAD_CONST               0
              158  LOAD_CONST               None
              160  IMPORT_NAME              attr
              162  STORE_NAME               attr

 L.  32       164  LOAD_CONST               0
              166  LOAD_CONST               ('CIMultiDict', 'MultiDict', 'MultiDictProxy', 'istr')
              168  IMPORT_NAME              multidict
              170  IMPORT_FROM              CIMultiDict
              172  STORE_NAME               CIMultiDict
              174  IMPORT_FROM              MultiDict
              176  STORE_NAME               MultiDict
              178  IMPORT_FROM              MultiDictProxy
              180  STORE_NAME               MultiDictProxy
              182  IMPORT_FROM              istr
              184  STORE_NAME               istr
              186  POP_TOP          

 L.  33       188  LOAD_CONST               0
              190  LOAD_CONST               ('URL',)
              192  IMPORT_NAME              yarl
              194  IMPORT_FROM              URL
              196  STORE_NAME               URL
              198  POP_TOP          

 L.  35       200  LOAD_CONST               1
              202  LOAD_CONST               ('hdrs', 'http', 'payload')
              204  IMPORT_NAME              
              206  IMPORT_FROM              hdrs
              208  STORE_NAME               hdrs
              210  IMPORT_FROM              http
              212  STORE_NAME               http
              214  IMPORT_FROM              payload
              216  STORE_NAME               payload
              218  POP_TOP          

 L.  36       220  LOAD_CONST               1
              222  LOAD_CONST               ('AbstractCookieJar',)
              224  IMPORT_NAME              abc
              226  IMPORT_FROM              AbstractCookieJar
              228  STORE_NAME               AbstractCookieJar
              230  POP_TOP          

 L.  37       232  LOAD_CONST               1
              234  LOAD_CONST               ('ClientConnectionError', 'ClientConnectorCertificateError', 'ClientConnectorError', 'ClientConnectorSSLError', 'ClientError', 'ClientHttpProxyError', 'ClientOSError', 'ClientPayloadError', 'ClientProxyConnectionError', 'ClientResponseError', 'ClientSSLError', 'ContentTypeError', 'InvalidURL', 'ServerConnectionError', 'ServerDisconnectedError', 'ServerFingerprintMismatch', 'ServerTimeoutError', 'TooManyRedirects', 'WSServerHandshakeError')
              236  IMPORT_NAME              client_exceptions
              238  IMPORT_FROM              ClientConnectionError
              240  STORE_NAME               ClientConnectionError
              242  IMPORT_FROM              ClientConnectorCertificateError
              244  STORE_NAME               ClientConnectorCertificateError
              246  IMPORT_FROM              ClientConnectorError
              248  STORE_NAME               ClientConnectorError
              250  IMPORT_FROM              ClientConnectorSSLError
              252  STORE_NAME               ClientConnectorSSLError
              254  IMPORT_FROM              ClientError
              256  STORE_NAME               ClientError
              258  IMPORT_FROM              ClientHttpProxyError
              260  STORE_NAME               ClientHttpProxyError
              262  IMPORT_FROM              ClientOSError
              264  STORE_NAME               ClientOSError
              266  IMPORT_FROM              ClientPayloadError
              268  STORE_NAME               ClientPayloadError
              270  IMPORT_FROM              ClientProxyConnectionError
              272  STORE_NAME               ClientProxyConnectionError
              274  IMPORT_FROM              ClientResponseError
              276  STORE_NAME               ClientResponseError
              278  IMPORT_FROM              ClientSSLError
              280  STORE_NAME               ClientSSLError
              282  IMPORT_FROM              ContentTypeError
              284  STORE_NAME               ContentTypeError
              286  IMPORT_FROM              InvalidURL
              288  STORE_NAME               InvalidURL
              290  IMPORT_FROM              ServerConnectionError
              292  STORE_NAME               ServerConnectionError
              294  IMPORT_FROM              ServerDisconnectedError
              296  STORE_NAME               ServerDisconnectedError
              298  IMPORT_FROM              ServerFingerprintMismatch
              300  STORE_NAME               ServerFingerprintMismatch
              302  IMPORT_FROM              ServerTimeoutError
              304  STORE_NAME               ServerTimeoutError
              306  IMPORT_FROM              TooManyRedirects
              308  STORE_NAME               TooManyRedirects
              310  IMPORT_FROM              WSServerHandshakeError
              312  STORE_NAME               WSServerHandshakeError
              314  POP_TOP          

 L.  58       316  LOAD_CONST               1
              318  LOAD_CONST               ('ClientRequest', 'ClientResponse', 'Fingerprint', 'RequestInfo', '_merge_ssl_params')
              320  IMPORT_NAME              client_reqrep
              322  IMPORT_FROM              ClientRequest
              324  STORE_NAME               ClientRequest
              326  IMPORT_FROM              ClientResponse
              328  STORE_NAME               ClientResponse
              330  IMPORT_FROM              Fingerprint
              332  STORE_NAME               Fingerprint
              334  IMPORT_FROM              RequestInfo
              336  STORE_NAME               RequestInfo
              338  IMPORT_FROM              _merge_ssl_params
              340  STORE_NAME               _merge_ssl_params
              342  POP_TOP          

 L.  65       344  LOAD_CONST               1
              346  LOAD_CONST               ('ClientWebSocketResponse',)
              348  IMPORT_NAME              client_ws
              350  IMPORT_FROM              ClientWebSocketResponse
              352  STORE_NAME               ClientWebSocketResponse
              354  POP_TOP          

 L.  66       356  LOAD_CONST               1
              358  LOAD_CONST               ('BaseConnector', 'NamedPipeConnector', 'TCPConnector', 'UnixConnector')
              360  IMPORT_NAME              connector
              362  IMPORT_FROM              BaseConnector
              364  STORE_NAME               BaseConnector
              366  IMPORT_FROM              NamedPipeConnector
              368  STORE_NAME               NamedPipeConnector
              370  IMPORT_FROM              TCPConnector
              372  STORE_NAME               TCPConnector
              374  IMPORT_FROM              UnixConnector
              376  STORE_NAME               UnixConnector
              378  POP_TOP          

 L.  72       380  LOAD_CONST               1
              382  LOAD_CONST               ('CookieJar',)
              384  IMPORT_NAME              cookiejar
              386  IMPORT_FROM              CookieJar
              388  STORE_NAME               CookieJar
              390  POP_TOP          

 L.  73       392  LOAD_CONST               1
              394  LOAD_CONST               ('DEBUG', 'PY_36', 'BasicAuth', 'CeilTimeout', 'TimeoutHandle', 'get_running_loop', 'proxies_from_env', 'sentinel', 'strip_auth_from_url')
              396  IMPORT_NAME              helpers
              398  IMPORT_FROM              DEBUG
              400  STORE_NAME               DEBUG
              402  IMPORT_FROM              PY_36
              404  STORE_NAME               PY_36
              406  IMPORT_FROM              BasicAuth
              408  STORE_NAME               BasicAuth
              410  IMPORT_FROM              CeilTimeout
              412  STORE_NAME               CeilTimeout
              414  IMPORT_FROM              TimeoutHandle
              416  STORE_NAME               TimeoutHandle
              418  IMPORT_FROM              get_running_loop
              420  STORE_NAME               get_running_loop
              422  IMPORT_FROM              proxies_from_env
              424  STORE_NAME               proxies_from_env
              426  IMPORT_FROM              sentinel
              428  STORE_NAME               sentinel
              430  IMPORT_FROM              strip_auth_from_url
              432  STORE_NAME               strip_auth_from_url
              434  POP_TOP          

 L.  84       436  LOAD_CONST               1
              438  LOAD_CONST               ('WS_KEY', 'HttpVersion', 'WebSocketReader', 'WebSocketWriter')
              440  IMPORT_NAME              http
              442  IMPORT_FROM              WS_KEY
              444  STORE_NAME               WS_KEY
              446  IMPORT_FROM              HttpVersion
              448  STORE_NAME               HttpVersion
              450  IMPORT_FROM              WebSocketReader
              452  STORE_NAME               WebSocketReader
              454  IMPORT_FROM              WebSocketWriter
              456  STORE_NAME               WebSocketWriter
              458  POP_TOP          

 L.  85       460  LOAD_CONST               1
              462  LOAD_CONST               ('WSHandshakeError', 'WSMessage', 'ws_ext_gen', 'ws_ext_parse')
              464  IMPORT_NAME              http_websocket
              466  IMPORT_FROM              WSHandshakeError
              468  STORE_NAME               WSHandshakeError
              470  IMPORT_FROM              WSMessage
              472  STORE_NAME               WSMessage
              474  IMPORT_FROM              ws_ext_gen
              476  STORE_NAME               ws_ext_gen
              478  IMPORT_FROM              ws_ext_parse
              480  STORE_NAME               ws_ext_parse
              482  POP_TOP          

 L.  86       484  LOAD_CONST               1
              486  LOAD_CONST               ('FlowControlDataQueue',)
              488  IMPORT_NAME              streams
              490  IMPORT_FROM              FlowControlDataQueue
              492  STORE_NAME               FlowControlDataQueue
              494  POP_TOP          

 L.  87       496  LOAD_CONST               1
              498  LOAD_CONST               ('Trace', 'TraceConfig')
              500  IMPORT_NAME              tracing
              502  IMPORT_FROM              Trace
              504  STORE_NAME               Trace
              506  IMPORT_FROM              TraceConfig
              508  STORE_NAME               TraceConfig
              510  POP_TOP          

 L.  88       512  LOAD_CONST               1
              514  LOAD_CONST               ('JSONEncoder', 'LooseCookies', 'LooseHeaders', 'StrOrURL')
              516  IMPORT_NAME              typedefs
              518  IMPORT_FROM              JSONEncoder
              520  STORE_NAME               JSONEncoder
              522  IMPORT_FROM              LooseCookies
              524  STORE_NAME               LooseCookies
              526  IMPORT_FROM              LooseHeaders
              528  STORE_NAME               LooseHeaders
              530  IMPORT_FROM              StrOrURL
              532  STORE_NAME               StrOrURL
              534  POP_TOP          

 L.  90       536  LOAD_CONST               ('ClientConnectionError', 'ClientConnectorCertificateError', 'ClientConnectorError', 'ClientConnectorSSLError', 'ClientError', 'ClientHttpProxyError', 'ClientOSError', 'ClientPayloadError', 'ClientProxyConnectionError', 'ClientResponseError', 'ClientSSLError', 'ContentTypeError', 'InvalidURL', 'ServerConnectionError', 'ServerDisconnectedError', 'ServerFingerprintMismatch', 'ServerTimeoutError', 'TooManyRedirects', 'WSServerHandshakeError', 'ClientRequest', 'ClientResponse', 'Fingerprint', 'RequestInfo', 'BaseConnector', 'TCPConnector', 'UnixConnector', 'NamedPipeConnector', 'ClientWebSocketResponse', 'ClientSession', 'ClientTimeout', 'request')
              538  STORE_NAME               __all__

 L. 130       540  SETUP_FINALLY       558  'to 558'

 L. 131       542  LOAD_CONST               0
              544  LOAD_CONST               ('SSLContext',)
              546  IMPORT_NAME              ssl
              548  IMPORT_FROM              SSLContext
              550  STORE_NAME               SSLContext
              552  POP_TOP          
              554  POP_BLOCK        
              556  JUMP_FORWARD        582  'to 582'
            558_0  COME_FROM_FINALLY   540  '540'

 L. 132       558  DUP_TOP          
              560  LOAD_NAME                ImportError
          562_564  <121>               580  ''
              566  POP_TOP          
              568  POP_TOP          
              570  POP_TOP          

 L. 133       572  LOAD_NAME                object
              574  STORE_NAME               SSLContext
              576  POP_EXCEPT       
              578  JUMP_FORWARD        582  'to 582'
              580  <48>             
            582_0  COME_FROM           578  '578'
            582_1  COME_FROM           556  '556'

 L. 136       582  LOAD_NAME                attr
              584  LOAD_ATTR                s
              586  LOAD_CONST               True
              588  LOAD_CONST               True
              590  LOAD_CONST               True
              592  LOAD_CONST               ('auto_attribs', 'frozen', 'slots')
              594  CALL_FUNCTION_KW_3     3  '3 total positional and keyword args'

 L. 137       596  LOAD_BUILD_CLASS 
              598  LOAD_CODE                <code_object ClientTimeout>
              600  LOAD_STR                 'ClientTimeout'
              602  MAKE_FUNCTION_0          'Neither defaults, keyword-only args, annotations, nor closures'
              604  LOAD_STR                 'ClientTimeout'
              606  CALL_FUNCTION_2       2  ''
              608  CALL_FUNCTION_1       1  ''
              610  STORE_NAME               ClientTimeout

 L. 158       612  LOAD_NAME                ClientTimeout
              614  LOAD_CONST               300
              616  LOAD_CONST               ('total',)
              618  CALL_FUNCTION_KW_1     1  '1 total positional and keyword args'
              620  STORE_NAME               DEFAULT_TIMEOUT

 L. 160       622  LOAD_NAME                TypeVar
              624  LOAD_STR                 '_RetType'
              626  CALL_FUNCTION_1       1  ''
              628  STORE_NAME               _RetType

 L. 163       630  LOAD_BUILD_CLASS 
              632  LOAD_CODE                <code_object ClientSession>
              634  LOAD_STR                 'ClientSession'
              636  MAKE_FUNCTION_0          'Neither defaults, keyword-only args, annotations, nor closures'
              638  LOAD_STR                 'ClientSession'
              640  CALL_FUNCTION_2       2  ''
              642  STORE_NAME               ClientSession

 L.1093       644  LOAD_BUILD_CLASS 
              646  LOAD_CODE                <code_object _BaseRequestContextManager>
              648  LOAD_STR                 '_BaseRequestContextManager'
              650  MAKE_FUNCTION_0          'Neither defaults, keyword-only args, annotations, nor closures'
              652  LOAD_STR                 '_BaseRequestContextManager'
              654  LOAD_NAME                Coroutine
              656  LOAD_NAME                Any
              658  LOAD_NAME                Any
              660  LOAD_NAME                _RetType
              662  BUILD_TUPLE_3         3 
              664  BINARY_SUBSCR    
              666  LOAD_NAME                Generic
              668  LOAD_NAME                _RetType
              670  BINARY_SUBSCR    
              672  CALL_FUNCTION_4       4  ''
              674  STORE_NAME               _BaseRequestContextManager

 L.1121       676  LOAD_BUILD_CLASS 
              678  LOAD_CODE                <code_object _RequestContextManager>
              680  LOAD_STR                 '_RequestContextManager'
              682  MAKE_FUNCTION_0          'Neither defaults, keyword-only args, annotations, nor closures'
              684  LOAD_STR                 '_RequestContextManager'
              686  LOAD_NAME                _BaseRequestContextManager
              688  LOAD_NAME                ClientResponse
              690  BINARY_SUBSCR    
              692  CALL_FUNCTION_3       3  ''
              694  STORE_NAME               _RequestContextManager

 L.1136       696  LOAD_BUILD_CLASS 
              698  LOAD_CODE                <code_object _WSRequestContextManager>
              700  LOAD_STR                 '_WSRequestContextManager'
              702  MAKE_FUNCTION_0          'Neither defaults, keyword-only args, annotations, nor closures'
              704  LOAD_STR                 '_WSRequestContextManager'
              706  LOAD_NAME                _BaseRequestContextManager
              708  LOAD_NAME                ClientWebSocketResponse
              710  BINARY_SUBSCR    
              712  CALL_FUNCTION_3       3  ''
              714  STORE_NAME               _WSRequestContextManager

 L.1146       716  LOAD_BUILD_CLASS 
              718  LOAD_CODE                <code_object _SessionRequestContextManager>
              720  LOAD_STR                 '_SessionRequestContextManager'
              722  MAKE_FUNCTION_0          'Neither defaults, keyword-only args, annotations, nor closures'
              724  LOAD_STR                 '_SessionRequestContextManager'
              726  CALL_FUNCTION_2       2  ''
              728  STORE_NAME               _SessionRequestContextManager

 L.1183       730  LOAD_CONST               None

 L.1184       732  LOAD_CONST               None

 L.1185       734  LOAD_CONST               None

 L.1186       736  LOAD_CONST               None

 L.1187       738  LOAD_CONST               None

 L.1188       740  LOAD_CONST               None

 L.1189       742  LOAD_CONST               True

 L.1190       744  LOAD_CONST               10

 L.1191       746  LOAD_CONST               None

 L.1192       748  LOAD_CONST               None

 L.1193       750  LOAD_CONST               False

 L.1194       752  LOAD_CONST               None

 L.1195       754  LOAD_CONST               True

 L.1196       756  LOAD_CONST               None

 L.1197       758  LOAD_CONST               None

 L.1198       760  LOAD_NAME                sentinel

 L.1199       762  LOAD_CONST               None

 L.1200       764  LOAD_NAME                http
              766  LOAD_ATTR                HttpVersion11

 L.1201       768  LOAD_CONST               None

 L.1202       770  LOAD_CONST               None

 L.1203       772  LOAD_CONST               None

 L.1179       774  LOAD_CONST               ('params', 'data', 'json', 'headers', 'skip_auto_headers', 'auth', 'allow_redirects', 'max_redirects', 'compress', 'chunked', 'expect100', 'raise_for_status', 'read_until_eof', 'proxy', 'proxy_auth', 'timeout', 'cookies', 'version', 'connector', 'read_bufsize', 'loop')
              776  BUILD_CONST_KEY_MAP_21    21 

 L.1180       778  LOAD_NAME                str

 L.1181       780  LOAD_NAME                StrOrURL

 L.1183       782  LOAD_NAME                Optional
              784  LOAD_NAME                Mapping
              786  LOAD_NAME                str
              788  LOAD_NAME                str
              790  BUILD_TUPLE_2         2 
              792  BINARY_SUBSCR    
              794  BINARY_SUBSCR    

 L.1184       796  LOAD_NAME                Any

 L.1185       798  LOAD_NAME                Any

 L.1186       800  LOAD_NAME                Optional
              802  LOAD_NAME                LooseHeaders
              804  BINARY_SUBSCR    

 L.1187       806  LOAD_NAME                Optional
              808  LOAD_NAME                Iterable
              810  LOAD_NAME                str
              812  BINARY_SUBSCR    
              814  BINARY_SUBSCR    

 L.1188       816  LOAD_NAME                Optional
              818  LOAD_NAME                BasicAuth
              820  BINARY_SUBSCR    

 L.1189       822  LOAD_NAME                bool

 L.1190       824  LOAD_NAME                int

 L.1191       826  LOAD_NAME                Optional
              828  LOAD_NAME                str
              830  BINARY_SUBSCR    

 L.1192       832  LOAD_NAME                Optional
              834  LOAD_NAME                bool
              836  BINARY_SUBSCR    

 L.1193       838  LOAD_NAME                bool

 L.1194       840  LOAD_NAME                Optional
              842  LOAD_NAME                bool
              844  BINARY_SUBSCR    

 L.1195       846  LOAD_NAME                bool

 L.1196       848  LOAD_NAME                Optional
              850  LOAD_NAME                StrOrURL
              852  BINARY_SUBSCR    

 L.1197       854  LOAD_NAME                Optional
              856  LOAD_NAME                BasicAuth
              858  BINARY_SUBSCR    

 L.1198       860  LOAD_NAME                Union
              862  LOAD_NAME                ClientTimeout
              864  LOAD_NAME                object
              866  BUILD_TUPLE_2         2 
              868  BINARY_SUBSCR    

 L.1199       870  LOAD_NAME                Optional
              872  LOAD_NAME                LooseCookies
              874  BINARY_SUBSCR    

 L.1200       876  LOAD_NAME                HttpVersion

 L.1201       878  LOAD_NAME                Optional
              880  LOAD_NAME                BaseConnector
              882  BINARY_SUBSCR    

 L.1202       884  LOAD_NAME                Optional
              886  LOAD_NAME                int
              888  BINARY_SUBSCR    

 L.1203       890  LOAD_NAME                Optional
              892  LOAD_NAME                asyncio
              894  LOAD_ATTR                AbstractEventLoop
              896  BINARY_SUBSCR    

 L.1204       898  LOAD_NAME                _SessionRequestContextManager

 L.1179       900  LOAD_CONST               ('method', 'url', 'params', 'data', 'json', 'headers', 'skip_auto_headers', 'auth', 'allow_redirects', 'max_redirects', 'compress', 'chunked', 'expect100', 'raise_for_status', 'read_until_eof', 'proxy', 'proxy_auth', 'timeout', 'cookies', 'version', 'connector', 'read_bufsize', 'loop', 'return')
              902  BUILD_CONST_KEY_MAP_24    24 
              904  LOAD_CODE                <code_object request>
              906  LOAD_STR                 'request'
              908  MAKE_FUNCTION_6          'keyword-only, annotation'
              910  STORE_NAME               request

Parse error at or near `<121>' instruction at offset 562_564

Instruction context:
   
 L. 132       558  DUP_TOP          
                 560  LOAD_NAME                ImportError
->           562_564  <121>               580  ''
                 566  POP_TOP          
                 568  POP_TOP          
                 570  POP_TOP          

test/134316.pyc -- 
# decompile failed
