
# file test/134344.pyc
# --- This code section failed: ---

 L.  80         0  LOAD_NAME                __name__
                2  STORE_NAME               __module__
                4  LOAD_STR                 'Application'
                6  STORE_NAME               __qualname__

 L.  81         8  LOAD_NAME                frozenset

 L.  82        10  BUILD_LIST_0          0 
               12  LOAD_CONST               ('logger', '_debug', '_router', '_loop', '_handler_args', '_middlewares', '_middlewares_handlers', '_run_middlewares', '_state', '_frozen', '_pre_frozen', '_subapps', '_on_response_prepare', '_on_startup', '_on_shutdown', '_on_cleanup', '_client_max_size', '_cleanup_ctx')
               14  CALL_FINALLY         17  'to 17'

 L.  81        16  CALL_FUNCTION_1       1  ''
               18  STORE_NAME               ATTRS

 L. 107        20  LOAD_NAME                web_logger

 L. 108        22  LOAD_CONST               None

 L. 109        24  LOAD_CONST               ()

 L. 110        26  LOAD_CONST               None

 L. 111        28  LOAD_CONST               1048576

 L. 112        30  LOAD_CONST               None

 L. 113        32  LOAD_CONST               Ellipsis

 L. 104        34  LOAD_CONST               ('logger', 'router', 'middlewares', 'handler_args', 'client_max_size', 'loop', 'debug')
               36  BUILD_CONST_KEY_MAP_7     7 

 L. 107        38  LOAD_NAME                logging
               40  LOAD_ATTR                Logger

 L. 108        42  LOAD_NAME                Optional
               44  LOAD_NAME                UrlDispatcher
               46  BINARY_SUBSCR    

 L. 109        48  LOAD_NAME                Iterable
               50  LOAD_NAME                _Middleware
               52  BINARY_SUBSCR    

 L. 110        54  LOAD_NAME                Optional
               56  LOAD_NAME                Mapping
               58  LOAD_NAME                str
               60  LOAD_NAME                Any
               62  BUILD_TUPLE_2         2 
               64  BINARY_SUBSCR    
               66  BINARY_SUBSCR    

 L. 111        68  LOAD_NAME                int

 L. 112        70  LOAD_NAME                Optional
               72  LOAD_NAME                asyncio
               74  LOAD_ATTR                AbstractEventLoop
               76  BINARY_SUBSCR    

 L. 113        78  LOAD_NAME                Any

 L. 114        80  LOAD_CONST               None

 L. 104        82  LOAD_CONST               ('logger', 'router', 'middlewares', 'handler_args', 'client_max_size', 'loop', 'debug', 'return')
               84  BUILD_CONST_KEY_MAP_8     8 
               86  LOAD_CODE                <code_object __init__>
               88  LOAD_STR                 'Application.__init__'
               90  MAKE_FUNCTION_6          'keyword-only, annotation'
               92  STORE_NAME               __init__

 L. 159        94  LOAD_NAME                Type
               96  LOAD_STR                 'Application'
               98  BINARY_SUBSCR    
              100  LOAD_CONST               None
              102  LOAD_CONST               ('cls', 'return')
              104  BUILD_CONST_KEY_MAP_2     2 
              106  LOAD_CODE                <code_object __init_subclass__>
              108  LOAD_STR                 'Application.__init_subclass__'
              110  MAKE_FUNCTION_4          'annotation'
              112  STORE_NAME               __init_subclass__

 L. 167       114  LOAD_NAME                DEBUG
              116  POP_JUMP_IF_FALSE   140  'to 140'

 L. 169       118  LOAD_NAME                str
              120  LOAD_NAME                Any
              122  LOAD_CONST               None
              124  LOAD_CONST               ('name', 'val', 'return')
              126  BUILD_CONST_KEY_MAP_3     3 
              128  LOAD_CLOSURE             '__class__'
              130  BUILD_TUPLE_1         1 
              132  LOAD_CODE                <code_object __setattr__>
              134  LOAD_STR                 'Application.__setattr__'
              136  MAKE_FUNCTION_12         'annotation, closure'
              138  STORE_NAME               __setattr__
            140_0  COME_FROM           116  '116'

 L. 181       140  LOAD_NAME                object
              142  LOAD_NAME                bool
              144  LOAD_CONST               ('other', 'return')
              146  BUILD_CONST_KEY_MAP_2     2 
              148  LOAD_CODE                <code_object __eq__>
              150  LOAD_STR                 'Application.__eq__'
              152  MAKE_FUNCTION_4          'annotation'
              154  STORE_NAME               __eq__

 L. 184       156  LOAD_NAME                str
              158  LOAD_NAME                Any
              160  LOAD_CONST               ('key', 'return')
              162  BUILD_CONST_KEY_MAP_2     2 
              164  LOAD_CODE                <code_object __getitem__>
              166  LOAD_STR                 'Application.__getitem__'
              168  MAKE_FUNCTION_4          'annotation'
              170  STORE_NAME               __getitem__

 L. 187       172  LOAD_CONST               None
              174  LOAD_CONST               ('return',)
              176  BUILD_CONST_KEY_MAP_1     1 
              178  LOAD_CODE                <code_object _check_frozen>
              180  LOAD_STR                 'Application._check_frozen'
              182  MAKE_FUNCTION_4          'annotation'
              184  STORE_NAME               _check_frozen

 L. 195       186  LOAD_NAME                str
              188  LOAD_NAME                Any
              190  LOAD_CONST               None
              192  LOAD_CONST               ('key', 'value', 'return')
              194  BUILD_CONST_KEY_MAP_3     3 
              196  LOAD_CODE                <code_object __setitem__>
              198  LOAD_STR                 'Application.__setitem__'
              200  MAKE_FUNCTION_4          'annotation'
              202  STORE_NAME               __setitem__

 L. 199       204  LOAD_NAME                str
              206  LOAD_CONST               None
              208  LOAD_CONST               ('key', 'return')
              210  BUILD_CONST_KEY_MAP_2     2 
              212  LOAD_CODE                <code_object __delitem__>
              214  LOAD_STR                 'Application.__delitem__'
              216  MAKE_FUNCTION_4          'annotation'
              218  STORE_NAME               __delitem__

 L. 203       220  LOAD_NAME                int
              222  LOAD_CONST               ('return',)
              224  BUILD_CONST_KEY_MAP_1     1 
              226  LOAD_CODE                <code_object __len__>
              228  LOAD_STR                 'Application.__len__'
              230  MAKE_FUNCTION_4          'annotation'
              232  STORE_NAME               __len__

 L. 206       234  LOAD_NAME                Iterator
              236  LOAD_NAME                str
              238  BINARY_SUBSCR    
              240  LOAD_CONST               ('return',)
              242  BUILD_CONST_KEY_MAP_1     1 
              244  LOAD_CODE                <code_object __iter__>
              246  LOAD_STR                 'Application.__iter__'
              248  MAKE_FUNCTION_4          'annotation'
              250  STORE_NAME               __iter__

 L. 210       252  LOAD_NAME                property

 L. 211       254  LOAD_NAME                asyncio
              256  LOAD_ATTR                AbstractEventLoop
              258  LOAD_CONST               ('return',)
              260  BUILD_CONST_KEY_MAP_1     1 
              262  LOAD_CODE                <code_object loop>
              264  LOAD_STR                 'Application.loop'
              266  MAKE_FUNCTION_4          'annotation'
              268  CALL_FUNCTION_1       1  ''
              270  STORE_NAME               loop

 L. 218       272  LOAD_NAME                Optional
              274  LOAD_NAME                asyncio
              276  LOAD_ATTR                AbstractEventLoop
              278  BINARY_SUBSCR    
              280  LOAD_CONST               None
              282  LOAD_CONST               ('loop', 'return')
              284  BUILD_CONST_KEY_MAP_2     2 
              286  LOAD_CODE                <code_object _set_loop>
              288  LOAD_STR                 'Application._set_loop'
              290  MAKE_FUNCTION_4          'annotation'
              292  STORE_NAME               _set_loop

 L. 236       294  LOAD_NAME                property

 L. 237       296  LOAD_NAME                bool
              298  LOAD_CONST               ('return',)
              300  BUILD_CONST_KEY_MAP_1     1 
              302  LOAD_CODE                <code_object pre_frozen>
              304  LOAD_STR                 'Application.pre_frozen'
              306  MAKE_FUNCTION_4          'annotation'
              308  CALL_FUNCTION_1       1  ''
              310  STORE_NAME               pre_frozen

 L. 240       312  LOAD_CONST               None
              314  LOAD_CONST               ('return',)
              316  BUILD_CONST_KEY_MAP_1     1 
              318  LOAD_CODE                <code_object pre_freeze>
              320  LOAD_STR                 'Application.pre_freeze'
              322  MAKE_FUNCTION_4          'annotation'
              324  STORE_NAME               pre_freeze

 L. 265       326  LOAD_NAME                property

 L. 266       328  LOAD_NAME                bool
              330  LOAD_CONST               ('return',)
              332  BUILD_CONST_KEY_MAP_1     1 
              334  LOAD_CODE                <code_object frozen>
              336  LOAD_STR                 'Application.frozen'
              338  MAKE_FUNCTION_4          'annotation'
              340  CALL_FUNCTION_1       1  ''
              342  STORE_NAME               frozen

 L. 269       344  LOAD_CONST               None
              346  LOAD_CONST               ('return',)
              348  BUILD_CONST_KEY_MAP_1     1 
              350  LOAD_CODE                <code_object freeze>
              352  LOAD_STR                 'Application.freeze'
              354  MAKE_FUNCTION_4          'annotation'
              356  STORE_NAME               freeze

 L. 278       358  LOAD_NAME                property

 L. 279       360  LOAD_NAME                bool
              362  LOAD_CONST               ('return',)
              364  BUILD_CONST_KEY_MAP_1     1 
              366  LOAD_CODE                <code_object debug>
              368  LOAD_STR                 'Application.debug'
              370  MAKE_FUNCTION_4          'annotation'
              372  CALL_FUNCTION_1       1  ''
              374  STORE_NAME               debug

 L. 283       376  LOAD_STR                 'Application'
              378  LOAD_CONST               None
              380  LOAD_CONST               ('subapp', 'return')
              382  BUILD_CONST_KEY_MAP_2     2 
              384  LOAD_CODE                <code_object _reg_subapp_signals>
              386  LOAD_STR                 'Application._reg_subapp_signals'
              388  MAKE_FUNCTION_4          'annotation'
              390  STORE_NAME               _reg_subapp_signals

 L. 297       392  LOAD_NAME                str
              394  LOAD_STR                 'Application'
              396  LOAD_NAME                AbstractResource
              398  LOAD_CONST               ('prefix', 'subapp', 'return')
              400  BUILD_CONST_KEY_MAP_3     3 
              402  LOAD_CODE                <code_object add_subapp>
              404  LOAD_STR                 'Application.add_subapp'
              406  MAKE_FUNCTION_4          'annotation'
              408  STORE_NAME               add_subapp

 L. 307       410  LOAD_NAME                Callable
              412  BUILD_LIST_0          0 
              414  LOAD_NAME                AbstractResource
              416  BUILD_TUPLE_2         2 
              418  BINARY_SUBSCR    
              420  LOAD_STR                 'Application'

 L. 308       422  LOAD_NAME                AbstractResource

 L. 306       424  LOAD_CONST               ('resource_factory', 'subapp', 'return')
              426  BUILD_CONST_KEY_MAP_3     3 
              428  LOAD_CODE                <code_object _add_subapp>
              430  LOAD_STR                 'Application._add_subapp'
              432  MAKE_FUNCTION_4          'annotation'
              434  STORE_NAME               _add_subapp

 L. 322       436  LOAD_NAME                str
              438  LOAD_STR                 'Application'
              440  LOAD_NAME                AbstractResource
              442  LOAD_CONST               ('domain', 'subapp', 'return')
              444  BUILD_CONST_KEY_MAP_3     3 
              446  LOAD_CODE                <code_object add_domain>
              448  LOAD_STR                 'Application.add_domain'
              450  MAKE_FUNCTION_4          'annotation'
              452  STORE_NAME               add_domain

 L. 332       454  LOAD_NAME                Iterable
              456  LOAD_NAME                AbstractRouteDef
              458  BINARY_SUBSCR    
              460  LOAD_NAME                List
              462  LOAD_NAME                AbstractRoute
              464  BINARY_SUBSCR    
              466  LOAD_CONST               ('routes', 'return')
              468  BUILD_CONST_KEY_MAP_2     2 
              470  LOAD_CODE                <code_object add_routes>
              472  LOAD_STR                 'Application.add_routes'
              474  MAKE_FUNCTION_4          'annotation'
              476  STORE_NAME               add_routes

 L. 335       478  LOAD_NAME                property

 L. 336       480  LOAD_NAME                _RespPrepareSignal
              482  LOAD_CONST               ('return',)
              484  BUILD_CONST_KEY_MAP_1     1 
              486  LOAD_CODE                <code_object on_response_prepare>
              488  LOAD_STR                 'Application.on_response_prepare'
              490  MAKE_FUNCTION_4          'annotation'
              492  CALL_FUNCTION_1       1  ''
              494  STORE_NAME               on_response_prepare

 L. 339       496  LOAD_NAME                property

 L. 340       498  LOAD_NAME                _AppSignal
              500  LOAD_CONST               ('return',)
              502  BUILD_CONST_KEY_MAP_1     1 
              504  LOAD_CODE                <code_object on_startup>
              506  LOAD_STR                 'Application.on_startup'
              508  MAKE_FUNCTION_4          'annotation'
              510  CALL_FUNCTION_1       1  ''
              512  STORE_NAME               on_startup

 L. 343       514  LOAD_NAME                property

 L. 344       516  LOAD_NAME                _AppSignal
              518  LOAD_CONST               ('return',)
              520  BUILD_CONST_KEY_MAP_1     1 
              522  LOAD_CODE                <code_object on_shutdown>
              524  LOAD_STR                 'Application.on_shutdown'
              526  MAKE_FUNCTION_4          'annotation'
              528  CALL_FUNCTION_1       1  ''
              530  STORE_NAME               on_shutdown

 L. 347       532  LOAD_NAME                property

 L. 348       534  LOAD_NAME                _AppSignal
              536  LOAD_CONST               ('return',)
              538  BUILD_CONST_KEY_MAP_1     1 
              540  LOAD_CODE                <code_object on_cleanup>
              542  LOAD_STR                 'Application.on_cleanup'
              544  MAKE_FUNCTION_4          'annotation'
              546  CALL_FUNCTION_1       1  ''
              548  STORE_NAME               on_cleanup

 L. 351       550  LOAD_NAME                property

 L. 352       552  LOAD_STR                 'CleanupContext'
              554  LOAD_CONST               ('return',)
              556  BUILD_CONST_KEY_MAP_1     1 
              558  LOAD_CODE                <code_object cleanup_ctx>
              560  LOAD_STR                 'Application.cleanup_ctx'
              562  MAKE_FUNCTION_4          'annotation'
              564  CALL_FUNCTION_1       1  ''
              566  STORE_NAME               cleanup_ctx

 L. 355       568  LOAD_NAME                property

 L. 356       570  LOAD_NAME                UrlDispatcher
              572  LOAD_CONST               ('return',)
              574  BUILD_CONST_KEY_MAP_1     1 
              576  LOAD_CODE                <code_object router>
              578  LOAD_STR                 'Application.router'
              580  MAKE_FUNCTION_4          'annotation'
              582  CALL_FUNCTION_1       1  ''
              584  STORE_NAME               router

 L. 359       586  LOAD_NAME                property

 L. 360       588  LOAD_NAME                _Middlewares
              590  LOAD_CONST               ('return',)
              592  BUILD_CONST_KEY_MAP_1     1 
              594  LOAD_CODE                <code_object middlewares>
              596  LOAD_STR                 'Application.middlewares'
              598  MAKE_FUNCTION_4          'annotation'
              600  CALL_FUNCTION_1       1  ''
              602  STORE_NAME               middlewares

 L. 366       604  LOAD_CONST               None

 L. 367       606  LOAD_NAME                AccessLogger

 L. 363       608  LOAD_CONST               ('loop', 'access_log_class')
              610  BUILD_CONST_KEY_MAP_2     2 

 L. 366       612  LOAD_NAME                Optional
              614  LOAD_NAME                asyncio
              616  LOAD_ATTR                AbstractEventLoop
              618  BINARY_SUBSCR    

 L. 367       620  LOAD_NAME                Type
              622  LOAD_NAME                AbstractAccessLogger
              624  BINARY_SUBSCR    

 L. 368       626  LOAD_NAME                Any

 L. 369       628  LOAD_NAME                Server

 L. 363       630  LOAD_CONST               ('loop', 'access_log_class', 'kwargs', 'return')
              632  BUILD_CONST_KEY_MAP_4     4 
              634  LOAD_CODE                <code_object _make_handler>
              636  LOAD_STR                 'Application._make_handler'
              638  MAKE_FUNCTION_6          'keyword-only, annotation'
              640  STORE_NAME               _make_handler

 L. 396       642  LOAD_CONST               None

 L. 397       644  LOAD_NAME                AccessLogger

 L. 393       646  LOAD_CONST               ('loop', 'access_log_class')
              648  BUILD_CONST_KEY_MAP_2     2 

 L. 396       650  LOAD_NAME                Optional
              652  LOAD_NAME                asyncio
              654  LOAD_ATTR                AbstractEventLoop
              656  BINARY_SUBSCR    

 L. 397       658  LOAD_NAME                Type
              660  LOAD_NAME                AbstractAccessLogger
              662  BINARY_SUBSCR    

 L. 398       664  LOAD_NAME                Any

 L. 399       666  LOAD_NAME                Server

 L. 393       668  LOAD_CONST               ('loop', 'access_log_class', 'kwargs', 'return')
              670  BUILD_CONST_KEY_MAP_4     4 
              672  LOAD_CODE                <code_object make_handler>
              674  LOAD_STR                 'Application.make_handler'
              676  MAKE_FUNCTION_6          'keyword-only, annotation'
              678  STORE_NAME               make_handler

 L. 411       680  LOAD_CONST               None
              682  LOAD_CONST               ('return',)
              684  BUILD_CONST_KEY_MAP_1     1 
              686  LOAD_CODE                <code_object startup>
              688  LOAD_STR                 'Application.startup'
              690  MAKE_FUNCTION_4          'annotation'
              692  STORE_NAME               startup

 L. 418       694  LOAD_CONST               None
              696  LOAD_CONST               ('return',)
              698  BUILD_CONST_KEY_MAP_1     1 
              700  LOAD_CODE                <code_object shutdown>
              702  LOAD_STR                 'Application.shutdown'
              704  MAKE_FUNCTION_4          'annotation'
              706  STORE_NAME               shutdown

 L. 425       708  LOAD_CONST               None
              710  LOAD_CONST               ('return',)
              712  BUILD_CONST_KEY_MAP_1     1 
              714  LOAD_CODE                <code_object cleanup>
              716  LOAD_STR                 'Application.cleanup'
              718  MAKE_FUNCTION_4          'annotation'
              720  STORE_NAME               cleanup

 L. 439       722  LOAD_NAME                Request

 L. 432       724  BUILD_TUPLE_1         1 

 L. 434       726  LOAD_NAME                RawRequestMessage

 L. 435       728  LOAD_NAME                StreamReader

 L. 436       730  LOAD_NAME                RequestHandler

 L. 437       732  LOAD_NAME                AbstractStreamWriter

 L. 438       734  LOAD_STR                 'asyncio.Task[None]'

 L. 439       736  LOAD_NAME                Type
              738  LOAD_NAME                Request
              740  BINARY_SUBSCR    

 L. 440       742  LOAD_NAME                Request

 L. 432       744  LOAD_CONST               ('message', 'payload', 'protocol', 'writer', 'task', '_cls', 'return')
              746  BUILD_CONST_KEY_MAP_7     7 
              748  LOAD_CODE                <code_object _make_request>
              750  LOAD_STR                 'Application._make_request'
              752  MAKE_FUNCTION_5          'default, annotation'
              754  STORE_NAME               _make_request

 L. 451       756  LOAD_NAME                Iterator
              758  LOAD_NAME                Tuple
              760  LOAD_NAME                _Middleware
              762  LOAD_NAME                bool
              764  BUILD_TUPLE_2         2 
              766  BINARY_SUBSCR    
              768  BINARY_SUBSCR    
              770  LOAD_CONST               ('return',)
              772  BUILD_CONST_KEY_MAP_1     1 
              774  LOAD_CODE                <code_object _prepare_middleware>
              776  LOAD_STR                 'Application._prepare_middleware'
              778  MAKE_FUNCTION_4          'annotation'
              780  STORE_NAME               _prepare_middleware

 L. 465       782  LOAD_NAME                Request
              784  LOAD_NAME                StreamResponse
              786  LOAD_CONST               ('request', 'return')
              788  BUILD_CONST_KEY_MAP_2     2 
              790  LOAD_CODE                <code_object _handle>
              792  LOAD_STR                 'Application._handle'
              794  MAKE_FUNCTION_4          'annotation'
              796  STORE_NAME               _handle

 L. 503       798  LOAD_STR                 'Application'
              800  LOAD_CONST               ('return',)
              802  BUILD_CONST_KEY_MAP_1     1 
              804  LOAD_CODE                <code_object __call__>
              806  LOAD_STR                 'Application.__call__'
              808  MAKE_FUNCTION_4          'annotation'
              810  STORE_NAME               __call__

 L. 507       812  LOAD_NAME                str
              814  LOAD_CONST               ('return',)
              816  BUILD_CONST_KEY_MAP_1     1 
              818  LOAD_CODE                <code_object __repr__>
              820  LOAD_STR                 'Application.__repr__'
              822  MAKE_FUNCTION_4          'annotation'
              824  STORE_NAME               __repr__

 L. 510       826  LOAD_NAME                bool
              828  LOAD_CONST               ('return',)
              830  BUILD_CONST_KEY_MAP_1     1 
              832  LOAD_CODE                <code_object __bool__>
              834  LOAD_STR                 'Application.__bool__'
              836  MAKE_FUNCTION_4          'annotation'
              838  STORE_NAME               __bool__
              840  LOAD_CLOSURE             '__class__'
              842  DUP_TOP          
              844  STORE_NAME               __classcell__
              846  RETURN_VALUE     
               -1  RETURN_LAST      

Parse error at or near `CALL_FINALLY' instruction at offset 14

Instruction context:
   
 L.  82        10  BUILD_LIST_0          0 
                  12  LOAD_CONST               ('logger', '_debug', '_router', '_loop', '_handler_args', '_middlewares', '_middlewares_handlers', '_run_middlewares', '_state', '_frozen', '_pre_frozen', '_subapps', '_on_response_prepare', '_on_startup', '_on_shutdown', '_on_cleanup', '_client_max_size', '_cleanup_ctx')
->                14  CALL_FINALLY         17  'to 17'

test/134344.pyc -- 
# decompile failed
