Instruction context:
   
 L. 269        14  LOAD_FAST                'self'
                  16  LOAD_ATTR                _current_app
                  18  LOAD_CONST               None
->                20  <117>                 0  ''
                  22  POP_JUMP_IF_FALSE    30  'to 30'
Instruction context:
   
 L. 276         6  LOAD_FAST                'app'
                   8  LOAD_CONST               None
->                10  <117>                 1  ''
                  12  POP_JUMP_IF_TRUE     18  'to 18'
                  14  <74>             
                  16  RAISE_VARARGS_1       1  'exception instance'
                18_0  COME_FROM            12  '12'
Instruction context:
   
 L. 282         4  LOAD_FAST                'app'
                   6  LOAD_FAST                'self'
                   8  LOAD_ATTR                _apps
->                10  <118>                 1  ''
                  12  POP_JUMP_IF_FALSE    32  'to 32'
Instruction context:
   
 L. 357         6  CALL_FUNCTION_2       2  ''
                   8  POP_JUMP_IF_TRUE     24  'to 24'
->                10  <74>             
Instruction context:
   
 L. 366        20  LOAD_FAST                'match_dict'
                  22  LOAD_CONST               None
->                24  <117>                 0  ''
                  26  POP_JUMP_IF_FALSE    36  'to 36'
Instruction context:
   
 L. 394        14  LOAD_FAST                'path'
                  16  POP_JUMP_IF_FALSE    32  'to 32'
                  18  LOAD_FAST                'path'
                  20  LOAD_METHOD              startswith
                  22  LOAD_STR                 '/'
                  24  CALL_METHOD_1         1  ''
                  26  POP_JUMP_IF_TRUE     32  'to 32'
->                28  <74>             
                  30  RAISE_VARARGS_1       1  'exception instance'
                32_0  COME_FROM            26  '26'
                32_1  COME_FROM            16  '16'
Instruction context:
   
 L. 451       116  LOAD_FAST                'pattern'
                 118  LOAD_STR                 '(?P<{var}>{re})'
                 120  LOAD_ATTR                format
                 122  BUILD_TUPLE_0         0 
                 124  BUILD_MAP_0           0 
                 126  LOAD_FAST                'match'
                 128  LOAD_METHOD              groupdict
                 130  CALL_METHOD_0         0  ''
->               132  <164>                 1  ''
                 134  CALL_FUNCTION_EX_KW     1  'keyword and positional arguments'
                 136  INPLACE_ADD      
                 138  STORE_FAST               'pattern'
Instruction context:
   
 L. 484        12  LOAD_FAST                'match'
                  14  LOAD_CONST               None
->                16  <117>                 0  ''
                  18  POP_JUMP_IF_FALSE    24  'to 24'
Instruction context:
   
 L. 554        88  DUP_TOP          
                  90  LOAD_GLOBAL              FileNotFoundError
                  92  LOAD_GLOBAL              ValueError
                  94  BUILD_TUPLE_2         2 
->                96  <121>               144  ''
                  98  POP_TOP          
                 100  STORE_FAST               'error'
                 102  POP_TOP          
                 104  SETUP_FINALLY       136  'to 136'
Instruction context:
   
 L. 638        46  LOAD_FAST                'method'
                  48  LOAD_FAST                'allowed_methods'
->                50  <118>                 1  ''
                  52  POP_JUMP_IF_FALSE    62  'to 62'
Instruction context:
   
 L. 662        70  DUP_TOP          
                  72  LOAD_GLOBAL              ValueError
                  74  LOAD_GLOBAL              FileNotFoundError
                  76  BUILD_TUPLE_2         2 
->                78  <121>               116  ''
                  80  POP_TOP          
                  82  STORE_FAST               'error'
                  84  POP_TOP          
                  86  SETUP_FINALLY       108  'to 108'
Instruction context:
   
 L. 807        46  LOAD_STR                 '://'
                  48  LOAD_FAST                'domain'
->                50  <118>                 0  ''
                  52  POP_JUMP_IF_FALSE    62  'to 62'
Instruction context:
   
 L.1005        42  LOAD_FAST                'match_dict'
                  44  LOAD_CONST               None
->                46  <117>                 1  ''
                  48  POP_JUMP_IF_FALSE    58  'to 58'
Instruction context:
   
 L.1037         6  CALL_FUNCTION_2       2  ''
                   8  POP_JUMP_IF_TRUE     24  'to 24'
->                10  <74>             
Instruction context:
   
 L.1077        68  LOAD_STR                 '{'
                  70  LOAD_FAST                'path'
->                72  <118>                 0  ''
                  74  POP_JUMP_IF_TRUE    124  'to 124'
                  76  LOAD_STR                 '}'
                  78  LOAD_FAST                'path'
                  80  <118>                 0  ''
                  82  POP_JUMP_IF_TRUE    124  'to 124'
                  84  LOAD_GLOBAL              ROUTE_RE
                  86  LOAD_METHOD              search
                  88  LOAD_FAST                'path'
                  90  CALL_METHOD_1         1  ''
                  92  POP_JUMP_IF_TRUE    124  'to 124'
Instruction context:
   
 L.1160        18  LOAD_FAST                'resource'
                  20  LOAD_ATTR                add_route
                  22  LOAD_GLOBAL              hdrs
                  24  LOAD_ATTR                METH_HEAD
                  26  LOAD_FAST                'handler'
                  28  BUILD_TUPLE_2         2 
                  30  BUILD_MAP_0           0 
                  32  LOAD_FAST                'kwargs'
->                34  <164>                 1  ''
                  36  CALL_FUNCTION_EX_KW     1  'keyword and positional arguments'
                  38  POP_TOP          
                40_0  COME_FROM            16  '16'
Instruction context:
   
 L.1231         8  LOAD_STR                 '%'
                  10  LOAD_FAST                'value'
->                12  <118>                 0  ''
                  14  POP_JUMP_IF_FALSE    28  'to 28'

test/134355.pyc -- 
# decompile failed

# file test/134355.pyc
# Deparsing stopped due to parse error
