
# file test/134321.pyc
# --- This code section failed: ---

 L.   1         0  LOAD_CONST               0
                2  LOAD_CONST               None
                4  IMPORT_NAME              asyncio
                6  STORE_NAME               asyncio

 L.   2         8  LOAD_CONST               0
               10  LOAD_CONST               None
               12  IMPORT_NAME              functools
               14  STORE_NAME               functools

 L.   3        16  LOAD_CONST               0
               18  LOAD_CONST               None
               20  IMPORT_NAME              random
               22  STORE_NAME               random

 L.   4        24  LOAD_CONST               0
               26  LOAD_CONST               None
               28  IMPORT_NAME              sys
               30  STORE_NAME               sys

 L.   5        32  LOAD_CONST               0
               34  LOAD_CONST               None
               36  IMPORT_NAME              traceback
               38  STORE_NAME               traceback

 L.   6        40  LOAD_CONST               0
               42  LOAD_CONST               None
               44  IMPORT_NAME              warnings
               46  STORE_NAME               warnings

 L.   7        48  LOAD_CONST               0
               50  LOAD_CONST               ('defaultdict', 'deque')
               52  IMPORT_NAME              collections
               54  IMPORT_FROM              defaultdict
               56  STORE_NAME               defaultdict
               58  IMPORT_FROM              deque
               60  STORE_NAME               deque
               62  POP_TOP          

 L.   8        64  LOAD_CONST               0
               66  LOAD_CONST               ('suppress',)
               68  IMPORT_NAME              contextlib
               70  IMPORT_FROM              suppress
               72  STORE_NAME               suppress
               74  POP_TOP          

 L.   9        76  LOAD_CONST               0
               78  LOAD_CONST               ('SimpleCookie',)
               80  IMPORT_NAME_ATTR         http.cookies
               82  IMPORT_FROM              SimpleCookie
               84  STORE_NAME               SimpleCookie
               86  POP_TOP          

 L.  10        88  LOAD_CONST               0
               90  LOAD_CONST               ('cycle', 'islice')
               92  IMPORT_NAME              itertools
               94  IMPORT_FROM              cycle
               96  STORE_NAME               cycle
               98  IMPORT_FROM              islice
              100  STORE_NAME               islice
              102  POP_TOP          

 L.  11       104  LOAD_CONST               0
              106  LOAD_CONST               ('monotonic',)
              108  IMPORT_NAME              time
              110  IMPORT_FROM              monotonic
              112  STORE_NAME               monotonic
              114  POP_TOP          

 L.  12       116  LOAD_CONST               0
              118  LOAD_CONST               ('TracebackType',)
              120  IMPORT_NAME              types
              122  IMPORT_FROM              TracebackType
              124  STORE_NAME               TracebackType
              126  POP_TOP          

 L.  13       128  LOAD_CONST               0
              130  LOAD_CONST               ('TYPE_CHECKING', 'Any', 'Awaitable', 'Callable', 'DefaultDict', 'Dict', 'Iterator', 'List', 'Optional', 'Set', 'Tuple', 'Type', 'Union', 'cast')
              132  IMPORT_NAME              typing
              134  IMPORT_FROM              TYPE_CHECKING
              136  STORE_NAME               TYPE_CHECKING
              138  IMPORT_FROM              Any
              140  STORE_NAME               Any
              142  IMPORT_FROM              Awaitable
              144  STORE_NAME               Awaitable
              146  IMPORT_FROM              Callable
              148  STORE_NAME               Callable
              150  IMPORT_FROM              DefaultDict
              152  STORE_NAME               DefaultDict
              154  IMPORT_FROM              Dict
              156  STORE_NAME               Dict
              158  IMPORT_FROM              Iterator
              160  STORE_NAME               Iterator
              162  IMPORT_FROM              List
              164  STORE_NAME               List
              166  IMPORT_FROM              Optional
              168  STORE_NAME               Optional
              170  IMPORT_FROM              Set
              172  STORE_NAME               Set
              174  IMPORT_FROM              Tuple
              176  STORE_NAME               Tuple
              178  IMPORT_FROM              Type
              180  STORE_NAME               Type
              182  IMPORT_FROM              Union
              184  STORE_NAME               Union
              186  IMPORT_FROM              cast
              188  STORE_NAME               cast
              190  POP_TOP          

 L.  30       192  LOAD_CONST               0
              194  LOAD_CONST               None
              196  IMPORT_NAME              attr
              198  STORE_NAME               attr

 L.  32       200  LOAD_CONST               1
              202  LOAD_CONST               ('hdrs', 'helpers')
              204  IMPORT_NAME              
              206  IMPORT_FROM              hdrs
              208  STORE_NAME               hdrs
              210  IMPORT_FROM              helpers
              212  STORE_NAME               helpers
              214  POP_TOP          

 L.  33       216  LOAD_CONST               1
              218  LOAD_CONST               ('AbstractResolver',)
              220  IMPORT_NAME              abc
              222  IMPORT_FROM              AbstractResolver
              224  STORE_NAME               AbstractResolver
              226  POP_TOP          

 L.  34       228  LOAD_CONST               1
              230  LOAD_CONST               ('ClientConnectionError', 'ClientConnectorCertificateError', 'ClientConnectorError', 'ClientConnectorSSLError', 'ClientHttpProxyError', 'ClientProxyConnectionError', 'ServerFingerprintMismatch', 'cert_errors', 'ssl_errors')
              232  IMPORT_NAME              client_exceptions
              234  IMPORT_FROM              ClientConnectionError
              236  STORE_NAME               ClientConnectionError
              238  IMPORT_FROM              ClientConnectorCertificateError
              240  STORE_NAME               ClientConnectorCertificateError
              242  IMPORT_FROM              ClientConnectorError
              244  STORE_NAME               ClientConnectorError
              246  IMPORT_FROM              ClientConnectorSSLError
              248  STORE_NAME               ClientConnectorSSLError
              250  IMPORT_FROM              ClientHttpProxyError
              252  STORE_NAME               ClientHttpProxyError
              254  IMPORT_FROM              ClientProxyConnectionError
              256  STORE_NAME               ClientProxyConnectionError
              258  IMPORT_FROM              ServerFingerprintMismatch
              260  STORE_NAME               ServerFingerprintMismatch
              262  IMPORT_FROM              cert_errors
              264  STORE_NAME               cert_errors
              266  IMPORT_FROM              ssl_errors
              268  STORE_NAME               ssl_errors
              270  POP_TOP          

 L.  45       272  LOAD_CONST               1
              274  LOAD_CONST               ('ResponseHandler',)
              276  IMPORT_NAME              client_proto
              278  IMPORT_FROM              ResponseHandler
              280  STORE_NAME               ResponseHandler
              282  POP_TOP          

 L.  46       284  LOAD_CONST               1
              286  LOAD_CONST               ('ClientRequest', 'Fingerprint', '_merge_ssl_params')
              288  IMPORT_NAME              client_reqrep
              290  IMPORT_FROM              ClientRequest
              292  STORE_NAME               ClientRequest
              294  IMPORT_FROM              Fingerprint
              296  STORE_NAME               Fingerprint
              298  IMPORT_FROM              _merge_ssl_params
              300  STORE_NAME               _merge_ssl_params
              302  POP_TOP          

 L.  47       304  LOAD_CONST               1
              306  LOAD_CONST               ('PY_36', 'CeilTimeout', 'get_running_loop', 'is_ip_address', 'noop', 'sentinel')
              308  IMPORT_NAME              helpers
              310  IMPORT_FROM              PY_36
              312  STORE_NAME               PY_36
              314  IMPORT_FROM              CeilTimeout
              316  STORE_NAME               CeilTimeout
              318  IMPORT_FROM              get_running_loop
              320  STORE_NAME               get_running_loop
              322  IMPORT_FROM              is_ip_address
              324  STORE_NAME               is_ip_address
              326  IMPORT_FROM              noop
              328  STORE_NAME               noop
              330  IMPORT_FROM              sentinel
              332  STORE_NAME               sentinel
              334  POP_TOP          

 L.  48       336  LOAD_CONST               1
              338  LOAD_CONST               ('RESPONSES',)
              340  IMPORT_NAME              http
              342  IMPORT_FROM              RESPONSES
              344  STORE_NAME               RESPONSES
              346  POP_TOP          

 L.  49       348  LOAD_CONST               1
              350  LOAD_CONST               ('EventResultOrError',)
              352  IMPORT_NAME              locks
              354  IMPORT_FROM              EventResultOrError
              356  STORE_NAME               EventResultOrError
              358  POP_TOP          

 L.  50       360  LOAD_CONST               1
              362  LOAD_CONST               ('DefaultResolver',)
              364  IMPORT_NAME              resolver
              366  IMPORT_FROM              DefaultResolver
              368  STORE_NAME               DefaultResolver
              370  POP_TOP          

 L.  52       372  SETUP_FINALLY       392  'to 392'

 L.  53       374  LOAD_CONST               0
              376  LOAD_CONST               None
              378  IMPORT_NAME              ssl
              380  STORE_NAME               ssl

 L.  55       382  LOAD_NAME                ssl
              384  LOAD_ATTR                SSLContext
              386  STORE_NAME               SSLContext
              388  POP_BLOCK        
              390  JUMP_FORWARD        420  'to 420'
            392_0  COME_FROM_FINALLY   372  '372'

 L.  56       392  DUP_TOP          
              394  LOAD_NAME                ImportError
          396_398  <121>               418  ''
              400  POP_TOP          
              402  POP_TOP          
              404  POP_TOP          

 L.  57       406  LOAD_CONST               None
              408  STORE_NAME               ssl

 L.  58       410  LOAD_NAME                object
              412  STORE_NAME               SSLContext
              414  POP_EXCEPT       
              416  JUMP_FORWARD        420  'to 420'
              418  <48>             
            420_0  COME_FROM           416  '416'
            420_1  COME_FROM           390  '390'

 L.  61       420  LOAD_CONST               ('BaseConnector', 'TCPConnector', 'UnixConnector', 'NamedPipeConnector')
              422  STORE_NAME               __all__

 L.  64       424  LOAD_NAME                TYPE_CHECKING
          426_428  POP_JUMP_IF_FALSE   466  'to 466'

 L.  65       430  LOAD_CONST               1
              432  LOAD_CONST               ('ClientTimeout',)
              434  IMPORT_NAME              client
              436  IMPORT_FROM              ClientTimeout
              438  STORE_NAME               ClientTimeout
              440  POP_TOP          

 L.  66       442  LOAD_CONST               1
              444  LOAD_CONST               ('ConnectionKey',)
              446  IMPORT_NAME              client_reqrep
              448  IMPORT_FROM              ConnectionKey
              450  STORE_NAME               ConnectionKey
              452  POP_TOP          

 L.  67       454  LOAD_CONST               1
              456  LOAD_CONST               ('Trace',)
              458  IMPORT_NAME              tracing
              460  IMPORT_FROM              Trace
              462  STORE_NAME               Trace
              464  POP_TOP          
            466_0  COME_FROM           426  '426'

 L.  70       466  LOAD_BUILD_CLASS 
              468  LOAD_CODE                <code_object _DeprecationWaiter>
              470  LOAD_STR                 '_DeprecationWaiter'
              472  MAKE_FUNCTION_0          'Neither defaults, keyword-only args, annotations, nor closures'
              474  LOAD_STR                 '_DeprecationWaiter'
              476  CALL_FUNCTION_2       2  ''
              478  STORE_NAME               _DeprecationWaiter

 L.  90       480  LOAD_BUILD_CLASS 
              482  LOAD_CODE                <code_object Connection>
              484  LOAD_STR                 'Connection'
              486  MAKE_FUNCTION_0          'Neither defaults, keyword-only args, annotations, nor closures'
              488  LOAD_STR                 'Connection'
              490  CALL_FUNCTION_2       2  ''
              492  STORE_NAME               Connection

 L. 180       494  LOAD_BUILD_CLASS 
              496  LOAD_CODE                <code_object _TransportPlaceholder>
              498  LOAD_STR                 '_TransportPlaceholder'
              500  MAKE_FUNCTION_0          'Neither defaults, keyword-only args, annotations, nor closures'
              502  LOAD_STR                 '_TransportPlaceholder'
              504  CALL_FUNCTION_2       2  ''
              506  STORE_NAME               _TransportPlaceholder

 L. 187       508  LOAD_BUILD_CLASS 
              510  LOAD_CODE                <code_object BaseConnector>
              512  LOAD_STR                 'BaseConnector'
              514  MAKE_FUNCTION_0          'Neither defaults, keyword-only args, annotations, nor closures'
              516  LOAD_STR                 'BaseConnector'
              518  CALL_FUNCTION_2       2  ''
              520  STORE_NAME               BaseConnector

 L. 671       522  LOAD_BUILD_CLASS 
              524  LOAD_CODE                <code_object _DNSCacheTable>
              526  LOAD_STR                 '_DNSCacheTable'
              528  MAKE_FUNCTION_0          'Neither defaults, keyword-only args, annotations, nor closures'
              530  LOAD_STR                 '_DNSCacheTable'
              532  CALL_FUNCTION_2       2  ''
              534  STORE_NAME               _DNSCacheTable

 L. 712       536  LOAD_BUILD_CLASS 
              538  LOAD_CODE                <code_object TCPConnector>
              540  LOAD_STR                 'TCPConnector'
              542  MAKE_FUNCTION_0          'Neither defaults, keyword-only args, annotations, nor closures'
              544  LOAD_STR                 'TCPConnector'
              546  LOAD_NAME                BaseConnector
              548  CALL_FUNCTION_3       3  ''
              550  STORE_NAME               TCPConnector

 L.1153       552  LOAD_BUILD_CLASS 
              554  LOAD_CODE                <code_object UnixConnector>
              556  LOAD_STR                 'UnixConnector'
              558  MAKE_FUNCTION_0          'Neither defaults, keyword-only args, annotations, nor closures'
              560  LOAD_STR                 'UnixConnector'
              562  LOAD_NAME                BaseConnector
              564  CALL_FUNCTION_3       3  ''
              566  STORE_NAME               UnixConnector

 L.1202       568  LOAD_BUILD_CLASS 
              570  LOAD_CODE                <code_object NamedPipeConnector>
              572  LOAD_STR                 'NamedPipeConnector'
              574  MAKE_FUNCTION_0          'Neither defaults, keyword-only args, annotations, nor closures'
              576  LOAD_STR                 'NamedPipeConnector'
              578  LOAD_NAME                BaseConnector
              580  CALL_FUNCTION_3       3  ''
              582  STORE_NAME               NamedPipeConnector

Parse error at or near `<121>' instruction at offset 396_398

Instruction context:
   
 L.  56       392  DUP_TOP          
                 394  LOAD_NAME                ImportError
->           396_398  <121>               418  ''
                 400  POP_TOP          
                 402  POP_TOP          
                 404  POP_TOP          

test/134321.pyc -- 
# decompile failed
