
# file test/134398.pyc
# --- This code section failed: ---

 L.   1         0  LOAD_CONST               0
                2  LOAD_CONST               ('absolute_import', 'division', 'print_function')
                4  IMPORT_NAME              __future__
                6  IMPORT_FROM              absolute_import
                8  STORE_NAME               absolute_import
               10  IMPORT_FROM              division
               12  STORE_NAME               division
               14  IMPORT_FROM              print_function
               16  STORE_NAME               print_function
               18  POP_TOP          

 L.   3        20  LOAD_CONST               0
               22  LOAD_CONST               None
               24  IMPORT_NAME              copy
               26  STORE_NAME               copy

 L.   4        28  LOAD_CONST               0
               30  LOAD_CONST               None
               32  IMPORT_NAME              inspect
               34  STORE_NAME               inspect

 L.   5        36  LOAD_CONST               0
               38  LOAD_CONST               None
               40  IMPORT_NAME              linecache
               42  STORE_NAME               linecache

 L.   6        44  LOAD_CONST               0
               46  LOAD_CONST               None
               48  IMPORT_NAME              sys
               50  STORE_NAME               sys

 L.   7        52  LOAD_CONST               0
               54  LOAD_CONST               None
               56  IMPORT_NAME              threading
               58  STORE_NAME               threading

 L.   8        60  LOAD_CONST               0
               62  LOAD_CONST               None
               64  IMPORT_NAME              uuid
               66  STORE_NAME               uuid

 L.   9        68  LOAD_CONST               0
               70  LOAD_CONST               None
               72  IMPORT_NAME              warnings
               74  STORE_NAME               warnings

 L.  11        76  LOAD_CONST               0
               78  LOAD_CONST               ('itemgetter',)
               80  IMPORT_NAME              operator
               82  IMPORT_FROM              itemgetter
               84  STORE_NAME               itemgetter
               86  POP_TOP          

 L.  13        88  LOAD_CONST               1
               90  LOAD_CONST               ('_config', 'setters')
               92  IMPORT_NAME              
               94  IMPORT_FROM              _config
               96  STORE_NAME               _config
               98  IMPORT_FROM              setters
              100  STORE_NAME               setters
              102  POP_TOP          

 L.  14       104  LOAD_CONST               1
              106  LOAD_CONST               ('PY2', 'PYPY', 'isclass', 'iteritems', 'metadata_proxy', 'new_class', 'ordered_dict', 'set_closure_cell')
              108  IMPORT_NAME              _compat
              110  IMPORT_FROM              PY2
              112  STORE_NAME               PY2
              114  IMPORT_FROM              PYPY
              116  STORE_NAME               PYPY
              118  IMPORT_FROM              isclass
              120  STORE_NAME               isclass
              122  IMPORT_FROM              iteritems
              124  STORE_NAME               iteritems
              126  IMPORT_FROM              metadata_proxy
              128  STORE_NAME               metadata_proxy
              130  IMPORT_FROM              new_class
              132  STORE_NAME               new_class
              134  IMPORT_FROM              ordered_dict
              136  STORE_NAME               ordered_dict
              138  IMPORT_FROM              set_closure_cell
              140  STORE_NAME               set_closure_cell
              142  POP_TOP          

 L.  24       144  LOAD_CONST               1
              146  LOAD_CONST               ('DefaultAlreadySetError', 'FrozenInstanceError', 'NotAnAttrsClassError', 'PythonTooOldError', 'UnannotatedAttributeError')
              148  IMPORT_NAME              exceptions
              150  IMPORT_FROM              DefaultAlreadySetError
              152  STORE_NAME               DefaultAlreadySetError
              154  IMPORT_FROM              FrozenInstanceError
              156  STORE_NAME               FrozenInstanceError
              158  IMPORT_FROM              NotAnAttrsClassError
              160  STORE_NAME               NotAnAttrsClassError
              162  IMPORT_FROM              PythonTooOldError
              164  STORE_NAME               PythonTooOldError
              166  IMPORT_FROM              UnannotatedAttributeError
              168  STORE_NAME               UnannotatedAttributeError
              170  POP_TOP          

 L.  33       172  LOAD_NAME                PY2
              174  POP_JUMP_IF_TRUE    184  'to 184'

 L.  34       176  LOAD_CONST               0
              178  LOAD_CONST               None
              180  IMPORT_NAME              typing
              182  STORE_NAME               typing
            184_0  COME_FROM           174  '174'

 L.  38       184  LOAD_NAME                object
              186  LOAD_ATTR                __setattr__
              188  STORE_NAME               _obj_setattr

 L.  39       190  LOAD_STR                 '__attr_converter_%s'
              192  STORE_NAME               _init_converter_pat

 L.  40       194  LOAD_STR                 '__attr_factory_{}'
              196  STORE_NAME               _init_factory_pat

 L.  42       198  LOAD_STR                 '    {attr_name} = _attrs_property(_attrs_itemgetter({index}))'

 L.  41       200  STORE_NAME               _tuple_property_pat

 L.  44       202  LOAD_CONST               ('typing.ClassVar', 't.ClassVar', 'ClassVar', 'typing_extensions.ClassVar')
              204  STORE_NAME               _classvar_prefixes

 L.  53       206  LOAD_STR                 '_attrs_cached_hash'
              208  STORE_NAME               _hash_cache_field

 L.  55       210  LOAD_NAME                metadata_proxy
              212  BUILD_MAP_0           0 
              214  CALL_FUNCTION_1       1  ''
              216  STORE_NAME               _empty_metadata_singleton

 L.  58       218  LOAD_NAME                object
              220  CALL_FUNCTION_0       0  ''
              222  STORE_NAME               _sentinel

 L.  61       224  LOAD_BUILD_CLASS 
              226  LOAD_CODE                <code_object _Nothing>
              228  LOAD_STR                 '_Nothing'
              230  MAKE_FUNCTION_0          'Neither defaults, keyword-only args, annotations, nor closures'
              232  LOAD_STR                 '_Nothing'
              234  LOAD_NAME                object
              236  CALL_FUNCTION_3       3  ''
              238  STORE_NAME               _Nothing

 L.  87       240  LOAD_NAME                _Nothing
              242  CALL_FUNCTION_0       0  ''
              244  STORE_NAME               NOTHING

 L.  93       246  LOAD_BUILD_CLASS 
              248  LOAD_CODE                <code_object _CacheHashWrapper>
              250  LOAD_STR                 '_CacheHashWrapper'
              252  MAKE_FUNCTION_0          'Neither defaults, keyword-only args, annotations, nor closures'
              254  LOAD_STR                 '_CacheHashWrapper'
              256  LOAD_NAME                int
              258  CALL_FUNCTION_3       3  ''
              260  STORE_NAME               _CacheHashWrapper

 L. 119       262  LOAD_NAME                NOTHING

 L. 120       264  LOAD_CONST               None

 L. 121       266  LOAD_CONST               True

 L. 122       268  LOAD_CONST               None

 L. 123       270  LOAD_CONST               None

 L. 124       272  LOAD_CONST               True

 L. 125       274  LOAD_CONST               None

 L. 126       276  LOAD_CONST               None

 L. 127       278  LOAD_CONST               None

 L. 128       280  LOAD_CONST               None

 L. 129       282  LOAD_CONST               False

 L. 130       284  LOAD_CONST               None

 L. 131       286  LOAD_CONST               None

 L. 132       288  LOAD_CONST               None

 L. 118       290  BUILD_TUPLE_14       14 
              292  LOAD_CODE                <code_object attrib>
              294  LOAD_STR                 'attrib'
              296  MAKE_FUNCTION_1          'default'
              298  STORE_NAME               attrib

 L. 314       300  LOAD_CONST               (None, '')
              302  LOAD_CODE                <code_object _compile_and_eval>
              304  LOAD_STR                 '_compile_and_eval'
              306  MAKE_FUNCTION_1          'default'
              308  STORE_NAME               _compile_and_eval

 L. 322       310  LOAD_CONST               (None,)
              312  LOAD_CODE                <code_object _make_method>
              314  LOAD_STR                 '_make_method'
              316  MAKE_FUNCTION_1          'default'
              318  STORE_NAME               _make_method

 L. 344       320  LOAD_CODE                <code_object _make_attr_tuple_class>
              322  LOAD_STR                 '_make_attr_tuple_class'
              324  MAKE_FUNCTION_0          'Neither defaults, keyword-only args, annotations, nor closures'
              326  STORE_NAME               _make_attr_tuple_class

 L. 373       328  LOAD_NAME                _make_attr_tuple_class

 L. 374       330  LOAD_STR                 '_Attributes'

 L. 375       332  BUILD_LIST_0          0 
              334  LOAD_CONST               ('attrs', 'base_attrs', 'base_attrs_map')
              336  CALL_FINALLY        339  'to 339'

 L. 373       338  CALL_FUNCTION_2       2  ''
              340  STORE_NAME               _Attributes

 L. 386       342  LOAD_CODE                <code_object _is_class_var>
              344  LOAD_STR                 '_is_class_var'
              346  MAKE_FUNCTION_0          'Neither defaults, keyword-only args, annotations, nor closures'
              348  STORE_NAME               _is_class_var

 L. 403       350  LOAD_CODE                <code_object _has_own_attribute>
              352  LOAD_STR                 '_has_own_attribute'
              354  MAKE_FUNCTION_0          'Neither defaults, keyword-only args, annotations, nor closures'
              356  STORE_NAME               _has_own_attribute

 L. 421       358  LOAD_CODE                <code_object _get_annotations>
              360  LOAD_STR                 '_get_annotations'
              362  MAKE_FUNCTION_0          'Neither defaults, keyword-only args, annotations, nor closures'
              364  STORE_NAME               _get_annotations

 L. 431       366  LOAD_CODE                <code_object _counter_getter>
              368  LOAD_STR                 '_counter_getter'
              370  MAKE_FUNCTION_0          'Neither defaults, keyword-only args, annotations, nor closures'
              372  STORE_NAME               _counter_getter

 L. 438       374  LOAD_CODE                <code_object _collect_base_attrs>
              376  LOAD_STR                 '_collect_base_attrs'
              378  MAKE_FUNCTION_0          'Neither defaults, keyword-only args, annotations, nor closures'
              380  STORE_NAME               _collect_base_attrs

 L. 469       382  LOAD_CODE                <code_object _collect_base_attrs_broken>
              384  LOAD_STR                 '_collect_base_attrs_broken'
              386  MAKE_FUNCTION_0          'Neither defaults, keyword-only args, annotations, nor closures'
              388  STORE_NAME               _collect_base_attrs_broken

 L. 497       390  LOAD_CODE                <code_object _transform_attrs>
              392  LOAD_STR                 '_transform_attrs'
              394  MAKE_FUNCTION_0          'Neither defaults, keyword-only args, annotations, nor closures'
              396  STORE_NAME               _transform_attrs

 L. 604       398  LOAD_NAME                PYPY
          400_402  POP_JUMP_IF_FALSE   414  'to 414'

 L. 606       404  LOAD_CODE                <code_object _frozen_setattrs>
              406  LOAD_STR                 '_frozen_setattrs'
              408  MAKE_FUNCTION_0          'Neither defaults, keyword-only args, annotations, nor closures'
              410  STORE_NAME               _frozen_setattrs
              412  JUMP_FORWARD        422  'to 422'
            414_0  COME_FROM           400  '400'

 L. 622       414  LOAD_CODE                <code_object _frozen_setattrs>
              416  LOAD_STR                 '_frozen_setattrs'
              418  MAKE_FUNCTION_0          'Neither defaults, keyword-only args, annotations, nor closures'
              420  STORE_NAME               _frozen_setattrs
            422_0  COME_FROM           412  '412'

 L. 629       422  LOAD_CODE                <code_object _frozen_delattrs>
              424  LOAD_STR                 '_frozen_delattrs'
              426  MAKE_FUNCTION_0          'Neither defaults, keyword-only args, annotations, nor closures'
              428  STORE_NAME               _frozen_delattrs

 L. 636       430  LOAD_BUILD_CLASS 
              432  LOAD_CODE                <code_object _ClassBuilder>
              434  LOAD_STR                 '_ClassBuilder'
              436  MAKE_FUNCTION_0          'Neither defaults, keyword-only args, annotations, nor closures'
              438  LOAD_STR                 '_ClassBuilder'
              440  LOAD_NAME                object
              442  CALL_FUNCTION_3       3  ''
              444  STORE_NAME               _ClassBuilder

 L.1072       446  LOAD_STR                 'The usage of `cmp` is deprecated and will be removed on or after 2021-06-01.  Please use `eq` and `order` instead.'

 L.1071       448  STORE_NAME               _CMP_DEPRECATION

 L.1077       450  LOAD_CODE                <code_object _determine_attrs_eq_order>
              452  LOAD_STR                 '_determine_attrs_eq_order'
              454  MAKE_FUNCTION_0          'Neither defaults, keyword-only args, annotations, nor closures'
              456  STORE_NAME               _determine_attrs_eq_order

 L.1103       458  LOAD_CODE                <code_object _determine_attrib_eq_order>
              460  LOAD_STR                 '_determine_attrib_eq_order'
              462  MAKE_FUNCTION_0          'Neither defaults, keyword-only args, annotations, nor closures'
              464  STORE_NAME               _determine_attrib_eq_order

 L.1144       466  LOAD_CONST               (True,)
              468  LOAD_CODE                <code_object _determine_whether_to_implement>
              470  LOAD_STR                 '_determine_whether_to_implement'
              472  MAKE_FUNCTION_1          'default'
              474  STORE_NAME               _determine_whether_to_implement

 L.1172       476  LOAD_CONST               (None, None, None, None, None, None, None, False, False, True, False, False, False, False, False, None, None, False, False, None, None, None)
              478  LOAD_CODE                <code_object attrs>
              480  LOAD_STR                 'attrs'
              482  MAKE_FUNCTION_1          'default'
              484  STORE_NAME               attrs

 L.1569       486  LOAD_NAME                attrs
              488  STORE_NAME               _attrs

 L.1576       490  LOAD_NAME                PY2
          492_494  POP_JUMP_IF_FALSE   506  'to 506'

 L.1578       496  LOAD_CODE                <code_object _has_frozen_base_class>
              498  LOAD_STR                 '_has_frozen_base_class'
              500  MAKE_FUNCTION_0          'Neither defaults, keyword-only args, annotations, nor closures'
              502  STORE_NAME               _has_frozen_base_class
              504  JUMP_FORWARD        514  'to 514'
            506_0  COME_FROM           492  '492'

 L.1592       506  LOAD_CODE                <code_object _has_frozen_base_class>
              508  LOAD_STR                 '_has_frozen_base_class'
              510  MAKE_FUNCTION_0          'Neither defaults, keyword-only args, annotations, nor closures'
              512  STORE_NAME               _has_frozen_base_class
            514_0  COME_FROM           504  '504'

 L.1600       514  LOAD_CODE                <code_object _generate_unique_filename>
              516  LOAD_STR                 '_generate_unique_filename'
              518  MAKE_FUNCTION_0          'Neither defaults, keyword-only args, annotations, nor closures'
              520  STORE_NAME               _generate_unique_filename

 L.1630       522  LOAD_CODE                <code_object _make_hash>
              524  LOAD_STR                 '_make_hash'
              526  MAKE_FUNCTION_0          'Neither defaults, keyword-only args, annotations, nor closures'
              528  STORE_NAME               _make_hash

 L.1696       530  LOAD_CODE                <code_object _add_hash>
              532  LOAD_STR                 '_add_hash'
              534  MAKE_FUNCTION_0          'Neither defaults, keyword-only args, annotations, nor closures'
              536  STORE_NAME               _add_hash

 L.1704       538  LOAD_CODE                <code_object _make_ne>
              540  LOAD_STR                 '_make_ne'
              542  MAKE_FUNCTION_0          'Neither defaults, keyword-only args, annotations, nor closures'
              544  STORE_NAME               _make_ne

 L.1723       546  LOAD_CODE                <code_object _make_eq>
              548  LOAD_STR                 '_make_eq'
              550  MAKE_FUNCTION_0          'Neither defaults, keyword-only args, annotations, nor closures'
              552  STORE_NAME               _make_eq

 L.1775       554  LOAD_CODE                <code_object _make_order>
              556  LOAD_STR                 '_make_order'
              558  MAKE_FUNCTION_0          'Neither defaults, keyword-only args, annotations, nor closures'
              560  STORE_NAME               _make_order

 L.1831       562  LOAD_CONST               (None,)
              564  LOAD_CODE                <code_object _add_eq>
              566  LOAD_STR                 '_add_eq'
              568  MAKE_FUNCTION_1          'default'
              570  STORE_NAME               _add_eq

 L.1844       572  LOAD_NAME                threading
              574  LOAD_METHOD              local
              576  CALL_METHOD_0         0  ''
              578  STORE_NAME               _already_repring

 L.1847       580  LOAD_CODE                <code_object _make_repr>
              582  LOAD_STR                 '_make_repr'
              584  MAKE_FUNCTION_0          'Neither defaults, keyword-only args, annotations, nor closures'
              586  STORE_NAME               _make_repr

 L.1906       588  LOAD_CONST               (None, None)
              590  LOAD_CODE                <code_object _add_repr>
              592  LOAD_STR                 '_add_repr'
              594  MAKE_FUNCTION_1          'default'
              596  STORE_NAME               _add_repr

 L.1917       598  LOAD_CODE                <code_object fields>
              600  LOAD_STR                 'fields'
              602  MAKE_FUNCTION_0          'Neither defaults, keyword-only args, annotations, nor closures'
              604  STORE_NAME               fields

 L.1945       606  LOAD_CODE                <code_object fields_dict>
              608  LOAD_STR                 'fields_dict'
              610  MAKE_FUNCTION_0          'Neither defaults, keyword-only args, annotations, nor closures'
              612  STORE_NAME               fields_dict

 L.1973       614  LOAD_CODE                <code_object validate>
              616  LOAD_STR                 'validate'
              618  MAKE_FUNCTION_0          'Neither defaults, keyword-only args, annotations, nor closures'
              620  STORE_NAME               validate

 L.1990       622  LOAD_CODE                <code_object _is_slot_cls>
              624  LOAD_STR                 '_is_slot_cls'
              626  MAKE_FUNCTION_0          'Neither defaults, keyword-only args, annotations, nor closures'
              628  STORE_NAME               _is_slot_cls

 L.1994       630  LOAD_CODE                <code_object _is_slot_attr>
              632  LOAD_STR                 '_is_slot_attr'
              634  MAKE_FUNCTION_0          'Neither defaults, keyword-only args, annotations, nor closures'
              636  STORE_NAME               _is_slot_attr

 L.2001       638  LOAD_CODE                <code_object _make_init>
              640  LOAD_STR                 '_make_init'
              642  MAKE_FUNCTION_0          'Neither defaults, keyword-only args, annotations, nor closures'
              644  STORE_NAME               _make_init

 L.2074       646  LOAD_CODE                <code_object _setattr>
              648  LOAD_STR                 '_setattr'
              650  MAKE_FUNCTION_0          'Neither defaults, keyword-only args, annotations, nor closures'
              652  STORE_NAME               _setattr

 L.2081       654  LOAD_CODE                <code_object _setattr_with_converter>
              656  LOAD_STR                 '_setattr_with_converter'
              658  MAKE_FUNCTION_0          'Neither defaults, keyword-only args, annotations, nor closures'
              660  STORE_NAME               _setattr_with_converter

 L.2093       662  LOAD_CODE                <code_object _assign>
              664  LOAD_STR                 '_assign'
              666  MAKE_FUNCTION_0          'Neither defaults, keyword-only args, annotations, nor closures'
              668  STORE_NAME               _assign

 L.2104       670  LOAD_CODE                <code_object _assign_with_converter>
              672  LOAD_STR                 '_assign_with_converter'
              674  MAKE_FUNCTION_0          'Neither defaults, keyword-only args, annotations, nor closures'
              676  STORE_NAME               _assign_with_converter

 L.2119       678  LOAD_NAME                PY2
          680_682  POP_JUMP_IF_FALSE   702  'to 702'

 L.2121       684  LOAD_CONST               (None,)
              686  LOAD_CODE                <code_object _unpack_kw_only_py2>
              688  LOAD_STR                 '_unpack_kw_only_py2'
              690  MAKE_FUNCTION_1          'default'
              692  STORE_NAME               _unpack_kw_only_py2

 L.2135       694  LOAD_CODE                <code_object _unpack_kw_only_lines_py2>
              696  LOAD_STR                 '_unpack_kw_only_lines_py2'
              698  MAKE_FUNCTION_0          'Neither defaults, keyword-only args, annotations, nor closures'
              700  STORE_NAME               _unpack_kw_only_lines_py2
            702_0  COME_FROM           680  '680'

 L.2176       702  LOAD_CODE                <code_object _attrs_to_init_script>
              704  LOAD_STR                 '_attrs_to_init_script'
              706  MAKE_FUNCTION_0          'Neither defaults, keyword-only args, annotations, nor closures'
              708  STORE_NAME               _attrs_to_init_script

 L.2473       710  LOAD_BUILD_CLASS 
              712  LOAD_CODE                <code_object Attribute>
              714  LOAD_STR                 'Attribute'
              716  MAKE_FUNCTION_0          'Neither defaults, keyword-only args, annotations, nor closures'
              718  LOAD_STR                 'Attribute'
              720  LOAD_NAME                object
              722  CALL_FUNCTION_3       3  ''
              724  STORE_NAME               Attribute

 L.2663       726  LOAD_LISTCOMP            '<code_object <listcomp>>'
              728  LOAD_STR                 '<listcomp>'
              730  MAKE_FUNCTION_0          'Neither defaults, keyword-only args, annotations, nor closures'

 L.2676       732  LOAD_NAME                Attribute
              734  LOAD_ATTR                __slots__

 L.2663       736  GET_ITER         
              738  CALL_FUNCTION_1       1  ''
              740  STORE_NAME               _a

 L.2679       742  LOAD_NAME                _add_hash

 L.2680       744  LOAD_NAME                _add_eq

 L.2681       746  LOAD_NAME                _add_repr
              748  LOAD_NAME                Attribute
              750  LOAD_NAME                _a
              752  LOAD_CONST               ('attrs',)
              754  CALL_FUNCTION_KW_2     2  '2 total positional and keyword args'

 L.2682       756  LOAD_LISTCOMP            '<code_object <listcomp>>'
              758  LOAD_STR                 '<listcomp>'
              760  MAKE_FUNCTION_0          'Neither defaults, keyword-only args, annotations, nor closures'
              762  LOAD_NAME                _a
              764  GET_ITER         
              766  CALL_FUNCTION_1       1  ''

 L.2680       768  LOAD_CONST               ('attrs',)
              770  CALL_FUNCTION_KW_2     2  '2 total positional and keyword args'

 L.2684       772  LOAD_LISTCOMP            '<code_object <listcomp>>'
              774  LOAD_STR                 '<listcomp>'
              776  MAKE_FUNCTION_0          'Neither defaults, keyword-only args, annotations, nor closures'
              778  LOAD_NAME                _a
              780  GET_ITER         
              782  CALL_FUNCTION_1       1  ''

 L.2679       784  LOAD_CONST               ('attrs',)
              786  CALL_FUNCTION_KW_2     2  '2 total positional and keyword args'
              788  STORE_NAME               Attribute

 L.2688       790  LOAD_BUILD_CLASS 
              792  LOAD_CODE                <code_object _CountingAttr>
              794  LOAD_STR                 '_CountingAttr'
              796  MAKE_FUNCTION_0          'Neither defaults, keyword-only args, annotations, nor closures'
              798  LOAD_STR                 '_CountingAttr'
              800  LOAD_NAME                object
              802  CALL_FUNCTION_3       3  ''
              804  STORE_NAME               _CountingAttr

 L.2828       806  LOAD_NAME                _add_eq
              808  LOAD_NAME                _add_repr
              810  LOAD_NAME                _CountingAttr
              812  CALL_FUNCTION_1       1  ''
              814  CALL_FUNCTION_1       1  ''
              816  STORE_NAME               _CountingAttr

 L.2831       818  LOAD_BUILD_CLASS 
              820  LOAD_CODE                <code_object Factory>
              822  LOAD_STR                 'Factory'
              824  MAKE_FUNCTION_0          'Neither defaults, keyword-only args, annotations, nor closures'
              826  LOAD_STR                 'Factory'
              828  LOAD_NAME                object
              830  CALL_FUNCTION_3       3  ''
              832  STORE_NAME               Factory

 L.2870       834  LOAD_LISTCOMP            '<code_object <listcomp>>'
              836  LOAD_STR                 '<listcomp>'
              838  MAKE_FUNCTION_0          'Neither defaults, keyword-only args, annotations, nor closures'

 L.2883       840  LOAD_NAME                Factory
              842  LOAD_ATTR                __slots__

 L.2870       844  GET_ITER         
              846  CALL_FUNCTION_1       1  ''
              848  STORE_NAME               _f

 L.2886       850  LOAD_NAME                _add_hash
              852  LOAD_NAME                _add_eq
              854  LOAD_NAME                _add_repr
              856  LOAD_NAME                Factory
              858  LOAD_NAME                _f
              860  LOAD_CONST               ('attrs',)
              862  CALL_FUNCTION_KW_2     2  '2 total positional and keyword args'
              864  LOAD_NAME                _f
              866  LOAD_CONST               ('attrs',)
              868  CALL_FUNCTION_KW_2     2  '2 total positional and keyword args'
              870  LOAD_NAME                _f
              872  LOAD_CONST               ('attrs',)
              874  CALL_FUNCTION_KW_2     2  '2 total positional and keyword args'
              876  STORE_NAME               Factory

 L.2889       878  LOAD_NAME                object
              880  BUILD_TUPLE_1         1 
              882  BUILD_TUPLE_1         1 
              884  LOAD_CODE                <code_object make_class>
              886  LOAD_STR                 'make_class'
              888  MAKE_FUNCTION_1          'default'
              890  STORE_NAME               make_class

 L.2965       892  LOAD_NAME                attrs
              894  LOAD_CONST               True
              896  LOAD_CONST               True
              898  LOAD_CONST               ('slots', 'hash')
              900  CALL_FUNCTION_KW_2     2  '2 total positional and keyword args'

 L.2966       902  LOAD_BUILD_CLASS 
              904  LOAD_CODE                <code_object _AndValidator>
              906  LOAD_STR                 '_AndValidator'
              908  MAKE_FUNCTION_0          'Neither defaults, keyword-only args, annotations, nor closures'
              910  LOAD_STR                 '_AndValidator'
              912  LOAD_NAME                object
              914  CALL_FUNCTION_3       3  ''
              916  CALL_FUNCTION_1       1  ''
              918  STORE_NAME               _AndValidator

 L.2978       920  LOAD_CODE                <code_object and_>
              922  LOAD_STR                 'and_'
              924  MAKE_FUNCTION_0          'Neither defaults, keyword-only args, annotations, nor closures'
              926  STORE_NAME               and_

 L.2999       928  LOAD_CODE                <code_object pipe>
              930  LOAD_STR                 'pipe'
              932  MAKE_FUNCTION_0          'Neither defaults, keyword-only args, annotations, nor closures'
              934  STORE_NAME               pipe

Parse error at or near `CALL_FINALLY' instruction at offset 336

Instruction context:
   
 L. 375       332  BUILD_LIST_0          0 
                 334  LOAD_CONST               ('attrs', 'base_attrs', 'base_attrs_map')
->               336  CALL_FINALLY        339  'to 339'

test/134398.pyc -- 
# decompile failed
