Instruction context:
   
 L.   6        32  BUILD_LIST_0          0 
                  34  LOAD_CONST               ('DBusAddress', 'new_method_call', 'new_method_return', 'new_error', 'new_signal', 'MessageGenerator', 'Properties', 'Introspectable', 'DBusErrorResponse')
->                36  CALL_FINALLY         39  'to 39'
                  38  STORE_NAME               __all__

test/134662.pyc -- 
# decompile failed

# file test/134662.pyc
# --- This code section failed: ---

 L.   1         0  LOAD_CONST               0
                2  LOAD_CONST               ('Union',)
                4  IMPORT_NAME              typing
                6  IMPORT_FROM              Union
                8  STORE_NAME               Union
               10  POP_TOP          

 L.   2        12  LOAD_CONST               0
               14  LOAD_CONST               ('warn',)
               16  IMPORT_NAME              warnings
               18  IMPORT_FROM              warn
               20  STORE_NAME               warn
               22  POP_TOP          

 L.   4        24  LOAD_CONST               1
               26  LOAD_CONST               ('*',)
               28  IMPORT_NAME              low_level
               30  IMPORT_STAR      

 L.   6        32  BUILD_LIST_0          0 
               34  LOAD_CONST               ('DBusAddress', 'new_method_call', 'new_method_return', 'new_error', 'new_signal', 'MessageGenerator', 'Properties', 'Introspectable', 'DBusErrorResponse')
               36  CALL_FINALLY         39  'to 39'
               38  STORE_NAME               __all__

 L.  18        40  LOAD_BUILD_CLASS 
               42  LOAD_CODE                <code_object DBusAddress>
               44  LOAD_STR                 'DBusAddress'
               46  MAKE_FUNCTION_0          'Neither defaults, keyword-only args, annotations, nor closures'
               48  LOAD_STR                 'DBusAddress'
               50  CALL_FUNCTION_2       2  ''
               52  STORE_NAME               DBusAddress

 L.  39        54  LOAD_BUILD_CLASS 
               56  LOAD_CODE                <code_object DBusObject>
               58  LOAD_STR                 'DBusObject'
               60  MAKE_FUNCTION_0          'Neither defaults, keyword-only args, annotations, nor closures'
               62  LOAD_STR                 'DBusObject'
               64  LOAD_NAME                DBusAddress
               66  CALL_FUNCTION_3       3  ''
               68  STORE_NAME               DBusObject

 L.  44        70  LOAD_CODE                <code_object new_header>
               72  LOAD_STR                 'new_header'
               74  MAKE_FUNCTION_0          'Neither defaults, keyword-only args, annotations, nor closures'
               76  STORE_NAME               new_header

 L.  48        78  LOAD_CONST               (None, ())
               80  LOAD_CODE                <code_object new_method_call>
               82  LOAD_STR                 'new_method_call'
               84  MAKE_FUNCTION_1          'default'
               86  STORE_NAME               new_method_call

 L.  73        88  LOAD_CONST               (None, ())
               90  LOAD_CODE                <code_object new_method_return>
               92  LOAD_STR                 'new_method_return'
               94  MAKE_FUNCTION_1          'default'
               96  STORE_NAME               new_method_return

 L.  89        98  LOAD_CONST               (None, ())
              100  LOAD_CODE                <code_object new_error>
              102  LOAD_STR                 'new_error'
              104  MAKE_FUNCTION_1          'default'
              106  STORE_NAME               new_error

 L. 107       108  LOAD_CONST               (None, ())
              110  LOAD_CODE                <code_object new_signal>
              112  LOAD_STR                 'new_signal'
              114  MAKE_FUNCTION_1          'default'
              116  STORE_NAME               new_signal

 L. 126       118  LOAD_BUILD_CLASS 
              120  LOAD_CODE                <code_object MessageGenerator>
              122  LOAD_STR                 'MessageGenerator'
              124  MAKE_FUNCTION_0          'Neither defaults, keyword-only args, annotations, nor closures'
              126  LOAD_STR                 'MessageGenerator'
              128  CALL_FUNCTION_2       2  ''
              130  STORE_NAME               MessageGenerator

 L. 140       132  LOAD_BUILD_CLASS 
              134  LOAD_CODE                <code_object ProxyBase>
              136  LOAD_STR                 'ProxyBase'
              138  MAKE_FUNCTION_0          'Neither defaults, keyword-only args, annotations, nor closures'
              140  LOAD_STR                 'ProxyBase'
              142  CALL_FUNCTION_2       2  ''
              144  STORE_NAME               ProxyBase

 L. 162       146  LOAD_BUILD_CLASS 
              148  LOAD_CODE                <code_object Properties>
              150  LOAD_STR                 'Properties'
              152  MAKE_FUNCTION_0          'Neither defaults, keyword-only args, annotations, nor closures'
              154  LOAD_STR                 'Properties'
              156  CALL_FUNCTION_2       2  ''
              158  STORE_NAME               Properties

 L. 190       160  LOAD_BUILD_CLASS 
              162  LOAD_CODE                <code_object Introspectable>
              164  LOAD_STR                 'Introspectable'
              166  MAKE_FUNCTION_0          'Neither defaults, keyword-only args, annotations, nor closures'
              168  LOAD_STR                 'Introspectable'
              170  LOAD_NAME                MessageGenerator
              172  CALL_FUNCTION_3       3  ''
              174  STORE_NAME               Introspectable

 L. 197       176  LOAD_BUILD_CLASS 
              178  LOAD_CODE                <code_object DBusErrorResponse>
              180  LOAD_STR                 'DBusErrorResponse'
              182  MAKE_FUNCTION_0          'Neither defaults, keyword-only args, annotations, nor closures'
              184  LOAD_STR                 'DBusErrorResponse'
              186  LOAD_NAME                Exception
              188  CALL_FUNCTION_3       3  ''
              190  STORE_NAME               DBusErrorResponse

 L. 207       192  LOAD_NAME                Message
              194  LOAD_CONST               ('msg',)
              196  BUILD_CONST_KEY_MAP_1     1 
              198  LOAD_CODE                <code_object unwrap_msg>
              200  LOAD_STR                 'unwrap_msg'
              202  MAKE_FUNCTION_4          'annotation'
              204  STORE_NAME               unwrap_msg

Parse error at or near `CALL_FINALLY' instruction at offset 36

