Instruction context:
   
 L.   8        40  BUILD_LIST_0          0 
                  42  LOAD_CONST               ('DBusNameFlags', 'DBus', 'message_bus', 'Monitoring', 'Stats', 'MatchRule')
->                44  CALL_FINALLY         47  'to 47'
                  46  STORE_NAME               __all__

test/134659.pyc -- 
# decompile failed

# file test/134659.pyc
# --- This code section failed: ---

 L.   1         0  LOAD_STR                 'Messages for talking to the DBus daemon itself\n\nGenerated by jeepney.bindgen and modified by hand.\n'
                2  STORE_NAME               __doc__

 L.   5         4  LOAD_CONST               1
                6  LOAD_CONST               ('Message', 'MessageType', 'HeaderFields')
                8  IMPORT_NAME              low_level
               10  IMPORT_FROM              Message
               12  STORE_NAME               Message
               14  IMPORT_FROM              MessageType
               16  STORE_NAME               MessageType
               18  IMPORT_FROM              HeaderFields
               20  STORE_NAME               HeaderFields
               22  POP_TOP          

 L.   6        24  LOAD_CONST               1
               26  LOAD_CONST               ('MessageGenerator', 'new_method_call')
               28  IMPORT_NAME              wrappers
               30  IMPORT_FROM              MessageGenerator
               32  STORE_NAME               MessageGenerator
               34  IMPORT_FROM              new_method_call
               36  STORE_NAME               new_method_call
               38  POP_TOP          

 L.   8        40  BUILD_LIST_0          0 
               42  LOAD_CONST               ('DBusNameFlags', 'DBus', 'message_bus', 'Monitoring', 'Stats', 'MatchRule')
               44  CALL_FINALLY         47  'to 47'
               46  STORE_NAME               __all__

 L.  17        48  LOAD_BUILD_CLASS 
               50  LOAD_CODE                <code_object DBusNameFlags>
               52  LOAD_STR                 'DBusNameFlags'
               54  MAKE_FUNCTION_0          'Neither defaults, keyword-only args, annotations, nor closures'
               56  LOAD_STR                 'DBusNameFlags'
               58  CALL_FUNCTION_2       2  ''
               60  STORE_NAME               DBusNameFlags

 L.  22        62  LOAD_BUILD_CLASS 
               64  LOAD_CODE                <code_object DBus>
               66  LOAD_STR                 'DBus'
               68  MAKE_FUNCTION_0          'Neither defaults, keyword-only args, annotations, nor closures'
               70  LOAD_STR                 'DBus'
               72  LOAD_NAME                MessageGenerator
               74  CALL_FUNCTION_3       3  ''
               76  STORE_NAME               DBus

 L.  96        78  LOAD_NAME                DBus
               80  CALL_FUNCTION_0       0  ''
               82  STORE_NAME               message_bus

 L.  98        84  LOAD_BUILD_CLASS 
               86  LOAD_CODE                <code_object Monitoring>
               88  LOAD_STR                 'Monitoring'
               90  MAKE_FUNCTION_0          'Neither defaults, keyword-only args, annotations, nor closures'
               92  LOAD_STR                 'Monitoring'
               94  LOAD_NAME                MessageGenerator
               96  CALL_FUNCTION_3       3  ''
               98  STORE_NAME               Monitoring

 L. 109       100  LOAD_BUILD_CLASS 
              102  LOAD_CODE                <code_object Stats>
              104  LOAD_STR                 'Stats'
              106  MAKE_FUNCTION_0          'Neither defaults, keyword-only args, annotations, nor closures'
              108  LOAD_STR                 'Stats'
              110  LOAD_NAME                MessageGenerator
              112  CALL_FUNCTION_3       3  ''
              114  STORE_NAME               Stats

 L. 127       116  LOAD_BUILD_CLASS 
              118  LOAD_CODE                <code_object MatchRule>
              120  LOAD_STR                 'MatchRule'
              122  MAKE_FUNCTION_0          'Neither defaults, keyword-only args, annotations, nor closures'
              124  LOAD_STR                 'MatchRule'
              126  CALL_FUNCTION_2       2  ''
              128  STORE_NAME               MatchRule

Parse error at or near `CALL_FINALLY' instruction at offset 44

