
# file test/134656.pyc
# --- This code section failed: ---

 L.   1         0  LOAD_CONST               0
                2  LOAD_CONST               None
                4  IMPORT_NAME              os
                6  STORE_NAME               os

 L.   2         8  LOAD_CONST               0
               10  LOAD_CONST               None
               12  IMPORT_NAME              re
               14  STORE_NAME               re

 L.   3        16  LOAD_CONST               0
               18  LOAD_CONST               None
               20  IMPORT_NAME              abc
               22  STORE_NAME               abc

 L.   4        24  LOAD_CONST               0
               26  LOAD_CONST               None
               28  IMPORT_NAME              csv
               30  STORE_NAME               csv

 L.   5        32  LOAD_CONST               0
               34  LOAD_CONST               None
               36  IMPORT_NAME              sys
               38  STORE_NAME               sys

 L.   6        40  LOAD_CONST               0
               42  LOAD_CONST               None
               44  IMPORT_NAME              zipp
               46  STORE_NAME               zipp

 L.   7        48  LOAD_CONST               0
               50  LOAD_CONST               None
               52  IMPORT_NAME              email
               54  STORE_NAME               email

 L.   8        56  LOAD_CONST               0
               58  LOAD_CONST               None
               60  IMPORT_NAME              inspect
               62  STORE_NAME               inspect

 L.   9        64  LOAD_CONST               0
               66  LOAD_CONST               None
               68  IMPORT_NAME              pathlib
               70  STORE_NAME               pathlib

 L.  10        72  LOAD_CONST               0
               74  LOAD_CONST               None
               76  IMPORT_NAME              operator
               78  STORE_NAME               operator

 L.  11        80  LOAD_CONST               0
               82  LOAD_CONST               None
               84  IMPORT_NAME              warnings
               86  STORE_NAME               warnings

 L.  12        88  LOAD_CONST               0
               90  LOAD_CONST               None
               92  IMPORT_NAME              functools
               94  STORE_NAME               functools

 L.  13        96  LOAD_CONST               0
               98  LOAD_CONST               None
              100  IMPORT_NAME              itertools
              102  STORE_NAME               itertools

 L.  14       104  LOAD_CONST               0
              106  LOAD_CONST               None
              108  IMPORT_NAME              posixpath
              110  STORE_NAME               posixpath

 L.  15       112  LOAD_CONST               0
              114  LOAD_CONST               None
              116  IMPORT_NAME_ATTR         collections.abc
              118  STORE_NAME               collections

 L.  17       120  LOAD_CONST               1
              122  LOAD_CONST               ('NullFinder', 'PyPy_repr', 'install', 'Protocol')
              124  IMPORT_NAME              _compat
              126  IMPORT_FROM              NullFinder
              128  STORE_NAME               NullFinder
              130  IMPORT_FROM              PyPy_repr
              132  STORE_NAME               PyPy_repr
              134  IMPORT_FROM              install
              136  STORE_NAME               install
              138  IMPORT_FROM              Protocol
              140  STORE_NAME               Protocol
              142  POP_TOP          

 L.  24       144  LOAD_CONST               1
              146  LOAD_CONST               ('unique_everseen',)
              148  IMPORT_NAME              _itertools
              150  IMPORT_FROM              unique_everseen
              152  STORE_NAME               unique_everseen
              154  POP_TOP          

 L.  26       156  LOAD_CONST               0
              158  LOAD_CONST               ('ConfigParser',)
              160  IMPORT_NAME              configparser
              162  IMPORT_FROM              ConfigParser
              164  STORE_NAME               ConfigParser
              166  POP_TOP          

 L.  27       168  LOAD_CONST               0
              170  LOAD_CONST               ('suppress',)
              172  IMPORT_NAME              contextlib
              174  IMPORT_FROM              suppress
              176  STORE_NAME               suppress
              178  POP_TOP          

 L.  28       180  LOAD_CONST               0
              182  LOAD_CONST               ('import_module',)
              184  IMPORT_NAME              importlib
              186  IMPORT_FROM              import_module
              188  STORE_NAME               import_module
              190  POP_TOP          

 L.  29       192  LOAD_CONST               0
              194  LOAD_CONST               ('MetaPathFinder',)
              196  IMPORT_NAME_ATTR         importlib.abc
              198  IMPORT_FROM              MetaPathFinder
              200  STORE_NAME               MetaPathFinder
              202  POP_TOP          

 L.  30       204  LOAD_CONST               0
              206  LOAD_CONST               ('starmap',)
              208  IMPORT_NAME              itertools
              210  IMPORT_FROM              starmap
              212  STORE_NAME               starmap
              214  POP_TOP          

 L.  31       216  LOAD_CONST               0
              218  LOAD_CONST               ('Any', 'List', 'Mapping', 'Optional', 'TypeVar', 'Union')
              220  IMPORT_NAME              typing
              222  IMPORT_FROM              Any
              224  STORE_NAME               Any
              226  IMPORT_FROM              List
              228  STORE_NAME               List
              230  IMPORT_FROM              Mapping
              232  STORE_NAME               Mapping
              234  IMPORT_FROM              Optional
              236  STORE_NAME               Optional
              238  IMPORT_FROM              TypeVar
              240  STORE_NAME               TypeVar
              242  IMPORT_FROM              Union
              244  STORE_NAME               Union
              246  POP_TOP          

 L.  34       248  BUILD_LIST_0          0 
              250  LOAD_CONST               ('Distribution', 'DistributionFinder', 'PackageNotFoundError', 'distribution', 'distributions', 'entry_points', 'files', 'metadata', 'requires', 'version')
              252  CALL_FINALLY        255  'to 255'
              254  STORE_NAME               __all__

 L.  48       256  LOAD_BUILD_CLASS 
              258  LOAD_CODE                <code_object PackageNotFoundError>
              260  LOAD_STR                 'PackageNotFoundError'
              262  MAKE_FUNCTION_0          'Neither defaults, keyword-only args, annotations, nor closures'
              264  LOAD_STR                 'PackageNotFoundError'
              266  LOAD_NAME                ModuleNotFoundError
              268  CALL_FUNCTION_3       3  ''
              270  STORE_NAME               PackageNotFoundError

 L.  61       272  LOAD_BUILD_CLASS 
              274  LOAD_CODE                <code_object EntryPoint>
              276  LOAD_STR                 'EntryPoint'
              278  MAKE_FUNCTION_0          'Neither defaults, keyword-only args, annotations, nor closures'
              280  LOAD_STR                 'EntryPoint'

 L.  62       282  LOAD_NAME                PyPy_repr
              284  LOAD_NAME                collections
              286  LOAD_METHOD              namedtuple
              288  LOAD_STR                 'EntryPointBase'
              290  LOAD_STR                 'name value group'
              292  CALL_METHOD_2         2  ''

 L.  61       294  CALL_FUNCTION_4       4  ''
              296  STORE_NAME               EntryPoint

 L. 161       298  LOAD_BUILD_CLASS 
              300  LOAD_CODE                <code_object EntryPoints>
              302  LOAD_STR                 'EntryPoints'
              304  MAKE_FUNCTION_0          'Neither defaults, keyword-only args, annotations, nor closures'
              306  LOAD_STR                 'EntryPoints'
              308  LOAD_NAME                tuple
              310  CALL_FUNCTION_3       3  ''
              312  STORE_NAME               EntryPoints

 L. 195       314  LOAD_CODE                <code_object flake8_bypass>
              316  LOAD_STR                 'flake8_bypass'
              318  MAKE_FUNCTION_0          'Neither defaults, keyword-only args, annotations, nor closures'
              320  STORE_NAME               flake8_bypass

 L. 200       322  LOAD_BUILD_CLASS 
              324  LOAD_CODE                <code_object Deprecated>
              326  LOAD_STR                 'Deprecated'
              328  MAKE_FUNCTION_0          'Neither defaults, keyword-only args, annotations, nor closures'
              330  LOAD_STR                 'Deprecated'
              332  CALL_FUNCTION_2       2  ''
              334  STORE_NAME               Deprecated

 L. 255       336  LOAD_BUILD_CLASS 
              338  LOAD_CODE                <code_object SelectableGroups>
              340  LOAD_STR                 'SelectableGroups'
              342  MAKE_FUNCTION_0          'Neither defaults, keyword-only args, annotations, nor closures'
              344  LOAD_STR                 'SelectableGroups'
              346  LOAD_NAME                dict
              348  CALL_FUNCTION_3       3  ''
              350  STORE_NAME               SelectableGroups

 L. 294       352  LOAD_BUILD_CLASS 
              354  LOAD_CODE                <code_object PackagePath>
              356  LOAD_STR                 'PackagePath'
              358  MAKE_FUNCTION_0          'Neither defaults, keyword-only args, annotations, nor closures'
              360  LOAD_STR                 'PackagePath'
              362  LOAD_NAME                pathlib
              364  LOAD_ATTR                PurePosixPath
              366  CALL_FUNCTION_3       3  ''
              368  STORE_NAME               PackagePath

 L. 310       370  LOAD_BUILD_CLASS 
              372  LOAD_CODE                <code_object FileHash>
              374  LOAD_STR                 'FileHash'
              376  MAKE_FUNCTION_0          'Neither defaults, keyword-only args, annotations, nor closures'
              378  LOAD_STR                 'FileHash'
              380  CALL_FUNCTION_2       2  ''
              382  STORE_NAME               FileHash

 L. 318       384  LOAD_NAME                TypeVar
              386  LOAD_STR                 '_T'
              388  CALL_FUNCTION_1       1  ''
              390  STORE_NAME               _T

 L. 321       392  LOAD_BUILD_CLASS 
              394  LOAD_CODE                <code_object PackageMetadata>
              396  LOAD_STR                 'PackageMetadata'
              398  MAKE_FUNCTION_0          'Neither defaults, keyword-only args, annotations, nor closures'
              400  LOAD_STR                 'PackageMetadata'
              402  LOAD_NAME                Protocol
              404  CALL_FUNCTION_3       3  ''
              406  STORE_NAME               PackageMetadata

 L. 337       408  LOAD_BUILD_CLASS 
              410  LOAD_CODE                <code_object Distribution>
              412  LOAD_STR                 'Distribution'
              414  MAKE_FUNCTION_0          'Neither defaults, keyword-only args, annotations, nor closures'
              416  LOAD_STR                 'Distribution'
              418  CALL_FUNCTION_2       2  ''
              420  STORE_NAME               Distribution

 L. 550       422  LOAD_BUILD_CLASS 
              424  LOAD_CODE                <code_object DistributionFinder>
              426  LOAD_STR                 'DistributionFinder'
              428  MAKE_FUNCTION_0          'Neither defaults, keyword-only args, annotations, nor closures'
              430  LOAD_STR                 'DistributionFinder'
              432  LOAD_NAME                MetaPathFinder
              434  CALL_FUNCTION_3       3  ''
              436  STORE_NAME               DistributionFinder

 L. 597       438  LOAD_BUILD_CLASS 
              440  LOAD_CODE                <code_object FastPath>
              442  LOAD_STR                 'FastPath'
              444  MAKE_FUNCTION_0          'Neither defaults, keyword-only args, annotations, nor closures'
              446  LOAD_STR                 'FastPath'
              448  CALL_FUNCTION_2       2  ''
              450  STORE_NAME               FastPath

 L. 632       452  LOAD_BUILD_CLASS 
              454  LOAD_CODE                <code_object Prepared>
              456  LOAD_STR                 'Prepared'
              458  MAKE_FUNCTION_0          'Neither defaults, keyword-only args, annotations, nor closures'
              460  LOAD_STR                 'Prepared'
              462  CALL_FUNCTION_2       2  ''
              464  STORE_NAME               Prepared

 L. 692       466  LOAD_NAME                install

 L. 693       468  LOAD_BUILD_CLASS 
              470  LOAD_CODE                <code_object MetadataPathFinder>
              472  LOAD_STR                 'MetadataPathFinder'
              474  MAKE_FUNCTION_0          'Neither defaults, keyword-only args, annotations, nor closures'
              476  LOAD_STR                 'MetadataPathFinder'
              478  LOAD_NAME                NullFinder
              480  LOAD_NAME                DistributionFinder
              482  CALL_FUNCTION_4       4  ''
              484  CALL_FUNCTION_1       1  ''
              486  STORE_NAME               MetadataPathFinder

 L. 721       488  LOAD_BUILD_CLASS 
              490  LOAD_CODE                <code_object PathDistribution>
              492  LOAD_STR                 'PathDistribution'
              494  MAKE_FUNCTION_0          'Neither defaults, keyword-only args, annotations, nor closures'
              496  LOAD_STR                 'PathDistribution'
              498  LOAD_NAME                Distribution
              500  CALL_FUNCTION_3       3  ''
              502  STORE_NAME               PathDistribution

 L. 746       504  LOAD_CODE                <code_object distribution>
              506  LOAD_STR                 'distribution'
              508  MAKE_FUNCTION_0          'Neither defaults, keyword-only args, annotations, nor closures'
              510  STORE_NAME               distribution

 L. 755       512  LOAD_CODE                <code_object distributions>
              514  LOAD_STR                 'distributions'
              516  MAKE_FUNCTION_0          'Neither defaults, keyword-only args, annotations, nor closures'
              518  STORE_NAME               distributions

 L. 763       520  LOAD_NAME                PackageMetadata
              522  LOAD_CONST               ('return',)
              524  BUILD_CONST_KEY_MAP_1     1 
              526  LOAD_CODE                <code_object metadata>
              528  LOAD_STR                 'metadata'
              530  MAKE_FUNCTION_4          'annotation'
              532  STORE_NAME               metadata

 L. 772       534  LOAD_CODE                <code_object version>
              536  LOAD_STR                 'version'
              538  MAKE_FUNCTION_0          'Neither defaults, keyword-only args, annotations, nor closures'
              540  STORE_NAME               version

 L. 782       542  LOAD_NAME                Union
              544  LOAD_NAME                EntryPoints
              546  LOAD_NAME                SelectableGroups
              548  BUILD_TUPLE_2         2 
              550  BINARY_SUBSCR    
              552  LOAD_CONST               ('return',)
              554  BUILD_CONST_KEY_MAP_1     1 
              556  LOAD_CODE                <code_object entry_points>
              558  LOAD_STR                 'entry_points'
              560  MAKE_FUNCTION_4          'annotation'
              562  STORE_NAME               entry_points

 L. 806       564  LOAD_CODE                <code_object files>
              566  LOAD_STR                 'files'
              568  MAKE_FUNCTION_0          'Neither defaults, keyword-only args, annotations, nor closures'
              570  STORE_NAME               files

 L. 815       572  LOAD_CODE                <code_object requires>
              574  LOAD_STR                 'requires'
              576  MAKE_FUNCTION_0          'Neither defaults, keyword-only args, annotations, nor closures'
              578  STORE_NAME               requires

 L. 825       580  LOAD_NAME                Mapping
              582  LOAD_NAME                str
              584  LOAD_NAME                List
              586  LOAD_NAME                str
              588  BINARY_SUBSCR    
              590  BUILD_TUPLE_2         2 
              592  BINARY_SUBSCR    
              594  LOAD_CONST               ('return',)
              596  BUILD_CONST_KEY_MAP_1     1 
              598  LOAD_CODE                <code_object packages_distributions>
              600  LOAD_STR                 'packages_distributions'
              602  MAKE_FUNCTION_4          'annotation'
              604  STORE_NAME               packages_distributions

Parse error at or near `CALL_FINALLY' instruction at offset 252

Instruction context:
   
 L.  34       248  BUILD_LIST_0          0 
                 250  LOAD_CONST               ('Distribution', 'DistributionFinder', 'PackageNotFoundError', 'distribution', 'distributions', 'entry_points', 'files', 'metadata', 'requires', 'version')
->               252  CALL_FINALLY        255  'to 255'
                 254  STORE_NAME               __all__

test/134656.pyc -- 
# decompile failed
