
# file test/134772.pyc
# --- This code section failed: ---

 L.   3         0  LOAD_STR                 '\nrequests.adapters\n~~~~~~~~~~~~~~~~~\n\nThis module contains the transport adapters that Requests uses to define\nand maintain connections.\n'
                2  STORE_NAME               __doc__

 L.  11         4  LOAD_CONST               0
                6  LOAD_CONST               None
                8  IMPORT_NAME_ATTR         os.path
               10  STORE_NAME               os

 L.  12        12  LOAD_CONST               0
               14  LOAD_CONST               None
               16  IMPORT_NAME              socket
               18  STORE_NAME               socket

 L.  14        20  LOAD_CONST               0
               22  LOAD_CONST               ('PoolManager', 'proxy_from_url')
               24  IMPORT_NAME_ATTR         urllib3.poolmanager
               26  IMPORT_FROM              PoolManager
               28  STORE_NAME               PoolManager
               30  IMPORT_FROM              proxy_from_url
               32  STORE_NAME               proxy_from_url
               34  POP_TOP          

 L.  15        36  LOAD_CONST               0
               38  LOAD_CONST               ('HTTPResponse',)
               40  IMPORT_NAME_ATTR         urllib3.response
               42  IMPORT_FROM              HTTPResponse
               44  STORE_NAME               HTTPResponse
               46  POP_TOP          

 L.  16        48  LOAD_CONST               0
               50  LOAD_CONST               ('parse_url',)
               52  IMPORT_NAME_ATTR         urllib3.util
               54  IMPORT_FROM              parse_url
               56  STORE_NAME               parse_url
               58  POP_TOP          

 L.  17        60  LOAD_CONST               0
               62  LOAD_CONST               ('Timeout',)
               64  IMPORT_NAME_ATTR         urllib3.util
               66  IMPORT_FROM              Timeout
               68  STORE_NAME               TimeoutSauce
               70  POP_TOP          

 L.  18        72  LOAD_CONST               0
               74  LOAD_CONST               ('Retry',)
               76  IMPORT_NAME_ATTR         urllib3.util.retry
               78  IMPORT_FROM              Retry
               80  STORE_NAME               Retry
               82  POP_TOP          

 L.  19        84  LOAD_CONST               0
               86  LOAD_CONST               ('ClosedPoolError',)
               88  IMPORT_NAME_ATTR         urllib3.exceptions
               90  IMPORT_FROM              ClosedPoolError
               92  STORE_NAME               ClosedPoolError
               94  POP_TOP          

 L.  20        96  LOAD_CONST               0
               98  LOAD_CONST               ('ConnectTimeoutError',)
              100  IMPORT_NAME_ATTR         urllib3.exceptions
              102  IMPORT_FROM              ConnectTimeoutError
              104  STORE_NAME               ConnectTimeoutError
              106  POP_TOP          

 L.  21       108  LOAD_CONST               0
              110  LOAD_CONST               ('HTTPError',)
              112  IMPORT_NAME_ATTR         urllib3.exceptions
              114  IMPORT_FROM              HTTPError
              116  STORE_NAME               _HTTPError
              118  POP_TOP          

 L.  22       120  LOAD_CONST               0
              122  LOAD_CONST               ('MaxRetryError',)
              124  IMPORT_NAME_ATTR         urllib3.exceptions
              126  IMPORT_FROM              MaxRetryError
              128  STORE_NAME               MaxRetryError
              130  POP_TOP          

 L.  23       132  LOAD_CONST               0
              134  LOAD_CONST               ('NewConnectionError',)
              136  IMPORT_NAME_ATTR         urllib3.exceptions
              138  IMPORT_FROM              NewConnectionError
              140  STORE_NAME               NewConnectionError
              142  POP_TOP          

 L.  24       144  LOAD_CONST               0
              146  LOAD_CONST               ('ProxyError',)
              148  IMPORT_NAME_ATTR         urllib3.exceptions
              150  IMPORT_FROM              ProxyError
              152  STORE_NAME               _ProxyError
              154  POP_TOP          

 L.  25       156  LOAD_CONST               0
              158  LOAD_CONST               ('ProtocolError',)
              160  IMPORT_NAME_ATTR         urllib3.exceptions
              162  IMPORT_FROM              ProtocolError
              164  STORE_NAME               ProtocolError
              166  POP_TOP          

 L.  26       168  LOAD_CONST               0
              170  LOAD_CONST               ('ReadTimeoutError',)
              172  IMPORT_NAME_ATTR         urllib3.exceptions
              174  IMPORT_FROM              ReadTimeoutError
              176  STORE_NAME               ReadTimeoutError
              178  POP_TOP          

 L.  27       180  LOAD_CONST               0
              182  LOAD_CONST               ('SSLError',)
              184  IMPORT_NAME_ATTR         urllib3.exceptions
              186  IMPORT_FROM              SSLError
              188  STORE_NAME               _SSLError
              190  POP_TOP          

 L.  28       192  LOAD_CONST               0
              194  LOAD_CONST               ('ResponseError',)
              196  IMPORT_NAME_ATTR         urllib3.exceptions
              198  IMPORT_FROM              ResponseError
              200  STORE_NAME               ResponseError
              202  POP_TOP          

 L.  29       204  LOAD_CONST               0
              206  LOAD_CONST               ('LocationValueError',)
              208  IMPORT_NAME_ATTR         urllib3.exceptions
              210  IMPORT_FROM              LocationValueError
              212  STORE_NAME               LocationValueError
              214  POP_TOP          

 L.  31       216  LOAD_CONST               1
              218  LOAD_CONST               ('Response',)
              220  IMPORT_NAME              models
              222  IMPORT_FROM              Response
              224  STORE_NAME               Response
              226  POP_TOP          

 L.  32       228  LOAD_CONST               1
              230  LOAD_CONST               ('urlparse', 'basestring')
              232  IMPORT_NAME              compat
              234  IMPORT_FROM              urlparse
              236  STORE_NAME               urlparse
              238  IMPORT_FROM              basestring
              240  STORE_NAME               basestring
              242  POP_TOP          

 L.  33       244  LOAD_CONST               1
              246  LOAD_CONST               ('DEFAULT_CA_BUNDLE_PATH', 'extract_zipped_paths', 'get_encoding_from_headers', 'prepend_scheme_if_needed', 'get_auth_from_url', 'urldefragauth', 'select_proxy')
              248  IMPORT_NAME              utils
              250  IMPORT_FROM              DEFAULT_CA_BUNDLE_PATH
              252  STORE_NAME               DEFAULT_CA_BUNDLE_PATH
              254  IMPORT_FROM              extract_zipped_paths
              256  STORE_NAME               extract_zipped_paths
              258  IMPORT_FROM              get_encoding_from_headers
              260  STORE_NAME               get_encoding_from_headers
              262  IMPORT_FROM              prepend_scheme_if_needed
              264  STORE_NAME               prepend_scheme_if_needed
              266  IMPORT_FROM              get_auth_from_url
              268  STORE_NAME               get_auth_from_url
              270  IMPORT_FROM              urldefragauth
              272  STORE_NAME               urldefragauth
              274  IMPORT_FROM              select_proxy
              276  STORE_NAME               select_proxy
              278  POP_TOP          

 L.  36       280  LOAD_CONST               1
              282  LOAD_CONST               ('CaseInsensitiveDict',)
              284  IMPORT_NAME              structures
              286  IMPORT_FROM              CaseInsensitiveDict
              288  STORE_NAME               CaseInsensitiveDict
              290  POP_TOP          

 L.  37       292  LOAD_CONST               1
              294  LOAD_CONST               ('extract_cookies_to_jar',)
              296  IMPORT_NAME              cookies
              298  IMPORT_FROM              extract_cookies_to_jar
              300  STORE_NAME               extract_cookies_to_jar
              302  POP_TOP          

 L.  38       304  LOAD_CONST               1
              306  LOAD_CONST               ('ConnectionError', 'ConnectTimeout', 'ReadTimeout', 'SSLError', 'ProxyError', 'RetryError', 'InvalidSchema', 'InvalidProxyURL', 'InvalidURL')
              308  IMPORT_NAME              exceptions
              310  IMPORT_FROM              ConnectionError
              312  STORE_NAME               ConnectionError
              314  IMPORT_FROM              ConnectTimeout
              316  STORE_NAME               ConnectTimeout
              318  IMPORT_FROM              ReadTimeout
              320  STORE_NAME               ReadTimeout
              322  IMPORT_FROM              SSLError
              324  STORE_NAME               SSLError
              326  IMPORT_FROM              ProxyError
              328  STORE_NAME               ProxyError
              330  IMPORT_FROM              RetryError
              332  STORE_NAME               RetryError
              334  IMPORT_FROM              InvalidSchema
              336  STORE_NAME               InvalidSchema
              338  IMPORT_FROM              InvalidProxyURL
              340  STORE_NAME               InvalidProxyURL
              342  IMPORT_FROM              InvalidURL
              344  STORE_NAME               InvalidURL
              346  POP_TOP          

 L.  41       348  LOAD_CONST               1
              350  LOAD_CONST               ('_basic_auth_str',)
              352  IMPORT_NAME              auth
              354  IMPORT_FROM              _basic_auth_str
              356  STORE_NAME               _basic_auth_str
              358  POP_TOP          

 L.  43       360  SETUP_FINALLY       378  'to 378'

 L.  44       362  LOAD_CONST               0
              364  LOAD_CONST               ('SOCKSProxyManager',)
              366  IMPORT_NAME_ATTR         urllib3.contrib.socks
              368  IMPORT_FROM              SOCKSProxyManager
              370  STORE_NAME               SOCKSProxyManager
              372  POP_TOP          
              374  POP_BLOCK        
              376  JUMP_FORWARD        406  'to 406'
            378_0  COME_FROM_FINALLY   360  '360'

 L.  45       378  DUP_TOP          
              380  LOAD_NAME                ImportError
          382_384  <121>               404  ''
              386  POP_TOP          
              388  POP_TOP          
              390  POP_TOP          

 L.  46       392  LOAD_CODE                <code_object SOCKSProxyManager>
              394  LOAD_STR                 'SOCKSProxyManager'
              396  MAKE_FUNCTION_0          'Neither defaults, keyword-only args, annotations, nor closures'
              398  STORE_NAME               SOCKSProxyManager
              400  POP_EXCEPT       
              402  JUMP_FORWARD        406  'to 406'
              404  <48>             
            406_0  COME_FROM           402  '402'
            406_1  COME_FROM           376  '376'

 L.  49       406  LOAD_CONST               False
              408  STORE_NAME               DEFAULT_POOLBLOCK

 L.  50       410  LOAD_CONST               10
              412  STORE_NAME               DEFAULT_POOLSIZE

 L.  51       414  LOAD_CONST               0
              416  STORE_NAME               DEFAULT_RETRIES

 L.  52       418  LOAD_CONST               None
              420  STORE_NAME               DEFAULT_POOL_TIMEOUT

 L.  55       422  LOAD_BUILD_CLASS 
              424  LOAD_CODE                <code_object BaseAdapter>
              426  LOAD_STR                 'BaseAdapter'
              428  MAKE_FUNCTION_0          'Neither defaults, keyword-only args, annotations, nor closures'
              430  LOAD_STR                 'BaseAdapter'
              432  LOAD_NAME                object
              434  CALL_FUNCTION_3       3  ''
              436  STORE_NAME               BaseAdapter

 L.  84       438  LOAD_BUILD_CLASS 
              440  LOAD_CODE                <code_object HTTPAdapter>
              442  LOAD_STR                 'HTTPAdapter'
              444  MAKE_FUNCTION_0          'Neither defaults, keyword-only args, annotations, nor closures'
              446  LOAD_STR                 'HTTPAdapter'
              448  LOAD_NAME                BaseAdapter
              450  CALL_FUNCTION_3       3  ''
              452  STORE_NAME               HTTPAdapter

Parse error at or near `<121>' instruction at offset 382_384

Instruction context:
   
 L.  45       378  DUP_TOP          
                 380  LOAD_NAME                ImportError
->           382_384  <121>               404  ''
                 386  POP_TOP          
                 388  POP_TOP          
                 390  POP_TOP          

test/134772.pyc -- 
# decompile failed
