
test/134749.pyc -- 
# decompile failed

# file test/134749.pyc
# --- This code section failed: ---

 L.  49         0  BUILD_LIST_0          0 
                2  LOAD_CONST               (1, 3, 0)
                4  CALL_FINALLY          7  'to 7'
                6  STORE_NAME               VERSION

 L.  51         8  LOAD_CONST               1
               10  LOAD_CONST               ('AES', 'AESModeOfOperationCTR', 'AESModeOfOperationCBC', 'AESModeOfOperationCFB', 'AESModeOfOperationECB', 'AESModeOfOperationOFB', 'AESModesOfOperation', 'Counter')
               12  IMPORT_NAME              aes
               14  IMPORT_FROM              AES
               16  STORE_NAME               AES
               18  IMPORT_FROM              AESModeOfOperationCTR
               20  STORE_NAME               AESModeOfOperationCTR
               22  IMPORT_FROM              AESModeOfOperationCBC
               24  STORE_NAME               AESModeOfOperationCBC
               26  IMPORT_FROM              AESModeOfOperationCFB
               28  STORE_NAME               AESModeOfOperationCFB
               30  IMPORT_FROM              AESModeOfOperationECB
               32  STORE_NAME               AESModeOfOperationECB
               34  IMPORT_FROM              AESModeOfOperationOFB
               36  STORE_NAME               AESModeOfOperationOFB
               38  IMPORT_FROM              AESModesOfOperation
               40  STORE_NAME               AESModesOfOperation
               42  IMPORT_FROM              Counter
               44  STORE_NAME               Counter
               46  POP_TOP          

 L.  52        48  LOAD_CONST               1
               50  LOAD_CONST               ('decrypt_stream', 'Decrypter', 'encrypt_stream', 'Encrypter')
               52  IMPORT_NAME              blockfeeder
               54  IMPORT_FROM              decrypt_stream
               56  STORE_NAME               decrypt_stream
               58  IMPORT_FROM              Decrypter
               60  STORE_NAME               Decrypter
               62  IMPORT_FROM              encrypt_stream
               64  STORE_NAME               encrypt_stream
               66  IMPORT_FROM              Encrypter
               68  STORE_NAME               Encrypter
               70  POP_TOP          

 L.  53        72  LOAD_CONST               1
               74  LOAD_CONST               ('PADDING_NONE', 'PADDING_DEFAULT')
               76  IMPORT_NAME              blockfeeder
               78  IMPORT_FROM              PADDING_NONE
               80  STORE_NAME               PADDING_NONE
               82  IMPORT_FROM              PADDING_DEFAULT
               84  STORE_NAME               PADDING_DEFAULT
               86  POP_TOP          

Parse error at or near `None' instruction at offset -1

