Instruction context:
   
 L. 227       186  LOAD_NAME                Image
                 188  LOAD_METHOD              register_extensions
                 190  LOAD_NAME                SgiImageFile
                 192  LOAD_ATTR                format
                 194  BUILD_LIST_0          0 
                 196  LOAD_CONST               ('.bw', '.rgb', '.rgba', '.sgi')
->               198  CALL_FINALLY        201  'to 201'
                 200  CALL_METHOD_2         2  ''

test/14424.pyc -- 
# decompile failed

# file test/14424.pyc
# --- This code section failed: ---

 L.  25         0  LOAD_CONST               0
                2  LOAD_CONST               None
                4  IMPORT_NAME              os
                6  STORE_NAME               os

 L.  26         8  LOAD_CONST               0
               10  LOAD_CONST               None
               12  IMPORT_NAME              struct
               14  STORE_NAME               struct

 L.  28        16  LOAD_CONST               1
               18  LOAD_CONST               ('Image', 'ImageFile')
               20  IMPORT_NAME              
               22  IMPORT_FROM              Image
               24  STORE_NAME               Image
               26  IMPORT_FROM              ImageFile
               28  STORE_NAME               ImageFile
               30  POP_TOP          

 L.  29        32  LOAD_CONST               1
               34  LOAD_CONST               ('i16be',)
               36  IMPORT_NAME              _binary
               38  IMPORT_FROM              i16be
               40  STORE_NAME               i16
               42  POP_TOP          

 L.  30        44  LOAD_CONST               1
               46  LOAD_CONST               ('o8',)
               48  IMPORT_NAME              _binary
               50  IMPORT_FROM              o8
               52  STORE_NAME               o8
               54  POP_TOP          

 L.  33        56  LOAD_CODE                <code_object _accept>
               58  LOAD_STR                 '_accept'
               60  MAKE_FUNCTION_0          'Neither defaults, keyword-only args, annotations, nor closures'
               62  STORE_NAME               _accept

 L.  38        64  LOAD_STR                 'L'

 L.  39        66  LOAD_STR                 'L'

 L.  40        68  LOAD_STR                 'L;16B'

 L.  41        70  LOAD_STR                 'L;16B'

 L.  42        72  LOAD_STR                 'RGB'

 L.  43        74  LOAD_STR                 'RGB;16B'

 L.  44        76  LOAD_STR                 'RGBA'

 L.  45        78  LOAD_STR                 'RGBA;16B'

 L.  37        80  LOAD_CONST               ((1, 1, 1), (1, 2, 1), (2, 1, 1), (2, 2, 1), (1, 3, 3), (2, 3, 3), (1, 3, 4), (2, 3, 4))
               82  BUILD_CONST_KEY_MAP_8     8 
               84  STORE_NAME               MODES

 L.  51        86  LOAD_BUILD_CLASS 
               88  LOAD_CODE                <code_object SgiImageFile>
               90  LOAD_STR                 'SgiImageFile'
               92  MAKE_FUNCTION_0          'Neither defaults, keyword-only args, annotations, nor closures'
               94  LOAD_STR                 'SgiImageFile'
               96  LOAD_NAME                ImageFile
               98  LOAD_ATTR                ImageFile
              100  CALL_FUNCTION_3       3  ''
              102  STORE_NAME               SgiImageFile

 L. 125       104  LOAD_CODE                <code_object _save>
              106  LOAD_STR                 '_save'
              108  MAKE_FUNCTION_0          'Neither defaults, keyword-only args, annotations, nor closures'
              110  STORE_NAME               _save

 L. 199       112  LOAD_BUILD_CLASS 
              114  LOAD_CODE                <code_object SGI16Decoder>
              116  LOAD_STR                 'SGI16Decoder'
              118  MAKE_FUNCTION_0          'Neither defaults, keyword-only args, annotations, nor closures'
              120  LOAD_STR                 'SGI16Decoder'
              122  LOAD_NAME                ImageFile
              124  LOAD_ATTR                PyDecoder
              126  CALL_FUNCTION_3       3  ''
              128  STORE_NAME               SGI16Decoder

 L. 222       130  LOAD_NAME                Image
              132  LOAD_METHOD              register_decoder
              134  LOAD_STR                 'SGI16'
              136  LOAD_NAME                SGI16Decoder
              138  CALL_METHOD_2         2  ''
              140  POP_TOP          

 L. 223       142  LOAD_NAME                Image
              144  LOAD_METHOD              register_open
              146  LOAD_NAME                SgiImageFile
              148  LOAD_ATTR                format
              150  LOAD_NAME                SgiImageFile
              152  LOAD_NAME                _accept
              154  CALL_METHOD_3         3  ''
              156  POP_TOP          

 L. 224       158  LOAD_NAME                Image
              160  LOAD_METHOD              register_save
              162  LOAD_NAME                SgiImageFile
              164  LOAD_ATTR                format
              166  LOAD_NAME                _save
              168  CALL_METHOD_2         2  ''
              170  POP_TOP          

 L. 225       172  LOAD_NAME                Image
              174  LOAD_METHOD              register_mime
              176  LOAD_NAME                SgiImageFile
              178  LOAD_ATTR                format
              180  LOAD_STR                 'image/sgi'
              182  CALL_METHOD_2         2  ''
              184  POP_TOP          

 L. 227       186  LOAD_NAME                Image
              188  LOAD_METHOD              register_extensions
              190  LOAD_NAME                SgiImageFile
              192  LOAD_ATTR                format
              194  BUILD_LIST_0          0 
              196  LOAD_CONST               ('.bw', '.rgb', '.rgba', '.sgi')
              198  CALL_FINALLY        201  'to 201'
              200  CALL_METHOD_2         2  ''
              202  POP_TOP          

Parse error at or near `CALL_FINALLY' instruction at offset 198

