
test/162663.pyc -- 
# decompile failed

# file test/162663.pyc
# --- This code section failed: ---

 L.   1         0  BUILD_LIST_0          0 
                2  LOAD_CONST               ('matrix', 'bmat', 'mat', 'asmatrix')
                4  CALL_FINALLY          7  'to 7'
                6  STORE_NAME               __all__

 L.   3         8  LOAD_CONST               0
               10  LOAD_CONST               None
               12  IMPORT_NAME              sys
               14  STORE_NAME               sys

 L.   4        16  LOAD_CONST               0
               18  LOAD_CONST               None
               20  IMPORT_NAME              warnings
               22  STORE_NAME               warnings

 L.   5        24  LOAD_CONST               0
               26  LOAD_CONST               None
               28  IMPORT_NAME              ast
               30  STORE_NAME               ast

 L.   6        32  LOAD_CONST               0
               34  LOAD_CONST               None
               36  IMPORT_NAME_ATTR         numpy.core.numeric
               38  IMPORT_FROM              core
               40  ROT_TWO          
               42  POP_TOP          
               44  IMPORT_FROM              numeric
               46  STORE_NAME               N
               48  POP_TOP          

 L.   7        50  LOAD_CONST               0
               52  LOAD_CONST               ('concatenate', 'isscalar')
               54  IMPORT_NAME_ATTR         numpy.core.numeric
               56  IMPORT_FROM              concatenate
               58  STORE_NAME               concatenate
               60  IMPORT_FROM              isscalar
               62  STORE_NAME               isscalar
               64  POP_TOP          

 L.   8        66  LOAD_CONST               0
               68  LOAD_CONST               ('set_module',)
               70  IMPORT_NAME_ATTR         numpy.core.overrides
               72  IMPORT_FROM              set_module
               74  STORE_NAME               set_module
               76  POP_TOP          

 L.  11        78  LOAD_CONST               0
               80  LOAD_CONST               ('matrix_power',)
               82  IMPORT_NAME_ATTR         numpy.linalg
               84  IMPORT_FROM              matrix_power
               86  STORE_NAME               matrix_power
               88  POP_TOP          

 L.  14        90  LOAD_CODE                <code_object _convert_from_string>
               92  LOAD_STR                 '_convert_from_string'
               94  MAKE_FUNCTION_0          'Neither defaults, keyword-only args, annotations, nor closures'
               96  STORE_NAME               _convert_from_string

 L.  36        98  LOAD_NAME                set_module
              100  LOAD_STR                 'numpy'
              102  CALL_FUNCTION_1       1  ''

 L.  37       104  LOAD_CONST               (None,)
              106  LOAD_CODE                <code_object asmatrix>
              108  LOAD_STR                 'asmatrix'
              110  MAKE_FUNCTION_1          'default'
              112  CALL_FUNCTION_1       1  ''
              114  STORE_NAME               asmatrix

 L.  72       116  LOAD_NAME                set_module
              118  LOAD_STR                 'numpy'
              120  CALL_FUNCTION_1       1  ''

 L.  73       122  LOAD_BUILD_CLASS 
              124  LOAD_CODE                <code_object matrix>
              126  LOAD_STR                 'matrix'
              128  MAKE_FUNCTION_0          'Neither defaults, keyword-only args, annotations, nor closures'
              130  LOAD_STR                 'matrix'
              132  LOAD_NAME                N
              134  LOAD_ATTR                ndarray
              136  CALL_FUNCTION_3       3  ''
              138  CALL_FUNCTION_1       1  ''
              140  STORE_NAME               matrix

 L.1010       142  LOAD_CODE                <code_object _from_string>
              144  LOAD_STR                 '_from_string'
              146  MAKE_FUNCTION_0          'Neither defaults, keyword-only args, annotations, nor closures'
              148  STORE_NAME               _from_string

 L.1035       150  LOAD_NAME                set_module
              152  LOAD_STR                 'numpy'
              154  CALL_FUNCTION_1       1  ''

 L.1036       156  LOAD_CONST               (None, None)
              158  LOAD_CODE                <code_object bmat>
              160  LOAD_STR                 'bmat'
              162  MAKE_FUNCTION_1          'default'
              164  CALL_FUNCTION_1       1  ''
              166  STORE_NAME               bmat

 L.1113       168  LOAD_NAME                asmatrix
              170  STORE_NAME               mat

Parse error at or near `None' instruction at offset -1

