
# file test/162606.pyc
# --- This code section failed: ---

 L.   1         0  LOAD_STR                 '\nThis module contains a set of functions for vectorized string\noperations and methods.\n\n.. note::\n   The `chararray` class exists for backwards compatibility with\n   Numarray, it is not recommended for new development. Starting from numpy\n   1.4, if one needs arrays of strings, it is recommended to use arrays of\n   `dtype` `object_`, `string_` or `unicode_`, and use the free functions\n   in the `numpy.char` module for fast vectorized string operations.\n\nSome methods will only be available if the corresponding string method is\navailable in your version of Python.\n\nThe preferred alias for `defchararray` is `numpy.char`.\n\n'
                2  STORE_NAME               __doc__

 L.  18         4  LOAD_CONST               0
                6  LOAD_CONST               None
                8  IMPORT_NAME              functools
               10  STORE_NAME               functools

 L.  19        12  LOAD_CONST               0
               14  LOAD_CONST               None
               16  IMPORT_NAME              sys
               18  STORE_NAME               sys

 L.  20        20  LOAD_CONST               1
               22  LOAD_CONST               ('string_', 'unicode_', 'integer', 'int_', 'object_', 'bool_', 'character')
               24  IMPORT_NAME              numerictypes
               26  IMPORT_FROM              string_
               28  STORE_NAME               string_
               30  IMPORT_FROM              unicode_
               32  STORE_NAME               unicode_
               34  IMPORT_FROM              integer
               36  STORE_NAME               integer
               38  IMPORT_FROM              int_
               40  STORE_NAME               int_
               42  IMPORT_FROM              object_
               44  STORE_NAME               object_
               46  IMPORT_FROM              bool_
               48  STORE_NAME               bool_
               50  IMPORT_FROM              character
               52  STORE_NAME               character
               54  POP_TOP          

 L.  22        56  LOAD_CONST               1
               58  LOAD_CONST               ('ndarray', 'compare_chararrays')
               60  IMPORT_NAME              numeric
               62  IMPORT_FROM              ndarray
               64  STORE_NAME               ndarray
               66  IMPORT_FROM              compare_chararrays
               68  STORE_NAME               compare_chararrays
               70  POP_TOP          

 L.  23        72  LOAD_CONST               1
               74  LOAD_CONST               ('array',)
               76  IMPORT_NAME              numeric
               78  IMPORT_FROM              array
               80  STORE_NAME               narray
               82  POP_TOP          

 L.  24        84  LOAD_CONST               0
               86  LOAD_CONST               ('_vec_string',)
               88  IMPORT_NAME_ATTR         numpy.core.multiarray
               90  IMPORT_FROM              _vec_string
               92  STORE_NAME               _vec_string
               94  POP_TOP          

 L.  25        96  LOAD_CONST               0
               98  LOAD_CONST               ('set_module',)
              100  IMPORT_NAME_ATTR         numpy.core.overrides
              102  IMPORT_FROM              set_module
              104  STORE_NAME               set_module
              106  POP_TOP          

 L.  26       108  LOAD_CONST               0
              110  LOAD_CONST               ('overrides',)
              112  IMPORT_NAME_ATTR         numpy.core
              114  IMPORT_FROM              overrides
              116  STORE_NAME               overrides
              118  POP_TOP          

 L.  27       120  LOAD_CONST               0
              122  LOAD_CONST               ('asbytes',)
              124  IMPORT_NAME_ATTR         numpy.compat
              126  IMPORT_FROM              asbytes
              128  STORE_NAME               asbytes
              130  POP_TOP          

 L.  28       132  LOAD_CONST               0
              134  LOAD_CONST               None
              136  IMPORT_NAME              numpy
              138  STORE_NAME               numpy

 L.  30       140  BUILD_LIST_0          0 
              142  LOAD_CONST               ('equal', 'not_equal', 'greater_equal', 'less_equal', 'greater', 'less', 'str_len', 'add', 'multiply', 'mod', 'capitalize', 'center', 'count', 'decode', 'encode', 'endswith', 'expandtabs', 'find', 'index', 'isalnum', 'isalpha', 'isdigit', 'islower', 'isspace', 'istitle', 'isupper', 'join', 'ljust', 'lower', 'lstrip', 'partition', 'replace', 'rfind', 'rindex', 'rjust', 'rpartition', 'rsplit', 'rstrip', 'split', 'splitlines', 'startswith', 'strip', 'swapcase', 'title', 'translate', 'upper', 'zfill', 'isnumeric', 'isdecimal', 'array', 'asarray')
              144  CALL_FINALLY        147  'to 147'
              146  STORE_NAME               __all__

 L.  43       148  LOAD_CONST               0
              150  STORE_GLOBAL             _globalvar

 L.  45       152  LOAD_NAME                functools
              154  LOAD_ATTR                partial

 L.  46       156  LOAD_NAME                overrides
              158  LOAD_ATTR                array_function_dispatch
              160  LOAD_STR                 'numpy.char'

 L.  45       162  LOAD_CONST               ('module',)
              164  CALL_FUNCTION_KW_2     2  '2 total positional and keyword args'
              166  STORE_NAME               array_function_dispatch

 L.  49       168  LOAD_CODE                <code_object _use_unicode>
              170  LOAD_STR                 '_use_unicode'
              172  MAKE_FUNCTION_0          'Neither defaults, keyword-only args, annotations, nor closures'
              174  STORE_NAME               _use_unicode

 L.  63       176  LOAD_CODE                <code_object _to_string_or_unicode_array>
              178  LOAD_STR                 '_to_string_or_unicode_array'
              180  MAKE_FUNCTION_0          'Neither defaults, keyword-only args, annotations, nor closures'
              182  STORE_NAME               _to_string_or_unicode_array

 L.  70       184  LOAD_CODE                <code_object _clean_args>
              186  LOAD_STR                 '_clean_args'
              188  MAKE_FUNCTION_0          'Neither defaults, keyword-only args, annotations, nor closures'
              190  STORE_NAME               _clean_args

 L.  86       192  LOAD_CODE                <code_object _get_num_chars>
              194  LOAD_STR                 '_get_num_chars'
              196  MAKE_FUNCTION_0          'Neither defaults, keyword-only args, annotations, nor closures'
              198  STORE_NAME               _get_num_chars

 L.  97       200  LOAD_CODE                <code_object _binary_op_dispatcher>
              202  LOAD_STR                 '_binary_op_dispatcher'
              204  MAKE_FUNCTION_0          'Neither defaults, keyword-only args, annotations, nor closures'
              206  STORE_NAME               _binary_op_dispatcher

 L. 101       208  LOAD_NAME                array_function_dispatch
              210  LOAD_NAME                _binary_op_dispatcher
              212  CALL_FUNCTION_1       1  ''

 L. 102       214  LOAD_CODE                <code_object equal>
              216  LOAD_STR                 'equal'
              218  MAKE_FUNCTION_0          'Neither defaults, keyword-only args, annotations, nor closures'
              220  CALL_FUNCTION_1       1  ''
              222  STORE_NAME               equal

 L. 127       224  LOAD_NAME                array_function_dispatch
              226  LOAD_NAME                _binary_op_dispatcher
              228  CALL_FUNCTION_1       1  ''

 L. 128       230  LOAD_CODE                <code_object not_equal>
              232  LOAD_STR                 'not_equal'
              234  MAKE_FUNCTION_0          'Neither defaults, keyword-only args, annotations, nor closures'
              236  CALL_FUNCTION_1       1  ''
              238  STORE_NAME               not_equal

 L. 153       240  LOAD_NAME                array_function_dispatch
              242  LOAD_NAME                _binary_op_dispatcher
              244  CALL_FUNCTION_1       1  ''

 L. 154       246  LOAD_CODE                <code_object greater_equal>
              248  LOAD_STR                 'greater_equal'
              250  MAKE_FUNCTION_0          'Neither defaults, keyword-only args, annotations, nor closures'
              252  CALL_FUNCTION_1       1  ''
              254  STORE_NAME               greater_equal

 L. 180       256  LOAD_NAME                array_function_dispatch
              258  LOAD_NAME                _binary_op_dispatcher
              260  CALL_FUNCTION_1       1  ''

 L. 181       262  LOAD_CODE                <code_object less_equal>
              264  LOAD_STR                 'less_equal'
              266  MAKE_FUNCTION_0          'Neither defaults, keyword-only args, annotations, nor closures'
              268  CALL_FUNCTION_1       1  ''
              270  STORE_NAME               less_equal

 L. 206       272  LOAD_NAME                array_function_dispatch
              274  LOAD_NAME                _binary_op_dispatcher
              276  CALL_FUNCTION_1       1  ''

 L. 207       278  LOAD_CODE                <code_object greater>
              280  LOAD_STR                 'greater'
              282  MAKE_FUNCTION_0          'Neither defaults, keyword-only args, annotations, nor closures'
              284  CALL_FUNCTION_1       1  ''
              286  STORE_NAME               greater

 L. 232       288  LOAD_NAME                array_function_dispatch
              290  LOAD_NAME                _binary_op_dispatcher
              292  CALL_FUNCTION_1       1  ''

 L. 233       294  LOAD_CODE                <code_object less>
              296  LOAD_STR                 'less'
              298  MAKE_FUNCTION_0          'Neither defaults, keyword-only args, annotations, nor closures'
              300  CALL_FUNCTION_1       1  ''
              302  STORE_NAME               less

 L. 258       304  LOAD_CODE                <code_object _unary_op_dispatcher>
              306  LOAD_STR                 '_unary_op_dispatcher'
              308  MAKE_FUNCTION_0          'Neither defaults, keyword-only args, annotations, nor closures'
              310  STORE_NAME               _unary_op_dispatcher

 L. 262       312  LOAD_NAME                array_function_dispatch
              314  LOAD_NAME                _unary_op_dispatcher
              316  CALL_FUNCTION_1       1  ''

 L. 263       318  LOAD_CODE                <code_object str_len>
              320  LOAD_STR                 'str_len'
              322  MAKE_FUNCTION_0          'Neither defaults, keyword-only args, annotations, nor closures'
              324  CALL_FUNCTION_1       1  ''
              326  STORE_NAME               str_len

 L. 286       328  LOAD_NAME                array_function_dispatch
              330  LOAD_NAME                _binary_op_dispatcher
              332  CALL_FUNCTION_1       1  ''

 L. 287       334  LOAD_CODE                <code_object add>
              336  LOAD_STR                 'add'
              338  MAKE_FUNCTION_0          'Neither defaults, keyword-only args, annotations, nor closures'
              340  CALL_FUNCTION_1       1  ''
              342  STORE_NAME               add

 L. 314       344  LOAD_CODE                <code_object _multiply_dispatcher>
              346  LOAD_STR                 '_multiply_dispatcher'
              348  MAKE_FUNCTION_0          'Neither defaults, keyword-only args, annotations, nor closures'
              350  STORE_NAME               _multiply_dispatcher

 L. 318       352  LOAD_NAME                array_function_dispatch
              354  LOAD_NAME                _multiply_dispatcher
              356  CALL_FUNCTION_1       1  ''

 L. 319       358  LOAD_CODE                <code_object multiply>
              360  LOAD_STR                 'multiply'
              362  MAKE_FUNCTION_0          'Neither defaults, keyword-only args, annotations, nor closures'
              364  CALL_FUNCTION_1       1  ''
              366  STORE_NAME               multiply

 L. 348       368  LOAD_CODE                <code_object _mod_dispatcher>
              370  LOAD_STR                 '_mod_dispatcher'
              372  MAKE_FUNCTION_0          'Neither defaults, keyword-only args, annotations, nor closures'
              374  STORE_NAME               _mod_dispatcher

 L. 352       376  LOAD_NAME                array_function_dispatch
              378  LOAD_NAME                _mod_dispatcher
              380  CALL_FUNCTION_1       1  ''

 L. 353       382  LOAD_CODE                <code_object mod>
              384  LOAD_STR                 'mod'
              386  MAKE_FUNCTION_0          'Neither defaults, keyword-only args, annotations, nor closures'
              388  CALL_FUNCTION_1       1  ''
              390  STORE_NAME               mod

 L. 380       392  LOAD_NAME                array_function_dispatch
              394  LOAD_NAME                _unary_op_dispatcher
              396  CALL_FUNCTION_1       1  ''

 L. 381       398  LOAD_CODE                <code_object capitalize>
              400  LOAD_STR                 'capitalize'
              402  MAKE_FUNCTION_0          'Neither defaults, keyword-only args, annotations, nor closures'
              404  CALL_FUNCTION_1       1  ''
              406  STORE_NAME               capitalize

 L. 419       408  LOAD_CONST               (None,)
              410  LOAD_CODE                <code_object _center_dispatcher>
              412  LOAD_STR                 '_center_dispatcher'
              414  MAKE_FUNCTION_1          'default'
              416  STORE_NAME               _center_dispatcher

 L. 423       418  LOAD_NAME                array_function_dispatch
              420  LOAD_NAME                _center_dispatcher
              422  CALL_FUNCTION_1       1  ''

 L. 424       424  LOAD_CONST               (' ',)
              426  LOAD_CODE                <code_object center>
              428  LOAD_STR                 'center'
              430  MAKE_FUNCTION_1          'default'
              432  CALL_FUNCTION_1       1  ''
              434  STORE_NAME               center

 L. 460       436  LOAD_CONST               (None, None)
              438  LOAD_CODE                <code_object _count_dispatcher>
              440  LOAD_STR                 '_count_dispatcher'
              442  MAKE_FUNCTION_1          'default'
              444  STORE_NAME               _count_dispatcher

 L. 464       446  LOAD_NAME                array_function_dispatch
              448  LOAD_NAME                _count_dispatcher
              450  CALL_FUNCTION_1       1  ''

 L. 465       452  LOAD_CONST               (0, None)
              454  LOAD_CODE                <code_object count>
              456  LOAD_STR                 'count'
              458  MAKE_FUNCTION_1          'default'
              460  CALL_FUNCTION_1       1  ''
              462  STORE_NAME               count

 L. 510       464  LOAD_CONST               (None, None)
              466  LOAD_CODE                <code_object _code_dispatcher>
              468  LOAD_STR                 '_code_dispatcher'
              470  MAKE_FUNCTION_1          'default'
              472  STORE_NAME               _code_dispatcher

 L. 514       474  LOAD_NAME                array_function_dispatch
              476  LOAD_NAME                _code_dispatcher
              478  CALL_FUNCTION_1       1  ''

 L. 515       480  LOAD_CONST               (None, None)
              482  LOAD_CODE                <code_object decode>
              484  LOAD_STR                 'decode'
              486  MAKE_FUNCTION_1          'default'
              488  CALL_FUNCTION_1       1  ''
              490  STORE_NAME               decode

 L. 560       492  LOAD_NAME                array_function_dispatch
              494  LOAD_NAME                _code_dispatcher
              496  CALL_FUNCTION_1       1  ''

 L. 561       498  LOAD_CONST               (None, None)
              500  LOAD_CODE                <code_object encode>
              502  LOAD_STR                 'encode'
              504  MAKE_FUNCTION_1          'default'
              506  CALL_FUNCTION_1       1  ''
              508  STORE_NAME               encode

 L. 596       510  LOAD_CONST               (None, None)
              512  LOAD_CODE                <code_object _endswith_dispatcher>
              514  LOAD_STR                 '_endswith_dispatcher'
              516  MAKE_FUNCTION_1          'default'
              518  STORE_NAME               _endswith_dispatcher

 L. 600       520  LOAD_NAME                array_function_dispatch
              522  LOAD_NAME                _endswith_dispatcher
              524  CALL_FUNCTION_1       1  ''

 L. 601       526  LOAD_CONST               (0, None)
              528  LOAD_CODE                <code_object endswith>
              530  LOAD_STR                 'endswith'
              532  MAKE_FUNCTION_1          'default'
              534  CALL_FUNCTION_1       1  ''
              536  STORE_NAME               endswith

 L. 644       538  LOAD_CONST               (None,)
              540  LOAD_CODE                <code_object _expandtabs_dispatcher>
              542  LOAD_STR                 '_expandtabs_dispatcher'
              544  MAKE_FUNCTION_1          'default'
              546  STORE_NAME               _expandtabs_dispatcher

 L. 648       548  LOAD_NAME                array_function_dispatch
              550  LOAD_NAME                _expandtabs_dispatcher
              552  CALL_FUNCTION_1       1  ''

 L. 649       554  LOAD_CONST               (8,)
              556  LOAD_CODE                <code_object expandtabs>
              558  LOAD_STR                 'expandtabs'
              560  MAKE_FUNCTION_1          'default'
              562  CALL_FUNCTION_1       1  ''
              564  STORE_NAME               expandtabs

 L. 684       566  LOAD_NAME                array_function_dispatch
              568  LOAD_NAME                _count_dispatcher
              570  CALL_FUNCTION_1       1  ''

 L. 685       572  LOAD_CONST               (0, None)
              574  LOAD_CODE                <code_object find>
              576  LOAD_STR                 'find'
              578  MAKE_FUNCTION_1          'default'
              580  CALL_FUNCTION_1       1  ''
              582  STORE_NAME               find

 L. 720       584  LOAD_NAME                array_function_dispatch
              586  LOAD_NAME                _count_dispatcher
              588  CALL_FUNCTION_1       1  ''

 L. 721       590  LOAD_CONST               (0, None)
              592  LOAD_CODE                <code_object index>
              594  LOAD_STR                 'index'
              596  MAKE_FUNCTION_1          'default'
              598  CALL_FUNCTION_1       1  ''
              600  STORE_NAME               index

 L. 749       602  LOAD_NAME                array_function_dispatch
              604  LOAD_NAME                _unary_op_dispatcher
              606  CALL_FUNCTION_1       1  ''

 L. 750       608  LOAD_CODE                <code_object isalnum>
              610  LOAD_STR                 'isalnum'
              612  MAKE_FUNCTION_0          'Neither defaults, keyword-only args, annotations, nor closures'
              614  CALL_FUNCTION_1       1  ''
              616  STORE_NAME               isalnum

 L. 775       618  LOAD_NAME                array_function_dispatch
              620  LOAD_NAME                _unary_op_dispatcher
              622  CALL_FUNCTION_1       1  ''

 L. 776       624  LOAD_CODE                <code_object isalpha>
              626  LOAD_STR                 'isalpha'
              628  MAKE_FUNCTION_0          'Neither defaults, keyword-only args, annotations, nor closures'
              630  CALL_FUNCTION_1       1  ''
              632  STORE_NAME               isalpha

 L. 801       634  LOAD_NAME                array_function_dispatch
              636  LOAD_NAME                _unary_op_dispatcher
              638  CALL_FUNCTION_1       1  ''

 L. 802       640  LOAD_CODE                <code_object isdigit>
              642  LOAD_STR                 'isdigit'
              644  MAKE_FUNCTION_0          'Neither defaults, keyword-only args, annotations, nor closures'
              646  CALL_FUNCTION_1       1  ''
              648  STORE_NAME               isdigit

 L. 827       650  LOAD_NAME                array_function_dispatch
              652  LOAD_NAME                _unary_op_dispatcher
              654  CALL_FUNCTION_1       1  ''

 L. 828       656  LOAD_CODE                <code_object islower>
              658  LOAD_STR                 'islower'
              660  MAKE_FUNCTION_0          'Neither defaults, keyword-only args, annotations, nor closures'
              662  CALL_FUNCTION_1       1  ''
              664  STORE_NAME               islower

 L. 854       666  LOAD_NAME                array_function_dispatch
              668  LOAD_NAME                _unary_op_dispatcher
              670  CALL_FUNCTION_1       1  ''

 L. 855       672  LOAD_CODE                <code_object isspace>
              674  LOAD_STR                 'isspace'
              676  MAKE_FUNCTION_0          'Neither defaults, keyword-only args, annotations, nor closures'
              678  CALL_FUNCTION_1       1  ''
              680  STORE_NAME               isspace

 L. 881       682  LOAD_NAME                array_function_dispatch
              684  LOAD_NAME                _unary_op_dispatcher
              686  CALL_FUNCTION_1       1  ''

 L. 882       688  LOAD_CODE                <code_object istitle>
              690  LOAD_STR                 'istitle'
              692  MAKE_FUNCTION_0          'Neither defaults, keyword-only args, annotations, nor closures'
              694  CALL_FUNCTION_1       1  ''
              696  STORE_NAME               istitle

 L. 907       698  LOAD_NAME                array_function_dispatch
              700  LOAD_NAME                _unary_op_dispatcher
              702  CALL_FUNCTION_1       1  ''

 L. 908       704  LOAD_CODE                <code_object isupper>
              706  LOAD_STR                 'isupper'
              708  MAKE_FUNCTION_0          'Neither defaults, keyword-only args, annotations, nor closures'
              710  CALL_FUNCTION_1       1  ''
              712  STORE_NAME               isupper

 L. 934       714  LOAD_CODE                <code_object _join_dispatcher>
              716  LOAD_STR                 '_join_dispatcher'
              718  MAKE_FUNCTION_0          'Neither defaults, keyword-only args, annotations, nor closures'
              720  STORE_NAME               _join_dispatcher

 L. 938       722  LOAD_NAME                array_function_dispatch
              724  LOAD_NAME                _join_dispatcher
              726  CALL_FUNCTION_1       1  ''

 L. 939       728  LOAD_CODE                <code_object join>
              730  LOAD_STR                 'join'
              732  MAKE_FUNCTION_0          'Neither defaults, keyword-only args, annotations, nor closures'
              734  CALL_FUNCTION_1       1  ''
              736  STORE_NAME               join

 L. 965       738  LOAD_CONST               (None,)
              740  LOAD_CODE                <code_object _just_dispatcher>
              742  LOAD_STR                 '_just_dispatcher'
              744  MAKE_FUNCTION_1          'default'
              746  STORE_NAME               _just_dispatcher

 L. 969       748  LOAD_NAME                array_function_dispatch
              750  LOAD_NAME                _just_dispatcher
              752  CALL_FUNCTION_1       1  ''

 L. 970       754  LOAD_CONST               (' ',)
              756  LOAD_CODE                <code_object ljust>
              758  LOAD_STR                 'ljust'
              760  MAKE_FUNCTION_1          'default'
              762  CALL_FUNCTION_1       1  ''
              764  STORE_NAME               ljust

 L.1005       766  LOAD_NAME                array_function_dispatch
              768  LOAD_NAME                _unary_op_dispatcher
              770  CALL_FUNCTION_1       1  ''

 L.1006       772  LOAD_CODE                <code_object lower>
              774  LOAD_STR                 'lower'
              776  MAKE_FUNCTION_0          'Neither defaults, keyword-only args, annotations, nor closures'
              778  CALL_FUNCTION_1       1  ''
              780  STORE_NAME               lower

 L.1040       782  LOAD_CONST               (None,)
              784  LOAD_CODE                <code_object _strip_dispatcher>
              786  LOAD_STR                 '_strip_dispatcher'
              788  MAKE_FUNCTION_1          'default'
              790  STORE_NAME               _strip_dispatcher

 L.1044       792  LOAD_NAME                array_function_dispatch
              794  LOAD_NAME                _strip_dispatcher
              796  CALL_FUNCTION_1       1  ''

 L.1045       798  LOAD_CONST               (None,)
              800  LOAD_CODE                <code_object lstrip>
              802  LOAD_STR                 'lstrip'
              804  MAKE_FUNCTION_1          'default'
              806  CALL_FUNCTION_1       1  ''
              808  STORE_NAME               lstrip

 L.1099       810  LOAD_CODE                <code_object _partition_dispatcher>
              812  LOAD_STR                 '_partition_dispatcher'
              814  MAKE_FUNCTION_0          'Neither defaults, keyword-only args, annotations, nor closures'
              816  STORE_NAME               _partition_dispatcher

 L.1103       818  LOAD_NAME                array_function_dispatch
              820  LOAD_NAME                _partition_dispatcher
              822  CALL_FUNCTION_1       1  ''

 L.1104       824  LOAD_CODE                <code_object partition>
              826  LOAD_STR                 'partition'
              828  MAKE_FUNCTION_0          'Neither defaults, keyword-only args, annotations, nor closures'
              830  CALL_FUNCTION_1       1  ''
              832  STORE_NAME               partition

 L.1139       834  LOAD_CONST               (None,)
              836  LOAD_CODE                <code_object _replace_dispatcher>
              838  LOAD_STR                 '_replace_dispatcher'
              840  MAKE_FUNCTION_1          'default'
              842  STORE_NAME               _replace_dispatcher

 L.1143       844  LOAD_NAME                array_function_dispatch
              846  LOAD_NAME                _replace_dispatcher
              848  CALL_FUNCTION_1       1  ''

 L.1144       850  LOAD_CONST               (None,)
              852  LOAD_CODE                <code_object replace>
              854  LOAD_STR                 'replace'
              856  MAKE_FUNCTION_1          'default'
              858  CALL_FUNCTION_1       1  ''
              860  STORE_NAME               replace

 L.1176       862  LOAD_NAME                array_function_dispatch
              864  LOAD_NAME                _count_dispatcher
              866  CALL_FUNCTION_1       1  ''

 L.1177       868  LOAD_CONST               (0, None)
              870  LOAD_CODE                <code_object rfind>
              872  LOAD_STR                 'rfind'
              874  MAKE_FUNCTION_1          'default'
              876  CALL_FUNCTION_1       1  ''
              878  STORE_NAME               rfind

 L.1209       880  LOAD_NAME                array_function_dispatch
              882  LOAD_NAME                _count_dispatcher
              884  CALL_FUNCTION_1       1  ''

 L.1210       886  LOAD_CONST               (0, None)
              888  LOAD_CODE                <code_object rindex>
              890  LOAD_STR                 'rindex'
              892  MAKE_FUNCTION_1          'default'
              894  CALL_FUNCTION_1       1  ''
              896  STORE_NAME               rindex

 L.1239       898  LOAD_NAME                array_function_dispatch
              900  LOAD_NAME                _just_dispatcher
              902  CALL_FUNCTION_1       1  ''

 L.1240       904  LOAD_CONST               (' ',)
              906  LOAD_CODE                <code_object rjust>
              908  LOAD_STR                 'rjust'
              910  MAKE_FUNCTION_1          'default'
              912  CALL_FUNCTION_1       1  ''
              914  STORE_NAME               rjust

 L.1275       916  LOAD_NAME                array_function_dispatch
              918  LOAD_NAME                _partition_dispatcher
              920  CALL_FUNCTION_1       1  ''

 L.1276       922  LOAD_CODE                <code_object rpartition>
              924  LOAD_STR                 'rpartition'
              926  MAKE_FUNCTION_0          'Neither defaults, keyword-only args, annotations, nor closures'
              928  CALL_FUNCTION_1       1  ''
              930  STORE_NAME               rpartition

 L.1311       932  LOAD_CONST               (None, None)
              934  LOAD_CODE                <code_object _split_dispatcher>
              936  LOAD_STR                 '_split_dispatcher'
              938  MAKE_FUNCTION_1          'default'
              940  STORE_NAME               _split_dispatcher

 L.1315       942  LOAD_NAME                array_function_dispatch
              944  LOAD_NAME                _split_dispatcher
              946  CALL_FUNCTION_1       1  ''

 L.1316       948  LOAD_CONST               (None, None)
              950  LOAD_CODE                <code_object rsplit>
              952  LOAD_STR                 'rsplit'
              954  MAKE_FUNCTION_1          'default'
              956  CALL_FUNCTION_1       1  ''
              958  STORE_NAME               rsplit

 L.1353       960  LOAD_CONST               (None,)
              962  LOAD_CODE                <code_object _strip_dispatcher>
              964  LOAD_STR                 '_strip_dispatcher'
              966  MAKE_FUNCTION_1          'default'
              968  STORE_NAME               _strip_dispatcher

 L.1357       970  LOAD_NAME                array_function_dispatch
              972  LOAD_NAME                _strip_dispatcher
              974  CALL_FUNCTION_1       1  ''

 L.1358       976  LOAD_CONST               (None,)
              978  LOAD_CODE                <code_object rstrip>
              980  LOAD_STR                 'rstrip'
              982  MAKE_FUNCTION_1          'default'
              984  CALL_FUNCTION_1       1  ''
              986  STORE_NAME               rstrip

 L.1402       988  LOAD_NAME                array_function_dispatch
              990  LOAD_NAME                _split_dispatcher
              992  CALL_FUNCTION_1       1  ''

 L.1403       994  LOAD_CONST               (None, None)
              996  LOAD_CODE                <code_object split>
              998  LOAD_STR                 'split'
             1000  MAKE_FUNCTION_1          'default'
             1002  CALL_FUNCTION_1       1  ''
             1004  STORE_NAME               split

 L.1437      1006  LOAD_CONST               (None,)
             1008  LOAD_CODE                <code_object _splitlines_dispatcher>
             1010  LOAD_STR                 '_splitlines_dispatcher'
             1012  MAKE_FUNCTION_1          'default'
             1014  STORE_NAME               _splitlines_dispatcher

 L.1441      1016  LOAD_NAME                array_function_dispatch
             1018  LOAD_NAME                _splitlines_dispatcher
             1020  CALL_FUNCTION_1       1  ''

 L.1442      1022  LOAD_CONST               (None,)
             1024  LOAD_CODE                <code_object splitlines>
             1026  LOAD_STR                 'splitlines'
             1028  MAKE_FUNCTION_1          'default'
             1030  CALL_FUNCTION_1       1  ''
             1032  STORE_NAME               splitlines

 L.1471      1034  LOAD_CONST               (None, None)
             1036  LOAD_CODE                <code_object _startswith_dispatcher>
             1038  LOAD_STR                 '_startswith_dispatcher'
             1040  MAKE_FUNCTION_1          'default'
             1042  STORE_NAME               _startswith_dispatcher

 L.1475      1044  LOAD_NAME                array_function_dispatch
             1046  LOAD_NAME                _startswith_dispatcher
             1048  CALL_FUNCTION_1       1  ''

 L.1476      1050  LOAD_CONST               (0, None)
             1052  LOAD_CODE                <code_object startswith>
             1054  LOAD_STR                 'startswith'
             1056  MAKE_FUNCTION_1          'default'
             1058  CALL_FUNCTION_1       1  ''
             1060  STORE_NAME               startswith

 L.1507      1062  LOAD_NAME                array_function_dispatch
             1064  LOAD_NAME                _strip_dispatcher
             1066  CALL_FUNCTION_1       1  ''

 L.1508      1068  LOAD_CONST               (None,)
             1070  LOAD_CODE                <code_object strip>
             1072  LOAD_STR                 'strip'
             1074  MAKE_FUNCTION_1          'default'
             1076  CALL_FUNCTION_1       1  ''
             1078  STORE_NAME               strip

 L.1552      1080  LOAD_NAME                array_function_dispatch
             1082  LOAD_NAME                _unary_op_dispatcher
             1084  CALL_FUNCTION_1       1  ''

 L.1553      1086  LOAD_CODE                <code_object swapcase>
             1088  LOAD_STR                 'swapcase'
             1090  MAKE_FUNCTION_0          'Neither defaults, keyword-only args, annotations, nor closures'
             1092  CALL_FUNCTION_1       1  ''
             1094  STORE_NAME               swapcase

 L.1590      1096  LOAD_NAME                array_function_dispatch
             1098  LOAD_NAME                _unary_op_dispatcher
             1100  CALL_FUNCTION_1       1  ''

 L.1591      1102  LOAD_CODE                <code_object title>
             1104  LOAD_STR                 'title'
             1106  MAKE_FUNCTION_0          'Neither defaults, keyword-only args, annotations, nor closures'
             1108  CALL_FUNCTION_1       1  ''
             1110  STORE_NAME               title

 L.1630      1112  LOAD_CONST               (None,)
             1114  LOAD_CODE                <code_object _translate_dispatcher>
             1116  LOAD_STR                 '_translate_dispatcher'
             1118  MAKE_FUNCTION_1          'default'
             1120  STORE_NAME               _translate_dispatcher

 L.1634      1122  LOAD_NAME                array_function_dispatch
             1124  LOAD_NAME                _translate_dispatcher
             1126  CALL_FUNCTION_1       1  ''

 L.1635      1128  LOAD_CONST               (None,)
             1130  LOAD_CODE                <code_object translate>
             1132  LOAD_STR                 'translate'
             1134  MAKE_FUNCTION_1          'default'
             1136  CALL_FUNCTION_1       1  ''
             1138  STORE_NAME               translate

 L.1671      1140  LOAD_NAME                array_function_dispatch
             1142  LOAD_NAME                _unary_op_dispatcher
             1144  CALL_FUNCTION_1       1  ''

 L.1672      1146  LOAD_CODE                <code_object upper>
             1148  LOAD_STR                 'upper'
             1150  MAKE_FUNCTION_0          'Neither defaults, keyword-only args, annotations, nor closures'
             1152  CALL_FUNCTION_1       1  ''
             1154  STORE_NAME               upper

 L.1706      1156  LOAD_CODE                <code_object _zfill_dispatcher>
             1158  LOAD_STR                 '_zfill_dispatcher'
             1160  MAKE_FUNCTION_0          'Neither defaults, keyword-only args, annotations, nor closures'
             1162  STORE_NAME               _zfill_dispatcher

 L.1710      1164  LOAD_NAME                array_function_dispatch
             1166  LOAD_NAME                _zfill_dispatcher
             1168  CALL_FUNCTION_1       1  ''

 L.1711      1170  LOAD_CODE                <code_object zfill>
             1172  LOAD_STR                 'zfill'
             1174  MAKE_FUNCTION_0          'Neither defaults, keyword-only args, annotations, nor closures'
             1176  CALL_FUNCTION_1       1  ''
             1178  STORE_NAME               zfill

 L.1741      1180  LOAD_NAME                array_function_dispatch
             1182  LOAD_NAME                _unary_op_dispatcher
             1184  CALL_FUNCTION_1       1  ''

 L.1742      1186  LOAD_CODE                <code_object isnumeric>
             1188  LOAD_STR                 'isnumeric'
             1190  MAKE_FUNCTION_0          'Neither defaults, keyword-only args, annotations, nor closures'
             1192  CALL_FUNCTION_1       1  ''
             1194  STORE_NAME               isnumeric

 L.1773      1196  LOAD_NAME                array_function_dispatch
             1198  LOAD_NAME                _unary_op_dispatcher
             1200  CALL_FUNCTION_1       1  ''

 L.1774      1202  LOAD_CODE                <code_object isdecimal>
             1204  LOAD_STR                 'isdecimal'
             1206  MAKE_FUNCTION_0          'Neither defaults, keyword-only args, annotations, nor closures'
             1208  CALL_FUNCTION_1       1  ''
             1210  STORE_NAME               isdecimal

 L.1805      1212  LOAD_NAME                set_module
             1214  LOAD_STR                 'numpy'
             1216  CALL_FUNCTION_1       1  ''

 L.1806      1218  LOAD_BUILD_CLASS 
             1220  LOAD_CODE                <code_object chararray>
             1222  LOAD_STR                 'chararray'
             1224  MAKE_FUNCTION_0          'Neither defaults, keyword-only args, annotations, nor closures'
             1226  LOAD_STR                 'chararray'
             1228  LOAD_NAME                ndarray
             1230  CALL_FUNCTION_3       3  ''
             1232  CALL_FUNCTION_1       1  ''
             1234  STORE_NAME               chararray

 L.2613      1236  LOAD_CONST               (None, True, None, None)
             1238  LOAD_CODE                <code_object array>
             1240  LOAD_STR                 'array'
             1242  MAKE_FUNCTION_1          'default'
             1244  STORE_NAME               array

 L.2746      1246  LOAD_CONST               (None, None, None)
             1248  LOAD_CODE                <code_object asarray>
             1250  LOAD_STR                 'asarray'
             1252  MAKE_FUNCTION_1          'default'
             1254  STORE_NAME               asarray

Parse error at or near `CALL_FINALLY' instruction at offset 144

Instruction context:
   
 L.  30       140  BUILD_LIST_0          0 
                 142  LOAD_CONST               ('equal', 'not_equal', 'greater_equal', 'less_equal', 'greater', 'less', 'str_len', 'add', 'multiply', 'mod', 'capitalize', 'center', 'count', 'decode', 'encode', 'endswith', 'expandtabs', 'find', 'index', 'isalnum', 'isalpha', 'isdigit', 'islower', 'isspace', 'istitle', 'isupper', 'join', 'ljust', 'lower', 'lstrip', 'partition', 'replace', 'rfind', 'rindex', 'rjust', 'rpartition', 'rsplit', 'rstrip', 'split', 'splitlines', 'startswith', 'strip', 'swapcase', 'title', 'translate', 'upper', 'zfill', 'isnumeric', 'isdecimal', 'array', 'asarray')
->               144  CALL_FINALLY        147  'to 147'
                 146  STORE_NAME               __all__

test/162606.pyc -- 
# decompile failed
