
# file test/162644.pyc
# --- This code section failed: ---

 L.   1         0  LOAD_CONST               0
                2  LOAD_CONST               None
                4  IMPORT_NAME              sys
                6  STORE_NAME               sys

 L.   2         8  LOAD_CONST               0
               10  LOAD_CONST               None
               12  IMPORT_NAME              os
               14  STORE_NAME               os

 L.   3        16  LOAD_CONST               0
               18  LOAD_CONST               None
               20  IMPORT_NAME              re
               22  STORE_NAME               re

 L.   4        24  LOAD_CONST               0
               26  LOAD_CONST               None
               28  IMPORT_NAME              functools
               30  STORE_NAME               functools

 L.   5        32  LOAD_CONST               0
               34  LOAD_CONST               None
               36  IMPORT_NAME              itertools
               38  STORE_NAME               itertools

 L.   6        40  LOAD_CONST               0
               42  LOAD_CONST               None
               44  IMPORT_NAME              warnings
               46  STORE_NAME               warnings

 L.   7        48  LOAD_CONST               0
               50  LOAD_CONST               None
               52  IMPORT_NAME              weakref
               54  STORE_NAME               weakref

 L.   8        56  LOAD_CONST               0
               58  LOAD_CONST               None
               60  IMPORT_NAME              contextlib
               62  STORE_NAME               contextlib

 L.   9        64  LOAD_CONST               0
               66  LOAD_CONST               ('itemgetter', 'index')
               68  IMPORT_NAME              operator
               70  IMPORT_FROM              itemgetter
               72  STORE_NAME               itemgetter
               74  IMPORT_FROM              index
               76  STORE_NAME               opindex
               78  POP_TOP          

 L.  10        80  LOAD_CONST               0
               82  LOAD_CONST               ('Mapping',)
               84  IMPORT_NAME_ATTR         collections.abc
               86  IMPORT_FROM              Mapping
               88  STORE_NAME               Mapping
               90  POP_TOP          

 L.  12        92  LOAD_CONST               0
               94  LOAD_CONST               None
               96  IMPORT_NAME              numpy
               98  STORE_NAME               np

 L.  13       100  LOAD_CONST               1
              102  LOAD_CONST               ('format',)
              104  IMPORT_NAME              
              106  IMPORT_FROM              format
              108  STORE_NAME               format
              110  POP_TOP          

 L.  14       112  LOAD_CONST               1
              114  LOAD_CONST               ('DataSource',)
              116  IMPORT_NAME              _datasource
              118  IMPORT_FROM              DataSource
              120  STORE_NAME               DataSource
              122  POP_TOP          

 L.  15       124  LOAD_CONST               0
              126  LOAD_CONST               ('overrides',)
              128  IMPORT_NAME_ATTR         numpy.core
              130  IMPORT_FROM              overrides
              132  STORE_NAME               overrides
              134  POP_TOP          

 L.  16       136  LOAD_CONST               0
              138  LOAD_CONST               ('packbits', 'unpackbits')
              140  IMPORT_NAME_ATTR         numpy.core.multiarray
              142  IMPORT_FROM              packbits
              144  STORE_NAME               packbits
              146  IMPORT_FROM              unpackbits
              148  STORE_NAME               unpackbits
              150  POP_TOP          

 L.  17       152  LOAD_CONST               0
              154  LOAD_CONST               ('set_array_function_like_doc', 'set_module')
              156  IMPORT_NAME_ATTR         numpy.core.overrides
              158  IMPORT_FROM              set_array_function_like_doc
              160  STORE_NAME               set_array_function_like_doc
              162  IMPORT_FROM              set_module
              164  STORE_NAME               set_module
              166  POP_TOP          

 L.  18       168  LOAD_CONST               0
              170  LOAD_CONST               ('recursive',)
              172  IMPORT_NAME_ATTR         numpy.core._internal
              174  IMPORT_FROM              recursive
              176  STORE_NAME               recursive
              178  POP_TOP          

 L.  19       180  LOAD_CONST               1
              182  LOAD_CONST               ('LineSplitter', 'NameValidator', 'StringConverter', 'ConverterError', 'ConverterLockError', 'ConversionWarning', '_is_string_like', 'has_nested_fields', 'flatten_dtype', 'easy_dtype', '_decode_line')
              184  IMPORT_NAME              _iotools
              186  IMPORT_FROM              LineSplitter
              188  STORE_NAME               LineSplitter
              190  IMPORT_FROM              NameValidator
              192  STORE_NAME               NameValidator
              194  IMPORT_FROM              StringConverter
              196  STORE_NAME               StringConverter
              198  IMPORT_FROM              ConverterError
              200  STORE_NAME               ConverterError
              202  IMPORT_FROM              ConverterLockError
              204  STORE_NAME               ConverterLockError
              206  IMPORT_FROM              ConversionWarning
              208  STORE_NAME               ConversionWarning
              210  IMPORT_FROM              _is_string_like
              212  STORE_NAME               _is_string_like
              214  IMPORT_FROM              has_nested_fields
              216  STORE_NAME               has_nested_fields
              218  IMPORT_FROM              flatten_dtype
              220  STORE_NAME               flatten_dtype
              222  IMPORT_FROM              easy_dtype
              224  STORE_NAME               easy_dtype
              226  IMPORT_FROM              _decode_line
              228  STORE_NAME               _decode_line
              230  POP_TOP          

 L.  25       232  LOAD_CONST               0
              234  LOAD_CONST               ('asbytes', 'asstr', 'asunicode', 'os_fspath', 'os_PathLike', 'pickle')
              236  IMPORT_NAME_ATTR         numpy.compat
              238  IMPORT_FROM              asbytes
              240  STORE_NAME               asbytes
              242  IMPORT_FROM              asstr
              244  STORE_NAME               asstr
              246  IMPORT_FROM              asunicode
              248  STORE_NAME               asunicode
              250  IMPORT_FROM              os_fspath
              252  STORE_NAME               os_fspath
              254  IMPORT_FROM              os_PathLike
              256  STORE_NAME               os_PathLike
              258  IMPORT_FROM              pickle
              260  STORE_NAME               pickle
              262  POP_TOP          

 L.  31       264  LOAD_NAME                set_module
              266  LOAD_STR                 'numpy'
              268  CALL_FUNCTION_1       1  ''

 L.  32       270  LOAD_CODE                <code_object loads>
              272  LOAD_STR                 'loads'
              274  MAKE_FUNCTION_0          'Neither defaults, keyword-only args, annotations, nor closures'
              276  CALL_FUNCTION_1       1  ''
              278  STORE_NAME               loads

 L.  40       280  BUILD_LIST_0          0 
              282  LOAD_CONST               ('savetxt', 'loadtxt', 'genfromtxt', 'ndfromtxt', 'mafromtxt', 'recfromtxt', 'recfromcsv', 'load', 'loads', 'save', 'savez', 'savez_compressed', 'packbits', 'unpackbits', 'fromregex', 'DataSource')
              284  CALL_FINALLY        287  'to 287'
              286  STORE_NAME               __all__

 L.  47       288  LOAD_NAME                functools
              290  LOAD_ATTR                partial

 L.  48       292  LOAD_NAME                overrides
              294  LOAD_ATTR                array_function_dispatch
              296  LOAD_STR                 'numpy'

 L.  47       298  LOAD_CONST               ('module',)
              300  CALL_FUNCTION_KW_2     2  '2 total positional and keyword args'
              302  STORE_NAME               array_function_dispatch

 L.  51       304  LOAD_BUILD_CLASS 
              306  LOAD_CODE                <code_object BagObj>
              308  LOAD_STR                 'BagObj'
              310  MAKE_FUNCTION_0          'Neither defaults, keyword-only args, annotations, nor closures'
              312  LOAD_STR                 'BagObj'
              314  CALL_FUNCTION_2       2  ''
              316  STORE_NAME               BagObj

 L. 100       318  LOAD_CODE                <code_object zipfile_factory>
              320  LOAD_STR                 'zipfile_factory'
              322  MAKE_FUNCTION_0          'Neither defaults, keyword-only args, annotations, nor closures'
              324  STORE_NAME               zipfile_factory

 L. 115       326  LOAD_BUILD_CLASS 
              328  LOAD_CODE                <code_object NpzFile>
              330  LOAD_STR                 'NpzFile'
              332  MAKE_FUNCTION_0          'Neither defaults, keyword-only args, annotations, nor closures'
              334  LOAD_STR                 'NpzFile'
              336  LOAD_NAME                Mapping
              338  CALL_FUNCTION_3       3  ''
              340  STORE_NAME               NpzFile

 L. 284       342  LOAD_NAME                set_module
              344  LOAD_STR                 'numpy'
              346  CALL_FUNCTION_1       1  ''

 L. 285       348  LOAD_CONST               (None, False, True, 'ASCII')
              350  LOAD_CODE                <code_object load>
              352  LOAD_STR                 'load'
              354  MAKE_FUNCTION_1          'default'
              356  CALL_FUNCTION_1       1  ''
              358  STORE_NAME               load

 L. 454       360  LOAD_CONST               (None, None)
              362  LOAD_CODE                <code_object _save_dispatcher>
              364  LOAD_STR                 '_save_dispatcher'
              366  MAKE_FUNCTION_1          'default'
              368  STORE_NAME               _save_dispatcher

 L. 458       370  LOAD_NAME                array_function_dispatch
              372  LOAD_NAME                _save_dispatcher
              374  CALL_FUNCTION_1       1  ''

 L. 459       376  LOAD_CONST               (True, True)
              378  LOAD_CODE                <code_object save>
              380  LOAD_STR                 'save'
              382  MAKE_FUNCTION_1          'default'
              384  CALL_FUNCTION_1       1  ''
              386  STORE_NAME               save

 L. 533       388  LOAD_CODE                <code_object _savez_dispatcher>
              390  LOAD_STR                 '_savez_dispatcher'
              392  MAKE_FUNCTION_0          'Neither defaults, keyword-only args, annotations, nor closures'
              394  STORE_NAME               _savez_dispatcher

 L. 538       396  LOAD_NAME                array_function_dispatch
              398  LOAD_NAME                _savez_dispatcher
              400  CALL_FUNCTION_1       1  ''

 L. 539       402  LOAD_CODE                <code_object savez>
              404  LOAD_STR                 'savez'
              406  MAKE_FUNCTION_0          'Neither defaults, keyword-only args, annotations, nor closures'
              408  CALL_FUNCTION_1       1  ''
              410  STORE_NAME               savez

 L. 621       412  LOAD_CODE                <code_object _savez_compressed_dispatcher>
              414  LOAD_STR                 '_savez_compressed_dispatcher'
              416  MAKE_FUNCTION_0          'Neither defaults, keyword-only args, annotations, nor closures'
              418  STORE_NAME               _savez_compressed_dispatcher

 L. 626       420  LOAD_NAME                array_function_dispatch
              422  LOAD_NAME                _savez_compressed_dispatcher
              424  CALL_FUNCTION_1       1  ''

 L. 627       426  LOAD_CODE                <code_object savez_compressed>
              428  LOAD_STR                 'savez_compressed'
              430  MAKE_FUNCTION_0          'Neither defaults, keyword-only args, annotations, nor closures'
              432  CALL_FUNCTION_1       1  ''
              434  STORE_NAME               savez_compressed

 L. 692       436  LOAD_CONST               (True, None)
              438  LOAD_CODE                <code_object _savez>
              440  LOAD_STR                 '_savez'
              442  MAKE_FUNCTION_1          'default'
              444  STORE_NAME               _savez

 L. 729       446  LOAD_CODE                <code_object _getconv>
              448  LOAD_STR                 '_getconv'
              450  MAKE_FUNCTION_0          'Neither defaults, keyword-only args, annotations, nor closures'
              452  STORE_NAME               _getconv

 L. 762       454  LOAD_CONST               50000
              456  STORE_NAME               _loadtxt_chunksize

 L. 765       458  LOAD_CONST               (None, None, None, None, None, None, None, None, None, None)

 L. 767       460  LOAD_CONST               None

 L. 765       462  LOAD_CONST               ('like',)
              464  BUILD_CONST_KEY_MAP_1     1 
              466  LOAD_CODE                <code_object _loadtxt_dispatcher>
              468  LOAD_STR                 '_loadtxt_dispatcher'
              470  MAKE_FUNCTION_3          'default, keyword-only'
              472  STORE_NAME               _loadtxt_dispatcher

 L. 771       474  LOAD_NAME                set_array_function_like_doc

 L. 772       476  LOAD_NAME                set_module
              478  LOAD_STR                 'numpy'
              480  CALL_FUNCTION_1       1  ''

 L. 773       482  LOAD_NAME                float
              484  LOAD_STR                 '#'
              486  LOAD_CONST               None

 L. 774       488  LOAD_CONST               None
              490  LOAD_CONST               0
              492  LOAD_CONST               None
              494  LOAD_CONST               False

 L. 775       496  LOAD_CONST               0
              498  LOAD_STR                 'bytes'
              500  LOAD_CONST               None

 L. 773       502  BUILD_TUPLE_10       10 

 L. 775       504  LOAD_CONST               None

 L. 773       506  LOAD_CONST               ('like',)
              508  BUILD_CONST_KEY_MAP_1     1 
              510  LOAD_CODE                <code_object loadtxt>
              512  LOAD_STR                 'loadtxt'
              514  MAKE_FUNCTION_3          'default, keyword-only'
              516  CALL_FUNCTION_1       1  ''
              518  CALL_FUNCTION_1       1  ''
              520  STORE_NAME               loadtxt

 L.1191       522  LOAD_NAME                array_function_dispatch

 L.1192       524  LOAD_NAME                _loadtxt_dispatcher

 L.1191       526  CALL_FUNCTION_1       1  ''

 L.1193       528  LOAD_NAME                loadtxt

 L.1191       530  CALL_FUNCTION_1       1  ''
              532  STORE_NAME               _loadtxt_with_like

 L.1196       534  LOAD_CONST               (None, None, None, None, None, None, None)
              536  LOAD_CODE                <code_object _savetxt_dispatcher>
              538  LOAD_STR                 '_savetxt_dispatcher'
              540  MAKE_FUNCTION_1          'default'
              542  STORE_NAME               _savetxt_dispatcher

 L.1202       544  LOAD_NAME                array_function_dispatch
              546  LOAD_NAME                _savetxt_dispatcher
              548  CALL_FUNCTION_1       1  ''

 L.1203       550  LOAD_CONST               ('%.18e', ' ', '\n', '', '', '# ', None)
              552  LOAD_CODE                <code_object savetxt>
              554  LOAD_STR                 'savetxt'
              556  MAKE_FUNCTION_1          'default'
              558  CALL_FUNCTION_1       1  ''
              560  STORE_NAME               savetxt

 L.1450       562  LOAD_NAME                set_module
              564  LOAD_STR                 'numpy'
              566  CALL_FUNCTION_1       1  ''

 L.1451       568  LOAD_CONST               (None,)
              570  LOAD_CODE                <code_object fromregex>
              572  LOAD_STR                 'fromregex'
              574  MAKE_FUNCTION_1          'default'
              576  CALL_FUNCTION_1       1  ''
              578  STORE_NAME               fromregex

 L.1549       580  LOAD_CONST               (None, None, None, None, None, None, None, None, None, None, None, None, None, None, None, None, None, None, None, None, None, None)

 L.1556       582  LOAD_CONST               None

 L.1549       584  LOAD_CONST               ('like',)
              586  BUILD_CONST_KEY_MAP_1     1 
              588  LOAD_CODE                <code_object _genfromtxt_dispatcher>
              590  LOAD_STR                 '_genfromtxt_dispatcher'
              592  MAKE_FUNCTION_3          'default, keyword-only'
              594  STORE_NAME               _genfromtxt_dispatcher

 L.1560       596  LOAD_NAME                set_array_function_like_doc

 L.1561       598  LOAD_NAME                set_module
              600  LOAD_STR                 'numpy'
              602  CALL_FUNCTION_1       1  ''

 L.1562       604  LOAD_NAME                float
              606  LOAD_STR                 '#'
              608  LOAD_CONST               None

 L.1563       610  LOAD_CONST               0
              612  LOAD_CONST               0
              614  LOAD_CONST               None

 L.1564       616  LOAD_CONST               None
              618  LOAD_CONST               None
              620  LOAD_CONST               None

 L.1565       622  LOAD_CONST               None
              624  LOAD_CONST               None

 L.1566       626  LOAD_STR                 ''
              628  LOAD_METHOD              join
              630  LOAD_NAME                sorted
              632  LOAD_NAME                NameValidator
              634  LOAD_ATTR                defaultdeletechars
              636  CALL_FUNCTION_1       1  ''
              638  CALL_METHOD_1         1  ''

 L.1567       640  LOAD_STR                 '_'
              642  LOAD_CONST               False
              644  LOAD_CONST               True

 L.1568       646  LOAD_STR                 'f%i'
              648  LOAD_CONST               None
              650  LOAD_CONST               False
              652  LOAD_CONST               True

 L.1569       654  LOAD_CONST               True
              656  LOAD_CONST               None
              658  LOAD_STR                 'bytes'

 L.1562       660  BUILD_TUPLE_22       22 

 L.1570       662  LOAD_CONST               None

 L.1562       664  LOAD_CONST               ('like',)
              666  BUILD_CONST_KEY_MAP_1     1 
              668  LOAD_CODE                <code_object genfromtxt>
              670  LOAD_STR                 'genfromtxt'
              672  MAKE_FUNCTION_3          'default, keyword-only'
              674  CALL_FUNCTION_1       1  ''
              676  CALL_FUNCTION_1       1  ''
              678  STORE_NAME               genfromtxt

 L.2287       680  LOAD_NAME                array_function_dispatch

 L.2288       682  LOAD_NAME                _genfromtxt_dispatcher

 L.2287       684  CALL_FUNCTION_1       1  ''

 L.2289       686  LOAD_NAME                genfromtxt

 L.2287       688  CALL_FUNCTION_1       1  ''
              690  STORE_NAME               _genfromtxt_with_like

 L.2292       692  LOAD_CODE                <code_object ndfromtxt>
              694  LOAD_STR                 'ndfromtxt'
              696  MAKE_FUNCTION_0          'Neither defaults, keyword-only args, annotations, nor closures'
              698  STORE_NAME               ndfromtxt

 L.2320       700  LOAD_CODE                <code_object mafromtxt>
              702  LOAD_STR                 'mafromtxt'
              704  MAKE_FUNCTION_0          'Neither defaults, keyword-only args, annotations, nor closures'
              706  STORE_NAME               mafromtxt

 L.2348       708  LOAD_CODE                <code_object recfromtxt>
              710  LOAD_STR                 'recfromtxt'
              712  MAKE_FUNCTION_0          'Neither defaults, keyword-only args, annotations, nor closures'
              714  STORE_NAME               recfromtxt

 L.2380       716  LOAD_CODE                <code_object recfromcsv>
              718  LOAD_STR                 'recfromcsv'
              720  MAKE_FUNCTION_0          'Neither defaults, keyword-only args, annotations, nor closures'
              722  STORE_NAME               recfromcsv

Parse error at or near `CALL_FINALLY' instruction at offset 284

Instruction context:
   
 L.  40       280  BUILD_LIST_0          0 
                 282  LOAD_CONST               ('savetxt', 'loadtxt', 'genfromtxt', 'ndfromtxt', 'mafromtxt', 'recfromtxt', 'recfromcsv', 'load', 'loads', 'save', 'savez', 'savez_compressed', 'packbits', 'unpackbits', 'fromregex', 'DataSource')
->               284  CALL_FINALLY        287  'to 287'
                 286  STORE_NAME               __all__

test/162644.pyc -- 
# decompile failed
