
# file test/162639.pyc
# --- This code section failed: ---

 L.   1         0  LOAD_CONST               0
                2  LOAD_CONST               None
                4  IMPORT_NAME_ATTR         collections.abc
                6  STORE_NAME               collections

 L.   2         8  LOAD_CONST               0
               10  LOAD_CONST               None
               12  IMPORT_NAME              functools
               14  STORE_NAME               functools

 L.   3        16  LOAD_CONST               0
               18  LOAD_CONST               None
               20  IMPORT_NAME              re
               22  STORE_NAME               re

 L.   4        24  LOAD_CONST               0
               26  LOAD_CONST               None
               28  IMPORT_NAME              sys
               30  STORE_NAME               sys

 L.   5        32  LOAD_CONST               0
               34  LOAD_CONST               None
               36  IMPORT_NAME              warnings
               38  STORE_NAME               warnings

 L.   7        40  LOAD_CONST               0
               42  LOAD_CONST               None
               44  IMPORT_NAME              numpy
               46  STORE_NAME               np

 L.   8        48  LOAD_CONST               0
               50  LOAD_CONST               None
               52  IMPORT_NAME_ATTR         numpy.core.numeric
               54  IMPORT_FROM              core
               56  ROT_TWO          
               58  POP_TOP          
               60  IMPORT_FROM              numeric
               62  STORE_NAME               _nx
               64  POP_TOP          

 L.   9        66  LOAD_CONST               0
               68  LOAD_CONST               ('transpose',)
               70  IMPORT_NAME_ATTR         numpy.core
               72  IMPORT_FROM              transpose
               74  STORE_NAME               transpose
               76  POP_TOP          

 L.  10        78  LOAD_CONST               0
               80  LOAD_CONST               ('ones', 'zeros_like', 'arange', 'concatenate', 'array', 'asarray', 'asanyarray', 'empty', 'ndarray', 'around', 'floor', 'ceil', 'take', 'dot', 'where', 'intp', 'integer', 'isscalar', 'absolute')
               82  IMPORT_NAME_ATTR         numpy.core.numeric
               84  IMPORT_FROM              ones
               86  STORE_NAME               ones
               88  IMPORT_FROM              zeros_like
               90  STORE_NAME               zeros_like
               92  IMPORT_FROM              arange
               94  STORE_NAME               arange
               96  IMPORT_FROM              concatenate
               98  STORE_NAME               concatenate
              100  IMPORT_FROM              array
              102  STORE_NAME               array
              104  IMPORT_FROM              asarray
              106  STORE_NAME               asarray
              108  IMPORT_FROM              asanyarray
              110  STORE_NAME               asanyarray
              112  IMPORT_FROM              empty
              114  STORE_NAME               empty
              116  IMPORT_FROM              ndarray
              118  STORE_NAME               ndarray
              120  IMPORT_FROM              around
              122  STORE_NAME               around
              124  IMPORT_FROM              floor
              126  STORE_NAME               floor
              128  IMPORT_FROM              ceil
              130  STORE_NAME               ceil
              132  IMPORT_FROM              take
              134  STORE_NAME               take
              136  IMPORT_FROM              dot
              138  STORE_NAME               dot
              140  IMPORT_FROM              where
              142  STORE_NAME               where
              144  IMPORT_FROM              intp
              146  STORE_NAME               intp
              148  IMPORT_FROM              integer
              150  STORE_NAME               integer
              152  IMPORT_FROM              isscalar
              154  STORE_NAME               isscalar
              156  IMPORT_FROM              absolute
              158  STORE_NAME               absolute
              160  POP_TOP          

 L.  15       162  LOAD_CONST               0
              164  LOAD_CONST               ('pi', 'add', 'arctan2', 'frompyfunc', 'cos', 'less_equal', 'sqrt', 'sin', 'mod', 'exp', 'not_equal', 'subtract')
              166  IMPORT_NAME_ATTR         numpy.core.umath
              168  IMPORT_FROM              pi
              170  STORE_NAME               pi
              172  IMPORT_FROM              add
              174  STORE_NAME               add
              176  IMPORT_FROM              arctan2
              178  STORE_NAME               arctan2
              180  IMPORT_FROM              frompyfunc
              182  STORE_NAME               frompyfunc
              184  IMPORT_FROM              cos
              186  STORE_NAME               cos
              188  IMPORT_FROM              less_equal
              190  STORE_NAME               less_equal
              192  IMPORT_FROM              sqrt
              194  STORE_NAME               sqrt
              196  IMPORT_FROM              sin
              198  STORE_NAME               sin
              200  IMPORT_FROM              mod
              202  STORE_NAME               mod
              204  IMPORT_FROM              exp
              206  STORE_NAME               exp
              208  IMPORT_FROM              not_equal
              210  STORE_NAME               not_equal
              212  IMPORT_FROM              subtract
              214  STORE_NAME               subtract
              216  POP_TOP          

 L.  19       218  LOAD_CONST               0
              220  LOAD_CONST               ('ravel', 'nonzero', 'partition', 'mean', 'any', 'sum')
              222  IMPORT_NAME_ATTR         numpy.core.fromnumeric
              224  IMPORT_FROM              ravel
              226  STORE_NAME               ravel
              228  IMPORT_FROM              nonzero
              230  STORE_NAME               nonzero
              232  IMPORT_FROM              partition
              234  STORE_NAME               partition
              236  IMPORT_FROM              mean
              238  STORE_NAME               mean
              240  IMPORT_FROM              any
              242  STORE_NAME               any
              244  IMPORT_FROM              sum
              246  STORE_NAME               sum
              248  POP_TOP          

 L.  22       250  LOAD_CONST               0
              252  LOAD_CONST               ('typecodes',)
              254  IMPORT_NAME_ATTR         numpy.core.numerictypes
              256  IMPORT_FROM              typecodes
              258  STORE_NAME               typecodes
              260  POP_TOP          

 L.  23       262  LOAD_CONST               0
              264  LOAD_CONST               ('set_module',)
              266  IMPORT_NAME_ATTR         numpy.core.overrides
              268  IMPORT_FROM              set_module
              270  STORE_NAME               set_module
              272  POP_TOP          

 L.  24       274  LOAD_CONST               0
              276  LOAD_CONST               ('overrides',)
              278  IMPORT_NAME_ATTR         numpy.core
              280  IMPORT_FROM              overrides
              282  STORE_NAME               overrides
              284  POP_TOP          

 L.  25       286  LOAD_CONST               0
              288  LOAD_CONST               ('add_newdoc',)
              290  IMPORT_NAME_ATTR         numpy.core.function_base
              292  IMPORT_FROM              add_newdoc
              294  STORE_NAME               add_newdoc
              296  POP_TOP          

 L.  26       298  LOAD_CONST               0
              300  LOAD_CONST               ('diag',)
              302  IMPORT_NAME_ATTR         numpy.lib.twodim_base
              304  IMPORT_FROM              diag
              306  STORE_NAME               diag
              308  POP_TOP          

 L.  27       310  LOAD_CONST               0
              312  LOAD_CONST               ('_insert', 'add_docstring', 'bincount', 'normalize_axis_index', '_monotonicity', 'interp', 'interp_complex')
              314  IMPORT_NAME_ATTR         numpy.core.multiarray
              316  IMPORT_FROM              _insert
              318  STORE_NAME               _insert
              320  IMPORT_FROM              add_docstring
              322  STORE_NAME               add_docstring
              324  IMPORT_FROM              bincount
              326  STORE_NAME               bincount
              328  IMPORT_FROM              normalize_axis_index
              330  STORE_NAME               normalize_axis_index
              332  IMPORT_FROM              _monotonicity
              334  STORE_NAME               _monotonicity
              336  IMPORT_FROM              interp
              338  STORE_NAME               compiled_interp
              340  IMPORT_FROM              interp_complex
              342  STORE_NAME               compiled_interp_complex
              344  POP_TOP          

 L.  31       346  LOAD_CONST               0
              348  LOAD_CONST               ('_add_newdoc_ufunc',)
              350  IMPORT_NAME_ATTR         numpy.core.umath
              352  IMPORT_FROM              _add_newdoc_ufunc
              354  STORE_NAME               add_newdoc_ufunc
              356  POP_TOP          

 L.  33       358  LOAD_CONST               0
              360  LOAD_CONST               None
              362  IMPORT_NAME              builtins
              364  STORE_NAME               builtins

 L.  36       366  LOAD_CONST               0
              368  LOAD_CONST               ('histogram', 'histogramdd')
              370  IMPORT_NAME_ATTR         numpy.lib.histograms
              372  IMPORT_FROM              histogram
              374  STORE_NAME               histogram
              376  IMPORT_FROM              histogramdd
              378  STORE_NAME               histogramdd
              380  POP_TOP          

 L.  39       382  LOAD_NAME                functools
              384  LOAD_ATTR                partial

 L.  40       386  LOAD_NAME                overrides
              388  LOAD_ATTR                array_function_dispatch
              390  LOAD_STR                 'numpy'

 L.  39       392  LOAD_CONST               ('module',)
              394  CALL_FUNCTION_KW_2     2  '2 total positional and keyword args'
              396  STORE_NAME               array_function_dispatch

 L.  43       398  BUILD_LIST_0          0 
              400  LOAD_CONST               ('select', 'piecewise', 'trim_zeros', 'copy', 'iterable', 'percentile', 'diff', 'gradient', 'angle', 'unwrap', 'sort_complex', 'disp', 'flip', 'rot90', 'extract', 'place', 'vectorize', 'asarray_chkfinite', 'average', 'bincount', 'digitize', 'cov', 'corrcoef', 'msort', 'median', 'sinc', 'hamming', 'hanning', 'bartlett', 'blackman', 'kaiser', 'trapz', 'i0', 'add_newdoc', 'add_docstring', 'meshgrid', 'delete', 'insert', 'append', 'interp', 'add_newdoc_ufunc', 'quantile')
              402  CALL_FINALLY        405  'to 405'
              404  STORE_NAME               __all__

 L.  55       406  LOAD_CONST               (None, None)
              408  LOAD_CODE                <code_object _rot90_dispatcher>
              410  LOAD_STR                 '_rot90_dispatcher'
              412  MAKE_FUNCTION_1          'default'
              414  STORE_NAME               _rot90_dispatcher

 L.  59       416  LOAD_NAME                array_function_dispatch
              418  LOAD_NAME                _rot90_dispatcher
              420  CALL_FUNCTION_1       1  ''

 L.  60       422  LOAD_CONST               (1, (0, 1))
              424  LOAD_CODE                <code_object rot90>
              426  LOAD_STR                 'rot90'
              428  MAKE_FUNCTION_1          'default'
              430  CALL_FUNCTION_1       1  ''
              432  STORE_NAME               rot90

 L. 146       434  LOAD_CONST               (None,)
              436  LOAD_CODE                <code_object _flip_dispatcher>
              438  LOAD_STR                 '_flip_dispatcher'
              440  MAKE_FUNCTION_1          'default'
              442  STORE_NAME               _flip_dispatcher

 L. 150       444  LOAD_NAME                array_function_dispatch
              446  LOAD_NAME                _flip_dispatcher
              448  CALL_FUNCTION_1       1  ''

 L. 151       450  LOAD_CONST               (None,)
              452  LOAD_CODE                <code_object flip>
              454  LOAD_STR                 'flip'
              456  MAKE_FUNCTION_1          'default'
              458  CALL_FUNCTION_1       1  ''
              460  STORE_NAME               flip

 L. 244       462  LOAD_NAME                set_module
              464  LOAD_STR                 'numpy'
              466  CALL_FUNCTION_1       1  ''

 L. 245       468  LOAD_CODE                <code_object iterable>
              470  LOAD_STR                 'iterable'
              472  MAKE_FUNCTION_0          'Neither defaults, keyword-only args, annotations, nor closures'
              474  CALL_FUNCTION_1       1  ''
              476  STORE_NAME               iterable

 L. 276       478  LOAD_CONST               (None, None, None)
              480  LOAD_CODE                <code_object _average_dispatcher>
              482  LOAD_STR                 '_average_dispatcher'
              484  MAKE_FUNCTION_1          'default'
              486  STORE_NAME               _average_dispatcher

 L. 280       488  LOAD_NAME                array_function_dispatch
              490  LOAD_NAME                _average_dispatcher
              492  CALL_FUNCTION_1       1  ''

 L. 281       494  LOAD_CONST               (None, None, False)
              496  LOAD_CODE                <code_object average>
              498  LOAD_STR                 'average'
              500  MAKE_FUNCTION_1          'default'
              502  CALL_FUNCTION_1       1  ''
              504  STORE_NAME               average

 L. 422       506  LOAD_NAME                set_module
              508  LOAD_STR                 'numpy'
              510  CALL_FUNCTION_1       1  ''

 L. 423       512  LOAD_CONST               (None, None)
              514  LOAD_CODE                <code_object asarray_chkfinite>
              516  LOAD_STR                 'asarray_chkfinite'
              518  MAKE_FUNCTION_1          'default'
              520  CALL_FUNCTION_1       1  ''
              522  STORE_NAME               asarray_chkfinite

 L. 493       524  LOAD_CODE                <code_object _piecewise_dispatcher>
              526  LOAD_STR                 '_piecewise_dispatcher'
              528  MAKE_FUNCTION_0          'Neither defaults, keyword-only args, annotations, nor closures'
              530  STORE_NAME               _piecewise_dispatcher

 L. 500       532  LOAD_NAME                array_function_dispatch
              534  LOAD_NAME                _piecewise_dispatcher
              536  CALL_FUNCTION_1       1  ''

 L. 501       538  LOAD_CODE                <code_object piecewise>
              540  LOAD_STR                 'piecewise'
              542  MAKE_FUNCTION_0          'Neither defaults, keyword-only args, annotations, nor closures'
              544  CALL_FUNCTION_1       1  ''
              546  STORE_NAME               piecewise

 L. 621       548  LOAD_CONST               (None,)
              550  LOAD_CODE                <code_object _select_dispatcher>
              552  LOAD_STR                 '_select_dispatcher'
              554  MAKE_FUNCTION_1          'default'
              556  STORE_NAME               _select_dispatcher

 L. 626       558  LOAD_NAME                array_function_dispatch
              560  LOAD_NAME                _select_dispatcher
              562  CALL_FUNCTION_1       1  ''

 L. 627       564  LOAD_CONST               (0,)
              566  LOAD_CODE                <code_object select>
              568  LOAD_STR                 'select'
              570  MAKE_FUNCTION_1          'default'
              572  CALL_FUNCTION_1       1  ''
              574  STORE_NAME               select

 L. 722       576  LOAD_CONST               (None, None)
              578  LOAD_CODE                <code_object _copy_dispatcher>
              580  LOAD_STR                 '_copy_dispatcher'
              582  MAKE_FUNCTION_1          'default'
              584  STORE_NAME               _copy_dispatcher

 L. 726       586  LOAD_NAME                array_function_dispatch
              588  LOAD_NAME                _copy_dispatcher
              590  CALL_FUNCTION_1       1  ''

 L. 727       592  LOAD_CONST               ('K', False)
              594  LOAD_CODE                <code_object copy>
              596  LOAD_STR                 'copy'
              598  MAKE_FUNCTION_1          'default'
              600  CALL_FUNCTION_1       1  ''
              602  STORE_NAME               copy

 L. 809       604  LOAD_CONST               None
              606  LOAD_CONST               None
              608  LOAD_CONST               ('axis', 'edge_order')
              610  BUILD_CONST_KEY_MAP_2     2 
              612  LOAD_CODE                <code_object _gradient_dispatcher>
              614  LOAD_STR                 '_gradient_dispatcher'
              616  MAKE_FUNCTION_2          'keyword-only'
              618  STORE_NAME               _gradient_dispatcher

 L. 814       620  LOAD_NAME                array_function_dispatch
              622  LOAD_NAME                _gradient_dispatcher
              624  CALL_FUNCTION_1       1  ''

 L. 815       626  LOAD_CONST               None
              628  LOAD_CONST               1
              630  LOAD_CONST               ('axis', 'edge_order')
              632  BUILD_CONST_KEY_MAP_2     2 
              634  LOAD_CODE                <code_object gradient>
              636  LOAD_STR                 'gradient'
              638  MAKE_FUNCTION_2          'keyword-only'
              640  CALL_FUNCTION_1       1  ''
              642  STORE_NAME               gradient

 L.1160       644  LOAD_CONST               (None, None, None, None)
              646  LOAD_CODE                <code_object _diff_dispatcher>
              648  LOAD_STR                 '_diff_dispatcher'
              650  MAKE_FUNCTION_1          'default'
              652  STORE_NAME               _diff_dispatcher

 L.1164       654  LOAD_NAME                array_function_dispatch
              656  LOAD_NAME                _diff_dispatcher
              658  CALL_FUNCTION_1       1  ''

 L.1165       660  LOAD_CONST               1
              662  LOAD_CONST               -1
              664  LOAD_NAME                np
              666  LOAD_ATTR                _NoValue
              668  LOAD_NAME                np
              670  LOAD_ATTR                _NoValue
              672  BUILD_TUPLE_4         4 
              674  LOAD_CODE                <code_object diff>
              676  LOAD_STR                 'diff'
              678  MAKE_FUNCTION_1          'default'
              680  CALL_FUNCTION_1       1  ''
              682  STORE_NAME               diff

 L.1297       684  LOAD_CONST               (None, None, None)
              686  LOAD_CODE                <code_object _interp_dispatcher>
              688  LOAD_STR                 '_interp_dispatcher'
              690  MAKE_FUNCTION_1          'default'
              692  STORE_NAME               _interp_dispatcher

 L.1301       694  LOAD_NAME                array_function_dispatch
              696  LOAD_NAME                _interp_dispatcher
              698  CALL_FUNCTION_1       1  ''

 L.1302       700  LOAD_CONST               (None, None, None)
              702  LOAD_CODE                <code_object interp>
              704  LOAD_STR                 'interp'
              706  MAKE_FUNCTION_1          'default'
              708  CALL_FUNCTION_1       1  ''
              710  STORE_NAME               interp

 L.1442       712  LOAD_CONST               (None,)
              714  LOAD_CODE                <code_object _angle_dispatcher>
              716  LOAD_STR                 '_angle_dispatcher'
              718  MAKE_FUNCTION_1          'default'
              720  STORE_NAME               _angle_dispatcher

 L.1446       722  LOAD_NAME                array_function_dispatch
              724  LOAD_NAME                _angle_dispatcher
              726  CALL_FUNCTION_1       1  ''

 L.1447       728  LOAD_CONST               (False,)
              730  LOAD_CODE                <code_object angle>
              732  LOAD_STR                 'angle'
              734  MAKE_FUNCTION_1          'default'
              736  CALL_FUNCTION_1       1  ''
              738  STORE_NAME               angle

 L.1499       740  LOAD_CONST               (None, None)
              742  LOAD_CONST               None
              744  LOAD_CONST               ('period',)
              746  BUILD_CONST_KEY_MAP_1     1 
              748  LOAD_CODE                <code_object _unwrap_dispatcher>
              750  LOAD_STR                 '_unwrap_dispatcher'
              752  MAKE_FUNCTION_3          'default, keyword-only'
              754  STORE_NAME               _unwrap_dispatcher

 L.1503       756  LOAD_NAME                array_function_dispatch
              758  LOAD_NAME                _unwrap_dispatcher
              760  CALL_FUNCTION_1       1  ''

 L.1504       762  LOAD_CONST               (None, -1)
              764  LOAD_CONST               2
              766  LOAD_NAME                pi
              768  BINARY_MULTIPLY  
              770  LOAD_CONST               ('period',)
              772  BUILD_CONST_KEY_MAP_1     1 
              774  LOAD_CODE                <code_object unwrap>
              776  LOAD_STR                 'unwrap'
              778  MAKE_FUNCTION_3          'default, keyword-only'
              780  CALL_FUNCTION_1       1  ''
              782  STORE_NAME               unwrap

 L.1599       784  LOAD_CODE                <code_object _sort_complex>
              786  LOAD_STR                 '_sort_complex'
              788  MAKE_FUNCTION_0          'Neither defaults, keyword-only args, annotations, nor closures'
              790  STORE_NAME               _sort_complex

 L.1603       792  LOAD_NAME                array_function_dispatch
              794  LOAD_NAME                _sort_complex
              796  CALL_FUNCTION_1       1  ''

 L.1604       798  LOAD_CODE                <code_object sort_complex>
              800  LOAD_STR                 'sort_complex'
              802  MAKE_FUNCTION_0          'Neither defaults, keyword-only args, annotations, nor closures'
              804  CALL_FUNCTION_1       1  ''
              806  STORE_NAME               sort_complex

 L.1640       808  LOAD_CONST               (None,)
              810  LOAD_CODE                <code_object _trim_zeros>
              812  LOAD_STR                 '_trim_zeros'
              814  MAKE_FUNCTION_1          'default'
              816  STORE_NAME               _trim_zeros

 L.1644       818  LOAD_NAME                array_function_dispatch
              820  LOAD_NAME                _trim_zeros
              822  CALL_FUNCTION_1       1  ''

 L.1645       824  LOAD_CONST               ('fb',)
              826  LOAD_CODE                <code_object trim_zeros>
              828  LOAD_STR                 'trim_zeros'
              830  MAKE_FUNCTION_1          'default'
              832  CALL_FUNCTION_1       1  ''
              834  STORE_NAME               trim_zeros

 L.1697       836  LOAD_CODE                <code_object _extract_dispatcher>
              838  LOAD_STR                 '_extract_dispatcher'
              840  MAKE_FUNCTION_0          'Neither defaults, keyword-only args, annotations, nor closures'
              842  STORE_NAME               _extract_dispatcher

 L.1701       844  LOAD_NAME                array_function_dispatch
              846  LOAD_NAME                _extract_dispatcher
              848  CALL_FUNCTION_1       1  ''

 L.1702       850  LOAD_CODE                <code_object extract>
              852  LOAD_STR                 'extract'
              854  MAKE_FUNCTION_0          'Neither defaults, keyword-only args, annotations, nor closures'
              856  CALL_FUNCTION_1       1  ''
              858  STORE_NAME               extract

 L.1753       860  LOAD_CODE                <code_object _place_dispatcher>
              862  LOAD_STR                 '_place_dispatcher'
              864  MAKE_FUNCTION_0          'Neither defaults, keyword-only args, annotations, nor closures'
              866  STORE_NAME               _place_dispatcher

 L.1757       868  LOAD_NAME                array_function_dispatch
              870  LOAD_NAME                _place_dispatcher
              872  CALL_FUNCTION_1       1  ''

 L.1758       874  LOAD_CODE                <code_object place>
              876  LOAD_STR                 'place'
              878  MAKE_FUNCTION_0          'Neither defaults, keyword-only args, annotations, nor closures'
              880  CALL_FUNCTION_1       1  ''
              882  STORE_NAME               place

 L.1801       884  LOAD_CONST               (None, True)
              886  LOAD_CODE                <code_object disp>
              888  LOAD_STR                 'disp'
              890  MAKE_FUNCTION_1          'default'
              892  STORE_NAME               disp

 L.1844       894  LOAD_STR                 '\\w+'
              896  STORE_NAME               _DIMENSION_NAME

 L.1845       898  LOAD_STR                 '(?:{0:}(?:,{0:})*)?'
              900  LOAD_METHOD              format
              902  LOAD_NAME                _DIMENSION_NAME
              904  CALL_METHOD_1         1  ''
              906  STORE_NAME               _CORE_DIMENSION_LIST

 L.1846       908  LOAD_STR                 '\\({}\\)'
              910  LOAD_METHOD              format
              912  LOAD_NAME                _CORE_DIMENSION_LIST
              914  CALL_METHOD_1         1  ''
              916  STORE_NAME               _ARGUMENT

 L.1847       918  LOAD_STR                 '{0:}(?:,{0:})*'
              920  LOAD_METHOD              format
              922  LOAD_NAME                _ARGUMENT
              924  CALL_METHOD_1         1  ''
              926  STORE_NAME               _ARGUMENT_LIST

 L.1848       928  LOAD_STR                 '^{0:}->{0:}$'
              930  LOAD_METHOD              format
              932  LOAD_NAME                _ARGUMENT_LIST
              934  CALL_METHOD_1         1  ''
              936  STORE_NAME               _SIGNATURE

 L.1851       938  LOAD_CODE                <code_object _parse_gufunc_signature>
              940  LOAD_STR                 '_parse_gufunc_signature'
              942  MAKE_FUNCTION_0          'Neither defaults, keyword-only args, annotations, nor closures'
              944  STORE_NAME               _parse_gufunc_signature

 L.1874       946  LOAD_CODE                <code_object _update_dim_sizes>
              948  LOAD_STR                 '_update_dim_sizes'
              950  MAKE_FUNCTION_0          'Neither defaults, keyword-only args, annotations, nor closures'
              952  STORE_NAME               _update_dim_sizes

 L.1908       954  LOAD_CODE                <code_object _parse_input_dimensions>
              956  LOAD_STR                 '_parse_input_dimensions'
              958  MAKE_FUNCTION_0          'Neither defaults, keyword-only args, annotations, nor closures'
              960  STORE_NAME               _parse_input_dimensions

 L.1937       962  LOAD_CODE                <code_object _calculate_shapes>
              964  LOAD_STR                 '_calculate_shapes'
              966  MAKE_FUNCTION_0          'Neither defaults, keyword-only args, annotations, nor closures'
              968  STORE_NAME               _calculate_shapes

 L.1943       970  LOAD_CODE                <code_object _create_arrays>
              972  LOAD_STR                 '_create_arrays'
              974  MAKE_FUNCTION_0          'Neither defaults, keyword-only args, annotations, nor closures'
              976  STORE_NAME               _create_arrays

 L.1951       978  LOAD_NAME                set_module
              980  LOAD_STR                 'numpy'
              982  CALL_FUNCTION_1       1  ''

 L.1952       984  LOAD_BUILD_CLASS 
              986  LOAD_CODE                <code_object vectorize>
              988  LOAD_STR                 'vectorize'
              990  MAKE_FUNCTION_0          'Neither defaults, keyword-only args, annotations, nor closures'
              992  LOAD_STR                 'vectorize'
              994  CALL_FUNCTION_2       2  ''
              996  CALL_FUNCTION_1       1  ''
              998  STORE_NAME               vectorize

 L.2319      1000  LOAD_CONST               (None, None, None, None, None, None)

 L.2320      1002  LOAD_CONST               None

 L.2319      1004  LOAD_CONST               ('dtype',)
             1006  BUILD_CONST_KEY_MAP_1     1 
             1008  LOAD_CODE                <code_object _cov_dispatcher>
             1010  LOAD_STR                 '_cov_dispatcher'
             1012  MAKE_FUNCTION_3          'default, keyword-only'
             1014  STORE_NAME               _cov_dispatcher

 L.2324      1016  LOAD_NAME                array_function_dispatch
             1018  LOAD_NAME                _cov_dispatcher
             1020  CALL_FUNCTION_1       1  ''

 L.2325      1022  LOAD_CONST               (None, True, False, None, None, None)

 L.2326      1024  LOAD_CONST               None

 L.2325      1026  LOAD_CONST               ('dtype',)
             1028  BUILD_CONST_KEY_MAP_1     1 
             1030  LOAD_CODE                <code_object cov>
             1032  LOAD_STR                 'cov'
             1034  MAKE_FUNCTION_3          'default, keyword-only'
             1036  CALL_FUNCTION_1       1  ''
             1038  STORE_NAME               cov

 L.2546      1040  LOAD_CONST               (None, None, None, None)

 L.2547      1042  LOAD_CONST               None

 L.2546      1044  LOAD_CONST               ('dtype',)
             1046  BUILD_CONST_KEY_MAP_1     1 
             1048  LOAD_CODE                <code_object _corrcoef_dispatcher>
             1050  LOAD_STR                 '_corrcoef_dispatcher'
             1052  MAKE_FUNCTION_3          'default, keyword-only'
             1054  STORE_NAME               _corrcoef_dispatcher

 L.2551      1056  LOAD_NAME                array_function_dispatch
             1058  LOAD_NAME                _corrcoef_dispatcher
             1060  CALL_FUNCTION_1       1  ''

 L.2552      1062  LOAD_CONST               None
             1064  LOAD_CONST               True
             1066  LOAD_NAME                np
             1068  LOAD_ATTR                _NoValue
             1070  LOAD_NAME                np
             1072  LOAD_ATTR                _NoValue
             1074  BUILD_TUPLE_4         4 

 L.2553      1076  LOAD_CONST               None

 L.2552      1078  LOAD_CONST               ('dtype',)
             1080  BUILD_CONST_KEY_MAP_1     1 
             1082  LOAD_CODE                <code_object corrcoef>
             1084  LOAD_STR                 'corrcoef'
             1086  MAKE_FUNCTION_3          'default, keyword-only'
             1088  CALL_FUNCTION_1       1  ''
             1090  STORE_NAME               corrcoef

 L.2704      1092  LOAD_NAME                set_module
             1094  LOAD_STR                 'numpy'
             1096  CALL_FUNCTION_1       1  ''

 L.2705      1098  LOAD_CODE                <code_object blackman>
             1100  LOAD_STR                 'blackman'
             1102  MAKE_FUNCTION_0          'Neither defaults, keyword-only args, annotations, nor closures'
             1104  CALL_FUNCTION_1       1  ''
             1106  STORE_NAME               blackman

 L.2804      1108  LOAD_NAME                set_module
             1110  LOAD_STR                 'numpy'
             1112  CALL_FUNCTION_1       1  ''

 L.2805      1114  LOAD_CODE                <code_object bartlett>
             1116  LOAD_STR                 'bartlett'
             1118  MAKE_FUNCTION_0          'Neither defaults, keyword-only args, annotations, nor closures'
             1120  CALL_FUNCTION_1       1  ''
             1122  STORE_NAME               bartlett

 L.2913      1124  LOAD_NAME                set_module
             1126  LOAD_STR                 'numpy'
             1128  CALL_FUNCTION_1       1  ''

 L.2914      1130  LOAD_CODE                <code_object hanning>
             1132  LOAD_STR                 'hanning'
             1134  MAKE_FUNCTION_0          'Neither defaults, keyword-only args, annotations, nor closures'
             1136  CALL_FUNCTION_1       1  ''
             1138  STORE_NAME               hanning

 L.3017      1140  LOAD_NAME                set_module
             1142  LOAD_STR                 'numpy'
             1144  CALL_FUNCTION_1       1  ''

 L.3018      1146  LOAD_CODE                <code_object hamming>
             1148  LOAD_STR                 'hamming'
             1150  MAKE_FUNCTION_0          'Neither defaults, keyword-only args, annotations, nor closures'
             1152  CALL_FUNCTION_1       1  ''
             1154  STORE_NAME               hamming

 L.3119      1156  BUILD_LIST_0          0 
             1158  LOAD_CONST               (-4.4153416464793395e-18, 3.3307945188222384e-17, -2.431279846547955e-16, 1.715391285555133e-15, -1.1685332877993451e-14, 7.676185498604936e-14, -4.856446783111929e-13, 2.95505266312964e-12, -1.726826291441556e-11, 9.675809035373237e-11, -5.189795601635263e-10, 2.6598237246823866e-09, -1.300025009986248e-08, 6.046995022541919e-08, -2.670793853940612e-07, 1.1173875391201037e-06, -4.4167383584587505e-06, 1.6448448070728896e-05, -5.754195010082104e-05, 0.00018850288509584165, -0.0005763755745385824, 0.0016394756169413357, -0.004324309995050576, 0.010546460394594998, -0.02373741480589947, 0.04930528423967071, -0.09490109704804764, 0.17162090152220877, -0.3046826723431984, 0.6767952744094761)
             1160  CALL_FINALLY       1163  'to 1163'
             1162  STORE_NAME               _i0A

 L.3152      1164  BUILD_LIST_0          0 
             1166  LOAD_CONST               (-7.233180487874754e-18, -4.830504485944182e-18, 4.46562142029676e-17, 3.461222867697461e-17, -2.8276239805165836e-16, -3.425485619677219e-16, 1.7725601330565263e-15, 3.8116806693526224e-15, -9.554846698828307e-15, -4.150569347287222e-14, 1.54008621752141e-14, 3.8527783827421426e-13, 7.180124451383666e-13, -1.7941785315068062e-12, -1.3215811840447713e-11, -3.1499165279632416e-11, 1.1889147107846439e-11, 4.94060238822497e-10, 3.3962320257083865e-09, 2.266668990498178e-08, 2.0489185894690638e-07, 2.8913705208347567e-06, 6.889758346916825e-05, 0.0033691164782556943, 0.8044904110141088)
             1168  CALL_FINALLY       1171  'to 1171'
             1170  STORE_NAME               _i0B

 L.3181      1172  LOAD_CODE                <code_object _chbevl>
             1174  LOAD_STR                 '_chbevl'
             1176  MAKE_FUNCTION_0          'Neither defaults, keyword-only args, annotations, nor closures'
             1178  STORE_NAME               _chbevl

 L.3193      1180  LOAD_CODE                <code_object _i0_1>
             1182  LOAD_STR                 '_i0_1'
             1184  MAKE_FUNCTION_0          'Neither defaults, keyword-only args, annotations, nor closures'
             1186  STORE_NAME               _i0_1

 L.3197      1188  LOAD_CODE                <code_object _i0_2>
             1190  LOAD_STR                 '_i0_2'
             1192  MAKE_FUNCTION_0          'Neither defaults, keyword-only args, annotations, nor closures'
             1194  STORE_NAME               _i0_2

 L.3201      1196  LOAD_CODE                <code_object _i0_dispatcher>
             1198  LOAD_STR                 '_i0_dispatcher'
             1200  MAKE_FUNCTION_0          'Neither defaults, keyword-only args, annotations, nor closures'
             1202  STORE_NAME               _i0_dispatcher

 L.3205      1204  LOAD_NAME                array_function_dispatch
             1206  LOAD_NAME                _i0_dispatcher
             1208  CALL_FUNCTION_1       1  ''

 L.3206      1210  LOAD_CODE                <code_object i0>
             1212  LOAD_STR                 'i0'
             1214  MAKE_FUNCTION_0          'Neither defaults, keyword-only args, annotations, nor closures'
             1216  CALL_FUNCTION_1       1  ''
             1218  STORE_NAME               i0

 L.3267      1220  LOAD_NAME                set_module
             1222  LOAD_STR                 'numpy'
             1224  CALL_FUNCTION_1       1  ''

 L.3268      1226  LOAD_CODE                <code_object kaiser>
             1228  LOAD_STR                 'kaiser'
             1230  MAKE_FUNCTION_0          'Neither defaults, keyword-only args, annotations, nor closures'
             1232  CALL_FUNCTION_1       1  ''
             1234  STORE_NAME               kaiser

 L.3395      1236  LOAD_CODE                <code_object _sinc_dispatcher>
             1238  LOAD_STR                 '_sinc_dispatcher'
             1240  MAKE_FUNCTION_0          'Neither defaults, keyword-only args, annotations, nor closures'
             1242  STORE_NAME               _sinc_dispatcher

 L.3399      1244  LOAD_NAME                array_function_dispatch
             1246  LOAD_NAME                _sinc_dispatcher
             1248  CALL_FUNCTION_1       1  ''

 L.3400      1250  LOAD_CODE                <code_object sinc>
             1252  LOAD_STR                 'sinc'
             1254  MAKE_FUNCTION_0          'Neither defaults, keyword-only args, annotations, nor closures'
             1256  CALL_FUNCTION_1       1  ''
             1258  STORE_NAME               sinc

 L.3480      1260  LOAD_CODE                <code_object _msort_dispatcher>
             1262  LOAD_STR                 '_msort_dispatcher'
             1264  MAKE_FUNCTION_0          'Neither defaults, keyword-only args, annotations, nor closures'
             1266  STORE_NAME               _msort_dispatcher

 L.3484      1268  LOAD_NAME                array_function_dispatch
             1270  LOAD_NAME                _msort_dispatcher
             1272  CALL_FUNCTION_1       1  ''

 L.3485      1274  LOAD_CODE                <code_object msort>
             1276  LOAD_STR                 'msort'
             1278  MAKE_FUNCTION_0          'Neither defaults, keyword-only args, annotations, nor closures'
             1280  CALL_FUNCTION_1       1  ''
             1282  STORE_NAME               msort

 L.3513      1284  LOAD_CODE                <code_object _ureduce>
             1286  LOAD_STR                 '_ureduce'
             1288  MAKE_FUNCTION_0          'Neither defaults, keyword-only args, annotations, nor closures'
             1290  STORE_NAME               _ureduce

 L.3568      1292  LOAD_CONST               (None, None, None, None)
             1294  LOAD_CODE                <code_object _median_dispatcher>
             1296  LOAD_STR                 '_median_dispatcher'
             1298  MAKE_FUNCTION_1          'default'
             1300  STORE_NAME               _median_dispatcher

 L.3573      1302  LOAD_NAME                array_function_dispatch
             1304  LOAD_NAME                _median_dispatcher
             1306  CALL_FUNCTION_1       1  ''

 L.3574      1308  LOAD_CONST               (None, None, False, False)
             1310  LOAD_CODE                <code_object median>
             1312  LOAD_STR                 'median'
             1314  MAKE_FUNCTION_1          'default'
             1316  CALL_FUNCTION_1       1  ''
             1318  STORE_NAME               median

 L.3663      1320  LOAD_CONST               (None, None, False)
             1322  LOAD_CODE                <code_object _median>
             1324  LOAD_STR                 '_median'
             1326  MAKE_FUNCTION_1          'default'
             1328  STORE_NAME               _median

 L.3719      1330  LOAD_CONST               (None, None, None, None, None)
             1332  LOAD_CODE                <code_object _percentile_dispatcher>
             1334  LOAD_STR                 '_percentile_dispatcher'
             1336  MAKE_FUNCTION_1          'default'
             1338  STORE_NAME               _percentile_dispatcher

 L.3724      1340  LOAD_NAME                array_function_dispatch
             1342  LOAD_NAME                _percentile_dispatcher
             1344  CALL_FUNCTION_1       1  ''

 L.3725      1346  LOAD_CONST               (None, None, False, 'linear', False)
             1348  LOAD_CODE                <code_object percentile>
             1350  LOAD_STR                 'percentile'
             1352  MAKE_FUNCTION_1          'default'
             1354  CALL_FUNCTION_1       1  ''
             1356  STORE_NAME               percentile

 L.3871      1358  LOAD_CONST               (None, None, None, None, None)
             1360  LOAD_CODE                <code_object _quantile_dispatcher>
             1362  LOAD_STR                 '_quantile_dispatcher'
             1364  MAKE_FUNCTION_1          'default'
             1366  STORE_NAME               _quantile_dispatcher

 L.3876      1368  LOAD_NAME                array_function_dispatch
             1370  LOAD_NAME                _quantile_dispatcher
             1372  CALL_FUNCTION_1       1  ''

 L.3877      1374  LOAD_CONST               (None, None, False, 'linear', False)
             1376  LOAD_CODE                <code_object quantile>
             1378  LOAD_STR                 'quantile'
             1380  MAKE_FUNCTION_1          'default'
             1382  CALL_FUNCTION_1       1  ''
             1384  STORE_NAME               quantile

 L.3983      1386  LOAD_CONST               (None, None, False, 'linear', False)
             1388  LOAD_CODE                <code_object _quantile_unchecked>
             1390  LOAD_STR                 '_quantile_unchecked'
             1392  MAKE_FUNCTION_1          'default'
             1394  STORE_NAME               _quantile_unchecked

 L.3995      1396  LOAD_CODE                <code_object _quantile_is_valid>
             1398  LOAD_STR                 '_quantile_is_valid'
             1400  MAKE_FUNCTION_0          'Neither defaults, keyword-only args, annotations, nor closures'
             1402  STORE_NAME               _quantile_is_valid

 L.4007      1404  LOAD_CONST               (None,)
             1406  LOAD_CODE                <code_object _lerp>
             1408  LOAD_STR                 '_lerp'
             1410  MAKE_FUNCTION_1          'default'
             1412  STORE_NAME               _lerp

 L.4018      1414  LOAD_CONST               (None, None, False, 'linear', False)
             1416  LOAD_CODE                <code_object _quantile_ureduce_func>
             1418  LOAD_STR                 '_quantile_ureduce_func'
             1420  MAKE_FUNCTION_1          'default'
             1422  STORE_NAME               _quantile_ureduce_func

 L.4125      1424  LOAD_CONST               (None, None, None)
             1426  LOAD_CODE                <code_object _trapz_dispatcher>
             1428  LOAD_STR                 '_trapz_dispatcher'
             1430  MAKE_FUNCTION_1          'default'
             1432  STORE_NAME               _trapz_dispatcher

 L.4129      1434  LOAD_NAME                array_function_dispatch
             1436  LOAD_NAME                _trapz_dispatcher
             1438  CALL_FUNCTION_1       1  ''

 L.4130      1440  LOAD_CONST               (None, 1.0, -1)
             1442  LOAD_CODE                <code_object trapz>
             1444  LOAD_STR                 'trapz'
             1446  MAKE_FUNCTION_1          'default'
             1448  CALL_FUNCTION_1       1  ''
             1450  STORE_NAME               trapz

 L.4243      1452  LOAD_CONST               None
             1454  LOAD_CONST               None
             1456  LOAD_CONST               None
             1458  LOAD_CONST               ('copy', 'sparse', 'indexing')
             1460  BUILD_CONST_KEY_MAP_3     3 
             1462  LOAD_CODE                <code_object _meshgrid_dispatcher>
             1464  LOAD_STR                 '_meshgrid_dispatcher'
             1466  MAKE_FUNCTION_2          'keyword-only'
             1468  STORE_NAME               _meshgrid_dispatcher

 L.4248      1470  LOAD_NAME                array_function_dispatch
             1472  LOAD_NAME                _meshgrid_dispatcher
             1474  CALL_FUNCTION_1       1  ''

 L.4249      1476  LOAD_CONST               True
             1478  LOAD_CONST               False
             1480  LOAD_STR                 'xy'
             1482  LOAD_CONST               ('copy', 'sparse', 'indexing')
             1484  BUILD_CONST_KEY_MAP_3     3 
             1486  LOAD_CODE                <code_object meshgrid>
             1488  LOAD_STR                 'meshgrid'
             1490  MAKE_FUNCTION_2          'keyword-only'
             1492  CALL_FUNCTION_1       1  ''
             1494  STORE_NAME               meshgrid

 L.4378      1496  LOAD_CONST               (None,)
             1498  LOAD_CODE                <code_object _delete_dispatcher>
             1500  LOAD_STR                 '_delete_dispatcher'
             1502  MAKE_FUNCTION_1          'default'
             1504  STORE_NAME               _delete_dispatcher

 L.4382      1506  LOAD_NAME                array_function_dispatch
             1508  LOAD_NAME                _delete_dispatcher
             1510  CALL_FUNCTION_1       1  ''

 L.4383      1512  LOAD_CONST               (None,)
             1514  LOAD_CODE                <code_object delete>
             1516  LOAD_STR                 'delete'
             1518  MAKE_FUNCTION_1          'default'
             1520  CALL_FUNCTION_1       1  ''
             1522  STORE_NAME               delete

 L.4563      1524  LOAD_CONST               (None,)
             1526  LOAD_CODE                <code_object _insert_dispatcher>
             1528  LOAD_STR                 '_insert_dispatcher'
             1530  MAKE_FUNCTION_1          'default'
             1532  STORE_NAME               _insert_dispatcher

 L.4567      1534  LOAD_NAME                array_function_dispatch
             1536  LOAD_NAME                _insert_dispatcher
             1538  CALL_FUNCTION_1       1  ''

 L.4568      1540  LOAD_CONST               (None,)
             1542  LOAD_CODE                <code_object insert>
             1544  LOAD_STR                 'insert'
             1546  MAKE_FUNCTION_1          'default'
             1548  CALL_FUNCTION_1       1  ''
             1550  STORE_NAME               insert

 L.4758      1552  LOAD_CONST               (None,)
             1554  LOAD_CODE                <code_object _append_dispatcher>
             1556  LOAD_STR                 '_append_dispatcher'
             1558  MAKE_FUNCTION_1          'default'
             1560  STORE_NAME               _append_dispatcher

 L.4762      1562  LOAD_NAME                array_function_dispatch
             1564  LOAD_NAME                _append_dispatcher
             1566  CALL_FUNCTION_1       1  ''

 L.4763      1568  LOAD_CONST               (None,)
             1570  LOAD_CODE                <code_object append>
             1572  LOAD_STR                 'append'
             1574  MAKE_FUNCTION_1          'default'
             1576  CALL_FUNCTION_1       1  ''
             1578  STORE_NAME               append

 L.4820      1580  LOAD_CONST               (None,)
             1582  LOAD_CODE                <code_object _digitize_dispatcher>
             1584  LOAD_STR                 '_digitize_dispatcher'
             1586  MAKE_FUNCTION_1          'default'
             1588  STORE_NAME               _digitize_dispatcher

 L.4824      1590  LOAD_NAME                array_function_dispatch
             1592  LOAD_NAME                _digitize_dispatcher
             1594  CALL_FUNCTION_1       1  ''

 L.4825      1596  LOAD_CONST               (False,)
             1598  LOAD_CODE                <code_object digitize>
             1600  LOAD_STR                 'digitize'
             1602  MAKE_FUNCTION_1          'default'
             1604  CALL_FUNCTION_1       1  ''
             1606  STORE_NAME               digitize

Parse error at or near `CALL_FINALLY' instruction at offset 402

Instruction context:
   
 L.  43       398  BUILD_LIST_0          0 
                 400  LOAD_CONST               ('select', 'piecewise', 'trim_zeros', 'copy', 'iterable', 'percentile', 'diff', 'gradient', 'angle', 'unwrap', 'sort_complex', 'disp', 'flip', 'rot90', 'extract', 'place', 'vectorize', 'asarray_chkfinite', 'average', 'bincount', 'digitize', 'cov', 'corrcoef', 'msort', 'median', 'sinc', 'hamming', 'hanning', 'bartlett', 'blackman', 'kaiser', 'trapz', 'i0', 'add_newdoc', 'add_docstring', 'meshgrid', 'delete', 'insert', 'append', 'interp', 'add_newdoc_ufunc', 'quantile')
->               402  CALL_FINALLY        405  'to 405'
                 404  STORE_NAME               __all__

test/162639.pyc -- 
# decompile failed
