
# file test/162649.pyc
# --- This code section failed: ---

 L.   1         0  LOAD_STR                 ' Basic functions for manipulating 2d arrays\n\n'
                2  STORE_NAME               __doc__

 L.   4         4  LOAD_CONST               0
                6  LOAD_CONST               None
                8  IMPORT_NAME              functools
               10  STORE_NAME               functools

 L.   6        12  LOAD_CONST               0
               14  LOAD_CONST               ('asanyarray', 'arange', 'zeros', 'greater_equal', 'multiply', 'ones', 'asarray', 'where', 'int8', 'int16', 'int32', 'int64', 'intp', 'empty', 'promote_types', 'diagonal', 'nonzero', 'indices')
               16  IMPORT_NAME_ATTR         numpy.core.numeric
               18  IMPORT_FROM              asanyarray
               20  STORE_NAME               asanyarray
               22  IMPORT_FROM              arange
               24  STORE_NAME               arange
               26  IMPORT_FROM              zeros
               28  STORE_NAME               zeros
               30  IMPORT_FROM              greater_equal
               32  STORE_NAME               greater_equal
               34  IMPORT_FROM              multiply
               36  STORE_NAME               multiply
               38  IMPORT_FROM              ones
               40  STORE_NAME               ones
               42  IMPORT_FROM              asarray
               44  STORE_NAME               asarray
               46  IMPORT_FROM              where
               48  STORE_NAME               where
               50  IMPORT_FROM              int8
               52  STORE_NAME               int8
               54  IMPORT_FROM              int16
               56  STORE_NAME               int16
               58  IMPORT_FROM              int32
               60  STORE_NAME               int32
               62  IMPORT_FROM              int64
               64  STORE_NAME               int64
               66  IMPORT_FROM              intp
               68  STORE_NAME               intp
               70  IMPORT_FROM              empty
               72  STORE_NAME               empty
               74  IMPORT_FROM              promote_types
               76  STORE_NAME               promote_types
               78  IMPORT_FROM              diagonal
               80  STORE_NAME               diagonal
               82  IMPORT_FROM              nonzero
               84  STORE_NAME               nonzero
               86  IMPORT_FROM              indices
               88  STORE_NAME               indices
               90  POP_TOP          

 L.  11        92  LOAD_CONST               0
               94  LOAD_CONST               ('set_array_function_like_doc', 'set_module')
               96  IMPORT_NAME_ATTR         numpy.core.overrides
               98  IMPORT_FROM              set_array_function_like_doc
              100  STORE_NAME               set_array_function_like_doc
              102  IMPORT_FROM              set_module
              104  STORE_NAME               set_module
              106  POP_TOP          

 L.  12       108  LOAD_CONST               0
              110  LOAD_CONST               ('overrides',)
              112  IMPORT_NAME_ATTR         numpy.core
              114  IMPORT_FROM              overrides
              116  STORE_NAME               overrides
              118  POP_TOP          

 L.  13       120  LOAD_CONST               0
              122  LOAD_CONST               ('iinfo',)
              124  IMPORT_NAME_ATTR         numpy.core
              126  IMPORT_FROM              iinfo
              128  STORE_NAME               iinfo
              130  POP_TOP          

 L.  14       132  LOAD_CONST               0
              134  LOAD_CONST               ('broadcast_to',)
              136  IMPORT_NAME_ATTR         numpy.lib.stride_tricks
              138  IMPORT_FROM              broadcast_to
              140  STORE_NAME               broadcast_to
              142  POP_TOP          

 L.  17       144  BUILD_LIST_0          0 
              146  LOAD_CONST               ('diag', 'diagflat', 'eye', 'fliplr', 'flipud', 'tri', 'triu', 'tril', 'vander', 'histogram2d', 'mask_indices', 'tril_indices', 'tril_indices_from', 'triu_indices', 'triu_indices_from')
              148  CALL_FINALLY        151  'to 151'
              150  STORE_NAME               __all__

 L.  23       152  LOAD_NAME                functools
              154  LOAD_ATTR                partial

 L.  24       156  LOAD_NAME                overrides
              158  LOAD_ATTR                array_function_dispatch
              160  LOAD_STR                 'numpy'

 L.  23       162  LOAD_CONST               ('module',)
              164  CALL_FUNCTION_KW_2     2  '2 total positional and keyword args'
              166  STORE_NAME               array_function_dispatch

 L.  27       168  LOAD_NAME                iinfo
              170  LOAD_NAME                int8
              172  CALL_FUNCTION_1       1  ''
              174  STORE_NAME               i1

 L.  28       176  LOAD_NAME                iinfo
              178  LOAD_NAME                int16
              180  CALL_FUNCTION_1       1  ''
              182  STORE_NAME               i2

 L.  29       184  LOAD_NAME                iinfo
              186  LOAD_NAME                int32
              188  CALL_FUNCTION_1       1  ''
              190  STORE_NAME               i4

 L.  32       192  LOAD_CODE                <code_object _min_int>
              194  LOAD_STR                 '_min_int'
              196  MAKE_FUNCTION_0          'Neither defaults, keyword-only args, annotations, nor closures'
              198  STORE_NAME               _min_int

 L.  43       200  LOAD_CODE                <code_object _flip_dispatcher>
              202  LOAD_STR                 '_flip_dispatcher'
              204  MAKE_FUNCTION_0          'Neither defaults, keyword-only args, annotations, nor closures'
              206  STORE_NAME               _flip_dispatcher

 L.  47       208  LOAD_NAME                array_function_dispatch
              210  LOAD_NAME                _flip_dispatcher
              212  CALL_FUNCTION_1       1  ''

 L.  48       214  LOAD_CODE                <code_object fliplr>
              216  LOAD_STR                 'fliplr'
              218  MAKE_FUNCTION_0          'Neither defaults, keyword-only args, annotations, nor closures'
              220  CALL_FUNCTION_1       1  ''
              222  STORE_NAME               fliplr

 L. 101       224  LOAD_NAME                array_function_dispatch
              226  LOAD_NAME                _flip_dispatcher
              228  CALL_FUNCTION_1       1  ''

 L. 102       230  LOAD_CODE                <code_object flipud>
              232  LOAD_STR                 'flipud'
              234  MAKE_FUNCTION_0          'Neither defaults, keyword-only args, annotations, nor closures'
              236  CALL_FUNCTION_1       1  ''
              238  STORE_NAME               flipud

 L. 157       240  LOAD_CONST               (None, None, None, None)
              242  LOAD_CONST               None
              244  LOAD_CONST               ('like',)
              246  BUILD_CONST_KEY_MAP_1     1 
              248  LOAD_CODE                <code_object _eye_dispatcher>
              250  LOAD_STR                 '_eye_dispatcher'
              252  MAKE_FUNCTION_3          'default, keyword-only'
              254  STORE_NAME               _eye_dispatcher

 L. 161       256  LOAD_NAME                set_array_function_like_doc

 L. 162       258  LOAD_NAME                set_module
              260  LOAD_STR                 'numpy'
              262  CALL_FUNCTION_1       1  ''

 L. 163       264  LOAD_CONST               None
              266  LOAD_CONST               0
              268  LOAD_NAME                float
              270  LOAD_STR                 'C'
              272  BUILD_TUPLE_4         4 
              274  LOAD_CONST               None
              276  LOAD_CONST               ('like',)
              278  BUILD_CONST_KEY_MAP_1     1 
              280  LOAD_CODE                <code_object eye>
              282  LOAD_STR                 'eye'
              284  MAKE_FUNCTION_3          'default, keyword-only'
              286  CALL_FUNCTION_1       1  ''
              288  CALL_FUNCTION_1       1  ''
              290  STORE_NAME               eye

 L. 225       292  LOAD_NAME                array_function_dispatch

 L. 226       294  LOAD_NAME                _eye_dispatcher

 L. 225       296  CALL_FUNCTION_1       1  ''

 L. 227       298  LOAD_NAME                eye

 L. 225       300  CALL_FUNCTION_1       1  ''
              302  STORE_NAME               _eye_with_like

 L. 230       304  LOAD_CONST               (None,)
              306  LOAD_CODE                <code_object _diag_dispatcher>
              308  LOAD_STR                 '_diag_dispatcher'
              310  MAKE_FUNCTION_1          'default'
              312  STORE_NAME               _diag_dispatcher

 L. 234       314  LOAD_NAME                array_function_dispatch
              316  LOAD_NAME                _diag_dispatcher
              318  CALL_FUNCTION_1       1  ''

 L. 235       320  LOAD_CONST               (0,)
              322  LOAD_CODE                <code_object diag>
              324  LOAD_STR                 'diag'
              326  MAKE_FUNCTION_1          'default'
              328  CALL_FUNCTION_1       1  ''
              330  STORE_NAME               diag

 L. 306       332  LOAD_NAME                array_function_dispatch
              334  LOAD_NAME                _diag_dispatcher
              336  CALL_FUNCTION_1       1  ''

 L. 307       338  LOAD_CONST               (0,)
              340  LOAD_CODE                <code_object diagflat>
              342  LOAD_STR                 'diagflat'
              344  MAKE_FUNCTION_1          'default'
              346  CALL_FUNCTION_1       1  ''
              348  STORE_NAME               diagflat

 L. 366       350  LOAD_CONST               (None, None, None)
              352  LOAD_CONST               None
              354  LOAD_CONST               ('like',)
              356  BUILD_CONST_KEY_MAP_1     1 
              358  LOAD_CODE                <code_object _tri_dispatcher>
              360  LOAD_STR                 '_tri_dispatcher'
              362  MAKE_FUNCTION_3          'default, keyword-only'
              364  STORE_NAME               _tri_dispatcher

 L. 370       366  LOAD_NAME                set_array_function_like_doc

 L. 371       368  LOAD_NAME                set_module
              370  LOAD_STR                 'numpy'
              372  CALL_FUNCTION_1       1  ''

 L. 372       374  LOAD_CONST               None
              376  LOAD_CONST               0
              378  LOAD_NAME                float
              380  BUILD_TUPLE_3         3 
              382  LOAD_CONST               None
              384  LOAD_CONST               ('like',)
              386  BUILD_CONST_KEY_MAP_1     1 
              388  LOAD_CODE                <code_object tri>
              390  LOAD_STR                 'tri'
              392  MAKE_FUNCTION_3          'default, keyword-only'
              394  CALL_FUNCTION_1       1  ''
              396  CALL_FUNCTION_1       1  ''
              398  STORE_NAME               tri

 L. 427       400  LOAD_NAME                array_function_dispatch

 L. 428       402  LOAD_NAME                _tri_dispatcher

 L. 427       404  CALL_FUNCTION_1       1  ''

 L. 429       406  LOAD_NAME                tri

 L. 427       408  CALL_FUNCTION_1       1  ''
              410  STORE_NAME               _tri_with_like

 L. 432       412  LOAD_CONST               (None,)
              414  LOAD_CODE                <code_object _trilu_dispatcher>
              416  LOAD_STR                 '_trilu_dispatcher'
              418  MAKE_FUNCTION_1          'default'
              420  STORE_NAME               _trilu_dispatcher

 L. 436       422  LOAD_NAME                array_function_dispatch
              424  LOAD_NAME                _trilu_dispatcher
              426  CALL_FUNCTION_1       1  ''

 L. 437       428  LOAD_CONST               (0,)
              430  LOAD_CODE                <code_object tril>
              432  LOAD_STR                 'tril'
              434  MAKE_FUNCTION_1          'default'
              436  CALL_FUNCTION_1       1  ''
              438  STORE_NAME               tril

 L. 475       440  LOAD_NAME                array_function_dispatch
              442  LOAD_NAME                _trilu_dispatcher
              444  CALL_FUNCTION_1       1  ''

 L. 476       446  LOAD_CONST               (0,)
              448  LOAD_CODE                <code_object triu>
              450  LOAD_STR                 'triu'
              452  MAKE_FUNCTION_1          'default'
              454  CALL_FUNCTION_1       1  ''
              456  STORE_NAME               triu

 L. 504       458  LOAD_CONST               (None, None)
              460  LOAD_CODE                <code_object _vander_dispatcher>
              462  LOAD_STR                 '_vander_dispatcher'
              464  MAKE_FUNCTION_1          'default'
              466  STORE_NAME               _vander_dispatcher

 L. 509       468  LOAD_NAME                array_function_dispatch
              470  LOAD_NAME                _vander_dispatcher
              472  CALL_FUNCTION_1       1  ''

 L. 510       474  LOAD_CONST               (None, False)
              476  LOAD_CODE                <code_object vander>
              478  LOAD_STR                 'vander'
              480  MAKE_FUNCTION_1          'default'
              482  CALL_FUNCTION_1       1  ''
              484  STORE_NAME               vander

 L. 600       486  LOAD_CONST               (None, None, None, None, None)
              488  LOAD_CODE                <code_object _histogram2d_dispatcher>
              490  LOAD_STR                 '_histogram2d_dispatcher'
              492  MAKE_FUNCTION_1          'default'
              494  STORE_NAME               _histogram2d_dispatcher

 L. 618       496  LOAD_NAME                array_function_dispatch
              498  LOAD_NAME                _histogram2d_dispatcher
              500  CALL_FUNCTION_1       1  ''

 L. 619       502  LOAD_CONST               (10, None, None, None, None)
              504  LOAD_CODE                <code_object histogram2d>
              506  LOAD_STR                 'histogram2d'
              508  MAKE_FUNCTION_1          'default'
              510  CALL_FUNCTION_1       1  ''
              512  STORE_NAME               histogram2d

 L. 755       514  LOAD_NAME                set_module
              516  LOAD_STR                 'numpy'
              518  CALL_FUNCTION_1       1  ''

 L. 756       520  LOAD_CONST               (0,)
              522  LOAD_CODE                <code_object mask_indices>
              524  LOAD_STR                 'mask_indices'
              526  MAKE_FUNCTION_1          'default'
              528  CALL_FUNCTION_1       1  ''
              530  STORE_NAME               mask_indices

 L. 826       532  LOAD_NAME                set_module
              534  LOAD_STR                 'numpy'
              536  CALL_FUNCTION_1       1  ''

 L. 827       538  LOAD_CONST               (0, None)
              540  LOAD_CODE                <code_object tril_indices>
              542  LOAD_STR                 'tril_indices'
              544  MAKE_FUNCTION_1          'default'
              546  CALL_FUNCTION_1       1  ''
              548  STORE_NAME               tril_indices

 L. 910       550  LOAD_CONST               (None,)
              552  LOAD_CODE                <code_object _trilu_indices_form_dispatcher>
              554  LOAD_STR                 '_trilu_indices_form_dispatcher'
              556  MAKE_FUNCTION_1          'default'
              558  STORE_NAME               _trilu_indices_form_dispatcher

 L. 914       560  LOAD_NAME                array_function_dispatch
              562  LOAD_NAME                _trilu_indices_form_dispatcher
              564  CALL_FUNCTION_1       1  ''

 L. 915       566  LOAD_CONST               (0,)
              568  LOAD_CODE                <code_object tril_indices_from>
              570  LOAD_STR                 'tril_indices_from'
              572  MAKE_FUNCTION_1          'default'
              574  CALL_FUNCTION_1       1  ''
              576  STORE_NAME               tril_indices_from

 L. 943       578  LOAD_NAME                set_module
              580  LOAD_STR                 'numpy'
              582  CALL_FUNCTION_1       1  ''

 L. 944       584  LOAD_CONST               (0, None)
              586  LOAD_CODE                <code_object triu_indices>
              588  LOAD_STR                 'triu_indices'
              590  MAKE_FUNCTION_1          'default'
              592  CALL_FUNCTION_1       1  ''
              594  STORE_NAME               triu_indices

 L.1029       596  LOAD_NAME                array_function_dispatch
              598  LOAD_NAME                _trilu_indices_form_dispatcher
              600  CALL_FUNCTION_1       1  ''

 L.1030       602  LOAD_CONST               (0,)
              604  LOAD_CODE                <code_object triu_indices_from>
              606  LOAD_STR                 'triu_indices_from'
              608  MAKE_FUNCTION_1          'default'
              610  CALL_FUNCTION_1       1  ''
              612  STORE_NAME               triu_indices_from

Parse error at or near `CALL_FINALLY' instruction at offset 148

Instruction context:
   
 L.  17       144  BUILD_LIST_0          0 
                 146  LOAD_CONST               ('diag', 'diagflat', 'eye', 'fliplr', 'flipud', 'tri', 'triu', 'tril', 'vander', 'histogram2d', 'mask_indices', 'tril_indices', 'tril_indices_from', 'triu_indices', 'triu_indices_from')
->               148  CALL_FINALLY        151  'to 151'
                 150  STORE_NAME               __all__

test/162649.pyc -- 
# decompile failed
