
# file test/162830.pyc
# --- This code section failed: ---

 L.  21         0  LOAD_STR                 'Utilities for writing code that runs on Python 2 and 3'
                2  STORE_NAME               __doc__

 L.  23         4  LOAD_CONST               0
                6  LOAD_CONST               ('absolute_import',)
                8  IMPORT_NAME              __future__
               10  IMPORT_FROM              absolute_import
               12  STORE_NAME               absolute_import
               14  POP_TOP          

 L.  25        16  LOAD_CONST               0
               18  LOAD_CONST               None
               20  IMPORT_NAME              functools
               22  STORE_NAME               functools

 L.  26        24  LOAD_CONST               0
               26  LOAD_CONST               None
               28  IMPORT_NAME              itertools
               30  STORE_NAME               itertools

 L.  27        32  LOAD_CONST               0
               34  LOAD_CONST               None
               36  IMPORT_NAME              operator
               38  STORE_NAME               operator

 L.  28        40  LOAD_CONST               0
               42  LOAD_CONST               None
               44  IMPORT_NAME              sys
               46  STORE_NAME               sys

 L.  29        48  LOAD_CONST               0
               50  LOAD_CONST               None
               52  IMPORT_NAME              types
               54  STORE_NAME               types

 L.  31        56  LOAD_STR                 'Benjamin Peterson <benjamin@python.org>'
               58  STORE_NAME               __author__

 L.  32        60  LOAD_STR                 '1.16.0'
               62  STORE_NAME               __version__

 L.  36        64  LOAD_NAME                sys
               66  LOAD_ATTR                version_info
               68  LOAD_CONST               0
               70  BINARY_SUBSCR    
               72  LOAD_CONST               2
               74  COMPARE_OP               ==
               76  STORE_NAME               PY2

 L.  37        78  LOAD_NAME                sys
               80  LOAD_ATTR                version_info
               82  LOAD_CONST               0
               84  BINARY_SUBSCR    
               86  LOAD_CONST               3
               88  COMPARE_OP               ==
               90  STORE_NAME               PY3

 L.  38        92  LOAD_NAME                sys
               94  LOAD_ATTR                version_info
               96  LOAD_CONST               0
               98  LOAD_CONST               2
              100  BUILD_SLICE_2         2 
              102  BINARY_SUBSCR    
              104  LOAD_CONST               (3, 4)
              106  COMPARE_OP               >=
              108  STORE_NAME               PY34

 L.  40       110  LOAD_NAME                PY3
              112  POP_JUMP_IF_FALSE   148  'to 148'

 L.  41       114  LOAD_NAME                str
              116  BUILD_TUPLE_1         1 
              118  STORE_NAME               string_types

 L.  42       120  LOAD_NAME                int
              122  BUILD_TUPLE_1         1 
              124  STORE_NAME               integer_types

 L.  43       126  LOAD_NAME                type
              128  BUILD_TUPLE_1         1 
              130  STORE_NAME               class_types

 L.  44       132  LOAD_NAME                str
              134  STORE_NAME               text_type

 L.  45       136  LOAD_NAME                bytes
              138  STORE_NAME               binary_type

 L.  47       140  LOAD_NAME                sys
              142  LOAD_ATTR                maxsize
              144  STORE_NAME               MAXSIZE
              146  JUMP_FORWARD        272  'to 272'
            148_0  COME_FROM           112  '112'

 L.  49       148  LOAD_NAME                basestring
              150  BUILD_TUPLE_1         1 
              152  STORE_NAME               string_types

 L.  50       154  LOAD_NAME                int
              156  LOAD_NAME                long
              158  BUILD_TUPLE_2         2 
              160  STORE_NAME               integer_types

 L.  51       162  LOAD_NAME                type
              164  LOAD_NAME                types
              166  LOAD_ATTR                ClassType
              168  BUILD_TUPLE_2         2 
              170  STORE_NAME               class_types

 L.  52       172  LOAD_NAME                unicode
              174  STORE_NAME               text_type

 L.  53       176  LOAD_NAME                str
              178  STORE_NAME               binary_type

 L.  55       180  LOAD_NAME                sys
              182  LOAD_ATTR                platform
              184  LOAD_METHOD              startswith
              186  LOAD_STR                 'java'
              188  CALL_METHOD_1         1  ''
              190  POP_JUMP_IF_FALSE   202  'to 202'

 L.  57       192  LOAD_NAME                int
              194  LOAD_CONST               2147483647
              196  CALL_FUNCTION_1       1  ''
              198  STORE_NAME               MAXSIZE
              200  JUMP_FORWARD        272  'to 272'
            202_0  COME_FROM           190  '190'

 L.  60       202  LOAD_BUILD_CLASS 
              204  LOAD_CODE                <code_object X>
              206  LOAD_STR                 'X'
              208  MAKE_FUNCTION_0          'Neither defaults, keyword-only args, annotations, nor closures'
              210  LOAD_STR                 'X'
              212  LOAD_NAME                object
              214  CALL_FUNCTION_3       3  ''
              216  STORE_NAME               X

 L.  64       218  SETUP_FINALLY       234  'to 234'

 L.  65       220  LOAD_NAME                len
              222  LOAD_NAME                X
              224  CALL_FUNCTION_0       0  ''
              226  CALL_FUNCTION_1       1  ''
              228  POP_TOP          
              230  POP_BLOCK        
              232  JUMP_FORWARD        262  'to 262'
            234_0  COME_FROM_FINALLY   218  '218'

 L.  66       234  DUP_TOP          
              236  LOAD_NAME                OverflowError
          238_240  <121>               260  ''
              242  POP_TOP          
              244  POP_TOP          
              246  POP_TOP          

 L.  68       248  LOAD_NAME                int
              250  LOAD_CONST               2147483647
              252  CALL_FUNCTION_1       1  ''
              254  STORE_NAME               MAXSIZE
              256  POP_EXCEPT       
              258  JUMP_FORWARD        270  'to 270'
              260  <48>             
            262_0  COME_FROM           232  '232'

 L.  71       262  LOAD_NAME                int
              264  LOAD_CONST               9223372036854775807
              266  CALL_FUNCTION_1       1  ''
              268  STORE_NAME               MAXSIZE
            270_0  COME_FROM           258  '258'

 L.  72       270  DELETE_NAME              X
            272_0  COME_FROM           200  '200'
            272_1  COME_FROM           146  '146'

 L.  74       272  LOAD_NAME                PY34
          274_276  POP_JUMP_IF_FALSE   292  'to 292'

 L.  75       278  LOAD_CONST               0
              280  LOAD_CONST               ('spec_from_loader',)
              282  IMPORT_NAME_ATTR         importlib.util
              284  IMPORT_FROM              spec_from_loader
              286  STORE_NAME               spec_from_loader
              288  POP_TOP          
              290  JUMP_FORWARD        296  'to 296'
            292_0  COME_FROM           274  '274'

 L.  77       292  LOAD_CONST               None
              294  STORE_NAME               spec_from_loader
            296_0  COME_FROM           290  '290'

 L.  80       296  LOAD_CODE                <code_object _add_doc>
              298  LOAD_STR                 '_add_doc'
              300  MAKE_FUNCTION_0          'Neither defaults, keyword-only args, annotations, nor closures'
              302  STORE_NAME               _add_doc

 L.  85       304  LOAD_CODE                <code_object _import_module>
              306  LOAD_STR                 '_import_module'
              308  MAKE_FUNCTION_0          'Neither defaults, keyword-only args, annotations, nor closures'
              310  STORE_NAME               _import_module

 L.  91       312  LOAD_BUILD_CLASS 
              314  LOAD_CODE                <code_object _LazyDescr>
              316  LOAD_STR                 '_LazyDescr'
              318  MAKE_FUNCTION_0          'Neither defaults, keyword-only args, annotations, nor closures'
              320  LOAD_STR                 '_LazyDescr'
              322  LOAD_NAME                object
              324  CALL_FUNCTION_3       3  ''
              326  STORE_NAME               _LazyDescr

 L. 107       328  LOAD_BUILD_CLASS 
              330  LOAD_CODE                <code_object MovedModule>
              332  LOAD_STR                 'MovedModule'
              334  MAKE_FUNCTION_0          'Neither defaults, keyword-only args, annotations, nor closures'
              336  LOAD_STR                 'MovedModule'
              338  LOAD_NAME                _LazyDescr
              340  CALL_FUNCTION_3       3  ''
              342  STORE_NAME               MovedModule

 L. 127       344  LOAD_BUILD_CLASS 
              346  LOAD_CODE                <code_object _LazyModule>
              348  LOAD_STR                 '_LazyModule'
              350  MAKE_FUNCTION_0          'Neither defaults, keyword-only args, annotations, nor closures'
              352  LOAD_STR                 '_LazyModule'
              354  LOAD_NAME                types
              356  LOAD_ATTR                ModuleType
              358  CALL_FUNCTION_3       3  ''
              360  STORE_NAME               _LazyModule

 L. 141       362  LOAD_BUILD_CLASS 
              364  LOAD_CODE                <code_object MovedAttribute>
              366  LOAD_STR                 'MovedAttribute'
              368  MAKE_FUNCTION_0          'Neither defaults, keyword-only args, annotations, nor closures'
              370  LOAD_STR                 'MovedAttribute'
              372  LOAD_NAME                _LazyDescr
              374  CALL_FUNCTION_3       3  ''
              376  STORE_NAME               MovedAttribute

 L. 165       378  LOAD_BUILD_CLASS 
              380  LOAD_CODE                <code_object _SixMetaPathImporter>
              382  LOAD_STR                 '_SixMetaPathImporter'
              384  MAKE_FUNCTION_0          'Neither defaults, keyword-only args, annotations, nor closures'
              386  LOAD_STR                 '_SixMetaPathImporter'
              388  LOAD_NAME                object
              390  CALL_FUNCTION_3       3  ''
              392  STORE_NAME               _SixMetaPathImporter

 L. 240       394  LOAD_NAME                _SixMetaPathImporter
              396  LOAD_NAME                __name__
              398  CALL_FUNCTION_1       1  ''
              400  STORE_NAME               _importer

 L. 243       402  LOAD_BUILD_CLASS 
              404  LOAD_CODE                <code_object _MovedItems>
              406  LOAD_STR                 '_MovedItems'
              408  MAKE_FUNCTION_0          'Neither defaults, keyword-only args, annotations, nor closures'
              410  LOAD_STR                 '_MovedItems'
              412  LOAD_NAME                _LazyModule
              414  CALL_FUNCTION_3       3  ''
              416  STORE_NAME               _MovedItems

 L. 251       418  LOAD_NAME                MovedAttribute
              420  LOAD_STR                 'cStringIO'
              422  LOAD_STR                 'cStringIO'
              424  LOAD_STR                 'io'
              426  LOAD_STR                 'StringIO'
              428  CALL_FUNCTION_4       4  ''

 L. 252       430  LOAD_NAME                MovedAttribute
              432  LOAD_STR                 'filter'
              434  LOAD_STR                 'itertools'
              436  LOAD_STR                 'builtins'
              438  LOAD_STR                 'ifilter'
              440  LOAD_STR                 'filter'
              442  CALL_FUNCTION_5       5  ''

 L. 253       444  LOAD_NAME                MovedAttribute

 L. 254       446  LOAD_STR                 'filterfalse'
              448  LOAD_STR                 'itertools'
              450  LOAD_STR                 'itertools'
              452  LOAD_STR                 'ifilterfalse'
              454  LOAD_STR                 'filterfalse'

 L. 253       456  CALL_FUNCTION_5       5  ''

 L. 256       458  LOAD_NAME                MovedAttribute
              460  LOAD_STR                 'input'
              462  LOAD_STR                 '__builtin__'
              464  LOAD_STR                 'builtins'
              466  LOAD_STR                 'raw_input'
              468  LOAD_STR                 'input'
              470  CALL_FUNCTION_5       5  ''

 L. 257       472  LOAD_NAME                MovedAttribute
              474  LOAD_STR                 'intern'
              476  LOAD_STR                 '__builtin__'
              478  LOAD_STR                 'sys'
              480  CALL_FUNCTION_3       3  ''

 L. 258       482  LOAD_NAME                MovedAttribute
              484  LOAD_STR                 'map'
              486  LOAD_STR                 'itertools'
              488  LOAD_STR                 'builtins'
              490  LOAD_STR                 'imap'
              492  LOAD_STR                 'map'
              494  CALL_FUNCTION_5       5  ''

 L. 259       496  LOAD_NAME                MovedAttribute
              498  LOAD_STR                 'getcwd'
              500  LOAD_STR                 'os'
              502  LOAD_STR                 'os'
              504  LOAD_STR                 'getcwdu'
              506  LOAD_STR                 'getcwd'
              508  CALL_FUNCTION_5       5  ''

 L. 260       510  LOAD_NAME                MovedAttribute
              512  LOAD_STR                 'getcwdb'
              514  LOAD_STR                 'os'
              516  LOAD_STR                 'os'
              518  LOAD_STR                 'getcwd'
              520  LOAD_STR                 'getcwdb'
              522  CALL_FUNCTION_5       5  ''

 L. 261       524  LOAD_NAME                MovedAttribute
              526  LOAD_STR                 'getoutput'
              528  LOAD_STR                 'commands'
              530  LOAD_STR                 'subprocess'
              532  CALL_FUNCTION_3       3  ''

 L. 262       534  LOAD_NAME                MovedAttribute
              536  LOAD_STR                 'range'
              538  LOAD_STR                 '__builtin__'
              540  LOAD_STR                 'builtins'
              542  LOAD_STR                 'xrange'
              544  LOAD_STR                 'range'
              546  CALL_FUNCTION_5       5  ''

 L. 263       548  LOAD_NAME                MovedAttribute

 L. 264       550  LOAD_STR                 'reload_module'
              552  LOAD_STR                 '__builtin__'
              554  LOAD_NAME                PY34
          556_558  POP_JUMP_IF_FALSE   564  'to 564'
              560  LOAD_STR                 'importlib'
              562  JUMP_FORWARD        566  'to 566'
            564_0  COME_FROM           556  '556'
              564  LOAD_STR                 'imp'
            566_0  COME_FROM           562  '562'
              566  LOAD_STR                 'reload'

 L. 263       568  CALL_FUNCTION_4       4  ''

 L. 266       570  LOAD_NAME                MovedAttribute
              572  LOAD_STR                 'reduce'
              574  LOAD_STR                 '__builtin__'
              576  LOAD_STR                 'functools'
              578  CALL_FUNCTION_3       3  ''

 L. 267       580  LOAD_NAME                MovedAttribute
              582  LOAD_STR                 'shlex_quote'
              584  LOAD_STR                 'pipes'
              586  LOAD_STR                 'shlex'
              588  LOAD_STR                 'quote'
              590  CALL_FUNCTION_4       4  ''

 L. 268       592  LOAD_NAME                MovedAttribute
              594  LOAD_STR                 'StringIO'
              596  LOAD_STR                 'StringIO'
              598  LOAD_STR                 'io'
              600  CALL_FUNCTION_3       3  ''

 L. 269       602  LOAD_NAME                MovedAttribute
              604  LOAD_STR                 'UserDict'
              606  LOAD_STR                 'UserDict'
              608  LOAD_STR                 'collections'
              610  CALL_FUNCTION_3       3  ''

 L. 270       612  LOAD_NAME                MovedAttribute
              614  LOAD_STR                 'UserList'
              616  LOAD_STR                 'UserList'
              618  LOAD_STR                 'collections'
              620  CALL_FUNCTION_3       3  ''

 L. 271       622  LOAD_NAME                MovedAttribute
              624  LOAD_STR                 'UserString'
              626  LOAD_STR                 'UserString'
              628  LOAD_STR                 'collections'
              630  CALL_FUNCTION_3       3  ''

 L. 272       632  LOAD_NAME                MovedAttribute
              634  LOAD_STR                 'xrange'
              636  LOAD_STR                 '__builtin__'
              638  LOAD_STR                 'builtins'
              640  LOAD_STR                 'xrange'
              642  LOAD_STR                 'range'
              644  CALL_FUNCTION_5       5  ''

 L. 273       646  LOAD_NAME                MovedAttribute
              648  LOAD_STR                 'zip'
              650  LOAD_STR                 'itertools'
              652  LOAD_STR                 'builtins'
              654  LOAD_STR                 'izip'
              656  LOAD_STR                 'zip'
              658  CALL_FUNCTION_5       5  ''

 L. 274       660  LOAD_NAME                MovedAttribute

 L. 275       662  LOAD_STR                 'zip_longest'
              664  LOAD_STR                 'itertools'
              666  LOAD_STR                 'itertools'
              668  LOAD_STR                 'izip_longest'
              670  LOAD_STR                 'zip_longest'

 L. 274       672  CALL_FUNCTION_5       5  ''

 L. 277       674  LOAD_NAME                MovedModule
              676  LOAD_STR                 'builtins'
              678  LOAD_STR                 '__builtin__'
              680  CALL_FUNCTION_2       2  ''

 L. 278       682  LOAD_NAME                MovedModule
              684  LOAD_STR                 'configparser'
              686  LOAD_STR                 'ConfigParser'
              688  CALL_FUNCTION_2       2  ''

 L. 279       690  LOAD_NAME                MovedModule

 L. 280       692  LOAD_STR                 'collections_abc'

 L. 281       694  LOAD_STR                 'collections'

 L. 282       696  LOAD_NAME                sys
              698  LOAD_ATTR                version_info
              700  LOAD_CONST               (3, 3)
              702  COMPARE_OP               >=
          704_706  POP_JUMP_IF_FALSE   712  'to 712'
              708  LOAD_STR                 'collections.abc'
              710  JUMP_FORWARD        714  'to 714'
            712_0  COME_FROM           704  '704'
              712  LOAD_STR                 'collections'
            714_0  COME_FROM           710  '710'

 L. 279       714  CALL_FUNCTION_3       3  ''

 L. 284       716  LOAD_NAME                MovedModule
              718  LOAD_STR                 'copyreg'
              720  LOAD_STR                 'copy_reg'
              722  CALL_FUNCTION_2       2  ''

 L. 285       724  LOAD_NAME                MovedModule
              726  LOAD_STR                 'dbm_gnu'
              728  LOAD_STR                 'gdbm'
              730  LOAD_STR                 'dbm.gnu'
              732  CALL_FUNCTION_3       3  ''

 L. 286       734  LOAD_NAME                MovedModule
              736  LOAD_STR                 'dbm_ndbm'
              738  LOAD_STR                 'dbm'
              740  LOAD_STR                 'dbm.ndbm'
              742  CALL_FUNCTION_3       3  ''

 L. 287       744  LOAD_NAME                MovedModule

 L. 288       746  LOAD_STR                 '_dummy_thread'

 L. 289       748  LOAD_STR                 'dummy_thread'

 L. 290       750  LOAD_NAME                sys
              752  LOAD_ATTR                version_info
              754  LOAD_CONST               (3, 9)
              756  COMPARE_OP               <
          758_760  POP_JUMP_IF_FALSE   766  'to 766'
              762  LOAD_STR                 '_dummy_thread'
              764  JUMP_FORWARD        768  'to 768'
            766_0  COME_FROM           758  '758'
              766  LOAD_STR                 '_thread'
            768_0  COME_FROM           764  '764'

 L. 287       768  CALL_FUNCTION_3       3  ''

 L. 292       770  LOAD_NAME                MovedModule
              772  LOAD_STR                 'http_cookiejar'
              774  LOAD_STR                 'cookielib'
              776  LOAD_STR                 'http.cookiejar'
              778  CALL_FUNCTION_3       3  ''

 L. 293       780  LOAD_NAME                MovedModule
              782  LOAD_STR                 'http_cookies'
              784  LOAD_STR                 'Cookie'
              786  LOAD_STR                 'http.cookies'
              788  CALL_FUNCTION_3       3  ''

 L. 294       790  LOAD_NAME                MovedModule
              792  LOAD_STR                 'html_entities'
              794  LOAD_STR                 'htmlentitydefs'
              796  LOAD_STR                 'html.entities'
              798  CALL_FUNCTION_3       3  ''

 L. 295       800  LOAD_NAME                MovedModule
              802  LOAD_STR                 'html_parser'
              804  LOAD_STR                 'HTMLParser'
              806  LOAD_STR                 'html.parser'
              808  CALL_FUNCTION_3       3  ''

 L. 296       810  LOAD_NAME                MovedModule
              812  LOAD_STR                 'http_client'
              814  LOAD_STR                 'httplib'
              816  LOAD_STR                 'http.client'
              818  CALL_FUNCTION_3       3  ''

 L. 297       820  LOAD_NAME                MovedModule
              822  LOAD_STR                 'email_mime_base'
              824  LOAD_STR                 'email.MIMEBase'
              826  LOAD_STR                 'email.mime.base'
              828  CALL_FUNCTION_3       3  ''

 L. 298       830  LOAD_NAME                MovedModule
              832  LOAD_STR                 'email_mime_image'
              834  LOAD_STR                 'email.MIMEImage'
              836  LOAD_STR                 'email.mime.image'
              838  CALL_FUNCTION_3       3  ''

 L. 299       840  LOAD_NAME                MovedModule
              842  LOAD_STR                 'email_mime_multipart'
              844  LOAD_STR                 'email.MIMEMultipart'
              846  LOAD_STR                 'email.mime.multipart'
              848  CALL_FUNCTION_3       3  ''

 L. 300       850  LOAD_NAME                MovedModule

 L. 301       852  LOAD_STR                 'email_mime_nonmultipart'
              854  LOAD_STR                 'email.MIMENonMultipart'
              856  LOAD_STR                 'email.mime.nonmultipart'

 L. 300       858  CALL_FUNCTION_3       3  ''

 L. 303       860  LOAD_NAME                MovedModule
              862  LOAD_STR                 'email_mime_text'
              864  LOAD_STR                 'email.MIMEText'
              866  LOAD_STR                 'email.mime.text'
              868  CALL_FUNCTION_3       3  ''

 L. 304       870  LOAD_NAME                MovedModule
              872  LOAD_STR                 'BaseHTTPServer'
              874  LOAD_STR                 'BaseHTTPServer'
              876  LOAD_STR                 'http.server'
              878  CALL_FUNCTION_3       3  ''

 L. 305       880  LOAD_NAME                MovedModule
              882  LOAD_STR                 'CGIHTTPServer'
              884  LOAD_STR                 'CGIHTTPServer'
              886  LOAD_STR                 'http.server'
              888  CALL_FUNCTION_3       3  ''

 L. 306       890  LOAD_NAME                MovedModule
              892  LOAD_STR                 'SimpleHTTPServer'
              894  LOAD_STR                 'SimpleHTTPServer'
              896  LOAD_STR                 'http.server'
              898  CALL_FUNCTION_3       3  ''

 L. 307       900  LOAD_NAME                MovedModule
              902  LOAD_STR                 'cPickle'
              904  LOAD_STR                 'cPickle'
              906  LOAD_STR                 'pickle'
              908  CALL_FUNCTION_3       3  ''

 L. 308       910  LOAD_NAME                MovedModule
              912  LOAD_STR                 'queue'
              914  LOAD_STR                 'Queue'
              916  CALL_FUNCTION_2       2  ''

 L. 309       918  LOAD_NAME                MovedModule
              920  LOAD_STR                 'reprlib'
              922  LOAD_STR                 'repr'
              924  CALL_FUNCTION_2       2  ''

 L. 310       926  LOAD_NAME                MovedModule
              928  LOAD_STR                 'socketserver'
              930  LOAD_STR                 'SocketServer'
              932  CALL_FUNCTION_2       2  ''

 L. 311       934  LOAD_NAME                MovedModule
              936  LOAD_STR                 '_thread'
              938  LOAD_STR                 'thread'
              940  LOAD_STR                 '_thread'
              942  CALL_FUNCTION_3       3  ''

 L. 312       944  LOAD_NAME                MovedModule
              946  LOAD_STR                 'tkinter'
              948  LOAD_STR                 'Tkinter'
              950  CALL_FUNCTION_2       2  ''

 L. 313       952  LOAD_NAME                MovedModule
              954  LOAD_STR                 'tkinter_dialog'
              956  LOAD_STR                 'Dialog'
              958  LOAD_STR                 'tkinter.dialog'
              960  CALL_FUNCTION_3       3  ''

 L. 314       962  LOAD_NAME                MovedModule
              964  LOAD_STR                 'tkinter_filedialog'
              966  LOAD_STR                 'FileDialog'
              968  LOAD_STR                 'tkinter.filedialog'
              970  CALL_FUNCTION_3       3  ''

 L. 315       972  LOAD_NAME                MovedModule
              974  LOAD_STR                 'tkinter_scrolledtext'
              976  LOAD_STR                 'ScrolledText'
              978  LOAD_STR                 'tkinter.scrolledtext'
              980  CALL_FUNCTION_3       3  ''

 L. 316       982  LOAD_NAME                MovedModule
              984  LOAD_STR                 'tkinter_simpledialog'
              986  LOAD_STR                 'SimpleDialog'
              988  LOAD_STR                 'tkinter.simpledialog'
              990  CALL_FUNCTION_3       3  ''

 L. 317       992  LOAD_NAME                MovedModule
              994  LOAD_STR                 'tkinter_tix'
              996  LOAD_STR                 'Tix'
              998  LOAD_STR                 'tkinter.tix'
             1000  CALL_FUNCTION_3       3  ''

 L. 318      1002  LOAD_NAME                MovedModule
             1004  LOAD_STR                 'tkinter_ttk'
             1006  LOAD_STR                 'ttk'
             1008  LOAD_STR                 'tkinter.ttk'
             1010  CALL_FUNCTION_3       3  ''

 L. 319      1012  LOAD_NAME                MovedModule
             1014  LOAD_STR                 'tkinter_constants'
             1016  LOAD_STR                 'Tkconstants'
             1018  LOAD_STR                 'tkinter.constants'
             1020  CALL_FUNCTION_3       3  ''

 L. 320      1022  LOAD_NAME                MovedModule
             1024  LOAD_STR                 'tkinter_dnd'
             1026  LOAD_STR                 'Tkdnd'
             1028  LOAD_STR                 'tkinter.dnd'
             1030  CALL_FUNCTION_3       3  ''

 L. 321      1032  LOAD_NAME                MovedModule
             1034  LOAD_STR                 'tkinter_colorchooser'
             1036  LOAD_STR                 'tkColorChooser'
             1038  LOAD_STR                 'tkinter.colorchooser'
             1040  CALL_FUNCTION_3       3  ''

 L. 322      1042  LOAD_NAME                MovedModule
             1044  LOAD_STR                 'tkinter_commondialog'
             1046  LOAD_STR                 'tkCommonDialog'
             1048  LOAD_STR                 'tkinter.commondialog'
             1050  CALL_FUNCTION_3       3  ''

 L. 323      1052  LOAD_NAME                MovedModule
             1054  LOAD_STR                 'tkinter_tkfiledialog'
             1056  LOAD_STR                 'tkFileDialog'
             1058  LOAD_STR                 'tkinter.filedialog'
             1060  CALL_FUNCTION_3       3  ''

 L. 324      1062  LOAD_NAME                MovedModule
             1064  LOAD_STR                 'tkinter_font'
             1066  LOAD_STR                 'tkFont'
             1068  LOAD_STR                 'tkinter.font'
             1070  CALL_FUNCTION_3       3  ''

 L. 325      1072  LOAD_NAME                MovedModule
             1074  LOAD_STR                 'tkinter_messagebox'
             1076  LOAD_STR                 'tkMessageBox'
             1078  LOAD_STR                 'tkinter.messagebox'
             1080  CALL_FUNCTION_3       3  ''

 L. 326      1082  LOAD_NAME                MovedModule
             1084  LOAD_STR                 'tkinter_tksimpledialog'
             1086  LOAD_STR                 'tkSimpleDialog'
             1088  LOAD_STR                 'tkinter.simpledialog'
             1090  CALL_FUNCTION_3       3  ''

 L. 327      1092  LOAD_NAME                MovedModule
             1094  LOAD_STR                 'urllib_parse'
             1096  LOAD_NAME                __name__
             1098  LOAD_STR                 '.moves.urllib_parse'
             1100  BINARY_ADD       
             1102  LOAD_STR                 'urllib.parse'
             1104  CALL_FUNCTION_3       3  ''

 L. 328      1106  LOAD_NAME                MovedModule
             1108  LOAD_STR                 'urllib_error'
             1110  LOAD_NAME                __name__
             1112  LOAD_STR                 '.moves.urllib_error'
             1114  BINARY_ADD       
             1116  LOAD_STR                 'urllib.error'
             1118  CALL_FUNCTION_3       3  ''

 L. 329      1120  LOAD_NAME                MovedModule
             1122  LOAD_STR                 'urllib'
             1124  LOAD_NAME                __name__
             1126  LOAD_STR                 '.moves.urllib'
             1128  BINARY_ADD       
             1130  LOAD_NAME                __name__
             1132  LOAD_STR                 '.moves.urllib'
             1134  BINARY_ADD       
             1136  CALL_FUNCTION_3       3  ''

 L. 330      1138  LOAD_NAME                MovedModule
             1140  LOAD_STR                 'urllib_robotparser'
             1142  LOAD_STR                 'robotparser'
             1144  LOAD_STR                 'urllib.robotparser'
             1146  CALL_FUNCTION_3       3  ''

 L. 331      1148  LOAD_NAME                MovedModule
             1150  LOAD_STR                 'xmlrpc_client'
             1152  LOAD_STR                 'xmlrpclib'
             1154  LOAD_STR                 'xmlrpc.client'
             1156  CALL_FUNCTION_3       3  ''

 L. 332      1158  LOAD_NAME                MovedModule
             1160  LOAD_STR                 'xmlrpc_server'
             1162  LOAD_STR                 'SimpleXMLRPCServer'
             1164  LOAD_STR                 'xmlrpc.server'
             1166  CALL_FUNCTION_3       3  ''

 L. 250      1168  BUILD_LIST_66        66 
             1170  STORE_NAME               _moved_attributes

 L. 335      1172  LOAD_NAME                sys
             1174  LOAD_ATTR                platform
             1176  LOAD_STR                 'win32'
             1178  COMPARE_OP               ==
         1180_1182  POP_JUMP_IF_FALSE  1200  'to 1200'

 L. 336      1184  LOAD_NAME                _moved_attributes

 L. 337      1186  LOAD_NAME                MovedModule
             1188  LOAD_STR                 'winreg'
             1190  LOAD_STR                 '_winreg'
             1192  CALL_FUNCTION_2       2  ''

 L. 336      1194  BUILD_LIST_1          1 
             1196  INPLACE_ADD      
             1198  STORE_NAME               _moved_attributes
           1200_0  COME_FROM          1180  '1180'

 L. 340      1200  LOAD_NAME                _moved_attributes
             1202  GET_ITER         
           1204_0  COME_FROM          1252  '1252'
           1204_1  COME_FROM          1230  '1230'
             1204  FOR_ITER           1256  'to 1256'
             1206  STORE_NAME               attr

 L. 341      1208  LOAD_NAME                setattr
             1210  LOAD_NAME                _MovedItems
             1212  LOAD_NAME                attr
             1214  LOAD_ATTR                name
             1216  LOAD_NAME                attr
             1218  CALL_FUNCTION_3       3  ''
             1220  POP_TOP          

 L. 342      1222  LOAD_NAME                isinstance
             1224  LOAD_NAME                attr
             1226  LOAD_NAME                MovedModule
             1228  CALL_FUNCTION_2       2  ''
         1230_1232  POP_JUMP_IF_FALSE_BACK  1204  'to 1204'

 L. 343      1234  LOAD_NAME                _importer
             1236  LOAD_METHOD              _add_module
             1238  LOAD_NAME                attr
             1240  LOAD_STR                 'moves.'
             1242  LOAD_NAME                attr
             1244  LOAD_ATTR                name
             1246  BINARY_ADD       
             1248  CALL_METHOD_2         2  ''
             1250  POP_TOP          
         1252_1254  JUMP_BACK          1204  'to 1204'
           1256_0  COME_FROM          1204  '1204'

 L. 344      1256  DELETE_NAME              attr

 L. 346      1258  LOAD_NAME                _moved_attributes
             1260  LOAD_NAME                _MovedItems
             1262  STORE_ATTR               _moved_attributes

 L. 348      1264  LOAD_NAME                _MovedItems
             1266  LOAD_NAME                __name__
             1268  LOAD_STR                 '.moves'
             1270  BINARY_ADD       
             1272  CALL_FUNCTION_1       1  ''
             1274  STORE_NAME               moves

 L. 349      1276  LOAD_NAME                _importer
             1278  LOAD_METHOD              _add_module
             1280  LOAD_NAME                moves
             1282  LOAD_STR                 'moves'
             1284  CALL_METHOD_2         2  ''
             1286  POP_TOP          

 L. 352      1288  LOAD_BUILD_CLASS 
             1290  LOAD_CODE                <code_object Module_six_moves_urllib_parse>
             1292  LOAD_STR                 'Module_six_moves_urllib_parse'
             1294  MAKE_FUNCTION_0          'Neither defaults, keyword-only args, annotations, nor closures'
             1296  LOAD_STR                 'Module_six_moves_urllib_parse'
             1298  LOAD_NAME                _LazyModule
             1300  CALL_FUNCTION_3       3  ''
             1302  STORE_NAME               Module_six_moves_urllib_parse

 L. 358      1304  LOAD_NAME                MovedAttribute
             1306  LOAD_STR                 'ParseResult'
             1308  LOAD_STR                 'urlparse'
             1310  LOAD_STR                 'urllib.parse'
             1312  CALL_FUNCTION_3       3  ''

 L. 359      1314  LOAD_NAME                MovedAttribute
             1316  LOAD_STR                 'SplitResult'
             1318  LOAD_STR                 'urlparse'
             1320  LOAD_STR                 'urllib.parse'
             1322  CALL_FUNCTION_3       3  ''

 L. 360      1324  LOAD_NAME                MovedAttribute
             1326  LOAD_STR                 'parse_qs'
             1328  LOAD_STR                 'urlparse'
             1330  LOAD_STR                 'urllib.parse'
             1332  CALL_FUNCTION_3       3  ''

 L. 361      1334  LOAD_NAME                MovedAttribute
             1336  LOAD_STR                 'parse_qsl'
             1338  LOAD_STR                 'urlparse'
             1340  LOAD_STR                 'urllib.parse'
             1342  CALL_FUNCTION_3       3  ''

 L. 362      1344  LOAD_NAME                MovedAttribute
             1346  LOAD_STR                 'urldefrag'
             1348  LOAD_STR                 'urlparse'
             1350  LOAD_STR                 'urllib.parse'
             1352  CALL_FUNCTION_3       3  ''

 L. 363      1354  LOAD_NAME                MovedAttribute
             1356  LOAD_STR                 'urljoin'
             1358  LOAD_STR                 'urlparse'
             1360  LOAD_STR                 'urllib.parse'
             1362  CALL_FUNCTION_3       3  ''

 L. 364      1364  LOAD_NAME                MovedAttribute
             1366  LOAD_STR                 'urlparse'
             1368  LOAD_STR                 'urlparse'
             1370  LOAD_STR                 'urllib.parse'
             1372  CALL_FUNCTION_3       3  ''

 L. 365      1374  LOAD_NAME                MovedAttribute
             1376  LOAD_STR                 'urlsplit'
             1378  LOAD_STR                 'urlparse'
             1380  LOAD_STR                 'urllib.parse'
             1382  CALL_FUNCTION_3       3  ''

 L. 366      1384  LOAD_NAME                MovedAttribute
             1386  LOAD_STR                 'urlunparse'
             1388  LOAD_STR                 'urlparse'
             1390  LOAD_STR                 'urllib.parse'
             1392  CALL_FUNCTION_3       3  ''

 L. 367      1394  LOAD_NAME                MovedAttribute
             1396  LOAD_STR                 'urlunsplit'
             1398  LOAD_STR                 'urlparse'
             1400  LOAD_STR                 'urllib.parse'
             1402  CALL_FUNCTION_3       3  ''

 L. 368      1404  LOAD_NAME                MovedAttribute
             1406  LOAD_STR                 'quote'
             1408  LOAD_STR                 'urllib'
             1410  LOAD_STR                 'urllib.parse'
             1412  CALL_FUNCTION_3       3  ''

 L. 369      1414  LOAD_NAME                MovedAttribute
             1416  LOAD_STR                 'quote_plus'
             1418  LOAD_STR                 'urllib'
             1420  LOAD_STR                 'urllib.parse'
             1422  CALL_FUNCTION_3       3  ''

 L. 370      1424  LOAD_NAME                MovedAttribute
             1426  LOAD_STR                 'unquote'
             1428  LOAD_STR                 'urllib'
             1430  LOAD_STR                 'urllib.parse'
             1432  CALL_FUNCTION_3       3  ''

 L. 371      1434  LOAD_NAME                MovedAttribute
             1436  LOAD_STR                 'unquote_plus'
             1438  LOAD_STR                 'urllib'
             1440  LOAD_STR                 'urllib.parse'
             1442  CALL_FUNCTION_3       3  ''

 L. 372      1444  LOAD_NAME                MovedAttribute

 L. 373      1446  LOAD_STR                 'unquote_to_bytes'
             1448  LOAD_STR                 'urllib'
             1450  LOAD_STR                 'urllib.parse'
             1452  LOAD_STR                 'unquote'
             1454  LOAD_STR                 'unquote_to_bytes'

 L. 372      1456  CALL_FUNCTION_5       5  ''

 L. 375      1458  LOAD_NAME                MovedAttribute
             1460  LOAD_STR                 'urlencode'
             1462  LOAD_STR                 'urllib'
             1464  LOAD_STR                 'urllib.parse'
             1466  CALL_FUNCTION_3       3  ''

 L. 376      1468  LOAD_NAME                MovedAttribute
             1470  LOAD_STR                 'splitquery'
             1472  LOAD_STR                 'urllib'
             1474  LOAD_STR                 'urllib.parse'
             1476  CALL_FUNCTION_3       3  ''

 L. 377      1478  LOAD_NAME                MovedAttribute
             1480  LOAD_STR                 'splittag'
             1482  LOAD_STR                 'urllib'
             1484  LOAD_STR                 'urllib.parse'
             1486  CALL_FUNCTION_3       3  ''

 L. 378      1488  LOAD_NAME                MovedAttribute
             1490  LOAD_STR                 'splituser'
             1492  LOAD_STR                 'urllib'
             1494  LOAD_STR                 'urllib.parse'
             1496  CALL_FUNCTION_3       3  ''

 L. 379      1498  LOAD_NAME                MovedAttribute
             1500  LOAD_STR                 'splitvalue'
             1502  LOAD_STR                 'urllib'
             1504  LOAD_STR                 'urllib.parse'
             1506  CALL_FUNCTION_3       3  ''

 L. 380      1508  LOAD_NAME                MovedAttribute
             1510  LOAD_STR                 'uses_fragment'
             1512  LOAD_STR                 'urlparse'
             1514  LOAD_STR                 'urllib.parse'
             1516  CALL_FUNCTION_3       3  ''

 L. 381      1518  LOAD_NAME                MovedAttribute
             1520  LOAD_STR                 'uses_netloc'
             1522  LOAD_STR                 'urlparse'
             1524  LOAD_STR                 'urllib.parse'
             1526  CALL_FUNCTION_3       3  ''

 L. 382      1528  LOAD_NAME                MovedAttribute
             1530  LOAD_STR                 'uses_params'
             1532  LOAD_STR                 'urlparse'
             1534  LOAD_STR                 'urllib.parse'
             1536  CALL_FUNCTION_3       3  ''

 L. 383      1538  LOAD_NAME                MovedAttribute
             1540  LOAD_STR                 'uses_query'
             1542  LOAD_STR                 'urlparse'
             1544  LOAD_STR                 'urllib.parse'
             1546  CALL_FUNCTION_3       3  ''

 L. 384      1548  LOAD_NAME                MovedAttribute
             1550  LOAD_STR                 'uses_relative'
             1552  LOAD_STR                 'urlparse'
             1554  LOAD_STR                 'urllib.parse'
             1556  CALL_FUNCTION_3       3  ''

 L. 357      1558  BUILD_LIST_25        25 
             1560  STORE_NAME               _urllib_parse_moved_attributes

 L. 386      1562  LOAD_NAME                _urllib_parse_moved_attributes
             1564  GET_ITER         
           1566_0  COME_FROM          1584  '1584'
             1566  FOR_ITER           1588  'to 1588'
             1568  STORE_NAME               attr

 L. 387      1570  LOAD_NAME                setattr
             1572  LOAD_NAME                Module_six_moves_urllib_parse
             1574  LOAD_NAME                attr
             1576  LOAD_ATTR                name
             1578  LOAD_NAME                attr
             1580  CALL_FUNCTION_3       3  ''
             1582  POP_TOP          
         1584_1586  JUMP_BACK          1566  'to 1566'
           1588_0  COME_FROM          1566  '1566'

 L. 388      1588  DELETE_NAME              attr

 L. 390      1590  LOAD_NAME                _urllib_parse_moved_attributes
             1592  LOAD_NAME                Module_six_moves_urllib_parse
             1594  STORE_ATTR               _moved_attributes

 L. 392      1596  LOAD_NAME                _importer
             1598  LOAD_METHOD              _add_module

 L. 393      1600  LOAD_NAME                Module_six_moves_urllib_parse
             1602  LOAD_NAME                __name__
             1604  LOAD_STR                 '.moves.urllib_parse'
             1606  BINARY_ADD       
             1608  CALL_FUNCTION_1       1  ''

 L. 394      1610  LOAD_STR                 'moves.urllib_parse'

 L. 395      1612  LOAD_STR                 'moves.urllib.parse'

 L. 392      1614  CALL_METHOD_3         3  ''
             1616  POP_TOP          

 L. 399      1618  LOAD_BUILD_CLASS 
             1620  LOAD_CODE                <code_object Module_six_moves_urllib_error>
             1622  LOAD_STR                 'Module_six_moves_urllib_error'
             1624  MAKE_FUNCTION_0          'Neither defaults, keyword-only args, annotations, nor closures'
             1626  LOAD_STR                 'Module_six_moves_urllib_error'
             1628  LOAD_NAME                _LazyModule
             1630  CALL_FUNCTION_3       3  ''
             1632  STORE_NAME               Module_six_moves_urllib_error

 L. 405      1634  LOAD_NAME                MovedAttribute
             1636  LOAD_STR                 'URLError'
             1638  LOAD_STR                 'urllib2'
             1640  LOAD_STR                 'urllib.error'
             1642  CALL_FUNCTION_3       3  ''

 L. 406      1644  LOAD_NAME                MovedAttribute
             1646  LOAD_STR                 'HTTPError'
             1648  LOAD_STR                 'urllib2'
             1650  LOAD_STR                 'urllib.error'
             1652  CALL_FUNCTION_3       3  ''

 L. 407      1654  LOAD_NAME                MovedAttribute
             1656  LOAD_STR                 'ContentTooShortError'
             1658  LOAD_STR                 'urllib'
             1660  LOAD_STR                 'urllib.error'
             1662  CALL_FUNCTION_3       3  ''

 L. 404      1664  BUILD_LIST_3          3 
             1666  STORE_NAME               _urllib_error_moved_attributes

 L. 409      1668  LOAD_NAME                _urllib_error_moved_attributes
             1670  GET_ITER         
           1672_0  COME_FROM          1690  '1690'
             1672  FOR_ITER           1694  'to 1694'
             1674  STORE_NAME               attr

 L. 410      1676  LOAD_NAME                setattr
             1678  LOAD_NAME                Module_six_moves_urllib_error
             1680  LOAD_NAME                attr
             1682  LOAD_ATTR                name
             1684  LOAD_NAME                attr
             1686  CALL_FUNCTION_3       3  ''
             1688  POP_TOP          
         1690_1692  JUMP_BACK          1672  'to 1672'
           1694_0  COME_FROM          1672  '1672'

 L. 411      1694  DELETE_NAME              attr

 L. 413      1696  LOAD_NAME                _urllib_error_moved_attributes
             1698  LOAD_NAME                Module_six_moves_urllib_error
             1700  STORE_ATTR               _moved_attributes

 L. 415      1702  LOAD_NAME                _importer
             1704  LOAD_METHOD              _add_module

 L. 416      1706  LOAD_NAME                Module_six_moves_urllib_error
             1708  LOAD_NAME                __name__
             1710  LOAD_STR                 '.moves.urllib.error'
             1712  BINARY_ADD       
             1714  CALL_FUNCTION_1       1  ''

 L. 417      1716  LOAD_STR                 'moves.urllib_error'

 L. 418      1718  LOAD_STR                 'moves.urllib.error'

 L. 415      1720  CALL_METHOD_3         3  ''
             1722  POP_TOP          

 L. 422      1724  LOAD_BUILD_CLASS 
             1726  LOAD_CODE                <code_object Module_six_moves_urllib_request>
             1728  LOAD_STR                 'Module_six_moves_urllib_request'
             1730  MAKE_FUNCTION_0          'Neither defaults, keyword-only args, annotations, nor closures'
             1732  LOAD_STR                 'Module_six_moves_urllib_request'
             1734  LOAD_NAME                _LazyModule
             1736  CALL_FUNCTION_3       3  ''
             1738  STORE_NAME               Module_six_moves_urllib_request

 L. 428      1740  LOAD_NAME                MovedAttribute
             1742  LOAD_STR                 'urlopen'
             1744  LOAD_STR                 'urllib2'
             1746  LOAD_STR                 'urllib.request'
             1748  CALL_FUNCTION_3       3  ''

 L. 429      1750  LOAD_NAME                MovedAttribute
             1752  LOAD_STR                 'install_opener'
             1754  LOAD_STR                 'urllib2'
             1756  LOAD_STR                 'urllib.request'
             1758  CALL_FUNCTION_3       3  ''

 L. 430      1760  LOAD_NAME                MovedAttribute
             1762  LOAD_STR                 'build_opener'
             1764  LOAD_STR                 'urllib2'
             1766  LOAD_STR                 'urllib.request'
             1768  CALL_FUNCTION_3       3  ''

 L. 431      1770  LOAD_NAME                MovedAttribute
             1772  LOAD_STR                 'pathname2url'
             1774  LOAD_STR                 'urllib'
             1776  LOAD_STR                 'urllib.request'
             1778  CALL_FUNCTION_3       3  ''

 L. 432      1780  LOAD_NAME                MovedAttribute
             1782  LOAD_STR                 'url2pathname'
             1784  LOAD_STR                 'urllib'
             1786  LOAD_STR                 'urllib.request'
             1788  CALL_FUNCTION_3       3  ''

 L. 433      1790  LOAD_NAME                MovedAttribute
             1792  LOAD_STR                 'getproxies'
             1794  LOAD_STR                 'urllib'
             1796  LOAD_STR                 'urllib.request'
             1798  CALL_FUNCTION_3       3  ''

 L. 434      1800  LOAD_NAME                MovedAttribute
             1802  LOAD_STR                 'Request'
             1804  LOAD_STR                 'urllib2'
             1806  LOAD_STR                 'urllib.request'
             1808  CALL_FUNCTION_3       3  ''

 L. 435      1810  LOAD_NAME                MovedAttribute
             1812  LOAD_STR                 'OpenerDirector'
             1814  LOAD_STR                 'urllib2'
             1816  LOAD_STR                 'urllib.request'
             1818  CALL_FUNCTION_3       3  ''

 L. 436      1820  LOAD_NAME                MovedAttribute
             1822  LOAD_STR                 'HTTPDefaultErrorHandler'
             1824  LOAD_STR                 'urllib2'
             1826  LOAD_STR                 'urllib.request'
             1828  CALL_FUNCTION_3       3  ''

 L. 437      1830  LOAD_NAME                MovedAttribute
             1832  LOAD_STR                 'HTTPRedirectHandler'
             1834  LOAD_STR                 'urllib2'
             1836  LOAD_STR                 'urllib.request'
             1838  CALL_FUNCTION_3       3  ''

 L. 438      1840  LOAD_NAME                MovedAttribute
             1842  LOAD_STR                 'HTTPCookieProcessor'
             1844  LOAD_STR                 'urllib2'
             1846  LOAD_STR                 'urllib.request'
             1848  CALL_FUNCTION_3       3  ''

 L. 439      1850  LOAD_NAME                MovedAttribute
             1852  LOAD_STR                 'ProxyHandler'
             1854  LOAD_STR                 'urllib2'
             1856  LOAD_STR                 'urllib.request'
             1858  CALL_FUNCTION_3       3  ''

 L. 440      1860  LOAD_NAME                MovedAttribute
             1862  LOAD_STR                 'BaseHandler'
             1864  LOAD_STR                 'urllib2'
             1866  LOAD_STR                 'urllib.request'
             1868  CALL_FUNCTION_3       3  ''

 L. 441      1870  LOAD_NAME                MovedAttribute
             1872  LOAD_STR                 'HTTPPasswordMgr'
             1874  LOAD_STR                 'urllib2'
             1876  LOAD_STR                 'urllib.request'
             1878  CALL_FUNCTION_3       3  ''

 L. 442      1880  LOAD_NAME                MovedAttribute
             1882  LOAD_STR                 'HTTPPasswordMgrWithDefaultRealm'
             1884  LOAD_STR                 'urllib2'
             1886  LOAD_STR                 'urllib.request'
             1888  CALL_FUNCTION_3       3  ''

 L. 443      1890  LOAD_NAME                MovedAttribute
             1892  LOAD_STR                 'AbstractBasicAuthHandler'
             1894  LOAD_STR                 'urllib2'
             1896  LOAD_STR                 'urllib.request'
             1898  CALL_FUNCTION_3       3  ''

 L. 444      1900  LOAD_NAME                MovedAttribute
             1902  LOAD_STR                 'HTTPBasicAuthHandler'
             1904  LOAD_STR                 'urllib2'
             1906  LOAD_STR                 'urllib.request'
             1908  CALL_FUNCTION_3       3  ''

 L. 445      1910  LOAD_NAME                MovedAttribute
         1912_1914  LOAD_STR                 'ProxyBasicAuthHandler'
             1916  LOAD_STR                 'urllib2'
             1918  LOAD_STR                 'urllib.request'
             1920  CALL_FUNCTION_3       3  ''

 L. 446      1922  LOAD_NAME                MovedAttribute
         1924_1926  LOAD_STR                 'AbstractDigestAuthHandler'
             1928  LOAD_STR                 'urllib2'
             1930  LOAD_STR                 'urllib.request'
             1932  CALL_FUNCTION_3       3  ''

 L. 447      1934  LOAD_NAME                MovedAttribute
         1936_1938  LOAD_STR                 'HTTPDigestAuthHandler'
             1940  LOAD_STR                 'urllib2'
             1942  LOAD_STR                 'urllib.request'
             1944  CALL_FUNCTION_3       3  ''

 L. 448      1946  LOAD_NAME                MovedAttribute
         1948_1950  LOAD_STR                 'ProxyDigestAuthHandler'
             1952  LOAD_STR                 'urllib2'
             1954  LOAD_STR                 'urllib.request'
             1956  CALL_FUNCTION_3       3  ''

 L. 449      1958  LOAD_NAME                MovedAttribute
         1960_1962  LOAD_STR                 'HTTPHandler'
             1964  LOAD_STR                 'urllib2'
             1966  LOAD_STR                 'urllib.request'
             1968  CALL_FUNCTION_3       3  ''

 L. 450      1970  LOAD_NAME                MovedAttribute
         1972_1974  LOAD_STR                 'HTTPSHandler'
             1976  LOAD_STR                 'urllib2'
             1978  LOAD_STR                 'urllib.request'
             1980  CALL_FUNCTION_3       3  ''

 L. 451      1982  LOAD_NAME                MovedAttribute
         1984_1986  LOAD_STR                 'FileHandler'
             1988  LOAD_STR                 'urllib2'
             1990  LOAD_STR                 'urllib.request'
             1992  CALL_FUNCTION_3       3  ''

 L. 452      1994  LOAD_NAME                MovedAttribute
         1996_1998  LOAD_STR                 'FTPHandler'
             2000  LOAD_STR                 'urllib2'
             2002  LOAD_STR                 'urllib.request'
             2004  CALL_FUNCTION_3       3  ''

 L. 453      2006  LOAD_NAME                MovedAttribute
         2008_2010  LOAD_STR                 'CacheFTPHandler'
             2012  LOAD_STR                 'urllib2'
             2014  LOAD_STR                 'urllib.request'
             2016  CALL_FUNCTION_3       3  ''

 L. 454      2018  LOAD_NAME                MovedAttribute
         2020_2022  LOAD_STR                 'UnknownHandler'
             2024  LOAD_STR                 'urllib2'
             2026  LOAD_STR                 'urllib.request'
             2028  CALL_FUNCTION_3       3  ''

 L. 455      2030  LOAD_NAME                MovedAttribute
         2032_2034  LOAD_STR                 'HTTPErrorProcessor'
             2036  LOAD_STR                 'urllib2'
             2038  LOAD_STR                 'urllib.request'
             2040  CALL_FUNCTION_3       3  ''

 L. 456      2042  LOAD_NAME                MovedAttribute
         2044_2046  LOAD_STR                 'urlretrieve'
             2048  LOAD_STR                 'urllib'
             2050  LOAD_STR                 'urllib.request'
             2052  CALL_FUNCTION_3       3  ''

 L. 457      2054  LOAD_NAME                MovedAttribute
         2056_2058  LOAD_STR                 'urlcleanup'
             2060  LOAD_STR                 'urllib'
             2062  LOAD_STR                 'urllib.request'
             2064  CALL_FUNCTION_3       3  ''

 L. 458      2066  LOAD_NAME                MovedAttribute
         2068_2070  LOAD_STR                 'URLopener'
             2072  LOAD_STR                 'urllib'
             2074  LOAD_STR                 'urllib.request'
             2076  CALL_FUNCTION_3       3  ''

 L. 459      2078  LOAD_NAME                MovedAttribute
         2080_2082  LOAD_STR                 'FancyURLopener'
             2084  LOAD_STR                 'urllib'
             2086  LOAD_STR                 'urllib.request'
             2088  CALL_FUNCTION_3       3  ''

 L. 460      2090  LOAD_NAME                MovedAttribute
         2092_2094  LOAD_STR                 'proxy_bypass'
             2096  LOAD_STR                 'urllib'
             2098  LOAD_STR                 'urllib.request'
             2100  CALL_FUNCTION_3       3  ''

 L. 461      2102  LOAD_NAME                MovedAttribute
         2104_2106  LOAD_STR                 'parse_http_list'
             2108  LOAD_STR                 'urllib2'
             2110  LOAD_STR                 'urllib.request'
             2112  CALL_FUNCTION_3       3  ''

 L. 462      2114  LOAD_NAME                MovedAttribute
         2116_2118  LOAD_STR                 'parse_keqv_list'
             2120  LOAD_STR                 'urllib2'
             2122  LOAD_STR                 'urllib.request'
             2124  CALL_FUNCTION_3       3  ''

 L. 427      2126  BUILD_LIST_35        35 
             2128  STORE_NAME               _urllib_request_moved_attributes

 L. 464      2130  LOAD_NAME                _urllib_request_moved_attributes
             2132  GET_ITER         
           2134_0  COME_FROM          2152  '2152'
             2134  FOR_ITER           2156  'to 2156'
             2136  STORE_NAME               attr

 L. 465      2138  LOAD_NAME                setattr
             2140  LOAD_NAME                Module_six_moves_urllib_request
             2142  LOAD_NAME                attr
             2144  LOAD_ATTR                name
             2146  LOAD_NAME                attr
             2148  CALL_FUNCTION_3       3  ''
             2150  POP_TOP          
         2152_2154  JUMP_BACK          2134  'to 2134'
           2156_0  COME_FROM          2134  '2134'

 L. 466      2156  DELETE_NAME              attr

 L. 468      2158  LOAD_NAME                _urllib_request_moved_attributes
             2160  LOAD_NAME                Module_six_moves_urllib_request
             2162  STORE_ATTR               _moved_attributes

 L. 470      2164  LOAD_NAME                _importer
             2166  LOAD_METHOD              _add_module

 L. 471      2168  LOAD_NAME                Module_six_moves_urllib_request
             2170  LOAD_NAME                __name__
         2172_2174  LOAD_STR                 '.moves.urllib.request'
             2176  BINARY_ADD       
             2178  CALL_FUNCTION_1       1  ''

 L. 472  2180_2182  LOAD_STR                 'moves.urllib_request'

 L. 473  2184_2186  LOAD_STR                 'moves.urllib.request'

 L. 470      2188  CALL_METHOD_3         3  ''
             2190  POP_TOP          

 L. 477      2192  LOAD_BUILD_CLASS 
         2194_2196  LOAD_CODE                <code_object Module_six_moves_urllib_response>
         2198_2200  LOAD_STR                 'Module_six_moves_urllib_response'
             2202  MAKE_FUNCTION_0          'Neither defaults, keyword-only args, annotations, nor closures'
         2204_2206  LOAD_STR                 'Module_six_moves_urllib_response'
             2208  LOAD_NAME                _LazyModule
             2210  CALL_FUNCTION_3       3  ''
             2212  STORE_NAME               Module_six_moves_urllib_response

 L. 483      2214  LOAD_NAME                MovedAttribute
         2216_2218  LOAD_STR                 'addbase'
             2220  LOAD_STR                 'urllib'
         2222_2224  LOAD_STR                 'urllib.response'
             2226  CALL_FUNCTION_3       3  ''

 L. 484      2228  LOAD_NAME                MovedAttribute
         2230_2232  LOAD_STR                 'addclosehook'
             2234  LOAD_STR                 'urllib'
         2236_2238  LOAD_STR                 'urllib.response'
             2240  CALL_FUNCTION_3       3  ''

 L. 485      2242  LOAD_NAME                MovedAttribute
         2244_2246  LOAD_STR                 'addinfo'
             2248  LOAD_STR                 'urllib'
         2250_2252  LOAD_STR                 'urllib.response'
             2254  CALL_FUNCTION_3       3  ''

 L. 486      2256  LOAD_NAME                MovedAttribute
         2258_2260  LOAD_STR                 'addinfourl'
             2262  LOAD_STR                 'urllib'
         2264_2266  LOAD_STR                 'urllib.response'
             2268  CALL_FUNCTION_3       3  ''

 L. 482      2270  BUILD_LIST_4          4 
             2272  STORE_NAME               _urllib_response_moved_attributes

 L. 488      2274  LOAD_NAME                _urllib_response_moved_attributes
             2276  GET_ITER         
           2278_0  COME_FROM          2296  '2296'
             2278  FOR_ITER           2300  'to 2300'
             2280  STORE_NAME               attr

 L. 489      2282  LOAD_NAME                setattr
             2284  LOAD_NAME                Module_six_moves_urllib_response
             2286  LOAD_NAME                attr
             2288  LOAD_ATTR                name
             2290  LOAD_NAME                attr
             2292  CALL_FUNCTION_3       3  ''
             2294  POP_TOP          
         2296_2298  JUMP_BACK          2278  'to 2278'
           2300_0  COME_FROM          2278  '2278'

 L. 490      2300  DELETE_NAME              attr

 L. 492      2302  LOAD_NAME                _urllib_response_moved_attributes
             2304  LOAD_NAME                Module_six_moves_urllib_response
             2306  STORE_ATTR               _moved_attributes

 L. 494      2308  LOAD_NAME                _importer
             2310  LOAD_METHOD              _add_module

 L. 495      2312  LOAD_NAME                Module_six_moves_urllib_response
             2314  LOAD_NAME                __name__
         2316_2318  LOAD_STR                 '.moves.urllib.response'
             2320  BINARY_ADD       
             2322  CALL_FUNCTION_1       1  ''

 L. 496  2324_2326  LOAD_STR                 'moves.urllib_response'

 L. 497  2328_2330  LOAD_STR                 'moves.urllib.response'

 L. 494      2332  CALL_METHOD_3         3  ''
             2334  POP_TOP          

 L. 501      2336  LOAD_BUILD_CLASS 
         2338_2340  LOAD_CODE                <code_object Module_six_moves_urllib_robotparser>
         2342_2344  LOAD_STR                 'Module_six_moves_urllib_robotparser'
             2346  MAKE_FUNCTION_0          'Neither defaults, keyword-only args, annotations, nor closures'
         2348_2350  LOAD_STR                 'Module_six_moves_urllib_robotparser'
             2352  LOAD_NAME                _LazyModule
             2354  CALL_FUNCTION_3       3  ''
             2356  STORE_NAME               Module_six_moves_urllib_robotparser

 L. 507      2358  LOAD_NAME                MovedAttribute
         2360_2362  LOAD_STR                 'RobotFileParser'
             2364  LOAD_STR                 'robotparser'
             2366  LOAD_STR                 'urllib.robotparser'
             2368  CALL_FUNCTION_3       3  ''

 L. 506      2370  BUILD_LIST_1          1 
             2372  STORE_NAME               _urllib_robotparser_moved_attributes

 L. 509      2374  LOAD_NAME                _urllib_robotparser_moved_attributes
             2376  GET_ITER         
           2378_0  COME_FROM          2396  '2396'
             2378  FOR_ITER           2400  'to 2400'
             2380  STORE_NAME               attr

 L. 510      2382  LOAD_NAME                setattr
             2384  LOAD_NAME                Module_six_moves_urllib_robotparser
             2386  LOAD_NAME                attr
             2388  LOAD_ATTR                name
             2390  LOAD_NAME                attr
             2392  CALL_FUNCTION_3       3  ''
             2394  POP_TOP          
         2396_2398  JUMP_BACK          2378  'to 2378'
           2400_0  COME_FROM          2378  '2378'

 L. 511      2400  DELETE_NAME              attr

 L. 514      2402  LOAD_NAME                _urllib_robotparser_moved_attributes

 L. 513      2404  LOAD_NAME                Module_six_moves_urllib_robotparser
             2406  STORE_ATTR               _moved_attributes

 L. 517      2408  LOAD_NAME                _importer
             2410  LOAD_METHOD              _add_module

 L. 518      2412  LOAD_NAME                Module_six_moves_urllib_robotparser
             2414  LOAD_NAME                __name__
         2416_2418  LOAD_STR                 '.moves.urllib.robotparser'
             2420  BINARY_ADD       
             2422  CALL_FUNCTION_1       1  ''

 L. 519  2424_2426  LOAD_STR                 'moves.urllib_robotparser'

 L. 520  2428_2430  LOAD_STR                 'moves.urllib.robotparser'

 L. 517      2432  CALL_METHOD_3         3  ''
             2434  POP_TOP          

 L. 524      2436  LOAD_BUILD_CLASS 
         2438_2440  LOAD_CODE                <code_object Module_six_moves_urllib>
         2442_2444  LOAD_STR                 'Module_six_moves_urllib'
             2446  MAKE_FUNCTION_0          'Neither defaults, keyword-only args, annotations, nor closures'
         2448_2450  LOAD_STR                 'Module_six_moves_urllib'
             2452  LOAD_NAME                types
             2454  LOAD_ATTR                ModuleType
             2456  CALL_FUNCTION_3       3  ''
             2458  STORE_NAME               Module_six_moves_urllib

 L. 539      2460  LOAD_NAME                _importer
             2462  LOAD_METHOD              _add_module

 L. 540      2464  LOAD_NAME                Module_six_moves_urllib
             2466  LOAD_NAME                __name__
             2468  LOAD_STR                 '.moves.urllib'
             2470  BINARY_ADD       
             2472  CALL_FUNCTION_1       1  ''
         2474_2476  LOAD_STR                 'moves.urllib'

 L. 539      2478  CALL_METHOD_2         2  ''
             2480  POP_TOP          

 L. 544  2482_2484  LOAD_CODE                <code_object add_move>
         2486_2488  LOAD_STR                 'add_move'
             2490  MAKE_FUNCTION_0          'Neither defaults, keyword-only args, annotations, nor closures'
             2492  STORE_NAME               add_move

 L. 549  2494_2496  LOAD_CODE                <code_object remove_move>
         2498_2500  LOAD_STR                 'remove_move'
             2502  MAKE_FUNCTION_0          'Neither defaults, keyword-only args, annotations, nor closures'
             2504  STORE_NAME               remove_move

 L. 560      2506  LOAD_NAME                PY3
         2508_2510  POP_JUMP_IF_FALSE  2550  'to 2550'

 L. 561  2512_2514  LOAD_STR                 '__func__'
             2516  STORE_NAME               _meth_func

 L. 562  2518_2520  LOAD_STR                 '__self__'
             2522  STORE_NAME               _meth_self

 L. 564  2524_2526  LOAD_STR                 '__closure__'
             2528  STORE_NAME               _func_closure

 L. 565  2530_2532  LOAD_STR                 '__code__'
             2534  STORE_NAME               _func_code

 L. 566  2536_2538  LOAD_STR                 '__defaults__'
             2540  STORE_NAME               _func_defaults

 L. 567  2542_2544  LOAD_STR                 '__globals__'
             2546  STORE_NAME               _func_globals
             2548  JUMP_FORWARD       2586  'to 2586'
           2550_0  COME_FROM          2508  '2508'

 L. 569  2550_2552  LOAD_STR                 'im_func'
             2554  STORE_NAME               _meth_func

 L. 570  2556_2558  LOAD_STR                 'im_self'
             2560  STORE_NAME               _meth_self

 L. 572  2562_2564  LOAD_STR                 'func_closure'
             2566  STORE_NAME               _func_closure

 L. 573  2568_2570  LOAD_STR                 'func_code'
             2572  STORE_NAME               _func_code

 L. 574  2574_2576  LOAD_STR                 'func_defaults'
             2578  STORE_NAME               _func_defaults

 L. 575  2580_2582  LOAD_STR                 'func_globals'
             2584  STORE_NAME               _func_globals
           2586_0  COME_FROM          2548  '2548'

 L. 578      2586  SETUP_FINALLY      2596  'to 2596'

 L. 579      2588  LOAD_NAME                next
             2590  STORE_NAME               advance_iterator
             2592  POP_BLOCK        
             2594  JUMP_FORWARD       2628  'to 2628'
           2596_0  COME_FROM_FINALLY  2586  '2586'

 L. 580      2596  DUP_TOP          
             2598  LOAD_NAME                NameError
         2600_2602  <121>              2626  ''
             2604  POP_TOP          
             2606  POP_TOP          
             2608  POP_TOP          

 L. 582  2610_2612  LOAD_CODE                <code_object advance_iterator>
         2614_2616  LOAD_STR                 'advance_iterator'
             2618  MAKE_FUNCTION_0          'Neither defaults, keyword-only args, annotations, nor closures'
             2620  STORE_NAME               advance_iterator
             2622  POP_EXCEPT       
             2624  JUMP_FORWARD       2628  'to 2628'
             2626  <48>             
           2628_0  COME_FROM          2624  '2624'
           2628_1  COME_FROM          2594  '2594'

 L. 586      2628  LOAD_NAME                advance_iterator
             2630  STORE_NAME               next

 L. 589      2632  SETUP_FINALLY      2642  'to 2642'

 L. 590      2634  LOAD_NAME                callable
             2636  STORE_NAME               callable
             2638  POP_BLOCK        
             2640  JUMP_FORWARD       2674  'to 2674'
           2642_0  COME_FROM_FINALLY  2632  '2632'

 L. 591      2642  DUP_TOP          
             2644  LOAD_NAME                NameError
         2646_2648  <121>              2672  ''
             2650  POP_TOP          
             2652  POP_TOP          
             2654  POP_TOP          

 L. 593  2656_2658  LOAD_CODE                <code_object callable>
         2660_2662  LOAD_STR                 'callable'
             2664  MAKE_FUNCTION_0          'Neither defaults, keyword-only args, annotations, nor closures'
             2666  STORE_NAME               callable
             2668  POP_EXCEPT       
             2670  JUMP_FORWARD       2674  'to 2674'
             2672  <48>             
           2674_0  COME_FROM          2670  '2670'
           2674_1  COME_FROM          2640  '2640'

 L. 597      2674  LOAD_NAME                PY3
         2676_2678  POP_JUMP_IF_FALSE  2716  'to 2716'

 L. 599  2680_2682  LOAD_CODE                <code_object get_unbound_function>
         2684_2686  LOAD_STR                 'get_unbound_function'
             2688  MAKE_FUNCTION_0          'Neither defaults, keyword-only args, annotations, nor closures'
             2690  STORE_NAME               get_unbound_function

 L. 602      2692  LOAD_NAME                types
             2694  LOAD_ATTR                MethodType
             2696  STORE_NAME               create_bound_method

 L. 604  2698_2700  LOAD_CODE                <code_object create_unbound_method>
         2702_2704  LOAD_STR                 'create_unbound_method'
             2706  MAKE_FUNCTION_0          'Neither defaults, keyword-only args, annotations, nor closures'
             2708  STORE_NAME               create_unbound_method

 L. 607      2710  LOAD_NAME                object
             2712  STORE_NAME               Iterator
             2714  JUMP_FORWARD       2778  'to 2778'
           2716_0  COME_FROM          2676  '2676'

 L. 610  2716_2718  LOAD_CODE                <code_object get_unbound_function>
         2720_2722  LOAD_STR                 'get_unbound_function'
             2724  MAKE_FUNCTION_0          'Neither defaults, keyword-only args, annotations, nor closures'
             2726  STORE_NAME               get_unbound_function

 L. 613  2728_2730  LOAD_CODE                <code_object create_bound_method>
         2732_2734  LOAD_STR                 'create_bound_method'
             2736  MAKE_FUNCTION_0          'Neither defaults, keyword-only args, annotations, nor closures'
             2738  STORE_NAME               create_bound_method

 L. 616  2740_2742  LOAD_CODE                <code_object create_unbound_method>
         2744_2746  LOAD_STR                 'create_unbound_method'
             2748  MAKE_FUNCTION_0          'Neither defaults, keyword-only args, annotations, nor closures'
             2750  STORE_NAME               create_unbound_method

 L. 619      2752  LOAD_BUILD_CLASS 
         2754_2756  LOAD_CODE                <code_object Iterator>
         2758_2760  LOAD_STR                 'Iterator'
             2762  MAKE_FUNCTION_0          'Neither defaults, keyword-only args, annotations, nor closures'
         2764_2766  LOAD_STR                 'Iterator'
             2768  LOAD_NAME                object
             2770  CALL_FUNCTION_3       3  ''
             2772  STORE_NAME               Iterator

 L. 623      2774  LOAD_NAME                callable
             2776  STORE_NAME               callable
           2778_0  COME_FROM          2714  '2714'

 L. 624      2778  LOAD_NAME                _add_doc

 L. 625      2780  LOAD_NAME                get_unbound_function
         2782_2784  LOAD_STR                 'Get the function out of a possibly unbound function'

 L. 624      2786  CALL_FUNCTION_2       2  ''
             2788  POP_TOP          

 L. 629      2790  LOAD_NAME                operator
             2792  LOAD_METHOD              attrgetter
             2794  LOAD_NAME                _meth_func
             2796  CALL_METHOD_1         1  ''
             2798  STORE_NAME               get_method_function

 L. 630      2800  LOAD_NAME                operator
             2802  LOAD_METHOD              attrgetter
             2804  LOAD_NAME                _meth_self
             2806  CALL_METHOD_1         1  ''
             2808  STORE_NAME               get_method_self

 L. 631      2810  LOAD_NAME                operator
             2812  LOAD_METHOD              attrgetter
             2814  LOAD_NAME                _func_closure
             2816  CALL_METHOD_1         1  ''
             2818  STORE_NAME               get_function_closure

 L. 632      2820  LOAD_NAME                operator
             2822  LOAD_METHOD              attrgetter
             2824  LOAD_NAME                _func_code
             2826  CALL_METHOD_1         1  ''
             2828  STORE_NAME               get_function_code

 L. 633      2830  LOAD_NAME                operator
             2832  LOAD_METHOD              attrgetter
             2834  LOAD_NAME                _func_defaults
             2836  CALL_METHOD_1         1  ''
             2838  STORE_NAME               get_function_defaults

 L. 634      2840  LOAD_NAME                operator
             2842  LOAD_METHOD              attrgetter
             2844  LOAD_NAME                _func_globals
             2846  CALL_METHOD_1         1  ''
             2848  STORE_NAME               get_function_globals

 L. 637      2850  LOAD_NAME                PY3
         2852_2854  POP_JUMP_IF_FALSE  2942  'to 2942'

 L. 639  2856_2858  LOAD_CODE                <code_object iterkeys>
         2860_2862  LOAD_STR                 'iterkeys'
             2864  MAKE_FUNCTION_0          'Neither defaults, keyword-only args, annotations, nor closures'
             2866  STORE_NAME               iterkeys

 L. 642  2868_2870  LOAD_CODE                <code_object itervalues>
         2872_2874  LOAD_STR                 'itervalues'
             2876  MAKE_FUNCTION_0          'Neither defaults, keyword-only args, annotations, nor closures'
             2878  STORE_NAME               itervalues

 L. 645  2880_2882  LOAD_CODE                <code_object iteritems>
         2884_2886  LOAD_STR                 'iteritems'
             2888  MAKE_FUNCTION_0          'Neither defaults, keyword-only args, annotations, nor closures'
             2890  STORE_NAME               iteritems

 L. 648  2892_2894  LOAD_CODE                <code_object iterlists>
         2896_2898  LOAD_STR                 'iterlists'
             2900  MAKE_FUNCTION_0          'Neither defaults, keyword-only args, annotations, nor closures'
             2902  STORE_NAME               iterlists

 L. 651      2904  LOAD_NAME                operator
             2906  LOAD_METHOD              methodcaller
         2908_2910  LOAD_STR                 'keys'
             2912  CALL_METHOD_1         1  ''
             2914  STORE_NAME               viewkeys

 L. 653      2916  LOAD_NAME                operator
             2918  LOAD_METHOD              methodcaller
         2920_2922  LOAD_STR                 'values'
             2924  CALL_METHOD_1         1  ''
             2926  STORE_NAME               viewvalues

 L. 655      2928  LOAD_NAME                operator
             2930  LOAD_METHOD              methodcaller
         2932_2934  LOAD_STR                 'items'
             2936  CALL_METHOD_1         1  ''
             2938  STORE_NAME               viewitems
             2940  JUMP_FORWARD       3026  'to 3026'
           2942_0  COME_FROM          2852  '2852'

 L. 658  2942_2944  LOAD_CODE                <code_object iterkeys>
         2946_2948  LOAD_STR                 'iterkeys'
             2950  MAKE_FUNCTION_0          'Neither defaults, keyword-only args, annotations, nor closures'
             2952  STORE_NAME               iterkeys

 L. 661  2954_2956  LOAD_CODE                <code_object itervalues>
         2958_2960  LOAD_STR                 'itervalues'
             2962  MAKE_FUNCTION_0          'Neither defaults, keyword-only args, annotations, nor closures'
             2964  STORE_NAME               itervalues

 L. 664  2966_2968  LOAD_CODE                <code_object iteritems>
         2970_2972  LOAD_STR                 'iteritems'
             2974  MAKE_FUNCTION_0          'Neither defaults, keyword-only args, annotations, nor closures'
             2976  STORE_NAME               iteritems

 L. 667  2978_2980  LOAD_CODE                <code_object iterlists>
         2982_2984  LOAD_STR                 'iterlists'
             2986  MAKE_FUNCTION_0          'Neither defaults, keyword-only args, annotations, nor closures'
             2988  STORE_NAME               iterlists

 L. 670      2990  LOAD_NAME                operator
             2992  LOAD_METHOD              methodcaller
         2994_2996  LOAD_STR                 'viewkeys'
             2998  CALL_METHOD_1         1  ''
             3000  STORE_NAME               viewkeys

 L. 672      3002  LOAD_NAME                operator
             3004  LOAD_METHOD              methodcaller
         3006_3008  LOAD_STR                 'viewvalues'
             3010  CALL_METHOD_1         1  ''
             3012  STORE_NAME               viewvalues

 L. 674      3014  LOAD_NAME                operator
             3016  LOAD_METHOD              methodcaller
         3018_3020  LOAD_STR                 'viewitems'
             3022  CALL_METHOD_1         1  ''
             3024  STORE_NAME               viewitems
           3026_0  COME_FROM          2940  '2940'

 L. 676      3026  LOAD_NAME                _add_doc
             3028  LOAD_NAME                iterkeys
         3030_3032  LOAD_STR                 'Return an iterator over the keys of a dictionary.'
             3034  CALL_FUNCTION_2       2  ''
             3036  POP_TOP          

 L. 677      3038  LOAD_NAME                _add_doc
             3040  LOAD_NAME                itervalues
         3042_3044  LOAD_STR                 'Return an iterator over the values of a dictionary.'
             3046  CALL_FUNCTION_2       2  ''
             3048  POP_TOP          

 L. 678      3050  LOAD_NAME                _add_doc
             3052  LOAD_NAME                iteritems
         3054_3056  LOAD_STR                 'Return an iterator over the (key, value) pairs of a dictionary.'
             3058  CALL_FUNCTION_2       2  ''
             3060  POP_TOP          

 L. 679      3062  LOAD_NAME                _add_doc

 L. 680      3064  LOAD_NAME                iterlists
         3066_3068  LOAD_STR                 'Return an iterator over the (key, [values]) pairs of a dictionary.'

 L. 679      3070  CALL_FUNCTION_2       2  ''
             3072  POP_TOP          

 L. 684      3074  LOAD_NAME                PY3
         3076_3078  POP_JUMP_IF_FALSE  3240  'to 3240'

 L. 686  3080_3082  LOAD_CODE                <code_object b>
         3084_3086  LOAD_STR                 'b'
             3088  MAKE_FUNCTION_0          'Neither defaults, keyword-only args, annotations, nor closures'
             3090  STORE_NAME               b

 L. 689  3092_3094  LOAD_CODE                <code_object u>
         3096_3098  LOAD_STR                 'u'
             3100  MAKE_FUNCTION_0          'Neither defaults, keyword-only args, annotations, nor closures'
             3102  STORE_NAME               u

 L. 692      3104  LOAD_NAME                chr
             3106  STORE_NAME               unichr

 L. 693      3108  LOAD_CONST               0
             3110  LOAD_CONST               None
             3112  IMPORT_NAME              struct
             3114  STORE_NAME               struct

 L. 695      3116  LOAD_NAME                struct
             3118  LOAD_METHOD              Struct
         3120_3122  LOAD_STR                 '>B'
             3124  CALL_METHOD_1         1  ''
             3126  LOAD_ATTR                pack
             3128  STORE_NAME               int2byte

 L. 696      3130  DELETE_NAME              struct

 L. 697      3132  LOAD_NAME                operator
             3134  LOAD_METHOD              itemgetter
             3136  LOAD_CONST               0
             3138  CALL_METHOD_1         1  ''
             3140  STORE_NAME               byte2int

 L. 698      3142  LOAD_NAME                operator
             3144  LOAD_ATTR                getitem
             3146  STORE_NAME               indexbytes

 L. 699      3148  LOAD_NAME                iter
             3150  STORE_NAME               iterbytes

 L. 700      3152  LOAD_CONST               0
             3154  LOAD_CONST               None
             3156  IMPORT_NAME              io
             3158  STORE_NAME               io

 L. 702      3160  LOAD_NAME                io
             3162  LOAD_ATTR                StringIO
             3164  STORE_NAME               StringIO

 L. 703      3166  LOAD_NAME                io
             3168  LOAD_ATTR                BytesIO
             3170  STORE_NAME               BytesIO

 L. 704      3172  DELETE_NAME              io

 L. 705  3174_3176  LOAD_STR                 'assertCountEqual'
             3178  STORE_NAME               _assertCountEqual

 L. 706      3180  LOAD_NAME                sys
             3182  LOAD_ATTR                version_info
         3184_3186  LOAD_CONST               1
             3188  BINARY_SUBSCR    
         3190_3192  LOAD_CONST               1
             3194  COMPARE_OP               <=
         3196_3198  POP_JUMP_IF_FALSE  3220  'to 3220'

 L. 707  3200_3202  LOAD_STR                 'assertRaisesRegexp'
             3204  STORE_NAME               _assertRaisesRegex

 L. 708  3206_3208  LOAD_STR                 'assertRegexpMatches'
             3210  STORE_NAME               _assertRegex

 L. 709  3212_3214  LOAD_STR                 'assertNotRegexpMatches'
             3216  STORE_NAME               _assertNotRegex
             3218  JUMP_FORWARD       3238  'to 3238'
           3220_0  COME_FROM          3196  '3196'

 L. 711  3220_3222  LOAD_STR                 'assertRaisesRegex'
             3224  STORE_NAME               _assertRaisesRegex

 L. 712  3226_3228  LOAD_STR                 'assertRegex'
             3230  STORE_NAME               _assertRegex

 L. 713  3232_3234  LOAD_STR                 'assertNotRegex'
             3236  STORE_NAME               _assertNotRegex
           3238_0  COME_FROM          3218  '3218'
             3238  JUMP_FORWARD       3352  'to 3352'
           3240_0  COME_FROM          3076  '3076'

 L. 716  3240_3242  LOAD_CODE                <code_object b>
         3244_3246  LOAD_STR                 'b'
             3248  MAKE_FUNCTION_0          'Neither defaults, keyword-only args, annotations, nor closures'
             3250  STORE_NAME               b

 L. 721  3252_3254  LOAD_CODE                <code_object u>
         3256_3258  LOAD_STR                 'u'
             3260  MAKE_FUNCTION_0          'Neither defaults, keyword-only args, annotations, nor closures'
             3262  STORE_NAME               u

 L. 724      3264  LOAD_NAME                unichr
             3266  STORE_NAME               unichr

 L. 725      3268  LOAD_NAME                chr
             3270  STORE_NAME               int2byte

 L. 727  3272_3274  LOAD_CODE                <code_object byte2int>
         3276_3278  LOAD_STR                 'byte2int'
             3280  MAKE_FUNCTION_0          'Neither defaults, keyword-only args, annotations, nor closures'
             3282  STORE_NAME               byte2int

 L. 730  3284_3286  LOAD_CODE                <code_object indexbytes>
         3288_3290  LOAD_STR                 'indexbytes'
             3292  MAKE_FUNCTION_0          'Neither defaults, keyword-only args, annotations, nor closures'
             3294  STORE_NAME               indexbytes

 L. 733      3296  LOAD_NAME                functools
             3298  LOAD_METHOD              partial
             3300  LOAD_NAME                itertools
             3302  LOAD_ATTR                imap
             3304  LOAD_NAME                ord
             3306  CALL_METHOD_2         2  ''
             3308  STORE_NAME               iterbytes

 L. 734      3310  LOAD_CONST               0
             3312  LOAD_CONST               None
             3314  IMPORT_NAME              StringIO
             3316  STORE_NAME               StringIO

 L. 736      3318  LOAD_NAME                StringIO
             3320  LOAD_ATTR                StringIO
             3322  DUP_TOP          
             3324  STORE_NAME               StringIO
             3326  STORE_NAME               BytesIO

 L. 737  3328_3330  LOAD_STR                 'assertItemsEqual'
             3332  STORE_NAME               _assertCountEqual

 L. 738  3334_3336  LOAD_STR                 'assertRaisesRegexp'
             3338  STORE_NAME               _assertRaisesRegex

 L. 739  3340_3342  LOAD_STR                 'assertRegexpMatches'
             3344  STORE_NAME               _assertRegex

 L. 740  3346_3348  LOAD_STR                 'assertNotRegexpMatches'
             3350  STORE_NAME               _assertNotRegex
           3352_0  COME_FROM          3238  '3238'

 L. 741      3352  LOAD_NAME                _add_doc
             3354  LOAD_NAME                b
         3356_3358  LOAD_STR                 'Byte literal'
             3360  CALL_FUNCTION_2       2  ''
             3362  POP_TOP          

 L. 742      3364  LOAD_NAME                _add_doc
             3366  LOAD_NAME                u
         3368_3370  LOAD_STR                 'Text literal'
             3372  CALL_FUNCTION_2       2  ''
             3374  POP_TOP          

 L. 745  3376_3378  LOAD_CODE                <code_object assertCountEqual>
         3380_3382  LOAD_STR                 'assertCountEqual'
             3384  MAKE_FUNCTION_0          'Neither defaults, keyword-only args, annotations, nor closures'
             3386  STORE_NAME               assertCountEqual

 L. 749  3388_3390  LOAD_CODE                <code_object assertRaisesRegex>
         3392_3394  LOAD_STR                 'assertRaisesRegex'
             3396  MAKE_FUNCTION_0          'Neither defaults, keyword-only args, annotations, nor closures'
             3398  STORE_NAME               assertRaisesRegex

 L. 753  3400_3402  LOAD_CODE                <code_object assertRegex>
         3404_3406  LOAD_STR                 'assertRegex'
             3408  MAKE_FUNCTION_0          'Neither defaults, keyword-only args, annotations, nor closures'
             3410  STORE_NAME               assertRegex

 L. 757  3412_3414  LOAD_CODE                <code_object assertNotRegex>
         3416_3418  LOAD_STR                 'assertNotRegex'
             3420  MAKE_FUNCTION_0          'Neither defaults, keyword-only args, annotations, nor closures'
             3422  STORE_NAME               assertNotRegex

 L. 761      3424  LOAD_NAME                PY3
         3426_3428  POP_JUMP_IF_FALSE  3462  'to 3462'

 L. 762      3430  LOAD_NAME                getattr
             3432  LOAD_NAME                moves
             3434  LOAD_ATTR                builtins
         3436_3438  LOAD_STR                 'exec'
             3440  CALL_FUNCTION_2       2  ''
             3442  STORE_NAME               exec_

 L. 764  3444_3446  LOAD_CONST               (None,)
         3448_3450  LOAD_CODE                <code_object reraise>
         3452_3454  LOAD_STR                 'reraise'
             3456  MAKE_FUNCTION_1          'default'
             3458  STORE_NAME               reraise
             3460  JUMP_FORWARD       3488  'to 3488'
           3462_0  COME_FROM          3426  '3426'

 L. 778  3462_3464  LOAD_CONST               (None, None)
         3466_3468  LOAD_CODE                <code_object exec_>
         3470_3472  LOAD_STR                 'exec_'
             3474  MAKE_FUNCTION_1          'default'
             3476  STORE_NAME               exec_

 L. 790      3478  LOAD_NAME                exec_

 L. 791  3480_3482  LOAD_STR                 'def reraise(tp, value, tb=None):\n    try:\n        raise tp, value, tb\n    finally:\n        tb = None\n'

 L. 790      3484  CALL_FUNCTION_1       1  ''
             3486  POP_TOP          
           3488_0  COME_FROM          3460  '3460'

 L. 800      3488  LOAD_NAME                sys
             3490  LOAD_ATTR                version_info
             3492  LOAD_CONST               None
             3494  LOAD_CONST               2
             3496  BUILD_SLICE_2         2 
             3498  BINARY_SUBSCR    
         3500_3502  LOAD_CONST               (3,)
             3504  COMPARE_OP               >
         3506_3508  POP_JUMP_IF_FALSE  3522  'to 3522'

 L. 801      3510  LOAD_NAME                exec_

 L. 802  3512_3514  LOAD_STR                 'def raise_from(value, from_value):\n    try:\n        raise value from from_value\n    finally:\n        value = None\n'

 L. 801      3516  CALL_FUNCTION_1       1  ''
             3518  POP_TOP          
             3520  JUMP_FORWARD       3534  'to 3534'
           3522_0  COME_FROM          3506  '3506'

 L. 811  3522_3524  LOAD_CODE                <code_object raise_from>
         3526_3528  LOAD_STR                 'raise_from'
             3530  MAKE_FUNCTION_0          'Neither defaults, keyword-only args, annotations, nor closures'
             3532  STORE_NAME               raise_from
           3534_0  COME_FROM          3520  '3520'

 L. 815      3534  LOAD_NAME                getattr
             3536  LOAD_NAME                moves
             3538  LOAD_ATTR                builtins
         3540_3542  LOAD_STR                 'print'
             3544  LOAD_CONST               None
             3546  CALL_FUNCTION_3       3  ''
             3548  STORE_NAME               print_

 L. 816      3550  LOAD_NAME                print_
             3552  LOAD_CONST               None
             3554  <117>                 0  ''
         3556_3558  POP_JUMP_IF_FALSE  3572  'to 3572'

 L. 818  3560_3562  LOAD_CODE                <code_object print_>
         3564_3566  LOAD_STR                 'print_'
             3568  MAKE_FUNCTION_0          'Neither defaults, keyword-only args, annotations, nor closures'
             3570  STORE_NAME               print_
           3572_0  COME_FROM          3556  '3556'

 L. 876      3572  LOAD_NAME                sys
             3574  LOAD_ATTR                version_info
             3576  LOAD_CONST               None
             3578  LOAD_CONST               2
             3580  BUILD_SLICE_2         2 
             3582  BINARY_SUBSCR    
             3584  LOAD_CONST               (3, 3)
             3586  COMPARE_OP               <
         3588_3590  POP_JUMP_IF_FALSE  3608  'to 3608'

 L. 877      3592  LOAD_NAME                print_
             3594  STORE_NAME               _print

 L. 879  3596_3598  LOAD_CODE                <code_object print_>
         3600_3602  LOAD_STR                 'print_'
             3604  MAKE_FUNCTION_0          'Neither defaults, keyword-only args, annotations, nor closures'
             3606  STORE_NAME               print_
           3608_0  COME_FROM          3588  '3588'

 L. 887      3608  LOAD_NAME                _add_doc
             3610  LOAD_NAME                reraise
         3612_3614  LOAD_STR                 'Reraise an exception.'
             3616  CALL_FUNCTION_2       2  ''
             3618  POP_TOP          

 L. 889      3620  LOAD_NAME                sys
             3622  LOAD_ATTR                version_info
             3624  LOAD_CONST               0
             3626  LOAD_CONST               2
             3628  BUILD_SLICE_2         2 
             3630  BINARY_SUBSCR    
             3632  LOAD_CONST               (3, 4)
             3634  COMPARE_OP               <
         3636_3638  POP_JUMP_IF_FALSE  3706  'to 3706'

 L. 898      3640  LOAD_NAME                functools
             3642  LOAD_ATTR                WRAPPER_ASSIGNMENTS

 L. 899      3644  LOAD_NAME                functools
             3646  LOAD_ATTR                WRAPPER_UPDATES

 L. 895      3648  BUILD_TUPLE_2         2 
         3650_3652  LOAD_CODE                <code_object _update_wrapper>
         3654_3656  LOAD_STR                 '_update_wrapper'
             3658  MAKE_FUNCTION_1          'default'
             3660  STORE_NAME               _update_wrapper

 L. 913      3662  LOAD_NAME                functools
             3664  LOAD_ATTR                update_wrapper
             3666  LOAD_ATTR                __doc__
             3668  LOAD_NAME                _update_wrapper
             3670  STORE_ATTR               __doc__

 L. 917      3672  LOAD_NAME                functools
             3674  LOAD_ATTR                WRAPPER_ASSIGNMENTS

 L. 918      3676  LOAD_NAME                functools
             3678  LOAD_ATTR                WRAPPER_UPDATES

 L. 915      3680  BUILD_TUPLE_2         2 
         3682_3684  LOAD_CODE                <code_object wraps>
         3686_3688  LOAD_STR                 'wraps'
             3690  MAKE_FUNCTION_1          'default'
             3692  STORE_NAME               wraps

 L. 924      3694  LOAD_NAME                functools
             3696  LOAD_ATTR                wraps
             3698  LOAD_ATTR                __doc__
             3700  LOAD_NAME                wraps
             3702  STORE_ATTR               __doc__
             3704  JUMP_FORWARD       3712  'to 3712'
           3706_0  COME_FROM          3636  '3636'

 L. 927      3706  LOAD_NAME                functools
             3708  LOAD_ATTR                wraps
             3710  STORE_NAME               wraps
           3712_0  COME_FROM          3704  '3704'

 L. 930  3712_3714  LOAD_CODE                <code_object with_metaclass>
         3716_3718  LOAD_STR                 'with_metaclass'
             3720  MAKE_FUNCTION_0          'Neither defaults, keyword-only args, annotations, nor closures'
             3722  STORE_NAME               with_metaclass

 L. 954  3724_3726  LOAD_CODE                <code_object add_metaclass>
         3728_3730  LOAD_STR                 'add_metaclass'
             3732  MAKE_FUNCTION_0          'Neither defaults, keyword-only args, annotations, nor closures'
             3734  STORE_NAME               add_metaclass

 L. 974  3736_3738  LOAD_CONST               ('utf-8', 'strict')
         3740_3742  LOAD_CODE                <code_object ensure_binary>
         3744_3746  LOAD_STR                 'ensure_binary'
             3748  MAKE_FUNCTION_1          'default'
             3750  STORE_NAME               ensure_binary

 L. 992  3752_3754  LOAD_CONST               ('utf-8', 'strict')
         3756_3758  LOAD_CODE                <code_object ensure_str>
         3760_3762  LOAD_STR                 'ensure_str'
             3764  MAKE_FUNCTION_1          'default'
             3766  STORE_NAME               ensure_str

 L.1015  3768_3770  LOAD_CONST               ('utf-8', 'strict')
         3772_3774  LOAD_CODE                <code_object ensure_text>
         3776_3778  LOAD_STR                 'ensure_text'
             3780  MAKE_FUNCTION_1          'default'
             3782  STORE_NAME               ensure_text

 L.1034  3784_3786  LOAD_CODE                <code_object python_2_unicode_compatible>
         3788_3790  LOAD_STR                 'python_2_unicode_compatible'
             3792  MAKE_FUNCTION_0          'Neither defaults, keyword-only args, annotations, nor closures'
             3794  STORE_NAME               python_2_unicode_compatible

 L.1056      3796  BUILD_LIST_0          0 
             3798  STORE_NAME               __path__

 L.1057      3800  LOAD_NAME                __name__
             3802  STORE_NAME               __package__

 L.1058      3804  LOAD_NAME                globals
             3806  CALL_FUNCTION_0       0  ''
             3808  LOAD_METHOD              get
         3810_3812  LOAD_STR                 '__spec__'
             3814  CALL_METHOD_1         1  ''
             3816  LOAD_CONST               None
             3818  <117>                 1  ''
         3820_3822  POP_JUMP_IF_FALSE  3830  'to 3830'

 L.1059      3824  BUILD_LIST_0          0 
             3826  LOAD_NAME                __spec__
             3828  STORE_ATTR               submodule_search_locations
           3830_0  COME_FROM          3820  '3820'

 L.1063      3830  LOAD_NAME                sys
             3832  LOAD_ATTR                meta_path
         3834_3836  POP_JUMP_IF_FALSE  3906  'to 3906'

 L.1064      3838  LOAD_NAME                enumerate
             3840  LOAD_NAME                sys
             3842  LOAD_ATTR                meta_path
             3844  CALL_FUNCTION_1       1  ''
             3846  GET_ITER         
           3848_0  COME_FROM          3898  '3898'
           3848_1  COME_FROM          3880  '3880'
           3848_2  COME_FROM          3868  '3868'
             3848  FOR_ITER           3902  'to 3902'
             3850  UNPACK_SEQUENCE_2     2 
             3852  STORE_NAME               i
             3854  STORE_NAME               importer

 L.1070      3856  LOAD_NAME                type
             3858  LOAD_NAME                importer
             3860  CALL_FUNCTION_1       1  ''
             3862  LOAD_ATTR                __name__
             3864  LOAD_STR                 '_SixMetaPathImporter'
             3866  COMPARE_OP               ==

 L.1069  3868_3870  POP_JUMP_IF_FALSE_BACK  3848  'to 3848'

 L.1071      3872  LOAD_NAME                importer
             3874  LOAD_ATTR                name
             3876  LOAD_NAME                __name__
             3878  COMPARE_OP               ==

 L.1069  3880_3882  POP_JUMP_IF_FALSE_BACK  3848  'to 3848'

 L.1073      3884  LOAD_NAME                sys
             3886  LOAD_ATTR                meta_path
             3888  LOAD_NAME                i
             3890  DELETE_SUBSCR    

 L.1074      3892  POP_TOP          
         3894_3896  BREAK_LOOP         3902  'to 3902'
         3898_3900  JUMP_BACK          3848  'to 3848'
           3902_0  COME_FROM          3894  '3894'
           3902_1  COME_FROM          3848  '3848'

 L.1075      3902  DELETE_NAME              i
             3904  DELETE_NAME              importer
           3906_0  COME_FROM          3834  '3834'

 L.1077      3906  LOAD_NAME                sys
             3908  LOAD_ATTR                meta_path
             3910  LOAD_METHOD              append
             3912  LOAD_NAME                _importer
             3914  CALL_METHOD_1         1  ''
             3916  POP_TOP          

Parse error at or near `<121>' instruction at offset 238_240

Instruction context:
   
 L.  66       234  DUP_TOP          
                 236  LOAD_NAME                OverflowError
->           238_240  <121>               260  ''
                 242  POP_TOP          
                 244  POP_TOP          
                 246  POP_TOP          

test/162830.pyc -- 
# decompile failed
