
# file test/163470.pyc
# --- This code section failed: ---

 L.   1         0  LOAD_CONST               0
                2  LOAD_CONST               None
                4  IMPORT_NAME              io
                6  STORE_NAME               io

 L.   2         8  LOAD_CONST               0
               10  LOAD_CONST               None
               12  IMPORT_NAME              os
               14  STORE_NAME               os

 L.   3        16  LOAD_CONST               0
               18  LOAD_CONST               None
               20  IMPORT_NAME              re
               22  STORE_NAME               re

 L.   4        24  LOAD_CONST               0
               26  LOAD_CONST               None
               28  IMPORT_NAME              abc
               30  STORE_NAME               abc

 L.   5        32  LOAD_CONST               0
               34  LOAD_CONST               None
               36  IMPORT_NAME              csv
               38  STORE_NAME               csv

 L.   6        40  LOAD_CONST               0
               42  LOAD_CONST               None
               44  IMPORT_NAME              sys
               46  STORE_NAME               sys

 L.   7        48  LOAD_CONST               0
               50  LOAD_CONST               None
               52  IMPORT_NAME              email
               54  STORE_NAME               email

 L.   8        56  LOAD_CONST               0
               58  LOAD_CONST               None
               60  IMPORT_NAME              pathlib
               62  STORE_NAME               pathlib

 L.   9        64  LOAD_CONST               0
               66  LOAD_CONST               None
               68  IMPORT_NAME              zipfile
               70  STORE_NAME               zipfile

 L.  10        72  LOAD_CONST               0
               74  LOAD_CONST               None
               76  IMPORT_NAME              operator
               78  STORE_NAME               operator

 L.  11        80  LOAD_CONST               0
               82  LOAD_CONST               None
               84  IMPORT_NAME              functools
               86  STORE_NAME               functools

 L.  12        88  LOAD_CONST               0
               90  LOAD_CONST               None
               92  IMPORT_NAME              itertools
               94  STORE_NAME               itertools

 L.  13        96  LOAD_CONST               0
               98  LOAD_CONST               None
              100  IMPORT_NAME              posixpath
              102  STORE_NAME               posixpath

 L.  14       104  LOAD_CONST               0
              106  LOAD_CONST               None
              108  IMPORT_NAME              collections
              110  STORE_NAME               collections

 L.  16       112  LOAD_CONST               0
              114  LOAD_CONST               ('ConfigParser',)
              116  IMPORT_NAME              configparser
              118  IMPORT_FROM              ConfigParser
              120  STORE_NAME               ConfigParser
              122  POP_TOP          

 L.  17       124  LOAD_CONST               0
              126  LOAD_CONST               ('suppress',)
              128  IMPORT_NAME              contextlib
              130  IMPORT_FROM              suppress
              132  STORE_NAME               suppress
              134  POP_TOP          

 L.  18       136  LOAD_CONST               0
              138  LOAD_CONST               ('import_module',)
              140  IMPORT_NAME              importlib
              142  IMPORT_FROM              import_module
              144  STORE_NAME               import_module
              146  POP_TOP          

 L.  19       148  LOAD_CONST               0
              150  LOAD_CONST               ('MetaPathFinder',)
              152  IMPORT_NAME_ATTR         importlib.abc
              154  IMPORT_FROM              MetaPathFinder
              156  STORE_NAME               MetaPathFinder
              158  POP_TOP          

 L.  20       160  LOAD_CONST               0
              162  LOAD_CONST               ('starmap',)
              164  IMPORT_NAME              itertools
              166  IMPORT_FROM              starmap
              168  STORE_NAME               starmap
              170  POP_TOP          

 L.  23       172  BUILD_LIST_0          0 
              174  LOAD_CONST               ('Distribution', 'DistributionFinder', 'PackageNotFoundError', 'distribution', 'distributions', 'entry_points', 'files', 'metadata', 'requires', 'version')
              176  CALL_FINALLY        179  'to 179'
              178  STORE_NAME               __all__

 L.  37       180  LOAD_BUILD_CLASS 
              182  LOAD_CODE                <code_object PackageNotFoundError>
              184  LOAD_STR                 'PackageNotFoundError'
              186  MAKE_FUNCTION_0          'Neither defaults, keyword-only args, annotations, nor closures'
              188  LOAD_STR                 'PackageNotFoundError'
              190  LOAD_NAME                ModuleNotFoundError
              192  CALL_FUNCTION_3       3  ''
              194  STORE_NAME               PackageNotFoundError

 L.  41       196  LOAD_BUILD_CLASS 
              198  LOAD_CODE                <code_object EntryPoint>
              200  LOAD_STR                 'EntryPoint'
              202  MAKE_FUNCTION_0          'Neither defaults, keyword-only args, annotations, nor closures'
              204  LOAD_STR                 'EntryPoint'

 L.  42       206  LOAD_NAME                collections
              208  LOAD_METHOD              namedtuple
              210  LOAD_STR                 'EntryPointBase'
              212  LOAD_STR                 'name value group'
              214  CALL_METHOD_2         2  ''

 L.  41       216  CALL_FUNCTION_3       3  ''
              218  STORE_NAME               EntryPoint

 L. 129       220  LOAD_BUILD_CLASS 
              222  LOAD_CODE                <code_object PackagePath>
              224  LOAD_STR                 'PackagePath'
              226  MAKE_FUNCTION_0          'Neither defaults, keyword-only args, annotations, nor closures'
              228  LOAD_STR                 'PackagePath'
              230  LOAD_NAME                pathlib
              232  LOAD_ATTR                PurePosixPath
              234  CALL_FUNCTION_3       3  ''
              236  STORE_NAME               PackagePath

 L. 145       238  LOAD_BUILD_CLASS 
              240  LOAD_CODE                <code_object FileHash>
              242  LOAD_STR                 'FileHash'
              244  MAKE_FUNCTION_0          'Neither defaults, keyword-only args, annotations, nor closures'
              246  LOAD_STR                 'FileHash'
              248  CALL_FUNCTION_2       2  ''
              250  STORE_NAME               FileHash

 L. 153       252  LOAD_BUILD_CLASS 
              254  LOAD_CODE                <code_object Distribution>
              256  LOAD_STR                 'Distribution'
              258  MAKE_FUNCTION_0          'Neither defaults, keyword-only args, annotations, nor closures'
              260  LOAD_STR                 'Distribution'
              262  CALL_FUNCTION_2       2  ''
              264  STORE_NAME               Distribution

 L. 360       266  LOAD_BUILD_CLASS 
              268  LOAD_CODE                <code_object DistributionFinder>
              270  LOAD_STR                 'DistributionFinder'
              272  MAKE_FUNCTION_0          'Neither defaults, keyword-only args, annotations, nor closures'
              274  LOAD_STR                 'DistributionFinder'
              276  LOAD_NAME                MetaPathFinder
              278  CALL_FUNCTION_3       3  ''
              280  STORE_NAME               DistributionFinder

 L. 407       282  LOAD_BUILD_CLASS 
              284  LOAD_CODE                <code_object FastPath>
              286  LOAD_STR                 'FastPath'
              288  MAKE_FUNCTION_0          'Neither defaults, keyword-only args, annotations, nor closures'
              290  LOAD_STR                 'FastPath'
              292  CALL_FUNCTION_2       2  ''
              294  STORE_NAME               FastPath

 L. 455       296  LOAD_BUILD_CLASS 
              298  LOAD_CODE                <code_object Prepared>
              300  LOAD_STR                 'Prepared'
              302  MAKE_FUNCTION_0          'Neither defaults, keyword-only args, annotations, nor closures'
              304  LOAD_STR                 'Prepared'
              306  CALL_FUNCTION_2       2  ''
              308  STORE_NAME               Prepared

 L. 476       310  LOAD_BUILD_CLASS 
              312  LOAD_CODE                <code_object MetadataPathFinder>
              314  LOAD_STR                 'MetadataPathFinder'
              316  MAKE_FUNCTION_0          'Neither defaults, keyword-only args, annotations, nor closures'
              318  LOAD_STR                 'MetadataPathFinder'
              320  LOAD_NAME                DistributionFinder
              322  CALL_FUNCTION_3       3  ''
              324  STORE_NAME               MetadataPathFinder

 L. 499       326  LOAD_BUILD_CLASS 
              328  LOAD_CODE                <code_object PathDistribution>
              330  LOAD_STR                 'PathDistribution'
              332  MAKE_FUNCTION_0          'Neither defaults, keyword-only args, annotations, nor closures'
              334  LOAD_STR                 'PathDistribution'
              336  LOAD_NAME                Distribution
              338  CALL_FUNCTION_3       3  ''
              340  STORE_NAME               PathDistribution

 L. 518       342  LOAD_CODE                <code_object distribution>
              344  LOAD_STR                 'distribution'
              346  MAKE_FUNCTION_0          'Neither defaults, keyword-only args, annotations, nor closures'
              348  STORE_NAME               distribution

 L. 527       350  LOAD_CODE                <code_object distributions>
              352  LOAD_STR                 'distributions'
              354  MAKE_FUNCTION_0          'Neither defaults, keyword-only args, annotations, nor closures'
              356  STORE_NAME               distributions

 L. 535       358  LOAD_CODE                <code_object metadata>
              360  LOAD_STR                 'metadata'
              362  MAKE_FUNCTION_0          'Neither defaults, keyword-only args, annotations, nor closures'
              364  STORE_NAME               metadata

 L. 544       366  LOAD_CODE                <code_object version>
              368  LOAD_STR                 'version'
              370  MAKE_FUNCTION_0          'Neither defaults, keyword-only args, annotations, nor closures'
              372  STORE_NAME               version

 L. 554       374  LOAD_CODE                <code_object entry_points>
              376  LOAD_STR                 'entry_points'
              378  MAKE_FUNCTION_0          'Neither defaults, keyword-only args, annotations, nor closures'
              380  STORE_NAME               entry_points

 L. 570       382  LOAD_CODE                <code_object files>
              384  LOAD_STR                 'files'
              386  MAKE_FUNCTION_0          'Neither defaults, keyword-only args, annotations, nor closures'
              388  STORE_NAME               files

 L. 579       390  LOAD_CODE                <code_object requires>
              392  LOAD_STR                 'requires'
              394  MAKE_FUNCTION_0          'Neither defaults, keyword-only args, annotations, nor closures'
              396  STORE_NAME               requires

Parse error at or near `CALL_FINALLY' instruction at offset 176

Instruction context:
   
 L.  23       172  BUILD_LIST_0          0 
                 174  LOAD_CONST               ('Distribution', 'DistributionFinder', 'PackageNotFoundError', 'distribution', 'distributions', 'entry_points', 'files', 'metadata', 'requires', 'version')
->               176  CALL_FINALLY        179  'to 179'
                 178  STORE_NAME               __all__

test/163470.pyc -- 
# decompile failed
