
# file test/164806.pyc
# --- This code section failed: ---

 L.   1         0  LOAD_STR                 'PyPI and direct package downloading'
                2  STORE_NAME               __doc__

 L.   2         4  LOAD_CONST               0
                6  LOAD_CONST               None
                8  IMPORT_NAME              sys
               10  STORE_NAME               sys

 L.   3        12  LOAD_CONST               0
               14  LOAD_CONST               None
               16  IMPORT_NAME              os
               18  STORE_NAME               os

 L.   4        20  LOAD_CONST               0
               22  LOAD_CONST               None
               24  IMPORT_NAME              re
               26  STORE_NAME               re

 L.   5        28  LOAD_CONST               0
               30  LOAD_CONST               None
               32  IMPORT_NAME              shutil
               34  STORE_NAME               shutil

 L.   6        36  LOAD_CONST               0
               38  LOAD_CONST               None
               40  IMPORT_NAME              socket
               42  STORE_NAME               socket

 L.   7        44  LOAD_CONST               0
               46  LOAD_CONST               None
               48  IMPORT_NAME              base64
               50  STORE_NAME               base64

 L.   8        52  LOAD_CONST               0
               54  LOAD_CONST               None
               56  IMPORT_NAME              hashlib
               58  STORE_NAME               hashlib

 L.   9        60  LOAD_CONST               0
               62  LOAD_CONST               None
               64  IMPORT_NAME              itertools
               66  STORE_NAME               itertools

 L.  10        68  LOAD_CONST               0
               70  LOAD_CONST               None
               72  IMPORT_NAME              warnings
               74  STORE_NAME               warnings

 L.  11        76  LOAD_CONST               0
               78  LOAD_CONST               ('wraps',)
               80  IMPORT_NAME              functools
               82  IMPORT_FROM              wraps
               84  STORE_NAME               wraps
               86  POP_TOP          

 L.  13        88  LOAD_CONST               0
               90  LOAD_CONST               ('six',)
               92  IMPORT_NAME_ATTR         setuptools.extern
               94  IMPORT_FROM              six
               96  STORE_NAME               six
               98  POP_TOP          

 L.  14       100  LOAD_CONST               0
              102  LOAD_CONST               ('urllib', 'http_client', 'configparser', 'map')
              104  IMPORT_NAME_ATTR         setuptools.extern.six.moves
              106  IMPORT_FROM              urllib
              108  STORE_NAME               urllib
              110  IMPORT_FROM              http_client
              112  STORE_NAME               http_client
              114  IMPORT_FROM              configparser
              116  STORE_NAME               configparser
              118  IMPORT_FROM              map
              120  STORE_NAME               map
              122  POP_TOP          

 L.  16       124  LOAD_CONST               0
              126  LOAD_CONST               None
              128  IMPORT_NAME              setuptools
              130  STORE_NAME               setuptools

 L.  17       132  LOAD_CONST               0
              134  LOAD_CONST               ('CHECKOUT_DIST', 'Distribution', 'BINARY_DIST', 'normalize_path', 'SOURCE_DIST', 'Environment', 'find_distributions', 'safe_name', 'safe_version', 'to_filename', 'Requirement', 'DEVELOP_DIST', 'EGG_DIST')
              136  IMPORT_NAME              pkg_resources
              138  IMPORT_FROM              CHECKOUT_DIST
              140  STORE_NAME               CHECKOUT_DIST
              142  IMPORT_FROM              Distribution
              144  STORE_NAME               Distribution
              146  IMPORT_FROM              BINARY_DIST
              148  STORE_NAME               BINARY_DIST
              150  IMPORT_FROM              normalize_path
              152  STORE_NAME               normalize_path
              154  IMPORT_FROM              SOURCE_DIST
              156  STORE_NAME               SOURCE_DIST
              158  IMPORT_FROM              Environment
              160  STORE_NAME               Environment
              162  IMPORT_FROM              find_distributions
              164  STORE_NAME               find_distributions
              166  IMPORT_FROM              safe_name
              168  STORE_NAME               safe_name
              170  IMPORT_FROM              safe_version
              172  STORE_NAME               safe_version
              174  IMPORT_FROM              to_filename
              176  STORE_NAME               to_filename
              178  IMPORT_FROM              Requirement
              180  STORE_NAME               Requirement
              182  IMPORT_FROM              DEVELOP_DIST
              184  STORE_NAME               DEVELOP_DIST
              186  IMPORT_FROM              EGG_DIST
              188  STORE_NAME               EGG_DIST
              190  POP_TOP          

 L.  22       192  LOAD_CONST               0
              194  LOAD_CONST               ('ssl_support',)
              196  IMPORT_NAME              setuptools
              198  IMPORT_FROM              ssl_support
              200  STORE_NAME               ssl_support
              202  POP_TOP          

 L.  23       204  LOAD_CONST               0
              206  LOAD_CONST               ('log',)
              208  IMPORT_NAME              distutils
              210  IMPORT_FROM              log
              212  STORE_NAME               log
              214  POP_TOP          

 L.  24       216  LOAD_CONST               0
              218  LOAD_CONST               ('DistutilsError',)
              220  IMPORT_NAME_ATTR         distutils.errors
              222  IMPORT_FROM              DistutilsError
              224  STORE_NAME               DistutilsError
              226  POP_TOP          

 L.  25       228  LOAD_CONST               0
              230  LOAD_CONST               ('translate',)
              232  IMPORT_NAME              fnmatch
              234  IMPORT_FROM              translate
              236  STORE_NAME               translate
              238  POP_TOP          

 L.  26       240  LOAD_CONST               0
              242  LOAD_CONST               ('get_all_headers',)
              244  IMPORT_NAME_ATTR         setuptools.py27compat
              246  IMPORT_FROM              get_all_headers
              248  STORE_NAME               get_all_headers
              250  POP_TOP          

 L.  27       252  LOAD_CONST               0
              254  LOAD_CONST               ('unescape',)
              256  IMPORT_NAME_ATTR         setuptools.py33compat
              258  IMPORT_FROM              unescape
              260  STORE_NAME               unescape
              262  POP_TOP          

 L.  28       264  LOAD_CONST               0
              266  LOAD_CONST               ('Wheel',)
              268  IMPORT_NAME_ATTR         setuptools.wheel
              270  IMPORT_FROM              Wheel
              272  STORE_NAME               Wheel
              274  POP_TOP          

 L.  30       276  LOAD_NAME                type
              278  STORE_NAME               __metaclass__

 L.  32       280  LOAD_NAME                re
              282  LOAD_METHOD              compile
              284  LOAD_STR                 '^egg=([-A-Za-z0-9_.+!]+)$'
              286  CALL_METHOD_1         1  ''
              288  STORE_NAME               EGG_FRAGMENT

 L.  33       290  LOAD_NAME                re
              292  LOAD_METHOD              compile
              294  LOAD_STR                 'href\\s*=\\s*[\'"]?([^\'"> ]+)'
              296  LOAD_NAME                re
              298  LOAD_ATTR                I
              300  CALL_METHOD_2         2  ''
              302  STORE_NAME               HREF

 L.  34       304  LOAD_NAME                re
              306  LOAD_METHOD              compile

 L.  35       308  LOAD_STR                 '<a href="([^"#]+)">([^<]+)</a>\\n\\s+\\(<a (?:title="MD5 hash"\\n\\s+)href="[^?]+\\?:action=show_md5&amp;digest=([0-9a-f]{32})">md5</a>\\)'

 L.  34       310  CALL_METHOD_1         1  ''
              312  STORE_NAME               PYPI_MD5

 L.  38       314  LOAD_NAME                re
              316  LOAD_METHOD              compile
              318  LOAD_STR                 '([-+.a-z0-9]{2,}):'
              320  LOAD_NAME                re
              322  LOAD_ATTR                I
              324  CALL_METHOD_2         2  ''
              326  LOAD_ATTR                match
              328  STORE_NAME               URL_SCHEME

 L.  39       330  LOAD_STR                 '.tar.gz .tar.bz2 .tar .zip .tgz'
              332  LOAD_METHOD              split
              334  CALL_METHOD_0         0  ''
              336  STORE_NAME               EXTENSIONS

 L.  41       338  BUILD_LIST_0          0 
              340  LOAD_CONST               ('PackageIndex', 'distros_for_url', 'parse_bdist_wininst', 'interpret_distro_name')
              342  CALL_FINALLY        345  'to 345'
              344  STORE_NAME               __all__

 L.  46       346  LOAD_CONST               15
              348  STORE_NAME               _SOCKET_TIMEOUT

 L.  48       350  LOAD_STR                 'setuptools/{setuptools.__version__} Python-urllib/{py_major}'
              352  STORE_NAME               _tmpl

 L.  49       354  LOAD_NAME                _tmpl
              356  LOAD_ATTR                format

 L.  50       358  LOAD_STR                 '{}.{}'
              360  LOAD_ATTR                format
              362  LOAD_NAME                sys
              364  LOAD_ATTR                version_info
              366  CALL_FUNCTION_EX      0  'positional arguments only'
              368  LOAD_NAME                setuptools

 L.  49       370  LOAD_CONST               ('py_major', 'setuptools')
              372  CALL_FUNCTION_KW_2     2  '2 total positional and keyword args'
              374  STORE_NAME               user_agent

 L.  53       376  LOAD_CODE                <code_object parse_requirement_arg>
              378  LOAD_STR                 'parse_requirement_arg'
              380  MAKE_FUNCTION_0          'Neither defaults, keyword-only args, annotations, nor closures'
              382  STORE_NAME               parse_requirement_arg

 L.  62       384  LOAD_CODE                <code_object parse_bdist_wininst>
              386  LOAD_STR                 'parse_bdist_wininst'
              388  MAKE_FUNCTION_0          'Neither defaults, keyword-only args, annotations, nor closures'
              390  STORE_NAME               parse_bdist_wininst

 L.  86       392  LOAD_CODE                <code_object egg_info_for_url>
              394  LOAD_STR                 'egg_info_for_url'
              396  MAKE_FUNCTION_0          'Neither defaults, keyword-only args, annotations, nor closures'
              398  STORE_NAME               egg_info_for_url

 L.  97       400  LOAD_CONST               (None,)
              402  LOAD_CODE                <code_object distros_for_url>
              404  LOAD_STR                 'distros_for_url'
              406  MAKE_FUNCTION_1          'default'
              408  STORE_NAME               distros_for_url

 L. 111       410  LOAD_CONST               (None,)
              412  LOAD_CODE                <code_object distros_for_location>
              414  LOAD_STR                 'distros_for_location'
              416  MAKE_FUNCTION_1          'default'
              418  STORE_NAME               distros_for_location

 L. 144       420  LOAD_CONST               (None,)
              422  LOAD_CODE                <code_object distros_for_filename>
              424  LOAD_STR                 'distros_for_filename'
              426  MAKE_FUNCTION_1          'default'
              428  STORE_NAME               distros_for_filename

 L. 152       430  LOAD_CONST               None
              432  LOAD_NAME                SOURCE_DIST

 L. 153       434  LOAD_CONST               None

 L. 151       436  BUILD_TUPLE_3         3 
              438  LOAD_CODE                <code_object interpret_distro_name>
              440  LOAD_STR                 'interpret_distro_name'
              442  MAKE_FUNCTION_1          'default'
              444  STORE_NAME               interpret_distro_name

 L. 187       446  LOAD_CONST               (None,)
              448  LOAD_CODE                <code_object unique_everseen>
              450  LOAD_STR                 'unique_everseen'
              452  MAKE_FUNCTION_1          'default'
              454  STORE_NAME               unique_everseen

 L. 205       456  LOAD_CODE                <code_object unique_values>
              458  LOAD_STR                 'unique_values'
              460  MAKE_FUNCTION_0          'Neither defaults, keyword-only args, annotations, nor closures'
              462  STORE_NAME               unique_values

 L. 218       464  LOAD_NAME                re
              466  LOAD_METHOD              compile
              468  LOAD_STR                 '<([^>]*\\srel\\s*=\\s*[\'"]?([^\'">]+)[^>]*)>'
              470  LOAD_NAME                re
              472  LOAD_ATTR                I
              474  CALL_METHOD_2         2  ''
              476  STORE_NAME               REL

 L. 222       478  LOAD_NAME                unique_values

 L. 223       480  LOAD_CODE                <code_object find_external_links>
              482  LOAD_STR                 'find_external_links'
              484  MAKE_FUNCTION_0          'Neither defaults, keyword-only args, annotations, nor closures'
              486  CALL_FUNCTION_1       1  ''
              488  STORE_NAME               find_external_links

 L. 241       490  LOAD_BUILD_CLASS 
              492  LOAD_CODE                <code_object ContentChecker>
              494  LOAD_STR                 'ContentChecker'
              496  MAKE_FUNCTION_0          'Neither defaults, keyword-only args, annotations, nor closures'
              498  LOAD_STR                 'ContentChecker'
              500  CALL_FUNCTION_2       2  ''
              502  STORE_NAME               ContentChecker

 L. 266       504  LOAD_BUILD_CLASS 
              506  LOAD_CODE                <code_object HashChecker>
              508  LOAD_STR                 'HashChecker'
              510  MAKE_FUNCTION_0          'Neither defaults, keyword-only args, annotations, nor closures'
              512  LOAD_STR                 'HashChecker'
              514  LOAD_NAME                ContentChecker
              516  CALL_FUNCTION_3       3  ''
              518  STORE_NAME               HashChecker

 L. 299       520  LOAD_BUILD_CLASS 
              522  LOAD_CODE                <code_object PackageIndex>
              524  LOAD_STR                 'PackageIndex'
              526  MAKE_FUNCTION_0          'Neither defaults, keyword-only args, annotations, nor closures'
              528  LOAD_STR                 'PackageIndex'
              530  LOAD_NAME                Environment
              532  CALL_FUNCTION_3       3  ''
              534  STORE_NAME               PackageIndex

 L. 938       536  LOAD_NAME                re
              538  LOAD_METHOD              compile
              540  LOAD_STR                 '&(#(\\d+|x[\\da-fA-F]+)|[\\w.:-]+);?'
              542  CALL_METHOD_1         1  ''
              544  LOAD_ATTR                sub
              546  STORE_NAME               entity_sub

 L. 941       548  LOAD_CODE                <code_object decode_entity>
              550  LOAD_STR                 'decode_entity'
              552  MAKE_FUNCTION_0          'Neither defaults, keyword-only args, annotations, nor closures'
              554  STORE_NAME               decode_entity

 L. 946       556  LOAD_CODE                <code_object htmldecode>
              558  LOAD_STR                 'htmldecode'
              560  MAKE_FUNCTION_0          'Neither defaults, keyword-only args, annotations, nor closures'
              562  STORE_NAME               htmldecode

 L. 958       564  LOAD_CONST               (15,)
              566  LOAD_CODE                <code_object socket_timeout>
              568  LOAD_STR                 'socket_timeout'
              570  MAKE_FUNCTION_1          'default'
              572  STORE_NAME               socket_timeout

 L. 973       574  LOAD_CODE                <code_object _encode_auth>
              576  LOAD_STR                 '_encode_auth'
              578  MAKE_FUNCTION_0          'Neither defaults, keyword-only args, annotations, nor closures'
              580  STORE_NAME               _encode_auth

 L. 995       582  LOAD_BUILD_CLASS 
              584  LOAD_CODE                <code_object Credential>
              586  LOAD_STR                 'Credential'
              588  MAKE_FUNCTION_0          'Neither defaults, keyword-only args, annotations, nor closures'
              590  LOAD_STR                 'Credential'
              592  CALL_FUNCTION_2       2  ''
              594  STORE_NAME               Credential

 L.1012       596  LOAD_BUILD_CLASS 
              598  LOAD_CODE                <code_object PyPIConfig>
              600  LOAD_STR                 'PyPIConfig'
              602  MAKE_FUNCTION_0          'Neither defaults, keyword-only args, annotations, nor closures'
              604  LOAD_STR                 'PyPIConfig'
              606  LOAD_NAME                configparser
              608  LOAD_ATTR                RawConfigParser
              610  CALL_FUNCTION_3       3  ''
              612  STORE_NAME               PyPIConfig

 L.1050       614  LOAD_NAME                urllib
              616  LOAD_ATTR                request
              618  LOAD_ATTR                urlopen
              620  BUILD_TUPLE_1         1 
              622  LOAD_CODE                <code_object open_with_auth>
              624  LOAD_STR                 'open_with_auth'
              626  MAKE_FUNCTION_1          'default'
              628  STORE_NAME               open_with_auth

 L.1097       630  LOAD_CODE                <code_object _splituser>
              632  LOAD_STR                 '_splituser'
              634  MAKE_FUNCTION_0          'Neither defaults, keyword-only args, annotations, nor closures'
              636  STORE_NAME               _splituser

 L.1105       638  LOAD_NAME                socket_timeout
              640  LOAD_NAME                _SOCKET_TIMEOUT
              642  CALL_FUNCTION_1       1  ''
              644  LOAD_NAME                open_with_auth
              646  CALL_FUNCTION_1       1  ''
              648  STORE_NAME               open_with_auth

 L.1108       650  LOAD_CODE                <code_object fix_sf_url>
              652  LOAD_STR                 'fix_sf_url'
              654  MAKE_FUNCTION_0          'Neither defaults, keyword-only args, annotations, nor closures'
              656  STORE_NAME               fix_sf_url

 L.1112       658  LOAD_CODE                <code_object local_open>
              660  LOAD_STR                 'local_open'
              662  MAKE_FUNCTION_0          'Neither defaults, keyword-only args, annotations, nor closures'
              664  STORE_NAME               local_open

Parse error at or near `CALL_FINALLY' instruction at offset 342

Instruction context:
   
 L.  41       338  BUILD_LIST_0          0 
                 340  LOAD_CONST               ('PackageIndex', 'distros_for_url', 'parse_bdist_wininst', 'interpret_distro_name')
->               342  CALL_FINALLY        345  'to 345'
                 344  STORE_NAME               __all__

test/164806.pyc -- 
# decompile failed
