
test/177199.pyc -- 
# decompile failed

# file test/177199.pyc
# --- This code section failed: ---

 L.   1         0  BUILD_LIST_0          0 
                2  LOAD_CONST               ('FFI', 'VerificationError', 'VerificationMissing', 'CDefError', 'FFIError')
                4  CALL_FINALLY          7  'to 7'
                6  STORE_NAME               __all__

 L.   4         8  LOAD_CONST               1
               10  LOAD_CONST               ('FFI',)
               12  IMPORT_NAME              api
               14  IMPORT_FROM              FFI
               16  STORE_NAME               FFI
               18  POP_TOP          

 L.   5        20  LOAD_CONST               1
               22  LOAD_CONST               ('CDefError', 'FFIError', 'VerificationError', 'VerificationMissing')
               24  IMPORT_NAME              error
               26  IMPORT_FROM              CDefError
               28  STORE_NAME               CDefError
               30  IMPORT_FROM              FFIError
               32  STORE_NAME               FFIError
               34  IMPORT_FROM              VerificationError
               36  STORE_NAME               VerificationError
               38  IMPORT_FROM              VerificationMissing
               40  STORE_NAME               VerificationMissing
               42  POP_TOP          

 L.   6        44  LOAD_CONST               1
               46  LOAD_CONST               ('PkgConfigError',)
               48  IMPORT_NAME              error
               50  IMPORT_FROM              PkgConfigError
               52  STORE_NAME               PkgConfigError
               54  POP_TOP          

 L.   8        56  LOAD_STR                 '1.14.4'
               58  STORE_NAME               __version__

 L.   9        60  LOAD_CONST               (1, 14, 4)
               62  STORE_NAME               __version_info__

 L.  14        64  LOAD_STR                 '0.8.6'
               66  STORE_NAME               __version_verifier_modules__

Parse error at or near `None' instruction at offset -1

