Instruction context:
-> 
 L. 116        70  DUP_TOP          
                  72  LOAD_GLOBAL              IOError
                  74  <121>                90  ''
                  76  POP_TOP          
                  78  POP_TOP          
                  80  POP_TOP          
Instruction context:
   
 L. 155         4  LOAD_FAST                'fullname'
                   6  LOAD_FAST                'self'
                   8  LOAD_ATTR                toc
->                10  <118>                 0  ''
                  12  POP_JUMP_IF_FALSE    30  'to 30'
Instruction context:
   
 L. 201         4  LOAD_FAST                'entry_name'
                   6  LOAD_CONST               None
->                 8  <117>                 0  ''
                  10  POP_JUMP_IF_FALSE    16  'to 16'
Instruction context:
   
 L. 318        20  DUP_TOP          
                  22  LOAD_GLOBAL              Exception
->                24  <121>                68  ''
                  26  POP_TOP          
                  28  STORE_FAST               'e'
                  30  POP_TOP          
                  32  SETUP_FINALLY        60  'to 60'
Instruction context:
   
 L. 402         4  LOAD_FAST                'fullname'
                   6  LOAD_FAST                'self'
                   8  LOAD_ATTR                toc
->                10  <118>                 0  ''
                  12  POP_JUMP_IF_FALSE    30  'to 30'
Instruction context:
   
 L. 514        18  LOAD_GLOBAL              hasattr
                  20  LOAD_FAST                'module'
                  22  LOAD_STR                 '__file__'
                  24  CALL_FUNCTION_2       2  ''
                  26  POP_JUMP_IF_TRUE     32  'to 32'
->                28  <74>             
                  30  RAISE_VARARGS_1       1  'exception instance'
                32_0  COME_FROM            26  '26'
Instruction context:
   
 L. 574       112  LOAD_FAST                'item'
                 114  LOAD_FAST                'pathFinders'
->               116  <118>                 1  ''
                 118  POP_JUMP_IF_FALSE_BACK    80  'to 80'

test/181246.pyc -- 
# decompile failed

# file test/181246.pyc
# Deparsing stopped due to parse error
