Instruction context:
   
 L. 161       308  LOAD_FAST                'ld'
                 310  LOAD_CONST               1
                 312  CALL_FUNCTION_1       1  ''
                 314  LOAD_FAST                'epsneg_f128'
                 316  BINARY_SUBTRACT  
                 318  LOAD_FAST                'tiny_f128'
                 320  BINARY_TRUE_DIVIDE
                 322  LOAD_FAST                'ld'
                 324  LOAD_CONST               4
                 326  CALL_FUNCTION_1       1  ''
                 328  BINARY_MULTIPLY  
                 330  STORE_FAST               'huge_f128'
                 332  POP_BLOCK        
                 334  LOAD_CONST               None
->               336  DUP_TOP          
                 338  DUP_TOP          
                 340  CALL_FUNCTION_3       3  ''
                 342  POP_TOP          
                 344  JUMP_FORWARD        364  'to 364'
               346_0  COME_FROM_WITH      304  '304'
                 346  <49>             
             348_350  POP_JUMP_IF_TRUE    354  'to 354'
                 352  <48>             
               354_0  COME_FROM           348  '348'
                 354  POP_TOP          
                 356  POP_TOP          
                 358  POP_TOP          
                 360  POP_EXCEPT       
                 362  POP_TOP          
               364_0  COME_FROM           344  '344'
Instruction context:
   
 L. 261        10  LOAD_FAST                'params'
                  12  LOAD_CONST               None
->                14  <117>                 0  ''
                  16  POP_JUMP_IF_FALSE    30  'to 30'
Instruction context:
   
 L. 369        16  DUP_TOP          
                  18  LOAD_GLOBAL              TypeError
->                20  <121>                46  ''
                  22  POP_TOP          
                  24  POP_TOP          
                  26  POP_TOP          
Instruction context:
   
 L. 501        18  DUP_TOP          
                  20  LOAD_GLOBAL              TypeError
->                22  <121>                50  ''
                  24  POP_TOP          
                  26  POP_TOP          
                  28  POP_TOP          
Instruction context:
   
 L. 517        32  DUP_TOP          
                  34  LOAD_GLOBAL              KeyError
->                36  <121>                80  ''
                  38  POP_TOP          
                  40  POP_TOP          
                  42  POP_TOP          
Instruction context:
   
 L. 527        18  DUP_TOP          
                  20  LOAD_GLOBAL              KeyError
->                22  <121>                98  ''
                  24  POP_TOP          
                  26  POP_TOP          
                  28  POP_TOP          

test/1973.pyc -- 
# decompile failed

# file test/1973.pyc
# Deparsing stopped due to parse error
