
# file test/2010.pyc
# --- This code section failed: ---

 L.   1         0  LOAD_CONST               0
                2  LOAD_CONST               None
                4  IMPORT_NAME              functools
                6  STORE_NAME               functools

 L.   3         8  LOAD_CONST               0
               10  LOAD_CONST               None
               12  IMPORT_NAME_ATTR         numpy.core.numeric
               14  IMPORT_FROM              core
               16  ROT_TWO          
               18  POP_TOP          
               20  IMPORT_FROM              numeric
               22  STORE_NAME               _nx
               24  POP_TOP          

 L.   4        26  LOAD_CONST               0
               28  LOAD_CONST               ('asarray', 'zeros', 'outer', 'concatenate', 'array', 'asanyarray')
               30  IMPORT_NAME_ATTR         numpy.core.numeric
               32  IMPORT_FROM              asarray
               34  STORE_NAME               asarray
               36  IMPORT_FROM              zeros
               38  STORE_NAME               zeros
               40  IMPORT_FROM              outer
               42  STORE_NAME               outer
               44  IMPORT_FROM              concatenate
               46  STORE_NAME               concatenate
               48  IMPORT_FROM              array
               50  STORE_NAME               array
               52  IMPORT_FROM              asanyarray
               54  STORE_NAME               asanyarray
               56  POP_TOP          

 L.   7        58  LOAD_CONST               0
               60  LOAD_CONST               ('reshape', 'transpose')
               62  IMPORT_NAME_ATTR         numpy.core.fromnumeric
               64  IMPORT_FROM              reshape
               66  STORE_NAME               reshape
               68  IMPORT_FROM              transpose
               70  STORE_NAME               transpose
               72  POP_TOP          

 L.   8        74  LOAD_CONST               0
               76  LOAD_CONST               ('normalize_axis_index',)
               78  IMPORT_NAME_ATTR         numpy.core.multiarray
               80  IMPORT_FROM              normalize_axis_index
               82  STORE_NAME               normalize_axis_index
               84  POP_TOP          

 L.   9        86  LOAD_CONST               0
               88  LOAD_CONST               ('overrides',)
               90  IMPORT_NAME_ATTR         numpy.core
               92  IMPORT_FROM              overrides
               94  STORE_NAME               overrides
               96  POP_TOP          

 L.  10        98  LOAD_CONST               0
              100  LOAD_CONST               ('vstack', 'atleast_3d')
              102  IMPORT_NAME_ATTR         numpy.core
              104  IMPORT_FROM              vstack
              106  STORE_NAME               vstack
              108  IMPORT_FROM              atleast_3d
              110  STORE_NAME               atleast_3d
              112  POP_TOP          

 L.  11       114  LOAD_CONST               0
              116  LOAD_CONST               ('normalize_axis_tuple',)
              118  IMPORT_NAME_ATTR         numpy.core.numeric
              120  IMPORT_FROM              normalize_axis_tuple
              122  STORE_NAME               normalize_axis_tuple
              124  POP_TOP          

 L.  12       126  LOAD_CONST               0
              128  LOAD_CONST               ('_arrays_for_stack_dispatcher',)
              130  IMPORT_NAME_ATTR         numpy.core.shape_base
              132  IMPORT_FROM              _arrays_for_stack_dispatcher
              134  STORE_NAME               _arrays_for_stack_dispatcher
              136  POP_TOP          

 L.  13       138  LOAD_CONST               0
              140  LOAD_CONST               ('ndindex',)
              142  IMPORT_NAME_ATTR         numpy.lib.index_tricks
              144  IMPORT_FROM              ndindex
              146  STORE_NAME               ndindex
              148  POP_TOP          

 L.  14       150  LOAD_CONST               0
              152  LOAD_CONST               ('matrix',)
              154  IMPORT_NAME_ATTR         numpy.matrixlib.defmatrix
              156  IMPORT_FROM              matrix
              158  STORE_NAME               matrix
              160  POP_TOP          

 L.  17       162  BUILD_LIST_0          0 
              164  LOAD_CONST               ('column_stack', 'row_stack', 'dstack', 'array_split', 'split', 'hsplit', 'vsplit', 'dsplit', 'apply_over_axes', 'expand_dims', 'apply_along_axis', 'kron', 'tile', 'get_array_wrap', 'take_along_axis', 'put_along_axis')
              166  CALL_FINALLY        169  'to 169'
              168  STORE_NAME               __all__

 L.  25       170  LOAD_NAME                functools
              172  LOAD_ATTR                partial

 L.  26       174  LOAD_NAME                overrides
              176  LOAD_ATTR                array_function_dispatch
              178  LOAD_STR                 'numpy'

 L.  25       180  LOAD_CONST               ('module',)
              182  CALL_FUNCTION_KW_2     2  '2 total positional and keyword args'
              184  STORE_NAME               array_function_dispatch

 L.  29       186  LOAD_CODE                <code_object _make_along_axis_idx>
              188  LOAD_STR                 '_make_along_axis_idx'
              190  MAKE_FUNCTION_0          'Neither defaults, keyword-only args, annotations, nor closures'
              192  STORE_NAME               _make_along_axis_idx

 L.  52       194  LOAD_CODE                <code_object _take_along_axis_dispatcher>
              196  LOAD_STR                 '_take_along_axis_dispatcher'
              198  MAKE_FUNCTION_0          'Neither defaults, keyword-only args, annotations, nor closures'
              200  STORE_NAME               _take_along_axis_dispatcher

 L.  56       202  LOAD_NAME                array_function_dispatch
              204  LOAD_NAME                _take_along_axis_dispatcher
              206  CALL_FUNCTION_1       1  ''

 L.  57       208  LOAD_CODE                <code_object take_along_axis>
              210  LOAD_STR                 'take_along_axis'
              212  MAKE_FUNCTION_0          'Neither defaults, keyword-only args, annotations, nor closures'
              214  CALL_FUNCTION_1       1  ''
              216  STORE_NAME               take_along_axis

 L. 173       218  LOAD_CODE                <code_object _put_along_axis_dispatcher>
              220  LOAD_STR                 '_put_along_axis_dispatcher'
              222  MAKE_FUNCTION_0          'Neither defaults, keyword-only args, annotations, nor closures'
              224  STORE_NAME               _put_along_axis_dispatcher

 L. 177       226  LOAD_NAME                array_function_dispatch
              228  LOAD_NAME                _put_along_axis_dispatcher
              230  CALL_FUNCTION_1       1  ''

 L. 178       232  LOAD_CODE                <code_object put_along_axis>
              234  LOAD_STR                 'put_along_axis'
              236  MAKE_FUNCTION_0          'Neither defaults, keyword-only args, annotations, nor closures'
              238  CALL_FUNCTION_1       1  ''
              240  STORE_NAME               put_along_axis

 L. 263       242  LOAD_CODE                <code_object _apply_along_axis_dispatcher>
              244  LOAD_STR                 '_apply_along_axis_dispatcher'
              246  MAKE_FUNCTION_0          'Neither defaults, keyword-only args, annotations, nor closures'
              248  STORE_NAME               _apply_along_axis_dispatcher

 L. 267       250  LOAD_NAME                array_function_dispatch
              252  LOAD_NAME                _apply_along_axis_dispatcher
              254  CALL_FUNCTION_1       1  ''

 L. 268       256  LOAD_CODE                <code_object apply_along_axis>
              258  LOAD_STR                 'apply_along_axis'
              260  MAKE_FUNCTION_0          'Neither defaults, keyword-only args, annotations, nor closures'
              262  CALL_FUNCTION_1       1  ''
              264  STORE_NAME               apply_along_axis

 L. 417       266  LOAD_CODE                <code_object _apply_over_axes_dispatcher>
              268  LOAD_STR                 '_apply_over_axes_dispatcher'
              270  MAKE_FUNCTION_0          'Neither defaults, keyword-only args, annotations, nor closures'
              272  STORE_NAME               _apply_over_axes_dispatcher

 L. 421       274  LOAD_NAME                array_function_dispatch
              276  LOAD_NAME                _apply_over_axes_dispatcher
              278  CALL_FUNCTION_1       1  ''

 L. 422       280  LOAD_CODE                <code_object apply_over_axes>
              282  LOAD_STR                 'apply_over_axes'
              284  MAKE_FUNCTION_0          'Neither defaults, keyword-only args, annotations, nor closures'
              286  CALL_FUNCTION_1       1  ''
              288  STORE_NAME               apply_over_axes

 L. 508       290  LOAD_CODE                <code_object _expand_dims_dispatcher>
              292  LOAD_STR                 '_expand_dims_dispatcher'
              294  MAKE_FUNCTION_0          'Neither defaults, keyword-only args, annotations, nor closures'
              296  STORE_NAME               _expand_dims_dispatcher

 L. 512       298  LOAD_NAME                array_function_dispatch
              300  LOAD_NAME                _expand_dims_dispatcher
              302  CALL_FUNCTION_1       1  ''

 L. 513       304  LOAD_CODE                <code_object expand_dims>
              306  LOAD_STR                 'expand_dims'
              308  MAKE_FUNCTION_0          'Neither defaults, keyword-only args, annotations, nor closures'
              310  CALL_FUNCTION_1       1  ''
              312  STORE_NAME               expand_dims

 L. 605       314  LOAD_NAME                vstack
              316  STORE_NAME               row_stack

 L. 608       318  LOAD_CODE                <code_object _column_stack_dispatcher>
              320  LOAD_STR                 '_column_stack_dispatcher'
              322  MAKE_FUNCTION_0          'Neither defaults, keyword-only args, annotations, nor closures'
              324  STORE_NAME               _column_stack_dispatcher

 L. 612       326  LOAD_NAME                array_function_dispatch
              328  LOAD_NAME                _column_stack_dispatcher
              330  CALL_FUNCTION_1       1  ''

 L. 613       332  LOAD_CODE                <code_object column_stack>
              334  LOAD_STR                 'column_stack'
              336  MAKE_FUNCTION_0          'Neither defaults, keyword-only args, annotations, nor closures'
              338  CALL_FUNCTION_1       1  ''
              340  STORE_NAME               column_stack

 L. 659       342  LOAD_CODE                <code_object _dstack_dispatcher>
              344  LOAD_STR                 '_dstack_dispatcher'
              346  MAKE_FUNCTION_0          'Neither defaults, keyword-only args, annotations, nor closures'
              348  STORE_NAME               _dstack_dispatcher

 L. 663       350  LOAD_NAME                array_function_dispatch
              352  LOAD_NAME                _dstack_dispatcher
              354  CALL_FUNCTION_1       1  ''

 L. 664       356  LOAD_CODE                <code_object dstack>
              358  LOAD_STR                 'dstack'
              360  MAKE_FUNCTION_0          'Neither defaults, keyword-only args, annotations, nor closures'
              362  CALL_FUNCTION_1       1  ''
              364  STORE_NAME               dstack

 L. 726       366  LOAD_CODE                <code_object _replace_zero_by_x_arrays>
              368  LOAD_STR                 '_replace_zero_by_x_arrays'
              370  MAKE_FUNCTION_0          'Neither defaults, keyword-only args, annotations, nor closures'
              372  STORE_NAME               _replace_zero_by_x_arrays

 L. 735       374  LOAD_CONST               (None,)
              376  LOAD_CODE                <code_object _array_split_dispatcher>
              378  LOAD_STR                 '_array_split_dispatcher'
              380  MAKE_FUNCTION_1          'default'
              382  STORE_NAME               _array_split_dispatcher

 L. 739       384  LOAD_NAME                array_function_dispatch
              386  LOAD_NAME                _array_split_dispatcher
              388  CALL_FUNCTION_1       1  ''

 L. 740       390  LOAD_CONST               (0,)
              392  LOAD_CODE                <code_object array_split>
              394  LOAD_STR                 'array_split'
              396  MAKE_FUNCTION_1          'default'
              398  CALL_FUNCTION_1       1  ''
              400  STORE_NAME               array_split

 L. 795       402  LOAD_CONST               (None,)
              404  LOAD_CODE                <code_object _split_dispatcher>
              406  LOAD_STR                 '_split_dispatcher'
              408  MAKE_FUNCTION_1          'default'
              410  STORE_NAME               _split_dispatcher

 L. 799       412  LOAD_NAME                array_function_dispatch
              414  LOAD_NAME                _split_dispatcher
              416  CALL_FUNCTION_1       1  ''

 L. 800       418  LOAD_CONST               (0,)
              420  LOAD_CODE                <code_object split>
              422  LOAD_STR                 'split'
              424  MAKE_FUNCTION_1          'default'
              426  CALL_FUNCTION_1       1  ''
              428  STORE_NAME               split

 L. 877       430  LOAD_CODE                <code_object _hvdsplit_dispatcher>
              432  LOAD_STR                 '_hvdsplit_dispatcher'
              434  MAKE_FUNCTION_0          'Neither defaults, keyword-only args, annotations, nor closures'
              436  STORE_NAME               _hvdsplit_dispatcher

 L. 881       438  LOAD_NAME                array_function_dispatch
              440  LOAD_NAME                _hvdsplit_dispatcher
              442  CALL_FUNCTION_1       1  ''

 L. 882       444  LOAD_CODE                <code_object hsplit>
              446  LOAD_STR                 'hsplit'
              448  MAKE_FUNCTION_0          'Neither defaults, keyword-only args, annotations, nor closures'
              450  CALL_FUNCTION_1       1  ''
              452  STORE_NAME               hsplit

 L. 945       454  LOAD_NAME                array_function_dispatch
              456  LOAD_NAME                _hvdsplit_dispatcher
              458  CALL_FUNCTION_1       1  ''

 L. 946       460  LOAD_CODE                <code_object vsplit>
              462  LOAD_STR                 'vsplit'
              464  MAKE_FUNCTION_0          'Neither defaults, keyword-only args, annotations, nor closures'
              466  CALL_FUNCTION_1       1  ''
              468  STORE_NAME               vsplit

 L. 994       470  LOAD_NAME                array_function_dispatch
              472  LOAD_NAME                _hvdsplit_dispatcher
              474  CALL_FUNCTION_1       1  ''

 L. 995       476  LOAD_CODE                <code_object dsplit>
              478  LOAD_STR                 'dsplit'
              480  MAKE_FUNCTION_0          'Neither defaults, keyword-only args, annotations, nor closures'
              482  CALL_FUNCTION_1       1  ''
              484  STORE_NAME               dsplit

 L.1038       486  LOAD_CODE                <code_object get_array_prepare>
              488  LOAD_STR                 'get_array_prepare'
              490  MAKE_FUNCTION_0          'Neither defaults, keyword-only args, annotations, nor closures'
              492  STORE_NAME               get_array_prepare

 L.1050       494  LOAD_CODE                <code_object get_array_wrap>
              496  LOAD_STR                 'get_array_wrap'
              498  MAKE_FUNCTION_0          'Neither defaults, keyword-only args, annotations, nor closures'
              500  STORE_NAME               get_array_wrap

 L.1063       502  LOAD_CODE                <code_object _kron_dispatcher>
              504  LOAD_STR                 '_kron_dispatcher'
              506  MAKE_FUNCTION_0          'Neither defaults, keyword-only args, annotations, nor closures'
              508  STORE_NAME               _kron_dispatcher

 L.1067       510  LOAD_NAME                array_function_dispatch
              512  LOAD_NAME                _kron_dispatcher
              514  CALL_FUNCTION_1       1  ''

 L.1068       516  LOAD_CODE                <code_object kron>
              518  LOAD_STR                 'kron'
              520  MAKE_FUNCTION_0          'Neither defaults, keyword-only args, annotations, nor closures'
              522  CALL_FUNCTION_1       1  ''
              524  STORE_NAME               kron

 L.1167       526  LOAD_CODE                <code_object _tile_dispatcher>
              528  LOAD_STR                 '_tile_dispatcher'
              530  MAKE_FUNCTION_0          'Neither defaults, keyword-only args, annotations, nor closures'
              532  STORE_NAME               _tile_dispatcher

 L.1171       534  LOAD_NAME                array_function_dispatch
              536  LOAD_NAME                _tile_dispatcher
              538  CALL_FUNCTION_1       1  ''

 L.1172       540  LOAD_CODE                <code_object tile>
              542  LOAD_STR                 'tile'
              544  MAKE_FUNCTION_0          'Neither defaults, keyword-only args, annotations, nor closures'
              546  CALL_FUNCTION_1       1  ''
              548  STORE_NAME               tile

Parse error at or near `CALL_FINALLY' instruction at offset 166

Instruction context:
   
 L.  17       162  BUILD_LIST_0          0 
                 164  LOAD_CONST               ('column_stack', 'row_stack', 'dstack', 'array_split', 'split', 'hsplit', 'vsplit', 'dsplit', 'apply_over_axes', 'expand_dims', 'apply_along_axis', 'kron', 'tile', 'get_array_wrap', 'take_along_axis', 'put_along_axis')
->               166  CALL_FINALLY        169  'to 169'
                 168  STORE_NAME               __all__

test/2010.pyc -- 
# decompile failed
