
# file test/2015.pyc
# --- This code section failed: ---

 L.   1         0  LOAD_CONST               0
                2  LOAD_CONST               None
                4  IMPORT_NAME              os
                6  STORE_NAME               os

 L.   2         8  LOAD_CONST               0
               10  LOAD_CONST               None
               12  IMPORT_NAME              sys
               14  STORE_NAME               sys

 L.   3        16  LOAD_CONST               0
               18  LOAD_CONST               None
               20  IMPORT_NAME              textwrap
               22  STORE_NAME               textwrap

 L.   4        24  LOAD_CONST               0
               26  LOAD_CONST               None
               28  IMPORT_NAME              types
               30  STORE_NAME               types

 L.   5        32  LOAD_CONST               0
               34  LOAD_CONST               None
               36  IMPORT_NAME              re
               38  STORE_NAME               re

 L.   6        40  LOAD_CONST               0
               42  LOAD_CONST               None
               44  IMPORT_NAME              warnings
               46  STORE_NAME               warnings

 L.   8        48  LOAD_CONST               0
               50  LOAD_CONST               ('issubclass_', 'issubsctype', 'issubdtype')
               52  IMPORT_NAME_ATTR         numpy.core.numerictypes
               54  IMPORT_FROM              issubclass_
               56  STORE_NAME               issubclass_
               58  IMPORT_FROM              issubsctype
               60  STORE_NAME               issubsctype
               62  IMPORT_FROM              issubdtype
               64  STORE_NAME               issubdtype
               66  POP_TOP          

 L.   9        68  LOAD_CONST               0
               70  LOAD_CONST               ('set_module',)
               72  IMPORT_NAME_ATTR         numpy.core.overrides
               74  IMPORT_FROM              set_module
               76  STORE_NAME               set_module
               78  POP_TOP          

 L.  10        80  LOAD_CONST               0
               82  LOAD_CONST               ('ndarray', 'ufunc', 'asarray')
               84  IMPORT_NAME_ATTR         numpy.core
               86  IMPORT_FROM              ndarray
               88  STORE_NAME               ndarray
               90  IMPORT_FROM              ufunc
               92  STORE_NAME               ufunc
               94  IMPORT_FROM              asarray
               96  STORE_NAME               asarray
               98  POP_TOP          

 L.  11       100  LOAD_CONST               0
              102  LOAD_CONST               None
              104  IMPORT_NAME              numpy
              106  STORE_NAME               np

 L.  14       108  LOAD_CONST               0
              110  LOAD_CONST               ('getargspec', 'formatargspec')
              112  IMPORT_NAME_ATTR         numpy.compat
              114  IMPORT_FROM              getargspec
              116  STORE_NAME               getargspec
              118  IMPORT_FROM              formatargspec
              120  STORE_NAME               formatargspec
              122  POP_TOP          

 L.  16       124  BUILD_LIST_0          0 
              126  LOAD_CONST               ('issubclass_', 'issubsctype', 'issubdtype', 'deprecate', 'deprecate_with_doc', 'get_include', 'info', 'source', 'who', 'lookfor', 'byte_bounds', 'safe_eval')
              128  CALL_FINALLY        131  'to 131'
              130  STORE_NAME               __all__

 L.  22       132  LOAD_CODE                <code_object get_include>
              134  LOAD_STR                 'get_include'
              136  MAKE_FUNCTION_0          'Neither defaults, keyword-only args, annotations, nor closures'
              138  STORE_NAME               get_include

 L.  52       140  LOAD_CODE                <code_object _set_function_name>
              142  LOAD_STR                 '_set_function_name'
              144  MAKE_FUNCTION_0          'Neither defaults, keyword-only args, annotations, nor closures'
              146  STORE_NAME               _set_function_name

 L.  57       148  LOAD_BUILD_CLASS 
              150  LOAD_CODE                <code_object _Deprecate>
              152  LOAD_STR                 '_Deprecate'
              154  MAKE_FUNCTION_0          'Neither defaults, keyword-only args, annotations, nor closures'
              156  LOAD_STR                 '_Deprecate'
              158  CALL_FUNCTION_2       2  ''
              160  STORE_NAME               _Deprecate

 L. 133       162  LOAD_CODE                <code_object _get_indent>
              164  LOAD_STR                 '_get_indent'
              166  MAKE_FUNCTION_0          'Neither defaults, keyword-only args, annotations, nor closures'
              168  STORE_NAME               _get_indent

 L. 147       170  LOAD_CODE                <code_object deprecate>
              172  LOAD_STR                 'deprecate'
              174  MAKE_FUNCTION_0          'Neither defaults, keyword-only args, annotations, nor closures'
              176  STORE_NAME               deprecate

 L. 199       178  LOAD_LAMBDA              '<code_object <lambda>>'
              180  LOAD_STR                 '<lambda>'
              182  MAKE_FUNCTION_0          'Neither defaults, keyword-only args, annotations, nor closures'
              184  STORE_NAME               deprecate_with_doc

 L. 206       186  LOAD_CODE                <code_object byte_bounds>
              188  LOAD_STR                 'byte_bounds'
              190  MAKE_FUNCTION_0          'Neither defaults, keyword-only args, annotations, nor closures'
              192  STORE_NAME               byte_bounds

 L. 263       194  LOAD_CONST               (None,)
              196  LOAD_CODE                <code_object who>
              198  LOAD_STR                 'who'
              200  MAKE_FUNCTION_1          'default'
              202  STORE_NAME               who

 L. 368       204  LOAD_CODE                <code_object _split_line>
              206  LOAD_STR                 '_split_line'
              208  MAKE_FUNCTION_0          'Neither defaults, keyword-only args, annotations, nor closures'
              210  STORE_NAME               _split_line

 L. 387       212  LOAD_CONST               None
              214  STORE_GLOBAL             _namedict

 L. 388       216  LOAD_CONST               None
              218  STORE_GLOBAL             _dictlist

 L. 392       220  LOAD_CONST               ('numpy',)
              222  LOAD_CODE                <code_object _makenamedict>
              224  LOAD_STR                 '_makenamedict'
              226  MAKE_FUNCTION_1          'default'
              228  STORE_NAME               _makenamedict

 L. 412       230  LOAD_NAME                sys
              232  LOAD_ATTR                stdout
              234  BUILD_TUPLE_1         1 
              236  LOAD_CODE                <code_object _info>
              238  LOAD_STR                 '_info'
              240  MAKE_FUNCTION_1          'default'
              242  STORE_NAME               _info

 L. 463       244  LOAD_NAME                set_module
              246  LOAD_STR                 'numpy'
              248  CALL_FUNCTION_1       1  ''

 L. 464       250  LOAD_CONST               None
              252  LOAD_CONST               76
              254  LOAD_NAME                sys
              256  LOAD_ATTR                stdout
              258  LOAD_STR                 'numpy'
              260  BUILD_TUPLE_4         4 
              262  LOAD_CODE                <code_object info>
              264  LOAD_STR                 'info'
              266  MAKE_FUNCTION_1          'default'
              268  CALL_FUNCTION_1       1  ''
              270  STORE_NAME               info

 L. 634       272  LOAD_NAME                set_module
              274  LOAD_STR                 'numpy'
              276  CALL_FUNCTION_1       1  ''

 L. 635       278  LOAD_NAME                sys
              280  LOAD_ATTR                stdout
              282  BUILD_TUPLE_1         1 
              284  LOAD_CODE                <code_object source>
              286  LOAD_STR                 'source'
              288  MAKE_FUNCTION_1          'default'
              290  CALL_FUNCTION_1       1  ''
              292  STORE_NAME               source

 L. 686       294  BUILD_MAP_0           0 
              296  STORE_NAME               _lookfor_caches

 L. 690       298  LOAD_NAME                re
              300  LOAD_METHOD              compile
              302  LOAD_STR                 '[a-z0-9_]+\\(.*[,=].*\\)'
              304  LOAD_NAME                re
              306  LOAD_ATTR                I
              308  CALL_METHOD_2         2  ''
              310  STORE_NAME               _function_signature_re

 L. 693       312  LOAD_NAME                set_module
              314  LOAD_STR                 'numpy'
              316  CALL_FUNCTION_1       1  ''

 L. 694       318  LOAD_CONST               (None, True, False, None)
              320  LOAD_CODE                <code_object lookfor>
              322  LOAD_STR                 'lookfor'
              324  MAKE_FUNCTION_1          'default'
              326  CALL_FUNCTION_1       1  ''
              328  STORE_NAME               lookfor

 L. 817       330  LOAD_CODE                <code_object _lookfor_generate_cache>
              332  LOAD_STR                 '_lookfor_generate_cache'
              334  MAKE_FUNCTION_0          'Neither defaults, keyword-only args, annotations, nor closures'
              336  STORE_NAME               _lookfor_generate_cache

 L. 952       338  LOAD_CODE                <code_object _getmembers>
              340  LOAD_STR                 '_getmembers'
              342  MAKE_FUNCTION_0          'Neither defaults, keyword-only args, annotations, nor closures'
              344  STORE_NAME               _getmembers

 L. 962       346  LOAD_CODE                <code_object safe_eval>
              348  LOAD_STR                 'safe_eval'
              350  MAKE_FUNCTION_0          'Neither defaults, keyword-only args, annotations, nor closures'
              352  STORE_NAME               safe_eval

 L.1010       354  LOAD_CODE                <code_object _median_nancheck>
              356  LOAD_STR                 '_median_nancheck'
              358  MAKE_FUNCTION_0          'Neither defaults, keyword-only args, annotations, nor closures'
              360  STORE_NAME               _median_nancheck

Parse error at or near `CALL_FINALLY' instruction at offset 128

Instruction context:
   
 L.  16       124  BUILD_LIST_0          0 
                 126  LOAD_CONST               ('issubclass_', 'issubsctype', 'issubdtype', 'deprecate', 'deprecate_with_doc', 'get_include', 'info', 'source', 'who', 'lookfor', 'byte_bounds', 'safe_eval')
->               128  CALL_FINALLY        131  'to 131'
                 130  STORE_NAME               __all__

test/2015.pyc -- 
# decompile failed
