Instruction context:
   
 L. 112        22  LOAD_STR                 '#random'
                  24  LOAD_FAST                'want'
->                26  <118>                 0  ''
                  28  POP_JUMP_IF_FALSE    34  'to 34'
Instruction context:
   
 L. 222        34  LOAD_STR                 'scipy'
                  36  LOAD_FAST                'pkg_name'
->                38  <118>                 0  ''
                  40  POP_JUMP_IF_FALSE    84  'to 84'
Instruction context:
   
 L. 236        48  DUP_TOP          
                  50  LOAD_GLOBAL              AttributeError
->                52  <121>                66  ''
                  54  POP_TOP          
                  56  POP_TOP          
                  58  POP_TOP          
Instruction context:
   
 L. 264        12  LOAD_FAST                'bn'
                  14  LOAD_FAST                'self'
                  16  LOAD_ATTR                doctest_ignore
->                18  <118>                 0  ''
                  20  POP_JUMP_IF_FALSE    26  'to 26'
Instruction context:
   
 L. 338        52  DUP_TOP          
                  54  LOAD_GLOBAL              AssertionError
->                56  <121>                84  ''
                  58  POP_TOP          
                  60  POP_TOP          
                  62  POP_TOP          

test/2041.pyc -- 
# decompile failed

# file test/2041.pyc
# Deparsing stopped due to parse error
