Instruction context:
   
 L.   9        12  BUILD_LIST_0          0 
                  14  LOAD_CONST               ('tagClassUniversal', 'tagClassApplication', 'tagClassContext', 'tagClassPrivate', 'tagFormatSimple', 'tagFormatConstructed', 'tagCategoryImplicit', 'tagCategoryExplicit', 'tagCategoryUntagged', 'Tag', 'TagSet')
->                16  CALL_FINALLY         19  'to 19'
                  18  STORE_NAME               __all__

test/31729.pyc -- 
# decompile failed

# file test/31729.pyc
# --- This code section failed: ---

 L.   7         0  LOAD_CONST               0
                2  LOAD_CONST               ('error',)
                4  IMPORT_NAME              pyasn1
                6  IMPORT_FROM              error
                8  STORE_NAME               error
               10  POP_TOP          

 L.   9        12  BUILD_LIST_0          0 
               14  LOAD_CONST               ('tagClassUniversal', 'tagClassApplication', 'tagClassContext', 'tagClassPrivate', 'tagFormatSimple', 'tagFormatConstructed', 'tagCategoryImplicit', 'tagCategoryExplicit', 'tagCategoryUntagged', 'Tag', 'TagSet')
               16  CALL_FINALLY         19  'to 19'
               18  STORE_NAME               __all__

 L.  15        20  LOAD_CONST               0
               22  STORE_NAME               tagClassUniversal

 L.  18        24  LOAD_CONST               64
               26  STORE_NAME               tagClassApplication

 L.  21        28  LOAD_CONST               128
               30  STORE_NAME               tagClassContext

 L.  24        32  LOAD_CONST               192
               34  STORE_NAME               tagClassPrivate

 L.  27        36  LOAD_CONST               0
               38  STORE_NAME               tagFormatSimple

 L.  30        40  LOAD_CONST               32
               42  STORE_NAME               tagFormatConstructed

 L.  32        44  LOAD_CONST               1
               46  STORE_NAME               tagCategoryImplicit

 L.  33        48  LOAD_CONST               2
               50  STORE_NAME               tagCategoryExplicit

 L.  34        52  LOAD_CONST               4
               54  STORE_NAME               tagCategoryUntagged

 L.  37        56  LOAD_BUILD_CLASS 
               58  LOAD_CODE                <code_object Tag>
               60  LOAD_STR                 'Tag'
               62  MAKE_FUNCTION_0          'Neither defaults, keyword-only args, annotations, nor closures'
               64  LOAD_STR                 'Tag'
               66  LOAD_NAME                object
               68  CALL_FUNCTION_3       3  ''
               70  STORE_NAME               Tag

 L. 152        72  LOAD_BUILD_CLASS 
               74  LOAD_CODE                <code_object TagSet>
               76  LOAD_STR                 'TagSet'
               78  MAKE_FUNCTION_0          'Neither defaults, keyword-only args, annotations, nor closures'
               80  LOAD_STR                 'TagSet'
               82  LOAD_NAME                object
               84  CALL_FUNCTION_3       3  ''
               86  STORE_NAME               TagSet

 L. 334        88  LOAD_CODE                <code_object initTagSet>
               90  LOAD_STR                 'initTagSet'
               92  MAKE_FUNCTION_0          'Neither defaults, keyword-only args, annotations, nor closures'
               94  STORE_NAME               initTagSet

Parse error at or near `CALL_FINALLY' instruction at offset 16

