
# file test/31724.pyc
# --- This code section failed: ---

 L.   7         0  LOAD_CONST               0
                2  LOAD_CONST               None
                4  IMPORT_NAME              sys
                6  STORE_NAME               sys

 L.   9         8  LOAD_CONST               0
               10  LOAD_CONST               ('error',)
               12  IMPORT_NAME              pyasn1
               14  IMPORT_FROM              error
               16  STORE_NAME               error
               18  POP_TOP          

 L.  10        20  LOAD_CONST               0
               22  LOAD_CONST               ('tag',)
               24  IMPORT_NAME_ATTR         pyasn1.type
               26  IMPORT_FROM              tag
               28  STORE_NAME               tag
               30  POP_TOP          

 L.  11        32  LOAD_CONST               0
               34  LOAD_CONST               ('univ',)
               36  IMPORT_NAME_ATTR         pyasn1.type
               38  IMPORT_FROM              univ
               40  STORE_NAME               univ
               42  POP_TOP          

 L.  13        44  BUILD_LIST_0          0 
               46  LOAD_CONST               ('NumericString', 'PrintableString', 'TeletexString', 'T61String', 'VideotexString', 'IA5String', 'GraphicString', 'VisibleString', 'ISO646String', 'GeneralString', 'UniversalString', 'BMPString', 'UTF8String')
               48  CALL_FINALLY         51  'to 51'
               50  STORE_NAME               __all__

 L.  17        52  LOAD_NAME                univ
               54  LOAD_ATTR                NoValue
               56  STORE_NAME               NoValue

 L.  18        58  LOAD_NAME                univ
               60  LOAD_ATTR                noValue
               62  STORE_NAME               noValue

 L.  21        64  LOAD_BUILD_CLASS 
               66  LOAD_CODE                <code_object AbstractCharacterString>
               68  LOAD_STR                 'AbstractCharacterString'
               70  MAKE_FUNCTION_0          'Neither defaults, keyword-only args, annotations, nor closures'
               72  LOAD_STR                 'AbstractCharacterString'
               74  LOAD_NAME                univ
               76  LOAD_ATTR                OctetString
               78  CALL_FUNCTION_3       3  ''
               80  STORE_NAME               AbstractCharacterString

 L. 160        82  LOAD_BUILD_CLASS 
               84  LOAD_CODE                <code_object NumericString>
               86  LOAD_STR                 'NumericString'
               88  MAKE_FUNCTION_0          'Neither defaults, keyword-only args, annotations, nor closures'
               90  LOAD_STR                 'NumericString'
               92  LOAD_NAME                AbstractCharacterString
               94  CALL_FUNCTION_3       3  ''
               96  STORE_NAME               NumericString

 L. 175        98  LOAD_BUILD_CLASS 
              100  LOAD_CODE                <code_object PrintableString>
              102  LOAD_STR                 'PrintableString'
              104  MAKE_FUNCTION_0          'Neither defaults, keyword-only args, annotations, nor closures'
              106  LOAD_STR                 'PrintableString'
              108  LOAD_NAME                AbstractCharacterString
              110  CALL_FUNCTION_3       3  ''
              112  STORE_NAME               PrintableString

 L. 190       114  LOAD_BUILD_CLASS 
              116  LOAD_CODE                <code_object TeletexString>
              118  LOAD_STR                 'TeletexString'
              120  MAKE_FUNCTION_0          'Neither defaults, keyword-only args, annotations, nor closures'
              122  LOAD_STR                 'TeletexString'
              124  LOAD_NAME                AbstractCharacterString
              126  CALL_FUNCTION_3       3  ''
              128  STORE_NAME               TeletexString

 L. 205       130  LOAD_BUILD_CLASS 
              132  LOAD_CODE                <code_object T61String>
              134  LOAD_STR                 'T61String'
              136  MAKE_FUNCTION_0          'Neither defaults, keyword-only args, annotations, nor closures'
              138  LOAD_STR                 'T61String'
              140  LOAD_NAME                TeletexString
              142  CALL_FUNCTION_3       3  ''
              144  STORE_NAME               T61String

 L. 212       146  LOAD_BUILD_CLASS 
              148  LOAD_CODE                <code_object VideotexString>
              150  LOAD_STR                 'VideotexString'
              152  MAKE_FUNCTION_0          'Neither defaults, keyword-only args, annotations, nor closures'
              154  LOAD_STR                 'VideotexString'
              156  LOAD_NAME                AbstractCharacterString
              158  CALL_FUNCTION_3       3  ''
              160  STORE_NAME               VideotexString

 L. 227       162  LOAD_BUILD_CLASS 
              164  LOAD_CODE                <code_object IA5String>
              166  LOAD_STR                 'IA5String'
              168  MAKE_FUNCTION_0          'Neither defaults, keyword-only args, annotations, nor closures'
              170  LOAD_STR                 'IA5String'
              172  LOAD_NAME                AbstractCharacterString
              174  CALL_FUNCTION_3       3  ''
              176  STORE_NAME               IA5String

 L. 242       178  LOAD_BUILD_CLASS 
              180  LOAD_CODE                <code_object GraphicString>
              182  LOAD_STR                 'GraphicString'
              184  MAKE_FUNCTION_0          'Neither defaults, keyword-only args, annotations, nor closures'
              186  LOAD_STR                 'GraphicString'
              188  LOAD_NAME                AbstractCharacterString
              190  CALL_FUNCTION_3       3  ''
              192  STORE_NAME               GraphicString

 L. 257       194  LOAD_BUILD_CLASS 
              196  LOAD_CODE                <code_object VisibleString>
              198  LOAD_STR                 'VisibleString'
              200  MAKE_FUNCTION_0          'Neither defaults, keyword-only args, annotations, nor closures'
              202  LOAD_STR                 'VisibleString'
              204  LOAD_NAME                AbstractCharacterString
              206  CALL_FUNCTION_3       3  ''
              208  STORE_NAME               VisibleString

 L. 272       210  LOAD_BUILD_CLASS 
              212  LOAD_CODE                <code_object ISO646String>
              214  LOAD_STR                 'ISO646String'
              216  MAKE_FUNCTION_0          'Neither defaults, keyword-only args, annotations, nor closures'
              218  LOAD_STR                 'ISO646String'
              220  LOAD_NAME                VisibleString
              222  CALL_FUNCTION_3       3  ''
              224  STORE_NAME               ISO646String

 L. 278       226  LOAD_BUILD_CLASS 
              228  LOAD_CODE                <code_object GeneralString>
              230  LOAD_STR                 'GeneralString'
              232  MAKE_FUNCTION_0          'Neither defaults, keyword-only args, annotations, nor closures'
              234  LOAD_STR                 'GeneralString'
              236  LOAD_NAME                AbstractCharacterString
              238  CALL_FUNCTION_3       3  ''
              240  STORE_NAME               GeneralString

 L. 293       242  LOAD_BUILD_CLASS 
              244  LOAD_CODE                <code_object UniversalString>
              246  LOAD_STR                 'UniversalString'
              248  MAKE_FUNCTION_0          'Neither defaults, keyword-only args, annotations, nor closures'
              250  LOAD_STR                 'UniversalString'
              252  LOAD_NAME                AbstractCharacterString
              254  CALL_FUNCTION_3       3  ''
              256  STORE_NAME               UniversalString

 L. 308       258  LOAD_BUILD_CLASS 
              260  LOAD_CODE                <code_object BMPString>
              262  LOAD_STR                 'BMPString'
              264  MAKE_FUNCTION_0          'Neither defaults, keyword-only args, annotations, nor closures'
              266  LOAD_STR                 'BMPString'
              268  LOAD_NAME                AbstractCharacterString
              270  CALL_FUNCTION_3       3  ''
              272  STORE_NAME               BMPString

 L. 323       274  LOAD_BUILD_CLASS 
              276  LOAD_CODE                <code_object UTF8String>
              278  LOAD_STR                 'UTF8String'
              280  MAKE_FUNCTION_0          'Neither defaults, keyword-only args, annotations, nor closures'
              282  LOAD_STR                 'UTF8String'
              284  LOAD_NAME                AbstractCharacterString
              286  CALL_FUNCTION_3       3  ''
              288  STORE_NAME               UTF8String

Parse error at or near `CALL_FINALLY' instruction at offset 48

Instruction context:
   
 L.  13        44  BUILD_LIST_0          0 
                  46  LOAD_CONST               ('NumericString', 'PrintableString', 'TeletexString', 'T61String', 'VideotexString', 'IA5String', 'GraphicString', 'VisibleString', 'ISO646String', 'GeneralString', 'UniversalString', 'BMPString', 'UTF8String')
->                48  CALL_FINALLY         51  'to 51'
                  50  STORE_NAME               __all__

test/31724.pyc -- 
# decompile failed
