
# file test/39485.pyc
# --- This code section failed: ---

 L.   1         0  LOAD_CONST               0
                2  LOAD_CONST               None
                4  IMPORT_NAME              abc
                6  STORE_NAME               abc

 L.   2         8  LOAD_CONST               0
               10  LOAD_CONST               None
               12  IMPORT_NAME              asyncio
               14  STORE_NAME               asyncio

 L.   3        16  LOAD_CONST               0
               18  LOAD_CONST               None
               20  IMPORT_NAME              collections
               22  STORE_NAME               collections

 L.   4        24  LOAD_CONST               0
               26  LOAD_CONST               None
               28  IMPORT_NAME              re
               30  STORE_NAME               re

 L.   5        32  LOAD_CONST               0
               34  LOAD_CONST               None
               36  IMPORT_NAME              string
               38  STORE_NAME               string

 L.   6        40  LOAD_CONST               0
               42  LOAD_CONST               None
               44  IMPORT_NAME              zlib
               46  STORE_NAME               zlib

 L.   7        48  LOAD_CONST               0
               50  LOAD_CONST               ('IntEnum',)
               52  IMPORT_NAME              enum
               54  IMPORT_FROM              IntEnum
               56  STORE_NAME               IntEnum
               58  POP_TOP          

 L.   8        60  LOAD_CONST               0
               62  LOAD_CONST               ('Any', 'List', 'Optional', 'Tuple', 'Type', 'Union')
               64  IMPORT_NAME              typing
               66  IMPORT_FROM              Any
               68  STORE_NAME               Any
               70  IMPORT_FROM              List
               72  STORE_NAME               List
               74  IMPORT_FROM              Optional
               76  STORE_NAME               Optional
               78  IMPORT_FROM              Tuple
               80  STORE_NAME               Tuple
               82  IMPORT_FROM              Type
               84  STORE_NAME               Type
               86  IMPORT_FROM              Union
               88  STORE_NAME               Union
               90  POP_TOP          

 L.  10        92  LOAD_CONST               0
               94  LOAD_CONST               ('CIMultiDict', 'CIMultiDictProxy', 'istr')
               96  IMPORT_NAME              multidict
               98  IMPORT_FROM              CIMultiDict
              100  STORE_NAME               CIMultiDict
              102  IMPORT_FROM              CIMultiDictProxy
              104  STORE_NAME               CIMultiDictProxy
              106  IMPORT_FROM              istr
              108  STORE_NAME               istr
              110  POP_TOP          

 L.  11       112  LOAD_CONST               0
              114  LOAD_CONST               ('URL',)
              116  IMPORT_NAME              yarl
              118  IMPORT_FROM              URL
              120  STORE_NAME               URL
              122  POP_TOP          

 L.  13       124  LOAD_CONST               1
              126  LOAD_CONST               ('hdrs',)
              128  IMPORT_NAME              
              130  IMPORT_FROM              hdrs
              132  STORE_NAME               hdrs
              134  POP_TOP          

 L.  14       136  LOAD_CONST               1
              138  LOAD_CONST               ('BaseProtocol',)
              140  IMPORT_NAME              base_protocol
              142  IMPORT_FROM              BaseProtocol
              144  STORE_NAME               BaseProtocol
              146  POP_TOP          

 L.  15       148  LOAD_CONST               1
              150  LOAD_CONST               ('NO_EXTENSIONS', 'BaseTimerContext')
              152  IMPORT_NAME              helpers
              154  IMPORT_FROM              NO_EXTENSIONS
              156  STORE_NAME               NO_EXTENSIONS
              158  IMPORT_FROM              BaseTimerContext
              160  STORE_NAME               BaseTimerContext
              162  POP_TOP          

 L.  16       164  LOAD_CONST               1
              166  LOAD_CONST               ('BadStatusLine', 'ContentEncodingError', 'ContentLengthError', 'InvalidHeader', 'LineTooLong', 'TransferEncodingError')
              168  IMPORT_NAME              http_exceptions
              170  IMPORT_FROM              BadStatusLine
              172  STORE_NAME               BadStatusLine
              174  IMPORT_FROM              ContentEncodingError
              176  STORE_NAME               ContentEncodingError
              178  IMPORT_FROM              ContentLengthError
              180  STORE_NAME               ContentLengthError
              182  IMPORT_FROM              InvalidHeader
              184  STORE_NAME               InvalidHeader
              186  IMPORT_FROM              LineTooLong
              188  STORE_NAME               LineTooLong
              190  IMPORT_FROM              TransferEncodingError
              192  STORE_NAME               TransferEncodingError
              194  POP_TOP          

 L.  24       196  LOAD_CONST               1
              198  LOAD_CONST               ('HttpVersion', 'HttpVersion10')
              200  IMPORT_NAME              http_writer
              202  IMPORT_FROM              HttpVersion
              204  STORE_NAME               HttpVersion
              206  IMPORT_FROM              HttpVersion10
              208  STORE_NAME               HttpVersion10
              210  POP_TOP          

 L.  25       212  LOAD_CONST               1
              214  LOAD_CONST               ('internal_logger',)
              216  IMPORT_NAME              log
              218  IMPORT_FROM              internal_logger
              220  STORE_NAME               internal_logger
              222  POP_TOP          

 L.  26       224  LOAD_CONST               1
              226  LOAD_CONST               ('EMPTY_PAYLOAD', 'StreamReader')
              228  IMPORT_NAME              streams
              230  IMPORT_FROM              EMPTY_PAYLOAD
              232  STORE_NAME               EMPTY_PAYLOAD
              234  IMPORT_FROM              StreamReader
              236  STORE_NAME               StreamReader
              238  POP_TOP          

 L.  27       240  LOAD_CONST               1
              242  LOAD_CONST               ('RawHeaders',)
              244  IMPORT_NAME              typedefs
              246  IMPORT_FROM              RawHeaders
              248  STORE_NAME               RawHeaders
              250  POP_TOP          

 L.  29       252  SETUP_FINALLY       270  'to 270'

 L.  30       254  LOAD_CONST               0
              256  LOAD_CONST               None
              258  IMPORT_NAME              brotli
              260  STORE_NAME               brotli

 L.  32       262  LOAD_CONST               True
              264  STORE_NAME               HAS_BROTLI
              266  POP_BLOCK        
              268  JUMP_FORWARD        294  'to 294'
            270_0  COME_FROM_FINALLY   252  '252'

 L.  33       270  DUP_TOP          
              272  LOAD_NAME                ImportError
          274_276  <121>               292  ''
              278  POP_TOP          
              280  POP_TOP          
              282  POP_TOP          

 L.  34       284  LOAD_CONST               False
              286  STORE_NAME               HAS_BROTLI
              288  POP_EXCEPT       
              290  JUMP_FORWARD        294  'to 294'
              292  <48>             
            294_0  COME_FROM           290  '290'
            294_1  COME_FROM           268  '268'

 L.  37       294  LOAD_CONST               ('HeadersParser', 'HttpParser', 'HttpRequestParser', 'HttpResponseParser', 'RawRequestMessage', 'RawResponseMessage')
              296  STORE_NAME               __all__

 L.  46       298  LOAD_NAME                set
              300  LOAD_NAME                string
              302  LOAD_ATTR                printable
              304  CALL_FUNCTION_1       1  ''
              306  STORE_NAME               ASCIISET

 L.  55       308  LOAD_NAME                re
              310  LOAD_METHOD              compile
              312  LOAD_STR                 "[!#$%&'*+\\-.^_`|~0-9A-Za-z]+"
              314  CALL_METHOD_1         1  ''
              316  STORE_NAME               METHRE

 L.  56       318  LOAD_NAME                re
              320  LOAD_METHOD              compile
              322  LOAD_STR                 'HTTP/(\\d+).(\\d+)'
              324  CALL_METHOD_1         1  ''
              326  STORE_NAME               VERSRE

 L.  57       328  LOAD_NAME                re
              330  LOAD_METHOD              compile
              332  LOAD_CONST               b'[\\x00-\\x1F\\x7F()<>@,;:\\[\\]={} \\t\\\\\\\\\\"]'
              334  CALL_METHOD_1         1  ''
              336  STORE_NAME               HDRRE

 L.  59       338  LOAD_NAME                collections
              340  LOAD_METHOD              namedtuple

 L.  60       342  LOAD_STR                 'RawRequestMessage'

 L.  61       344  BUILD_LIST_0          0 
              346  LOAD_CONST               ('method', 'path', 'version', 'headers', 'raw_headers', 'should_close', 'compression', 'upgrade', 'chunked', 'url')
              348  CALL_FINALLY        351  'to 351'

 L.  59       350  CALL_METHOD_2         2  ''
              352  STORE_NAME               RawRequestMessage

 L.  75       354  LOAD_NAME                collections
              356  LOAD_METHOD              namedtuple

 L.  76       358  LOAD_STR                 'RawResponseMessage'

 L.  77       360  BUILD_LIST_0          0 
              362  LOAD_CONST               ('version', 'code', 'reason', 'headers', 'raw_headers', 'should_close', 'compression', 'upgrade', 'chunked')
              364  CALL_FINALLY        367  'to 367'

 L.  75       366  CALL_METHOD_2         2  ''
              368  STORE_NAME               RawResponseMessage

 L.  91       370  LOAD_BUILD_CLASS 
              372  LOAD_CODE                <code_object ParseState>
              374  LOAD_STR                 'ParseState'
              376  MAKE_FUNCTION_0          'Neither defaults, keyword-only args, annotations, nor closures'
              378  LOAD_STR                 'ParseState'
              380  LOAD_NAME                IntEnum
              382  CALL_FUNCTION_3       3  ''
              384  STORE_NAME               ParseState

 L.  99       386  LOAD_BUILD_CLASS 
              388  LOAD_CODE                <code_object ChunkState>
              390  LOAD_STR                 'ChunkState'
              392  MAKE_FUNCTION_0          'Neither defaults, keyword-only args, annotations, nor closures'
              394  LOAD_STR                 'ChunkState'
              396  LOAD_NAME                IntEnum
              398  CALL_FUNCTION_3       3  ''
              400  STORE_NAME               ChunkState

 L. 107       402  LOAD_BUILD_CLASS 
              404  LOAD_CODE                <code_object HeadersParser>
              406  LOAD_STR                 'HeadersParser'
              408  MAKE_FUNCTION_0          'Neither defaults, keyword-only args, annotations, nor closures'
              410  LOAD_STR                 'HeadersParser'
              412  CALL_FUNCTION_2       2  ''
              414  STORE_NAME               HeadersParser

 L. 201       416  LOAD_BUILD_CLASS 
              418  LOAD_CODE                <code_object HttpParser>
              420  LOAD_STR                 'HttpParser'
              422  MAKE_FUNCTION_0          'Neither defaults, keyword-only args, annotations, nor closures'
              424  LOAD_STR                 'HttpParser'
              426  LOAD_NAME                abc
              428  LOAD_ATTR                ABC
              430  CALL_FUNCTION_3       3  ''
              432  STORE_NAME               HttpParser

 L. 482       434  LOAD_BUILD_CLASS 
              436  LOAD_CODE                <code_object HttpRequestParser>
              438  LOAD_STR                 'HttpRequestParser'
              440  MAKE_FUNCTION_0          'Neither defaults, keyword-only args, annotations, nor closures'
              442  LOAD_STR                 'HttpRequestParser'
              444  LOAD_NAME                HttpParser
              446  CALL_FUNCTION_3       3  ''
              448  STORE_NAME               HttpRequestParser

 L. 557       450  LOAD_BUILD_CLASS 
              452  LOAD_CODE                <code_object HttpResponseParser>
              454  LOAD_STR                 'HttpResponseParser'
              456  MAKE_FUNCTION_0          'Neither defaults, keyword-only args, annotations, nor closures'
              458  LOAD_STR                 'HttpResponseParser'
              460  LOAD_NAME                HttpParser
              462  CALL_FUNCTION_3       3  ''
              464  STORE_NAME               HttpResponseParser

 L. 621       466  LOAD_BUILD_CLASS 
              468  LOAD_CODE                <code_object HttpPayloadParser>
              470  LOAD_STR                 'HttpPayloadParser'
              472  MAKE_FUNCTION_0          'Neither defaults, keyword-only args, annotations, nor closures'
              474  LOAD_STR                 'HttpPayloadParser'
              476  CALL_FUNCTION_2       2  ''
              478  STORE_NAME               HttpPayloadParser

 L. 812       480  LOAD_BUILD_CLASS 
              482  LOAD_CODE                <code_object DeflateBuffer>
              484  LOAD_STR                 'DeflateBuffer'
              486  MAKE_FUNCTION_0          'Neither defaults, keyword-only args, annotations, nor closures'
              488  LOAD_STR                 'DeflateBuffer'
              490  CALL_FUNCTION_2       2  ''
              492  STORE_NAME               DeflateBuffer

 L. 882       494  LOAD_NAME                HttpRequestParser
              496  STORE_NAME               HttpRequestParserPy

 L. 883       498  LOAD_NAME                HttpResponseParser
              500  STORE_NAME               HttpResponseParserPy

 L. 884       502  LOAD_NAME                RawRequestMessage
              504  STORE_NAME               RawRequestMessagePy

 L. 885       506  LOAD_NAME                RawResponseMessage
              508  STORE_NAME               RawResponseMessagePy

 L. 887       510  SETUP_FINALLY       562  'to 562'

 L. 888       512  LOAD_NAME                NO_EXTENSIONS
          514_516  POP_JUMP_IF_TRUE    558  'to 558'

 L. 889       518  LOAD_CONST               1
              520  LOAD_CONST               ('HttpRequestParser', 'HttpResponseParser', 'RawRequestMessage', 'RawResponseMessage')
              522  IMPORT_NAME              _http_parser
              524  IMPORT_FROM              HttpRequestParser
              526  STORE_NAME               HttpRequestParser
              528  IMPORT_FROM              HttpResponseParser
              530  STORE_NAME               HttpResponseParser
              532  IMPORT_FROM              RawRequestMessage
              534  STORE_NAME               RawRequestMessage
              536  IMPORT_FROM              RawResponseMessage
              538  STORE_NAME               RawResponseMessage
              540  POP_TOP          

 L. 896       542  LOAD_NAME                HttpRequestParser
              544  STORE_NAME               HttpRequestParserC

 L. 897       546  LOAD_NAME                HttpResponseParser
              548  STORE_NAME               HttpResponseParserC

 L. 898       550  LOAD_NAME                RawRequestMessage
              552  STORE_NAME               RawRequestMessageC

 L. 899       554  LOAD_NAME                RawResponseMessage
              556  STORE_NAME               RawResponseMessageC
            558_0  COME_FROM           514  '514'
              558  POP_BLOCK        
              560  JUMP_FORWARD        582  'to 582'
            562_0  COME_FROM_FINALLY   510  '510'

 L. 900       562  DUP_TOP          
              564  LOAD_NAME                ImportError
          566_568  <121>               580  ''
              570  POP_TOP          
              572  POP_TOP          
              574  POP_TOP          

 L. 901       576  POP_EXCEPT       
              578  JUMP_FORWARD        582  'to 582'
              580  <48>             
            582_0  COME_FROM           578  '578'
            582_1  COME_FROM           560  '560'

Parse error at or near `<121>' instruction at offset 274_276

Instruction context:
   
 L.  33       270  DUP_TOP          
                 272  LOAD_NAME                ImportError
->           274_276  <121>               292  ''
                 278  POP_TOP          
                 280  POP_TOP          
                 282  POP_TOP          

test/39485.pyc -- 
# decompile failed
