Instruction context:
   
 L.  24       104  BUILD_LIST_0          0 
                 106  LOAD_CONST               ('IDNABidiError', 'IDNAError', 'InvalidCodepoint', 'InvalidCodepointContext', 'alabel', 'check_bidi', 'check_hyphen_ok', 'check_initial_combiner', 'check_label', 'check_nfc', 'decode', 'encode', 'intranges_contain', 'ulabel', 'uts46_remap', 'valid_contextj', 'valid_contexto', 'valid_label_length', 'valid_string_length')
->               108  CALL_FINALLY        111  'to 111'

test/39672.pyc -- 
# decompile failed

# file test/39672.pyc
# --- This code section failed: ---

 L.   1         0  LOAD_CONST               1
                2  LOAD_CONST               ('__version__',)
                4  IMPORT_NAME              package_data
                6  IMPORT_FROM              __version__
                8  STORE_NAME               __version__
               10  POP_TOP          

 L.   2        12  LOAD_CONST               1
               14  LOAD_CONST               ('IDNABidiError', 'IDNAError', 'InvalidCodepoint', 'InvalidCodepointContext', 'alabel', 'check_bidi', 'check_hyphen_ok', 'check_initial_combiner', 'check_label', 'check_nfc', 'decode', 'encode', 'ulabel', 'uts46_remap', 'valid_contextj', 'valid_contexto', 'valid_label_length', 'valid_string_length')
               16  IMPORT_NAME              core
               18  IMPORT_FROM              IDNABidiError
               20  STORE_NAME               IDNABidiError
               22  IMPORT_FROM              IDNAError
               24  STORE_NAME               IDNAError
               26  IMPORT_FROM              InvalidCodepoint
               28  STORE_NAME               InvalidCodepoint
               30  IMPORT_FROM              InvalidCodepointContext
               32  STORE_NAME               InvalidCodepointContext
               34  IMPORT_FROM              alabel
               36  STORE_NAME               alabel
               38  IMPORT_FROM              check_bidi
               40  STORE_NAME               check_bidi
               42  IMPORT_FROM              check_hyphen_ok
               44  STORE_NAME               check_hyphen_ok
               46  IMPORT_FROM              check_initial_combiner
               48  STORE_NAME               check_initial_combiner
               50  IMPORT_FROM              check_label
               52  STORE_NAME               check_label
               54  IMPORT_FROM              check_nfc
               56  STORE_NAME               check_nfc
               58  IMPORT_FROM              decode
               60  STORE_NAME               decode
               62  IMPORT_FROM              encode
               64  STORE_NAME               encode
               66  IMPORT_FROM              ulabel
               68  STORE_NAME               ulabel
               70  IMPORT_FROM              uts46_remap
               72  STORE_NAME               uts46_remap
               74  IMPORT_FROM              valid_contextj
               76  STORE_NAME               valid_contextj
               78  IMPORT_FROM              valid_contexto
               80  STORE_NAME               valid_contexto
               82  IMPORT_FROM              valid_label_length
               84  STORE_NAME               valid_label_length
               86  IMPORT_FROM              valid_string_length
               88  STORE_NAME               valid_string_length
               90  POP_TOP          

 L.  22        92  LOAD_CONST               1
               94  LOAD_CONST               ('intranges_contain',)
               96  IMPORT_NAME              intranges
               98  IMPORT_FROM              intranges_contain
              100  STORE_NAME               intranges_contain
              102  POP_TOP          

 L.  24       104  BUILD_LIST_0          0 
              106  LOAD_CONST               ('IDNABidiError', 'IDNAError', 'InvalidCodepoint', 'InvalidCodepointContext', 'alabel', 'check_bidi', 'check_hyphen_ok', 'check_initial_combiner', 'check_label', 'check_nfc', 'decode', 'encode', 'intranges_contain', 'ulabel', 'uts46_remap', 'valid_contextj', 'valid_contexto', 'valid_label_length', 'valid_string_length')
              108  CALL_FINALLY        111  'to 111'
              110  STORE_NAME               __all__

Parse error at or near `CALL_FINALLY' instruction at offset 108

