
# file test/39760.pyc
# --- This code section failed: ---

 L.   1         0  LOAD_STR                 '\nTLS with SNI_-support for Python 2. Follow these instructions if you would\nlike to verify TLS certificates in Python 2. Note, the default libraries do\n*not* do certificate checking; you need to do additional work to validate\ncertificates yourself.\n\nThis needs the following packages installed:\n\n* `pyOpenSSL`_ (tested with 16.0.0)\n* `cryptography`_ (minimum 1.3.4, from pyopenssl)\n* `idna`_ (minimum 2.0, from cryptography)\n\nHowever, pyopenssl depends on cryptography, which depends on idna, so while we\nuse all three directly here we end up having relatively few packages required.\n\nYou can install them with the following command:\n\n.. code-block:: bash\n\n    $ python -m pip install pyopenssl cryptography idna\n\nTo activate certificate checking, call\n:func:`~urllib3.contrib.pyopenssl.inject_into_urllib3` from your Python code\nbefore you begin making HTTP requests. This can be done in a ``sitecustomize``\nmodule, or at any other time before your application begins using ``urllib3``,\nlike this:\n\n.. code-block:: python\n\n    try:\n        import urllib3.contrib.pyopenssl\n        urllib3.contrib.pyopenssl.inject_into_urllib3()\n    except ImportError:\n        pass\n\nNow you can use :mod:`urllib3` as you normally would, and it will support SNI\nwhen the required modules are installed.\n\nActivating this module also has the positive side effect of disabling SSL/TLS\ncompression in Python 2 (see `CRIME attack`_).\n\n.. _sni: https://en.wikipedia.org/wiki/Server_Name_Indication\n.. _crime attack: https://en.wikipedia.org/wiki/CRIME_(security_exploit)\n.. _pyopenssl: https://www.pyopenssl.org\n.. _cryptography: https://cryptography.io\n.. _idna: https://github.com/kjd/idna\n'
                2  STORE_NAME               __doc__

 L.  48         4  LOAD_CONST               0
                6  LOAD_CONST               ('absolute_import',)
                8  IMPORT_NAME              __future__
               10  IMPORT_FROM              absolute_import
               12  STORE_NAME               absolute_import
               14  POP_TOP          

 L.  50        16  LOAD_CONST               0
               18  LOAD_CONST               None
               20  IMPORT_NAME_ATTR         OpenSSL.SSL
               22  STORE_NAME               OpenSSL

 L.  51        24  LOAD_CONST               0
               26  LOAD_CONST               ('x509',)
               28  IMPORT_NAME              cryptography
               30  IMPORT_FROM              x509
               32  STORE_NAME               x509
               34  POP_TOP          

 L.  52        36  LOAD_CONST               0
               38  LOAD_CONST               ('backend',)
               40  IMPORT_NAME_ATTR         cryptography.hazmat.backends.openssl
               42  IMPORT_FROM              backend
               44  STORE_NAME               openssl_backend
               46  POP_TOP          

 L.  53        48  LOAD_CONST               0
               50  LOAD_CONST               ('_Certificate',)
               52  IMPORT_NAME_ATTR         cryptography.hazmat.backends.openssl.x509
               54  IMPORT_FROM              _Certificate
               56  STORE_NAME               _Certificate
               58  POP_TOP          

 L.  55        60  SETUP_FINALLY        78  'to 78'

 L.  56        62  LOAD_CONST               0
               64  LOAD_CONST               ('UnsupportedExtension',)
               66  IMPORT_NAME_ATTR         cryptography.x509
               68  IMPORT_FROM              UnsupportedExtension
               70  STORE_NAME               UnsupportedExtension
               72  POP_TOP          
               74  POP_BLOCK        
               76  JUMP_FORWARD        112  'to 112'
             78_0  COME_FROM_FINALLY    60  '60'

 L.  57        78  DUP_TOP          
               80  LOAD_NAME                ImportError
               82  <121>               110  ''
               84  POP_TOP          
               86  POP_TOP          
               88  POP_TOP          

 L.  59        90  LOAD_BUILD_CLASS 
               92  LOAD_CODE                <code_object UnsupportedExtension>
               94  LOAD_STR                 'UnsupportedExtension'
               96  MAKE_FUNCTION_0          'Neither defaults, keyword-only args, annotations, nor closures'
               98  LOAD_STR                 'UnsupportedExtension'
              100  LOAD_NAME                Exception
              102  CALL_FUNCTION_3       3  ''
              104  STORE_NAME               UnsupportedExtension
              106  POP_EXCEPT       
              108  JUMP_FORWARD        112  'to 112'
              110  <48>             
            112_0  COME_FROM           108  '108'
            112_1  COME_FROM            76  '76'

 L.  63       112  LOAD_CONST               0
              114  LOAD_CONST               ('BytesIO',)
              116  IMPORT_NAME              io
              118  IMPORT_FROM              BytesIO
              120  STORE_NAME               BytesIO
              122  POP_TOP          

 L.  64       124  LOAD_CONST               0
              126  LOAD_CONST               ('error',)
              128  IMPORT_NAME              socket
              130  IMPORT_FROM              error
              132  STORE_NAME               SocketError
              134  POP_TOP          

 L.  65       136  LOAD_CONST               0
              138  LOAD_CONST               ('timeout',)
              140  IMPORT_NAME              socket
              142  IMPORT_FROM              timeout
              144  STORE_NAME               timeout
              146  POP_TOP          

 L.  67       148  SETUP_FINALLY       166  'to 166'

 L.  68       150  LOAD_CONST               0
              152  LOAD_CONST               ('_fileobject',)
              154  IMPORT_NAME              socket
              156  IMPORT_FROM              _fileobject
              158  STORE_NAME               _fileobject
              160  POP_TOP          
              162  POP_BLOCK        
              164  JUMP_FORWARD        200  'to 200'
            166_0  COME_FROM_FINALLY   148  '148'

 L.  69       166  DUP_TOP          
              168  LOAD_NAME                ImportError
              170  <121>               198  ''
              172  POP_TOP          
              174  POP_TOP          
              176  POP_TOP          

 L.  70       178  LOAD_CONST               None
              180  STORE_NAME               _fileobject

 L.  71       182  LOAD_CONST               2
              184  LOAD_CONST               ('backport_makefile',)
              186  IMPORT_NAME_ATTR         packages.backports.makefile
              188  IMPORT_FROM              backport_makefile
              190  STORE_NAME               backport_makefile
              192  POP_TOP          
              194  POP_EXCEPT       
              196  JUMP_FORWARD        200  'to 200'
              198  <48>             
            200_0  COME_FROM           196  '196'
            200_1  COME_FROM           164  '164'

 L.  73       200  LOAD_CONST               0
              202  LOAD_CONST               None
              204  IMPORT_NAME              logging
              206  STORE_NAME               logging

 L.  74       208  LOAD_CONST               0
              210  LOAD_CONST               None
              212  IMPORT_NAME              ssl
              214  STORE_NAME               ssl

 L.  75       216  LOAD_CONST               0
              218  LOAD_CONST               None
              220  IMPORT_NAME              sys
              222  STORE_NAME               sys

 L.  77       224  LOAD_CONST               2
              226  LOAD_CONST               ('util',)
              228  IMPORT_NAME              
              230  IMPORT_FROM              util
              232  STORE_NAME               util
              234  POP_TOP          

 L.  78       236  LOAD_CONST               2
              238  LOAD_CONST               ('six',)
              240  IMPORT_NAME              packages
              242  IMPORT_FROM              six
              244  STORE_NAME               six
              246  POP_TOP          

 L.  79       248  LOAD_CONST               2
              250  LOAD_CONST               ('PROTOCOL_TLS_CLIENT',)
              252  IMPORT_NAME_ATTR         util.ssl_
              254  IMPORT_FROM              PROTOCOL_TLS_CLIENT
              256  STORE_NAME               PROTOCOL_TLS_CLIENT
              258  POP_TOP          

 L.  81       260  LOAD_STR                 'inject_into_urllib3'
              262  LOAD_STR                 'extract_from_urllib3'
              264  BUILD_LIST_2          2 
              266  STORE_NAME               __all__

 L.  84       268  LOAD_CONST               True
              270  STORE_NAME               HAS_SNI

 L.  88       272  LOAD_NAME                util
              274  LOAD_ATTR                PROTOCOL_TLS
              276  LOAD_NAME                OpenSSL
              278  LOAD_ATTR                SSL
              280  LOAD_ATTR                SSLv23_METHOD

 L.  89       282  LOAD_NAME                PROTOCOL_TLS_CLIENT
              284  LOAD_NAME                OpenSSL
              286  LOAD_ATTR                SSL
              288  LOAD_ATTR                SSLv23_METHOD

 L.  90       290  LOAD_NAME                ssl
              292  LOAD_ATTR                PROTOCOL_TLSv1
              294  LOAD_NAME                OpenSSL
              296  LOAD_ATTR                SSL
              298  LOAD_ATTR                TLSv1_METHOD

 L.  87       300  BUILD_MAP_3           3 
              302  STORE_NAME               _openssl_versions

 L.  93       304  LOAD_NAME                hasattr
              306  LOAD_NAME                ssl
              308  LOAD_STR                 'PROTOCOL_SSLv3'
              310  CALL_FUNCTION_2       2  ''
          312_314  POP_JUMP_IF_FALSE   344  'to 344'
              316  LOAD_NAME                hasattr
              318  LOAD_NAME                OpenSSL
              320  LOAD_ATTR                SSL
              322  LOAD_STR                 'SSLv3_METHOD'
              324  CALL_FUNCTION_2       2  ''
          326_328  POP_JUMP_IF_FALSE   344  'to 344'

 L.  94       330  LOAD_NAME                OpenSSL
              332  LOAD_ATTR                SSL
              334  LOAD_ATTR                SSLv3_METHOD
              336  LOAD_NAME                _openssl_versions
              338  LOAD_NAME                ssl
              340  LOAD_ATTR                PROTOCOL_SSLv3
              342  STORE_SUBSCR     
            344_0  COME_FROM           326  '326'
            344_1  COME_FROM           312  '312'

 L.  96       344  LOAD_NAME                hasattr
              346  LOAD_NAME                ssl
              348  LOAD_STR                 'PROTOCOL_TLSv1_1'
              350  CALL_FUNCTION_2       2  ''
          352_354  POP_JUMP_IF_FALSE   384  'to 384'
              356  LOAD_NAME                hasattr
              358  LOAD_NAME                OpenSSL
              360  LOAD_ATTR                SSL
              362  LOAD_STR                 'TLSv1_1_METHOD'
              364  CALL_FUNCTION_2       2  ''
          366_368  POP_JUMP_IF_FALSE   384  'to 384'

 L.  97       370  LOAD_NAME                OpenSSL
              372  LOAD_ATTR                SSL
              374  LOAD_ATTR                TLSv1_1_METHOD
              376  LOAD_NAME                _openssl_versions
              378  LOAD_NAME                ssl
              380  LOAD_ATTR                PROTOCOL_TLSv1_1
              382  STORE_SUBSCR     
            384_0  COME_FROM           366  '366'
            384_1  COME_FROM           352  '352'

 L.  99       384  LOAD_NAME                hasattr
              386  LOAD_NAME                ssl
              388  LOAD_STR                 'PROTOCOL_TLSv1_2'
              390  CALL_FUNCTION_2       2  ''
          392_394  POP_JUMP_IF_FALSE   424  'to 424'
              396  LOAD_NAME                hasattr
              398  LOAD_NAME                OpenSSL
              400  LOAD_ATTR                SSL
              402  LOAD_STR                 'TLSv1_2_METHOD'
              404  CALL_FUNCTION_2       2  ''
          406_408  POP_JUMP_IF_FALSE   424  'to 424'

 L. 100       410  LOAD_NAME                OpenSSL
              412  LOAD_ATTR                SSL
              414  LOAD_ATTR                TLSv1_2_METHOD
              416  LOAD_NAME                _openssl_versions
              418  LOAD_NAME                ssl
              420  LOAD_ATTR                PROTOCOL_TLSv1_2
              422  STORE_SUBSCR     
            424_0  COME_FROM           406  '406'
            424_1  COME_FROM           392  '392'

 L. 104       424  LOAD_NAME                ssl
              426  LOAD_ATTR                CERT_NONE
              428  LOAD_NAME                OpenSSL
              430  LOAD_ATTR                SSL
              432  LOAD_ATTR                VERIFY_NONE

 L. 105       434  LOAD_NAME                ssl
              436  LOAD_ATTR                CERT_OPTIONAL
              438  LOAD_NAME                OpenSSL
              440  LOAD_ATTR                SSL
              442  LOAD_ATTR                VERIFY_PEER

 L. 106       444  LOAD_NAME                ssl
              446  LOAD_ATTR                CERT_REQUIRED
              448  LOAD_NAME                OpenSSL
              450  LOAD_ATTR                SSL
              452  LOAD_ATTR                VERIFY_PEER

 L. 107       454  LOAD_NAME                OpenSSL
              456  LOAD_ATTR                SSL
              458  LOAD_ATTR                VERIFY_FAIL_IF_NO_PEER_CERT

 L. 106       460  BINARY_ADD       

 L. 103       462  BUILD_MAP_3           3 
              464  STORE_NAME               _stdlib_to_openssl_verify

 L. 109       466  LOAD_NAME                dict
              468  LOAD_GENEXPR             '<code_object <genexpr>>'
              470  LOAD_STR                 '<genexpr>'
              472  MAKE_FUNCTION_0          'Neither defaults, keyword-only args, annotations, nor closures'
              474  LOAD_NAME                _stdlib_to_openssl_verify
              476  LOAD_METHOD              items
              478  CALL_METHOD_0         0  ''
              480  GET_ITER         
              482  CALL_FUNCTION_1       1  ''
              484  CALL_FUNCTION_1       1  ''
              486  STORE_NAME               _openssl_to_stdlib_verify

 L. 112       488  LOAD_CONST               16384
              490  STORE_NAME               SSL_WRITE_BLOCKSIZE

 L. 114       492  LOAD_NAME                util
              494  LOAD_ATTR                HAS_SNI
              496  STORE_NAME               orig_util_HAS_SNI

 L. 115       498  LOAD_NAME                util
              500  LOAD_ATTR                ssl_
              502  LOAD_ATTR                SSLContext
              504  STORE_NAME               orig_util_SSLContext

 L. 118       506  LOAD_NAME                logging
              508  LOAD_METHOD              getLogger
              510  LOAD_NAME                __name__
              512  CALL_METHOD_1         1  ''
              514  STORE_NAME               log

 L. 121       516  LOAD_CODE                <code_object inject_into_urllib3>
              518  LOAD_STR                 'inject_into_urllib3'
              520  MAKE_FUNCTION_0          'Neither defaults, keyword-only args, annotations, nor closures'
              522  STORE_NAME               inject_into_urllib3

 L. 134       524  LOAD_CODE                <code_object extract_from_urllib3>
              526  LOAD_STR                 'extract_from_urllib3'
              528  MAKE_FUNCTION_0          'Neither defaults, keyword-only args, annotations, nor closures'
              530  STORE_NAME               extract_from_urllib3

 L. 145       532  LOAD_CODE                <code_object _validate_dependencies_met>
              534  LOAD_STR                 '_validate_dependencies_met'
              536  MAKE_FUNCTION_0          'Neither defaults, keyword-only args, annotations, nor closures'
              538  STORE_NAME               _validate_dependencies_met

 L. 171       540  LOAD_CODE                <code_object _dnsname_to_stdlib>
              542  LOAD_STR                 '_dnsname_to_stdlib'
              544  MAKE_FUNCTION_0          'Neither defaults, keyword-only args, annotations, nor closures'
              546  STORE_NAME               _dnsname_to_stdlib

 L. 214       548  LOAD_CODE                <code_object get_subj_alt_name>
              550  LOAD_STR                 'get_subj_alt_name'
              552  MAKE_FUNCTION_0          'Neither defaults, keyword-only args, annotations, nor closures'
              554  STORE_NAME               get_subj_alt_name

 L. 268       556  LOAD_BUILD_CLASS 
              558  LOAD_CODE                <code_object WrappedSocket>
              560  LOAD_STR                 'WrappedSocket'
              562  MAKE_FUNCTION_0          'Neither defaults, keyword-only args, annotations, nor closures'
              564  LOAD_STR                 'WrappedSocket'
              566  LOAD_NAME                object
              568  CALL_FUNCTION_3       3  ''
              570  STORE_NAME               WrappedSocket

 L. 403       572  LOAD_NAME                _fileobject
          574_576  POP_JUMP_IF_FALSE   590  'to 590'

 L. 405       578  LOAD_CONST               (-1,)
              580  LOAD_CODE                <code_object makefile>
              582  LOAD_STR                 'makefile'
              584  MAKE_FUNCTION_1          'default'
              586  STORE_NAME               makefile
              588  JUMP_FORWARD        594  'to 594'
            590_0  COME_FROM           574  '574'

 L. 411       590  LOAD_NAME                backport_makefile
              592  STORE_NAME               makefile
            594_0  COME_FROM           588  '588'

 L. 413       594  LOAD_NAME                makefile
              596  LOAD_NAME                WrappedSocket
              598  STORE_ATTR               makefile

 L. 416       600  LOAD_BUILD_CLASS 
              602  LOAD_CODE                <code_object PyOpenSSLContext>
              604  LOAD_STR                 'PyOpenSSLContext'
              606  MAKE_FUNCTION_0          'Neither defaults, keyword-only args, annotations, nor closures'
              608  LOAD_STR                 'PyOpenSSLContext'
              610  LOAD_NAME                object
              612  CALL_FUNCTION_3       3  ''
              614  STORE_NAME               PyOpenSSLContext

 L. 510       616  LOAD_CODE                <code_object _verify_callback>
              618  LOAD_STR                 '_verify_callback'
              620  MAKE_FUNCTION_0          'Neither defaults, keyword-only args, annotations, nor closures'
              622  STORE_NAME               _verify_callback

Parse error at or near `<121>' instruction at offset 82

Instruction context:
   
 L.  57        78  DUP_TOP          
                  80  LOAD_NAME                ImportError
->                82  <121>               110  ''
                  84  POP_TOP          
                  86  POP_TOP          
                  88  POP_TOP          

test/39760.pyc -- 
# decompile failed
