
# file test/4326.pyc
# --- This code section failed: ---

 L.   1         0  LOAD_CONST               0
                2  LOAD_CONST               None
                4  IMPORT_NAME              functools
                6  STORE_NAME               functools

 L.   2         8  LOAD_CONST               0
               10  LOAD_CONST               None
               12  IMPORT_NAME              itertools
               14  STORE_NAME               itertools

 L.   3        16  LOAD_CONST               0
               18  LOAD_CONST               None
               20  IMPORT_NAME              operator
               22  STORE_NAME               operator

 L.   4        24  LOAD_CONST               0
               26  LOAD_CONST               None
               28  IMPORT_NAME              sys
               30  STORE_NAME               sys

 L.   5        32  LOAD_CONST               0
               34  LOAD_CONST               None
               36  IMPORT_NAME              warnings
               38  STORE_NAME               warnings

 L.   6        40  LOAD_CONST               0
               42  LOAD_CONST               None
               44  IMPORT_NAME              numbers
               46  STORE_NAME               numbers

 L.   8        48  LOAD_CONST               0
               50  LOAD_CONST               None
               52  IMPORT_NAME              numpy
               54  STORE_NAME               np

 L.   9        56  LOAD_CONST               1
               58  LOAD_CONST               ('multiarray',)
               60  IMPORT_NAME              
               62  IMPORT_FROM              multiarray
               64  STORE_NAME               multiarray
               66  POP_TOP          

 L.  10        68  LOAD_CONST               1
               70  LOAD_CONST               ('_fastCopyAndTranspose', 'ALLOW_THREADS', 'BUFSIZE', 'CLIP', 'MAXDIMS', 'MAY_SHARE_BOUNDS', 'MAY_SHARE_EXACT', 'RAISE', 'WRAP', 'arange', 'array', 'broadcast', 'can_cast', 'compare_chararrays', 'concatenate', 'copyto', 'dot', 'dtype', 'empty', 'empty_like', 'flatiter', 'frombuffer', 'fromfile', 'fromiter', 'fromstring', 'inner', 'lexsort', 'matmul', 'may_share_memory', 'min_scalar_type', 'ndarray', 'nditer', 'nested_iters', 'promote_types', 'putmask', 'result_type', 'set_numeric_ops', 'shares_memory', 'vdot', 'where', 'zeros', 'normalize_axis_index')
               72  IMPORT_NAME              multiarray
               74  IMPORT_FROM              _fastCopyAndTranspose
               76  STORE_NAME               fastCopyAndTranspose
               78  IMPORT_FROM              ALLOW_THREADS
               80  STORE_NAME               ALLOW_THREADS
               82  IMPORT_FROM              BUFSIZE
               84  STORE_NAME               BUFSIZE
               86  IMPORT_FROM              CLIP
               88  STORE_NAME               CLIP
               90  IMPORT_FROM              MAXDIMS
               92  STORE_NAME               MAXDIMS
               94  IMPORT_FROM              MAY_SHARE_BOUNDS
               96  STORE_NAME               MAY_SHARE_BOUNDS
               98  IMPORT_FROM              MAY_SHARE_EXACT
              100  STORE_NAME               MAY_SHARE_EXACT
              102  IMPORT_FROM              RAISE
              104  STORE_NAME               RAISE
              106  IMPORT_FROM              WRAP
              108  STORE_NAME               WRAP
              110  IMPORT_FROM              arange
              112  STORE_NAME               arange
              114  IMPORT_FROM              array
              116  STORE_NAME               array
              118  IMPORT_FROM              broadcast
              120  STORE_NAME               broadcast
              122  IMPORT_FROM              can_cast
              124  STORE_NAME               can_cast
              126  IMPORT_FROM              compare_chararrays
              128  STORE_NAME               compare_chararrays
              130  IMPORT_FROM              concatenate
              132  STORE_NAME               concatenate
              134  IMPORT_FROM              copyto
              136  STORE_NAME               copyto
              138  IMPORT_FROM              dot
              140  STORE_NAME               dot
              142  IMPORT_FROM              dtype
              144  STORE_NAME               dtype
              146  IMPORT_FROM              empty
              148  STORE_NAME               empty
              150  IMPORT_FROM              empty_like
              152  STORE_NAME               empty_like
              154  IMPORT_FROM              flatiter
              156  STORE_NAME               flatiter
              158  IMPORT_FROM              frombuffer
              160  STORE_NAME               frombuffer
              162  IMPORT_FROM              fromfile
              164  STORE_NAME               fromfile
              166  IMPORT_FROM              fromiter
              168  STORE_NAME               fromiter
              170  IMPORT_FROM              fromstring
              172  STORE_NAME               fromstring
              174  IMPORT_FROM              inner
              176  STORE_NAME               inner
              178  IMPORT_FROM              lexsort
              180  STORE_NAME               lexsort
              182  IMPORT_FROM              matmul
              184  STORE_NAME               matmul
              186  IMPORT_FROM              may_share_memory
              188  STORE_NAME               may_share_memory
              190  IMPORT_FROM              min_scalar_type
              192  STORE_NAME               min_scalar_type
              194  IMPORT_FROM              ndarray
              196  STORE_NAME               ndarray
              198  IMPORT_FROM              nditer
              200  STORE_NAME               nditer
              202  IMPORT_FROM              nested_iters
              204  STORE_NAME               nested_iters
              206  IMPORT_FROM              promote_types
              208  STORE_NAME               promote_types
              210  IMPORT_FROM              putmask
              212  STORE_NAME               putmask
              214  IMPORT_FROM              result_type
              216  STORE_NAME               result_type
              218  IMPORT_FROM              set_numeric_ops
              220  STORE_NAME               set_numeric_ops
              222  IMPORT_FROM              shares_memory
              224  STORE_NAME               shares_memory
              226  IMPORT_FROM              vdot
              228  STORE_NAME               vdot
              230  IMPORT_FROM              where
              232  STORE_NAME               where
              234  IMPORT_FROM              zeros
              236  STORE_NAME               zeros
              238  IMPORT_FROM              normalize_axis_index
              240  STORE_NAME               normalize_axis_index
              242  POP_TOP          

 L.  21       244  LOAD_CONST               1
              246  LOAD_CONST               ('overrides',)
              248  IMPORT_NAME              
              250  IMPORT_FROM              overrides
              252  STORE_NAME               overrides
              254  POP_TOP          

 L.  22       256  LOAD_CONST               1
              258  LOAD_CONST               ('umath',)
              260  IMPORT_NAME              
              262  IMPORT_FROM              umath
              264  STORE_NAME               umath
              266  POP_TOP          

 L.  23       268  LOAD_CONST               1
              270  LOAD_CONST               ('shape_base',)
              272  IMPORT_NAME              
              274  IMPORT_FROM              shape_base
              276  STORE_NAME               shape_base
              278  POP_TOP          

 L.  24       280  LOAD_CONST               1
              282  LOAD_CONST               ('set_array_function_like_doc', 'set_module')
              284  IMPORT_NAME              overrides
              286  IMPORT_FROM              set_array_function_like_doc
              288  STORE_NAME               set_array_function_like_doc
              290  IMPORT_FROM              set_module
              292  STORE_NAME               set_module
              294  POP_TOP          

 L.  25       296  LOAD_CONST               1
              298  LOAD_CONST               ('multiply', 'invert', 'sin', 'PINF', 'NAN')
              300  IMPORT_NAME              umath
              302  IMPORT_FROM              multiply
              304  STORE_NAME               multiply
              306  IMPORT_FROM              invert
              308  STORE_NAME               invert
              310  IMPORT_FROM              sin
              312  STORE_NAME               sin
              314  IMPORT_FROM              PINF
              316  STORE_NAME               PINF
              318  IMPORT_FROM              NAN
              320  STORE_NAME               NAN
              322  POP_TOP          

 L.  26       324  LOAD_CONST               1
              326  LOAD_CONST               ('numerictypes',)
              328  IMPORT_NAME              
              330  IMPORT_FROM              numerictypes
              332  STORE_NAME               numerictypes
              334  POP_TOP          

 L.  27       336  LOAD_CONST               1
              338  LOAD_CONST               ('longlong', 'intc', 'int_', 'float_', 'complex_', 'bool_')
              340  IMPORT_NAME              numerictypes
              342  IMPORT_FROM              longlong
              344  STORE_NAME               longlong
              346  IMPORT_FROM              intc
              348  STORE_NAME               intc
              350  IMPORT_FROM              int_
              352  STORE_NAME               int_
              354  IMPORT_FROM              float_
              356  STORE_NAME               float_
              358  IMPORT_FROM              complex_
              360  STORE_NAME               complex_
              362  IMPORT_FROM              bool_
              364  STORE_NAME               bool_
              366  POP_TOP          

 L.  28       368  LOAD_CONST               1
              370  LOAD_CONST               ('TooHardError', 'AxisError')
              372  IMPORT_NAME              _exceptions
              374  IMPORT_FROM              TooHardError
              376  STORE_NAME               TooHardError
              378  IMPORT_FROM              AxisError
              380  STORE_NAME               AxisError
              382  POP_TOP          

 L.  29       384  LOAD_CONST               1
              386  LOAD_CONST               ('asarray', 'asanyarray')
              388  IMPORT_NAME              _asarray
              390  IMPORT_FROM              asarray
              392  STORE_NAME               asarray
              394  IMPORT_FROM              asanyarray
              396  STORE_NAME               asanyarray
              398  POP_TOP          

 L.  30       400  LOAD_CONST               1
              402  LOAD_CONST               ('errstate',)
              404  IMPORT_NAME              _ufunc_config
              406  IMPORT_FROM              errstate
              408  STORE_NAME               errstate
              410  POP_TOP          

 L.  32       412  LOAD_NAME                invert
              414  STORE_NAME               bitwise_not

 L.  33       416  LOAD_NAME                type
              418  LOAD_NAME                sin
              420  CALL_FUNCTION_1       1  ''
              422  STORE_NAME               ufunc

 L.  34       424  LOAD_CONST               None
              426  STORE_NAME               newaxis

 L.  36       428  LOAD_NAME                functools
              430  LOAD_ATTR                partial

 L.  37       432  LOAD_NAME                overrides
              434  LOAD_ATTR                array_function_dispatch
              436  LOAD_STR                 'numpy'

 L.  36       438  LOAD_CONST               ('module',)
              440  CALL_FUNCTION_KW_2     2  '2 total positional and keyword args'
              442  STORE_NAME               array_function_dispatch

 L.  40       444  BUILD_LIST_0          0 
              446  LOAD_CONST               ('newaxis', 'ndarray', 'flatiter', 'nditer', 'nested_iters', 'ufunc', 'arange', 'array', 'zeros', 'count_nonzero', 'empty', 'broadcast', 'dtype', 'fromstring', 'fromfile', 'frombuffer', 'where', 'argwhere', 'copyto', 'concatenate', 'fastCopyAndTranspose', 'lexsort', 'set_numeric_ops', 'can_cast', 'promote_types', 'min_scalar_type', 'result_type', 'isfortran', 'empty_like', 'zeros_like', 'ones_like', 'correlate', 'convolve', 'inner', 'dot', 'outer', 'vdot', 'roll', 'rollaxis', 'moveaxis', 'cross', 'tensordot', 'little_endian', 'fromiter', 'array_equal', 'array_equiv', 'indices', 'fromfunction', 'isclose', 'isscalar', 'binary_repr', 'base_repr', 'ones', 'identity', 'allclose', 'compare_chararrays', 'putmask', 'flatnonzero', 'Inf', 'inf', 'infty', 'Infinity', 'nan', 'NaN', 'False_', 'True_', 'bitwise_not', 'CLIP', 'RAISE', 'WRAP', 'MAXDIMS', 'BUFSIZE', 'ALLOW_THREADS', 'ComplexWarning', 'full', 'full_like', 'matmul', 'shares_memory', 'may_share_memory', 'MAY_SHARE_BOUNDS', 'MAY_SHARE_EXACT', 'TooHardError', 'AxisError')
              448  CALL_FINALLY        451  'to 451'
              450  STORE_NAME               __all__

 L.  59       452  LOAD_NAME                set_module
              454  LOAD_STR                 'numpy'
              456  CALL_FUNCTION_1       1  ''

 L.  60       458  LOAD_BUILD_CLASS 
              460  LOAD_CODE                <code_object ComplexWarning>
              462  LOAD_STR                 'ComplexWarning'
              464  MAKE_FUNCTION_0          'Neither defaults, keyword-only args, annotations, nor closures'
              466  LOAD_STR                 'ComplexWarning'
              468  LOAD_NAME                RuntimeWarning
              470  CALL_FUNCTION_3       3  ''
              472  CALL_FUNCTION_1       1  ''
              474  STORE_NAME               ComplexWarning

 L.  71       476  LOAD_CONST               (None, None, None, None)
              478  LOAD_CODE                <code_object _zeros_like_dispatcher>
              480  LOAD_STR                 '_zeros_like_dispatcher'
              482  MAKE_FUNCTION_1          'default'
              484  STORE_NAME               _zeros_like_dispatcher

 L.  75       486  LOAD_NAME                array_function_dispatch
              488  LOAD_NAME                _zeros_like_dispatcher
              490  CALL_FUNCTION_1       1  ''

 L.  76       492  LOAD_CONST               (None, 'K', True, None)
              494  LOAD_CODE                <code_object zeros_like>
              496  LOAD_STR                 'zeros_like'
              498  MAKE_FUNCTION_1          'default'
              500  CALL_FUNCTION_1       1  ''
              502  STORE_NAME               zeros_like

 L. 144       504  LOAD_CONST               (None, None)
              506  LOAD_CONST               None
              508  LOAD_CONST               ('like',)
              510  BUILD_CONST_KEY_MAP_1     1 
              512  LOAD_CODE                <code_object _ones_dispatcher>
              514  LOAD_STR                 '_ones_dispatcher'
              516  MAKE_FUNCTION_3          'default, keyword-only'
              518  STORE_NAME               _ones_dispatcher

 L. 148       520  LOAD_NAME                set_array_function_like_doc

 L. 149       522  LOAD_NAME                set_module
              524  LOAD_STR                 'numpy'
              526  CALL_FUNCTION_1       1  ''

 L. 150       528  LOAD_CONST               (None, 'C')
              530  LOAD_CONST               None
              532  LOAD_CONST               ('like',)
              534  BUILD_CONST_KEY_MAP_1     1 
              536  LOAD_CODE                <code_object ones>
              538  LOAD_STR                 'ones'
              540  MAKE_FUNCTION_3          'default, keyword-only'
              542  CALL_FUNCTION_1       1  ''
              544  CALL_FUNCTION_1       1  ''
              546  STORE_NAME               ones

 L. 208       548  LOAD_NAME                array_function_dispatch

 L. 209       550  LOAD_NAME                _ones_dispatcher

 L. 208       552  CALL_FUNCTION_1       1  ''

 L. 210       554  LOAD_NAME                ones

 L. 208       556  CALL_FUNCTION_1       1  ''
              558  STORE_NAME               _ones_with_like

 L. 213       560  LOAD_CONST               (None, None, None, None)
              562  LOAD_CODE                <code_object _ones_like_dispatcher>
              564  LOAD_STR                 '_ones_like_dispatcher'
              566  MAKE_FUNCTION_1          'default'
              568  STORE_NAME               _ones_like_dispatcher

 L. 217       570  LOAD_NAME                array_function_dispatch
              572  LOAD_NAME                _ones_like_dispatcher
              574  CALL_FUNCTION_1       1  ''

 L. 218       576  LOAD_CONST               (None, 'K', True, None)
              578  LOAD_CODE                <code_object ones_like>
              580  LOAD_STR                 'ones_like'
              582  MAKE_FUNCTION_1          'default'
              584  CALL_FUNCTION_1       1  ''
              586  STORE_NAME               ones_like

 L. 284       588  LOAD_CONST               (None, None)
              590  LOAD_CONST               None
              592  LOAD_CONST               ('like',)
              594  BUILD_CONST_KEY_MAP_1     1 
              596  LOAD_CODE                <code_object _full_dispatcher>
              598  LOAD_STR                 '_full_dispatcher'
              600  MAKE_FUNCTION_3          'default, keyword-only'
              602  STORE_NAME               _full_dispatcher

 L. 288       604  LOAD_NAME                set_array_function_like_doc

 L. 289       606  LOAD_NAME                set_module
              608  LOAD_STR                 'numpy'
              610  CALL_FUNCTION_1       1  ''

 L. 290       612  LOAD_CONST               (None, 'C')
              614  LOAD_CONST               None
              616  LOAD_CONST               ('like',)
              618  BUILD_CONST_KEY_MAP_1     1 
              620  LOAD_CODE                <code_object full>
              622  LOAD_STR                 'full'
              624  MAKE_FUNCTION_3          'default, keyword-only'
              626  CALL_FUNCTION_1       1  ''
              628  CALL_FUNCTION_1       1  ''
              630  STORE_NAME               full

 L. 347       632  LOAD_NAME                array_function_dispatch

 L. 348       634  LOAD_NAME                _full_dispatcher

 L. 347       636  CALL_FUNCTION_1       1  ''

 L. 349       638  LOAD_NAME                full

 L. 347       640  CALL_FUNCTION_1       1  ''
              642  STORE_NAME               _full_with_like

 L. 352       644  LOAD_CONST               (None, None, None, None)
              646  LOAD_CODE                <code_object _full_like_dispatcher>
              648  LOAD_STR                 '_full_like_dispatcher'
              650  MAKE_FUNCTION_1          'default'
              652  STORE_NAME               _full_like_dispatcher

 L. 356       654  LOAD_NAME                array_function_dispatch
              656  LOAD_NAME                _full_like_dispatcher
              658  CALL_FUNCTION_1       1  ''

 L. 357       660  LOAD_CONST               (None, 'K', True, None)
              662  LOAD_CODE                <code_object full_like>
              664  LOAD_STR                 'full_like'
              666  MAKE_FUNCTION_1          'default'
              668  CALL_FUNCTION_1       1  ''
              670  STORE_NAME               full_like

 L. 420       672  LOAD_CONST               (None,)
              674  LOAD_CONST               None
              676  LOAD_CONST               ('keepdims',)
              678  BUILD_CONST_KEY_MAP_1     1 
              680  LOAD_CODE                <code_object _count_nonzero_dispatcher>
              682  LOAD_STR                 '_count_nonzero_dispatcher'
              684  MAKE_FUNCTION_3          'default, keyword-only'
              686  STORE_NAME               _count_nonzero_dispatcher

 L. 424       688  LOAD_NAME                array_function_dispatch
              690  LOAD_NAME                _count_nonzero_dispatcher
              692  CALL_FUNCTION_1       1  ''

 L. 425       694  LOAD_CONST               (None,)
              696  LOAD_CONST               False
              698  LOAD_CONST               ('keepdims',)
              700  BUILD_CONST_KEY_MAP_1     1 
              702  LOAD_CODE                <code_object count_nonzero>
              704  LOAD_STR                 'count_nonzero'
              706  MAKE_FUNCTION_3          'default, keyword-only'
              708  CALL_FUNCTION_1       1  ''
              710  STORE_NAME               count_nonzero

 L. 498       712  LOAD_NAME                set_module
              714  LOAD_STR                 'numpy'
              716  CALL_FUNCTION_1       1  ''

 L. 499       718  LOAD_CODE                <code_object isfortran>
              720  LOAD_STR                 'isfortran'
              722  MAKE_FUNCTION_0          'Neither defaults, keyword-only args, annotations, nor closures'
              724  CALL_FUNCTION_1       1  ''
              726  STORE_NAME               isfortran

 L. 566       728  LOAD_CODE                <code_object _argwhere_dispatcher>
              730  LOAD_STR                 '_argwhere_dispatcher'
              732  MAKE_FUNCTION_0          'Neither defaults, keyword-only args, annotations, nor closures'
              734  STORE_NAME               _argwhere_dispatcher

 L. 570       736  LOAD_NAME                array_function_dispatch
              738  LOAD_NAME                _argwhere_dispatcher
              740  CALL_FUNCTION_1       1  ''

 L. 571       742  LOAD_CODE                <code_object argwhere>
              744  LOAD_STR                 'argwhere'
              746  MAKE_FUNCTION_0          'Neither defaults, keyword-only args, annotations, nor closures'
              748  CALL_FUNCTION_1       1  ''
              750  STORE_NAME               argwhere

 L. 620       752  LOAD_CODE                <code_object _flatnonzero_dispatcher>
              754  LOAD_STR                 '_flatnonzero_dispatcher'
              756  MAKE_FUNCTION_0          'Neither defaults, keyword-only args, annotations, nor closures'
              758  STORE_NAME               _flatnonzero_dispatcher

 L. 624       760  LOAD_NAME                array_function_dispatch
              762  LOAD_NAME                _flatnonzero_dispatcher
              764  CALL_FUNCTION_1       1  ''

 L. 625       766  LOAD_CODE                <code_object flatnonzero>
              768  LOAD_STR                 'flatnonzero'
              770  MAKE_FUNCTION_0          'Neither defaults, keyword-only args, annotations, nor closures'
              772  CALL_FUNCTION_1       1  ''
              774  STORE_NAME               flatnonzero

 L. 665       776  LOAD_CONST               0

 L. 666       778  LOAD_CONST               1

 L. 667       780  LOAD_CONST               2

 L. 665       782  LOAD_CONST               ('v', 's', 'f')
              784  BUILD_CONST_KEY_MAP_3     3 
              786  STORE_NAME               _mode_from_name_dict

 L. 670       788  LOAD_CODE                <code_object _mode_from_name>
              790  LOAD_STR                 '_mode_from_name'
              792  MAKE_FUNCTION_0          'Neither defaults, keyword-only args, annotations, nor closures'
              794  STORE_NAME               _mode_from_name

 L. 676       796  LOAD_CONST               (None,)
              798  LOAD_CODE                <code_object _correlate_dispatcher>
              800  LOAD_STR                 '_correlate_dispatcher'
              802  MAKE_FUNCTION_1          'default'
              804  STORE_NAME               _correlate_dispatcher

 L. 680       806  LOAD_NAME                array_function_dispatch
              808  LOAD_NAME                _correlate_dispatcher
              810  CALL_FUNCTION_1       1  ''

 L. 681       812  LOAD_CONST               ('valid',)
              814  LOAD_CODE                <code_object correlate>
              816  LOAD_STR                 'correlate'
              818  MAKE_FUNCTION_1          'default'
              820  CALL_FUNCTION_1       1  ''
              822  STORE_NAME               correlate

 L. 749       824  LOAD_CONST               (None,)
              826  LOAD_CODE                <code_object _convolve_dispatcher>
              828  LOAD_STR                 '_convolve_dispatcher'
              830  MAKE_FUNCTION_1          'default'
              832  STORE_NAME               _convolve_dispatcher

 L. 753       834  LOAD_NAME                array_function_dispatch
              836  LOAD_NAME                _convolve_dispatcher
              838  CALL_FUNCTION_1       1  ''

 L. 754       840  LOAD_CONST               ('full',)
              842  LOAD_CODE                <code_object convolve>
              844  LOAD_STR                 'convolve'
              846  MAKE_FUNCTION_1          'default'
              848  CALL_FUNCTION_1       1  ''
              850  STORE_NAME               convolve

 L. 853       852  LOAD_CONST               (None,)
              854  LOAD_CODE                <code_object _outer_dispatcher>
              856  LOAD_STR                 '_outer_dispatcher'
              858  MAKE_FUNCTION_1          'default'
              860  STORE_NAME               _outer_dispatcher

 L. 857       862  LOAD_NAME                array_function_dispatch
              864  LOAD_NAME                _outer_dispatcher
              866  CALL_FUNCTION_1       1  ''

 L. 858       868  LOAD_CONST               (None,)
              870  LOAD_CODE                <code_object outer>
              872  LOAD_STR                 'outer'
              874  MAKE_FUNCTION_1          'default'
              876  CALL_FUNCTION_1       1  ''
              878  STORE_NAME               outer

 L. 945       880  LOAD_CONST               (None,)
              882  LOAD_CODE                <code_object _tensordot_dispatcher>
              884  LOAD_STR                 '_tensordot_dispatcher'
              886  MAKE_FUNCTION_1          'default'
              888  STORE_NAME               _tensordot_dispatcher

 L. 949       890  LOAD_NAME                array_function_dispatch
              892  LOAD_NAME                _tensordot_dispatcher
              894  CALL_FUNCTION_1       1  ''

 L. 950       896  LOAD_CONST               (2,)
              898  LOAD_CODE                <code_object tensordot>
              900  LOAD_STR                 'tensordot'
              902  MAKE_FUNCTION_1          'default'
              904  CALL_FUNCTION_1       1  ''
              906  STORE_NAME               tensordot

 L.1142       908  LOAD_CONST               (None,)
              910  LOAD_CODE                <code_object _roll_dispatcher>
              912  LOAD_STR                 '_roll_dispatcher'
              914  MAKE_FUNCTION_1          'default'
              916  STORE_NAME               _roll_dispatcher

 L.1146       918  LOAD_NAME                array_function_dispatch
              920  LOAD_NAME                _roll_dispatcher
              922  CALL_FUNCTION_1       1  ''

 L.1147       924  LOAD_CONST               (None,)
              926  LOAD_CODE                <code_object roll>
              928  LOAD_STR                 'roll'
              930  MAKE_FUNCTION_1          'default'
              932  CALL_FUNCTION_1       1  ''
              934  STORE_NAME               roll

 L.1247       936  LOAD_CONST               (None,)
              938  LOAD_CODE                <code_object _rollaxis_dispatcher>
              940  LOAD_STR                 '_rollaxis_dispatcher'
              942  MAKE_FUNCTION_1          'default'
              944  STORE_NAME               _rollaxis_dispatcher

 L.1251       946  LOAD_NAME                array_function_dispatch
              948  LOAD_NAME                _rollaxis_dispatcher
              950  CALL_FUNCTION_1       1  ''

 L.1252       952  LOAD_CONST               (0,)
              954  LOAD_CODE                <code_object rollaxis>
              956  LOAD_STR                 'rollaxis'
              958  MAKE_FUNCTION_1          'default'
              960  CALL_FUNCTION_1       1  ''
              962  STORE_NAME               rollaxis

 L.1341       964  LOAD_CONST               (None, False)
              966  LOAD_CODE                <code_object normalize_axis_tuple>
              968  LOAD_STR                 'normalize_axis_tuple'
              970  MAKE_FUNCTION_1          'default'
              972  STORE_NAME               normalize_axis_tuple

 L.1400       974  LOAD_CODE                <code_object _moveaxis_dispatcher>
              976  LOAD_STR                 '_moveaxis_dispatcher'
              978  MAKE_FUNCTION_0          'Neither defaults, keyword-only args, annotations, nor closures'
              980  STORE_NAME               _moveaxis_dispatcher

 L.1404       982  LOAD_NAME                array_function_dispatch
              984  LOAD_NAME                _moveaxis_dispatcher
              986  CALL_FUNCTION_1       1  ''

 L.1405       988  LOAD_CODE                <code_object moveaxis>
              990  LOAD_STR                 'moveaxis'
              992  MAKE_FUNCTION_0          'Neither defaults, keyword-only args, annotations, nor closures'
              994  CALL_FUNCTION_1       1  ''
              996  STORE_NAME               moveaxis

 L.1477       998  LOAD_CODE                <code_object _move_axis_to_0>
             1000  LOAD_STR                 '_move_axis_to_0'
             1002  MAKE_FUNCTION_0          'Neither defaults, keyword-only args, annotations, nor closures'
             1004  STORE_NAME               _move_axis_to_0

 L.1481      1006  LOAD_CONST               (None, None, None, None)
             1008  LOAD_CODE                <code_object _cross_dispatcher>
             1010  LOAD_STR                 '_cross_dispatcher'
             1012  MAKE_FUNCTION_1          'default'
             1014  STORE_NAME               _cross_dispatcher

 L.1485      1016  LOAD_NAME                array_function_dispatch
             1018  LOAD_NAME                _cross_dispatcher
             1020  CALL_FUNCTION_1       1  ''

 L.1486      1022  LOAD_CONST               (-1, -1, -1, None)
             1024  LOAD_CODE                <code_object cross>
             1026  LOAD_STR                 'cross'
             1028  MAKE_FUNCTION_1          'default'
             1030  CALL_FUNCTION_1       1  ''
             1032  STORE_NAME               cross

 L.1683      1034  LOAD_NAME                sys
             1036  LOAD_ATTR                byteorder
             1038  LOAD_STR                 'little'
             1040  COMPARE_OP               ==
             1042  STORE_NAME               little_endian

 L.1686      1044  LOAD_NAME                set_module
             1046  LOAD_STR                 'numpy'
             1048  CALL_FUNCTION_1       1  ''

 L.1687      1050  LOAD_NAME                int
             1052  LOAD_CONST               False
             1054  BUILD_TUPLE_2         2 
             1056  LOAD_CODE                <code_object indices>
             1058  LOAD_STR                 'indices'
             1060  MAKE_FUNCTION_1          'default'
             1062  CALL_FUNCTION_1       1  ''
             1064  STORE_NAME               indices

 L.1789      1066  LOAD_CONST               None
             1068  LOAD_CONST               None
             1070  LOAD_CONST               ('dtype', 'like')
             1072  BUILD_CONST_KEY_MAP_2     2 
             1074  LOAD_CODE                <code_object _fromfunction_dispatcher>
             1076  LOAD_STR                 '_fromfunction_dispatcher'
             1078  MAKE_FUNCTION_2          'keyword-only'
             1080  STORE_NAME               _fromfunction_dispatcher

 L.1793      1082  LOAD_NAME                set_array_function_like_doc

 L.1794      1084  LOAD_NAME                set_module
             1086  LOAD_STR                 'numpy'
             1088  CALL_FUNCTION_1       1  ''

 L.1795      1090  LOAD_NAME                float
             1092  LOAD_CONST               None
             1094  LOAD_CONST               ('dtype', 'like')
             1096  BUILD_CONST_KEY_MAP_2     2 
             1098  LOAD_CODE                <code_object fromfunction>
             1100  LOAD_STR                 'fromfunction'
             1102  MAKE_FUNCTION_2          'keyword-only'
             1104  CALL_FUNCTION_1       1  ''
             1106  CALL_FUNCTION_1       1  ''
             1108  STORE_NAME               fromfunction

 L.1856      1110  LOAD_NAME                array_function_dispatch

 L.1857      1112  LOAD_NAME                _fromfunction_dispatcher

 L.1856      1114  CALL_FUNCTION_1       1  ''

 L.1858      1116  LOAD_NAME                fromfunction

 L.1856      1118  CALL_FUNCTION_1       1  ''
             1120  STORE_NAME               _fromfunction_with_like

 L.1861      1122  LOAD_CODE                <code_object _frombuffer>
             1124  LOAD_STR                 '_frombuffer'
             1126  MAKE_FUNCTION_0          'Neither defaults, keyword-only args, annotations, nor closures'
             1128  STORE_NAME               _frombuffer

 L.1865      1130  LOAD_NAME                set_module
             1132  LOAD_STR                 'numpy'
             1134  CALL_FUNCTION_1       1  ''

 L.1866      1136  LOAD_CODE                <code_object isscalar>
             1138  LOAD_STR                 'isscalar'
             1140  MAKE_FUNCTION_0          'Neither defaults, keyword-only args, annotations, nor closures'
             1142  CALL_FUNCTION_1       1  ''
             1144  STORE_NAME               isscalar

 L.1946      1146  LOAD_NAME                set_module
             1148  LOAD_STR                 'numpy'
             1150  CALL_FUNCTION_1       1  ''

 L.1947      1152  LOAD_CONST               (None,)
             1154  LOAD_CODE                <code_object binary_repr>
             1156  LOAD_STR                 'binary_repr'
             1158  MAKE_FUNCTION_1          'default'
             1160  CALL_FUNCTION_1       1  ''
             1162  STORE_NAME               binary_repr

 L.2061      1164  LOAD_NAME                set_module
             1166  LOAD_STR                 'numpy'
             1168  CALL_FUNCTION_1       1  ''

 L.2062      1170  LOAD_CONST               (2, 0)
             1172  LOAD_CODE                <code_object base_repr>
             1174  LOAD_STR                 'base_repr'
             1176  MAKE_FUNCTION_1          'default'
             1178  CALL_FUNCTION_1       1  ''
             1180  STORE_NAME               base_repr

 L.2122      1182  LOAD_CODE                <code_object _maketup>
             1184  LOAD_STR                 '_maketup'
             1186  MAKE_FUNCTION_0          'Neither defaults, keyword-only args, annotations, nor closures'
             1188  STORE_NAME               _maketup

 L.2133      1190  LOAD_CONST               (None,)
             1192  LOAD_CONST               None
             1194  LOAD_CONST               ('like',)
             1196  BUILD_CONST_KEY_MAP_1     1 
             1198  LOAD_CODE                <code_object _identity_dispatcher>
             1200  LOAD_STR                 '_identity_dispatcher'
             1202  MAKE_FUNCTION_3          'default, keyword-only'
             1204  STORE_NAME               _identity_dispatcher

 L.2137      1206  LOAD_NAME                set_array_function_like_doc

 L.2138      1208  LOAD_NAME                set_module
             1210  LOAD_STR                 'numpy'
             1212  CALL_FUNCTION_1       1  ''

 L.2139      1214  LOAD_CONST               (None,)
             1216  LOAD_CONST               None
             1218  LOAD_CONST               ('like',)
             1220  BUILD_CONST_KEY_MAP_1     1 
             1222  LOAD_CODE                <code_object identity>
             1224  LOAD_STR                 'identity'
             1226  MAKE_FUNCTION_3          'default, keyword-only'
             1228  CALL_FUNCTION_1       1  ''
             1230  CALL_FUNCTION_1       1  ''
             1232  STORE_NAME               identity

 L.2177      1234  LOAD_NAME                array_function_dispatch

 L.2178      1236  LOAD_NAME                _identity_dispatcher

 L.2177      1238  CALL_FUNCTION_1       1  ''

 L.2179      1240  LOAD_NAME                identity

 L.2177      1242  CALL_FUNCTION_1       1  ''
             1244  STORE_NAME               _identity_with_like

 L.2182      1246  LOAD_CONST               (None, None, None)
             1248  LOAD_CODE                <code_object _allclose_dispatcher>
             1250  LOAD_STR                 '_allclose_dispatcher'
             1252  MAKE_FUNCTION_1          'default'
             1254  STORE_NAME               _allclose_dispatcher

 L.2186      1256  LOAD_NAME                array_function_dispatch
             1258  LOAD_NAME                _allclose_dispatcher
             1260  CALL_FUNCTION_1       1  ''

 L.2187      1262  LOAD_CONST               (1e-05, 1e-08, False)
             1264  LOAD_CODE                <code_object allclose>
             1266  LOAD_STR                 'allclose'
             1268  MAKE_FUNCTION_1          'default'
             1270  CALL_FUNCTION_1       1  ''
             1272  STORE_NAME               allclose

 L.2260      1274  LOAD_CONST               (None, None, None)
             1276  LOAD_CODE                <code_object _isclose_dispatcher>
             1278  LOAD_STR                 '_isclose_dispatcher'
             1280  MAKE_FUNCTION_1          'default'
             1282  STORE_NAME               _isclose_dispatcher

 L.2264      1284  LOAD_NAME                array_function_dispatch
             1286  LOAD_NAME                _isclose_dispatcher
             1288  CALL_FUNCTION_1       1  ''

 L.2265      1290  LOAD_CONST               (1e-05, 1e-08, False)
             1292  LOAD_CODE                <code_object isclose>
             1294  LOAD_STR                 'isclose'
             1296  MAKE_FUNCTION_1          'default'
             1298  CALL_FUNCTION_1       1  ''
             1300  STORE_NAME               isclose

 L.2388      1302  LOAD_CONST               (None,)
             1304  LOAD_CODE                <code_object _array_equal_dispatcher>
             1306  LOAD_STR                 '_array_equal_dispatcher'
             1308  MAKE_FUNCTION_1          'default'
             1310  STORE_NAME               _array_equal_dispatcher

 L.2392      1312  LOAD_NAME                array_function_dispatch
             1314  LOAD_NAME                _array_equal_dispatcher
             1316  CALL_FUNCTION_1       1  ''

 L.2393      1318  LOAD_CONST               (False,)
             1320  LOAD_CODE                <code_object array_equal>
             1322  LOAD_STR                 'array_equal'
             1324  MAKE_FUNCTION_1          'default'
             1326  CALL_FUNCTION_1       1  ''
             1328  STORE_NAME               array_equal

 L.2463      1330  LOAD_CODE                <code_object _array_equiv_dispatcher>
             1332  LOAD_STR                 '_array_equiv_dispatcher'
             1334  MAKE_FUNCTION_0          'Neither defaults, keyword-only args, annotations, nor closures'
             1336  STORE_NAME               _array_equiv_dispatcher

 L.2467      1338  LOAD_NAME                array_function_dispatch
             1340  LOAD_NAME                _array_equiv_dispatcher
             1342  CALL_FUNCTION_1       1  ''

 L.2468      1344  LOAD_CODE                <code_object array_equiv>
             1346  LOAD_STR                 'array_equiv'
             1348  MAKE_FUNCTION_0          'Neither defaults, keyword-only args, annotations, nor closures'
             1350  CALL_FUNCTION_1       1  ''
             1352  STORE_NAME               array_equiv

 L.2515      1354  LOAD_NAME                PINF
             1356  DUP_TOP          
             1358  STORE_NAME               Inf
             1360  DUP_TOP          
             1362  STORE_NAME               inf
             1364  DUP_TOP          
             1366  STORE_NAME               infty
             1368  STORE_NAME               Infinity

 L.2516      1370  LOAD_NAME                NAN
             1372  DUP_TOP          
             1374  STORE_NAME               nan
             1376  STORE_NAME               NaN

 L.2517      1378  LOAD_NAME                bool_
             1380  LOAD_CONST               False
             1382  CALL_FUNCTION_1       1  ''
             1384  STORE_NAME               False_

 L.2518      1386  LOAD_NAME                bool_
             1388  LOAD_CONST               True
             1390  CALL_FUNCTION_1       1  ''
             1392  STORE_NAME               True_

 L.2521      1394  LOAD_CODE                <code_object extend_all>
             1396  LOAD_STR                 'extend_all'
             1398  MAKE_FUNCTION_0          'Neither defaults, keyword-only args, annotations, nor closures'
             1400  STORE_NAME               extend_all

 L.2529      1402  LOAD_CONST               1
             1404  LOAD_CONST               ('*',)
             1406  IMPORT_NAME              umath
             1408  IMPORT_STAR      

 L.2530      1410  LOAD_CONST               1
             1412  LOAD_CONST               ('*',)
             1414  IMPORT_NAME              numerictypes
             1416  IMPORT_STAR      

 L.2531      1418  LOAD_CONST               1
             1420  LOAD_CONST               ('fromnumeric',)
             1422  IMPORT_NAME              
             1424  IMPORT_FROM              fromnumeric
             1426  STORE_NAME               fromnumeric
             1428  POP_TOP          

 L.2532      1430  LOAD_CONST               1
             1432  LOAD_CONST               ('*',)
             1434  IMPORT_NAME              fromnumeric
             1436  IMPORT_STAR      

 L.2533      1438  LOAD_CONST               1
             1440  LOAD_CONST               ('arrayprint',)
             1442  IMPORT_NAME              
             1444  IMPORT_FROM              arrayprint
             1446  STORE_NAME               arrayprint
             1448  POP_TOP          

 L.2534      1450  LOAD_CONST               1
             1452  LOAD_CONST               ('*',)
             1454  IMPORT_NAME              arrayprint
             1456  IMPORT_STAR      

 L.2535      1458  LOAD_CONST               1
             1460  LOAD_CONST               ('_asarray',)
             1462  IMPORT_NAME              
             1464  IMPORT_FROM              _asarray
             1466  STORE_NAME               _asarray
             1468  POP_TOP          

 L.2536      1470  LOAD_CONST               1
             1472  LOAD_CONST               ('*',)
             1474  IMPORT_NAME              _asarray
             1476  IMPORT_STAR      

 L.2537      1478  LOAD_CONST               1
             1480  LOAD_CONST               ('_ufunc_config',)
             1482  IMPORT_NAME              
             1484  IMPORT_FROM              _ufunc_config
             1486  STORE_NAME               _ufunc_config
             1488  POP_TOP          

 L.2538      1490  LOAD_CONST               1
             1492  LOAD_CONST               ('*',)
             1494  IMPORT_NAME              _ufunc_config
             1496  IMPORT_STAR      

 L.2539      1498  LOAD_NAME                extend_all
             1500  LOAD_NAME                fromnumeric
             1502  CALL_FUNCTION_1       1  ''
             1504  POP_TOP          

 L.2540      1506  LOAD_NAME                extend_all
             1508  LOAD_NAME                umath
             1510  CALL_FUNCTION_1       1  ''
             1512  POP_TOP          

 L.2541      1514  LOAD_NAME                extend_all
             1516  LOAD_NAME                numerictypes
             1518  CALL_FUNCTION_1       1  ''
             1520  POP_TOP          

 L.2542      1522  LOAD_NAME                extend_all
             1524  LOAD_NAME                arrayprint
             1526  CALL_FUNCTION_1       1  ''
             1528  POP_TOP          

 L.2543      1530  LOAD_NAME                extend_all
             1532  LOAD_NAME                _asarray
             1534  CALL_FUNCTION_1       1  ''
             1536  POP_TOP          

 L.2544      1538  LOAD_NAME                extend_all
             1540  LOAD_NAME                _ufunc_config
             1542  CALL_FUNCTION_1       1  ''
             1544  POP_TOP          

Parse error at or near `CALL_FINALLY' instruction at offset 448

Instruction context:
   
 L.  40       444  BUILD_LIST_0          0 
                 446  LOAD_CONST               ('newaxis', 'ndarray', 'flatiter', 'nditer', 'nested_iters', 'ufunc', 'arange', 'array', 'zeros', 'count_nonzero', 'empty', 'broadcast', 'dtype', 'fromstring', 'fromfile', 'frombuffer', 'where', 'argwhere', 'copyto', 'concatenate', 'fastCopyAndTranspose', 'lexsort', 'set_numeric_ops', 'can_cast', 'promote_types', 'min_scalar_type', 'result_type', 'isfortran', 'empty_like', 'zeros_like', 'ones_like', 'correlate', 'convolve', 'inner', 'dot', 'outer', 'vdot', 'roll', 'rollaxis', 'moveaxis', 'cross', 'tensordot', 'little_endian', 'fromiter', 'array_equal', 'array_equiv', 'indices', 'fromfunction', 'isclose', 'isscalar', 'binary_repr', 'base_repr', 'ones', 'identity', 'allclose', 'compare_chararrays', 'putmask', 'flatnonzero', 'Inf', 'inf', 'infty', 'Infinity', 'nan', 'NaN', 'False_', 'True_', 'bitwise_not', 'CLIP', 'RAISE', 'WRAP', 'MAXDIMS', 'BUFSIZE', 'ALLOW_THREADS', 'ComplexWarning', 'full', 'full_like', 'matmul', 'shares_memory', 'may_share_memory', 'MAY_SHARE_BOUNDS', 'MAY_SHARE_EXACT', 'TooHardError', 'AxisError')
->               448  CALL_FINALLY        451  'to 451'
                 450  STORE_NAME               __all__

test/4326.pyc -- 
# decompile failed
