Instruction context:
   
 L. 273        24  LOAD_FAST                'dtype'
                  26  LOAD_ATTR                names
                  28  LOAD_CONST               None
->                30  <117>                 1  ''
                  32  POP_JUMP_IF_FALSE    40  'to 40'
Instruction context:
   
 L. 326       146  LOAD_FAST                'name'
                 148  LOAD_STR                 ''
                 150  COMPARE_OP               ==
                 152  JUMP_IF_FALSE_OR_POP   174  'to 174'
                 154  LOAD_FAST                'dt'
                 156  LOAD_ATTR                type
                 158  LOAD_GLOBAL              numpy
                 160  LOAD_ATTR                void
->               162  <117>                 0  ''
                 164  JUMP_IF_FALSE_OR_POP   174  'to 174'
                 166  LOAD_FAST                'dt'
                 168  LOAD_ATTR                names
                 170  LOAD_CONST               None
                 172  <117>                 0  ''
               174_0  COME_FROM           164  '164'
               174_1  COME_FROM           152  '152'
                 174  STORE_FAST               'is_pad'
Instruction context:
   
 L. 371         8  LOAD_FAST                'version'
                  10  LOAD_CONST               None
->                12  <117>                 1  ''
                  14  POP_JUMP_IF_TRUE     20  'to 20'
                  16  <74>             
                  18  RAISE_VARARGS_1       1  'exception instance'
                20_0  COME_FROM            14  '14'
Instruction context:
   
 L. 397        14  DUP_TOP          
                  16  LOAD_GLOBAL              ValueError
->                18  <121>                30  ''
                  20  POP_TOP          
                  22  POP_TOP          
                  24  POP_TOP          
Instruction context:
   
 L. 436        78  LOAD_FAST                'version'
                  80  LOAD_CONST               None
->                82  <117>                 0  ''
                  84  POP_JUMP_IF_FALSE    96  'to 96'
Instruction context:
-> 
 L. 567       112  LOAD_FAST                'tokenize'
                 114  LOAD_METHOD              untokenize
                 116  LOAD_FAST                'tokens'
                 118  CALL_METHOD_1         1  ''
                 120  RETURN_VALUE     
Instruction context:
   
 L. 578        18  LOAD_FAST                'hinfo'
                  20  LOAD_CONST               None
->                22  <117>                 0  ''
                  24  POP_JUMP_IF_FALSE    40  'to 40'
Instruction context:
   
 L. 674        76  LOAD_FAST                'pickle_kwargs'
                  78  LOAD_CONST               None
->                80  <117>                 0  ''
                  82  POP_JUMP_IF_FALSE    88  'to 88'
Instruction context:
   
 L. 741        86  LOAD_FAST                'pickle_kwargs'
                  88  LOAD_CONST               None
->                90  <117>                 0  ''
                  92  POP_JUMP_IF_FALSE    98  'to 98'
Instruction context:
   
 L. 842        16  LOAD_STR                 'w'
                  18  LOAD_FAST                'mode'
->                20  <118>                 0  ''
                  22  POP_JUMP_IF_FALSE   150  'to 150'
Instruction context:
   
 L. 908        66  DUP_TOP          
                  68  LOAD_GLOBAL              io
                  70  LOAD_ATTR                BlockingIOError
->                72  <121>                84  ''
                  74  POP_TOP          
                  76  POP_TOP          
                  78  POP_TOP          

test/52839.pyc -- 
# decompile failed

# file test/52839.pyc
# Deparsing stopped due to parse error
