Instruction context:
-> 
 L. 112       220  LOAD_FAST                'result_path'
             222_224  POP_JUMP_IF_FALSE   278  'to 278'
                 226  LOAD_FAST                'result_path'
                 228  LOAD_CONST               0
                 230  BINARY_SUBSCR    
                 232  LOAD_FAST                'seps'
                 234  COMPARE_OP               not-in
             236_238  POP_JUMP_IF_FALSE   278  'to 278'
Instruction context:
   
 L. 572       122  POP_BLOCK        
->               124  POP_EXCEPT       
                 126  CALL_FINALLY        136  'to 136'
                 128  JUMP_FORWARD        174  'to 174'
               130_0  COME_FROM           120  '120'
Instruction context:
   
 L. 612        88  LOAD_FAST                'tail'
                  90  POP_JUMP_IF_FALSE   102  'to 102'
                  92  LOAD_GLOBAL              join
                  94  LOAD_FAST                'new_path'
                  96  LOAD_FAST                'tail'
                  98  CALL_FUNCTION_2       2  ''
                 100  JUMP_FORWARD        104  'to 104'
               102_0  COME_FROM            90  '90'
                 102  LOAD_FAST                'new_path'
               104_0  COME_FROM           100  '100'
                 104  POP_BLOCK        
->               106  ROT_FOUR         
                 108  POP_BLOCK        
                 110  POP_EXCEPT       
                 112  CALL_FINALLY        198  'to 198'
                 114  RETURN_VALUE     
               116_0  COME_FROM            86  '86'
                 116  POP_BLOCK        
                 118  JUMP_FORWARD        140  'to 140'
               120_0  COME_FROM_FINALLY    70  '70'

test/221.pyc -- 
# decompile failed

# file test/221.pyc
# Deparsing stopped due to parse error
