# uncompyle6 version 3.7.4
# Python bytecode 3.7 (3394)
# Decompiled from: Python 3.6.15 (default, Sep 28 2021, 20:18:52) 
# [GCC 10.2.1 20210110]
# Embedded file name: site-packages\youtube_dl\extractor\onet.py
from __future__ import unicode_literals
import re
from .common import InfoExtractor
from ..utils import determine_ext, ExtractorError, float_or_none, get_element_by_class, int_or_none, js_to_json, NO_DEFAULT, parse_iso8601, remove_start, strip_or_none, url_basename

class OnetBaseIE(InfoExtractor):
    _URL_BASE_RE = 'https?://(?:(?:www\\.)?onet\\.tv|onet100\\.vod\\.pl)/[a-z]/'

    def _search_mvp_id(self, webpage):
        return self._search_regex('id=(["\\\'])mvp:(?P<id>.+?)\\1',
          webpage, 'mvp id', group='id')

    def _extract_from_id--- This code section failed: ---

 L.  30         0  LOAD_FAST                'self'
                2  LOAD_ATTR                _download_json

 L.  31         4  LOAD_STR                 'http://qi.ckm.onetapi.pl/'
                6  LOAD_FAST                'video_id'

 L.  33         8  LOAD_FAST                'video_id'

 L.  34        10  LOAD_STR                 '2.0'

 L.  35        12  LOAD_STR                 'get_asset_detail'

 L.  36        14  LOAD_FAST                'video_id'

 L.  37        16  LOAD_STR                 'www.onet.pl'

 L.  38        18  LOAD_STR                 'application/jsonp'

 L.  39        20  LOAD_STR                 'player.front.onetapi.pl'
               22  LOAD_CONST               ('body[id]', 'body[jsonrpc]', 'body[method]', 'body[params][ID_Publikacji]', 'body[params][Service]', 'content-type', 'x-onet-app')
               24  BUILD_CONST_KEY_MAP_7     7 
               26  LOAD_CONST               ('query',)
               28  CALL_FUNCTION_KW_3     3  '3 total positional and keyword args'
               30  STORE_FAST               'response'

 L.  42        32  LOAD_FAST                'response'
               34  LOAD_METHOD              get
               36  LOAD_STR                 'error'
               38  CALL_METHOD_1         1  '1 positional argument'
               40  STORE_FAST               'error'

 L.  43        42  LOAD_FAST                'error'
               44  POP_JUMP_IF_FALSE    72  'to 72'

 L.  44        46  LOAD_GLOBAL              ExtractorError

 L.  45        48  LOAD_STR                 '%s said: %s'
               50  LOAD_FAST                'self'
               52  LOAD_ATTR                IE_NAME
               54  LOAD_FAST                'error'
               56  LOAD_STR                 'message'
               58  BINARY_SUBSCR    
               60  BUILD_TUPLE_2         2 
               62  BINARY_MODULO    
               64  LOAD_CONST               True
               66  LOAD_CONST               ('expected',)
               68  CALL_FUNCTION_KW_2     2  '2 total positional and keyword args'
               70  RAISE_VARARGS_1       1  'exception instance'
             72_0  COME_FROM            44  '44'

 L.  47        72  LOAD_FAST                'response'
               74  LOAD_STR                 'result'
               76  BINARY_SUBSCR    
               78  LOAD_METHOD              get
               80  LOAD_STR                 '0'
               82  CALL_METHOD_1         1  '1 positional argument'
               84  STORE_FAST               'video'

 L.  49        86  BUILD_LIST_0          0 
               88  STORE_FAST               'formats'

 L.  50     90_92  SETUP_LOOP          422  'to 422'
               94  LOAD_FAST                'video'
               96  LOAD_STR                 'formats'
               98  BINARY_SUBSCR    
              100  LOAD_METHOD              items
              102  CALL_METHOD_0         0  '0 positional arguments'
              104  GET_ITER         
          106_108  FOR_ITER            420  'to 420'
              110  UNPACK_SEQUENCE_2     2 
              112  STORE_FAST               'format_type'
              114  STORE_FAST               'formats_dict'

 L.  51       116  LOAD_GLOBAL              isinstance
              118  LOAD_FAST                'formats_dict'
              120  LOAD_GLOBAL              dict
              122  CALL_FUNCTION_2       2  '2 positional arguments'
              124  POP_JUMP_IF_TRUE    128  'to 128'

 L.  52       126  CONTINUE            106  'to 106'
            128_0  COME_FROM           124  '124'

 L.  53   128_130  SETUP_LOOP          418  'to 418'
              132  LOAD_FAST                'formats_dict'
              134  LOAD_METHOD              items
              136  CALL_METHOD_0         0  '0 positional arguments'
              138  GET_ITER         
          140_142  FOR_ITER            416  'to 416'
              144  UNPACK_SEQUENCE_2     2 
              146  STORE_FAST               'format_id'
              148  STORE_FAST               'format_list'

 L.  54       150  LOAD_GLOBAL              isinstance
              152  LOAD_FAST                'format_list'
              154  LOAD_GLOBAL              list
              156  CALL_FUNCTION_2       2  '2 positional arguments'
              158  POP_JUMP_IF_TRUE    162  'to 162'

 L.  55       160  CONTINUE            140  'to 140'
            162_0  COME_FROM           158  '158'

 L.  56       162  SETUP_LOOP          414  'to 414'
              164  LOAD_FAST                'format_list'
              166  GET_ITER         
              168  FOR_ITER            412  'to 412'
              170  STORE_FAST               'f'

 L.  57       172  LOAD_FAST                'f'
              174  LOAD_METHOD              get
              176  LOAD_STR                 'url'
              178  CALL_METHOD_1         1  '1 positional argument'
              180  STORE_FAST               'video_url'

 L.  58       182  LOAD_FAST                'video_url'
              184  POP_JUMP_IF_TRUE    188  'to 188'

 L.  59       186  CONTINUE            168  'to 168'
            188_0  COME_FROM           184  '184'

 L.  60       188  LOAD_GLOBAL              determine_ext
              190  LOAD_FAST                'video_url'
              192  CALL_FUNCTION_1       1  '1 positional argument'
              194  STORE_FAST               'ext'

 L.  61       196  LOAD_FAST                'format_id'
              198  LOAD_METHOD              startswith
              200  LOAD_STR                 'ism'
              202  CALL_METHOD_1         1  '1 positional argument'
              204  POP_JUMP_IF_FALSE   232  'to 232'

 L.  62       206  LOAD_FAST                'formats'
              208  LOAD_METHOD              extend
              210  LOAD_FAST                'self'
              212  LOAD_ATTR                _extract_ism_formats

 L.  63       214  LOAD_FAST                'video_url'
              216  LOAD_FAST                'video_id'
              218  LOAD_STR                 'mss'
              220  LOAD_CONST               False
              222  LOAD_CONST               ('fatal',)
              224  CALL_FUNCTION_KW_4     4  '4 total positional and keyword args'
              226  CALL_METHOD_1         1  '1 positional argument'
              228  POP_TOP          
              230  JUMP_BACK           168  'to 168'
            232_0  COME_FROM           204  '204'

 L.  64       232  LOAD_FAST                'ext'
              234  LOAD_STR                 'mpd'
              236  COMPARE_OP               ==
          238_240  POP_JUMP_IF_FALSE   268  'to 268'

 L.  65       242  LOAD_FAST                'formats'
              244  LOAD_METHOD              extend
              246  LOAD_FAST                'self'
              248  LOAD_ATTR                _extract_mpd_formats

 L.  66       250  LOAD_FAST                'video_url'
              252  LOAD_FAST                'video_id'
              254  LOAD_STR                 'dash'
              256  LOAD_CONST               False
              258  LOAD_CONST               ('mpd_id', 'fatal')
              260  CALL_FUNCTION_KW_4     4  '4 total positional and keyword args'
              262  CALL_METHOD_1         1  '1 positional argument'
              264  POP_TOP          
              266  JUMP_BACK           168  'to 168'
            268_0  COME_FROM           238  '238'

 L.  67       268  LOAD_FAST                'format_id'
              270  LOAD_METHOD              startswith
              272  LOAD_STR                 'hls'
              274  CALL_METHOD_1         1  '1 positional argument'
          276_278  POP_JUMP_IF_FALSE   310  'to 310'

 L.  68       280  LOAD_FAST                'formats'
              282  LOAD_METHOD              extend
              284  LOAD_FAST                'self'
              286  LOAD_ATTR                _extract_m3u8_formats

 L.  69       288  LOAD_FAST                'video_url'
              290  LOAD_FAST                'video_id'
              292  LOAD_STR                 'mp4'
              294  LOAD_STR                 'm3u8_native'

 L.  70       296  LOAD_STR                 'hls'
              298  LOAD_CONST               False
              300  LOAD_CONST               ('m3u8_id', 'fatal')
              302  CALL_FUNCTION_KW_6     6  '6 total positional and keyword args'
              304  CALL_METHOD_1         1  '1 positional argument'
              306  POP_TOP          
              308  JUMP_BACK           168  'to 168'
            310_0  COME_FROM           276  '276'

 L.  73       310  LOAD_FAST                'video_url'

 L.  74       312  LOAD_FAST                'format_id'

 L.  75       314  LOAD_GLOBAL              float_or_none
              316  LOAD_FAST                'f'
              318  LOAD_METHOD              get
              320  LOAD_STR                 'audio_bitrate'
              322  CALL_METHOD_1         1  '1 positional argument'
              324  CALL_FUNCTION_1       1  '1 positional argument'
              326  LOAD_CONST               ('url', 'format_id', 'abr')
              328  BUILD_CONST_KEY_MAP_3     3 
              330  STORE_FAST               'http_f'

 L.  77       332  LOAD_FAST                'format_type'
              334  LOAD_STR                 'audio'
              336  COMPARE_OP               ==
          338_340  POP_JUMP_IF_FALSE   352  'to 352'

 L.  78       342  LOAD_STR                 'none'
              344  LOAD_FAST                'http_f'
              346  LOAD_STR                 'vcodec'
              348  STORE_SUBSCR     
              350  JUMP_FORWARD        400  'to 400'
            352_0  COME_FROM           338  '338'

 L.  80       352  LOAD_FAST                'http_f'
              354  LOAD_METHOD              update

 L.  81       356  LOAD_GLOBAL              int_or_none
              358  LOAD_FAST                'f'
              360  LOAD_METHOD              get
              362  LOAD_STR                 'vertical_resolution'
              364  CALL_METHOD_1         1  '1 positional argument'
              366  CALL_FUNCTION_1       1  '1 positional argument'

 L.  82       368  LOAD_GLOBAL              int_or_none
              370  LOAD_FAST                'f'
              372  LOAD_METHOD              get
              374  LOAD_STR                 'horizontal_resolution'
              376  CALL_METHOD_1         1  '1 positional argument'
              378  CALL_FUNCTION_1       1  '1 positional argument'

 L.  83       380  LOAD_GLOBAL              float_or_none
              382  LOAD_FAST                'f'
              384  LOAD_METHOD              get
              386  LOAD_STR                 'video_bitrate'
              388  CALL_METHOD_1         1  '1 positional argument'
              390  CALL_FUNCTION_1       1  '1 positional argument'
              392  LOAD_CONST               ('height', 'width', 'vbr')
              394  BUILD_CONST_KEY_MAP_3     3 
              396  CALL_METHOD_1         1  '1 positional argument'
              398  POP_TOP          
            400_0  COME_FROM           350  '350'

 L.  85       400  LOAD_FAST                'formats'
              402  LOAD_METHOD              append
              404  LOAD_FAST                'http_f'
              406  CALL_METHOD_1         1  '1 positional argument'
              408  POP_TOP          
              410  JUMP_BACK           168  'to 168'
              412  POP_BLOCK        
            414_0  COME_FROM_LOOP      162  '162'
              414  JUMP_BACK           140  'to 140'
              416  POP_BLOCK        
            418_0  COME_FROM_LOOP      128  '128'
              418  JUMP_BACK           106  'to 106'
              420  POP_BLOCK        
            422_0  COME_FROM_LOOP       90  '90'

 L.  86       422  LOAD_FAST                'self'
              424  LOAD_METHOD              _sort_formats
              426  LOAD_FAST                'formats'
              428  CALL_METHOD_1         1  '1 positional argument'
              430  POP_TOP          

 L.  88       432  LOAD_FAST                'video'
              434  LOAD_METHOD              get
              436  LOAD_STR                 'meta'
              438  BUILD_MAP_0           0 
              440  CALL_METHOD_2         2  '2 positional arguments'
              442  STORE_FAST               'meta'

 L.  91       444  LOAD_FAST                'webpage'
          446_448  POP_JUMP_IF_FALSE   464  'to 464'
              450  LOAD_FAST                'self'
              452  LOAD_ATTR                _og_search_title
              454  LOAD_FAST                'webpage'
              456  LOAD_CONST               None
              458  LOAD_CONST               ('default',)
              460  CALL_FUNCTION_KW_2     2  '2 total positional and keyword args'
            462_0  COME_FROM           462  '462'
              462  JUMP_IF_TRUE_OR_POP   476  'to 476'
            464_0  COME_FROM           446  '446'
              464  LOAD_CONST               None
          466_468  JUMP_IF_TRUE_OR_POP   476  'to 476'
              470  LOAD_FAST                'meta'
              472  LOAD_STR                 'title'
              474  BINARY_SUBSCR    
            476_0  COME_FROM           466  '466'
              476  STORE_FAST               'title'

 L.  93       478  LOAD_FAST                'webpage'
          480_482  POP_JUMP_IF_FALSE   498  'to 498'
              484  LOAD_FAST                'self'
              486  LOAD_ATTR                _og_search_description
              488  LOAD_FAST                'webpage'
              490  LOAD_CONST               None
              492  LOAD_CONST               ('default',)
              494  CALL_FUNCTION_KW_2     2  '2 total positional and keyword args'
            496_0  COME_FROM           496  '496'
              496  JUMP_IF_TRUE_OR_POP   512  'to 512'
            498_0  COME_FROM           480  '480'
              498  LOAD_CONST               None
          500_502  JUMP_IF_TRUE_OR_POP   512  'to 512'
              504  LOAD_FAST                'meta'
              506  LOAD_METHOD              get
              508  LOAD_STR                 'description'
              510  CALL_METHOD_1         1  '1 positional argument'
            512_0  COME_FROM           500  '500'
              512  STORE_FAST               'description'

 L.  94       514  LOAD_FAST                'meta'
              516  LOAD_METHOD              get
              518  LOAD_STR                 'length'
              520  CALL_METHOD_1         1  '1 positional argument'
          522_524  JUMP_IF_TRUE_OR_POP   534  'to 534'
              526  LOAD_FAST                'meta'
              528  LOAD_METHOD              get
              530  LOAD_STR                 'lenght'
              532  CALL_METHOD_1         1  '1 positional argument'
            534_0  COME_FROM           522  '522'
              534  STORE_FAST               'duration'

 L.  95       536  LOAD_GLOBAL              parse_iso8601
              538  LOAD_FAST                'meta'
              540  LOAD_METHOD              get
              542  LOAD_STR                 'addDate'
              544  CALL_METHOD_1         1  '1 positional argument'
              546  LOAD_STR                 ' '
              548  CALL_FUNCTION_2       2  '2 positional arguments'
              550  STORE_FAST               'timestamp'

 L.  98       552  LOAD_FAST                'video_id'

 L.  99       554  LOAD_FAST                'title'

 L. 100       556  LOAD_FAST                'description'

 L. 101       558  LOAD_FAST                'duration'

 L. 102       560  LOAD_FAST                'timestamp'

 L. 103       562  LOAD_FAST                'formats'
              564  LOAD_CONST               ('id', 'title', 'description', 'duration', 'timestamp', 'formats')
              566  BUILD_CONST_KEY_MAP_6     6 
              568  RETURN_VALUE     
               -1  RETURN_LAST      

Parse error at or near `JUMP_IF_TRUE_OR_POP' instruction at offset 462


class OnetMVPIE(OnetBaseIE):
    _VALID_URL = 'onetmvp:(?P<id>\\d+\\.\\d+)'
    _TEST = {'url':'onetmvp:381027.1509591944', 
     'only_matching':True}

    def _real_extract(self, url):
        return self._extract_from_idself._match_idurl


class OnetIE(OnetBaseIE):
    _VALID_URL = OnetBaseIE._URL_BASE_RE + '[a-z]+/(?P<display_id>[0-9a-z-]+)/(?P<id>[0-9a-z]+)'
    IE_NAME = 'onet.tv'
    _TESTS = [
     {'url':'http://onet.tv/k/openerfestival/open-er-festival-2016-najdziwniejsze-wymagania-gwiazd/qbpyqc', 
      'md5':'436102770fb095c75b8bb0392d3da9ff', 
      'info_dict':{'id':'qbpyqc', 
       'display_id':'open-er-festival-2016-najdziwniejsze-wymagania-gwiazd', 
       'ext':'mp4', 
       'title':"Open'er Festival 2016: najdziwniejsze wymagania gwiazd", 
       'description':'Trzy samochody, których nigdy nie użyto, prywatne spa, hotel dekorowany czarnym suknem czy nielegalne używki. Organizatorzy koncertów i festiwali muszą stawać przed nie lada wyzwaniem zapraszając gwia...', 
       'upload_date':'20160705', 
       'timestamp':1467721580}},
     {'url':'https://onet100.vod.pl/k/openerfestival/open-er-festival-2016-najdziwniejsze-wymagania-gwiazd/qbpyqc', 
      'only_matching':True}]

    def _real_extract(self, url):
        mobj = re.matchself._VALID_URLurl
        display_id, video_id = mobj.group'display_id''id'
        webpage = self._download_webpageurldisplay_id
        mvp_id = self._search_mvp_idwebpage
        info_dict = self._extract_from_idmvp_idwebpage
        info_dict.update{'id':video_id, 
         'display_id':display_id}
        return info_dict


class OnetChannelIE(OnetBaseIE):
    _VALID_URL = OnetBaseIE._URL_BASE_RE + '(?P<id>[a-z]+)(?:[?#]|$)'
    IE_NAME = 'onet.tv:channel'
    _TESTS = [
     {'url':'http://onet.tv/k/openerfestival', 
      'info_dict':{'id':'openerfestival', 
       'title':"Open'er Festival", 
       'description':"Tak było na Open'er Festival 2016! Oglądaj nasze reportaże i wywiady z artystami."}, 
      'playlist_mincount':35},
     {'url':'https://onet100.vod.pl/k/openerfestival', 
      'only_matching':True}]

    def _real_extract(self, url):
        channel_id = self._match_idurl
        webpage = self._download_webpageurlchannel_id
        current_clip_info = self._parse_json((self._search_regex('var\\s+currentClip\\s*=\\s*({[^}]+})', webpage, 'video info')),
          channel_id, transform_source=(lambda s: js_to_json(re.sub("\\'\\s*\\+\\s*\\'", '', s))))
        video_id = remove_startcurrent_clip_info['ckmId']'mvp:'
        video_name = url_basename(current_clip_info['url'])
        if self._downloader.params.get'noplaylist':
            self.to_screen('Downloading just video %s because of --no-playlist' % video_name)
            return self._extract_from_idvideo_idwebpage
        self.to_screen('Downloading channel %s - add --no-playlist to just download video %s' % (
         channel_id, video_name))
        matches = re.findall('<a[^>]+href=[\\\'"](%s[a-z]+/[0-9a-z-]+/[0-9a-z]+)' % self._URL_BASE_RE)webpage
        entries = [self.url_resultvideo_linkOnetIE.ie_key for video_link in matches]
        channel_title = strip_or_none(get_element_by_class'o_channelName'webpage)
        channel_description = strip_or_none(get_element_by_class'o_channelDesc'webpage)
        return self.playlist_result(entries, channel_id, channel_title, channel_description)


class OnetPlIE(InfoExtractor):
    _VALID_URL = 'https?://(?:[^/]+\\.)?(?:onet|businessinsider\\.com|plejada)\\.pl/(?:[^/]+/)+(?P<id>[0-9a-z]+)'
    IE_NAME = 'onet.pl'
    _TESTS = [
     {'url':'http://eurosport.onet.pl/zimowe/skoki-narciarskie/ziobro-wygral-kwalifikacje-w-pjongczangu/9ckrly', 
      'md5':'b94021eb56214c3969380388b6e73cb0', 
      'info_dict':{'id':'1561707.1685479', 
       'ext':'mp4', 
       'title':'Ziobro wygrał kwalifikacje w Pjongczangu', 
       'description':'md5:61fb0740084d2d702ea96512a03585b4', 
       'upload_date':'20170214', 
       'timestamp':1487078046}},
     {'url':'http://film.onet.pl/pensjonat-nad-rozlewiskiem-relacja-z-planu-serialu/y428n0', 
      'info_dict':{'id':'501235.965429946', 
       'ext':'mp4', 
       'title':'"Pensjonat nad rozlewiskiem": relacja z planu serialu', 
       'upload_date':'20170622', 
       'timestamp':1498159955}, 
      'params':{'skip_download': True}},
     {'url':'http://film.onet.pl/zwiastuny/ghost-in-the-shell-drugi-zwiastun-pl/5q6yl3', 
      'only_matching':True},
     {'url':'http://moto.onet.pl/jak-wybierane-sa-miejsca-na-fotoradary/6rs04e', 
      'only_matching':True},
     {'url':'http://businessinsider.com.pl/wideo/scenariusz-na-koniec-swiata-wedlug-nasa/dwnqptk', 
      'only_matching':True},
     {'url':'http://plejada.pl/weronika-rosati-o-swoim-domniemanym-slubie/n2bq89', 
      'only_matching':True}]

    def _search_mvp_id(self, webpage, default=NO_DEFAULT):
        return self._search_regex('data-(?:params-)?mvp=["\\\'](\\d+\\.\\d+)',
          webpage, 'mvp id', default=default)

    def _real_extract(self, url):
        video_id = self._match_idurl
        webpage = self._download_webpageurlvideo_id
        mvp_id = self._search_mvp_id(webpage, default=None)
        if not mvp_id:
            pulsembed_url = self._search_regex('data-src=(["\\\'])(?P<url>(?:https?:)?//pulsembed\\.eu/.+?)\\1',
              webpage,
              'pulsembed url', group='url')
            webpage = self._download_webpage(pulsembed_url, video_id, 'Downloading pulsembed webpage')
            mvp_id = self._search_mvp_idwebpage
        return self.url_result(('onetmvp:%s' % mvp_id),
          (OnetMVPIE.ie_key), video_id=mvp_id)