# decompyle3 version 3.7.5
# Python bytecode 3.7 (3394)
# Decompiled from: Python 3.8.11 (default, Aug 17 2021, 15:56:41) 
# [GCC 10.2.1 20210110]
# Embedded file name: site-packages\youtube_dl\extractor\playtvak.py
from __future__ import unicode_literals
from .common import InfoExtractor
from ..compat import compat_urlparse, compat_urllib_parse_urlencode
from ..utils import ExtractorError, int_or_none, parse_iso8601, qualities

class PlaytvakIE(InfoExtractor):
    IE_DESC = 'Playtvak.cz, iDNES.cz and Lidovky.cz'
    _VALID_URL = 'https?://(?:.+?\\.)?(?:playtvak|idnes|lidovky|metro)\\.cz/.*\\?(?:c|idvideo)=(?P<id>[^&]+)'
    _TESTS = [
     {'url':'http://www.playtvak.cz/vyzente-vosy-a-srsne-ze-zahrady-dn5-/hodinovy-manzel.aspx?c=A150730_150323_hodinovy-manzel_kuko', 
      'md5':'4525ae312c324b4be2f4603cc78ceb4a', 
      'info_dict':{'id':'A150730_150323_hodinovy-manzel_kuko', 
       'ext':'mp4', 
       'title':'Vyžeňte vosy a sršně ze zahrady', 
       'description':'md5:4436e61b7df227a093778efb7e373571', 
       'thumbnail':'re:(?i)^https?://.*\\.(?:jpg|png)$', 
       'duration':279, 
       'timestamp':1438732860, 
       'upload_date':'20150805', 
       'is_live':False}},
     {'url':'http://slowtv.playtvak.cz/planespotting-0pr-/planespotting.aspx?c=A150624_164934_planespotting_cat', 
      'info_dict':{'id':'A150624_164934_planespotting_cat', 
       'ext':'flv', 
       'title':'re:^Planespotting [0-9]{4}-[0-9]{2}-[0-9]{2} [0-9]{2}:[0-9]{2}$', 
       'description':'Sledujte provoz na ranveji Letiště Václava Havla v Praze', 
       'is_live':True}, 
      'params':{'skip_download': True}},
     {'url':'https://slowtv.playtvak.cz/zive-sledujte-vlaky-v-primem-prenosu-dwi-/hlavni-nadrazi.aspx?c=A151218_145728_hlavni-nadrazi_plap', 
      'info_dict':{'id':'A151218_145728_hlavni-nadrazi_plap', 
       'ext':'flv', 
       'title':'re:^Hlavní nádraží [0-9]{4}-[0-9]{2}-[0-9]{2} [0-9]{2}:[0-9]{2}$', 
       'is_live':True}, 
      'params':{'skip_download': True}},
     {'url':'http://zpravy.idnes.cz/pes-zavreny-v-aute-rozbijeni-okynek-v-aute-fj5-/domaci.aspx?c=A150809_104116_domaci_pku', 
      'md5':'819832ba33cd7016e58a6658577fe289', 
      'info_dict':{'id':'A150809_104116_domaci_pku', 
       'ext':'mp4', 
       'title':'Zavřeli jsme mraženou pizzu do auta. Upekla se', 
       'description':'md5:01e73f02329e2e5760bd5eed4d42e3c2', 
       'thumbnail':'re:(?i)^https?://.*\\.(?:jpg|png)$', 
       'duration':39, 
       'timestamp':1438969140, 
       'upload_date':'20150807', 
       'is_live':False}},
     {'url':'http://www.lidovky.cz/dalsi-demonstrace-v-praze-o-migraci-duq-/video.aspx?c=A150808_214044_ln-video_ELE', 
      'md5':'c7209ac4ba9d234d4ad5bab7485bcee8', 
      'info_dict':{'id':'A150808_214044_ln-video_ELE', 
       'ext':'mp4', 
       'title':'Táhni! Demonstrace proti imigrantům budila emoce', 
       'description':'md5:97c81d589a9491fbfa323c9fa3cca72c', 
       'thumbnail':'re:(?i)^https?://.*\\.(?:jpg|png)$', 
       'timestamp':1439052180, 
       'upload_date':'20150808', 
       'is_live':False}},
     {'url':'http://www.metro.cz/video-pod-billboardem-se-na-vltavske-roztocil-kolotoc-deti-vozil-jen-par-hodin-1hx-/metro-extra.aspx?c=A141111_173251_metro-extra_row', 
      'md5':'84fc1deedcac37b7d4a6ccae7c716668', 
      'info_dict':{'id':'A141111_173251_metro-extra_row', 
       'ext':'mp4', 
       'title':'Recesisté udělali z billboardu kolotoč', 
       'description':'md5:7369926049588c3989a66c9c1a043c4c', 
       'thumbnail':'re:(?i)^https?://.*\\.(?:jpg|png)$', 
       'timestamp':1415725500, 
       'upload_date':'20141111', 
       'is_live':False}},
     {'url':'http://www.playtvak.cz/embed.aspx?idvideo=V150729_141549_play-porad_kuko', 
      'only_matching':True}]

    def _real_extract--- This code section failed: ---

 L. 103         0  LOAD_FAST                'self'
                2  LOAD_METHOD              _match_id
                4  LOAD_FAST                'url'
                6  CALL_METHOD_1         1  '1 positional argument'
                8  STORE_FAST               'video_id'

 L. 105        10  LOAD_FAST                'self'
               12  LOAD_METHOD              _download_webpage
               14  LOAD_FAST                'url'
               16  LOAD_FAST                'video_id'
               18  CALL_METHOD_2         2  '2 positional arguments'
               20  STORE_FAST               'webpage'

 L. 107        22  LOAD_FAST                'self'
               24  LOAD_METHOD              _html_search_regex

 L. 108        26  LOAD_STR                 'Misc\\.video(?:FLV)?\\(\\s*{\\s*data\\s*:\\s*"([^"]+)"'
               28  LOAD_FAST                'webpage'
               30  LOAD_STR                 'info url'
               32  CALL_METHOD_3         3  '3 positional arguments'
               34  STORE_FAST               'info_url'

 L. 110        36  LOAD_GLOBAL              compat_urlparse
               38  LOAD_METHOD              urlparse
               40  LOAD_FAST                'info_url'
               42  CALL_METHOD_1         1  '1 positional argument'
               44  STORE_FAST               'parsed_url'

 L. 112        46  LOAD_GLOBAL              compat_urlparse
               48  LOAD_METHOD              parse_qs
               50  LOAD_FAST                'parsed_url'
               52  LOAD_ATTR                query
               54  CALL_METHOD_1         1  '1 positional argument'
               56  STORE_FAST               'qs'

 L. 113        58  LOAD_FAST                'qs'
               60  LOAD_METHOD              update

 L. 114        62  LOAD_STR                 '0'
               64  BUILD_LIST_1          1 

 L. 115        66  LOAD_STR                 'js'
               68  BUILD_LIST_1          1 
               70  LOAD_CONST               ('reklama', 'type')
               72  BUILD_CONST_KEY_MAP_2     2 
               74  CALL_METHOD_1         1  '1 positional argument'
               76  POP_TOP          

 L. 118        78  LOAD_GLOBAL              compat_urlparse
               80  LOAD_METHOD              urlunparse

 L. 119        82  LOAD_FAST                'parsed_url'
               84  LOAD_ATTR                _replace
               86  LOAD_GLOBAL              compat_urllib_parse_urlencode
               88  LOAD_FAST                'qs'
               90  LOAD_CONST               True
               92  CALL_FUNCTION_2       2  '2 positional arguments'
               94  LOAD_CONST               ('query',)
               96  CALL_FUNCTION_KW_1     1  '1 total positional and keyword args'
               98  CALL_METHOD_1         1  '1 positional argument'
              100  STORE_FAST               'info_url'

 L. 121       102  LOAD_FAST                'self'
              104  LOAD_ATTR                _download_json

 L. 122       106  LOAD_FAST                'info_url'
              108  LOAD_FAST                'video_id'

 L. 123       110  LOAD_LAMBDA              '<code_object <lambda>>'
              112  LOAD_STR                 'PlaytvakIE._real_extract.<locals>.<lambda>'
              114  MAKE_FUNCTION_0          'Neither defaults, keyword-only args, annotations, nor closures'
              116  LOAD_CONST               ('transform_source',)
              118  CALL_FUNCTION_KW_3     3  '3 total positional and keyword args'
              120  STORE_FAST               'json_info'

 L. 125       122  LOAD_CONST               None
              124  STORE_FAST               'item'

 L. 126       126  SETUP_LOOP          178  'to 178'
              128  LOAD_FAST                'json_info'
              130  LOAD_STR                 'items'
              132  BINARY_SUBSCR    
              134  GET_ITER         
            136_0  COME_FROM           174  '174'
            136_1  COME_FROM           166  '166'
              136  FOR_ITER            176  'to 176'
              138  STORE_FAST               'i'

 L. 127       140  LOAD_FAST                'i'
              142  LOAD_METHOD              get
              144  LOAD_STR                 'type'
              146  CALL_METHOD_1         1  '1 positional argument'
              148  LOAD_STR                 'video'
              150  COMPARE_OP               ==
              152  POP_JUMP_IF_TRUE    168  'to 168'
              154  LOAD_FAST                'i'
              156  LOAD_METHOD              get
              158  LOAD_STR                 'type'
              160  CALL_METHOD_1         1  '1 positional argument'
              162  LOAD_STR                 'stream'
              164  COMPARE_OP               ==
              166  POP_JUMP_IF_FALSE_BACK   136  'to 136'
            168_0  COME_FROM           152  '152'

 L. 128       168  LOAD_FAST                'i'
              170  STORE_FAST               'item'

 L. 129       172  BREAK_LOOP       
              174  JUMP_BACK           136  'to 136'
              176  POP_BLOCK        
            178_0  COME_FROM_LOOP      126  '126'

 L. 130       178  LOAD_FAST                'item'
              180  POP_JUMP_IF_TRUE    190  'to 190'

 L. 131       182  LOAD_GLOBAL              ExtractorError
              184  LOAD_STR                 'No suitable stream found'
              186  CALL_FUNCTION_1       1  '1 positional argument'
              188  RAISE_VARARGS_1       1  'exception instance'
            190_0  COME_FROM           180  '180'

 L. 133       190  LOAD_GLOBAL              qualities
              192  LOAD_CONST               ('low', 'middle', 'high')
              194  CALL_FUNCTION_1       1  '1 positional argument'
              196  STORE_FAST               'quality'

 L. 135       198  BUILD_LIST_0          0 
              200  STORE_FAST               'formats'

 L. 136       202  SETUP_LOOP          362  'to 362'
              204  LOAD_FAST                'item'
              206  LOAD_STR                 'video'
              208  BINARY_SUBSCR    
              210  GET_ITER         
            212_0  COME_FROM           358  '358'
            212_1  COME_FROM           324  '324'
            212_2  COME_FROM           320  '320'
            212_3  COME_FROM           318  '318'
            212_4  COME_FROM           230  '230'
              212  FOR_ITER            360  'to 360'
              214  STORE_FAST               'fmt'

 L. 137       216  LOAD_FAST                'fmt'
              218  LOAD_METHOD              get
              220  LOAD_STR                 'file'
              222  CALL_METHOD_1         1  '1 positional argument'
              224  STORE_FAST               'video_url'

 L. 138       226  LOAD_FAST                'video_url'
              228  POP_JUMP_IF_TRUE    232  'to 232'

 L. 139       230  CONTINUE            212  'to 212'
            232_0  COME_FROM           228  '228'

 L. 141       232  LOAD_FAST                'fmt'
              234  LOAD_STR                 'format'
              236  BINARY_SUBSCR    
              238  STORE_FAST               'format_'

 L. 142       240  LOAD_STR                 '%s_%s'
              242  LOAD_FAST                'format_'
              244  LOAD_FAST                'fmt'
              246  LOAD_STR                 'quality'
              248  BINARY_SUBSCR    
              250  BUILD_TUPLE_2         2 
              252  BINARY_MODULO    
              254  STORE_FAST               'format_id'

 L. 143       256  LOAD_CONST               None
              258  STORE_FAST               'preference'

 L. 145       260  LOAD_FAST                'format_'
              262  LOAD_CONST               ('mp4', 'webm')
              264  COMPARE_OP               in
          266_268  POP_JUMP_IF_FALSE   276  'to 276'

 L. 146       270  LOAD_FAST                'format_'
              272  STORE_FAST               'ext'
              274  JUMP_FORWARD        326  'to 326'
            276_0  COME_FROM           266  '266'

 L. 147       276  LOAD_FAST                'format_'
              278  LOAD_STR                 'rtmp'
              280  COMPARE_OP               ==
          282_284  POP_JUMP_IF_FALSE   292  'to 292'

 L. 148       286  LOAD_STR                 'flv'
              288  STORE_FAST               'ext'
              290  JUMP_FORWARD        326  'to 326'
            292_0  COME_FROM           282  '282'

 L. 149       292  LOAD_FAST                'format_'
              294  LOAD_STR                 'apple'
              296  COMPARE_OP               ==
          298_300  POP_JUMP_IF_FALSE   312  'to 312'

 L. 150       302  LOAD_STR                 'mp4'
              304  STORE_FAST               'ext'

 L. 153       306  LOAD_CONST               -1
              308  STORE_FAST               'preference'
              310  JUMP_FORWARD        326  'to 326'
            312_0  COME_FROM           298  '298'

 L. 154       312  LOAD_FAST                'format_'
              314  LOAD_STR                 'adobe'
              316  COMPARE_OP               ==
              318  POP_JUMP_IF_FALSE_BACK   212  'to 212'

 L. 155       320  CONTINUE            212  'to 212'
              322  JUMP_FORWARD        326  'to 326'

 L. 157       324  CONTINUE            212  'to 212'
            326_0  COME_FROM           322  '322'
            326_1  COME_FROM           310  '310'
            326_2  COME_FROM           290  '290'
            326_3  COME_FROM           274  '274'

 L. 159       326  LOAD_FAST                'formats'
              328  LOAD_METHOD              append

 L. 160       330  LOAD_FAST                'video_url'

 L. 161       332  LOAD_FAST                'ext'

 L. 162       334  LOAD_FAST                'format_id'

 L. 163       336  LOAD_FAST                'quality'
              338  LOAD_FAST                'fmt'
              340  LOAD_METHOD              get
              342  LOAD_STR                 'quality'
              344  CALL_METHOD_1         1  '1 positional argument'
              346  CALL_FUNCTION_1       1  '1 positional argument'

 L. 164       348  LOAD_FAST                'preference'
              350  LOAD_CONST               ('url', 'ext', 'format_id', 'quality', 'preference')
              352  BUILD_CONST_KEY_MAP_5     5 
              354  CALL_METHOD_1         1  '1 positional argument'
              356  POP_TOP          
              358  JUMP_BACK           212  'to 212'
              360  POP_BLOCK        
            362_0  COME_FROM_LOOP      202  '202'

 L. 166       362  LOAD_FAST                'self'
              364  LOAD_METHOD              _sort_formats
              366  LOAD_FAST                'formats'
              368  CALL_METHOD_1         1  '1 positional argument'
              370  POP_TOP          

 L. 168       372  LOAD_FAST                'item'
              374  LOAD_STR                 'title'
              376  BINARY_SUBSCR    
              378  STORE_FAST               'title'

 L. 169       380  LOAD_FAST                'item'
              382  LOAD_STR                 'type'
              384  BINARY_SUBSCR    
              386  LOAD_STR                 'stream'
              388  COMPARE_OP               ==
              390  STORE_FAST               'is_live'

 L. 170       392  LOAD_FAST                'is_live'
          394_396  POP_JUMP_IF_FALSE   408  'to 408'

 L. 171       398  LOAD_FAST                'self'
              400  LOAD_METHOD              _live_title
              402  LOAD_FAST                'title'
              404  CALL_METHOD_1         1  '1 positional argument'
              406  STORE_FAST               'title'
            408_0  COME_FROM           394  '394'

 L. 172       408  LOAD_FAST                'self'
              410  LOAD_ATTR                _og_search_description
              412  LOAD_FAST                'webpage'
              414  LOAD_CONST               None
              416  LOAD_CONST               ('default',)
              418  CALL_FUNCTION_KW_2     2  '2 total positional and keyword args'
          420_422  JUMP_IF_TRUE_OR_POP   440  'to 440'
              424  LOAD_FAST                'self'
              426  LOAD_ATTR                _html_search_meta

 L. 173       428  LOAD_STR                 'description'
              430  LOAD_FAST                'webpage'
              432  LOAD_STR                 'description'
              434  LOAD_CONST               None
              436  LOAD_CONST               ('default',)
              438  CALL_FUNCTION_KW_4     4  '4 total positional and keyword args'
            440_0  COME_FROM           420  '420'
              440  STORE_FAST               'description'

 L. 174       442  LOAD_CONST               None
              444  STORE_FAST               'timestamp'

 L. 175       446  LOAD_CONST               None
              448  STORE_FAST               'duration'

 L. 176       450  LOAD_FAST                'is_live'
          452_454  POP_JUMP_IF_TRUE    502  'to 502'

 L. 177       456  LOAD_GLOBAL              int_or_none
              458  LOAD_FAST                'item'
              460  LOAD_METHOD              get
              462  LOAD_STR                 'length'
              464  CALL_METHOD_1         1  '1 positional argument'
              466  CALL_FUNCTION_1       1  '1 positional argument'
              468  STORE_FAST               'duration'

 L. 178       470  LOAD_FAST                'item'
              472  LOAD_METHOD              get
              474  LOAD_STR                 'published'
              476  CALL_METHOD_1         1  '1 positional argument'
              478  STORE_FAST               'timestamp'

 L. 179       480  LOAD_FAST                'timestamp'
          482_484  POP_JUMP_IF_FALSE   502  'to 502'

 L. 180       486  LOAD_GLOBAL              parse_iso8601
              488  LOAD_FAST                'timestamp'
              490  LOAD_CONST               None
              492  LOAD_CONST               -5
              494  BUILD_SLICE_2         2 
              496  BINARY_SUBSCR    
              498  CALL_FUNCTION_1       1  '1 positional argument'
              500  STORE_FAST               'timestamp'
            502_0  COME_FROM           482  '482'
            502_1  COME_FROM           452  '452'

 L. 183       502  LOAD_FAST                'video_id'

 L. 184       504  LOAD_FAST                'title'

 L. 185       506  LOAD_FAST                'description'

 L. 186       508  LOAD_FAST                'item'
              510  LOAD_METHOD              get
              512  LOAD_STR                 'image'
              514  CALL_METHOD_1         1  '1 positional argument'

 L. 187       516  LOAD_FAST                'duration'

 L. 188       518  LOAD_FAST                'timestamp'

 L. 189       520  LOAD_FAST                'is_live'

 L. 190       522  LOAD_FAST                'formats'
              524  LOAD_CONST               ('id', 'title', 'description', 'thumbnail', 'duration', 'timestamp', 'is_live', 'formats')
              526  BUILD_CONST_KEY_MAP_8     8 
              528  RETURN_VALUE     
               -1  RETURN_LAST      

Parse error at or near `JUMP_FORWARD' instruction at offset 322