Instruction context:
   
 L. 212        52  DUP_TOP          
                  54  LOAD_GLOBAL              OSError
                  56  COMPARE_OP               exception-match
                  58  POP_JUMP_IF_FALSE    72  'to 72'
                  60  POP_TOP          
->                62  POP_TOP          
                  64  POP_TOP          
Instruction context:
   
 L. 264       232  LOAD_FAST                'dst'
                 234  POP_BLOCK        
->               236  POP_BLOCK        
                 238  ROT_TWO          
                 240  BEGIN_FINALLY    
                 242  WITH_CLEANUP_START
                 244  WITH_CLEANUP_FINISH
                 246  POP_FINALLY           0  ''
                 248  POP_BLOCK        
                 250  ROT_TWO          
                 252  BEGIN_FINALLY    
                 254  WITH_CLEANUP_START
                 256  WITH_CLEANUP_FINISH
                 258  POP_FINALLY           0  ''
                 260  RETURN_VALUE     
               262_0  COME_FROM_FINALLY   216  '216'
Instruction context:
   
 L. 318        60  POP_BLOCK        
                  62  POP_EXCEPT       
->                64  CALL_FINALLY         70  'to 70'
                  66  LOAD_CONST               None
                  68  RETURN_VALUE     
                70_0  COME_FROM            64  '64'
                70_1  COME_FROM_FINALLY    34  '34'
                  70  LOAD_CONST               None
                  72  STORE_FAST               'e'
                  74  DELETE_FAST              'e'
                  76  END_FINALLY      
                  78  POP_EXCEPT       
                  80  JUMP_FORWARD         84  'to 84'
                82_0  COME_FROM            26  '26'
                  82  END_FINALLY      
                84_0  COME_FROM            80  '80'
                84_1  COME_FROM            18  '18'
Instruction context:
   
 L. 478       258  POP_BLOCK        
->               260  JUMP_BACK            74  'to 74'
               262_0  COME_FROM           254  '254'
               262_1  COME_FROM           248  '248'
Instruction context:
   
 L. 547        44  LOAD_CONST               ('entries', 'src', 'dst', 'symlinks', 'ignore', 'copy_function', 'ignore_dangling_symlinks', 'dirs_exist_ok')
                  46  CALL_FUNCTION_KW_8     8  '8 total positional and keyword args'
                  48  POP_BLOCK        
->                50  ROT_TWO          
                  52  BEGIN_FINALLY    
                  54  WITH_CLEANUP_START
                  56  WITH_CLEANUP_FINISH
                  58  POP_FINALLY           0  ''
                  60  RETURN_VALUE     
                62_0  COME_FROM_WITH       22  '22'
                  62  WITH_CLEANUP_START
                  64  WITH_CLEANUP_FINISH
Instruction context:
   
 L. 562        54  DUP_TOP          
                  56  LOAD_GLOBAL              OSError
                  58  COMPARE_OP               exception-match
                  60  POP_JUMP_IF_FALSE    74  'to 74'
                  62  POP_TOP          
->                64  POP_TOP          
                  66  POP_TOP          
Instruction context:
   
 L. 571        50  DUP_TOP          
                  52  LOAD_GLOBAL              OSError
                  54  COMPARE_OP               exception-match
                  56  POP_JUMP_IF_FALSE    70  'to 70'
                  58  POP_TOP          
->                60  POP_TOP          
                  62  POP_TOP          
Instruction context:
   
 L. 577        16  DUP_TOP          
                  18  LOAD_GLOBAL              OSError
                  20  COMPARE_OP               exception-match
                  22  POP_JUMP_IF_FALSE    36  'to 36'
                  24  POP_TOP          
->                26  POP_TOP          
                  28  POP_TOP          
Instruction context:
   
 L. 602       156  POP_EXCEPT       
                 158  JUMP_BACK            82  'to 82'
->               160  POP_EXCEPT       
                 162  JUMP_FORWARD        166  'to 166'
               164_0  COME_FROM           128  '128'
                 164  END_FINALLY      
               166_0  COME_FROM           162  '162'
               166_1  COME_FROM           120  '120'
Instruction context:
   
 L. 622        76  POP_BLOCK        
                  78  POP_EXCEPT       
->                80  CALL_FINALLY         86  'to 86'
                  82  LOAD_CONST               None
                  84  RETURN_VALUE     
                86_0  COME_FROM            80  '80'
                86_1  COME_FROM_FINALLY    50  '50'
                  86  LOAD_CONST               None
                  88  STORE_FAST               'err'
                  90  DELETE_FAST              'err'
                  92  END_FINALLY      
                  94  POP_EXCEPT       
                  96  JUMP_FORWARD        100  'to 100'
                98_0  COME_FROM            42  '42'
                  98  END_FINALLY      
               100_0  COME_FROM            96  '96'
               100_1  COME_FROM            34  '34'
Instruction context:
   
 L. 700       116  POP_EXCEPT       
->               118  LOAD_CONST               None
                 120  RETURN_VALUE     
               122_0  COME_FROM            90  '90'
                 122  END_FINALLY      
               124_0  COME_FROM            82  '82'

../test/112159.pyc -- 
# decompile failed

# file ../test/112159.pyc
# Deparsing stopped due to parse error
