Instruction context:
   
 L. 492        16  DUP_TOP          
                  18  LOAD_GLOBAL              Exception
                  20  COMPARE_OP               exception-match
                  22  POP_JUMP_IF_FALSE    34  'to 34'
                  24  POP_TOP          
->                26  POP_TOP          
                  28  POP_TOP          
Instruction context:
   
 L. 645       110  LOAD_CLOSURE             'attr_selector'
                 112  BUILD_TUPLE_1         1 
->               114  LOAD_DICTCOMP            '<code_object <dictcomp>>'
                 116  LOAD_STR                 'Browser.select_form.<locals>.<dictcomp>'
                 118  MAKE_FUNCTION_8          'closure'
Instruction context:
   
 L. 789        42  DUP_TOP          
                  44  LOAD_GLOBAL              StopIteration
                  46  COMPARE_OP               exception-match
                  48  POP_JUMP_IF_FALSE    66  'to 66'
                  50  POP_TOP          
->                52  POP_TOP          
                  54  POP_TOP          
Instruction context:
   
 L. 853       272  LOAD_FAST                'orig_nr'
->               274  STORE_FAST               'nr'

../test/118215.pyc -- 
# decompile failed

# file ../test/118215.pyc
# Deparsing stopped due to parse error
