Instruction context:
   
 L. 195        56  GET_ITER         
                  58  CALL_FUNCTION_1       1  ''
                  60  POP_BLOCK        
->                62  ROT_TWO          
                  64  BEGIN_FINALLY    
                  66  WITH_CLEANUP_START
                  68  WITH_CLEANUP_FINISH
                  70  POP_FINALLY           0  ''
                  72  RETURN_VALUE     
                74_0  COME_FROM_WITH       26  '26'
                  74  WITH_CLEANUP_START
                  76  WITH_CLEANUP_FINISH
Instruction context:
   
 L. 353        26  POP_BLOCK        
->                28  BEGIN_FINALLY    
                  30  WITH_CLEANUP_START
                  32  WITH_CLEANUP_FINISH
                  34  POP_FINALLY           0  ''
                  36  LOAD_CONST               None
                  38  RETURN_VALUE     
                40_0  COME_FROM            24  '24'
Instruction context:
   
 L. 364        32  LOAD_GLOBAL              set
                  34  CALL_FUNCTION_0       0  ''
                  36  POP_BLOCK        
->                38  ROT_TWO          
                  40  BEGIN_FINALLY    
                  42  WITH_CLEANUP_START
                  44  WITH_CLEANUP_FINISH
                  46  POP_FINALLY           0  ''
                  48  RETURN_VALUE     
                50_0  COME_FROM            30  '30'
Instruction context:
   
 L. 472         8  LOAD_FAST                'self'
                  10  LOAD_ATTR                _session_pool
                  12  LOAD_METHOD              pop_all
                  14  CALL_METHOD_0         0  ''
                  16  POP_BLOCK        
->                18  ROT_TWO          
                  20  BEGIN_FINALLY    
                  22  WITH_CLEANUP_START
                  24  WITH_CLEANUP_FINISH
                  26  POP_FINALLY           0  ''
                  28  RETURN_VALUE     
                30_0  COME_FROM_WITH        4  '4'
                  30  WITH_CLEANUP_START
                  32  WITH_CLEANUP_FINISH
Instruction context:
   
 L. 497       116  LOAD_FAST                'self'
                 118  LOAD_ATTR                _session_pool
                 120  LOAD_METHOD              get_server_session
                 122  LOAD_FAST                'session_timeout'
                 124  CALL_METHOD_1         1  ''
                 126  POP_BLOCK        
->               128  ROT_TWO          
                 130  BEGIN_FINALLY    
                 132  WITH_CLEANUP_START
                 134  WITH_CLEANUP_FINISH
                 136  POP_FINALLY           0  ''
                 138  RETURN_VALUE     
               140_0  COME_FROM_WITH        4  '4'
                 140  WITH_CLEANUP_START
                 142  WITH_CLEANUP_FINISH

../test/118304.pyc -- 
# decompile failed

# file ../test/118304.pyc
# Deparsing stopped due to parse error
