# uncompyle6 version 3.7.4
# Python bytecode 3.8 (3413)
# Decompiled from: Python 3.6.15 (default, Sep 28 2021, 20:18:52) 
# [GCC 10.2.1 20210110]
# Embedded file name: chardet\jpcntx.py
jp2CharContext = ((0, 0, 0, 2, 0, 0, 0, 0, 0, 0, 0, 0, 0, 0, 0, 0, 0, 0, 0, 0, 0, 0, 0, 0, 0, 0, 0, 0, 0, 0, 0, 0, 0, 0, 0, 0, 0, 0, 0, 1, 0, 0, 0, 0, 0, 0, 0, 0, 0, 0, 0, 0, 0, 0, 0, 0, 0, 0, 0, 0, 0, 0, 0, 0, 0, 0, 0, 1, 0, 0, 0, 1, 0, 0, 0, 0, 0, 0, 0, 0, 0, 0, 1),
                  (2, 4, 0, 4, 0, 3, 0, 4, 0, 3, 4, 4, 4, 2, 4, 3, 3, 4, 3, 2, 3, 3, 4, 2, 3, 3, 3, 2, 4, 1, 4, 3, 3, 1, 5, 4, 3, 4, 3, 4, 3, 5, 3, 0, 3, 5, 4, 2, 0, 3, 1, 0, 3, 3, 0, 3, 3, 0, 1, 1, 0, 4, 3, 0, 3, 3, 0, 4, 0, 2, 0, 3, 5, 5, 5, 5, 4, 0, 4, 1, 0, 3, 4),
                  (0, 0, 1, 0, 0, 0, 0, 0, 0, 0, 0, 0, 0, 0, 0, 0, 0, 0, 0, 0, 0, 0, 0, 0, 0, 0, 0, 0, 0, 0, 0, 0, 0, 0, 1, 0, 0, 0, 0, 0, 0, 0, 0, 0, 0, 0, 0, 0, 0, 0, 0, 0, 0, 0, 0, 0, 0, 0, 0, 0, 0, 0, 0, 0, 0, 0, 0, 0, 0, 0, 0, 0, 0, 0, 0, 0, 0, 0, 0, 0, 0, 0, 2),
                  (0, 4, 0, 5, 0, 5, 0, 4, 0, 4, 5, 4, 4, 3, 5, 3, 5, 1, 5, 3, 4, 3, 4, 4, 3, 4, 3, 3, 4, 3, 5, 4, 4, 3, 5, 5, 3, 5, 5, 5, 3, 5, 5, 3, 4, 5, 5, 3, 1, 3, 2, 0, 3, 4, 0, 4, 2, 0, 4, 2, 1, 5, 3, 2, 3, 5, 0, 4, 0, 2, 0, 5, 4, 4, 5, 4, 5, 0, 4, 0, 0, 4, 4),
                  (0, 0, 0, 0, 0, 0, 0, 0, 0, 0, 0, 0, 0, 0, 0, 0, 0, 0, 0, 0, 0, 0, 0, 0, 0, 0, 0, 0, 0, 0, 0, 0, 0, 0, 0, 0, 0, 0, 0, 0, 0, 0, 0, 0, 0, 0, 0, 0, 0, 0, 0, 0, 0, 0, 0, 0, 0, 0, 0, 0, 0, 0, 0, 0, 0, 0, 0, 0, 0, 0, 0, 0, 0, 0, 0, 0, 0, 0, 0, 0, 0, 0, 0),
                  (0, 3, 0, 4, 0, 3, 0, 3, 0, 4, 5, 4, 3, 3, 3, 3, 4, 3, 5, 4, 4, 3, 5, 4, 4, 3, 4, 3, 4, 4, 4, 4, 5, 3, 4, 4, 3, 4, 5, 5, 4, 5, 5, 1, 4, 5, 4, 3, 0, 3, 3, 1, 3, 3, 0, 4, 4, 0, 3, 3, 1, 5, 3, 3, 3, 5, 0, 4, 0, 3, 0, 4, 4, 3, 4, 3, 3, 0, 4, 1, 1, 3, 4),
                  (0, 0, 0, 0, 0, 0, 0, 0, 0, 0, 0, 0, 0, 0, 0, 0, 0, 0, 0, 0, 0, 0, 0, 0, 0, 0, 0, 0, 0, 0, 0, 0, 0, 0, 1, 0, 0, 0, 0, 0, 0, 0, 0, 0, 0, 0, 0, 0, 0, 0, 0, 0, 0, 0, 0, 0, 0, 0, 0, 0, 0, 0, 0, 0, 0, 0, 0, 0, 0, 0, 0, 0, 0, 0, 0, 0, 0, 0, 0, 0, 0, 0, 0),
                  (0, 4, 0, 3, 0, 3, 0, 4, 0, 3, 4, 4, 3, 2, 2, 1, 2, 1, 3, 1, 3, 3, 3, 3, 3, 4, 3, 1, 3, 3, 5, 3, 3, 0, 4, 3, 0, 5, 4, 3, 3, 5, 4, 4, 3, 4, 4, 5, 0, 1, 2, 0, 1, 2, 0, 2, 2, 0, 1, 0, 0, 5, 2, 2, 1, 4, 0, 3, 0, 1, 0, 4, 4, 3, 5, 4, 3, 0, 2, 1, 0, 4, 3),
                  (0, 0, 0, 0, 0, 0, 0, 0, 0, 0, 0, 0, 0, 0, 0, 0, 0, 0, 0, 0, 0, 0, 0, 0, 0, 0, 0, 0, 0, 0, 0, 0, 0, 0, 0, 0, 0, 0, 0, 1, 0, 0, 0, 0, 0, 0, 0, 0, 0, 0, 0, 0, 0, 0, 0, 0, 0, 0, 0, 0, 0, 0, 0, 0, 0, 0, 0, 0, 0, 0, 0, 0, 0, 0, 0, 0, 0, 0, 0, 0, 0, 0, 0),
                  (0, 3, 0, 5, 0, 4, 0, 2, 1, 4, 4, 2, 4, 1, 4, 2, 4, 2, 4, 3, 3, 3, 4, 3, 3, 3, 3, 1, 4, 2, 3, 3, 3, 1, 4, 4, 1, 1, 1, 4, 3, 3, 2, 0, 2, 4, 3, 2, 0, 3, 3, 0, 3, 1, 1, 0, 0, 0, 3, 3, 0, 4, 2, 2, 3, 4, 0, 4, 0, 3, 0, 4, 4, 5, 3, 4, 4, 0, 3, 0, 0, 1, 4),
                  (1, 4, 0, 4, 0, 4, 0, 4, 0, 3, 5, 4, 4, 3, 4, 3, 5, 4, 3, 3, 4, 3, 5, 4, 4, 4, 4, 3, 4, 2, 4, 3, 3, 1, 5, 4, 3, 2, 4, 5, 4, 5, 5, 4, 4, 5, 4, 4, 0, 3, 2, 2, 3, 3, 0, 4, 3, 1, 3, 2, 1, 4, 3, 3, 4, 5, 0, 3, 0, 2, 0, 4, 5, 5, 4, 5, 4, 0, 4, 0, 0, 5, 4),
                  (0, 5, 0, 5, 0, 4, 0, 3, 0, 4, 4, 3, 4, 3, 3, 3, 4, 0, 4, 4, 4, 3, 4, 3, 4, 3, 3, 1, 4, 2, 4, 3, 4, 0, 5, 4, 1, 4, 5, 4, 4, 5, 3, 2, 4, 3, 4, 3, 2, 4, 1, 3, 3, 3, 2, 3, 2, 0, 4, 3, 3, 4, 3, 3, 3, 4, 0, 4, 0, 3, 0, 4, 5, 4, 4, 4, 3, 0, 4, 1, 0, 1, 3),
                  (0, 3, 1, 4, 0, 3, 0, 2, 0, 3, 4, 4, 3, 1, 4, 2, 3, 3, 4, 3, 4, 3, 4, 3, 4, 4, 3, 2, 3, 1, 5, 4, 4, 1, 4, 4, 3, 5, 4, 4, 3, 5, 5, 4, 3, 4, 4, 3, 1, 2, 3, 1, 2, 2, 0, 3, 2, 0, 3, 1, 0, 5, 3, 3, 3, 4, 3, 3, 3, 3, 4, 4, 4, 4, 5, 4, 2, 0, 3, 3, 2, 4, 3),
                  (0, 2, 0, 3, 0, 1, 0, 1, 0, 0, 3, 2, 0, 0, 2, 0, 1, 0, 2, 1, 3, 3, 3, 1, 2, 3, 1, 0, 1, 0, 4, 2, 1, 1, 3, 3, 0, 4, 3, 3, 1, 4, 3, 3, 0, 3, 3, 2, 0, 0, 0, 0, 1, 0, 0, 2, 0, 0, 0, 0, 0, 4, 1, 0, 2, 3, 2, 2, 2, 1, 3, 3, 3, 4, 4, 3, 2, 0, 3, 1, 0, 3, 3),
                  (0, 4, 0, 4, 0, 3, 0, 3, 0, 4, 4, 4, 3, 3, 3, 3, 3, 3, 4, 3, 4, 2, 4, 3, 4, 3, 3, 2, 4, 3, 4, 5, 4, 1, 4, 5, 3, 5, 4, 5, 3, 5, 4, 0, 3, 5, 5, 3, 1, 3, 3, 2, 2, 3, 0, 3, 4, 1, 3, 3, 2, 4, 3, 3, 3, 4, 0, 4, 0, 3, 0, 4, 5, 4, 4, 5, 3, 0, 4, 1, 0, 3, 4),
                  (0, 2, 0, 3, 0, 3, 0, 0, 0, 2, 2, 2, 1, 0, 1, 0, 0, 0, 3, 0, 3, 0, 3, 0, 1, 3, 1, 0, 3, 1, 3, 3, 3, 1, 3, 3, 3, 0, 1, 3, 1, 3, 4, 0, 0, 3, 1, 1, 0, 3, 2, 0, 0, 0, 0, 1, 3, 0, 1, 0, 0, 3, 3, 2, 0, 3, 0, 0, 0, 0, 0, 3, 4, 3, 4, 3, 3, 0, 3, 0, 0, 2, 3),
                  (2, 3, 0, 3, 0, 2, 0, 1, 0, 3, 3, 4, 3, 1, 3, 1, 1, 1, 3, 1, 4, 3, 4, 3, 3, 3, 0, 0, 3, 1, 5, 4, 3, 1, 4, 3, 2, 5, 5, 4, 4, 4, 4, 3, 3, 4, 4, 4, 0, 2, 1, 1, 3, 2, 0, 1, 2, 0, 0, 1, 0, 4, 1, 3, 3, 3, 0, 3, 0, 1, 0, 4, 4, 4, 5, 5, 3, 0, 2, 0, 0, 4, 4),
                  (0, 2, 0, 1, 0, 3, 1, 3, 0, 2, 3, 3, 3, 0, 3, 1, 0, 0, 3, 0, 3, 2, 3, 1, 3, 2, 1, 1, 0, 0, 4, 2, 1, 0, 2, 3, 1, 4, 3, 2, 0, 4, 4, 3, 1, 3, 1, 3, 0, 1, 0, 0, 1, 0, 0, 0, 1, 0, 0, 0, 0, 4, 1, 1, 1, 2, 0, 3, 0, 0, 0, 3, 4, 2, 4, 3, 2, 0, 1, 0, 0, 3, 3),
                  (0, 1, 0, 4, 0, 5, 0, 4, 0, 2, 4, 4, 2, 3, 3, 2, 3, 3, 5, 3, 3, 3, 4, 3, 4, 2, 3, 0, 4, 3, 3, 3, 4, 1, 4, 3, 2, 1, 5, 5, 3, 4, 5, 1, 3, 5, 4, 2, 0, 3, 3, 0, 1, 3, 0, 4, 2, 0, 1, 3, 1, 4, 3, 3, 3, 3, 0, 3, 0, 1, 0, 3, 4, 4, 4, 5, 5, 0, 3, 0, 1, 4, 5),
                  (0, 2, 0, 3, 0, 3, 0, 0, 0, 2, 3, 1, 3, 0, 4, 0, 1, 1, 3, 0, 3, 4, 3, 2, 3, 1, 0, 3, 3, 2, 3, 1, 3, 0, 2, 3, 0, 2, 1, 4, 1, 2, 2, 0, 0, 3, 3, 0, 0, 2, 0, 0, 0, 1, 0, 0, 0, 0, 2, 2, 0, 3, 2, 1, 3, 3, 0, 2, 0, 2, 0, 0, 3, 3, 1, 2, 4, 0, 3, 0, 2, 2, 3),
                  (2, 4, 0, 5, 0, 4, 0, 4, 0, 2, 4, 4, 4, 3, 4, 3, 3, 3, 1, 2, 4, 3, 4, 3, 4, 4, 5, 0, 3, 3, 3, 3, 2, 0, 4, 3, 1, 4, 3, 4, 1, 4, 4, 3, 3, 4, 4, 3, 1, 2, 3, 0, 4, 2, 0, 4, 1, 0, 3, 3, 0, 4, 3, 3, 3, 4, 0, 4, 0, 2, 0, 3, 5, 3, 4, 5, 2, 0, 3, 0, 0, 4, 5),
                  (0, 3, 0, 4, 0, 1, 0, 1, 0, 1, 3, 2, 2, 1, 3, 0, 3, 0, 2, 0, 2, 0, 3, 0, 2, 0, 0, 0, 1, 0, 1, 1, 0, 0, 3, 1, 0, 0, 0, 4, 0, 3, 1, 0, 2, 1, 3, 0, 0, 0, 0, 0, 0, 3, 0, 0, 0, 0, 0, 0, 0, 4, 2, 2, 3, 1, 0, 3, 0, 0, 0, 1, 4, 4, 4, 3, 0, 0, 4, 0, 0, 1, 4),
                  (1, 4, 1, 5, 0, 3, 0, 3, 0, 4, 5, 4, 4, 3, 5, 3, 3, 4, 4, 3, 4, 1, 3, 3, 3, 3, 2, 1, 4, 1, 5, 4, 3, 1, 4, 4, 3, 5, 4, 4, 3, 5, 4, 3, 3, 4, 4, 4, 0, 3, 3, 1, 2, 3, 0, 3, 1, 0, 3, 3, 0, 5, 4, 4, 4, 4, 4, 4, 3, 3, 5, 4, 4, 3, 3, 5, 4, 0, 3, 2, 0, 4, 4),
                  (0, 2, 0, 3, 0, 1, 0, 0, 0, 1, 3, 3, 3, 2, 4, 1, 3, 0, 3, 1, 3, 0, 2, 2, 1, 1, 0, 0, 2, 0, 4, 3, 1, 0, 4, 3, 0, 4, 4, 4, 1, 4, 3, 1, 1, 3, 3, 1, 0, 2, 0, 0, 1, 3, 0, 0, 0, 0, 2, 0, 0, 4, 3, 2, 4, 3, 5, 4, 3, 3, 3, 4, 3, 3, 4, 3, 3, 0, 2, 1, 0, 3, 3),
                  (0, 2, 0, 4, 0, 3, 0, 2, 0, 2, 5, 5, 3, 4, 4, 4, 4, 1, 4, 3, 3, 0, 4, 3, 4, 3, 1, 3, 3, 2, 4, 3, 0, 3, 4, 3, 0, 3, 4, 4, 2, 4, 4, 0, 4, 5, 3, 3, 2, 2, 1, 1, 1, 2, 0, 1, 5, 0, 3, 3, 2, 4, 3, 3, 3, 4, 0, 3, 0, 2, 0, 4, 4, 3, 5, 5, 0, 0, 3, 0, 2, 3, 3),
                  (0, 3, 0, 4, 0, 3, 0, 1, 0, 3, 4, 3, 3, 1, 3, 3, 3, 0, 3, 1, 3, 0, 4, 3, 3, 1, 1, 0, 3, 0, 3, 3, 0, 0, 4, 4, 0, 1, 5, 4, 3, 3, 5, 0, 3, 3, 4, 3, 0, 2, 0, 1, 1, 1, 0, 1, 3, 0, 1, 2, 1, 3, 3, 2, 3, 3, 0, 3, 0, 1, 0, 1, 3, 3, 4, 4, 1, 0, 1, 2, 2, 1, 3),
                  (0, 1, 0, 4, 0, 4, 0, 3, 0, 1, 3, 3, 3, 2, 3, 1, 1, 0, 3, 0, 3, 3, 4, 3, 2, 4, 2, 0, 1, 0, 4, 3, 2, 0, 4, 3, 0, 5, 3, 3, 2, 4, 4, 4, 3, 3, 3, 4, 0, 1, 3, 0, 0, 1, 0, 0, 1, 0, 0, 0, 0, 4, 2, 3, 3, 3, 0, 3, 0, 0, 0, 4, 4, 4, 5, 3, 2, 0, 3, 3, 0, 3, 5),
                  (0, 2, 0, 3, 0, 0, 0, 3, 0, 1, 3, 0, 2, 0, 0, 0, 1, 0, 3, 1, 1, 3, 3, 0, 0, 3, 0, 0, 3, 0, 2, 3, 1, 0, 3, 1, 0, 3, 3, 2, 0, 4, 2, 2, 0, 2, 0, 0, 0, 4, 0, 0, 0, 0, 0, 0, 0, 0, 0, 0, 0, 2, 1, 2, 0, 1, 0, 1, 0, 0, 0, 1, 3, 1, 2, 0, 0, 0, 1, 0, 0, 1, 4),
                  (0, 3, 0, 3, 0, 5, 0, 1, 0, 2, 4, 3, 1, 3, 3, 2, 1, 1, 5, 2, 1, 0, 5, 1, 2, 0, 0, 0, 3, 3, 2, 2, 3, 2, 4, 3, 0, 0, 3, 3, 1, 3, 3, 0, 2, 5, 3, 4, 0, 3, 3, 0, 1, 2, 0, 2, 2, 0, 3, 2, 0, 2, 2, 3, 3, 3, 0, 2, 0, 1, 0, 3, 4, 4, 2, 5, 4, 0, 3, 0, 0, 3, 5),
                  (0, 3, 0, 3, 0, 3, 0, 1, 0, 3, 3, 3, 3, 0, 3, 0, 2, 0, 2, 1, 1, 0, 2, 0, 1, 0, 0, 0, 2, 1, 0, 0, 1, 0, 3, 2, 0, 0, 3, 3, 1, 2, 3, 1, 0, 3, 3, 0, 0, 1, 0, 0, 0, 0, 0, 2, 0, 0, 0, 0, 0, 2, 3, 1, 2, 3, 0, 3, 0, 1, 0, 3, 2, 1, 0, 4, 3, 0, 1, 1, 0, 3, 3),
                  (0, 4, 0, 5, 0, 3, 0, 3, 0, 4, 5, 5, 4, 3, 5, 3, 4, 3, 5, 3, 3, 2, 5, 3, 4, 4, 4, 3, 4, 3, 4, 5, 5, 3, 4, 4, 3, 4, 4, 5, 4, 4, 4, 3, 4, 5, 5, 4, 2, 3, 4, 2, 3, 4, 0, 3, 3, 1, 4, 3, 2, 4, 3, 3, 5, 5, 0, 3, 0, 3, 0, 5, 5, 5, 5, 4, 4, 0, 4, 0, 1, 4, 4),
                  (0, 4, 0, 4, 0, 3, 0, 3, 0, 3, 5, 4, 4, 2, 3, 2, 5, 1, 3, 2, 5, 1, 4, 2, 3, 2, 3, 3, 4, 3, 3, 3, 3, 2, 5, 4, 1, 3, 3, 5, 3, 4, 4, 0, 4, 4, 3, 1, 1, 3, 1, 0, 2, 3, 0, 2, 3, 0, 3, 0, 0, 4, 3, 1, 3, 4, 0, 3, 0, 2, 0, 4, 4, 4, 3, 4, 5, 0, 4, 0, 0, 3, 4),
                  (0, 3, 0, 3, 0, 3, 1, 2, 0, 3, 4, 4, 3, 3, 3, 0, 2, 2, 4, 3, 3, 1, 3, 3, 3, 1, 1, 0, 3, 1, 4, 3, 2, 3, 4, 4, 2, 4, 4, 4, 3, 4, 4, 3, 2, 4, 4, 3, 1, 3, 3, 1, 3, 3, 0, 4, 1, 0, 2, 2, 1, 4, 3, 2, 3, 3, 5, 4, 3, 3, 5, 4, 4, 3, 3, 0, 4, 0, 3, 2, 2, 4, 4),
                  (0, 2, 0, 1, 0, 0, 0, 0, 0, 1, 2, 1, 3, 0, 0, 0, 0, 0, 2, 0, 1, 2, 1, 0, 0, 1, 0, 0, 0, 0, 3, 0, 0, 1, 0, 1, 1, 3, 1, 0, 0, 0, 1, 1, 0, 1, 1, 0, 0, 0, 0, 0, 2, 0, 0, 0, 0, 0, 0, 0, 0, 1, 1, 2, 2, 0, 3, 4, 0, 0, 0, 1, 1, 0, 0, 1, 0, 0, 0, 0, 0, 1, 1),
                  (0, 1, 0, 0, 0, 1, 0, 0, 0, 0, 4, 0, 4, 1, 4, 0, 3, 0, 4, 0, 3, 0, 4, 0, 3, 0, 3, 0, 4, 1, 5, 1, 4, 0, 0, 3, 0, 5, 0, 5, 2, 0, 1, 0, 0, 0, 2, 1, 4, 0, 1, 3, 0, 0, 3, 0, 0, 3, 1, 1, 4, 1, 0, 0, 0, 0, 0, 0, 0, 0, 0, 0, 0, 0, 1, 0, 0, 0, 0, 0, 0, 0, 0),
                  (1, 4, 0, 5, 0, 3, 0, 2, 0, 3, 5, 4, 4, 3, 4, 3, 5, 3, 4, 3, 3, 0, 4, 3, 3, 3, 3, 3, 3, 2, 4, 4, 3, 1, 3, 4, 4, 5, 4, 4, 3, 4, 4, 1, 3, 5, 4, 3, 3, 3, 1, 2, 2, 3, 3, 1, 3, 1, 3, 3, 3, 5, 3, 3, 4, 5, 0, 3, 0, 3, 0, 3, 4, 3, 4, 4, 3, 0, 3, 0, 2, 4, 3),
                  (0, 1, 0, 4, 0, 0, 0, 0, 0, 1, 4, 0, 4, 1, 4, 2, 4, 0, 3, 0, 1, 0, 1, 0, 0, 0, 0, 0, 2, 0, 3, 1, 1, 1, 0, 3, 0, 0, 0, 1, 2, 1, 0, 0, 1, 1, 1, 1, 0, 1, 0, 0, 0, 1, 0, 0, 3, 0, 0, 0, 0, 3, 2, 0, 2, 2, 0, 1, 0, 0, 0, 2, 3, 2, 3, 3, 0, 0, 0, 0, 2, 1, 0),
                  (0, 5, 1, 5, 0, 3, 0, 3, 0, 5, 4, 4, 5, 1, 5, 3, 3, 0, 4, 3, 4, 3, 5, 3, 4, 3, 3, 2, 4, 3, 4, 3, 3, 0, 3, 3, 1, 4, 4, 3, 4, 4, 4, 3, 4, 5, 5, 3, 2, 3, 1, 1, 3, 3, 1, 3, 1, 1, 3, 3, 2, 4, 5, 3, 3, 5, 0, 4, 0, 3, 0, 4, 4, 3, 5, 3, 3, 0, 3, 4, 0, 4, 3),
                  (0, 5, 0, 5, 0, 3, 0, 2, 0, 4, 4, 3, 5, 2, 4, 3, 3, 3, 4, 4, 4, 3, 5, 3, 5, 3, 3, 1, 4, 0, 4, 3, 3, 0, 3, 3, 0, 4, 4, 4, 4, 5, 4, 3, 3, 5, 5, 3, 2, 3, 1, 2, 3, 2, 0, 1, 0, 0, 3, 2, 2, 4, 4, 3, 1, 5, 0, 4, 0, 3, 0, 4, 3, 1, 3, 2, 1, 0, 3, 3, 0, 3, 3),
                  (0, 4, 0, 5, 0, 5, 0, 4, 0, 4, 5, 5, 5, 3, 4, 3, 3, 2, 5, 4, 4, 3, 5, 3, 5, 3, 4, 0, 4, 3, 4, 4, 3, 2, 4, 4, 3, 4, 5, 4, 4, 5, 5, 0, 3, 5, 5, 4, 1, 3, 3, 2, 3, 3, 1, 3, 1, 0, 4, 3, 1, 4, 4, 3, 4, 5, 0, 4, 0, 2, 0, 4, 3, 4, 4, 3, 3, 0, 4, 0, 0, 5, 5),
                  (0, 4, 0, 4, 0, 5, 0, 1, 1, 3, 3, 4, 4, 3, 4, 1, 3, 0, 5, 1, 3, 0, 3, 1, 3, 1, 1, 0, 3, 0, 3, 3, 4, 0, 4, 3, 0, 4, 4, 4, 3, 4, 4, 0, 3, 5, 4, 1, 0, 3, 0, 0, 2, 3, 0, 3, 1, 0, 3, 1, 0, 3, 2, 1, 3, 5, 0, 3, 0, 1, 0, 3, 2, 3, 3, 4, 4, 0, 2, 2, 0, 4, 4),
                  (2, 4, 0, 5, 0, 4, 0, 3, 0, 4, 5, 5, 4, 3, 5, 3, 5, 3, 5, 3, 5, 2, 5, 3, 4, 3, 3, 4, 3, 4, 5, 3, 2, 1, 5, 4, 3, 2, 3, 4, 5, 3, 4, 1, 2, 5, 4, 3, 0, 3, 3, 0, 3, 2, 0, 2, 3, 0, 4, 1, 0, 3, 4, 3, 3, 5, 0, 3, 0, 1, 0, 4, 5, 5, 5, 4, 3, 0, 4, 2, 0, 3, 5),
                  (0, 5, 0, 4, 0, 4, 0, 2, 0, 5, 4, 3, 4, 3, 4, 3, 3, 3, 4, 3, 4, 2, 5, 3, 5, 3, 4, 1, 4, 3, 4, 4, 4, 0, 3, 5, 0, 4, 4, 4, 4, 5, 3, 1, 3, 4, 5, 3, 3, 3, 3, 3, 3, 3, 0, 2, 2, 0, 3, 3, 2, 4, 3, 3, 3, 5, 3, 4, 1, 3, 3, 5, 3, 2, 0, 0, 0, 0, 4, 3, 1, 3, 3),
                  (0, 1, 0, 3, 0, 3, 0, 1, 0, 1, 3, 3, 3, 2, 3, 3, 3, 0, 3, 0, 0, 0, 3, 1, 3, 0, 0, 0, 2, 2, 2, 3, 0, 0, 3, 2, 0, 1, 2, 4, 1, 3, 3, 0, 0, 3, 3, 3, 0, 1, 0, 0, 2, 1, 0, 0, 3, 0, 3, 1, 0, 3, 0, 0, 1, 3, 0, 2, 0, 1, 0, 3, 3, 1, 3, 3, 0, 0, 1, 1, 0, 3, 3),
                  (0, 2, 0, 3, 0, 2, 1, 4, 0, 2, 2, 3, 1, 1, 3, 1, 1, 0, 2, 0, 3, 1, 2, 3, 1, 3, 0, 0, 1, 0, 4, 3, 2, 3, 3, 3, 1, 4, 2, 3, 3, 3, 3, 1, 0, 3, 1, 4, 0, 1, 1, 0, 1, 2, 0, 1, 1, 0, 1, 1, 0, 3, 1, 3, 2, 2, 0, 1, 0, 0, 0, 2, 3, 3, 3, 1, 0, 0, 0, 0, 0, 2, 3),
                  (0, 5, 0, 4, 0, 5, 0, 2, 0, 4, 5, 5, 3, 3, 4, 3, 3, 1, 5, 4, 4, 2, 4, 4, 4, 3, 4, 2, 4, 3, 5, 5, 4, 3, 3, 4, 3, 3, 5, 5, 4, 5, 5, 1, 3, 4, 5, 3, 1, 4, 3, 1, 3, 3, 0, 3, 3, 1, 4, 3, 1, 4, 5, 3, 3, 5, 0, 4, 0, 3, 0, 5, 3, 3, 1, 4, 3, 0, 4, 0, 1, 5, 3),
                  (0, 5, 0, 5, 0, 4, 0, 2, 0, 4, 4, 3, 4, 3, 3, 3, 3, 3, 5, 4, 4, 4, 4, 4, 4, 5, 3, 3, 5, 2, 4, 4, 4, 3, 4, 4, 3, 3, 4, 4, 5, 5, 3, 3, 4, 3, 4, 3, 3, 4, 3, 3, 3, 3, 1, 2, 2, 1, 4, 3, 3, 5, 4, 4, 3, 4, 0, 4, 0, 3, 0, 4, 4, 4, 4, 4, 1, 0, 4, 2, 0, 2, 4),
                  (0, 4, 0, 4, 0, 3, 0, 1, 0, 3, 5, 2, 3, 0, 3, 0, 2, 1, 4, 2, 3, 3, 4, 1, 4, 3, 3, 2, 4, 1, 3, 3, 3, 0, 3, 3, 0, 0, 3, 3, 3, 5, 3, 3, 3, 3, 3, 2, 0, 2, 0, 0, 2, 0, 0, 2, 0, 0, 1, 0, 0, 3, 1, 2, 2, 3, 0, 3, 0, 2, 0, 4, 4, 3, 3, 4, 1, 0, 3, 0, 0, 2, 4),
                  (0, 0, 0, 4, 0, 0, 0, 0, 0, 0, 1, 0, 1, 0, 2, 0, 0, 0, 0, 0, 1, 0, 2, 0, 1, 0, 0, 0, 0, 0, 3, 1, 3, 0, 3, 2, 0, 0, 0, 1, 0, 3, 2, 0, 0, 2, 0, 0, 0, 0, 0, 0, 0, 0, 0, 0, 0, 0, 0, 0, 0, 0, 0, 0, 0, 0, 0, 0, 0, 0, 0, 0, 3, 4, 0, 2, 0, 0, 0, 0, 0, 0, 2),
                  (0, 2, 1, 3, 0, 2, 0, 2, 0, 3, 3, 3, 3, 1, 3, 1, 3, 3, 3, 3, 3, 3, 4, 2, 2, 1, 2, 1, 4, 0, 4, 3, 1, 3, 3, 3, 2, 4, 3, 5, 4, 3, 3, 3, 3, 3, 3, 3, 0, 1, 3, 0, 2, 0, 0, 1, 0, 0, 1, 0, 0, 4, 2, 0, 2, 3, 0, 3, 3, 0, 3, 3, 4, 2, 3, 1, 4, 0, 1, 2, 0, 2, 3),
                  (0, 3, 0, 3, 0, 1, 0, 3, 0, 2, 3, 3, 3, 0, 3, 1, 2, 0, 3, 3, 2, 3, 3, 2, 3, 2, 3, 1, 3, 0, 4, 3, 2, 0, 3, 3, 1, 4, 3, 3, 2, 3, 4, 3, 1, 3, 3, 1, 1, 0, 1, 1, 0, 1, 0, 1, 0, 1, 0, 0, 0, 4, 1, 1, 0, 3, 0, 3, 1, 0, 2, 3, 3, 3, 3, 3, 1, 0, 0, 2, 0, 3, 3),
                  (0, 0, 0, 0, 0, 0, 0, 0, 0, 0, 3, 0, 2, 0, 3, 0, 0, 0, 0, 0, 0, 0, 3, 0, 0, 0, 0, 0, 0, 0, 3, 0, 3, 0, 3, 1, 0, 1, 0, 1, 0, 0, 1, 0, 0, 0, 0, 0, 0, 0, 0, 0, 0, 0, 0, 0, 0, 0, 0, 0, 0, 0, 0, 0, 0, 0, 0, 0, 3, 0, 2, 0, 2, 3, 0, 0, 0, 0, 0, 0, 0, 0, 3),
                  (0, 2, 0, 3, 1, 3, 0, 3, 0, 2, 3, 3, 3, 1, 3, 1, 3, 1, 3, 1, 3, 3, 3, 1, 3, 0, 2, 3, 1, 1, 4, 3, 3, 2, 3, 3, 1, 2, 2, 4, 1, 3, 3, 0, 1, 4, 2, 3, 0, 1, 3, 0, 3, 0, 0, 1, 3, 0, 2, 0, 0, 3, 3, 2, 1, 3, 0, 3, 0, 2, 0, 3, 4, 4, 4, 3, 1, 0, 3, 0, 0, 3, 3),
                  (0, 2, 0, 1, 0, 2, 0, 0, 0, 1, 3, 2, 2, 1, 3, 0, 1, 1, 3, 0, 3, 2, 3, 1, 2, 0, 2, 0, 1, 1, 3, 3, 3, 0, 3, 3, 1, 1, 2, 3, 2, 3, 3, 1, 2, 3, 2, 0, 0, 1, 0, 0, 0, 0, 0, 0, 3, 0, 1, 0, 0, 2, 1, 2, 1, 3, 0, 3, 0, 0, 0, 3, 4, 4, 4, 3, 2, 0, 2, 0, 0, 2, 4),
                  (0, 0, 0, 1, 0, 1, 0, 0, 0, 0, 1, 0, 0, 0, 1, 0, 0, 0, 0, 0, 0, 0, 1, 1, 1, 0, 0, 0, 0, 0, 0, 0, 0, 0, 2, 2, 0, 0, 0, 1, 0, 0, 0, 0, 0, 0, 0, 0, 0, 0, 0, 0, 0, 0, 0, 0, 0, 0, 0, 0, 0, 0, 0, 0, 0, 0, 0, 1, 0, 0, 0, 0, 1, 3, 1, 0, 0, 0, 0, 0, 0, 0, 3),
                  (0, 3, 0, 3, 0, 2, 0, 3, 0, 3, 3, 3, 2, 3, 2, 2, 2, 0, 3, 1, 3, 3, 3, 2, 3, 3, 0, 0, 3, 0, 3, 2, 2, 0, 2, 3, 1, 4, 3, 4, 3, 3, 2, 3, 1, 5, 4, 4, 0, 3, 1, 2, 1, 3, 0, 3, 1, 1, 2, 0, 2, 3, 1, 3, 1, 3, 0, 3, 0, 1, 0, 3, 3, 4, 4, 2, 1, 0, 2, 1, 0, 2, 4),
                  (0, 1, 0, 3, 0, 1, 0, 2, 0, 1, 4, 2, 5, 1, 4, 0, 2, 0, 2, 1, 3, 1, 4, 0, 2, 1, 0, 0, 2, 1, 4, 1, 1, 0, 3, 3, 0, 5, 1, 3, 2, 3, 3, 1, 0, 3, 2, 3, 0, 1, 0, 0, 0, 0, 0, 0, 1, 0, 0, 0, 0, 4, 0, 1, 0, 3, 0, 2, 0, 1, 0, 3, 3, 3, 4, 3, 3, 0, 0, 0, 0, 2, 3),
                  (0, 0, 0, 1, 0, 0, 0, 0, 0, 0, 2, 0, 1, 0, 0, 0, 0, 0, 1, 0, 0, 0, 0, 0, 0, 0, 0, 0, 0, 0, 3, 0, 0, 0, 0, 0, 0, 1, 0, 0, 0, 0, 0, 0, 0, 0, 0, 0, 0, 0, 0, 0, 0, 0, 0, 0, 0, 0, 0, 0, 0, 0, 0, 0, 0, 0, 0, 0, 0, 0, 0, 0, 2, 1, 0, 0, 1, 0, 0, 0, 0, 0, 3),
                  (0, 1, 0, 3, 0, 4, 0, 3, 0, 2, 4, 3, 1, 0, 3, 2, 2, 1, 3, 1, 2, 2, 3, 1, 1, 1, 2, 1, 3, 0, 1, 2, 0, 1, 3, 2, 1, 3, 0, 5, 5, 1, 0, 0, 1, 3, 2, 1, 0, 3, 0, 0, 1, 0, 0, 0, 0, 0, 3, 4, 0, 1, 1, 1, 3, 2, 0, 2, 0, 1, 0, 2, 3, 3, 1, 2, 3, 0, 1, 0, 1, 0, 4),
                  (0, 0, 0, 1, 0, 3, 0, 3, 0, 2, 2, 1, 0, 0, 4, 0, 3, 0, 3, 1, 3, 0, 3, 0, 3, 0, 1, 0, 3, 0, 3, 1, 3, 0, 3, 3, 0, 0, 1, 2, 1, 1, 1, 0, 1, 2, 0, 0, 0, 1, 0, 0, 1, 0, 0, 0, 0, 0, 0, 0, 0, 2, 2, 1, 2, 0, 0, 2, 0, 0, 0, 0, 2, 3, 3, 3, 3, 0, 0, 0, 0, 1, 4),
                  (0, 0, 0, 3, 0, 3, 0, 0, 0, 0, 3, 1, 1, 0, 3, 0, 1, 0, 2, 0, 1, 0, 0, 0, 0, 0, 0, 0, 1, 0, 3, 0, 2, 0, 2, 3, 0, 0, 2, 2, 3, 1, 2, 0, 0, 1, 0, 0, 0, 0, 0, 0, 0, 0, 0, 1, 0, 0, 0, 0, 0, 0, 0, 0, 0, 0, 0, 0, 0, 0, 0, 0, 0, 3, 0, 0, 2, 0, 0, 0, 0, 2, 3),
                  (2, 4, 0, 5, 0, 5, 0, 4, 0, 3, 4, 3, 3, 3, 4, 3, 3, 3, 4, 3, 4, 4, 5, 4, 5, 5, 5, 2, 3, 0, 5, 5, 4, 1, 5, 4, 3, 1, 5, 4, 3, 4, 4, 3, 3, 4, 3, 3, 0, 3, 2, 0, 2, 3, 0, 3, 0, 0, 3, 3, 0, 5, 3, 2, 3, 3, 0, 3, 0, 3, 0, 3, 4, 5, 4, 5, 3, 0, 4, 3, 0, 3, 4),
                  (0, 3, 0, 3, 0, 3, 0, 3, 0, 3, 3, 4, 3, 2, 3, 2, 3, 0, 4, 3, 3, 3, 3, 3, 3, 3, 3, 0, 3, 2, 4, 3, 3, 1, 3, 4, 3, 4, 4, 4, 3, 4, 4, 3, 2, 4, 4, 1, 0, 2, 0, 0, 1, 1, 0, 2, 0, 0, 3, 1, 0, 5, 3, 2, 1, 3, 0, 3, 0, 1, 2, 4, 3, 2, 4, 3, 3, 0, 3, 2, 0, 4, 4),
                  (0, 3, 0, 3, 0, 1, 0, 0, 0, 1, 4, 3, 3, 2, 3, 1, 3, 1, 4, 2, 3, 2, 4, 2, 3, 4, 3, 0, 2, 2, 3, 3, 3, 0, 3, 3, 3, 0, 3, 4, 1, 3, 3, 0, 3, 4, 3, 3, 0, 1, 1, 0, 1, 0, 0, 0, 4, 0, 3, 0, 0, 3, 1, 2, 1, 3, 0, 4, 0, 1, 0, 4, 3, 3, 4, 3, 3, 0, 2, 0, 0, 3, 3),
                  (0, 3, 0, 4, 0, 1, 0, 3, 0, 3, 4, 3, 3, 0, 3, 3, 3, 1, 3, 1, 3, 3, 4, 3, 3, 3, 0, 0, 3, 1, 5, 3, 3, 1, 3, 3, 2, 5, 4, 3, 3, 4, 5, 3, 2, 5, 3, 4, 0, 1, 0, 0, 0, 0, 0, 2, 0, 0, 1, 1, 0, 4, 2, 2, 1, 3, 0, 3, 0, 2, 0, 4, 4, 3, 5, 3, 2, 0, 1, 1, 0, 3, 4),
                  (0, 5, 0, 4, 0, 5, 0, 2, 0, 4, 4, 3, 3, 2, 3, 3, 3, 1, 4, 3, 4, 1, 5, 3, 4, 3, 4, 0, 4, 2, 4, 3, 4, 1, 5, 4, 0, 4, 4, 4, 4, 5, 4, 1, 3, 5, 4, 2, 1, 4, 1, 1, 3, 2, 0, 3, 1, 0, 3, 2, 1, 4, 3, 3, 3, 4, 0, 4, 0, 3, 0, 4, 4, 4, 3, 3, 3, 0, 4, 2, 0, 3, 4),
                  (1, 4, 0, 4, 0, 3, 0, 1, 0, 3, 3, 3, 1, 1, 3, 3, 2, 2, 3, 3, 1, 0, 3, 2, 2, 1, 2, 0, 3, 1, 2, 1, 2, 0, 3, 2, 0, 2, 2, 3, 3, 4, 3, 0, 3, 3, 1, 2, 0, 1, 1, 3, 1, 2, 0, 0, 3, 0, 1, 1, 0, 3, 2, 2, 3, 3, 0, 3, 0, 0, 0, 2, 3, 3, 4, 3, 3, 0, 1, 0, 0, 1, 4),
                  (0, 4, 0, 4, 0, 4, 0, 0, 0, 3, 4, 4, 3, 1, 4, 2, 3, 2, 3, 3, 3, 1, 4, 3, 4, 0, 3, 0, 4, 2, 3, 3, 2, 2, 5, 4, 2, 1, 3, 4, 3, 4, 3, 1, 3, 3, 4, 2, 0, 2, 1, 0, 3, 3, 0, 0, 2, 0, 3, 1, 0, 4, 4, 3, 4, 3, 0, 4, 0, 1, 0, 2, 4, 4, 4, 4, 4, 0, 3, 2, 0, 3, 3),
                  (0, 0, 0, 1, 0, 4, 0, 0, 0, 0, 0, 0, 1, 1, 1, 0, 0, 0, 0, 0, 0, 0, 0, 0, 1, 0, 0, 0, 0, 0, 0, 0, 1, 0, 3, 2, 0, 0, 1, 0, 0, 0, 1, 0, 0, 0, 0, 0, 0, 1, 0, 0, 0, 0, 0, 0, 0, 0, 0, 0, 0, 0, 0, 0, 0, 0, 0, 0, 0, 0, 0, 0, 0, 0, 0, 0, 1, 0, 0, 0, 0, 0, 2),
                  (0, 2, 0, 3, 0, 4, 0, 4, 0, 1, 3, 3, 3, 0, 4, 0, 2, 1, 2, 1, 1, 1, 2, 0, 3, 1, 1, 0, 1, 0, 3, 1, 0, 0, 3, 3, 2, 0, 1, 1, 0, 0, 0, 0, 0, 1, 0, 2, 0, 2, 2, 0, 3, 1, 0, 0, 1, 0, 1, 1, 0, 1, 2, 0, 3, 0, 0, 0, 0, 1, 0, 0, 3, 3, 4, 3, 1, 0, 1, 0, 3, 0, 2),
                  (0, 0, 0, 3, 0, 5, 0, 0, 0, 0, 1, 0, 2, 0, 3, 1, 0, 1, 3, 0, 0, 0, 2, 0, 0, 0, 1, 0, 0, 0, 1, 1, 0, 0, 4, 0, 0, 0, 2, 3, 0, 1, 4, 1, 0, 2, 0, 0, 0, 0, 0, 0, 0, 0, 0, 0, 0, 0, 0, 3, 0, 0, 0, 0, 0, 1, 0, 0, 0, 0, 0, 0, 0, 2, 0, 0, 3, 0, 0, 0, 0, 0, 3),
                  (0, 2, 0, 5, 0, 5, 0, 1, 0, 2, 4, 3, 3, 2, 5, 1, 3, 2, 3, 3, 3, 0, 4, 1, 2, 0, 3, 0, 4, 0, 2, 2, 1, 1, 5, 3, 0, 0, 1, 4, 2, 3, 2, 0, 3, 3, 3, 2, 0, 2, 4, 1, 1, 2, 0, 1, 1, 0, 3, 1, 0, 1, 3, 1, 2, 3, 0, 2, 0, 0, 0, 1, 3, 5, 4, 4, 4, 0, 3, 0, 0, 1, 3),
                  (0, 4, 0, 5, 0, 4, 0, 4, 0, 4, 5, 4, 3, 3, 4, 3, 3, 3, 4, 3, 4, 4, 5, 3, 4, 5, 4, 2, 4, 2, 3, 4, 3, 1, 4, 4, 1, 3, 5, 4, 4, 5, 5, 4, 4, 5, 5, 5, 2, 3, 3, 1, 4, 3, 1, 3, 3, 0, 3, 3, 1, 4, 3, 4, 4, 4, 0, 3, 0, 4, 0, 3, 3, 4, 4, 5, 0, 0, 4, 3, 0, 4, 5),
                  (0, 4, 0, 4, 0, 3, 0, 3, 0, 3, 4, 4, 4, 3, 3, 2, 4, 3, 4, 3, 4, 3, 5, 3, 4, 3, 2, 1, 4, 2, 4, 4, 3, 1, 3, 4, 2, 4, 5, 5, 3, 4, 5, 4, 1, 5, 4, 3, 0, 3, 2, 2, 3, 2, 1, 3, 1, 0, 3, 3, 3, 5, 3, 3, 3, 5, 4, 4, 2, 3, 3, 4, 3, 3, 3, 2, 1, 0, 3, 2, 1, 4, 3),
                  (0, 4, 0, 5, 0, 4, 0, 3, 0, 3, 5, 5, 3, 2, 4, 3, 4, 0, 5, 4, 4, 1, 4, 4, 4, 3, 3, 3, 4, 3, 5, 5, 2, 3, 3, 4, 1, 2, 5, 5, 3, 5, 5, 2, 3, 5, 5, 4, 0, 3, 2, 0, 3, 3, 1, 1, 5, 1, 4, 1, 0, 4, 3, 2, 3, 5, 0, 4, 0, 3, 0, 5, 4, 3, 4, 3, 0, 0, 4, 1, 0, 4, 4),
                  (1, 3, 0, 4, 0, 2, 0, 2, 0, 2, 5, 5, 3, 3, 3, 3, 3, 0, 4, 2, 3, 4, 4, 4, 3, 4, 0, 0, 3, 4, 5, 4, 3, 3, 3, 3, 2, 5, 5, 4, 5, 5, 5, 4, 3, 5, 5, 5, 1, 3, 1, 0, 1, 0, 0, 3, 2, 0, 4, 2, 0, 5, 2, 3, 2, 4, 1, 3, 0, 3, 0, 4, 5, 4, 5, 4, 3, 0, 4, 2, 0, 5, 4),
                  (0, 3, 0, 4, 0, 5, 0, 3, 0, 3, 4, 4, 3, 2, 3, 2, 3, 3, 3, 3, 3, 2, 4, 3, 3, 2, 2, 0, 3, 3, 3, 3, 3, 1, 3, 3, 3, 0, 4, 4, 3, 4, 4, 1, 1, 4, 4, 2, 0, 3, 1, 0, 1, 1, 0, 4, 1, 0, 2, 3, 1, 3, 3, 1, 3, 4, 0, 3, 0, 1, 0, 3, 1, 3, 0, 0, 1, 0, 2, 0, 0, 4, 4),
                  (0, 0, 0, 0, 0, 0, 0, 0, 0, 0, 0, 0, 0, 0, 0, 0, 0, 0, 0, 0, 0, 0, 0, 0, 0, 0, 0, 0, 0, 0, 0, 0, 0, 0, 0, 0, 0, 0, 0, 0, 0, 0, 0, 0, 0, 0, 0, 0, 0, 0, 0, 0, 0, 0, 0, 0, 0, 0, 0, 0, 0, 0, 0, 0, 0, 0, 0, 0, 0, 0, 0, 0, 0, 0, 0, 0, 0, 0, 0, 0, 0, 0, 0),
                  (0, 3, 0, 3, 0, 2, 0, 3, 0, 1, 5, 4, 3, 3, 3, 1, 4, 2, 1, 2, 3, 4, 4, 2, 4, 4, 5, 0, 3, 1, 4, 3, 4, 0, 4, 3, 3, 3, 2, 3, 2, 5, 3, 4, 3, 2, 2, 3, 0, 0, 3, 0, 2, 1, 0, 1, 2, 0, 0, 0, 0, 2, 1, 1, 3, 1, 0, 2, 0, 4, 0, 3, 4, 4, 4, 5, 2, 0, 2, 0, 0, 1, 3),
                  (0, 0, 0, 0, 0, 0, 0, 0, 0, 0, 0, 0, 0, 0, 1, 0, 0, 0, 0, 0, 1, 1, 1, 0, 0, 1, 1, 0, 0, 0, 4, 2, 1, 1, 0, 1, 0, 3, 2, 0, 0, 3, 1, 1, 1, 2, 2, 0, 0, 0, 0, 0, 0, 0, 0, 0, 0, 0, 0, 0, 0, 3, 0, 1, 0, 0, 0, 2, 0, 0, 0, 1, 4, 0, 4, 2, 1, 0, 0, 0, 0, 0, 1),
                  (0, 0, 0, 0, 0, 0, 0, 0, 0, 1, 0, 1, 0, 0, 0, 0, 1, 0, 0, 0, 0, 0, 0, 1, 0, 1, 0, 0, 0, 0, 3, 1, 0, 0, 0, 2, 0, 2, 1, 0, 0, 1, 2, 1, 0, 1, 1, 0, 0, 3, 0, 0, 0, 0, 0, 0, 0, 0, 0, 0, 0, 1, 3, 1, 0, 0, 0, 0, 0, 1, 0, 0, 2, 1, 0, 0, 0, 0, 0, 0, 0, 0, 2),
                  (0, 4, 0, 4, 0, 4, 0, 3, 0, 4, 4, 3, 4, 2, 4, 3, 2, 0, 4, 4, 4, 3, 5, 3, 5, 3, 3, 2, 4, 2, 4, 3, 4, 3, 1, 4, 0, 2, 3, 4, 4, 4, 3, 3, 3, 4, 4, 4, 3, 4, 1, 3, 4, 3, 2, 1, 2, 1, 3, 3, 3, 4, 4, 3, 3, 5, 0, 4, 0, 3, 0, 4, 3, 3, 3, 2, 1, 0, 3, 0, 0, 3, 3),
                  (0, 4, 0, 3, 0, 3, 0, 3, 0, 3, 5, 5, 3, 3, 3, 3, 4, 3, 4, 3, 3, 3, 4, 4, 4, 3, 3, 3, 3, 4, 3, 5, 3, 3, 1, 3, 2, 4, 5, 5, 5, 5, 4, 3, 4, 5, 5, 3, 2, 2, 3, 3, 3, 3, 2, 3, 3, 1, 2, 3, 2, 4, 3, 3, 3, 4, 0, 4, 0, 2, 0, 4, 3, 2, 2, 1, 2, 0, 3, 0, 0, 4, 1))

class JapaneseContextAnalysis(object):
    NUM_OF_CATEGORY = 6
    DONT_KNOW = -1
    ENOUGH_REL_THRESHOLD = 100
    MAX_REL_THRESHOLD = 1000
    MINIMUM_DATA_THRESHOLD = 4

    def __init__(self):
        self._total_rel = None
        self._rel_sample = None
        self._need_to_skip_char_num = None
        self._last_char_order = None
        self._done = None
        self.reset()

    def reset(self):
        self._total_rel = 0
        self._rel_sample = [
         0] * self.NUM_OF_CATEGORY
        self._need_to_skip_char_num = 0
        self._last_char_order = -1
        self._done = False

    def feed(self, byte_str, num_bytes):
        if self._done:
            return
        else:
            i = self._need_to_skip_char_num
            while i < num_bytes:
                order, char_len = self.get_order(byte_str[i:i + 2])
                i += char_len
                if i > num_bytes:
                    self._need_to_skip_char_num = i - num_bytes
                    self._last_char_order = -1
                else:
                    if order != -1:
                        if self._last_char_order != -1:
                            self._total_rel += 1
                            if self._total_rel > self.MAX_REL_THRESHOLD:
                                self._done = True
                                break
                            self._rel_sample[jp2CharContext[self._last_char_order][order]] += 1
                    self._last_char_order = order

    def got_enough_data(self):
        return self._total_rel > self.ENOUGH_REL_THRESHOLD

    def get_confidence(self):
        if self._total_rel > self.MINIMUM_DATA_THRESHOLD:
            return (self._total_rel - self._rel_sample[0]) / self._total_rel
        return self.DONT_KNOW

    def get_order(self, byte_str):
        return (-1, 1)


class SJISContextAnalysis(JapaneseContextAnalysis):

    def __init__(self):
        super(SJISContextAnalysis, self).__init__()
        self._charset_name = 'SHIFT_JIS'

    @property
    def charset_name(self):
        return self._charset_name

    def get_order--- This code section failed: ---

 L. 193         0  LOAD_FAST                'byte_str'
                2  POP_JUMP_IF_TRUE      8  'to 8'

 L. 194         4  LOAD_CONST               (-1, 1)
                6  RETURN_VALUE     
              8_0  COME_FROM             2  '2'

 L. 196         8  LOAD_FAST                'byte_str'
               10  LOAD_CONST               0
               12  BINARY_SUBSCR    
               14  STORE_FAST               'first_char'

 L. 197        16  LOAD_CONST               129
               18  LOAD_FAST                'first_char'
               20  DUP_TOP          
               22  ROT_THREE        
               24  COMPARE_OP               <=
               26  POP_JUMP_IF_FALSE    36  'to 36'
               28  LOAD_CONST               159
               30  COMPARE_OP               <=
               32  POP_JUMP_IF_TRUE     62  'to 62'
               34  JUMP_FORWARD         38  'to 38'
             36_0  COME_FROM            26  '26'
               36  POP_TOP          
             38_0  COME_FROM            34  '34'
               38  LOAD_CONST               224
               40  LOAD_FAST                'first_char'
               42  DUP_TOP          
               44  ROT_THREE        
               46  COMPARE_OP               <=
               48  POP_JUMP_IF_FALSE    58  'to 58'
               50  LOAD_CONST               252
               52  COMPARE_OP               <=
               54  POP_JUMP_IF_FALSE   106  'to 106'
               56  JUMP_FORWARD         62  'to 62'
             58_0  COME_FROM            48  '48'
               58  POP_TOP          
               60  JUMP_FORWARD        106  'to 106'
             62_0  COME_FROM            56  '56'
             62_1  COME_FROM            32  '32'

 L. 198        62  LOAD_CONST               2
               64  STORE_FAST               'char_len'

 L. 199        66  LOAD_FAST                'first_char'
               68  LOAD_CONST               135
               70  COMPARE_OP               ==
               72  POP_JUMP_IF_TRUE     98  'to 98'
               74  LOAD_CONST               250
               76  LOAD_FAST                'first_char'
               78  DUP_TOP          
               80  ROT_THREE        
               82  COMPARE_OP               <=
               84  POP_JUMP_IF_FALSE    94  'to 94'
               86  LOAD_CONST               252
               88  COMPARE_OP               <=
               90  POP_JUMP_IF_FALSE   110  'to 110'
               92  JUMP_FORWARD         98  'to 98'
             94_0  COME_FROM            84  '84'
               94  POP_TOP          
               96  JUMP_ABSOLUTE       110  'to 110'
             98_0  COME_FROM            92  '92'
             98_1  COME_FROM            72  '72'

 L. 200        98  LOAD_STR                 'CP932'
              100  LOAD_FAST                'self'
              102  STORE_ATTR               _charset_name
              104  JUMP_FORWARD        110  'to 110'
            106_0  COME_FROM            60  '60'
            106_1  COME_FROM            54  '54'

 L. 202       106  LOAD_CONST               1
              108  STORE_FAST               'char_len'
            110_0  COME_FROM           104  '104'
            110_1  COME_FROM            90  '90'

 L. 205       110  LOAD_GLOBAL              len
              112  LOAD_FAST                'byte_str'
              114  CALL_FUNCTION_1       1  ''
              116  LOAD_CONST               1
              118  COMPARE_OP               >
              120  POP_JUMP_IF_FALSE   174  'to 174'

 L. 206       122  LOAD_FAST                'byte_str'
              124  LOAD_CONST               1
              126  BINARY_SUBSCR    
              128  STORE_FAST               'second_char'

 L. 207       130  LOAD_FAST                'first_char'
              132  LOAD_CONST               202
              134  COMPARE_OP               ==
              136  POP_JUMP_IF_FALSE   174  'to 174'
              138  LOAD_CONST               159
              140  LOAD_FAST                'second_char'
              142  DUP_TOP          
              144  ROT_THREE        
              146  COMPARE_OP               <=
              148  POP_JUMP_IF_FALSE   158  'to 158'
              150  LOAD_CONST               241
              152  COMPARE_OP               <=
              154  POP_JUMP_IF_FALSE   174  'to 174'
              156  JUMP_FORWARD        162  'to 162'
            158_0  COME_FROM           148  '148'
              158  POP_TOP          
              160  JUMP_FORWARD        174  'to 174'
            162_0  COME_FROM           156  '156'

 L. 208       162  LOAD_FAST                'second_char'
              164  LOAD_CONST               159
              166  BINARY_SUBTRACT  
              168  LOAD_FAST                'char_len'
              170  BUILD_TUPLE_2         2 
              172  RETURN_VALUE     
            174_0  COME_FROM           160  '160'
            174_1  COME_FROM           154  '154'
            174_2  COME_FROM           136  '136'
            174_3  COME_FROM           120  '120'

 L. 210       174  LOAD_CONST               -1
              176  LOAD_FAST                'char_len'
              178  BUILD_TUPLE_2         2 
              180  RETURN_VALUE     
               -1  RETURN_LAST      

Parse error at or near `COME_FROM' instruction at offset 106_0


class EUCJPContextAnalysis(JapaneseContextAnalysis):

    def get_order(self, byte_str):
        if not byte_str:
            return (-1, 1)
        else:
            first_char = byte_str[0]
            if not first_char == 142:
                if 161 <= first_char <= 254:
                    char_len = 2
            elif first_char == 143:
                char_len = 3
            else:
                char_len = 1
        if len(byte_str) > 1:
            second_char = byte_str[1]
            if first_char == 164:
                if 161 <= second_char <= 243:
                    return (
                     second_char - 161, char_len)
        return (
         -1, char_len)