# uncompyle6 version 3.7.4
# Python bytecode 3.8 (3413)
# Decompiled from: Python 3.6.15 (default, Sep 28 2021, 20:18:52) 
# [GCC 10.2.1 20210110]
# Embedded file name: site-packages\requests\packages\chardet\jpcntx.py
from .compat import wrap_ord
NUM_OF_CATEGORY = 6
DONT_KNOW = -1
ENOUGH_REL_THRESHOLD = 100
MAX_REL_THRESHOLD = 1000
MINIMUM_DATA_THRESHOLD = 4
jp2CharContext = ((0, 0, 0, 2, 0, 0, 0, 0, 0, 0, 0, 0, 0, 0, 0, 0, 0, 0, 0, 0, 0, 0, 0, 0, 0, 0, 0, 0, 0, 0, 0, 0, 0, 0, 0, 0, 0, 0, 0, 1, 0, 0, 0, 0, 0, 0, 0, 0, 0, 0, 0, 0, 0, 0, 0, 0, 0, 0, 0, 0, 0, 0, 0, 0, 0, 0, 0, 1, 0, 0, 0, 1, 0, 0, 0, 0, 0, 0, 0, 0, 0, 0, 1),
                  (2, 4, 0, 4, 0, 3, 0, 4, 0, 3, 4, 4, 4, 2, 4, 3, 3, 4, 3, 2, 3, 3, 4, 2, 3, 3, 3, 2, 4, 1, 4, 3, 3, 1, 5, 4, 3, 4, 3, 4, 3, 5, 3, 0, 3, 5, 4, 2, 0, 3, 1, 0, 3, 3, 0, 3, 3, 0, 1, 1, 0, 4, 3, 0, 3, 3, 0, 4, 0, 2, 0, 3, 5, 5, 5, 5, 4, 0, 4, 1, 0, 3, 4),
                  (0, 0, 1, 0, 0, 0, 0, 0, 0, 0, 0, 0, 0, 0, 0, 0, 0, 0, 0, 0, 0, 0, 0, 0, 0, 0, 0, 0, 0, 0, 0, 0, 0, 0, 1, 0, 0, 0, 0, 0, 0, 0, 0, 0, 0, 0, 0, 0, 0, 0, 0, 0, 0, 0, 0, 0, 0, 0, 0, 0, 0, 0, 0, 0, 0, 0, 0, 0, 0, 0, 0, 0, 0, 0, 0, 0, 0, 0, 0, 0, 0, 0, 2),
                  (0, 4, 0, 5, 0, 5, 0, 4, 0, 4, 5, 4, 4, 3, 5, 3, 5, 1, 5, 3, 4, 3, 4, 4, 3, 4, 3, 3, 4, 3, 5, 4, 4, 3, 5, 5, 3, 5, 5, 5, 3, 5, 5, 3, 4, 5, 5, 3, 1, 3, 2, 0, 3, 4, 0, 4, 2, 0, 4, 2, 1, 5, 3, 2, 3, 5, 0, 4, 0, 2, 0, 5, 4, 4, 5, 4, 5, 0, 4, 0, 0, 4, 4),
                  (0, 0, 0, 0, 0, 0, 0, 0, 0, 0, 0, 0, 0, 0, 0, 0, 0, 0, 0, 0, 0, 0, 0, 0, 0, 0, 0, 0, 0, 0, 0, 0, 0, 0, 0, 0, 0, 0, 0, 0, 0, 0, 0, 0, 0, 0, 0, 0, 0, 0, 0, 0, 0, 0, 0, 0, 0, 0, 0, 0, 0, 0, 0, 0, 0, 0, 0, 0, 0, 0, 0, 0, 0, 0, 0, 0, 0, 0, 0, 0, 0, 0, 0),
                  (0, 3, 0, 4, 0, 3, 0, 3, 0, 4, 5, 4, 3, 3, 3, 3, 4, 3, 5, 4, 4, 3, 5, 4, 4, 3, 4, 3, 4, 4, 4, 4, 5, 3, 4, 4, 3, 4, 5, 5, 4, 5, 5, 1, 4, 5, 4, 3, 0, 3, 3, 1, 3, 3, 0, 4, 4, 0, 3, 3, 1, 5, 3, 3, 3, 5, 0, 4, 0, 3, 0, 4, 4, 3, 4, 3, 3, 0, 4, 1, 1, 3, 4),
                  (0, 0, 0, 0, 0, 0, 0, 0, 0, 0, 0, 0, 0, 0, 0, 0, 0, 0, 0, 0, 0, 0, 0, 0, 0, 0, 0, 0, 0, 0, 0, 0, 0, 0, 1, 0, 0, 0, 0, 0, 0, 0, 0, 0, 0, 0, 0, 0, 0, 0, 0, 0, 0, 0, 0, 0, 0, 0, 0, 0, 0, 0, 0, 0, 0, 0, 0, 0, 0, 0, 0, 0, 0, 0, 0, 0, 0, 0, 0, 0, 0, 0, 0),
                  (0, 4, 0, 3, 0, 3, 0, 4, 0, 3, 4, 4, 3, 2, 2, 1, 2, 1, 3, 1, 3, 3, 3, 3, 3, 4, 3, 1, 3, 3, 5, 3, 3, 0, 4, 3, 0, 5, 4, 3, 3, 5, 4, 4, 3, 4, 4, 5, 0, 1, 2, 0, 1, 2, 0, 2, 2, 0, 1, 0, 0, 5, 2, 2, 1, 4, 0, 3, 0, 1, 0, 4, 4, 3, 5, 4, 3, 0, 2, 1, 0, 4, 3),
                  (0, 0, 0, 0, 0, 0, 0, 0, 0, 0, 0, 0, 0, 0, 0, 0, 0, 0, 0, 0, 0, 0, 0, 0, 0, 0, 0, 0, 0, 0, 0, 0, 0, 0, 0, 0, 0, 0, 0, 1, 0, 0, 0, 0, 0, 0, 0, 0, 0, 0, 0, 0, 0, 0, 0, 0, 0, 0, 0, 0, 0, 0, 0, 0, 0, 0, 0, 0, 0, 0, 0, 0, 0, 0, 0, 0, 0, 0, 0, 0, 0, 0, 0),
                  (0, 3, 0, 5, 0, 4, 0, 2, 1, 4, 4, 2, 4, 1, 4, 2, 4, 2, 4, 3, 3, 3, 4, 3, 3, 3, 3, 1, 4, 2, 3, 3, 3, 1, 4, 4, 1, 1, 1, 4, 3, 3, 2, 0, 2, 4, 3, 2, 0, 3, 3, 0, 3, 1, 1, 0, 0, 0, 3, 3, 0, 4, 2, 2, 3, 4, 0, 4, 0, 3, 0, 4, 4, 5, 3, 4, 4, 0, 3, 0, 0, 1, 4),
                  (1, 4, 0, 4, 0, 4, 0, 4, 0, 3, 5, 4, 4, 3, 4, 3, 5, 4, 3, 3, 4, 3, 5, 4, 4, 4, 4, 3, 4, 2, 4, 3, 3, 1, 5, 4, 3, 2, 4, 5, 4, 5, 5, 4, 4, 5, 4, 4, 0, 3, 2, 2, 3, 3, 0, 4, 3, 1, 3, 2, 1, 4, 3, 3, 4, 5, 0, 3, 0, 2, 0, 4, 5, 5, 4, 5, 4, 0, 4, 0, 0, 5, 4),
                  (0, 5, 0, 5, 0, 4, 0, 3, 0, 4, 4, 3, 4, 3, 3, 3, 4, 0, 4, 4, 4, 3, 4, 3, 4, 3, 3, 1, 4, 2, 4, 3, 4, 0, 5, 4, 1, 4, 5, 4, 4, 5, 3, 2, 4, 3, 4, 3, 2, 4, 1, 3, 3, 3, 2, 3, 2, 0, 4, 3, 3, 4, 3, 3, 3, 4, 0, 4, 0, 3, 0, 4, 5, 4, 4, 4, 3, 0, 4, 1, 0, 1, 3),
                  (0, 3, 1, 4, 0, 3, 0, 2, 0, 3, 4, 4, 3, 1, 4, 2, 3, 3, 4, 3, 4, 3, 4, 3, 4, 4, 3, 2, 3, 1, 5, 4, 4, 1, 4, 4, 3, 5, 4, 4, 3, 5, 5, 4, 3, 4, 4, 3, 1, 2, 3, 1, 2, 2, 0, 3, 2, 0, 3, 1, 0, 5, 3, 3, 3, 4, 3, 3, 3, 3, 4, 4, 4, 4, 5, 4, 2, 0, 3, 3, 2, 4, 3),
                  (0, 2, 0, 3, 0, 1, 0, 1, 0, 0, 3, 2, 0, 0, 2, 0, 1, 0, 2, 1, 3, 3, 3, 1, 2, 3, 1, 0, 1, 0, 4, 2, 1, 1, 3, 3, 0, 4, 3, 3, 1, 4, 3, 3, 0, 3, 3, 2, 0, 0, 0, 0, 1, 0, 0, 2, 0, 0, 0, 0, 0, 4, 1, 0, 2, 3, 2, 2, 2, 1, 3, 3, 3, 4, 4, 3, 2, 0, 3, 1, 0, 3, 3),
                  (0, 4, 0, 4, 0, 3, 0, 3, 0, 4, 4, 4, 3, 3, 3, 3, 3, 3, 4, 3, 4, 2, 4, 3, 4, 3, 3, 2, 4, 3, 4, 5, 4, 1, 4, 5, 3, 5, 4, 5, 3, 5, 4, 0, 3, 5, 5, 3, 1, 3, 3, 2, 2, 3, 0, 3, 4, 1, 3, 3, 2, 4, 3, 3, 3, 4, 0, 4, 0, 3, 0, 4, 5, 4, 4, 5, 3, 0, 4, 1, 0, 3, 4),
                  (0, 2, 0, 3, 0, 3, 0, 0, 0, 2, 2, 2, 1, 0, 1, 0, 0, 0, 3, 0, 3, 0, 3, 0, 1, 3, 1, 0, 3, 1, 3, 3, 3, 1, 3, 3, 3, 0, 1, 3, 1, 3, 4, 0, 0, 3, 1, 1, 0, 3, 2, 0, 0, 0, 0, 1, 3, 0, 1, 0, 0, 3, 3, 2, 0, 3, 0, 0, 0, 0, 0, 3, 4, 3, 4, 3, 3, 0, 3, 0, 0, 2, 3),
                  (2, 3, 0, 3, 0, 2, 0, 1, 0, 3, 3, 4, 3, 1, 3, 1, 1, 1, 3, 1, 4, 3, 4, 3, 3, 3, 0, 0, 3, 1, 5, 4, 3, 1, 4, 3, 2, 5, 5, 4, 4, 4, 4, 3, 3, 4, 4, 4, 0, 2, 1, 1, 3, 2, 0, 1, 2, 0, 0, 1, 0, 4, 1, 3, 3, 3, 0, 3, 0, 1, 0, 4, 4, 4, 5, 5, 3, 0, 2, 0, 0, 4, 4),
                  (0, 2, 0, 1, 0, 3, 1, 3, 0, 2, 3, 3, 3, 0, 3, 1, 0, 0, 3, 0, 3, 2, 3, 1, 3, 2, 1, 1, 0, 0, 4, 2, 1, 0, 2, 3, 1, 4, 3, 2, 0, 4, 4, 3, 1, 3, 1, 3, 0, 1, 0, 0, 1, 0, 0, 0, 1, 0, 0, 0, 0, 4, 1, 1, 1, 2, 0, 3, 0, 0, 0, 3, 4, 2, 4, 3, 2, 0, 1, 0, 0, 3, 3),
                  (0, 1, 0, 4, 0, 5, 0, 4, 0, 2, 4, 4, 2, 3, 3, 2, 3, 3, 5, 3, 3, 3, 4, 3, 4, 2, 3, 0, 4, 3, 3, 3, 4, 1, 4, 3, 2, 1, 5, 5, 3, 4, 5, 1, 3, 5, 4, 2, 0, 3, 3, 0, 1, 3, 0, 4, 2, 0, 1, 3, 1, 4, 3, 3, 3, 3, 0, 3, 0, 1, 0, 3, 4, 4, 4, 5, 5, 0, 3, 0, 1, 4, 5),
                  (0, 2, 0, 3, 0, 3, 0, 0, 0, 2, 3, 1, 3, 0, 4, 0, 1, 1, 3, 0, 3, 4, 3, 2, 3, 1, 0, 3, 3, 2, 3, 1, 3, 0, 2, 3, 0, 2, 1, 4, 1, 2, 2, 0, 0, 3, 3, 0, 0, 2, 0, 0, 0, 1, 0, 0, 0, 0, 2, 2, 0, 3, 2, 1, 3, 3, 0, 2, 0, 2, 0, 0, 3, 3, 1, 2, 4, 0, 3, 0, 2, 2, 3),
                  (2, 4, 0, 5, 0, 4, 0, 4, 0, 2, 4, 4, 4, 3, 4, 3, 3, 3, 1, 2, 4, 3, 4, 3, 4, 4, 5, 0, 3, 3, 3, 3, 2, 0, 4, 3, 1, 4, 3, 4, 1, 4, 4, 3, 3, 4, 4, 3, 1, 2, 3, 0, 4, 2, 0, 4, 1, 0, 3, 3, 0, 4, 3, 3, 3, 4, 0, 4, 0, 2, 0, 3, 5, 3, 4, 5, 2, 0, 3, 0, 0, 4, 5),
                  (0, 3, 0, 4, 0, 1, 0, 1, 0, 1, 3, 2, 2, 1, 3, 0, 3, 0, 2, 0, 2, 0, 3, 0, 2, 0, 0, 0, 1, 0, 1, 1, 0, 0, 3, 1, 0, 0, 0, 4, 0, 3, 1, 0, 2, 1, 3, 0, 0, 0, 0, 0, 0, 3, 0, 0, 0, 0, 0, 0, 0, 4, 2, 2, 3, 1, 0, 3, 0, 0, 0, 1, 4, 4, 4, 3, 0, 0, 4, 0, 0, 1, 4),
                  (1, 4, 1, 5, 0, 3, 0, 3, 0, 4, 5, 4, 4, 3, 5, 3, 3, 4, 4, 3, 4, 1, 3, 3, 3, 3, 2, 1, 4, 1, 5, 4, 3, 1, 4, 4, 3, 5, 4, 4, 3, 5, 4, 3, 3, 4, 4, 4, 0, 3, 3, 1, 2, 3, 0, 3, 1, 0, 3, 3, 0, 5, 4, 4, 4, 4, 4, 4, 3, 3, 5, 4, 4, 3, 3, 5, 4, 0, 3, 2, 0, 4, 4),
                  (0, 2, 0, 3, 0, 1, 0, 0, 0, 1, 3, 3, 3, 2, 4, 1, 3, 0, 3, 1, 3, 0, 2, 2, 1, 1, 0, 0, 2, 0, 4, 3, 1, 0, 4, 3, 0, 4, 4, 4, 1, 4, 3, 1, 1, 3, 3, 1, 0, 2, 0, 0, 1, 3, 0, 0, 0, 0, 2, 0, 0, 4, 3, 2, 4, 3, 5, 4, 3, 3, 3, 4, 3, 3, 4, 3, 3, 0, 2, 1, 0, 3, 3),
                  (0, 2, 0, 4, 0, 3, 0, 2, 0, 2, 5, 5, 3, 4, 4, 4, 4, 1, 4, 3, 3, 0, 4, 3, 4, 3, 1, 3, 3, 2, 4, 3, 0, 3, 4, 3, 0, 3, 4, 4, 2, 4, 4, 0, 4, 5, 3, 3, 2, 2, 1, 1, 1, 2, 0, 1, 5, 0, 3, 3, 2, 4, 3, 3, 3, 4, 0, 3, 0, 2, 0, 4, 4, 3, 5, 5, 0, 0, 3, 0, 2, 3, 3),
                  (0, 3, 0, 4, 0, 3, 0, 1, 0, 3, 4, 3, 3, 1, 3, 3, 3, 0, 3, 1, 3, 0, 4, 3, 3, 1, 1, 0, 3, 0, 3, 3, 0, 0, 4, 4, 0, 1, 5, 4, 3, 3, 5, 0, 3, 3, 4, 3, 0, 2, 0, 1, 1, 1, 0, 1, 3, 0, 1, 2, 1, 3, 3, 2, 3, 3, 0, 3, 0, 1, 0, 1, 3, 3, 4, 4, 1, 0, 1, 2, 2, 1, 3),
                  (0, 1, 0, 4, 0, 4, 0, 3, 0, 1, 3, 3, 3, 2, 3, 1, 1, 0, 3, 0, 3, 3, 4, 3, 2, 4, 2, 0, 1, 0, 4, 3, 2, 0, 4, 3, 0, 5, 3, 3, 2, 4, 4, 4, 3, 3, 3, 4, 0, 1, 3, 0, 0, 1, 0, 0, 1, 0, 0, 0, 0, 4, 2, 3, 3, 3, 0, 3, 0, 0, 0, 4, 4, 4, 5, 3, 2, 0, 3, 3, 0, 3, 5),
                  (0, 2, 0, 3, 0, 0, 0, 3, 0, 1, 3, 0, 2, 0, 0, 0, 1, 0, 3, 1, 1, 3, 3, 0, 0, 3, 0, 0, 3, 0, 2, 3, 1, 0, 3, 1, 0, 3, 3, 2, 0, 4, 2, 2, 0, 2, 0, 0, 0, 4, 0, 0, 0, 0, 0, 0, 0, 0, 0, 0, 0, 2, 1, 2, 0, 1, 0, 1, 0, 0, 0, 1, 3, 1, 2, 0, 0, 0, 1, 0, 0, 1, 4),
                  (0, 3, 0, 3, 0, 5, 0, 1, 0, 2, 4, 3, 1, 3, 3, 2, 1, 1, 5, 2, 1, 0, 5, 1, 2, 0, 0, 0, 3, 3, 2, 2, 3, 2, 4, 3, 0, 0, 3, 3, 1, 3, 3, 0, 2, 5, 3, 4, 0, 3, 3, 0, 1, 2, 0, 2, 2, 0, 3, 2, 0, 2, 2, 3, 3, 3, 0, 2, 0, 1, 0, 3, 4, 4, 2, 5, 4, 0, 3, 0, 0, 3, 5),
                  (0, 3, 0, 3, 0, 3, 0, 1, 0, 3, 3, 3, 3, 0, 3, 0, 2, 0, 2, 1, 1, 0, 2, 0, 1, 0, 0, 0, 2, 1, 0, 0, 1, 0, 3, 2, 0, 0, 3, 3, 1, 2, 3, 1, 0, 3, 3, 0, 0, 1, 0, 0, 0, 0, 0, 2, 0, 0, 0, 0, 0, 2, 3, 1, 2, 3, 0, 3, 0, 1, 0, 3, 2, 1, 0, 4, 3, 0, 1, 1, 0, 3, 3),
                  (0, 4, 0, 5, 0, 3, 0, 3, 0, 4, 5, 5, 4, 3, 5, 3, 4, 3, 5, 3, 3, 2, 5, 3, 4, 4, 4, 3, 4, 3, 4, 5, 5, 3, 4, 4, 3, 4, 4, 5, 4, 4, 4, 3, 4, 5, 5, 4, 2, 3, 4, 2, 3, 4, 0, 3, 3, 1, 4, 3, 2, 4, 3, 3, 5, 5, 0, 3, 0, 3, 0, 5, 5, 5, 5, 4, 4, 0, 4, 0, 1, 4, 4),
                  (0, 4, 0, 4, 0, 3, 0, 3, 0, 3, 5, 4, 4, 2, 3, 2, 5, 1, 3, 2, 5, 1, 4, 2, 3, 2, 3, 3, 4, 3, 3, 3, 3, 2, 5, 4, 1, 3, 3, 5, 3, 4, 4, 0, 4, 4, 3, 1, 1, 3, 1, 0, 2, 3, 0, 2, 3, 0, 3, 0, 0, 4, 3, 1, 3, 4, 0, 3, 0, 2, 0, 4, 4, 4, 3, 4, 5, 0, 4, 0, 0, 3, 4),
                  (0, 3, 0, 3, 0, 3, 1, 2, 0, 3, 4, 4, 3, 3, 3, 0, 2, 2, 4, 3, 3, 1, 3, 3, 3, 1, 1, 0, 3, 1, 4, 3, 2, 3, 4, 4, 2, 4, 4, 4, 3, 4, 4, 3, 2, 4, 4, 3, 1, 3, 3, 1, 3, 3, 0, 4, 1, 0, 2, 2, 1, 4, 3, 2, 3, 3, 5, 4, 3, 3, 5, 4, 4, 3, 3, 0, 4, 0, 3, 2, 2, 4, 4),
                  (0, 2, 0, 1, 0, 0, 0, 0, 0, 1, 2, 1, 3, 0, 0, 0, 0, 0, 2, 0, 1, 2, 1, 0, 0, 1, 0, 0, 0, 0, 3, 0, 0, 1, 0, 1, 1, 3, 1, 0, 0, 0, 1, 1, 0, 1, 1, 0, 0, 0, 0, 0, 2, 0, 0, 0, 0, 0, 0, 0, 0, 1, 1, 2, 2, 0, 3, 4, 0, 0, 0, 1, 1, 0, 0, 1, 0, 0, 0, 0, 0, 1, 1),
                  (0, 1, 0, 0, 0, 1, 0, 0, 0, 0, 4, 0, 4, 1, 4, 0, 3, 0, 4, 0, 3, 0, 4, 0, 3, 0, 3, 0, 4, 1, 5, 1, 4, 0, 0, 3, 0, 5, 0, 5, 2, 0, 1, 0, 0, 0, 2, 1, 4, 0, 1, 3, 0, 0, 3, 0, 0, 3, 1, 1, 4, 1, 0, 0, 0, 0, 0, 0, 0, 0, 0, 0, 0, 0, 1, 0, 0, 0, 0, 0, 0, 0, 0),
                  (1, 4, 0, 5, 0, 3, 0, 2, 0, 3, 5, 4, 4, 3, 4, 3, 5, 3, 4, 3, 3, 0, 4, 3, 3, 3, 3, 3, 3, 2, 4, 4, 3, 1, 3, 4, 4, 5, 4, 4, 3, 4, 4, 1, 3, 5, 4, 3, 3, 3, 1, 2, 2, 3, 3, 1, 3, 1, 3, 3, 3, 5, 3, 3, 4, 5, 0, 3, 0, 3, 0, 3, 4, 3, 4, 4, 3, 0, 3, 0, 2, 4, 3),
                  (0, 1, 0, 4, 0, 0, 0, 0, 0, 1, 4, 0, 4, 1, 4, 2, 4, 0, 3, 0, 1, 0, 1, 0, 0, 0, 0, 0, 2, 0, 3, 1, 1, 1, 0, 3, 0, 0, 0, 1, 2, 1, 0, 0, 1, 1, 1, 1, 0, 1, 0, 0, 0, 1, 0, 0, 3, 0, 0, 0, 0, 3, 2, 0, 2, 2, 0, 1, 0, 0, 0, 2, 3, 2, 3, 3, 0, 0, 0, 0, 2, 1, 0),
                  (0, 5, 1, 5, 0, 3, 0, 3, 0, 5, 4, 4, 5, 1, 5, 3, 3, 0, 4, 3, 4, 3, 5, 3, 4, 3, 3, 2, 4, 3, 4, 3, 3, 0, 3, 3, 1, 4, 4, 3, 4, 4, 4, 3, 4, 5, 5, 3, 2, 3, 1, 1, 3, 3, 1, 3, 1, 1, 3, 3, 2, 4, 5, 3, 3, 5, 0, 4, 0, 3, 0, 4, 4, 3, 5, 3, 3, 0, 3, 4, 0, 4, 3),
                  (0, 5, 0, 5, 0, 3, 0, 2, 0, 4, 4, 3, 5, 2, 4, 3, 3, 3, 4, 4, 4, 3, 5, 3, 5, 3, 3, 1, 4, 0, 4, 3, 3, 0, 3, 3, 0, 4, 4, 4, 4, 5, 4, 3, 3, 5, 5, 3, 2, 3, 1, 2, 3, 2, 0, 1, 0, 0, 3, 2, 2, 4, 4, 3, 1, 5, 0, 4, 0, 3, 0, 4, 3, 1, 3, 2, 1, 0, 3, 3, 0, 3, 3),
                  (0, 4, 0, 5, 0, 5, 0, 4, 0, 4, 5, 5, 5, 3, 4, 3, 3, 2, 5, 4, 4, 3, 5, 3, 5, 3, 4, 0, 4, 3, 4, 4, 3, 2, 4, 4, 3, 4, 5, 4, 4, 5, 5, 0, 3, 5, 5, 4, 1, 3, 3, 2, 3, 3, 1, 3, 1, 0, 4, 3, 1, 4, 4, 3, 4, 5, 0, 4, 0, 2, 0, 4, 3, 4, 4, 3, 3, 0, 4, 0, 0, 5, 5),
                  (0, 4, 0, 4, 0, 5, 0, 1, 1, 3, 3, 4, 4, 3, 4, 1, 3, 0, 5, 1, 3, 0, 3, 1, 3, 1, 1, 0, 3, 0, 3, 3, 4, 0, 4, 3, 0, 4, 4, 4, 3, 4, 4, 0, 3, 5, 4, 1, 0, 3, 0, 0, 2, 3, 0, 3, 1, 0, 3, 1, 0, 3, 2, 1, 3, 5, 0, 3, 0, 1, 0, 3, 2, 3, 3, 4, 4, 0, 2, 2, 0, 4, 4),
                  (2, 4, 0, 5, 0, 4, 0, 3, 0, 4, 5, 5, 4, 3, 5, 3, 5, 3, 5, 3, 5, 2, 5, 3, 4, 3, 3, 4, 3, 4, 5, 3, 2, 1, 5, 4, 3, 2, 3, 4, 5, 3, 4, 1, 2, 5, 4, 3, 0, 3, 3, 0, 3, 2, 0, 2, 3, 0, 4, 1, 0, 3, 4, 3, 3, 5, 0, 3, 0, 1, 0, 4, 5, 5, 5, 4, 3, 0, 4, 2, 0, 3, 5),
                  (0, 5, 0, 4, 0, 4, 0, 2, 0, 5, 4, 3, 4, 3, 4, 3, 3, 3, 4, 3, 4, 2, 5, 3, 5, 3, 4, 1, 4, 3, 4, 4, 4, 0, 3, 5, 0, 4, 4, 4, 4, 5, 3, 1, 3, 4, 5, 3, 3, 3, 3, 3, 3, 3, 0, 2, 2, 0, 3, 3, 2, 4, 3, 3, 3, 5, 3, 4, 1, 3, 3, 5, 3, 2, 0, 0, 0, 0, 4, 3, 1, 3, 3),
                  (0, 1, 0, 3, 0, 3, 0, 1, 0, 1, 3, 3, 3, 2, 3, 3, 3, 0, 3, 0, 0, 0, 3, 1, 3, 0, 0, 0, 2, 2, 2, 3, 0, 0, 3, 2, 0, 1, 2, 4, 1, 3, 3, 0, 0, 3, 3, 3, 0, 1, 0, 0, 2, 1, 0, 0, 3, 0, 3, 1, 0, 3, 0, 0, 1, 3, 0, 2, 0, 1, 0, 3, 3, 1, 3, 3, 0, 0, 1, 1, 0, 3, 3),
                  (0, 2, 0, 3, 0, 2, 1, 4, 0, 2, 2, 3, 1, 1, 3, 1, 1, 0, 2, 0, 3, 1, 2, 3, 1, 3, 0, 0, 1, 0, 4, 3, 2, 3, 3, 3, 1, 4, 2, 3, 3, 3, 3, 1, 0, 3, 1, 4, 0, 1, 1, 0, 1, 2, 0, 1, 1, 0, 1, 1, 0, 3, 1, 3, 2, 2, 0, 1, 0, 0, 0, 2, 3, 3, 3, 1, 0, 0, 0, 0, 0, 2, 3),
                  (0, 5, 0, 4, 0, 5, 0, 2, 0, 4, 5, 5, 3, 3, 4, 3, 3, 1, 5, 4, 4, 2, 4, 4, 4, 3, 4, 2, 4, 3, 5, 5, 4, 3, 3, 4, 3, 3, 5, 5, 4, 5, 5, 1, 3, 4, 5, 3, 1, 4, 3, 1, 3, 3, 0, 3, 3, 1, 4, 3, 1, 4, 5, 3, 3, 5, 0, 4, 0, 3, 0, 5, 3, 3, 1, 4, 3, 0, 4, 0, 1, 5, 3),
                  (0, 5, 0, 5, 0, 4, 0, 2, 0, 4, 4, 3, 4, 3, 3, 3, 3, 3, 5, 4, 4, 4, 4, 4, 4, 5, 3, 3, 5, 2, 4, 4, 4, 3, 4, 4, 3, 3, 4, 4, 5, 5, 3, 3, 4, 3, 4, 3, 3, 4, 3, 3, 3, 3, 1, 2, 2, 1, 4, 3, 3, 5, 4, 4, 3, 4, 0, 4, 0, 3, 0, 4, 4, 4, 4, 4, 1, 0, 4, 2, 0, 2, 4),
                  (0, 4, 0, 4, 0, 3, 0, 1, 0, 3, 5, 2, 3, 0, 3, 0, 2, 1, 4, 2, 3, 3, 4, 1, 4, 3, 3, 2, 4, 1, 3, 3, 3, 0, 3, 3, 0, 0, 3, 3, 3, 5, 3, 3, 3, 3, 3, 2, 0, 2, 0, 0, 2, 0, 0, 2, 0, 0, 1, 0, 0, 3, 1, 2, 2, 3, 0, 3, 0, 2, 0, 4, 4, 3, 3, 4, 1, 0, 3, 0, 0, 2, 4),
                  (0, 0, 0, 4, 0, 0, 0, 0, 0, 0, 1, 0, 1, 0, 2, 0, 0, 0, 0, 0, 1, 0, 2, 0, 1, 0, 0, 0, 0, 0, 3, 1, 3, 0, 3, 2, 0, 0, 0, 1, 0, 3, 2, 0, 0, 2, 0, 0, 0, 0, 0, 0, 0, 0, 0, 0, 0, 0, 0, 0, 0, 0, 0, 0, 0, 0, 0, 0, 0, 0, 0, 0, 3, 4, 0, 2, 0, 0, 0, 0, 0, 0, 2),
                  (0, 2, 1, 3, 0, 2, 0, 2, 0, 3, 3, 3, 3, 1, 3, 1, 3, 3, 3, 3, 3, 3, 4, 2, 2, 1, 2, 1, 4, 0, 4, 3, 1, 3, 3, 3, 2, 4, 3, 5, 4, 3, 3, 3, 3, 3, 3, 3, 0, 1, 3, 0, 2, 0, 0, 1, 0, 0, 1, 0, 0, 4, 2, 0, 2, 3, 0, 3, 3, 0, 3, 3, 4, 2, 3, 1, 4, 0, 1, 2, 0, 2, 3),
                  (0, 3, 0, 3, 0, 1, 0, 3, 0, 2, 3, 3, 3, 0, 3, 1, 2, 0, 3, 3, 2, 3, 3, 2, 3, 2, 3, 1, 3, 0, 4, 3, 2, 0, 3, 3, 1, 4, 3, 3, 2, 3, 4, 3, 1, 3, 3, 1, 1, 0, 1, 1, 0, 1, 0, 1, 0, 1, 0, 0, 0, 4, 1, 1, 0, 3, 0, 3, 1, 0, 2, 3, 3, 3, 3, 3, 1, 0, 0, 2, 0, 3, 3),
                  (0, 0, 0, 0, 0, 0, 0, 0, 0, 0, 3, 0, 2, 0, 3, 0, 0, 0, 0, 0, 0, 0, 3, 0, 0, 0, 0, 0, 0, 0, 3, 0, 3, 0, 3, 1, 0, 1, 0, 1, 0, 0, 1, 0, 0, 0, 0, 0, 0, 0, 0, 0, 0, 0, 0, 0, 0, 0, 0, 0, 0, 0, 0, 0, 0, 0, 0, 0, 3, 0, 2, 0, 2, 3, 0, 0, 0, 0, 0, 0, 0, 0, 3),
                  (0, 2, 0, 3, 1, 3, 0, 3, 0, 2, 3, 3, 3, 1, 3, 1, 3, 1, 3, 1, 3, 3, 3, 1, 3, 0, 2, 3, 1, 1, 4, 3, 3, 2, 3, 3, 1, 2, 2, 4, 1, 3, 3, 0, 1, 4, 2, 3, 0, 1, 3, 0, 3, 0, 0, 1, 3, 0, 2, 0, 0, 3, 3, 2, 1, 3, 0, 3, 0, 2, 0, 3, 4, 4, 4, 3, 1, 0, 3, 0, 0, 3, 3),
                  (0, 2, 0, 1, 0, 2, 0, 0, 0, 1, 3, 2, 2, 1, 3, 0, 1, 1, 3, 0, 3, 2, 3, 1, 2, 0, 2, 0, 1, 1, 3, 3, 3, 0, 3, 3, 1, 1, 2, 3, 2, 3, 3, 1, 2, 3, 2, 0, 0, 1, 0, 0, 0, 0, 0, 0, 3, 0, 1, 0, 0, 2, 1, 2, 1, 3, 0, 3, 0, 0, 0, 3, 4, 4, 4, 3, 2, 0, 2, 0, 0, 2, 4),
                  (0, 0, 0, 1, 0, 1, 0, 0, 0, 0, 1, 0, 0, 0, 1, 0, 0, 0, 0, 0, 0, 0, 1, 1, 1, 0, 0, 0, 0, 0, 0, 0, 0, 0, 2, 2, 0, 0, 0, 1, 0, 0, 0, 0, 0, 0, 0, 0, 0, 0, 0, 0, 0, 0, 0, 0, 0, 0, 0, 0, 0, 0, 0, 0, 0, 0, 0, 1, 0, 0, 0, 0, 1, 3, 1, 0, 0, 0, 0, 0, 0, 0, 3),
                  (0, 3, 0, 3, 0, 2, 0, 3, 0, 3, 3, 3, 2, 3, 2, 2, 2, 0, 3, 1, 3, 3, 3, 2, 3, 3, 0, 0, 3, 0, 3, 2, 2, 0, 2, 3, 1, 4, 3, 4, 3, 3, 2, 3, 1, 5, 4, 4, 0, 3, 1, 2, 1, 3, 0, 3, 1, 1, 2, 0, 2, 3, 1, 3, 1, 3, 0, 3, 0, 1, 0, 3, 3, 4, 4, 2, 1, 0, 2, 1, 0, 2, 4),
                  (0, 1, 0, 3, 0, 1, 0, 2, 0, 1, 4, 2, 5, 1, 4, 0, 2, 0, 2, 1, 3, 1, 4, 0, 2, 1, 0, 0, 2, 1, 4, 1, 1, 0, 3, 3, 0, 5, 1, 3, 2, 3, 3, 1, 0, 3, 2, 3, 0, 1, 0, 0, 0, 0, 0, 0, 1, 0, 0, 0, 0, 4, 0, 1, 0, 3, 0, 2, 0, 1, 0, 3, 3, 3, 4, 3, 3, 0, 0, 0, 0, 2, 3),
                  (0, 0, 0, 1, 0, 0, 0, 0, 0, 0, 2, 0, 1, 0, 0, 0, 0, 0, 1, 0, 0, 0, 0, 0, 0, 0, 0, 0, 0, 0, 3, 0, 0, 0, 0, 0, 0, 1, 0, 0, 0, 0, 0, 0, 0, 0, 0, 0, 0, 0, 0, 0, 0, 0, 0, 0, 0, 0, 0, 0, 0, 0, 0, 0, 0, 0, 0, 0, 0, 0, 0, 0, 2, 1, 0, 0, 1, 0, 0, 0, 0, 0, 3),
                  (0, 1, 0, 3, 0, 4, 0, 3, 0, 2, 4, 3, 1, 0, 3, 2, 2, 1, 3, 1, 2, 2, 3, 1, 1, 1, 2, 1, 3, 0, 1, 2, 0, 1, 3, 2, 1, 3, 0, 5, 5, 1, 0, 0, 1, 3, 2, 1, 0, 3, 0, 0, 1, 0, 0, 0, 0, 0, 3, 4, 0, 1, 1, 1, 3, 2, 0, 2, 0, 1, 0, 2, 3, 3, 1, 2, 3, 0, 1, 0, 1, 0, 4),
                  (0, 0, 0, 1, 0, 3, 0, 3, 0, 2, 2, 1, 0, 0, 4, 0, 3, 0, 3, 1, 3, 0, 3, 0, 3, 0, 1, 0, 3, 0, 3, 1, 3, 0, 3, 3, 0, 0, 1, 2, 1, 1, 1, 0, 1, 2, 0, 0, 0, 1, 0, 0, 1, 0, 0, 0, 0, 0, 0, 0, 0, 2, 2, 1, 2, 0, 0, 2, 0, 0, 0, 0, 2, 3, 3, 3, 3, 0, 0, 0, 0, 1, 4),
                  (0, 0, 0, 3, 0, 3, 0, 0, 0, 0, 3, 1, 1, 0, 3, 0, 1, 0, 2, 0, 1, 0, 0, 0, 0, 0, 0, 0, 1, 0, 3, 0, 2, 0, 2, 3, 0, 0, 2, 2, 3, 1, 2, 0, 0, 1, 0, 0, 0, 0, 0, 0, 0, 0, 0, 1, 0, 0, 0, 0, 0, 0, 0, 0, 0, 0, 0, 0, 0, 0, 0, 0, 0, 3, 0, 0, 2, 0, 0, 0, 0, 2, 3),
                  (2, 4, 0, 5, 0, 5, 0, 4, 0, 3, 4, 3, 3, 3, 4, 3, 3, 3, 4, 3, 4, 4, 5, 4, 5, 5, 5, 2, 3, 0, 5, 5, 4, 1, 5, 4, 3, 1, 5, 4, 3, 4, 4, 3, 3, 4, 3, 3, 0, 3, 2, 0, 2, 3, 0, 3, 0, 0, 3, 3, 0, 5, 3, 2, 3, 3, 0, 3, 0, 3, 0, 3, 4, 5, 4, 5, 3, 0, 4, 3, 0, 3, 4),
                  (0, 3, 0, 3, 0, 3, 0, 3, 0, 3, 3, 4, 3, 2, 3, 2, 3, 0, 4, 3, 3, 3, 3, 3, 3, 3, 3, 0, 3, 2, 4, 3, 3, 1, 3, 4, 3, 4, 4, 4, 3, 4, 4, 3, 2, 4, 4, 1, 0, 2, 0, 0, 1, 1, 0, 2, 0, 0, 3, 1, 0, 5, 3, 2, 1, 3, 0, 3, 0, 1, 2, 4, 3, 2, 4, 3, 3, 0, 3, 2, 0, 4, 4),
                  (0, 3, 0, 3, 0, 1, 0, 0, 0, 1, 4, 3, 3, 2, 3, 1, 3, 1, 4, 2, 3, 2, 4, 2, 3, 4, 3, 0, 2, 2, 3, 3, 3, 0, 3, 3, 3, 0, 3, 4, 1, 3, 3, 0, 3, 4, 3, 3, 0, 1, 1, 0, 1, 0, 0, 0, 4, 0, 3, 0, 0, 3, 1, 2, 1, 3, 0, 4, 0, 1, 0, 4, 3, 3, 4, 3, 3, 0, 2, 0, 0, 3, 3),
                  (0, 3, 0, 4, 0, 1, 0, 3, 0, 3, 4, 3, 3, 0, 3, 3, 3, 1, 3, 1, 3, 3, 4, 3, 3, 3, 0, 0, 3, 1, 5, 3, 3, 1, 3, 3, 2, 5, 4, 3, 3, 4, 5, 3, 2, 5, 3, 4, 0, 1, 0, 0, 0, 0, 0, 2, 0, 0, 1, 1, 0, 4, 2, 2, 1, 3, 0, 3, 0, 2, 0, 4, 4, 3, 5, 3, 2, 0, 1, 1, 0, 3, 4),
                  (0, 5, 0, 4, 0, 5, 0, 2, 0, 4, 4, 3, 3, 2, 3, 3, 3, 1, 4, 3, 4, 1, 5, 3, 4, 3, 4, 0, 4, 2, 4, 3, 4, 1, 5, 4, 0, 4, 4, 4, 4, 5, 4, 1, 3, 5, 4, 2, 1, 4, 1, 1, 3, 2, 0, 3, 1, 0, 3, 2, 1, 4, 3, 3, 3, 4, 0, 4, 0, 3, 0, 4, 4, 4, 3, 3, 3, 0, 4, 2, 0, 3, 4),
                  (1, 4, 0, 4, 0, 3, 0, 1, 0, 3, 3, 3, 1, 1, 3, 3, 2, 2, 3, 3, 1, 0, 3, 2, 2, 1, 2, 0, 3, 1, 2, 1, 2, 0, 3, 2, 0, 2, 2, 3, 3, 4, 3, 0, 3, 3, 1, 2, 0, 1, 1, 3, 1, 2, 0, 0, 3, 0, 1, 1, 0, 3, 2, 2, 3, 3, 0, 3, 0, 0, 0, 2, 3, 3, 4, 3, 3, 0, 1, 0, 0, 1, 4),
                  (0, 4, 0, 4, 0, 4, 0, 0, 0, 3, 4, 4, 3, 1, 4, 2, 3, 2, 3, 3, 3, 1, 4, 3, 4, 0, 3, 0, 4, 2, 3, 3, 2, 2, 5, 4, 2, 1, 3, 4, 3, 4, 3, 1, 3, 3, 4, 2, 0, 2, 1, 0, 3, 3, 0, 0, 2, 0, 3, 1, 0, 4, 4, 3, 4, 3, 0, 4, 0, 1, 0, 2, 4, 4, 4, 4, 4, 0, 3, 2, 0, 3, 3),
                  (0, 0, 0, 1, 0, 4, 0, 0, 0, 0, 0, 0, 1, 1, 1, 0, 0, 0, 0, 0, 0, 0, 0, 0, 1, 0, 0, 0, 0, 0, 0, 0, 1, 0, 3, 2, 0, 0, 1, 0, 0, 0, 1, 0, 0, 0, 0, 0, 0, 1, 0, 0, 0, 0, 0, 0, 0, 0, 0, 0, 0, 0, 0, 0, 0, 0, 0, 0, 0, 0, 0, 0, 0, 0, 0, 0, 1, 0, 0, 0, 0, 0, 2),
                  (0, 2, 0, 3, 0, 4, 0, 4, 0, 1, 3, 3, 3, 0, 4, 0, 2, 1, 2, 1, 1, 1, 2, 0, 3, 1, 1, 0, 1, 0, 3, 1, 0, 0, 3, 3, 2, 0, 1, 1, 0, 0, 0, 0, 0, 1, 0, 2, 0, 2, 2, 0, 3, 1, 0, 0, 1, 0, 1, 1, 0, 1, 2, 0, 3, 0, 0, 0, 0, 1, 0, 0, 3, 3, 4, 3, 1, 0, 1, 0, 3, 0, 2),
                  (0, 0, 0, 3, 0, 5, 0, 0, 0, 0, 1, 0, 2, 0, 3, 1, 0, 1, 3, 0, 0, 0, 2, 0, 0, 0, 1, 0, 0, 0, 1, 1, 0, 0, 4, 0, 0, 0, 2, 3, 0, 1, 4, 1, 0, 2, 0, 0, 0, 0, 0, 0, 0, 0, 0, 0, 0, 0, 0, 3, 0, 0, 0, 0, 0, 1, 0, 0, 0, 0, 0, 0, 0, 2, 0, 0, 3, 0, 0, 0, 0, 0, 3),
                  (0, 2, 0, 5, 0, 5, 0, 1, 0, 2, 4, 3, 3, 2, 5, 1, 3, 2, 3, 3, 3, 0, 4, 1, 2, 0, 3, 0, 4, 0, 2, 2, 1, 1, 5, 3, 0, 0, 1, 4, 2, 3, 2, 0, 3, 3, 3, 2, 0, 2, 4, 1, 1, 2, 0, 1, 1, 0, 3, 1, 0, 1, 3, 1, 2, 3, 0, 2, 0, 0, 0, 1, 3, 5, 4, 4, 4, 0, 3, 0, 0, 1, 3),
                  (0, 4, 0, 5, 0, 4, 0, 4, 0, 4, 5, 4, 3, 3, 4, 3, 3, 3, 4, 3, 4, 4, 5, 3, 4, 5, 4, 2, 4, 2, 3, 4, 3, 1, 4, 4, 1, 3, 5, 4, 4, 5, 5, 4, 4, 5, 5, 5, 2, 3, 3, 1, 4, 3, 1, 3, 3, 0, 3, 3, 1, 4, 3, 4, 4, 4, 0, 3, 0, 4, 0, 3, 3, 4, 4, 5, 0, 0, 4, 3, 0, 4, 5),
                  (0, 4, 0, 4, 0, 3, 0, 3, 0, 3, 4, 4, 4, 3, 3, 2, 4, 3, 4, 3, 4, 3, 5, 3, 4, 3, 2, 1, 4, 2, 4, 4, 3, 1, 3, 4, 2, 4, 5, 5, 3, 4, 5, 4, 1, 5, 4, 3, 0, 3, 2, 2, 3, 2, 1, 3, 1, 0, 3, 3, 3, 5, 3, 3, 3, 5, 4, 4, 2, 3, 3, 4, 3, 3, 3, 2, 1, 0, 3, 2, 1, 4, 3),
                  (0, 4, 0, 5, 0, 4, 0, 3, 0, 3, 5, 5, 3, 2, 4, 3, 4, 0, 5, 4, 4, 1, 4, 4, 4, 3, 3, 3, 4, 3, 5, 5, 2, 3, 3, 4, 1, 2, 5, 5, 3, 5, 5, 2, 3, 5, 5, 4, 0, 3, 2, 0, 3, 3, 1, 1, 5, 1, 4, 1, 0, 4, 3, 2, 3, 5, 0, 4, 0, 3, 0, 5, 4, 3, 4, 3, 0, 0, 4, 1, 0, 4, 4),
                  (1, 3, 0, 4, 0, 2, 0, 2, 0, 2, 5, 5, 3, 3, 3, 3, 3, 0, 4, 2, 3, 4, 4, 4, 3, 4, 0, 0, 3, 4, 5, 4, 3, 3, 3, 3, 2, 5, 5, 4, 5, 5, 5, 4, 3, 5, 5, 5, 1, 3, 1, 0, 1, 0, 0, 3, 2, 0, 4, 2, 0, 5, 2, 3, 2, 4, 1, 3, 0, 3, 0, 4, 5, 4, 5, 4, 3, 0, 4, 2, 0, 5, 4),
                  (0, 3, 0, 4, 0, 5, 0, 3, 0, 3, 4, 4, 3, 2, 3, 2, 3, 3, 3, 3, 3, 2, 4, 3, 3, 2, 2, 0, 3, 3, 3, 3, 3, 1, 3, 3, 3, 0, 4, 4, 3, 4, 4, 1, 1, 4, 4, 2, 0, 3, 1, 0, 1, 1, 0, 4, 1, 0, 2, 3, 1, 3, 3, 1, 3, 4, 0, 3, 0, 1, 0, 3, 1, 3, 0, 0, 1, 0, 2, 0, 0, 4, 4),
                  (0, 0, 0, 0, 0, 0, 0, 0, 0, 0, 0, 0, 0, 0, 0, 0, 0, 0, 0, 0, 0, 0, 0, 0, 0, 0, 0, 0, 0, 0, 0, 0, 0, 0, 0, 0, 0, 0, 0, 0, 0, 0, 0, 0, 0, 0, 0, 0, 0, 0, 0, 0, 0, 0, 0, 0, 0, 0, 0, 0, 0, 0, 0, 0, 0, 0, 0, 0, 0, 0, 0, 0, 0, 0, 0, 0, 0, 0, 0, 0, 0, 0, 0),
                  (0, 3, 0, 3, 0, 2, 0, 3, 0, 1, 5, 4, 3, 3, 3, 1, 4, 2, 1, 2, 3, 4, 4, 2, 4, 4, 5, 0, 3, 1, 4, 3, 4, 0, 4, 3, 3, 3, 2, 3, 2, 5, 3, 4, 3, 2, 2, 3, 0, 0, 3, 0, 2, 1, 0, 1, 2, 0, 0, 0, 0, 2, 1, 1, 3, 1, 0, 2, 0, 4, 0, 3, 4, 4, 4, 5, 2, 0, 2, 0, 0, 1, 3),
                  (0, 0, 0, 0, 0, 0, 0, 0, 0, 0, 0, 0, 0, 0, 1, 0, 0, 0, 0, 0, 1, 1, 1, 0, 0, 1, 1, 0, 0, 0, 4, 2, 1, 1, 0, 1, 0, 3, 2, 0, 0, 3, 1, 1, 1, 2, 2, 0, 0, 0, 0, 0, 0, 0, 0, 0, 0, 0, 0, 0, 0, 3, 0, 1, 0, 0, 0, 2, 0, 0, 0, 1, 4, 0, 4, 2, 1, 0, 0, 0, 0, 0, 1),
                  (0, 0, 0, 0, 0, 0, 0, 0, 0, 1, 0, 1, 0, 0, 0, 0, 1, 0, 0, 0, 0, 0, 0, 1, 0, 1, 0, 0, 0, 0, 3, 1, 0, 0, 0, 2, 0, 2, 1, 0, 0, 1, 2, 1, 0, 1, 1, 0, 0, 3, 0, 0, 0, 0, 0, 0, 0, 0, 0, 0, 0, 1, 3, 1, 0, 0, 0, 0, 0, 1, 0, 0, 2, 1, 0, 0, 0, 0, 0, 0, 0, 0, 2),
                  (0, 4, 0, 4, 0, 4, 0, 3, 0, 4, 4, 3, 4, 2, 4, 3, 2, 0, 4, 4, 4, 3, 5, 3, 5, 3, 3, 2, 4, 2, 4, 3, 4, 3, 1, 4, 0, 2, 3, 4, 4, 4, 3, 3, 3, 4, 4, 4, 3, 4, 1, 3, 4, 3, 2, 1, 2, 1, 3, 3, 3, 4, 4, 3, 3, 5, 0, 4, 0, 3, 0, 4, 3, 3, 3, 2, 1, 0, 3, 0, 0, 3, 3),
                  (0, 4, 0, 3, 0, 3, 0, 3, 0, 3, 5, 5, 3, 3, 3, 3, 4, 3, 4, 3, 3, 3, 4, 4, 4, 3, 3, 3, 3, 4, 3, 5, 3, 3, 1, 3, 2, 4, 5, 5, 5, 5, 4, 3, 4, 5, 5, 3, 2, 2, 3, 3, 3, 3, 2, 3, 3, 1, 2, 3, 2, 4, 3, 3, 3, 4, 0, 4, 0, 2, 0, 4, 3, 2, 2, 1, 2, 0, 3, 0, 0, 4, 1))

class JapaneseContextAnalysis:

    def __init__(self):
        self.reset()

    def reset(self):
        self._mTotalRel = 0
        self._mRelSample = [
         0] * NUM_OF_CATEGORY
        self._mNeedToSkipCharNum = 0
        self._mLastCharOrder = -1
        self._mDone = False

    def feed(self, aBuf, aLen):
        if self._mDone:
            return
        else:
            i = self._mNeedToSkipCharNum
            while i < aLen:
                order, charLen = self.get_order(aBuf[i:i + 2])
                i += charLen
                if i > aLen:
                    self._mNeedToSkipCharNum = i - aLen
                    self._mLastCharOrder = -1
                else:
                    if order != -1:
                        if self._mLastCharOrder != -1:
                            self._mTotalRel += 1
                            if self._mTotalRel > MAX_REL_THRESHOLD:
                                self._mDone = True
                                break
                            self._mRelSample[jp2CharContext[self._mLastCharOrder][order]] += 1
                    self._mLastCharOrder = order

    def got_enough_data(self):
        return self._mTotalRel > ENOUGH_REL_THRESHOLD

    def get_confidence(self):
        if self._mTotalRel > MINIMUM_DATA_THRESHOLD:
            return (self._mTotalRel - self._mRelSample[0]) / self._mTotalRel
        return DONT_KNOW

    def get_order(self, aBuf):
        return (-1, 1)


class SJISContextAnalysis(JapaneseContextAnalysis):

    def __init__(self):
        self.charset_name = 'SHIFT_JIS'

    def get_charset_name(self):
        return self.charset_name

    def get_order--- This code section failed: ---

 L. 187         0  LOAD_FAST                'aBuf'
                2  POP_JUMP_IF_TRUE      8  'to 8'

 L. 188         4  LOAD_CONST               (-1, 1)
                6  RETURN_VALUE     
              8_0  COME_FROM             2  '2'

 L. 190         8  LOAD_GLOBAL              wrap_ord
               10  LOAD_FAST                'aBuf'
               12  LOAD_CONST               0
               14  BINARY_SUBSCR    
               16  CALL_FUNCTION_1       1  ''
               18  STORE_FAST               'first_char'

 L. 191        20  LOAD_CONST               129
               22  LOAD_FAST                'first_char'
               24  DUP_TOP          
               26  ROT_THREE        
               28  COMPARE_OP               <=
               30  POP_JUMP_IF_FALSE    40  'to 40'
               32  LOAD_CONST               159
               34  COMPARE_OP               <=
               36  POP_JUMP_IF_TRUE     66  'to 66'
               38  JUMP_FORWARD         42  'to 42'
             40_0  COME_FROM            30  '30'
               40  POP_TOP          
             42_0  COME_FROM            38  '38'
               42  LOAD_CONST               224
               44  LOAD_FAST                'first_char'
               46  DUP_TOP          
               48  ROT_THREE        
               50  COMPARE_OP               <=
               52  POP_JUMP_IF_FALSE    62  'to 62'
               54  LOAD_CONST               252
               56  COMPARE_OP               <=
               58  POP_JUMP_IF_FALSE   110  'to 110'
               60  JUMP_FORWARD         66  'to 66'
             62_0  COME_FROM            52  '52'
               62  POP_TOP          
               64  JUMP_FORWARD        110  'to 110'
             66_0  COME_FROM            60  '60'
             66_1  COME_FROM            36  '36'

 L. 192        66  LOAD_CONST               2
               68  STORE_FAST               'charLen'

 L. 193        70  LOAD_FAST                'first_char'
               72  LOAD_CONST               135
               74  COMPARE_OP               ==
               76  POP_JUMP_IF_TRUE    102  'to 102'
               78  LOAD_CONST               250
               80  LOAD_FAST                'first_char'
               82  DUP_TOP          
               84  ROT_THREE        
               86  COMPARE_OP               <=
               88  POP_JUMP_IF_FALSE    98  'to 98'
               90  LOAD_CONST               252
               92  COMPARE_OP               <=
               94  POP_JUMP_IF_FALSE   114  'to 114'
               96  JUMP_FORWARD        102  'to 102'
             98_0  COME_FROM            88  '88'
               98  POP_TOP          
              100  JUMP_ABSOLUTE       114  'to 114'
            102_0  COME_FROM            96  '96'
            102_1  COME_FROM            76  '76'

 L. 194       102  LOAD_STR                 'CP932'
              104  LOAD_FAST                'self'
              106  STORE_ATTR               charset_name
              108  JUMP_FORWARD        114  'to 114'
            110_0  COME_FROM            64  '64'
            110_1  COME_FROM            58  '58'

 L. 196       110  LOAD_CONST               1
              112  STORE_FAST               'charLen'
            114_0  COME_FROM           108  '108'
            114_1  COME_FROM            94  '94'

 L. 199       114  LOAD_GLOBAL              len
              116  LOAD_FAST                'aBuf'
              118  CALL_FUNCTION_1       1  ''
              120  LOAD_CONST               1
              122  COMPARE_OP               >
              124  POP_JUMP_IF_FALSE   182  'to 182'

 L. 200       126  LOAD_GLOBAL              wrap_ord
              128  LOAD_FAST                'aBuf'
              130  LOAD_CONST               1
              132  BINARY_SUBSCR    
              134  CALL_FUNCTION_1       1  ''
              136  STORE_FAST               'second_char'

 L. 201       138  LOAD_FAST                'first_char'
              140  LOAD_CONST               202
              142  COMPARE_OP               ==
              144  POP_JUMP_IF_FALSE   182  'to 182'
              146  LOAD_CONST               159
              148  LOAD_FAST                'second_char'
              150  DUP_TOP          
              152  ROT_THREE        
              154  COMPARE_OP               <=
              156  POP_JUMP_IF_FALSE   166  'to 166'
              158  LOAD_CONST               241
              160  COMPARE_OP               <=
              162  POP_JUMP_IF_FALSE   182  'to 182'
              164  JUMP_FORWARD        170  'to 170'
            166_0  COME_FROM           156  '156'
              166  POP_TOP          
              168  JUMP_FORWARD        182  'to 182'
            170_0  COME_FROM           164  '164'

 L. 202       170  LOAD_FAST                'second_char'
              172  LOAD_CONST               159
              174  BINARY_SUBTRACT  
              176  LOAD_FAST                'charLen'
              178  BUILD_TUPLE_2         2 
              180  RETURN_VALUE     
            182_0  COME_FROM           168  '168'
            182_1  COME_FROM           162  '162'
            182_2  COME_FROM           144  '144'
            182_3  COME_FROM           124  '124'

 L. 204       182  LOAD_CONST               -1
              184  LOAD_FAST                'charLen'
              186  BUILD_TUPLE_2         2 
              188  RETURN_VALUE     
               -1  RETURN_LAST      

Parse error at or near `COME_FROM' instruction at offset 110_0


class EUCJPContextAnalysis(JapaneseContextAnalysis):

    def get_order(self, aBuf):
        if not aBuf:
            return (-1, 1)
        else:
            first_char = wrap_ord(aBuf[0])
            if not first_char == 142:
                if 161 <= first_char <= 254:
                    charLen = 2
            elif first_char == 143:
                charLen = 3
            else:
                charLen = 1
        if len(aBuf) > 1:
            second_char = wrap_ord(aBuf[1])
            if first_char == 164:
                if 161 <= second_char <= 243:
                    return (
                     second_char - 161, charLen)
        return (
         -1, charLen)