Instruction context:
   
 L. 596        66  LOAD_FAST                'self'
                  68  LOAD_ATTR                _root
                  70  POP_BLOCK        
->                72  CALL_FINALLY        124  'to 124'
                  74  RETURN_VALUE     
                76_0  COME_FROM            52  '52'
                76_1  COME_FROM            36  '36'
Instruction context:
   
 L. 939       384  LOAD_FAST                'write'
                 386  LOAD_STR                 '</'
                 388  LOAD_FAST                'tag'
                 390  BINARY_ADD       
                 392  LOAD_STR                 '>'
                 394  BINARY_ADD       
                 396  CALL_FUNCTION_1       1  ''
                 398  POP_TOP          
->               400  JUMP_FORWARD        410  'to 410'
               402_0  COME_FROM           324  '324'
Instruction context:
   
 L.1070        68  DUP_TOP          
                  70  LOAD_GLOBAL              TypeError
                  72  LOAD_GLOBAL              AttributeError
                  74  BUILD_TUPLE_2         2 
                  76  COMPARE_OP               exception-match
                  78  POP_JUMP_IF_FALSE    98  'to 98'
                  80  POP_TOP          
->                82  POP_TOP          
                  84  POP_TOP          
Instruction context:
   
 L.1098       168  DUP_TOP          
                 170  LOAD_GLOBAL              TypeError
                 172  LOAD_GLOBAL              AttributeError
                 174  BUILD_TUPLE_2         2 
                 176  COMPARE_OP               exception-match
                 178  POP_JUMP_IF_FALSE   198  'to 198'
                 180  POP_TOP          
->               182  POP_TOP          
                 184  POP_TOP          
Instruction context:
   
 L.1111        68  DUP_TOP          
                  70  LOAD_GLOBAL              TypeError
                  72  LOAD_GLOBAL              AttributeError
                  74  BUILD_TUPLE_2         2 
                  76  COMPARE_OP               exception-match
                  78  POP_JUMP_IF_FALSE    98  'to 98'
                  80  POP_TOP          
->                82  POP_TOP          
                  84  POP_TOP          
Instruction context:
   
 L.1708       102  LOAD_FAST                'close_handler'
                 104  CALL_FUNCTION_0       0  ''
                 106  POP_BLOCK        
->               108  CALL_FINALLY        116  'to 116'
                 110  RETURN_VALUE     
               112_0  COME_FROM            98  '98'
                 112  POP_BLOCK        
                 114  BEGIN_FINALLY    
               116_0  COME_FROM           108  '108'
               116_1  COME_FROM_FINALLY    66  '66'
Instruction context:
   
 L.1904        14  LOAD_CLOSURE             'self'
                  16  BUILD_TUPLE_1         1 
->                18  LOAD_DICTCOMP            '<code_object <dictcomp>>'
                  20  LOAD_STR                 'C14NWriterTarget._start.<locals>.<dictcomp>'
                  22  MAKE_FUNCTION_8          'closure'
                  24  LOAD_FAST                'attrs'
                  26  LOAD_METHOD              items
                  28  CALL_METHOD_0         0  ''
                  30  GET_ITER         
                  32  CALL_FUNCTION_1       1  ''
                  34  STORE_FAST               'attrs'
                36_0  COME_FROM            12  '12'
                36_1  COME_FROM             8  '8'
Instruction context:
   
 L.2024        88  DUP_TOP          
                  90  LOAD_GLOBAL              TypeError
                  92  LOAD_GLOBAL              AttributeError
                  94  BUILD_TUPLE_2         2 
                  96  COMPARE_OP               exception-match
                  98  POP_JUMP_IF_FALSE   118  'to 118'
                 100  POP_TOP          
->               102  POP_TOP          
                 104  POP_TOP          
Instruction context:
   
 L.2044       128  DUP_TOP          
                 130  LOAD_GLOBAL              TypeError
                 132  LOAD_GLOBAL              AttributeError
                 134  BUILD_TUPLE_2         2 
                 136  COMPARE_OP               exception-match
                 138  POP_JUMP_IF_FALSE   158  'to 158'
                 140  POP_TOP          
->               142  POP_TOP          
                 144  POP_TOP          

../test/151747.pyc -- 
# decompile failed

# file ../test/151747.pyc
# Deparsing stopped due to parse error
