Instruction context:
   
 L. 293        24  LOAD_FAST                'f'
                  26  LOAD_METHOD              read
                  28  CALL_METHOD_0         0  ''
                  30  LOAD_METHOD              strip
                  32  CALL_METHOD_0         0  ''
                  34  POP_BLOCK        
->                36  ROT_TWO          
                  38  BEGIN_FINALLY    
                  40  WITH_CLEANUP_START
                  42  WITH_CLEANUP_FINISH
                  44  POP_FINALLY           0  ''
                  46  POP_BLOCK        
                  48  RETURN_VALUE     
                50_0  COME_FROM_WITH       20  '20'
                  50  WITH_CLEANUP_START
                  52  WITH_CLEANUP_FINISH
                  54  END_FINALLY      
                  56  POP_BLOCK        
                  58  JUMP_FORWARD        102  'to 102'
                60_0  COME_FROM_FINALLY     0  '0'
Instruction context:
   
 L. 627       122  LOAD_FAST                'cpus'
                 124  POP_BLOCK        
->               126  ROT_TWO          
                 128  BEGIN_FINALLY    
                 130  WITH_CLEANUP_START
                 132  WITH_CLEANUP_FINISH
                 134  POP_FINALLY           0  ''
                 136  RETURN_VALUE     
               138_0  COME_FROM_WITH       28  '28'
                 138  WITH_CLEANUP_START
                 140  WITH_CLEANUP_FINISH
Instruction context:
   
 L. 634        14  DUP_TOP          
                  16  LOAD_GLOBAL              ValueError
                  18  COMPARE_OP               exception-match
                  20  POP_JUMP_IF_FALSE   198  'to 198'
                  22  POP_TOP          
->                24  POP_TOP          
                  26  POP_TOP          
Instruction context:
   
 L. 832        76  POP_EXCEPT       
                  78  JUMP_BACK            28  'to 28'
->                80  POP_EXCEPT       
                  82  JUMP_BACK            28  'to 28'
                84_0  COME_FROM            68  '68'
Instruction context:
   
 L. 858        56  POP_EXCEPT       
                  58  JUMP_BACK            10  'to 10'
->                60  POP_EXCEPT       
                  62  JUMP_BACK            10  'to 10'
                64_0  COME_FROM            48  '48'
                  64  END_FINALLY      
                  66  JUMP_BACK            10  'to 10'
Instruction context:
   
 L. 949       274  POP_EXCEPT       
                 276  JUMP_BACK            60  'to 60'
->               278  POP_EXCEPT       
                 280  JUMP_FORWARD        284  'to 284'
               282_0  COME_FROM           264  '264'
                 282  END_FINALLY      
               284_0  COME_FROM           280  '280'
               284_1  COME_FROM           256  '256'
Instruction context:
   
 L. 964        92  POP_EXCEPT       
->                94  JUMP_BACK            26  'to 26'
                96_0  COME_FROM            90  '90'
Instruction context:
   
 L.1282       212  POP_EXCEPT       
                 214  JUMP_BACK           122  'to 122'
->               216  POP_EXCEPT       
                 218  JUMP_FORWARD        222  'to 222'
               220_0  COME_FROM           204  '204'
                 220  END_FINALLY      
               222_0  COME_FROM           218  '218'
               222_1  COME_FROM           190  '190'
Instruction context:
   
 L.1370       122  POP_BLOCK        
                 124  POP_EXCEPT       
->               126  CALL_FINALLY        134  'to 134'
                 128  JUMP_BACK            60  'to 60'
                 130  POP_BLOCK        
                 132  BEGIN_FINALLY    
               134_0  COME_FROM           126  '126'
               134_1  COME_FROM_FINALLY   104  '104'
                 134  LOAD_CONST               None
                 136  STORE_FAST               'err'
                 138  DELETE_FAST              'err'
                 140  END_FINALLY      
                 142  POP_EXCEPT       
                 144  JUMP_FORWARD        148  'to 148'
               146_0  COME_FROM            96  '96'
                 146  END_FINALLY      
               148_0  COME_FROM           144  '144'
               148_1  COME_FROM            84  '84'
Instruction context:
   
 L.1500        62  LOAD_FAST                'ret'
                  64  ROT_TWO          
                  66  POP_TOP          
->                68  POP_BLOCK        
                  70  ROT_TWO          
                  72  BEGIN_FINALLY    
                  74  WITH_CLEANUP_START
                  76  WITH_CLEANUP_FINISH
                  78  POP_FINALLY           0  ''
                  80  RETURN_VALUE     
                  82  JUMP_BACK            24  'to 24'
Instruction context:
   
 L.1541        74  LOAD_FAST                'tgid'
                  76  LOAD_FAST                'pid'
                  78  COMPARE_OP               ==
                  80  ROT_TWO          
                  82  POP_TOP          
->                84  POP_BLOCK        
                  86  ROT_TWO          
                  88  BEGIN_FINALLY    
                  90  WITH_CLEANUP_START
                  92  WITH_CLEANUP_FINISH
                  94  POP_FINALLY           0  ''
                  96  POP_BLOCK        
                  98  RETURN_VALUE     
                 100  JUMP_BACK            44  'to 44'
Instruction context:
   
 L.1577        20  DUP_TOP          
                  22  LOAD_GLOBAL              PermissionError
                  24  COMPARE_OP               exception-match
                  26  POP_JUMP_IF_FALSE    52  'to 52'
                  28  POP_TOP          
->                30  POP_TOP          
                  32  POP_TOP          
Instruction context:
   
 L.1650        22  LOAD_FAST                'f'
                  24  LOAD_METHOD              read
                  26  CALL_METHOD_0         0  ''
                  28  POP_BLOCK        
->                30  ROT_TWO          
                  32  BEGIN_FINALLY    
                  34  WITH_CLEANUP_START
                  36  WITH_CLEANUP_FINISH
                  38  POP_FINALLY           0  ''
                  40  RETURN_VALUE     
                42_0  COME_FROM_WITH       18  '18'
                  42  WITH_CLEANUP_START
                  44  WITH_CLEANUP_FINISH
Instruction context:
   
 L.1657        26  LOAD_FAST                'f'
                  28  LOAD_METHOD              read
                  30  CALL_METHOD_0         0  ''
                  32  LOAD_METHOD              strip
                  34  CALL_METHOD_0         0  ''
                  36  POP_BLOCK        
->                38  ROT_TWO          
                  40  BEGIN_FINALLY    
                  42  WITH_CLEANUP_START
                  44  WITH_CLEANUP_FINISH
                  46  POP_FINALLY           0  ''
                  48  RETURN_VALUE     
                50_0  COME_FROM_WITH       22  '22'
                  50  WITH_CLEANUP_START
                  52  WITH_CLEANUP_FINISH
Instruction context:
   
 L.1680        24  DUP_TOP          
                  26  LOAD_GLOBAL              FileNotFoundError
                  28  LOAD_GLOBAL              ProcessLookupError
                  30  BUILD_TUPLE_2         2 
                  32  COMPARE_OP               exception-match
                  34  POP_JUMP_IF_FALSE   120  'to 120'
                  36  POP_TOP          
->                38  POP_TOP          
                  40  POP_TOP          
Instruction context:
   
 L.1731        36  DUP_TOP          
                  38  LOAD_GLOBAL              KeyError
                  40  COMPARE_OP               exception-match
                  42  POP_JUMP_IF_FALSE    56  'to 56'
                  44  POP_TOP          
->                46  POP_TOP          
                  48  POP_TOP          
Instruction context:
   
 L.1749        84  POP_EXCEPT       
                  86  JUMP_BACK            34  'to 34'
->                88  POP_EXCEPT       
                  90  JUMP_BACK            34  'to 34'
                92_0  COME_FROM            76  '76'
                  92  END_FINALLY      
                94_0  COME_FROM            68  '68'
Instruction context:
   
 L.1875       122  POP_EXCEPT       
->               124  JUMP_BACK             8  'to 8'
                 126  JUMP_FORWARD        140  'to 140'
               128_0  COME_FROM           120  '120'
Instruction context:
   
 L.1924        24  DUP_TOP          
                  26  LOAD_GLOBAL              FileNotFoundError
                  28  LOAD_GLOBAL              ProcessLookupError
                  30  BUILD_TUPLE_2         2 
                  32  COMPARE_OP               exception-match
                  34  POP_JUMP_IF_FALSE    90  'to 90'
                  36  POP_TOP          
->                38  POP_TOP          
                  40  POP_TOP          
Instruction context:
   
 L.1969       120  POP_EXCEPT       
                 122  JUMP_BACK            42  'to 42'
->               124  POP_EXCEPT       
                 126  JUMP_FORWARD        130  'to 130'
               128_0  COME_FROM           108  '108'
                 128  END_FINALLY      
               130_0  COME_FROM           126  '126'
               130_1  COME_FROM           100  '100'
Instruction context:
   
 L.2098        94  POP_EXCEPT       
                  96  JUMP_BACK            34  'to 34'
->                98  POP_EXCEPT       
                 100  JUMP_BACK            34  'to 34'
               102_0  COME_FROM            82  '82'

../test/157323.pyc -- 
# decompile failed

# file ../test/157323.pyc
# Deparsing stopped due to parse error
