Instruction context:
   
 L. 206       106  LOAD_FAST                'self'
                 108  LOAD_METHOD              _get_cached_btype
                 110  LOAD_FAST                'cdecl'
                 112  LOAD_ATTR                _cffi_base_type
                 114  CALL_METHOD_1         1  ''
                 116  POP_BLOCK        
->               118  ROT_TWO          
                 120  BEGIN_FINALLY    
                 122  WITH_CLEANUP_START
                 124  WITH_CLEANUP_FINISH
                 126  POP_FINALLY           0  ''
                 128  RETURN_VALUE     
               130_0  COME_FROM_WITH      102  '102'
                 130  WITH_CLEANUP_START
                 132  WITH_CLEANUP_FINISH
                 134  END_FINALLY      
               136_0  COME_FROM            96  '96'
               136_1  COME_FROM            86  '86'
Instruction context:
   
 L. 483         8  LOAD_GLOBAL              model
                  10  LOAD_METHOD              pointer_cache
                  12  LOAD_FAST                'self'
                  14  LOAD_FAST                'ctype'
                  16  CALL_METHOD_2         2  ''
                  18  POP_BLOCK        
->                20  ROT_TWO          
                  22  BEGIN_FINALLY    
                  24  WITH_CLEANUP_START
                  26  WITH_CLEANUP_FINISH
                  28  POP_FINALLY           0  ''
                  30  RETURN_VALUE     
                32_0  COME_FROM_WITH        4  '4'
                  32  WITH_CLEANUP_START
                  34  WITH_CLEANUP_FINISH
Instruction context:
   
 L. 743       100  LOAD_FAST                'x'
                 102  LOAD_CONST               1
                 104  BINARY_SUBSCR    
                 106  POP_BLOCK        
->               108  ROT_TWO          
                 110  BEGIN_FINALLY    
                 112  WITH_CLEANUP_START
                 114  WITH_CLEANUP_FINISH
                 116  POP_FINALLY           0  ''
                 118  RETURN_VALUE     
               120_0  COME_FROM            98  '98'
Instruction context:
   
 L. 850        12  DUP_TOP          
                  14  LOAD_GLOBAL              KeyError
                  16  COMPARE_OP               exception-match
                  18  POP_JUMP_IF_FALSE   140  'to 140'
                  20  POP_TOP          
->                22  POP_TOP          
                  24  POP_TOP          
Instruction context:
   
 L. 899        28  POP_BLOCK        
->                30  BEGIN_FINALLY    
                  32  WITH_CLEANUP_START
                  34  WITH_CLEANUP_FINISH
                  36  POP_FINALLY           0  ''
                  38  LOAD_CONST               None
                  40  RETURN_VALUE     
                42_0  COME_FROM            26  '26'
Instruction context:
   
 L. 921        14  LOAD_DEREF               'accessors'
                  16  LOAD_METHOD              keys
                  18  CALL_METHOD_0         0  ''
                  20  POP_BLOCK        
->                22  ROT_TWO          
                  24  BEGIN_FINALLY    
                  26  WITH_CLEANUP_START
                  28  WITH_CLEANUP_FINISH
                  30  POP_FINALLY           0  ''
                  32  RETURN_VALUE     
                34_0  COME_FROM_WITH        4  '4'
                  34  WITH_CLEANUP_START
                  36  WITH_CLEANUP_FINISH
Instruction context:
   
 L. 961        82  LOAD_FAST                'ffi'
                  84  LOAD_METHOD              _get_cached_btype
                  86  LOAD_FAST                'tp'
                  88  CALL_METHOD_1         1  ''
                  90  POP_BLOCK        
->                92  ROT_TWO          
                  94  BEGIN_FINALLY    
                  96  WITH_CLEANUP_START
                  98  WITH_CLEANUP_FINISH
                 100  POP_FINALLY           0  ''
                 102  RETURN_VALUE     
               104_0  COME_FROM_WITH       78  '78'
                 104  WITH_CLEANUP_START
                 106  WITH_CLEANUP_FINISH

../test/183380.pyc -- 
# decompile failed

# file ../test/183380.pyc
# Deparsing stopped due to parse error
