Instruction context:
   
 L. 688        38  POP_EXCEPT       
->                40  LOAD_CONST               None
                  42  RETURN_VALUE     
                44_0  COME_FROM            36  '36'
Instruction context:
   
 L. 704        38  POP_EXCEPT       
->                40  LOAD_CONST               None
                  42  RETURN_VALUE     
                44_0  COME_FROM            36  '36'
Instruction context:
   
 L.1153        10  LOAD_FAST                'self'
                  12  LOAD_METHOD              single_request
                  14  LOAD_FAST                'host'
                  16  LOAD_FAST                'handler'
                  18  LOAD_FAST                'request_body'
                  20  LOAD_FAST                'verbose'
                  22  CALL_METHOD_4         4  ''
                  24  POP_BLOCK        
                  26  ROT_TWO          
->                28  POP_TOP          
                  30  RETURN_VALUE     
                32_0  COME_FROM_FINALLY     8  '8'

../test/112310.pyc -- 
# decompile failed

# file ../test/112310.pyc
# Deparsing stopped due to parse error
