Instruction context:
   
 L. 392        28  POP_EXCEPT       
                  30  JUMP_FORWARD         34  'to 34'
->              32_0  COME_FROM            20  '20'
                  32  END_FINALLY      
                34_0  COME_FROM            30  '30'
Instruction context:
-> 
 L. 567       148  LOAD_FAST                'tokenize'
                 150  LOAD_METHOD              untokenize
                 152  LOAD_FAST                'tokens'
                 154  CALL_METHOD_1         1  ''
                 156  LOAD_CONST               None
                 158  LOAD_CONST               -1
                 160  BUILD_SLICE_2         2 
                 162  BINARY_SUBSCR    
                 164  RETURN_VALUE     

../test/183781.pyc -- 
# decompile failed

# file ../test/183781.pyc
# Deparsing stopped due to parse error
