
# file test/101069.pyc
# --- This code section failed: ---

 L.   2         0  LOAD_STR                 '\nopcode module - potentially shared between dis and other modules which\noperate on bytecodes (e.g. peephole optimizers).\n'
                2  STORE_NAME               __doc__

 L.   7         4  BUILD_LIST_0          0 
                6  LOAD_CONST               ('cmp_op', 'hasconst', 'hasname', 'hasjrel', 'hasjabs', 'haslocal', 'hascompare', 'hasfree', 'opname', 'opmap', 'HAVE_ARGUMENT', 'EXTENDED_ARG', 'hasnargs')
                8  CALL_FINALLY         11  'to 11'
               10  STORE_NAME               __all__

 L.  18        12  SETUP_FINALLY        40  'to 40'

 L.  19        14  LOAD_CONST               0
               16  LOAD_CONST               ('stack_effect',)
               18  IMPORT_NAME              _opcode
               20  IMPORT_FROM              stack_effect
               22  STORE_NAME               stack_effect
               24  POP_TOP          

 L.  20        26  LOAD_NAME                __all__
               28  LOAD_METHOD              append
               30  LOAD_STR                 'stack_effect'
               32  CALL_METHOD_1         1  ''
               34  POP_TOP          
               36  POP_BLOCK        
               38  JUMP_FORWARD         58  'to 58'
             40_0  COME_FROM_FINALLY    12  '12'

 L.  21        40  DUP_TOP          
               42  LOAD_NAME                ImportError
               44  <121>                56  ''
               46  POP_TOP          
               48  POP_TOP          
               50  POP_TOP          

 L.  22        52  POP_EXCEPT       
               54  JUMP_FORWARD         58  'to 58'
               56  <48>             
             58_0  COME_FROM            54  '54'
             58_1  COME_FROM            38  '38'

 L.  24        58  LOAD_CONST               ('<', '<=', '==', '!=', '>', '>=')
               60  STORE_NAME               cmp_op

 L.  26        62  BUILD_LIST_0          0 
               64  STORE_NAME               hasconst

 L.  27        66  BUILD_LIST_0          0 
               68  STORE_NAME               hasname

 L.  28        70  BUILD_LIST_0          0 
               72  STORE_NAME               hasjrel

 L.  29        74  BUILD_LIST_0          0 
               76  STORE_NAME               hasjabs

 L.  30        78  BUILD_LIST_0          0 
               80  STORE_NAME               haslocal

 L.  31        82  BUILD_LIST_0          0 
               84  STORE_NAME               hascompare

 L.  32        86  BUILD_LIST_0          0 
               88  STORE_NAME               hasfree

 L.  33        90  BUILD_LIST_0          0 
               92  STORE_NAME               hasnargs

 L.  35        94  BUILD_MAP_0           0 
               96  STORE_NAME               opmap

 L.  36        98  LOAD_LISTCOMP            '<code_object <listcomp>>'
              100  LOAD_STR                 '<listcomp>'
              102  MAKE_FUNCTION_0          'Neither defaults, keyword-only args, annotations, nor closures'
              104  LOAD_NAME                range
              106  LOAD_CONST               256
              108  CALL_FUNCTION_1       1  ''
              110  GET_ITER         
              112  CALL_FUNCTION_1       1  ''
              114  STORE_NAME               opname

 L.  38       116  LOAD_CODE                <code_object def_op>
              118  LOAD_STR                 'def_op'
              120  MAKE_FUNCTION_0          'Neither defaults, keyword-only args, annotations, nor closures'
              122  STORE_NAME               def_op

 L.  42       124  LOAD_CODE                <code_object name_op>
              126  LOAD_STR                 'name_op'
              128  MAKE_FUNCTION_0          'Neither defaults, keyword-only args, annotations, nor closures'
              130  STORE_NAME               name_op

 L.  46       132  LOAD_CODE                <code_object jrel_op>
              134  LOAD_STR                 'jrel_op'
              136  MAKE_FUNCTION_0          'Neither defaults, keyword-only args, annotations, nor closures'
              138  STORE_NAME               jrel_op

 L.  50       140  LOAD_CODE                <code_object jabs_op>
              142  LOAD_STR                 'jabs_op'
              144  MAKE_FUNCTION_0          'Neither defaults, keyword-only args, annotations, nor closures'
              146  STORE_NAME               jabs_op

 L.  57       148  LOAD_NAME                def_op
              150  LOAD_STR                 'POP_TOP'
              152  LOAD_CONST               1
              154  CALL_FUNCTION_2       2  ''
              156  POP_TOP          

 L.  58       158  LOAD_NAME                def_op
              160  LOAD_STR                 'ROT_TWO'
              162  LOAD_CONST               2
              164  CALL_FUNCTION_2       2  ''
              166  POP_TOP          

 L.  59       168  LOAD_NAME                def_op
              170  LOAD_STR                 'ROT_THREE'
              172  LOAD_CONST               3
              174  CALL_FUNCTION_2       2  ''
              176  POP_TOP          

 L.  60       178  LOAD_NAME                def_op
              180  LOAD_STR                 'DUP_TOP'
              182  LOAD_CONST               4
              184  CALL_FUNCTION_2       2  ''
              186  POP_TOP          

 L.  61       188  LOAD_NAME                def_op
              190  LOAD_STR                 'DUP_TOP_TWO'
              192  LOAD_CONST               5
              194  CALL_FUNCTION_2       2  ''
              196  POP_TOP          

 L.  62       198  LOAD_NAME                def_op
              200  LOAD_STR                 'ROT_FOUR'
              202  LOAD_CONST               6
              204  CALL_FUNCTION_2       2  ''
              206  POP_TOP          

 L.  64       208  LOAD_NAME                def_op
              210  LOAD_STR                 'NOP'
              212  LOAD_CONST               9
              214  CALL_FUNCTION_2       2  ''
              216  POP_TOP          

 L.  65       218  LOAD_NAME                def_op
              220  LOAD_STR                 'UNARY_POSITIVE'
              222  LOAD_CONST               10
              224  CALL_FUNCTION_2       2  ''
              226  POP_TOP          

 L.  66       228  LOAD_NAME                def_op
              230  LOAD_STR                 'UNARY_NEGATIVE'
              232  LOAD_CONST               11
              234  CALL_FUNCTION_2       2  ''
              236  POP_TOP          

 L.  67       238  LOAD_NAME                def_op
              240  LOAD_STR                 'UNARY_NOT'
              242  LOAD_CONST               12
              244  CALL_FUNCTION_2       2  ''
              246  POP_TOP          

 L.  69       248  LOAD_NAME                def_op
              250  LOAD_STR                 'UNARY_INVERT'
              252  LOAD_CONST               15
              254  CALL_FUNCTION_2       2  ''
              256  POP_TOP          

 L.  71       258  LOAD_NAME                def_op
              260  LOAD_STR                 'BINARY_MATRIX_MULTIPLY'
              262  LOAD_CONST               16
              264  CALL_FUNCTION_2       2  ''
              266  POP_TOP          

 L.  72       268  LOAD_NAME                def_op
              270  LOAD_STR                 'INPLACE_MATRIX_MULTIPLY'
              272  LOAD_CONST               17
              274  CALL_FUNCTION_2       2  ''
              276  POP_TOP          

 L.  74       278  LOAD_NAME                def_op
              280  LOAD_STR                 'BINARY_POWER'
              282  LOAD_CONST               19
              284  CALL_FUNCTION_2       2  ''
              286  POP_TOP          

 L.  75       288  LOAD_NAME                def_op
              290  LOAD_STR                 'BINARY_MULTIPLY'
              292  LOAD_CONST               20
              294  CALL_FUNCTION_2       2  ''
              296  POP_TOP          

 L.  77       298  LOAD_NAME                def_op
              300  LOAD_STR                 'BINARY_MODULO'
              302  LOAD_CONST               22
              304  CALL_FUNCTION_2       2  ''
              306  POP_TOP          

 L.  78       308  LOAD_NAME                def_op
              310  LOAD_STR                 'BINARY_ADD'
              312  LOAD_CONST               23
              314  CALL_FUNCTION_2       2  ''
              316  POP_TOP          

 L.  79       318  LOAD_NAME                def_op
              320  LOAD_STR                 'BINARY_SUBTRACT'
              322  LOAD_CONST               24
              324  CALL_FUNCTION_2       2  ''
              326  POP_TOP          

 L.  80       328  LOAD_NAME                def_op
              330  LOAD_STR                 'BINARY_SUBSCR'
              332  LOAD_CONST               25
              334  CALL_FUNCTION_2       2  ''
              336  POP_TOP          

 L.  81       338  LOAD_NAME                def_op
              340  LOAD_STR                 'BINARY_FLOOR_DIVIDE'
              342  LOAD_CONST               26
              344  CALL_FUNCTION_2       2  ''
              346  POP_TOP          

 L.  82       348  LOAD_NAME                def_op
              350  LOAD_STR                 'BINARY_TRUE_DIVIDE'
              352  LOAD_CONST               27
              354  CALL_FUNCTION_2       2  ''
              356  POP_TOP          

 L.  83       358  LOAD_NAME                def_op
              360  LOAD_STR                 'INPLACE_FLOOR_DIVIDE'
              362  LOAD_CONST               28
              364  CALL_FUNCTION_2       2  ''
              366  POP_TOP          

 L.  84       368  LOAD_NAME                def_op
              370  LOAD_STR                 'INPLACE_TRUE_DIVIDE'
              372  LOAD_CONST               29
              374  CALL_FUNCTION_2       2  ''
              376  POP_TOP          

 L.  86       378  LOAD_NAME                def_op
              380  LOAD_STR                 'RERAISE'
              382  LOAD_CONST               48
              384  CALL_FUNCTION_2       2  ''
              386  POP_TOP          

 L.  87       388  LOAD_NAME                def_op
              390  LOAD_STR                 'WITH_EXCEPT_START'
              392  LOAD_CONST               49
              394  CALL_FUNCTION_2       2  ''
              396  POP_TOP          

 L.  88       398  LOAD_NAME                def_op
              400  LOAD_STR                 'GET_AITER'
              402  LOAD_CONST               50
              404  CALL_FUNCTION_2       2  ''
              406  POP_TOP          

 L.  89       408  LOAD_NAME                def_op
              410  LOAD_STR                 'GET_ANEXT'
              412  LOAD_CONST               51
              414  CALL_FUNCTION_2       2  ''
              416  POP_TOP          

 L.  90       418  LOAD_NAME                def_op
              420  LOAD_STR                 'BEFORE_ASYNC_WITH'
              422  LOAD_CONST               52
              424  CALL_FUNCTION_2       2  ''
              426  POP_TOP          

 L.  92       428  LOAD_NAME                def_op
              430  LOAD_STR                 'END_ASYNC_FOR'
              432  LOAD_CONST               54
              434  CALL_FUNCTION_2       2  ''
              436  POP_TOP          

 L.  93       438  LOAD_NAME                def_op
              440  LOAD_STR                 'INPLACE_ADD'
              442  LOAD_CONST               55
              444  CALL_FUNCTION_2       2  ''
              446  POP_TOP          

 L.  94       448  LOAD_NAME                def_op
              450  LOAD_STR                 'INPLACE_SUBTRACT'
              452  LOAD_CONST               56
              454  CALL_FUNCTION_2       2  ''
              456  POP_TOP          

 L.  95       458  LOAD_NAME                def_op
              460  LOAD_STR                 'INPLACE_MULTIPLY'
              462  LOAD_CONST               57
              464  CALL_FUNCTION_2       2  ''
              466  POP_TOP          

 L.  97       468  LOAD_NAME                def_op
              470  LOAD_STR                 'INPLACE_MODULO'
              472  LOAD_CONST               59
              474  CALL_FUNCTION_2       2  ''
              476  POP_TOP          

 L.  98       478  LOAD_NAME                def_op
              480  LOAD_STR                 'STORE_SUBSCR'
              482  LOAD_CONST               60
              484  CALL_FUNCTION_2       2  ''
              486  POP_TOP          

 L.  99       488  LOAD_NAME                def_op
              490  LOAD_STR                 'DELETE_SUBSCR'
              492  LOAD_CONST               61
              494  CALL_FUNCTION_2       2  ''
              496  POP_TOP          

 L. 100       498  LOAD_NAME                def_op
              500  LOAD_STR                 'BINARY_LSHIFT'
              502  LOAD_CONST               62
              504  CALL_FUNCTION_2       2  ''
              506  POP_TOP          

 L. 101       508  LOAD_NAME                def_op
              510  LOAD_STR                 'BINARY_RSHIFT'
              512  LOAD_CONST               63
              514  CALL_FUNCTION_2       2  ''
              516  POP_TOP          

 L. 102       518  LOAD_NAME                def_op
              520  LOAD_STR                 'BINARY_AND'
              522  LOAD_CONST               64
              524  CALL_FUNCTION_2       2  ''
              526  POP_TOP          

 L. 103       528  LOAD_NAME                def_op
              530  LOAD_STR                 'BINARY_XOR'
              532  LOAD_CONST               65
              534  CALL_FUNCTION_2       2  ''
              536  POP_TOP          

 L. 104       538  LOAD_NAME                def_op
              540  LOAD_STR                 'BINARY_OR'
              542  LOAD_CONST               66
              544  CALL_FUNCTION_2       2  ''
              546  POP_TOP          

 L. 105       548  LOAD_NAME                def_op
              550  LOAD_STR                 'INPLACE_POWER'
              552  LOAD_CONST               67
              554  CALL_FUNCTION_2       2  ''
              556  POP_TOP          

 L. 106       558  LOAD_NAME                def_op
              560  LOAD_STR                 'GET_ITER'
              562  LOAD_CONST               68
              564  CALL_FUNCTION_2       2  ''
              566  POP_TOP          

 L. 107       568  LOAD_NAME                def_op
              570  LOAD_STR                 'GET_YIELD_FROM_ITER'
              572  LOAD_CONST               69
              574  CALL_FUNCTION_2       2  ''
              576  POP_TOP          

 L. 109       578  LOAD_NAME                def_op
              580  LOAD_STR                 'PRINT_EXPR'
              582  LOAD_CONST               70
              584  CALL_FUNCTION_2       2  ''
              586  POP_TOP          

 L. 110       588  LOAD_NAME                def_op
              590  LOAD_STR                 'LOAD_BUILD_CLASS'
              592  LOAD_CONST               71
              594  CALL_FUNCTION_2       2  ''
              596  POP_TOP          

 L. 111       598  LOAD_NAME                def_op
              600  LOAD_STR                 'YIELD_FROM'
              602  LOAD_CONST               72
              604  CALL_FUNCTION_2       2  ''
              606  POP_TOP          

 L. 112       608  LOAD_NAME                def_op
              610  LOAD_STR                 'GET_AWAITABLE'
              612  LOAD_CONST               73
              614  CALL_FUNCTION_2       2  ''
              616  POP_TOP          

 L. 113       618  LOAD_NAME                def_op
              620  LOAD_STR                 'LOAD_ASSERTION_ERROR'
              622  LOAD_CONST               74
              624  CALL_FUNCTION_2       2  ''
              626  POP_TOP          

 L. 114       628  LOAD_NAME                def_op
              630  LOAD_STR                 'INPLACE_LSHIFT'
              632  LOAD_CONST               75
              634  CALL_FUNCTION_2       2  ''
              636  POP_TOP          

 L. 115       638  LOAD_NAME                def_op
              640  LOAD_STR                 'INPLACE_RSHIFT'
              642  LOAD_CONST               76
              644  CALL_FUNCTION_2       2  ''
              646  POP_TOP          

 L. 116       648  LOAD_NAME                def_op
              650  LOAD_STR                 'INPLACE_AND'
              652  LOAD_CONST               77
              654  CALL_FUNCTION_2       2  ''
              656  POP_TOP          

 L. 117       658  LOAD_NAME                def_op
              660  LOAD_STR                 'INPLACE_XOR'
              662  LOAD_CONST               78
              664  CALL_FUNCTION_2       2  ''
              666  POP_TOP          

 L. 118       668  LOAD_NAME                def_op
              670  LOAD_STR                 'INPLACE_OR'
              672  LOAD_CONST               79
              674  CALL_FUNCTION_2       2  ''
              676  POP_TOP          

 L. 120       678  LOAD_NAME                def_op
              680  LOAD_STR                 'LIST_TO_TUPLE'
              682  LOAD_CONST               82
              684  CALL_FUNCTION_2       2  ''
              686  POP_TOP          

 L. 121       688  LOAD_NAME                def_op
              690  LOAD_STR                 'RETURN_VALUE'
              692  LOAD_CONST               83
              694  CALL_FUNCTION_2       2  ''
              696  POP_TOP          

 L. 122       698  LOAD_NAME                def_op
              700  LOAD_STR                 'IMPORT_STAR'
              702  LOAD_CONST               84
              704  CALL_FUNCTION_2       2  ''
              706  POP_TOP          

 L. 123       708  LOAD_NAME                def_op
              710  LOAD_STR                 'SETUP_ANNOTATIONS'
              712  LOAD_CONST               85
              714  CALL_FUNCTION_2       2  ''
              716  POP_TOP          

 L. 124       718  LOAD_NAME                def_op
              720  LOAD_STR                 'YIELD_VALUE'
              722  LOAD_CONST               86
              724  CALL_FUNCTION_2       2  ''
              726  POP_TOP          

 L. 125       728  LOAD_NAME                def_op
              730  LOAD_STR                 'POP_BLOCK'
              732  LOAD_CONST               87
              734  CALL_FUNCTION_2       2  ''
              736  POP_TOP          

 L. 127       738  LOAD_NAME                def_op
              740  LOAD_STR                 'POP_EXCEPT'
              742  LOAD_CONST               89
              744  CALL_FUNCTION_2       2  ''
              746  POP_TOP          

 L. 129       748  LOAD_CONST               90
              750  STORE_NAME               HAVE_ARGUMENT

 L. 131       752  LOAD_NAME                name_op
              754  LOAD_STR                 'STORE_NAME'
              756  LOAD_CONST               90
              758  CALL_FUNCTION_2       2  ''
              760  POP_TOP          

 L. 132       762  LOAD_NAME                name_op
              764  LOAD_STR                 'DELETE_NAME'
              766  LOAD_CONST               91
              768  CALL_FUNCTION_2       2  ''
              770  POP_TOP          

 L. 133       772  LOAD_NAME                def_op
              774  LOAD_STR                 'UNPACK_SEQUENCE'
              776  LOAD_CONST               92
              778  CALL_FUNCTION_2       2  ''
              780  POP_TOP          

 L. 134       782  LOAD_NAME                jrel_op
              784  LOAD_STR                 'FOR_ITER'
              786  LOAD_CONST               93
              788  CALL_FUNCTION_2       2  ''
              790  POP_TOP          

 L. 135       792  LOAD_NAME                def_op
              794  LOAD_STR                 'UNPACK_EX'
              796  LOAD_CONST               94
              798  CALL_FUNCTION_2       2  ''
              800  POP_TOP          

 L. 136       802  LOAD_NAME                name_op
              804  LOAD_STR                 'STORE_ATTR'
              806  LOAD_CONST               95
              808  CALL_FUNCTION_2       2  ''
              810  POP_TOP          

 L. 137       812  LOAD_NAME                name_op
              814  LOAD_STR                 'DELETE_ATTR'
              816  LOAD_CONST               96
              818  CALL_FUNCTION_2       2  ''
              820  POP_TOP          

 L. 138       822  LOAD_NAME                name_op
              824  LOAD_STR                 'STORE_GLOBAL'
              826  LOAD_CONST               97
              828  CALL_FUNCTION_2       2  ''
              830  POP_TOP          

 L. 139       832  LOAD_NAME                name_op
              834  LOAD_STR                 'DELETE_GLOBAL'
              836  LOAD_CONST               98
              838  CALL_FUNCTION_2       2  ''
              840  POP_TOP          

 L. 140       842  LOAD_NAME                def_op
              844  LOAD_STR                 'LOAD_CONST'
              846  LOAD_CONST               100
              848  CALL_FUNCTION_2       2  ''
              850  POP_TOP          

 L. 141       852  LOAD_NAME                hasconst
              854  LOAD_METHOD              append
              856  LOAD_CONST               100
              858  CALL_METHOD_1         1  ''
              860  POP_TOP          

 L. 142       862  LOAD_NAME                name_op
              864  LOAD_STR                 'LOAD_NAME'
              866  LOAD_CONST               101
              868  CALL_FUNCTION_2       2  ''
              870  POP_TOP          

 L. 143       872  LOAD_NAME                def_op
              874  LOAD_STR                 'BUILD_TUPLE'
              876  LOAD_CONST               102
              878  CALL_FUNCTION_2       2  ''
              880  POP_TOP          

 L. 144       882  LOAD_NAME                def_op
              884  LOAD_STR                 'BUILD_LIST'
              886  LOAD_CONST               103
              888  CALL_FUNCTION_2       2  ''
              890  POP_TOP          

 L. 145       892  LOAD_NAME                def_op
              894  LOAD_STR                 'BUILD_SET'
              896  LOAD_CONST               104
              898  CALL_FUNCTION_2       2  ''
              900  POP_TOP          

 L. 146       902  LOAD_NAME                def_op
              904  LOAD_STR                 'BUILD_MAP'
              906  LOAD_CONST               105
              908  CALL_FUNCTION_2       2  ''
              910  POP_TOP          

 L. 147       912  LOAD_NAME                name_op
              914  LOAD_STR                 'LOAD_ATTR'
              916  LOAD_CONST               106
              918  CALL_FUNCTION_2       2  ''
              920  POP_TOP          

 L. 148       922  LOAD_NAME                def_op
              924  LOAD_STR                 'COMPARE_OP'
              926  LOAD_CONST               107
              928  CALL_FUNCTION_2       2  ''
              930  POP_TOP          

 L. 149       932  LOAD_NAME                hascompare
              934  LOAD_METHOD              append
              936  LOAD_CONST               107
              938  CALL_METHOD_1         1  ''
              940  POP_TOP          

 L. 150       942  LOAD_NAME                name_op
              944  LOAD_STR                 'IMPORT_NAME'
              946  LOAD_CONST               108
              948  CALL_FUNCTION_2       2  ''
              950  POP_TOP          

 L. 151       952  LOAD_NAME                name_op
              954  LOAD_STR                 'IMPORT_FROM'
              956  LOAD_CONST               109
              958  CALL_FUNCTION_2       2  ''
              960  POP_TOP          

 L. 153       962  LOAD_NAME                jrel_op
              964  LOAD_STR                 'JUMP_FORWARD'
              966  LOAD_CONST               110
              968  CALL_FUNCTION_2       2  ''
              970  POP_TOP          

 L. 154       972  LOAD_NAME                jabs_op
              974  LOAD_STR                 'JUMP_IF_FALSE_OR_POP'
              976  LOAD_CONST               111
              978  CALL_FUNCTION_2       2  ''
              980  POP_TOP          

 L. 155       982  LOAD_NAME                jabs_op
              984  LOAD_STR                 'JUMP_IF_TRUE_OR_POP'
              986  LOAD_CONST               112
              988  CALL_FUNCTION_2       2  ''
              990  POP_TOP          

 L. 156       992  LOAD_NAME                jabs_op
              994  LOAD_STR                 'JUMP_ABSOLUTE'
              996  LOAD_CONST               113
              998  CALL_FUNCTION_2       2  ''
             1000  POP_TOP          

 L. 157      1002  LOAD_NAME                jabs_op
             1004  LOAD_STR                 'POP_JUMP_IF_FALSE'
             1006  LOAD_CONST               114
             1008  CALL_FUNCTION_2       2  ''
             1010  POP_TOP          

 L. 158      1012  LOAD_NAME                jabs_op
             1014  LOAD_STR                 'POP_JUMP_IF_TRUE'
             1016  LOAD_CONST               115
             1018  CALL_FUNCTION_2       2  ''
             1020  POP_TOP          

 L. 160      1022  LOAD_NAME                name_op
             1024  LOAD_STR                 'LOAD_GLOBAL'
             1026  LOAD_CONST               116
             1028  CALL_FUNCTION_2       2  ''
             1030  POP_TOP          

 L. 162      1032  LOAD_NAME                def_op
             1034  LOAD_STR                 'IS_OP'
             1036  LOAD_CONST               117
             1038  CALL_FUNCTION_2       2  ''
             1040  POP_TOP          

 L. 163      1042  LOAD_NAME                def_op
             1044  LOAD_STR                 'CONTAINS_OP'
             1046  LOAD_CONST               118
             1048  CALL_FUNCTION_2       2  ''
             1050  POP_TOP          

 L. 165      1052  LOAD_NAME                jabs_op
             1054  LOAD_STR                 'JUMP_IF_NOT_EXC_MATCH'
             1056  LOAD_CONST               121
             1058  CALL_FUNCTION_2       2  ''
             1060  POP_TOP          

 L. 166      1062  LOAD_NAME                jrel_op
             1064  LOAD_STR                 'SETUP_FINALLY'
             1066  LOAD_CONST               122
             1068  CALL_FUNCTION_2       2  ''
             1070  POP_TOP          

 L. 168      1072  LOAD_NAME                def_op
             1074  LOAD_STR                 'LOAD_FAST'
             1076  LOAD_CONST               124
             1078  CALL_FUNCTION_2       2  ''
             1080  POP_TOP          

 L. 169      1082  LOAD_NAME                haslocal
             1084  LOAD_METHOD              append
             1086  LOAD_CONST               124
             1088  CALL_METHOD_1         1  ''
             1090  POP_TOP          

 L. 170      1092  LOAD_NAME                def_op
             1094  LOAD_STR                 'STORE_FAST'
             1096  LOAD_CONST               125
             1098  CALL_FUNCTION_2       2  ''
             1100  POP_TOP          

 L. 171      1102  LOAD_NAME                haslocal
             1104  LOAD_METHOD              append
             1106  LOAD_CONST               125
             1108  CALL_METHOD_1         1  ''
             1110  POP_TOP          

 L. 172      1112  LOAD_NAME                def_op
             1114  LOAD_STR                 'DELETE_FAST'
             1116  LOAD_CONST               126
             1118  CALL_FUNCTION_2       2  ''
             1120  POP_TOP          

 L. 173      1122  LOAD_NAME                haslocal
             1124  LOAD_METHOD              append
             1126  LOAD_CONST               126
             1128  CALL_METHOD_1         1  ''
             1130  POP_TOP          

 L. 175      1132  LOAD_NAME                def_op
             1134  LOAD_STR                 'RAISE_VARARGS'
             1136  LOAD_CONST               130
             1138  CALL_FUNCTION_2       2  ''
             1140  POP_TOP          

 L. 176      1142  LOAD_NAME                def_op
             1144  LOAD_STR                 'CALL_FUNCTION'
             1146  LOAD_CONST               131
             1148  CALL_FUNCTION_2       2  ''
             1150  POP_TOP          

 L. 177      1152  LOAD_NAME                def_op
             1154  LOAD_STR                 'MAKE_FUNCTION'
             1156  LOAD_CONST               132
             1158  CALL_FUNCTION_2       2  ''
             1160  POP_TOP          

 L. 178      1162  LOAD_NAME                def_op
             1164  LOAD_STR                 'BUILD_SLICE'
             1166  LOAD_CONST               133
             1168  CALL_FUNCTION_2       2  ''
             1170  POP_TOP          

 L. 179      1172  LOAD_NAME                def_op
             1174  LOAD_STR                 'LOAD_CLOSURE'
             1176  LOAD_CONST               135
             1178  CALL_FUNCTION_2       2  ''
             1180  POP_TOP          

 L. 180      1182  LOAD_NAME                hasfree
             1184  LOAD_METHOD              append
             1186  LOAD_CONST               135
             1188  CALL_METHOD_1         1  ''
             1190  POP_TOP          

 L. 181      1192  LOAD_NAME                def_op
             1194  LOAD_STR                 'LOAD_DEREF'
             1196  LOAD_CONST               136
             1198  CALL_FUNCTION_2       2  ''
             1200  POP_TOP          

 L. 182      1202  LOAD_NAME                hasfree
             1204  LOAD_METHOD              append
             1206  LOAD_CONST               136
             1208  CALL_METHOD_1         1  ''
             1210  POP_TOP          

 L. 183      1212  LOAD_NAME                def_op
             1214  LOAD_STR                 'STORE_DEREF'
             1216  LOAD_CONST               137
             1218  CALL_FUNCTION_2       2  ''
             1220  POP_TOP          

 L. 184      1222  LOAD_NAME                hasfree
             1224  LOAD_METHOD              append
             1226  LOAD_CONST               137
             1228  CALL_METHOD_1         1  ''
             1230  POP_TOP          

 L. 185      1232  LOAD_NAME                def_op
             1234  LOAD_STR                 'DELETE_DEREF'
             1236  LOAD_CONST               138
             1238  CALL_FUNCTION_2       2  ''
             1240  POP_TOP          

 L. 186      1242  LOAD_NAME                hasfree
             1244  LOAD_METHOD              append
             1246  LOAD_CONST               138
             1248  CALL_METHOD_1         1  ''
             1250  POP_TOP          

 L. 188      1252  LOAD_NAME                def_op
             1254  LOAD_STR                 'CALL_FUNCTION_KW'
             1256  LOAD_CONST               141
             1258  CALL_FUNCTION_2       2  ''
             1260  POP_TOP          

 L. 189      1262  LOAD_NAME                def_op
             1264  LOAD_STR                 'CALL_FUNCTION_EX'
             1266  LOAD_CONST               142
             1268  CALL_FUNCTION_2       2  ''
             1270  POP_TOP          

 L. 191      1272  LOAD_NAME                jrel_op
             1274  LOAD_STR                 'SETUP_WITH'
             1276  LOAD_CONST               143
             1278  CALL_FUNCTION_2       2  ''
             1280  POP_TOP          

 L. 193      1282  LOAD_NAME                def_op
             1284  LOAD_STR                 'LIST_APPEND'
             1286  LOAD_CONST               145
             1288  CALL_FUNCTION_2       2  ''
             1290  POP_TOP          

 L. 194      1292  LOAD_NAME                def_op
             1294  LOAD_STR                 'SET_ADD'
             1296  LOAD_CONST               146
             1298  CALL_FUNCTION_2       2  ''
             1300  POP_TOP          

 L. 195      1302  LOAD_NAME                def_op
             1304  LOAD_STR                 'MAP_ADD'
             1306  LOAD_CONST               147
             1308  CALL_FUNCTION_2       2  ''
             1310  POP_TOP          

 L. 197      1312  LOAD_NAME                def_op
             1314  LOAD_STR                 'LOAD_CLASSDEREF'
             1316  LOAD_CONST               148
             1318  CALL_FUNCTION_2       2  ''
             1320  POP_TOP          

 L. 198      1322  LOAD_NAME                hasfree
             1324  LOAD_METHOD              append
             1326  LOAD_CONST               148
             1328  CALL_METHOD_1         1  ''
             1330  POP_TOP          

 L. 200      1332  LOAD_NAME                def_op
             1334  LOAD_STR                 'EXTENDED_ARG'
             1336  LOAD_CONST               144
             1338  CALL_FUNCTION_2       2  ''
             1340  POP_TOP          

 L. 201      1342  LOAD_CONST               144
             1344  STORE_NAME               EXTENDED_ARG

 L. 203      1346  LOAD_NAME                jrel_op
             1348  LOAD_STR                 'SETUP_ASYNC_WITH'
             1350  LOAD_CONST               154
             1352  CALL_FUNCTION_2       2  ''
             1354  POP_TOP          

 L. 205      1356  LOAD_NAME                def_op
             1358  LOAD_STR                 'FORMAT_VALUE'
             1360  LOAD_CONST               155
             1362  CALL_FUNCTION_2       2  ''
             1364  POP_TOP          

 L. 206      1366  LOAD_NAME                def_op
             1368  LOAD_STR                 'BUILD_CONST_KEY_MAP'
             1370  LOAD_CONST               156
             1372  CALL_FUNCTION_2       2  ''
             1374  POP_TOP          

 L. 207      1376  LOAD_NAME                def_op
             1378  LOAD_STR                 'BUILD_STRING'
             1380  LOAD_CONST               157
             1382  CALL_FUNCTION_2       2  ''
             1384  POP_TOP          

 L. 209      1386  LOAD_NAME                name_op
             1388  LOAD_STR                 'LOAD_METHOD'
             1390  LOAD_CONST               160
             1392  CALL_FUNCTION_2       2  ''
             1394  POP_TOP          

 L. 210      1396  LOAD_NAME                def_op
             1398  LOAD_STR                 'CALL_METHOD'
             1400  LOAD_CONST               161
             1402  CALL_FUNCTION_2       2  ''
             1404  POP_TOP          

 L. 212      1406  LOAD_NAME                def_op
             1408  LOAD_STR                 'LIST_EXTEND'
             1410  LOAD_CONST               162
             1412  CALL_FUNCTION_2       2  ''
             1414  POP_TOP          

 L. 213      1416  LOAD_NAME                def_op
             1418  LOAD_STR                 'SET_UPDATE'
             1420  LOAD_CONST               163
             1422  CALL_FUNCTION_2       2  ''
             1424  POP_TOP          

 L. 214      1426  LOAD_NAME                def_op
             1428  LOAD_STR                 'DICT_MERGE'
             1430  LOAD_CONST               164
             1432  CALL_FUNCTION_2       2  ''
             1434  POP_TOP          

 L. 215      1436  LOAD_NAME                def_op
             1438  LOAD_STR                 'DICT_UPDATE'
             1440  LOAD_CONST               165
             1442  CALL_FUNCTION_2       2  ''
             1444  POP_TOP          

 L. 217      1446  DELETE_NAME              def_op
             1448  DELETE_NAME              name_op
             1450  DELETE_NAME              jrel_op
             1452  DELETE_NAME              jabs_op

Parse error at or near `CALL_FINALLY' instruction at offset 8

Instruction context:
   
 L.   7         4  BUILD_LIST_0          0 
                   6  LOAD_CONST               ('cmp_op', 'hasconst', 'hasname', 'hasjrel', 'hasjabs', 'haslocal', 'hascompare', 'hasfree', 'opname', 'opmap', 'HAVE_ARGUMENT', 'EXTENDED_ARG', 'hasnargs')
->                 8  CALL_FINALLY         11  'to 11'
                  10  STORE_NAME               __all__

test/101069.pyc -- 
# decompile failed
