Instruction context:
   
 L.  11         4  BUILD_LIST_0          0 
                   6  LOAD_CONST               ('CHECK_NONE', 'CHECK_CRC32', 'CHECK_CRC64', 'CHECK_SHA256', 'CHECK_ID_MAX', 'CHECK_UNKNOWN', 'FILTER_LZMA1', 'FILTER_LZMA2', 'FILTER_DELTA', 'FILTER_X86', 'FILTER_IA64', 'FILTER_ARM', 'FILTER_ARMTHUMB', 'FILTER_POWERPC', 'FILTER_SPARC', 'FORMAT_AUTO', 'FORMAT_XZ', 'FORMAT_ALONE', 'FORMAT_RAW', 'MF_HC3', 'MF_HC4', 'MF_BT2', 'MF_BT3', 'MF_BT4', 'MODE_FAST', 'MODE_NORMAL', 'PRESET_DEFAULT', 'PRESET_EXTREME', 'LZMACompressor', 'LZMADecompressor', 'LZMAFile', 'LZMAError', 'open', 'compress', 'decompress', 'is_check_supported')
->                 8  CALL_FINALLY         11  'to 11'
                  10  STORE_NAME               __all__

test/101063.pyc -- 
# decompile failed

# file test/101063.pyc
# --- This code section failed: ---

 L.   1         0  LOAD_STR                 'Interface to the liblzma compression library.\n\nThis module provides a class for reading and writing compressed files,\nclasses for incremental (de)compression, and convenience functions for\none-shot (de)compression.\n\nThese classes and functions support both the XZ and legacy LZMA\ncontainer formats, as well as raw compressed data streams.\n'
                2  STORE_NAME               __doc__

 L.  11         4  BUILD_LIST_0          0 
                6  LOAD_CONST               ('CHECK_NONE', 'CHECK_CRC32', 'CHECK_CRC64', 'CHECK_SHA256', 'CHECK_ID_MAX', 'CHECK_UNKNOWN', 'FILTER_LZMA1', 'FILTER_LZMA2', 'FILTER_DELTA', 'FILTER_X86', 'FILTER_IA64', 'FILTER_ARM', 'FILTER_ARMTHUMB', 'FILTER_POWERPC', 'FILTER_SPARC', 'FORMAT_AUTO', 'FORMAT_XZ', 'FORMAT_ALONE', 'FORMAT_RAW', 'MF_HC3', 'MF_HC4', 'MF_BT2', 'MF_BT3', 'MF_BT4', 'MODE_FAST', 'MODE_NORMAL', 'PRESET_DEFAULT', 'PRESET_EXTREME', 'LZMACompressor', 'LZMADecompressor', 'LZMAFile', 'LZMAError', 'open', 'compress', 'decompress', 'is_check_supported')
                8  CALL_FINALLY         11  'to 11'
               10  STORE_NAME               __all__

 L.  24        12  LOAD_CONST               0
               14  LOAD_CONST               None
               16  IMPORT_NAME              builtins
               18  STORE_NAME               builtins

 L.  25        20  LOAD_CONST               0
               22  LOAD_CONST               None
               24  IMPORT_NAME              io
               26  STORE_NAME               io

 L.  26        28  LOAD_CONST               0
               30  LOAD_CONST               None
               32  IMPORT_NAME              os
               34  STORE_NAME               os

 L.  27        36  LOAD_CONST               0
               38  LOAD_CONST               ('*',)
               40  IMPORT_NAME              _lzma
               42  IMPORT_STAR      

 L.  28        44  LOAD_CONST               0
               46  LOAD_CONST               ('_encode_filter_properties', '_decode_filter_properties')
               48  IMPORT_NAME              _lzma
               50  IMPORT_FROM              _encode_filter_properties
               52  STORE_NAME               _encode_filter_properties
               54  IMPORT_FROM              _decode_filter_properties
               56  STORE_NAME               _decode_filter_properties
               58  POP_TOP          

 L.  29        60  LOAD_CONST               0
               62  LOAD_CONST               None
               64  IMPORT_NAME              _compression
               66  STORE_NAME               _compression

 L.  32        68  LOAD_CONST               0
               70  STORE_NAME               _MODE_CLOSED

 L.  33        72  LOAD_CONST               1
               74  STORE_NAME               _MODE_READ

 L.  35        76  LOAD_CONST               3
               78  STORE_NAME               _MODE_WRITE

 L.  38        80  LOAD_BUILD_CLASS 
               82  LOAD_CODE                <code_object LZMAFile>
               84  LOAD_STR                 'LZMAFile'
               86  MAKE_FUNCTION_0          'Neither defaults, keyword-only args, annotations, nor closures'
               88  LOAD_STR                 'LZMAFile'
               90  LOAD_NAME                _compression
               92  LOAD_ATTR                BaseStream
               94  CALL_FUNCTION_3       3  ''
               96  STORE_NAME               LZMAFile

 L. 263        98  LOAD_CONST               ('rb',)

 L. 264       100  LOAD_CONST               None
              102  LOAD_CONST               -1
              104  LOAD_CONST               None
              106  LOAD_CONST               None

 L. 265       108  LOAD_CONST               None
              110  LOAD_CONST               None
              112  LOAD_CONST               None

 L. 263       114  LOAD_CONST               ('format', 'check', 'preset', 'filters', 'encoding', 'errors', 'newline')
              116  BUILD_CONST_KEY_MAP_7     7 
              118  LOAD_CODE                <code_object open>
              120  LOAD_STR                 'open'
              122  MAKE_FUNCTION_3          'default, keyword-only'
              124  STORE_NAME               open

 L. 310       126  LOAD_NAME                FORMAT_XZ
              128  LOAD_CONST               -1
              130  LOAD_CONST               None
              132  LOAD_CONST               None
              134  BUILD_TUPLE_4         4 
              136  LOAD_CODE                <code_object compress>
              138  LOAD_STR                 'compress'
              140  MAKE_FUNCTION_1          'default'
              142  STORE_NAME               compress

 L. 322       144  LOAD_NAME                FORMAT_AUTO
              146  LOAD_CONST               None
              148  LOAD_CONST               None
              150  BUILD_TUPLE_3         3 
              152  LOAD_CODE                <code_object decompress>
              154  LOAD_STR                 'decompress'
              156  MAKE_FUNCTION_1          'default'
              158  STORE_NAME               decompress

Parse error at or near `CALL_FINALLY' instruction at offset 8

