
# file test/101091.pyc
# --- This code section failed: ---

 L.   4         0  LOAD_STR                 "This module provides socket operations and some related functions.\nOn Unix, it supports IP (Internet Protocol) and Unix domain sockets.\nOn other systems, it only supports IP. Functions specific for a\nsocket are available as methods of the socket object.\n\nFunctions:\n\nsocket() -- create a new socket object\nsocketpair() -- create a pair of new socket objects [*]\nfromfd() -- create a socket object from an open file descriptor [*]\nsend_fds() -- Send file descriptor to the socket.\nrecv_fds() -- Recieve file descriptors from the socket.\nfromshare() -- create a socket object from data received from socket.share() [*]\ngethostname() -- return the current hostname\ngethostbyname() -- map a hostname to its IP number\ngethostbyaddr() -- map an IP number or hostname to DNS info\ngetservbyname() -- map a service name and a protocol name to a port number\ngetprotobyname() -- map a protocol name (e.g. 'tcp') to a number\nntohs(), ntohl() -- convert 16, 32 bit int from network to host byte order\nhtons(), htonl() -- convert 16, 32 bit int from host to network byte order\ninet_aton() -- convert IP addr string (123.45.67.89) to 32-bit packed format\ninet_ntoa() -- convert 32-bit packed format IP to string (123.45.67.89)\nsocket.getdefaulttimeout() -- get the default timeout value\nsocket.setdefaulttimeout() -- set the default timeout value\ncreate_connection() -- connects to an address, with an optional timeout and\n                       optional source address.\n\n [*] not available on all platforms!\n\nSpecial objects:\n\nSocketType -- type object for socket objects\nerror -- exception raised for I/O errors\nhas_ipv6 -- boolean value indicating if IPv6 is supported\n\nIntEnum constants:\n\nAF_INET, AF_UNIX -- socket domains (first argument to socket() call)\nSOCK_STREAM, SOCK_DGRAM, SOCK_RAW -- socket types (second argument)\n\nInteger constants:\n\nMany other constants may be defined; these may be used in calls to\nthe setsockopt() and getsockopt() methods.\n"
                2  STORE_NAME               __doc__

 L.  51         4  LOAD_CONST               0
                6  LOAD_CONST               None
                8  IMPORT_NAME              _socket
               10  STORE_NAME               _socket

 L.  52        12  LOAD_CONST               0
               14  LOAD_CONST               ('*',)
               16  IMPORT_NAME              _socket
               18  IMPORT_STAR      

 L.  54        20  LOAD_CONST               0
               22  LOAD_CONST               None
               24  IMPORT_NAME              os
               26  STORE_NAME               os
               28  LOAD_CONST               0
               30  LOAD_CONST               None
               32  IMPORT_NAME              sys
               34  STORE_NAME               sys
               36  LOAD_CONST               0
               38  LOAD_CONST               None
               40  IMPORT_NAME              io
               42  STORE_NAME               io
               44  LOAD_CONST               0
               46  LOAD_CONST               None
               48  IMPORT_NAME              selectors
               50  STORE_NAME               selectors

 L.  55        52  LOAD_CONST               0
               54  LOAD_CONST               ('IntEnum', 'IntFlag')
               56  IMPORT_NAME              enum
               58  IMPORT_FROM              IntEnum
               60  STORE_NAME               IntEnum
               62  IMPORT_FROM              IntFlag
               64  STORE_NAME               IntFlag
               66  POP_TOP          

 L.  57        68  SETUP_FINALLY        82  'to 82'

 L.  58        70  LOAD_CONST               0
               72  LOAD_CONST               None
               74  IMPORT_NAME              errno
               76  STORE_NAME               errno
               78  POP_BLOCK        
               80  JUMP_FORWARD        104  'to 104'
             82_0  COME_FROM_FINALLY    68  '68'

 L.  59        82  DUP_TOP          
               84  LOAD_NAME                ImportError
               86  <121>               102  ''
               88  POP_TOP          
               90  POP_TOP          
               92  POP_TOP          

 L.  60        94  LOAD_CONST               None
               96  STORE_NAME               errno
               98  POP_EXCEPT       
              100  JUMP_FORWARD        104  'to 104'
              102  <48>             
            104_0  COME_FROM           100  '100'
            104_1  COME_FROM            80  '80'

 L.  61       104  LOAD_NAME                getattr
              106  LOAD_NAME                errno
              108  LOAD_STR                 'EBADF'
              110  LOAD_CONST               9
              112  CALL_FUNCTION_3       3  ''
              114  STORE_NAME               EBADF

 L.  62       116  LOAD_NAME                getattr
              118  LOAD_NAME                errno
              120  LOAD_STR                 'EAGAIN'
              122  LOAD_CONST               11
              124  CALL_FUNCTION_3       3  ''
              126  STORE_NAME               EAGAIN

 L.  63       128  LOAD_NAME                getattr
              130  LOAD_NAME                errno
              132  LOAD_STR                 'EWOULDBLOCK'
              134  LOAD_CONST               11
              136  CALL_FUNCTION_3       3  ''
              138  STORE_NAME               EWOULDBLOCK

 L.  65       140  BUILD_LIST_0          0 
              142  LOAD_CONST               ('fromfd', 'getfqdn', 'create_connection', 'create_server', 'has_dualstack_ipv6', 'AddressFamily', 'SocketKind')
              144  CALL_FINALLY        147  'to 147'
              146  STORE_NAME               __all__

 L.  67       148  LOAD_NAME                __all__
              150  LOAD_METHOD              extend
              152  LOAD_NAME                os
              154  LOAD_METHOD              _get_exports_list
              156  LOAD_NAME                _socket
              158  CALL_METHOD_1         1  ''
              160  CALL_METHOD_1         1  ''
              162  POP_TOP          

 L.  75       164  LOAD_NAME                IntEnum
              166  LOAD_METHOD              _convert_

 L.  76       168  LOAD_STR                 'AddressFamily'

 L.  77       170  LOAD_NAME                __name__

 L.  78       172  LOAD_LAMBDA              '<code_object <lambda>>'
              174  LOAD_STR                 '<lambda>'
              176  MAKE_FUNCTION_0          'Neither defaults, keyword-only args, annotations, nor closures'

 L.  75       178  CALL_METHOD_3         3  ''
              180  POP_TOP          

 L.  80       182  LOAD_NAME                IntEnum
              184  LOAD_METHOD              _convert_

 L.  81       186  LOAD_STR                 'SocketKind'

 L.  82       188  LOAD_NAME                __name__

 L.  83       190  LOAD_LAMBDA              '<code_object <lambda>>'
              192  LOAD_STR                 '<lambda>'
              194  MAKE_FUNCTION_0          'Neither defaults, keyword-only args, annotations, nor closures'

 L.  80       196  CALL_METHOD_3         3  ''
              198  POP_TOP          

 L.  85       200  LOAD_NAME                IntFlag
              202  LOAD_METHOD              _convert_

 L.  86       204  LOAD_STR                 'MsgFlag'

 L.  87       206  LOAD_NAME                __name__

 L.  88       208  LOAD_LAMBDA              '<code_object <lambda>>'
              210  LOAD_STR                 '<lambda>'
              212  MAKE_FUNCTION_0          'Neither defaults, keyword-only args, annotations, nor closures'

 L.  85       214  CALL_METHOD_3         3  ''
              216  POP_TOP          

 L.  90       218  LOAD_NAME                IntFlag
              220  LOAD_METHOD              _convert_

 L.  91       222  LOAD_STR                 'AddressInfo'

 L.  92       224  LOAD_NAME                __name__

 L.  93       226  LOAD_LAMBDA              '<code_object <lambda>>'
              228  LOAD_STR                 '<lambda>'
              230  MAKE_FUNCTION_0          'Neither defaults, keyword-only args, annotations, nor closures'

 L.  90       232  CALL_METHOD_3         3  ''
              234  POP_TOP          

 L.  95       236  LOAD_STR                 '127.0.0.1'
              238  STORE_NAME               _LOCALHOST

 L.  96       240  LOAD_STR                 '::1'
              242  STORE_NAME               _LOCALHOST_V6

 L.  99       244  LOAD_CODE                <code_object _intenum_converter>
              246  LOAD_STR                 '_intenum_converter'
              248  MAKE_FUNCTION_0          'Neither defaults, keyword-only args, annotations, nor closures'
              250  STORE_NAME               _intenum_converter

 L. 111       252  LOAD_NAME                sys
              254  LOAD_ATTR                platform
              256  LOAD_METHOD              lower
              258  CALL_METHOD_0         0  ''
              260  LOAD_METHOD              startswith
              262  LOAD_STR                 'win'
              264  CALL_METHOD_1         1  ''
          266_268  POP_JUMP_IF_FALSE  1044  'to 1044'

 L. 112       270  BUILD_MAP_0           0 
              272  STORE_NAME               errorTab

 L. 113       274  LOAD_STR                 'Specified event object handle is invalid.'
              276  LOAD_NAME                errorTab
              278  LOAD_CONST               6
              280  STORE_SUBSCR     

 L. 114       282  LOAD_STR                 'Insufficient memory available.'
              284  LOAD_NAME                errorTab
              286  LOAD_CONST               8
              288  STORE_SUBSCR     

 L. 115       290  LOAD_STR                 'One or more parameters are invalid.'
              292  LOAD_NAME                errorTab
              294  LOAD_CONST               87
              296  STORE_SUBSCR     

 L. 116       298  LOAD_STR                 'Overlapped operation aborted.'
              300  LOAD_NAME                errorTab
              302  LOAD_CONST               995
              304  STORE_SUBSCR     

 L. 117       306  LOAD_STR                 'Overlapped I/O event object not in signaled state.'
              308  LOAD_NAME                errorTab
              310  LOAD_CONST               996
              312  STORE_SUBSCR     

 L. 118       314  LOAD_STR                 'Overlapped operation will complete later.'
              316  LOAD_NAME                errorTab
              318  LOAD_CONST               997
              320  STORE_SUBSCR     

 L. 119       322  LOAD_STR                 'The operation was interrupted.'
              324  LOAD_NAME                errorTab
              326  LOAD_CONST               10004
              328  STORE_SUBSCR     

 L. 120       330  LOAD_STR                 'A bad file handle was passed.'
              332  LOAD_NAME                errorTab
              334  LOAD_CONST               10009
              336  STORE_SUBSCR     

 L. 121       338  LOAD_STR                 'Permission denied.'
              340  LOAD_NAME                errorTab
              342  LOAD_CONST               10013
              344  STORE_SUBSCR     

 L. 122       346  LOAD_STR                 'A fault occurred on the network??'
              348  LOAD_NAME                errorTab
              350  LOAD_CONST               10014
              352  STORE_SUBSCR     

 L. 123       354  LOAD_STR                 'An invalid operation was attempted.'
              356  LOAD_NAME                errorTab
              358  LOAD_CONST               10022
              360  STORE_SUBSCR     

 L. 124       362  LOAD_STR                 'Too many open files.'
              364  LOAD_NAME                errorTab
              366  LOAD_CONST               10024
              368  STORE_SUBSCR     

 L. 125       370  LOAD_STR                 'The socket operation would block'
              372  LOAD_NAME                errorTab
              374  LOAD_CONST               10035
              376  STORE_SUBSCR     

 L. 126       378  LOAD_STR                 'A blocking operation is already in progress.'
              380  LOAD_NAME                errorTab
              382  LOAD_CONST               10036
              384  STORE_SUBSCR     

 L. 127       386  LOAD_STR                 'Operation already in progress.'
              388  LOAD_NAME                errorTab
              390  LOAD_CONST               10037
              392  STORE_SUBSCR     

 L. 128       394  LOAD_STR                 'Socket operation on nonsocket.'
              396  LOAD_NAME                errorTab
              398  LOAD_CONST               10038
              400  STORE_SUBSCR     

 L. 129       402  LOAD_STR                 'Destination address required.'
              404  LOAD_NAME                errorTab
              406  LOAD_CONST               10039
              408  STORE_SUBSCR     

 L. 130       410  LOAD_STR                 'Message too long.'
              412  LOAD_NAME                errorTab
              414  LOAD_CONST               10040
              416  STORE_SUBSCR     

 L. 131       418  LOAD_STR                 'Protocol wrong type for socket.'
              420  LOAD_NAME                errorTab
              422  LOAD_CONST               10041
              424  STORE_SUBSCR     

 L. 132       426  LOAD_STR                 'Bad protocol option.'
              428  LOAD_NAME                errorTab
              430  LOAD_CONST               10042
              432  STORE_SUBSCR     

 L. 133       434  LOAD_STR                 'Protocol not supported.'
              436  LOAD_NAME                errorTab
              438  LOAD_CONST               10043
              440  STORE_SUBSCR     

 L. 134       442  LOAD_STR                 'Socket type not supported.'
              444  LOAD_NAME                errorTab
              446  LOAD_CONST               10044
              448  STORE_SUBSCR     

 L. 135       450  LOAD_STR                 'Operation not supported.'
              452  LOAD_NAME                errorTab
              454  LOAD_CONST               10045
              456  STORE_SUBSCR     

 L. 136       458  LOAD_STR                 'Protocol family not supported.'
              460  LOAD_NAME                errorTab
              462  LOAD_CONST               10046
              464  STORE_SUBSCR     

 L. 137       466  LOAD_STR                 'Address family not supported by protocol family.'
              468  LOAD_NAME                errorTab
              470  LOAD_CONST               10047
              472  STORE_SUBSCR     

 L. 138       474  LOAD_STR                 'The network address is in use.'
              476  LOAD_NAME                errorTab
              478  LOAD_CONST               10048
              480  STORE_SUBSCR     

 L. 139       482  LOAD_STR                 'Cannot assign requested address.'
              484  LOAD_NAME                errorTab
              486  LOAD_CONST               10049
              488  STORE_SUBSCR     

 L. 140       490  LOAD_STR                 'Network is down.'
              492  LOAD_NAME                errorTab
              494  LOAD_CONST               10050
              496  STORE_SUBSCR     

 L. 141       498  LOAD_STR                 'Network is unreachable.'
              500  LOAD_NAME                errorTab
              502  LOAD_CONST               10051
              504  STORE_SUBSCR     

 L. 142       506  LOAD_STR                 'Network dropped connection on reset.'
              508  LOAD_NAME                errorTab
              510  LOAD_CONST               10052
              512  STORE_SUBSCR     

 L. 143       514  LOAD_STR                 'Software caused connection abort.'
              516  LOAD_NAME                errorTab
              518  LOAD_CONST               10053
              520  STORE_SUBSCR     

 L. 144       522  LOAD_STR                 'The connection has been reset.'
              524  LOAD_NAME                errorTab
              526  LOAD_CONST               10054
              528  STORE_SUBSCR     

 L. 145       530  LOAD_STR                 'No buffer space available.'
              532  LOAD_NAME                errorTab
              534  LOAD_CONST               10055
              536  STORE_SUBSCR     

 L. 146       538  LOAD_STR                 'Socket is already connected.'
              540  LOAD_NAME                errorTab
              542  LOAD_CONST               10056
              544  STORE_SUBSCR     

 L. 147       546  LOAD_STR                 'Socket is not connected.'
              548  LOAD_NAME                errorTab
              550  LOAD_CONST               10057
              552  STORE_SUBSCR     

 L. 148       554  LOAD_STR                 'The network has been shut down.'
              556  LOAD_NAME                errorTab
              558  LOAD_CONST               10058
              560  STORE_SUBSCR     

 L. 149       562  LOAD_STR                 'Too many references.'
              564  LOAD_NAME                errorTab
              566  LOAD_CONST               10059
              568  STORE_SUBSCR     

 L. 150       570  LOAD_STR                 'The operation timed out.'
              572  LOAD_NAME                errorTab
              574  LOAD_CONST               10060
              576  STORE_SUBSCR     

 L. 151       578  LOAD_STR                 'Connection refused.'
              580  LOAD_NAME                errorTab
              582  LOAD_CONST               10061
              584  STORE_SUBSCR     

 L. 152       586  LOAD_STR                 'Cannot translate name.'
              588  LOAD_NAME                errorTab
              590  LOAD_CONST               10062
              592  STORE_SUBSCR     

 L. 153       594  LOAD_STR                 'The name is too long.'
              596  LOAD_NAME                errorTab
              598  LOAD_CONST               10063
              600  STORE_SUBSCR     

 L. 154       602  LOAD_STR                 'The host is down.'
              604  LOAD_NAME                errorTab
              606  LOAD_CONST               10064
              608  STORE_SUBSCR     

 L. 155       610  LOAD_STR                 'The host is unreachable.'
              612  LOAD_NAME                errorTab
              614  LOAD_CONST               10065
              616  STORE_SUBSCR     

 L. 156       618  LOAD_STR                 'Directory not empty.'
              620  LOAD_NAME                errorTab
              622  LOAD_CONST               10066
              624  STORE_SUBSCR     

 L. 157       626  LOAD_STR                 'Too many processes.'
              628  LOAD_NAME                errorTab
              630  LOAD_CONST               10067
              632  STORE_SUBSCR     

 L. 158       634  LOAD_STR                 'User quota exceeded.'
              636  LOAD_NAME                errorTab
              638  LOAD_CONST               10068
              640  STORE_SUBSCR     

 L. 159       642  LOAD_STR                 'Disk quota exceeded.'
              644  LOAD_NAME                errorTab
              646  LOAD_CONST               10069
              648  STORE_SUBSCR     

 L. 160       650  LOAD_STR                 'Stale file handle reference.'
              652  LOAD_NAME                errorTab
              654  LOAD_CONST               10070
              656  STORE_SUBSCR     

 L. 161       658  LOAD_STR                 'Item is remote.'
              660  LOAD_NAME                errorTab
              662  LOAD_CONST               10071
              664  STORE_SUBSCR     

 L. 162       666  LOAD_STR                 'Network subsystem is unavailable.'
              668  LOAD_NAME                errorTab
              670  LOAD_CONST               10091
              672  STORE_SUBSCR     

 L. 163       674  LOAD_STR                 'Winsock.dll version out of range.'
              676  LOAD_NAME                errorTab
              678  LOAD_CONST               10092
              680  STORE_SUBSCR     

 L. 164       682  LOAD_STR                 'Successful WSAStartup not yet performed.'
              684  LOAD_NAME                errorTab
              686  LOAD_CONST               10093
              688  STORE_SUBSCR     

 L. 165       690  LOAD_STR                 'Graceful shutdown in progress.'
              692  LOAD_NAME                errorTab
              694  LOAD_CONST               10101
              696  STORE_SUBSCR     

 L. 166       698  LOAD_STR                 'No more results from WSALookupServiceNext.'
              700  LOAD_NAME                errorTab
              702  LOAD_CONST               10102
              704  STORE_SUBSCR     

 L. 167       706  LOAD_STR                 'Call has been canceled.'
              708  LOAD_NAME                errorTab
              710  LOAD_CONST               10103
              712  STORE_SUBSCR     

 L. 168       714  LOAD_STR                 'Procedure call table is invalid.'
              716  LOAD_NAME                errorTab
              718  LOAD_CONST               10104
              720  STORE_SUBSCR     

 L. 169       722  LOAD_STR                 'Service provider is invalid.'
              724  LOAD_NAME                errorTab
              726  LOAD_CONST               10105
              728  STORE_SUBSCR     

 L. 170       730  LOAD_STR                 'Service provider failed to initialize.'
              732  LOAD_NAME                errorTab
              734  LOAD_CONST               10106
              736  STORE_SUBSCR     

 L. 171       738  LOAD_STR                 'System call failure.'
              740  LOAD_NAME                errorTab
              742  LOAD_CONST               10107
              744  STORE_SUBSCR     

 L. 172       746  LOAD_STR                 'Service not found.'
              748  LOAD_NAME                errorTab
              750  LOAD_CONST               10108
              752  STORE_SUBSCR     

 L. 173       754  LOAD_STR                 'Class type not found.'
              756  LOAD_NAME                errorTab
              758  LOAD_CONST               10109
              760  STORE_SUBSCR     

 L. 174       762  LOAD_STR                 'No more results from WSALookupServiceNext.'
              764  LOAD_NAME                errorTab
              766  LOAD_CONST               10110
              768  STORE_SUBSCR     

 L. 175       770  LOAD_STR                 'Call was canceled.'
              772  LOAD_NAME                errorTab
              774  LOAD_CONST               10111
              776  STORE_SUBSCR     

 L. 176       778  LOAD_STR                 'Database query was refused.'
              780  LOAD_NAME                errorTab
              782  LOAD_CONST               10112
              784  STORE_SUBSCR     

 L. 177       786  LOAD_STR                 'Host not found.'
              788  LOAD_NAME                errorTab
              790  LOAD_CONST               11001
              792  STORE_SUBSCR     

 L. 178       794  LOAD_STR                 'Nonauthoritative host not found.'
              796  LOAD_NAME                errorTab
              798  LOAD_CONST               11002
              800  STORE_SUBSCR     

 L. 179       802  LOAD_STR                 'This is a nonrecoverable error.'
              804  LOAD_NAME                errorTab
              806  LOAD_CONST               11003
              808  STORE_SUBSCR     

 L. 180       810  LOAD_STR                 'Valid name, no data record requested type.'
              812  LOAD_NAME                errorTab
              814  LOAD_CONST               11004
              816  STORE_SUBSCR     

 L. 181       818  LOAD_STR                 'QoS receivers.'
              820  LOAD_NAME                errorTab
              822  LOAD_CONST               11005
              824  STORE_SUBSCR     

 L. 182       826  LOAD_STR                 'QoS senders.'
              828  LOAD_NAME                errorTab
              830  LOAD_CONST               11006
              832  STORE_SUBSCR     

 L. 183       834  LOAD_STR                 'No QoS senders.'
              836  LOAD_NAME                errorTab
              838  LOAD_CONST               11007
              840  STORE_SUBSCR     

 L. 184       842  LOAD_STR                 'QoS no receivers.'
              844  LOAD_NAME                errorTab
              846  LOAD_CONST               11008
              848  STORE_SUBSCR     

 L. 185       850  LOAD_STR                 'QoS request confirmed.'
              852  LOAD_NAME                errorTab
              854  LOAD_CONST               11009
              856  STORE_SUBSCR     

 L. 186       858  LOAD_STR                 'QoS admission error.'
              860  LOAD_NAME                errorTab
              862  LOAD_CONST               11010
              864  STORE_SUBSCR     

 L. 187       866  LOAD_STR                 'QoS policy failure.'
              868  LOAD_NAME                errorTab
              870  LOAD_CONST               11011
              872  STORE_SUBSCR     

 L. 188       874  LOAD_STR                 'QoS bad style.'
              876  LOAD_NAME                errorTab
              878  LOAD_CONST               11012
              880  STORE_SUBSCR     

 L. 189       882  LOAD_STR                 'QoS bad object.'
              884  LOAD_NAME                errorTab
              886  LOAD_CONST               11013
              888  STORE_SUBSCR     

 L. 190       890  LOAD_STR                 'QoS traffic control error.'
              892  LOAD_NAME                errorTab
              894  LOAD_CONST               11014
              896  STORE_SUBSCR     

 L. 191       898  LOAD_STR                 'QoS generic error.'
              900  LOAD_NAME                errorTab
              902  LOAD_CONST               11015
              904  STORE_SUBSCR     

 L. 192       906  LOAD_STR                 'QoS service type error.'
              908  LOAD_NAME                errorTab
              910  LOAD_CONST               11016
              912  STORE_SUBSCR     

 L. 193       914  LOAD_STR                 'QoS flowspec error.'
              916  LOAD_NAME                errorTab
              918  LOAD_CONST               11017
              920  STORE_SUBSCR     

 L. 194       922  LOAD_STR                 'Invalid QoS provider buffer.'
              924  LOAD_NAME                errorTab
              926  LOAD_CONST               11018
              928  STORE_SUBSCR     

 L. 195       930  LOAD_STR                 'Invalid QoS filter style.'
              932  LOAD_NAME                errorTab
              934  LOAD_CONST               11019
              936  STORE_SUBSCR     

 L. 196       938  LOAD_STR                 'Invalid QoS filter style.'
              940  LOAD_NAME                errorTab
              942  LOAD_CONST               11020
              944  STORE_SUBSCR     

 L. 197       946  LOAD_STR                 'Incorrect QoS filter count.'
              948  LOAD_NAME                errorTab
              950  LOAD_CONST               11021
              952  STORE_SUBSCR     

 L. 198       954  LOAD_STR                 'Invalid QoS object length.'
              956  LOAD_NAME                errorTab
              958  LOAD_CONST               11022
              960  STORE_SUBSCR     

 L. 199       962  LOAD_STR                 'Incorrect QoS flow count.'
              964  LOAD_NAME                errorTab
              966  LOAD_CONST               11023
              968  STORE_SUBSCR     

 L. 200       970  LOAD_STR                 'Unrecognized QoS object.'
              972  LOAD_NAME                errorTab
              974  LOAD_CONST               11024
              976  STORE_SUBSCR     

 L. 201       978  LOAD_STR                 'Invalid QoS policy object.'
              980  LOAD_NAME                errorTab
              982  LOAD_CONST               11025
              984  STORE_SUBSCR     

 L. 202       986  LOAD_STR                 'Invalid QoS flow descriptor.'
              988  LOAD_NAME                errorTab
              990  LOAD_CONST               11026
              992  STORE_SUBSCR     

 L. 203       994  LOAD_STR                 'Invalid QoS provider-specific flowspec.'
              996  LOAD_NAME                errorTab
              998  LOAD_CONST               11027
             1000  STORE_SUBSCR     

 L. 204      1002  LOAD_STR                 'Invalid QoS provider-specific filterspec.'
             1004  LOAD_NAME                errorTab
             1006  LOAD_CONST               11028
             1008  STORE_SUBSCR     

 L. 205      1010  LOAD_STR                 'Invalid QoS shape discard mode object.'
             1012  LOAD_NAME                errorTab
             1014  LOAD_CONST               11029
             1016  STORE_SUBSCR     

 L. 206      1018  LOAD_STR                 'Invalid QoS shaping rate object.'
             1020  LOAD_NAME                errorTab
             1022  LOAD_CONST               11030
             1024  STORE_SUBSCR     

 L. 207      1026  LOAD_STR                 'Reserved policy QoS element type.'
             1028  LOAD_NAME                errorTab
             1030  LOAD_CONST               11031
             1032  STORE_SUBSCR     

 L. 208      1034  LOAD_NAME                __all__
             1036  LOAD_METHOD              append
             1038  LOAD_STR                 'errorTab'
             1040  CALL_METHOD_1         1  ''
             1042  POP_TOP          
           1044_0  COME_FROM           266  '266'

 L. 211      1044  LOAD_BUILD_CLASS 
             1046  LOAD_CODE                <code_object _GiveupOnSendfile>
             1048  LOAD_STR                 '_GiveupOnSendfile'
             1050  MAKE_FUNCTION_0          'Neither defaults, keyword-only args, annotations, nor closures'
             1052  LOAD_STR                 '_GiveupOnSendfile'
             1054  LOAD_NAME                Exception
             1056  CALL_FUNCTION_3       3  ''
             1058  STORE_NAME               _GiveupOnSendfile

 L. 214      1060  LOAD_BUILD_CLASS 
             1062  LOAD_CODE                <code_object socket>
             1064  LOAD_STR                 'socket'
             1066  MAKE_FUNCTION_0          'Neither defaults, keyword-only args, annotations, nor closures'
             1068  LOAD_STR                 'socket'
             1070  LOAD_NAME                _socket
             1072  LOAD_ATTR                socket
             1074  CALL_FUNCTION_3       3  ''
             1076  STORE_NAME               socket

 L. 538      1078  LOAD_CONST               (0,)
             1080  LOAD_CODE                <code_object fromfd>
             1082  LOAD_STR                 'fromfd'
             1084  MAKE_FUNCTION_1          'default'
             1086  STORE_NAME               fromfd

 L. 547      1088  LOAD_NAME                hasattr
             1090  LOAD_NAME                _socket
             1092  LOAD_ATTR                socket
             1094  LOAD_STR                 'sendmsg'
             1096  CALL_FUNCTION_2       2  ''
         1098_1100  POP_JUMP_IF_FALSE  1130  'to 1130'

 L. 548      1102  LOAD_CONST               0
             1104  LOAD_CONST               None
             1106  IMPORT_NAME              array
             1108  STORE_NAME               array

 L. 550      1110  LOAD_CONST               (0, None)
             1112  LOAD_CODE                <code_object send_fds>
             1114  LOAD_STR                 'send_fds'
             1116  MAKE_FUNCTION_1          'default'
             1118  STORE_NAME               send_fds

 L. 557      1120  LOAD_NAME                __all__
             1122  LOAD_METHOD              append
             1124  LOAD_STR                 'send_fds'
             1126  CALL_METHOD_1         1  ''
             1128  POP_TOP          
           1130_0  COME_FROM          1098  '1098'

 L. 559      1130  LOAD_NAME                hasattr
             1132  LOAD_NAME                _socket
             1134  LOAD_ATTR                socket
             1136  LOAD_STR                 'recvmsg'
             1138  CALL_FUNCTION_2       2  ''
         1140_1142  POP_JUMP_IF_FALSE  1172  'to 1172'

 L. 560      1144  LOAD_CONST               0
             1146  LOAD_CONST               None
             1148  IMPORT_NAME              array
             1150  STORE_NAME               array

 L. 562      1152  LOAD_CONST               (0,)
             1154  LOAD_CODE                <code_object recv_fds>
             1156  LOAD_STR                 'recv_fds'
             1158  MAKE_FUNCTION_1          'default'
             1160  STORE_NAME               recv_fds

 L. 579      1162  LOAD_NAME                __all__
             1164  LOAD_METHOD              append
             1166  LOAD_STR                 'recv_fds'
             1168  CALL_METHOD_1         1  ''
             1170  POP_TOP          
           1172_0  COME_FROM          1140  '1140'

 L. 581      1172  LOAD_NAME                hasattr
             1174  LOAD_NAME                _socket
             1176  LOAD_ATTR                socket
             1178  LOAD_STR                 'share'
             1180  CALL_FUNCTION_2       2  ''
         1182_1184  POP_JUMP_IF_FALSE  1204  'to 1204'

 L. 582      1186  LOAD_CODE                <code_object fromshare>
             1188  LOAD_STR                 'fromshare'
             1190  MAKE_FUNCTION_0          'Neither defaults, keyword-only args, annotations, nor closures'
             1192  STORE_NAME               fromshare

 L. 589      1194  LOAD_NAME                __all__
             1196  LOAD_METHOD              append
             1198  LOAD_STR                 'fromshare'
             1200  CALL_METHOD_1         1  ''
             1202  POP_TOP          
           1204_0  COME_FROM          1182  '1182'

 L. 591      1204  LOAD_NAME                hasattr
             1206  LOAD_NAME                _socket
             1208  LOAD_STR                 'socketpair'
             1210  CALL_FUNCTION_2       2  ''
         1212_1214  POP_JUMP_IF_FALSE  1234  'to 1234'

 L. 593      1216  LOAD_CONST               None
             1218  LOAD_NAME                SOCK_STREAM
             1220  LOAD_CONST               0
             1222  BUILD_TUPLE_3         3 
             1224  LOAD_CODE                <code_object socketpair>
             1226  LOAD_STR                 'socketpair'
             1228  MAKE_FUNCTION_1          'default'
             1230  STORE_NAME               socketpair
             1232  JUMP_FORWARD       1260  'to 1260'
           1234_0  COME_FROM          1212  '1212'

 L. 614      1234  LOAD_NAME                AF_INET
             1236  LOAD_NAME                SOCK_STREAM
             1238  LOAD_CONST               0
             1240  BUILD_TUPLE_3         3 
             1242  LOAD_CODE                <code_object socketpair>
             1244  LOAD_STR                 'socketpair'
             1246  MAKE_FUNCTION_1          'default'
             1248  STORE_NAME               socketpair

 L. 650      1250  LOAD_NAME                __all__
             1252  LOAD_METHOD              append
             1254  LOAD_STR                 'socketpair'
             1256  CALL_METHOD_1         1  ''
             1258  POP_TOP          
           1260_0  COME_FROM          1232  '1232'

 L. 652      1260  LOAD_STR                 'socketpair([family[, type[, proto]]]) -> (socket object, socket object)\nCreate a pair of socket objects from the sockets returned by the platform\nsocketpair() function.\nThe arguments are the same as for socket() except the default family is AF_UNIX\nif defined on the platform; otherwise, the default is AF_INET.\n'
             1262  LOAD_NAME                socketpair
             1264  STORE_ATTR               __doc__

 L. 659      1266  LOAD_NAME                EAGAIN
             1268  LOAD_NAME                EWOULDBLOCK
             1270  BUILD_SET_2           2 
             1272  STORE_NAME               _blocking_errnos

 L. 661      1274  LOAD_BUILD_CLASS 
             1276  LOAD_CODE                <code_object SocketIO>
             1278  LOAD_STR                 'SocketIO'
             1280  MAKE_FUNCTION_0          'Neither defaults, keyword-only args, annotations, nor closures'
             1282  LOAD_STR                 'SocketIO'
             1284  LOAD_NAME                io
             1286  LOAD_ATTR                RawIOBase
             1288  CALL_FUNCTION_3       3  ''
             1290  STORE_NAME               SocketIO

 L. 778      1292  LOAD_CONST               ('',)
             1294  LOAD_CODE                <code_object getfqdn>
             1296  LOAD_STR                 'getfqdn'
             1298  MAKE_FUNCTION_1          'default'
             1300  STORE_NAME               getfqdn

 L. 804      1302  LOAD_NAME                object
             1304  CALL_FUNCTION_0       0  ''
             1306  STORE_NAME               _GLOBAL_DEFAULT_TIMEOUT

 L. 806      1308  LOAD_NAME                _GLOBAL_DEFAULT_TIMEOUT

 L. 807      1310  LOAD_CONST               None

 L. 806      1312  BUILD_TUPLE_2         2 
             1314  LOAD_CODE                <code_object create_connection>
             1316  LOAD_STR                 'create_connection'
             1318  MAKE_FUNCTION_1          'default'
             1320  STORE_NAME               create_connection

 L. 851      1322  LOAD_CODE                <code_object has_dualstack_ipv6>
             1324  LOAD_STR                 'has_dualstack_ipv6'
             1326  MAKE_FUNCTION_0          'Neither defaults, keyword-only args, annotations, nor closures'
             1328  STORE_NAME               has_dualstack_ipv6

 L. 867      1330  LOAD_NAME                AF_INET
             1332  LOAD_CONST               None
             1334  LOAD_CONST               False

 L. 868      1336  LOAD_CONST               False

 L. 867      1338  LOAD_CONST               ('family', 'backlog', 'reuse_port', 'dualstack_ipv6')
             1340  BUILD_CONST_KEY_MAP_4     4 
             1342  LOAD_CODE                <code_object create_server>
             1344  LOAD_STR                 'create_server'
             1346  MAKE_FUNCTION_2          'keyword-only'
             1348  STORE_NAME               create_server

 L. 936      1350  LOAD_CONST               (0, 0, 0, 0)
             1352  LOAD_CODE                <code_object getaddrinfo>
             1354  LOAD_STR                 'getaddrinfo'
             1356  MAKE_FUNCTION_1          'default'
             1358  STORE_NAME               getaddrinfo

Parse error at or near `<121>' instruction at offset 86

Instruction context:
   
 L.  59        82  DUP_TOP          
                  84  LOAD_NAME                ImportError
->                86  <121>               102  ''
                  88  POP_TOP          
                  90  POP_TOP          
                  92  POP_TOP          

test/101091.pyc -- 
# decompile failed
