Instruction context:
-> 
 L.  36       162  <164>                 1  ''
                 164  CALL_FUNCTION_EX_KW     1  'keyword and positional arguments'
                 166  POP_TOP          
                 168  POP_BLOCK        
                 170  JUMP_FORWARD        194  'to 194'
               172_0  COME_FROM_FINALLY   136  '136'
Instruction context:
   
 L.  59        26  LOAD_FAST                'self'
                  28  LOAD_ATTR                _pid
                  30  LOAD_CONST               None
->                32  <117>                 1  ''
                  34  POP_JUMP_IF_FALSE    54  'to 54'
Instruction context:
   
 L. 102        30  LOAD_FAST                'proto'
                  32  LOAD_CONST               None
->                34  <117>                 0  ''
                  36  POP_JUMP_IF_FALSE    40  'to 40'
Instruction context:
   
 L. 161        14  LOAD_FAST                'proc'
                  16  LOAD_ATTR                stdin
                  18  LOAD_CONST               None
->                20  <117>                 1  ''
                  22  POP_JUMP_IF_FALSE    66  'to 66'
Instruction context:
   
 L. 250        16  LOAD_CONST               None
->                18  LOAD_FAST                'self'
                  20  STORE_ATTR               _loop

test/101125.pyc -- 
# decompile failed

# file test/101125.pyc
# Deparsing stopped due to parse error
