Instruction context:
   
 L.  33        10  LOAD_FAST                'self'
                  12  LOAD_ATTR                stdin
                  14  LOAD_CONST               None
->                16  <117>                 1  ''
                  18  POP_JUMP_IF_FALSE    38  'to 38'
Instruction context:
   
 L.  45        16  LOAD_FAST                'stdout_transport'
                  18  LOAD_CONST               None
->                20  <117>                 1  ''
                  22  POP_JUMP_IF_FALSE    68  'to 68'
Instruction context:
   
 L.  72        36  LOAD_FAST                'reader'
                  38  LOAD_CONST               None
->                40  <117>                 1  ''
                  42  POP_JUMP_IF_FALSE    54  'to 54'
Instruction context:
   
 L.  78        14  LOAD_FAST                'pipe'
                  16  LOAD_CONST               None
->                18  <117>                 1  ''
                  20  POP_JUMP_IF_FALSE    30  'to 30'
Instruction context:
   
 L. 154        66  DUP_TOP          
                  68  LOAD_GLOBAL              BrokenPipeError
                  70  LOAD_GLOBAL              ConnectionResetError
                  72  BUILD_TUPLE_2         2 
->                74  <121>               122  ''
                  76  POP_TOP          
                  78  STORE_FAST               'exc'
                  80  POP_TOP          
                  82  SETUP_FINALLY       114  'to 114'
Instruction context:
   
 L. 171        28  LOAD_FAST                'fd'
                  30  LOAD_CONST               1
                  32  COMPARE_OP               ==
                  34  POP_JUMP_IF_TRUE     40  'to 40'
->                36  <74>             
                  38  RAISE_VARARGS_1       1  'exception instance'
                40_0  COME_FROM            34  '34'

test/101143.pyc -- 
# decompile failed

# file test/101143.pyc
# Deparsing stopped due to parse error
