Instruction context:
   
 L.  53        80  LOAD_GLOBAL              os
                  82  LOAD_ATTR                path
                  84  LOAD_ATTR                join
                  86  LOAD_FAST                'root_lib'
                  88  BUILD_LIST_1          1 
                  90  LOAD_FAST                'dir_comps'
->                92  CALL_FINALLY         95  'to 95'
                  94  WITH_CLEANUP_FINISH
                  96  CALL_FUNCTION_EX      0  'positional arguments only'
                  98  RETURN_VALUE     

test/101186.pyc -- 
# decompile failed

# file test/101186.pyc
# Deparsing stopped due to parse error
