Instruction context:
   
 L.  66       104  DUP_TOP          
                 106  LOAD_FAST                'struct'
                 108  LOAD_ATTR                error
->               110  <121>               128  ''
                 112  POP_TOP          
                 114  POP_TOP          
                 116  POP_TOP          
Instruction context:
   
 L.  91        18  LOAD_CONST               True
->                20  LOAD_FAST                'self'
                  22  STORE_ATTR               closed
                  24  JUMP_FORWARD         34  'to 34'
                26_0  COME_FROM_FINALLY     6  '6'
                  26  LOAD_CONST               True
                  28  LOAD_FAST                'self'
                  30  STORE_ATTR               closed
                  32  <48>             
                34_0  COME_FROM            24  '24'
Instruction context:
   
 L. 162        84  POP_BLOCK        
                  86  LOAD_CONST               None
->                88  RETURN_VALUE     
                90_0  COME_FROM_FINALLY    20  '20'

test/101391.pyc -- 
# decompile failed

# file test/101391.pyc
# Deparsing stopped due to parse error
