
# file test/101788.pyc
# --- This code section failed: ---

 L.   3         0  LOAD_STR                 '\nrequests.sessions\n~~~~~~~~~~~~~~~~~\n\nThis module provides a Session object to manage and persist settings across\nrequests (cookies, auth, proxies).\n'
                2  STORE_NAME               __doc__

 L.  10         4  LOAD_CONST               0
                6  LOAD_CONST               None
                8  IMPORT_NAME              os
               10  STORE_NAME               os

 L.  11        12  LOAD_CONST               0
               14  LOAD_CONST               None
               16  IMPORT_NAME              sys
               18  STORE_NAME               sys

 L.  12        20  LOAD_CONST               0
               22  LOAD_CONST               None
               24  IMPORT_NAME              time
               26  STORE_NAME               time

 L.  13        28  LOAD_CONST               0
               30  LOAD_CONST               ('timedelta',)
               32  IMPORT_NAME              datetime
               34  IMPORT_FROM              timedelta
               36  STORE_NAME               timedelta
               38  POP_TOP          

 L.  14        40  LOAD_CONST               0
               42  LOAD_CONST               ('OrderedDict',)
               44  IMPORT_NAME              collections
               46  IMPORT_FROM              OrderedDict
               48  STORE_NAME               OrderedDict
               50  POP_TOP          

 L.  16        52  LOAD_CONST               1
               54  LOAD_CONST               ('_basic_auth_str',)
               56  IMPORT_NAME              auth
               58  IMPORT_FROM              _basic_auth_str
               60  STORE_NAME               _basic_auth_str
               62  POP_TOP          

 L.  17        64  LOAD_CONST               1
               66  LOAD_CONST               ('cookielib', 'is_py3', 'urljoin', 'urlparse', 'Mapping')
               68  IMPORT_NAME              compat
               70  IMPORT_FROM              cookielib
               72  STORE_NAME               cookielib
               74  IMPORT_FROM              is_py3
               76  STORE_NAME               is_py3
               78  IMPORT_FROM              urljoin
               80  STORE_NAME               urljoin
               82  IMPORT_FROM              urlparse
               84  STORE_NAME               urlparse
               86  IMPORT_FROM              Mapping
               88  STORE_NAME               Mapping
               90  POP_TOP          

 L.  18        92  LOAD_CONST               1
               94  LOAD_CONST               ('cookiejar_from_dict', 'extract_cookies_to_jar', 'RequestsCookieJar', 'merge_cookies')
               96  IMPORT_NAME              cookies
               98  IMPORT_FROM              cookiejar_from_dict
              100  STORE_NAME               cookiejar_from_dict
              102  IMPORT_FROM              extract_cookies_to_jar
              104  STORE_NAME               extract_cookies_to_jar
              106  IMPORT_FROM              RequestsCookieJar
              108  STORE_NAME               RequestsCookieJar
              110  IMPORT_FROM              merge_cookies
              112  STORE_NAME               merge_cookies
              114  POP_TOP          

 L.  20       116  LOAD_CONST               1
              118  LOAD_CONST               ('Request', 'PreparedRequest', 'DEFAULT_REDIRECT_LIMIT')
              120  IMPORT_NAME              models
              122  IMPORT_FROM              Request
              124  STORE_NAME               Request
              126  IMPORT_FROM              PreparedRequest
              128  STORE_NAME               PreparedRequest
              130  IMPORT_FROM              DEFAULT_REDIRECT_LIMIT
              132  STORE_NAME               DEFAULT_REDIRECT_LIMIT
              134  POP_TOP          

 L.  21       136  LOAD_CONST               1
              138  LOAD_CONST               ('default_hooks', 'dispatch_hook')
              140  IMPORT_NAME              hooks
              142  IMPORT_FROM              default_hooks
              144  STORE_NAME               default_hooks
              146  IMPORT_FROM              dispatch_hook
              148  STORE_NAME               dispatch_hook
              150  POP_TOP          

 L.  22       152  LOAD_CONST               1
              154  LOAD_CONST               ('to_native_string',)
              156  IMPORT_NAME              _internal_utils
              158  IMPORT_FROM              to_native_string
              160  STORE_NAME               to_native_string
              162  POP_TOP          

 L.  23       164  LOAD_CONST               1
              166  LOAD_CONST               ('to_key_val_list', 'default_headers', 'DEFAULT_PORTS')
              168  IMPORT_NAME              utils
              170  IMPORT_FROM              to_key_val_list
              172  STORE_NAME               to_key_val_list
              174  IMPORT_FROM              default_headers
              176  STORE_NAME               default_headers
              178  IMPORT_FROM              DEFAULT_PORTS
              180  STORE_NAME               DEFAULT_PORTS
              182  POP_TOP          

 L.  24       184  LOAD_CONST               1
              186  LOAD_CONST               ('TooManyRedirects', 'InvalidSchema', 'ChunkedEncodingError', 'ContentDecodingError')
              188  IMPORT_NAME              exceptions
              190  IMPORT_FROM              TooManyRedirects
              192  STORE_NAME               TooManyRedirects
              194  IMPORT_FROM              InvalidSchema
              196  STORE_NAME               InvalidSchema
              198  IMPORT_FROM              ChunkedEncodingError
              200  STORE_NAME               ChunkedEncodingError
              202  IMPORT_FROM              ContentDecodingError
              204  STORE_NAME               ContentDecodingError
              206  POP_TOP          

 L.  27       208  LOAD_CONST               1
              210  LOAD_CONST               ('CaseInsensitiveDict',)
              212  IMPORT_NAME              structures
              214  IMPORT_FROM              CaseInsensitiveDict
              216  STORE_NAME               CaseInsensitiveDict
              218  POP_TOP          

 L.  28       220  LOAD_CONST               1
              222  LOAD_CONST               ('HTTPAdapter',)
              224  IMPORT_NAME              adapters
              226  IMPORT_FROM              HTTPAdapter
              228  STORE_NAME               HTTPAdapter
              230  POP_TOP          

 L.  30       232  LOAD_CONST               1
              234  LOAD_CONST               ('requote_uri', 'get_environ_proxies', 'get_netrc_auth', 'should_bypass_proxies', 'get_auth_from_url', 'rewind_body')
              236  IMPORT_NAME              utils
              238  IMPORT_FROM              requote_uri
              240  STORE_NAME               requote_uri
              242  IMPORT_FROM              get_environ_proxies
              244  STORE_NAME               get_environ_proxies
              246  IMPORT_FROM              get_netrc_auth
              248  STORE_NAME               get_netrc_auth
              250  IMPORT_FROM              should_bypass_proxies
              252  STORE_NAME               should_bypass_proxies
              254  IMPORT_FROM              get_auth_from_url
              256  STORE_NAME               get_auth_from_url
              258  IMPORT_FROM              rewind_body
              260  STORE_NAME               rewind_body
              262  POP_TOP          

 L.  35       264  LOAD_CONST               1
              266  LOAD_CONST               ('codes',)
              268  IMPORT_NAME              status_codes
              270  IMPORT_FROM              codes
              272  STORE_NAME               codes
              274  POP_TOP          

 L.  38       276  LOAD_CONST               1
              278  LOAD_CONST               ('REDIRECT_STATI',)
              280  IMPORT_NAME              models
              282  IMPORT_FROM              REDIRECT_STATI
              284  STORE_NAME               REDIRECT_STATI
              286  POP_TOP          

 L.  41       288  LOAD_NAME                sys
              290  LOAD_ATTR                platform
              292  LOAD_STR                 'win32'
              294  COMPARE_OP               ==
          296_298  POP_JUMP_IF_FALSE   340  'to 340'

 L.  42       300  SETUP_FINALLY       312  'to 312'

 L.  43       302  LOAD_NAME                time
              304  LOAD_ATTR                perf_counter
              306  STORE_NAME               preferred_clock
              308  POP_BLOCK        
              310  JUMP_FORWARD        338  'to 338'
            312_0  COME_FROM_FINALLY   300  '300'

 L.  44       312  DUP_TOP          
              314  LOAD_NAME                AttributeError
          316_318  <121>               336  ''
              320  POP_TOP          
              322  POP_TOP          
              324  POP_TOP          

 L.  45       326  LOAD_NAME                time
              328  LOAD_ATTR                clock
              330  STORE_NAME               preferred_clock
              332  POP_EXCEPT       
              334  JUMP_FORWARD        338  'to 338'
              336  <48>             
            338_0  COME_FROM           334  '334'
            338_1  COME_FROM           310  '310'
              338  JUMP_FORWARD        346  'to 346'
            340_0  COME_FROM           296  '296'

 L.  47       340  LOAD_NAME                time
              342  LOAD_ATTR                time
              344  STORE_NAME               preferred_clock
            346_0  COME_FROM           338  '338'

 L.  50       346  LOAD_NAME                OrderedDict
              348  BUILD_TUPLE_1         1 
              350  LOAD_CODE                <code_object merge_setting>
              352  LOAD_STR                 'merge_setting'
              354  MAKE_FUNCTION_1          'default'
              356  STORE_NAME               merge_setting

 L.  81       358  LOAD_NAME                OrderedDict
              360  BUILD_TUPLE_1         1 
              362  LOAD_CODE                <code_object merge_hooks>
              364  LOAD_STR                 'merge_hooks'
              366  MAKE_FUNCTION_1          'default'
              368  STORE_NAME               merge_hooks

 L.  96       370  LOAD_BUILD_CLASS 
              372  LOAD_CODE                <code_object SessionRedirectMixin>
              374  LOAD_STR                 'SessionRedirectMixin'
              376  MAKE_FUNCTION_0          'Neither defaults, keyword-only args, annotations, nor closures'
              378  LOAD_STR                 'SessionRedirectMixin'
              380  LOAD_NAME                object
              382  CALL_FUNCTION_3       3  ''
              384  STORE_NAME               SessionRedirectMixin

 L. 337       386  LOAD_BUILD_CLASS 
              388  LOAD_CODE                <code_object Session>
              390  LOAD_STR                 'Session'
              392  MAKE_FUNCTION_0          'Neither defaults, keyword-only args, annotations, nor closures'
              394  LOAD_STR                 'Session'
              396  LOAD_NAME                SessionRedirectMixin
              398  CALL_FUNCTION_3       3  ''
              400  STORE_NAME               Session

 L. 769       402  LOAD_CODE                <code_object session>
              404  LOAD_STR                 'session'
              406  MAKE_FUNCTION_0          'Neither defaults, keyword-only args, annotations, nor closures'
              408  STORE_NAME               session

Parse error at or near `<121>' instruction at offset 316_318

Instruction context:
   
 L.  44       312  DUP_TOP          
                 314  LOAD_NAME                AttributeError
->           316_318  <121>               336  ''
                 320  POP_TOP          
                 322  POP_TOP          
                 324  POP_TOP          

test/101788.pyc -- 
# decompile failed
