
# file test/101716.pyc
# --- This code section failed: ---

 L.   1         0  LOAD_CONST               0
                2  LOAD_CONST               None
                4  IMPORT_NAME              os
                6  STORE_NAME               os

 L.   3         8  LOAD_CONST               1
               10  LOAD_CONST               ('abc',)
               12  IMPORT_NAME              
               14  IMPORT_FROM              abc
               16  STORE_NAME               resources_abc
               18  POP_TOP          

 L.   4        20  LOAD_CONST               1
               22  LOAD_CONST               ('_common',)
               24  IMPORT_NAME              
               26  IMPORT_FROM              _common
               28  STORE_NAME               _common
               30  POP_TOP          

 L.   5        32  LOAD_CONST               1
               34  LOAD_CONST               ('as_file',)
               36  IMPORT_NAME              _common
               38  IMPORT_FROM              as_file
               40  STORE_NAME               as_file
               42  POP_TOP          

 L.   6        44  LOAD_CONST               0
               46  LOAD_CONST               ('contextmanager', 'suppress')
               48  IMPORT_NAME              contextlib
               50  IMPORT_FROM              contextmanager
               52  STORE_NAME               contextmanager
               54  IMPORT_FROM              suppress
               56  STORE_NAME               suppress
               58  POP_TOP          

 L.   7        60  LOAD_CONST               0
               62  LOAD_CONST               ('import_module',)
               64  IMPORT_NAME              importlib
               66  IMPORT_FROM              import_module
               68  STORE_NAME               import_module
               70  POP_TOP          

 L.   8        72  LOAD_CONST               0
               74  LOAD_CONST               ('ResourceLoader',)
               76  IMPORT_NAME_ATTR         importlib.abc
               78  IMPORT_FROM              ResourceLoader
               80  STORE_NAME               ResourceLoader
               82  POP_TOP          

 L.   9        84  LOAD_CONST               0
               86  LOAD_CONST               ('BytesIO', 'TextIOWrapper')
               88  IMPORT_NAME              io
               90  IMPORT_FROM              BytesIO
               92  STORE_NAME               BytesIO
               94  IMPORT_FROM              TextIOWrapper
               96  STORE_NAME               TextIOWrapper
               98  POP_TOP          

 L.  10       100  LOAD_CONST               0
              102  LOAD_CONST               ('Path',)
              104  IMPORT_NAME              pathlib
              106  IMPORT_FROM              Path
              108  STORE_NAME               Path
              110  POP_TOP          

 L.  11       112  LOAD_CONST               0
              114  LOAD_CONST               ('ModuleType',)
              116  IMPORT_NAME              types
              118  IMPORT_FROM              ModuleType
              120  STORE_NAME               ModuleType
              122  POP_TOP          

 L.  12       124  LOAD_CONST               0
              126  LOAD_CONST               ('ContextManager', 'Iterable', 'Optional', 'Union')
              128  IMPORT_NAME              typing
              130  IMPORT_FROM              ContextManager
              132  STORE_NAME               ContextManager
              134  IMPORT_FROM              Iterable
              136  STORE_NAME               Iterable
              138  IMPORT_FROM              Optional
              140  STORE_NAME               Optional
              142  IMPORT_FROM              Union
              144  STORE_NAME               Union
              146  POP_TOP          

 L.  13       148  LOAD_CONST               0
              150  LOAD_CONST               ('cast',)
              152  IMPORT_NAME              typing
              154  IMPORT_FROM              cast
              156  STORE_NAME               cast
              158  POP_TOP          

 L.  14       160  LOAD_CONST               0
              162  LOAD_CONST               ('BinaryIO', 'TextIO')
              164  IMPORT_NAME_ATTR         typing.io
              166  IMPORT_FROM              BinaryIO
              168  STORE_NAME               BinaryIO
              170  IMPORT_FROM              TextIO
              172  STORE_NAME               TextIO
              174  POP_TOP          

 L.  17       176  BUILD_LIST_0          0 
              178  LOAD_CONST               ('Package', 'Resource', 'as_file', 'contents', 'files', 'is_resource', 'open_binary', 'open_text', 'path', 'read_binary', 'read_text')
              180  CALL_FINALLY        183  'to 183'
              182  STORE_NAME               __all__

 L.  32       184  LOAD_NAME                Union
              186  LOAD_NAME                str
              188  LOAD_NAME                ModuleType
              190  BUILD_TUPLE_2         2 
              192  BINARY_SUBSCR    
              194  STORE_NAME               Package

 L.  33       196  LOAD_NAME                Union
              198  LOAD_NAME                str
              200  LOAD_NAME                os
              202  LOAD_ATTR                PathLike
              204  BUILD_TUPLE_2         2 
              206  BINARY_SUBSCR    
              208  STORE_NAME               Resource

 L.  36       210  LOAD_NAME                ModuleType
              212  LOAD_CONST               ('return',)
              214  BUILD_CONST_KEY_MAP_1     1 
              216  LOAD_CODE                <code_object _resolve>
              218  LOAD_STR                 '_resolve'
              220  MAKE_FUNCTION_4          'annotation'
              222  STORE_NAME               _resolve

 L.  43       224  LOAD_NAME                ModuleType
              226  LOAD_CONST               ('return',)
              228  BUILD_CONST_KEY_MAP_1     1 
              230  LOAD_CODE                <code_object _get_package>
              232  LOAD_STR                 '_get_package'
              234  MAKE_FUNCTION_4          'annotation'
              236  STORE_NAME               _get_package

 L.  55       238  LOAD_NAME                str
              240  LOAD_CONST               ('return',)
              242  BUILD_CONST_KEY_MAP_1     1 
              244  LOAD_CODE                <code_object _normalize_path>
              246  LOAD_STR                 '_normalize_path'
              248  MAKE_FUNCTION_4          'annotation'
              250  STORE_NAME               _normalize_path

 L.  67       252  LOAD_NAME                ModuleType
              254  LOAD_NAME                Optional
              256  LOAD_NAME                resources_abc
              258  LOAD_ATTR                ResourceReader
              260  BINARY_SUBSCR    

 L.  66       262  LOAD_CONST               ('package', 'return')
              264  BUILD_CONST_KEY_MAP_2     2 
              266  LOAD_CODE                <code_object _get_resource_reader>
              268  LOAD_STR                 '_get_resource_reader'
              270  MAKE_FUNCTION_4          'annotation'
              272  STORE_NAME               _get_resource_reader

 L.  80       274  LOAD_CODE                <code_object _check_location>
              276  LOAD_STR                 '_check_location'
              278  MAKE_FUNCTION_0          'Neither defaults, keyword-only args, annotations, nor closures'
              280  STORE_NAME               _check_location

 L.  85       282  LOAD_NAME                Package
              284  LOAD_NAME                Resource
              286  LOAD_NAME                BinaryIO
              288  LOAD_CONST               ('package', 'resource', 'return')
              290  BUILD_CONST_KEY_MAP_3     3 
              292  LOAD_CODE                <code_object open_binary>
              294  LOAD_STR                 'open_binary'
              296  MAKE_FUNCTION_4          'annotation'
              298  STORE_NAME               open_binary

 L. 115       300  LOAD_CONST               ('utf-8', 'strict')
              302  LOAD_NAME                Package

 L. 116       304  LOAD_NAME                Resource

 L. 117       306  LOAD_NAME                str

 L. 118       308  LOAD_NAME                str
              310  LOAD_NAME                TextIO

 L. 115       312  LOAD_CONST               ('package', 'resource', 'encoding', 'errors', 'return')
              314  BUILD_CONST_KEY_MAP_5     5 
              316  LOAD_CODE                <code_object open_text>
              318  LOAD_STR                 'open_text'
              320  MAKE_FUNCTION_5          'default, annotation'
              322  STORE_NAME               open_text

 L. 124       324  LOAD_NAME                Package
              326  LOAD_NAME                Resource
              328  LOAD_NAME                bytes
              330  LOAD_CONST               ('package', 'resource', 'return')
              332  BUILD_CONST_KEY_MAP_3     3 
              334  LOAD_CODE                <code_object read_binary>
              336  LOAD_STR                 'read_binary'
              338  MAKE_FUNCTION_4          'annotation'
              340  STORE_NAME               read_binary

 L. 130       342  LOAD_CONST               ('utf-8', 'strict')
              344  LOAD_NAME                Package

 L. 131       346  LOAD_NAME                Resource

 L. 132       348  LOAD_NAME                str

 L. 133       350  LOAD_NAME                str
              352  LOAD_NAME                str

 L. 130       354  LOAD_CONST               ('package', 'resource', 'encoding', 'errors', 'return')
              356  BUILD_CONST_KEY_MAP_5     5 
              358  LOAD_CODE                <code_object read_text>
              360  LOAD_STR                 'read_text'
              362  MAKE_FUNCTION_5          'default, annotation'
              364  STORE_NAME               read_text

 L. 143       366  LOAD_NAME                Package
              368  LOAD_NAME                resources_abc
              370  LOAD_ATTR                Traversable
              372  LOAD_CONST               ('package', 'return')
              374  BUILD_CONST_KEY_MAP_2     2 
              376  LOAD_CODE                <code_object files>
              378  LOAD_STR                 'files'
              380  MAKE_FUNCTION_4          'annotation'
              382  STORE_NAME               files

 L. 151       384  LOAD_NAME                Package
              386  LOAD_NAME                Resource

 L. 152       388  LOAD_STR                 'ContextManager[Path]'

 L. 150       390  LOAD_CONST               ('package', 'resource', 'return')
              392  BUILD_CONST_KEY_MAP_3     3 
              394  LOAD_CODE                <code_object path>
              396  LOAD_STR                 'path'
              398  MAKE_FUNCTION_4          'annotation'
              400  STORE_NAME               path

 L. 169       402  LOAD_NAME                contextmanager

 L. 170       404  LOAD_CODE                <code_object _path_from_reader>
              406  LOAD_STR                 '_path_from_reader'
              408  MAKE_FUNCTION_0          'Neither defaults, keyword-only args, annotations, nor closures'
              410  CALL_FUNCTION_1       1  ''
              412  STORE_NAME               _path_from_reader

 L. 180       414  LOAD_NAME                Package
              416  LOAD_NAME                str
              418  LOAD_NAME                bool
              420  LOAD_CONST               ('package', 'name', 'return')
              422  BUILD_CONST_KEY_MAP_3     3 
              424  LOAD_CODE                <code_object is_resource>
              426  LOAD_STR                 'is_resource'
              428  MAKE_FUNCTION_4          'annotation'
              430  STORE_NAME               is_resource

 L. 196       432  LOAD_NAME                Package
              434  LOAD_NAME                Iterable
              436  LOAD_NAME                str
              438  BINARY_SUBSCR    
              440  LOAD_CONST               ('package', 'return')
              442  BUILD_CONST_KEY_MAP_2     2 
              444  LOAD_CODE                <code_object contents>
              446  LOAD_STR                 'contents'
              448  MAKE_FUNCTION_4          'annotation'
              450  STORE_NAME               contents

Parse error at or near `CALL_FINALLY' instruction at offset 180

Instruction context:
   
 L.  17       176  BUILD_LIST_0          0 
                 178  LOAD_CONST               ('Package', 'Resource', 'as_file', 'contents', 'files', 'is_resource', 'open_binary', 'open_text', 'path', 'read_binary', 'read_text')
->               180  CALL_FINALLY        183  'to 183'
                 182  STORE_NAME               __all__

test/101716.pyc -- 
# decompile failed
