
# file test/101824.pyc
# --- This code section failed: ---

 L.   1         0  LOAD_CONST               0
                2  LOAD_CONST               ('absolute_import',)
                4  IMPORT_NAME              __future__
                6  IMPORT_FROM              absolute_import
                8  STORE_NAME               absolute_import
               10  POP_TOP          

 L.   3        12  LOAD_CONST               0
               14  LOAD_CONST               None
               16  IMPORT_NAME              collections
               18  STORE_NAME               collections

 L.   4        20  LOAD_CONST               0
               22  LOAD_CONST               None
               24  IMPORT_NAME              functools
               26  STORE_NAME               functools

 L.   5        28  LOAD_CONST               0
               30  LOAD_CONST               None
               32  IMPORT_NAME              logging
               34  STORE_NAME               logging

 L.   7        36  LOAD_CONST               1
               38  LOAD_CONST               ('RecentlyUsedContainer',)
               40  IMPORT_NAME              _collections
               42  IMPORT_FROM              RecentlyUsedContainer
               44  STORE_NAME               RecentlyUsedContainer
               46  POP_TOP          

 L.   8        48  LOAD_CONST               1
               50  LOAD_CONST               ('HTTPConnectionPool', 'HTTPSConnectionPool', 'port_by_scheme')
               52  IMPORT_NAME              connectionpool
               54  IMPORT_FROM              HTTPConnectionPool
               56  STORE_NAME               HTTPConnectionPool
               58  IMPORT_FROM              HTTPSConnectionPool
               60  STORE_NAME               HTTPSConnectionPool
               62  IMPORT_FROM              port_by_scheme
               64  STORE_NAME               port_by_scheme
               66  POP_TOP          

 L.   9        68  LOAD_CONST               1
               70  LOAD_CONST               ('LocationValueError', 'MaxRetryError', 'ProxySchemeUnknown', 'ProxySchemeUnsupported', 'URLSchemeUnknown')
               72  IMPORT_NAME              exceptions
               74  IMPORT_FROM              LocationValueError
               76  STORE_NAME               LocationValueError
               78  IMPORT_FROM              MaxRetryError
               80  STORE_NAME               MaxRetryError
               82  IMPORT_FROM              ProxySchemeUnknown
               84  STORE_NAME               ProxySchemeUnknown
               86  IMPORT_FROM              ProxySchemeUnsupported
               88  STORE_NAME               ProxySchemeUnsupported
               90  IMPORT_FROM              URLSchemeUnknown
               92  STORE_NAME               URLSchemeUnknown
               94  POP_TOP          

 L.  16        96  LOAD_CONST               1
               98  LOAD_CONST               ('six',)
              100  IMPORT_NAME              packages
              102  IMPORT_FROM              six
              104  STORE_NAME               six
              106  POP_TOP          

 L.  17       108  LOAD_CONST               1
              110  LOAD_CONST               ('urljoin',)
              112  IMPORT_NAME_ATTR         packages.six.moves.urllib.parse
              114  IMPORT_FROM              urljoin
              116  STORE_NAME               urljoin
              118  POP_TOP          

 L.  18       120  LOAD_CONST               1
              122  LOAD_CONST               ('RequestMethods',)
              124  IMPORT_NAME              request
              126  IMPORT_FROM              RequestMethods
              128  STORE_NAME               RequestMethods
              130  POP_TOP          

 L.  19       132  LOAD_CONST               1
              134  LOAD_CONST               ('connection_requires_http_tunnel',)
              136  IMPORT_NAME_ATTR         util.proxy
              138  IMPORT_FROM              connection_requires_http_tunnel
              140  STORE_NAME               connection_requires_http_tunnel
              142  POP_TOP          

 L.  20       144  LOAD_CONST               1
              146  LOAD_CONST               ('Retry',)
              148  IMPORT_NAME_ATTR         util.retry
              150  IMPORT_FROM              Retry
              152  STORE_NAME               Retry
              154  POP_TOP          

 L.  21       156  LOAD_CONST               1
              158  LOAD_CONST               ('parse_url',)
              160  IMPORT_NAME_ATTR         util.url
              162  IMPORT_FROM              parse_url
              164  STORE_NAME               parse_url
              166  POP_TOP          

 L.  23       168  BUILD_LIST_0          0 
              170  LOAD_CONST               ('PoolManager', 'ProxyManager', 'proxy_from_url')
              172  CALL_FINALLY        175  'to 175'
              174  STORE_NAME               __all__

 L.  26       176  LOAD_NAME                logging
              178  LOAD_METHOD              getLogger
              180  LOAD_NAME                __name__
              182  CALL_METHOD_1         1  ''
              184  STORE_NAME               log

 L.  28       186  LOAD_CONST               ('key_file', 'cert_file', 'cert_reqs', 'ca_certs', 'ssl_version', 'ca_cert_dir', 'ssl_context', 'key_password')
              188  STORE_NAME               SSL_KEYWORDS

 L.  41       190  LOAD_CONST               ('key_scheme', 'key_host', 'key_port', 'key_timeout', 'key_retries', 'key_strict', 'key_block', 'key_source_address', 'key_key_file', 'key_key_password', 'key_cert_file', 'key_cert_reqs', 'key_ca_certs', 'key_ssl_version', 'key_ca_cert_dir', 'key_ssl_context', 'key_maxsize', 'key_headers', 'key__proxy', 'key__proxy_headers', 'key__proxy_config', 'key_socket_options', 'key__socks_options', 'key_assert_hostname', 'key_assert_fingerprint', 'key_server_hostname')
              192  STORE_NAME               _key_fields

 L.  72       194  LOAD_NAME                collections
              196  LOAD_METHOD              namedtuple
              198  LOAD_STR                 'PoolKey'
              200  LOAD_NAME                _key_fields
              202  CALL_METHOD_2         2  ''
              204  STORE_NAME               PoolKey

 L.  74       206  LOAD_CONST               ('ssl_context', 'use_forwarding_for_https')
              208  STORE_NAME               _proxy_config_fields

 L.  75       210  LOAD_NAME                collections
              212  LOAD_METHOD              namedtuple
              214  LOAD_STR                 'ProxyConfig'
              216  LOAD_NAME                _proxy_config_fields
              218  CALL_METHOD_2         2  ''
              220  STORE_NAME               ProxyConfig

 L.  78       222  LOAD_CODE                <code_object _default_key_normalizer>
              224  LOAD_STR                 '_default_key_normalizer'
              226  MAKE_FUNCTION_0          'Neither defaults, keyword-only args, annotations, nor closures'
              228  STORE_NAME               _default_key_normalizer

 L. 132       230  LOAD_NAME                functools
              232  LOAD_METHOD              partial
              234  LOAD_NAME                _default_key_normalizer
              236  LOAD_NAME                PoolKey
              238  CALL_METHOD_2         2  ''

 L. 133       240  LOAD_NAME                functools
              242  LOAD_METHOD              partial
              244  LOAD_NAME                _default_key_normalizer
              246  LOAD_NAME                PoolKey
              248  CALL_METHOD_2         2  ''

 L. 131       250  LOAD_CONST               ('http', 'https')
              252  BUILD_CONST_KEY_MAP_2     2 
              254  STORE_NAME               key_fn_by_scheme

 L. 136       256  LOAD_NAME                HTTPConnectionPool
              258  LOAD_NAME                HTTPSConnectionPool
              260  LOAD_CONST               ('http', 'https')
              262  BUILD_CONST_KEY_MAP_2     2 
              264  STORE_NAME               pool_classes_by_scheme

 L. 139       266  LOAD_BUILD_CLASS 
              268  LOAD_CODE                <code_object PoolManager>
              270  LOAD_STR                 'PoolManager'
              272  MAKE_FUNCTION_0          'Neither defaults, keyword-only args, annotations, nor closures'
              274  LOAD_STR                 'PoolManager'
              276  LOAD_NAME                RequestMethods
              278  CALL_FUNCTION_3       3  ''
              280  STORE_NAME               PoolManager

 L. 420       282  LOAD_BUILD_CLASS 
              284  LOAD_CODE                <code_object ProxyManager>
              286  LOAD_STR                 'ProxyManager'
              288  MAKE_FUNCTION_0          'Neither defaults, keyword-only args, annotations, nor closures'
              290  LOAD_STR                 'ProxyManager'
              292  LOAD_NAME                PoolManager
              294  CALL_FUNCTION_3       3  ''
              296  STORE_NAME               ProxyManager

 L. 535       298  LOAD_CODE                <code_object proxy_from_url>
              300  LOAD_STR                 'proxy_from_url'
              302  MAKE_FUNCTION_0          'Neither defaults, keyword-only args, annotations, nor closures'
              304  STORE_NAME               proxy_from_url

Parse error at or near `CALL_FINALLY' instruction at offset 172

Instruction context:
   
 L.  23       168  BUILD_LIST_0          0 
                 170  LOAD_CONST               ('PoolManager', 'ProxyManager', 'proxy_from_url')
->               172  CALL_FINALLY        175  'to 175'
                 174  STORE_NAME               __all__

test/101824.pyc -- 
# decompile failed
