Instruction context:
   
 L.   9        32  BUILD_LIST_0          0 
                  34  LOAD_CONST               ('DOMBuilder', 'DOMEntityResolver', 'DOMInputSource')
->                36  CALL_FINALLY         39  'to 39'
                  38  STORE_NAME               __all__

test/101859.pyc -- 
# decompile failed

# file test/101859.pyc
# --- This code section failed: ---

 L.   1         0  LOAD_STR                 "Implementation of the DOM Level 3 'LS-Load' feature."
                2  STORE_NAME               __doc__

 L.   3         4  LOAD_CONST               0
                6  LOAD_CONST               None
                8  IMPORT_NAME              copy
               10  STORE_NAME               copy

 L.   4        12  LOAD_CONST               0
               14  LOAD_CONST               None
               16  IMPORT_NAME_ATTR         xml.dom
               18  STORE_NAME               xml

 L.   6        20  LOAD_CONST               0
               22  LOAD_CONST               ('NodeFilter',)
               24  IMPORT_NAME_ATTR         xml.dom.NodeFilter
               26  IMPORT_FROM              NodeFilter
               28  STORE_NAME               NodeFilter
               30  POP_TOP          

 L.   9        32  BUILD_LIST_0          0 
               34  LOAD_CONST               ('DOMBuilder', 'DOMEntityResolver', 'DOMInputSource')
               36  CALL_FINALLY         39  'to 39'
               38  STORE_NAME               __all__

 L.  12        40  LOAD_BUILD_CLASS 
               42  LOAD_CODE                <code_object Options>
               44  LOAD_STR                 'Options'
               46  MAKE_FUNCTION_0          'Neither defaults, keyword-only args, annotations, nor closures'
               48  LOAD_STR                 'Options'
               50  CALL_FUNCTION_2       2  ''
               52  STORE_NAME               Options

 L.  44        54  LOAD_BUILD_CLASS 
               56  LOAD_CODE                <code_object DOMBuilder>
               58  LOAD_STR                 'DOMBuilder'
               60  MAKE_FUNCTION_0          'Neither defaults, keyword-only args, annotations, nor closures'
               62  LOAD_STR                 'DOMBuilder'
               64  CALL_FUNCTION_2       2  ''
               66  STORE_NAME               DOMBuilder

 L. 208        68  LOAD_CODE                <code_object _name_xform>
               70  LOAD_STR                 '_name_xform'
               72  MAKE_FUNCTION_0          'Neither defaults, keyword-only args, annotations, nor closures'
               74  STORE_NAME               _name_xform

 L. 212        76  LOAD_BUILD_CLASS 
               78  LOAD_CODE                <code_object DOMEntityResolver>
               80  LOAD_STR                 'DOMEntityResolver'
               82  MAKE_FUNCTION_0          'Neither defaults, keyword-only args, annotations, nor closures'
               84  LOAD_STR                 'DOMEntityResolver'
               86  LOAD_NAME                object
               88  CALL_FUNCTION_3       3  ''
               90  STORE_NAME               DOMEntityResolver

 L. 256        92  LOAD_BUILD_CLASS 
               94  LOAD_CODE                <code_object DOMInputSource>
               96  LOAD_STR                 'DOMInputSource'
               98  MAKE_FUNCTION_0          'Neither defaults, keyword-only args, annotations, nor closures'
              100  LOAD_STR                 'DOMInputSource'
              102  LOAD_NAME                object
              104  CALL_FUNCTION_3       3  ''
              106  STORE_NAME               DOMInputSource

 L. 305       108  LOAD_BUILD_CLASS 
              110  LOAD_CODE                <code_object DOMBuilderFilter>
              112  LOAD_STR                 'DOMBuilderFilter'
              114  MAKE_FUNCTION_0          'Neither defaults, keyword-only args, annotations, nor closures'
              116  LOAD_STR                 'DOMBuilderFilter'
              118  CALL_FUNCTION_2       2  ''
              120  STORE_NAME               DOMBuilderFilter

 L. 331       122  DELETE_NAME              NodeFilter

 L. 334       124  LOAD_BUILD_CLASS 
              126  LOAD_CODE                <code_object DocumentLS>
              128  LOAD_STR                 'DocumentLS'
              130  MAKE_FUNCTION_0          'Neither defaults, keyword-only args, annotations, nor closures'
              132  LOAD_STR                 'DocumentLS'
              134  CALL_FUNCTION_2       2  ''
              136  STORE_NAME               DocumentLS

 L. 367       138  LOAD_BUILD_CLASS 
              140  LOAD_CODE                <code_object DOMImplementationLS>
              142  LOAD_STR                 'DOMImplementationLS'
              144  MAKE_FUNCTION_0          'Neither defaults, keyword-only args, annotations, nor closures'
              146  LOAD_STR                 'DOMImplementationLS'
              148  CALL_FUNCTION_2       2  ''
              150  STORE_NAME               DOMImplementationLS

Parse error at or near `CALL_FINALLY' instruction at offset 36

