Instruction context:
   
 L.  18        56  BUILD_LIST_0          0 
                  58  LOAD_CONST               ('Cipher', 'CipherAlgorithm', 'BlockCipherAlgorithm', 'CipherContext', 'AEADCipherContext', 'AEADDecryptionContext', 'AEADEncryptionContext')
->                60  CALL_FINALLY         63  'to 63'

test/103878.pyc -- 
# decompile failed

# file test/103878.pyc
# --- This code section failed: ---

 L.   5         0  LOAD_CONST               0
                2  LOAD_CONST               ('absolute_import', 'division', 'print_function')
                4  IMPORT_NAME              __future__
                6  IMPORT_FROM              absolute_import
                8  STORE_NAME               absolute_import
               10  IMPORT_FROM              division
               12  STORE_NAME               division
               14  IMPORT_FROM              print_function
               16  STORE_NAME               print_function
               18  POP_TOP          

 L.   7        20  LOAD_CONST               0
               22  LOAD_CONST               ('AEADCipherContext', 'AEADDecryptionContext', 'AEADEncryptionContext', 'BlockCipherAlgorithm', 'Cipher', 'CipherAlgorithm', 'CipherContext')
               24  IMPORT_NAME_ATTR         cryptography.hazmat.primitives.ciphers.base
               26  IMPORT_FROM              AEADCipherContext
               28  STORE_NAME               AEADCipherContext
               30  IMPORT_FROM              AEADDecryptionContext
               32  STORE_NAME               AEADDecryptionContext
               34  IMPORT_FROM              AEADEncryptionContext
               36  STORE_NAME               AEADEncryptionContext
               38  IMPORT_FROM              BlockCipherAlgorithm
               40  STORE_NAME               BlockCipherAlgorithm
               42  IMPORT_FROM              Cipher
               44  STORE_NAME               Cipher
               46  IMPORT_FROM              CipherAlgorithm
               48  STORE_NAME               CipherAlgorithm
               50  IMPORT_FROM              CipherContext
               52  STORE_NAME               CipherContext
               54  POP_TOP          

 L.  18        56  BUILD_LIST_0          0 
               58  LOAD_CONST               ('Cipher', 'CipherAlgorithm', 'BlockCipherAlgorithm', 'CipherContext', 'AEADCipherContext', 'AEADDecryptionContext', 'AEADEncryptionContext')
               60  CALL_FINALLY         63  'to 63'
               62  STORE_NAME               __all__

Parse error at or near `CALL_FINALLY' instruction at offset 60

