
# file test/103892.pyc
# --- This code section failed: ---

 L.   5         0  LOAD_CONST               0
                2  LOAD_CONST               ('absolute_import', 'division', 'print_function')
                4  IMPORT_NAME              __future__
                6  IMPORT_FROM              absolute_import
                8  STORE_NAME               absolute_import
               10  IMPORT_FROM              division
               12  STORE_NAME               division
               14  IMPORT_FROM              print_function
               16  STORE_NAME               print_function
               18  POP_TOP          

 L.   7        20  LOAD_CONST               0
               22  LOAD_CONST               ('certificate_transparency',)
               24  IMPORT_NAME_ATTR         cryptography.x509
               26  IMPORT_FROM              certificate_transparency
               28  STORE_NAME               certificate_transparency
               30  POP_TOP          

 L.   8        32  LOAD_CONST               0
               34  LOAD_CONST               ('AttributeNotFound', 'Certificate', 'CertificateBuilder', 'CertificateRevocationList', 'CertificateRevocationListBuilder', 'CertificateSigningRequest', 'CertificateSigningRequestBuilder', 'InvalidVersion', 'RevokedCertificate', 'RevokedCertificateBuilder', 'Version', 'load_der_x509_certificate', 'load_der_x509_crl', 'load_der_x509_csr', 'load_pem_x509_certificate', 'load_pem_x509_crl', 'load_pem_x509_csr', 'random_serial_number')
               36  IMPORT_NAME_ATTR         cryptography.x509.base
               38  IMPORT_FROM              AttributeNotFound
               40  STORE_NAME               AttributeNotFound
               42  IMPORT_FROM              Certificate
               44  STORE_NAME               Certificate
               46  IMPORT_FROM              CertificateBuilder
               48  STORE_NAME               CertificateBuilder
               50  IMPORT_FROM              CertificateRevocationList
               52  STORE_NAME               CertificateRevocationList
               54  IMPORT_FROM              CertificateRevocationListBuilder
               56  STORE_NAME               CertificateRevocationListBuilder
               58  IMPORT_FROM              CertificateSigningRequest
               60  STORE_NAME               CertificateSigningRequest
               62  IMPORT_FROM              CertificateSigningRequestBuilder
               64  STORE_NAME               CertificateSigningRequestBuilder
               66  IMPORT_FROM              InvalidVersion
               68  STORE_NAME               InvalidVersion
               70  IMPORT_FROM              RevokedCertificate
               72  STORE_NAME               RevokedCertificate
               74  IMPORT_FROM              RevokedCertificateBuilder
               76  STORE_NAME               RevokedCertificateBuilder
               78  IMPORT_FROM              Version
               80  STORE_NAME               Version
               82  IMPORT_FROM              load_der_x509_certificate
               84  STORE_NAME               load_der_x509_certificate
               86  IMPORT_FROM              load_der_x509_crl
               88  STORE_NAME               load_der_x509_crl
               90  IMPORT_FROM              load_der_x509_csr
               92  STORE_NAME               load_der_x509_csr
               94  IMPORT_FROM              load_pem_x509_certificate
               96  STORE_NAME               load_pem_x509_certificate
               98  IMPORT_FROM              load_pem_x509_crl
              100  STORE_NAME               load_pem_x509_crl
              102  IMPORT_FROM              load_pem_x509_csr
              104  STORE_NAME               load_pem_x509_csr
              106  IMPORT_FROM              random_serial_number
              108  STORE_NAME               random_serial_number
              110  POP_TOP          

 L.  28       112  LOAD_CONST               0
              114  LOAD_CONST               ('AccessDescription', 'AuthorityInformationAccess', 'AuthorityKeyIdentifier', 'BasicConstraints', 'CRLDistributionPoints', 'CRLNumber', 'CRLReason', 'CertificateIssuer', 'CertificatePolicies', 'DeltaCRLIndicator', 'DistributionPoint', 'DuplicateExtension', 'ExtendedKeyUsage', 'Extension', 'ExtensionNotFound', 'ExtensionType', 'Extensions', 'FreshestCRL', 'GeneralNames', 'InhibitAnyPolicy', 'InvalidityDate', 'IssuerAlternativeName', 'IssuingDistributionPoint', 'KeyUsage', 'NameConstraints', 'NoticeReference', 'OCSPNoCheck', 'OCSPNonce', 'PolicyConstraints', 'PolicyInformation', 'PrecertPoison', 'PrecertificateSignedCertificateTimestamps', 'ReasonFlags', 'SignedCertificateTimestamps', 'SubjectAlternativeName', 'SubjectInformationAccess', 'SubjectKeyIdentifier', 'TLSFeature', 'TLSFeatureType', 'UnrecognizedExtension', 'UserNotice')
              116  IMPORT_NAME_ATTR         cryptography.x509.extensions
              118  IMPORT_FROM              AccessDescription
              120  STORE_NAME               AccessDescription
              122  IMPORT_FROM              AuthorityInformationAccess
              124  STORE_NAME               AuthorityInformationAccess
              126  IMPORT_FROM              AuthorityKeyIdentifier
              128  STORE_NAME               AuthorityKeyIdentifier
              130  IMPORT_FROM              BasicConstraints
              132  STORE_NAME               BasicConstraints
              134  IMPORT_FROM              CRLDistributionPoints
              136  STORE_NAME               CRLDistributionPoints
              138  IMPORT_FROM              CRLNumber
              140  STORE_NAME               CRLNumber
              142  IMPORT_FROM              CRLReason
              144  STORE_NAME               CRLReason
              146  IMPORT_FROM              CertificateIssuer
              148  STORE_NAME               CertificateIssuer
              150  IMPORT_FROM              CertificatePolicies
              152  STORE_NAME               CertificatePolicies
              154  IMPORT_FROM              DeltaCRLIndicator
              156  STORE_NAME               DeltaCRLIndicator
              158  IMPORT_FROM              DistributionPoint
              160  STORE_NAME               DistributionPoint
              162  IMPORT_FROM              DuplicateExtension
              164  STORE_NAME               DuplicateExtension
              166  IMPORT_FROM              ExtendedKeyUsage
              168  STORE_NAME               ExtendedKeyUsage
              170  IMPORT_FROM              Extension
              172  STORE_NAME               Extension
              174  IMPORT_FROM              ExtensionNotFound
              176  STORE_NAME               ExtensionNotFound
              178  IMPORT_FROM              ExtensionType
              180  STORE_NAME               ExtensionType
              182  IMPORT_FROM              Extensions
              184  STORE_NAME               Extensions
              186  IMPORT_FROM              FreshestCRL
              188  STORE_NAME               FreshestCRL
              190  IMPORT_FROM              GeneralNames
              192  STORE_NAME               GeneralNames
              194  IMPORT_FROM              InhibitAnyPolicy
              196  STORE_NAME               InhibitAnyPolicy
              198  IMPORT_FROM              InvalidityDate
              200  STORE_NAME               InvalidityDate
              202  IMPORT_FROM              IssuerAlternativeName
              204  STORE_NAME               IssuerAlternativeName
              206  IMPORT_FROM              IssuingDistributionPoint
              208  STORE_NAME               IssuingDistributionPoint
              210  IMPORT_FROM              KeyUsage
              212  STORE_NAME               KeyUsage
              214  IMPORT_FROM              NameConstraints
              216  STORE_NAME               NameConstraints
              218  IMPORT_FROM              NoticeReference
              220  STORE_NAME               NoticeReference
              222  IMPORT_FROM              OCSPNoCheck
              224  STORE_NAME               OCSPNoCheck
              226  IMPORT_FROM              OCSPNonce
              228  STORE_NAME               OCSPNonce
              230  IMPORT_FROM              PolicyConstraints
              232  STORE_NAME               PolicyConstraints
              234  IMPORT_FROM              PolicyInformation
              236  STORE_NAME               PolicyInformation
              238  IMPORT_FROM              PrecertPoison
              240  STORE_NAME               PrecertPoison
              242  IMPORT_FROM              PrecertificateSignedCertificateTimestamps
              244  STORE_NAME               PrecertificateSignedCertificateTimestamps
              246  IMPORT_FROM              ReasonFlags
              248  STORE_NAME               ReasonFlags
              250  IMPORT_FROM              SignedCertificateTimestamps
              252  STORE_NAME               SignedCertificateTimestamps
              254  IMPORT_FROM              SubjectAlternativeName
              256  STORE_NAME               SubjectAlternativeName
              258  IMPORT_FROM              SubjectInformationAccess
              260  STORE_NAME               SubjectInformationAccess
              262  IMPORT_FROM              SubjectKeyIdentifier
              264  STORE_NAME               SubjectKeyIdentifier
              266  IMPORT_FROM              TLSFeature
              268  STORE_NAME               TLSFeature
              270  IMPORT_FROM              TLSFeatureType
              272  STORE_NAME               TLSFeatureType
              274  IMPORT_FROM              UnrecognizedExtension
              276  STORE_NAME               UnrecognizedExtension
              278  IMPORT_FROM              UserNotice
              280  STORE_NAME               UserNotice
              282  POP_TOP          

 L.  71       284  LOAD_CONST               0
              286  LOAD_CONST               ('DNSName', 'DirectoryName', 'GeneralName', 'IPAddress', 'OtherName', 'RFC822Name', 'RegisteredID', 'UniformResourceIdentifier', 'UnsupportedGeneralNameType', '_GENERAL_NAMES')
              288  IMPORT_NAME_ATTR         cryptography.x509.general_name
              290  IMPORT_FROM              DNSName
              292  STORE_NAME               DNSName
              294  IMPORT_FROM              DirectoryName
              296  STORE_NAME               DirectoryName
              298  IMPORT_FROM              GeneralName
              300  STORE_NAME               GeneralName
              302  IMPORT_FROM              IPAddress
              304  STORE_NAME               IPAddress
              306  IMPORT_FROM              OtherName
              308  STORE_NAME               OtherName
              310  IMPORT_FROM              RFC822Name
              312  STORE_NAME               RFC822Name
              314  IMPORT_FROM              RegisteredID
              316  STORE_NAME               RegisteredID
              318  IMPORT_FROM              UniformResourceIdentifier
              320  STORE_NAME               UniformResourceIdentifier
              322  IMPORT_FROM              UnsupportedGeneralNameType
              324  STORE_NAME               UnsupportedGeneralNameType
              326  IMPORT_FROM              _GENERAL_NAMES
              328  STORE_NAME               _GENERAL_NAMES
              330  POP_TOP          

 L.  83       332  LOAD_CONST               0
              334  LOAD_CONST               ('Name', 'NameAttribute', 'RelativeDistinguishedName')
              336  IMPORT_NAME_ATTR         cryptography.x509.name
              338  IMPORT_FROM              Name
              340  STORE_NAME               Name
              342  IMPORT_FROM              NameAttribute
              344  STORE_NAME               NameAttribute
              346  IMPORT_FROM              RelativeDistinguishedName
              348  STORE_NAME               RelativeDistinguishedName
              350  POP_TOP          

 L.  88       352  LOAD_CONST               0
              354  LOAD_CONST               ('AuthorityInformationAccessOID', 'CRLEntryExtensionOID', 'CertificatePoliciesOID', 'ExtendedKeyUsageOID', 'ExtensionOID', 'NameOID', 'ObjectIdentifier', 'SignatureAlgorithmOID', '_SIG_OIDS_TO_HASH')
              356  IMPORT_NAME_ATTR         cryptography.x509.oid
              358  IMPORT_FROM              AuthorityInformationAccessOID
              360  STORE_NAME               AuthorityInformationAccessOID
              362  IMPORT_FROM              CRLEntryExtensionOID
              364  STORE_NAME               CRLEntryExtensionOID
              366  IMPORT_FROM              CertificatePoliciesOID
              368  STORE_NAME               CertificatePoliciesOID
              370  IMPORT_FROM              ExtendedKeyUsageOID
              372  STORE_NAME               ExtendedKeyUsageOID
              374  IMPORT_FROM              ExtensionOID
              376  STORE_NAME               ExtensionOID
              378  IMPORT_FROM              NameOID
              380  STORE_NAME               NameOID
              382  IMPORT_FROM              ObjectIdentifier
              384  STORE_NAME               ObjectIdentifier
              386  IMPORT_FROM              SignatureAlgorithmOID
              388  STORE_NAME               SignatureAlgorithmOID
              390  IMPORT_FROM              _SIG_OIDS_TO_HASH
              392  STORE_NAME               _SIG_OIDS_TO_HASH
              394  POP_TOP          

 L. 101       396  LOAD_NAME                ExtensionOID
              398  LOAD_ATTR                AUTHORITY_INFORMATION_ACCESS
              400  STORE_NAME               OID_AUTHORITY_INFORMATION_ACCESS

 L. 102       402  LOAD_NAME                ExtensionOID
              404  LOAD_ATTR                AUTHORITY_KEY_IDENTIFIER
              406  STORE_NAME               OID_AUTHORITY_KEY_IDENTIFIER

 L. 103       408  LOAD_NAME                ExtensionOID
              410  LOAD_ATTR                BASIC_CONSTRAINTS
              412  STORE_NAME               OID_BASIC_CONSTRAINTS

 L. 104       414  LOAD_NAME                ExtensionOID
              416  LOAD_ATTR                CERTIFICATE_POLICIES
              418  STORE_NAME               OID_CERTIFICATE_POLICIES

 L. 105       420  LOAD_NAME                ExtensionOID
              422  LOAD_ATTR                CRL_DISTRIBUTION_POINTS
              424  STORE_NAME               OID_CRL_DISTRIBUTION_POINTS

 L. 106       426  LOAD_NAME                ExtensionOID
              428  LOAD_ATTR                EXTENDED_KEY_USAGE
              430  STORE_NAME               OID_EXTENDED_KEY_USAGE

 L. 107       432  LOAD_NAME                ExtensionOID
              434  LOAD_ATTR                FRESHEST_CRL
              436  STORE_NAME               OID_FRESHEST_CRL

 L. 108       438  LOAD_NAME                ExtensionOID
              440  LOAD_ATTR                INHIBIT_ANY_POLICY
              442  STORE_NAME               OID_INHIBIT_ANY_POLICY

 L. 109       444  LOAD_NAME                ExtensionOID
              446  LOAD_ATTR                ISSUER_ALTERNATIVE_NAME
              448  STORE_NAME               OID_ISSUER_ALTERNATIVE_NAME

 L. 110       450  LOAD_NAME                ExtensionOID
              452  LOAD_ATTR                KEY_USAGE
              454  STORE_NAME               OID_KEY_USAGE

 L. 111       456  LOAD_NAME                ExtensionOID
              458  LOAD_ATTR                NAME_CONSTRAINTS
              460  STORE_NAME               OID_NAME_CONSTRAINTS

 L. 112       462  LOAD_NAME                ExtensionOID
              464  LOAD_ATTR                OCSP_NO_CHECK
              466  STORE_NAME               OID_OCSP_NO_CHECK

 L. 113       468  LOAD_NAME                ExtensionOID
              470  LOAD_ATTR                POLICY_CONSTRAINTS
              472  STORE_NAME               OID_POLICY_CONSTRAINTS

 L. 114       474  LOAD_NAME                ExtensionOID
              476  LOAD_ATTR                POLICY_MAPPINGS
              478  STORE_NAME               OID_POLICY_MAPPINGS

 L. 115       480  LOAD_NAME                ExtensionOID
              482  LOAD_ATTR                SUBJECT_ALTERNATIVE_NAME
              484  STORE_NAME               OID_SUBJECT_ALTERNATIVE_NAME

 L. 116       486  LOAD_NAME                ExtensionOID
              488  LOAD_ATTR                SUBJECT_DIRECTORY_ATTRIBUTES
              490  STORE_NAME               OID_SUBJECT_DIRECTORY_ATTRIBUTES

 L. 117       492  LOAD_NAME                ExtensionOID
              494  LOAD_ATTR                SUBJECT_INFORMATION_ACCESS
              496  STORE_NAME               OID_SUBJECT_INFORMATION_ACCESS

 L. 118       498  LOAD_NAME                ExtensionOID
              500  LOAD_ATTR                SUBJECT_KEY_IDENTIFIER
              502  STORE_NAME               OID_SUBJECT_KEY_IDENTIFIER

 L. 120       504  LOAD_NAME                SignatureAlgorithmOID
              506  LOAD_ATTR                DSA_WITH_SHA1
              508  STORE_NAME               OID_DSA_WITH_SHA1

 L. 121       510  LOAD_NAME                SignatureAlgorithmOID
              512  LOAD_ATTR                DSA_WITH_SHA224
              514  STORE_NAME               OID_DSA_WITH_SHA224

 L. 122       516  LOAD_NAME                SignatureAlgorithmOID
              518  LOAD_ATTR                DSA_WITH_SHA256
              520  STORE_NAME               OID_DSA_WITH_SHA256

 L. 123       522  LOAD_NAME                SignatureAlgorithmOID
              524  LOAD_ATTR                ECDSA_WITH_SHA1
              526  STORE_NAME               OID_ECDSA_WITH_SHA1

 L. 124       528  LOAD_NAME                SignatureAlgorithmOID
              530  LOAD_ATTR                ECDSA_WITH_SHA224
              532  STORE_NAME               OID_ECDSA_WITH_SHA224

 L. 125       534  LOAD_NAME                SignatureAlgorithmOID
              536  LOAD_ATTR                ECDSA_WITH_SHA256
              538  STORE_NAME               OID_ECDSA_WITH_SHA256

 L. 126       540  LOAD_NAME                SignatureAlgorithmOID
              542  LOAD_ATTR                ECDSA_WITH_SHA384
              544  STORE_NAME               OID_ECDSA_WITH_SHA384

 L. 127       546  LOAD_NAME                SignatureAlgorithmOID
              548  LOAD_ATTR                ECDSA_WITH_SHA512
              550  STORE_NAME               OID_ECDSA_WITH_SHA512

 L. 128       552  LOAD_NAME                SignatureAlgorithmOID
              554  LOAD_ATTR                RSA_WITH_MD5
              556  STORE_NAME               OID_RSA_WITH_MD5

 L. 129       558  LOAD_NAME                SignatureAlgorithmOID
              560  LOAD_ATTR                RSA_WITH_SHA1
              562  STORE_NAME               OID_RSA_WITH_SHA1

 L. 130       564  LOAD_NAME                SignatureAlgorithmOID
              566  LOAD_ATTR                RSA_WITH_SHA224
              568  STORE_NAME               OID_RSA_WITH_SHA224

 L. 131       570  LOAD_NAME                SignatureAlgorithmOID
              572  LOAD_ATTR                RSA_WITH_SHA256
              574  STORE_NAME               OID_RSA_WITH_SHA256

 L. 132       576  LOAD_NAME                SignatureAlgorithmOID
              578  LOAD_ATTR                RSA_WITH_SHA384
              580  STORE_NAME               OID_RSA_WITH_SHA384

 L. 133       582  LOAD_NAME                SignatureAlgorithmOID
              584  LOAD_ATTR                RSA_WITH_SHA512
              586  STORE_NAME               OID_RSA_WITH_SHA512

 L. 134       588  LOAD_NAME                SignatureAlgorithmOID
              590  LOAD_ATTR                RSASSA_PSS
              592  STORE_NAME               OID_RSASSA_PSS

 L. 136       594  LOAD_NAME                NameOID
              596  LOAD_ATTR                COMMON_NAME
              598  STORE_NAME               OID_COMMON_NAME

 L. 137       600  LOAD_NAME                NameOID
              602  LOAD_ATTR                COUNTRY_NAME
              604  STORE_NAME               OID_COUNTRY_NAME

 L. 138       606  LOAD_NAME                NameOID
              608  LOAD_ATTR                DOMAIN_COMPONENT
              610  STORE_NAME               OID_DOMAIN_COMPONENT

 L. 139       612  LOAD_NAME                NameOID
              614  LOAD_ATTR                DN_QUALIFIER
              616  STORE_NAME               OID_DN_QUALIFIER

 L. 140       618  LOAD_NAME                NameOID
              620  LOAD_ATTR                EMAIL_ADDRESS
              622  STORE_NAME               OID_EMAIL_ADDRESS

 L. 141       624  LOAD_NAME                NameOID
              626  LOAD_ATTR                GENERATION_QUALIFIER
              628  STORE_NAME               OID_GENERATION_QUALIFIER

 L. 142       630  LOAD_NAME                NameOID
              632  LOAD_ATTR                GIVEN_NAME
              634  STORE_NAME               OID_GIVEN_NAME

 L. 143       636  LOAD_NAME                NameOID
              638  LOAD_ATTR                LOCALITY_NAME
              640  STORE_NAME               OID_LOCALITY_NAME

 L. 144       642  LOAD_NAME                NameOID
              644  LOAD_ATTR                ORGANIZATIONAL_UNIT_NAME
              646  STORE_NAME               OID_ORGANIZATIONAL_UNIT_NAME

 L. 145       648  LOAD_NAME                NameOID
              650  LOAD_ATTR                ORGANIZATION_NAME
              652  STORE_NAME               OID_ORGANIZATION_NAME

 L. 146       654  LOAD_NAME                NameOID
              656  LOAD_ATTR                PSEUDONYM
              658  STORE_NAME               OID_PSEUDONYM

 L. 147       660  LOAD_NAME                NameOID
              662  LOAD_ATTR                SERIAL_NUMBER
              664  STORE_NAME               OID_SERIAL_NUMBER

 L. 148       666  LOAD_NAME                NameOID
              668  LOAD_ATTR                STATE_OR_PROVINCE_NAME
              670  STORE_NAME               OID_STATE_OR_PROVINCE_NAME

 L. 149       672  LOAD_NAME                NameOID
              674  LOAD_ATTR                SURNAME
              676  STORE_NAME               OID_SURNAME

 L. 150       678  LOAD_NAME                NameOID
              680  LOAD_ATTR                TITLE
              682  STORE_NAME               OID_TITLE

 L. 152       684  LOAD_NAME                ExtendedKeyUsageOID
              686  LOAD_ATTR                CLIENT_AUTH
              688  STORE_NAME               OID_CLIENT_AUTH

 L. 153       690  LOAD_NAME                ExtendedKeyUsageOID
              692  LOAD_ATTR                CODE_SIGNING
              694  STORE_NAME               OID_CODE_SIGNING

 L. 154       696  LOAD_NAME                ExtendedKeyUsageOID
              698  LOAD_ATTR                EMAIL_PROTECTION
              700  STORE_NAME               OID_EMAIL_PROTECTION

 L. 155       702  LOAD_NAME                ExtendedKeyUsageOID
              704  LOAD_ATTR                OCSP_SIGNING
              706  STORE_NAME               OID_OCSP_SIGNING

 L. 156       708  LOAD_NAME                ExtendedKeyUsageOID
              710  LOAD_ATTR                SERVER_AUTH
              712  STORE_NAME               OID_SERVER_AUTH

 L. 157       714  LOAD_NAME                ExtendedKeyUsageOID
              716  LOAD_ATTR                TIME_STAMPING
              718  STORE_NAME               OID_TIME_STAMPING

 L. 159       720  LOAD_NAME                CertificatePoliciesOID
              722  LOAD_ATTR                ANY_POLICY
              724  STORE_NAME               OID_ANY_POLICY

 L. 160       726  LOAD_NAME                CertificatePoliciesOID
              728  LOAD_ATTR                CPS_QUALIFIER
              730  STORE_NAME               OID_CPS_QUALIFIER

 L. 161       732  LOAD_NAME                CertificatePoliciesOID
              734  LOAD_ATTR                CPS_USER_NOTICE
              736  STORE_NAME               OID_CPS_USER_NOTICE

 L. 163       738  LOAD_NAME                CRLEntryExtensionOID
              740  LOAD_ATTR                CERTIFICATE_ISSUER
              742  STORE_NAME               OID_CERTIFICATE_ISSUER

 L. 164       744  LOAD_NAME                CRLEntryExtensionOID
              746  LOAD_ATTR                CRL_REASON
              748  STORE_NAME               OID_CRL_REASON

 L. 165       750  LOAD_NAME                CRLEntryExtensionOID
              752  LOAD_ATTR                INVALIDITY_DATE
              754  STORE_NAME               OID_INVALIDITY_DATE

 L. 167       756  LOAD_NAME                AuthorityInformationAccessOID
              758  LOAD_ATTR                CA_ISSUERS
              760  STORE_NAME               OID_CA_ISSUERS

 L. 168       762  LOAD_NAME                AuthorityInformationAccessOID
              764  LOAD_ATTR                OCSP
              766  STORE_NAME               OID_OCSP

 L. 170       768  BUILD_LIST_0          0 
              770  LOAD_CONST               ('certificate_transparency', 'load_pem_x509_certificate', 'load_der_x509_certificate', 'load_pem_x509_csr', 'load_der_x509_csr', 'load_pem_x509_crl', 'load_der_x509_crl', 'random_serial_number', 'AttributeNotFound', 'InvalidVersion', 'DeltaCRLIndicator', 'DuplicateExtension', 'ExtensionNotFound', 'UnsupportedGeneralNameType', 'NameAttribute', 'Name', 'RelativeDistinguishedName', 'ObjectIdentifier', 'ExtensionType', 'Extensions', 'Extension', 'ExtendedKeyUsage', 'FreshestCRL', 'IssuingDistributionPoint', 'TLSFeature', 'TLSFeatureType', 'OCSPNoCheck', 'BasicConstraints', 'CRLNumber', 'KeyUsage', 'AuthorityInformationAccess', 'SubjectInformationAccess', 'AccessDescription', 'CertificatePolicies', 'PolicyInformation', 'UserNotice', 'NoticeReference', 'SubjectKeyIdentifier', 'NameConstraints', 'CRLDistributionPoints', 'DistributionPoint', 'ReasonFlags', 'InhibitAnyPolicy', 'SubjectAlternativeName', 'IssuerAlternativeName', 'AuthorityKeyIdentifier', 'GeneralNames', 'GeneralName', 'RFC822Name', 'DNSName', 'UniformResourceIdentifier', 'RegisteredID', 'DirectoryName', 'IPAddress', 'OtherName', 'Certificate', 'CertificateRevocationList', 'CertificateRevocationListBuilder', 'CertificateSigningRequest', 'RevokedCertificate', 'RevokedCertificateBuilder', 'CertificateSigningRequestBuilder', 'CertificateBuilder', 'Version', '_SIG_OIDS_TO_HASH', 'OID_CA_ISSUERS', 'OID_OCSP', '_GENERAL_NAMES', 'CertificateIssuer', 'CRLReason', 'InvalidityDate', 'UnrecognizedExtension', 'PolicyConstraints', 'PrecertificateSignedCertificateTimestamps', 'PrecertPoison', 'OCSPNonce', 'SignedCertificateTimestamps')
              772  CALL_FINALLY        775  'to 775'
              774  STORE_NAME               __all__

Parse error at or near `CALL_FINALLY' instruction at offset 772

Instruction context:
   
 L. 170       768  BUILD_LIST_0          0 
                 770  LOAD_CONST               ('certificate_transparency', 'load_pem_x509_certificate', 'load_der_x509_certificate', 'load_pem_x509_csr', 'load_der_x509_csr', 'load_pem_x509_crl', 'load_der_x509_crl', 'random_serial_number', 'AttributeNotFound', 'InvalidVersion', 'DeltaCRLIndicator', 'DuplicateExtension', 'ExtensionNotFound', 'UnsupportedGeneralNameType', 'NameAttribute', 'Name', 'RelativeDistinguishedName', 'ObjectIdentifier', 'ExtensionType', 'Extensions', 'Extension', 'ExtendedKeyUsage', 'FreshestCRL', 'IssuingDistributionPoint', 'TLSFeature', 'TLSFeatureType', 'OCSPNoCheck', 'BasicConstraints', 'CRLNumber', 'KeyUsage', 'AuthorityInformationAccess', 'SubjectInformationAccess', 'AccessDescription', 'CertificatePolicies', 'PolicyInformation', 'UserNotice', 'NoticeReference', 'SubjectKeyIdentifier', 'NameConstraints', 'CRLDistributionPoints', 'DistributionPoint', 'ReasonFlags', 'InhibitAnyPolicy', 'SubjectAlternativeName', 'IssuerAlternativeName', 'AuthorityKeyIdentifier', 'GeneralNames', 'GeneralName', 'RFC822Name', 'DNSName', 'UniformResourceIdentifier', 'RegisteredID', 'DirectoryName', 'IPAddress', 'OtherName', 'Certificate', 'CertificateRevocationList', 'CertificateRevocationListBuilder', 'CertificateSigningRequest', 'RevokedCertificate', 'RevokedCertificateBuilder', 'CertificateSigningRequestBuilder', 'CertificateBuilder', 'Version', '_SIG_OIDS_TO_HASH', 'OID_CA_ISSUERS', 'OID_OCSP', '_GENERAL_NAMES', 'CertificateIssuer', 'CRLReason', 'InvalidityDate', 'UnrecognizedExtension', 'PolicyConstraints', 'PrecertificateSignedCertificateTimestamps', 'PrecertPoison', 'OCSPNonce', 'SignedCertificateTimestamps')
->               772  CALL_FINALLY        775  'to 775'

test/103892.pyc -- 
# decompile failed
