Instruction context:
   
 L.  28        96  BUILD_LIST_0          0 
                  98  LOAD_CONST               ('load_der_parameters', 'load_der_private_key', 'load_der_public_key', 'load_pem_parameters', 'load_pem_private_key', 'load_pem_public_key', 'load_ssh_private_key', 'load_ssh_public_key', 'Encoding', 'PrivateFormat', 'PublicFormat', 'ParameterFormat', 'KeySerializationEncryption', 'BestAvailableEncryption', 'NoEncryption')
->               100  CALL_FINALLY        103  'to 103'

test/103884.pyc -- 
# decompile failed

# file test/103884.pyc
# --- This code section failed: ---

 L.   5         0  LOAD_CONST               0
                2  LOAD_CONST               ('absolute_import', 'division', 'print_function')
                4  IMPORT_NAME              __future__
                6  IMPORT_FROM              absolute_import
                8  STORE_NAME               absolute_import
               10  IMPORT_FROM              division
               12  STORE_NAME               division
               14  IMPORT_FROM              print_function
               16  STORE_NAME               print_function
               18  POP_TOP          

 L.   7        20  LOAD_CONST               0
               22  LOAD_CONST               ('BestAvailableEncryption', 'Encoding', 'KeySerializationEncryption', 'NoEncryption', 'ParameterFormat', 'PrivateFormat', 'PublicFormat', 'load_der_parameters', 'load_der_private_key', 'load_der_public_key', 'load_pem_parameters', 'load_pem_private_key', 'load_pem_public_key')
               24  IMPORT_NAME_ATTR         cryptography.hazmat.primitives.serialization.base
               26  IMPORT_FROM              BestAvailableEncryption
               28  STORE_NAME               BestAvailableEncryption
               30  IMPORT_FROM              Encoding
               32  STORE_NAME               Encoding
               34  IMPORT_FROM              KeySerializationEncryption
               36  STORE_NAME               KeySerializationEncryption
               38  IMPORT_FROM              NoEncryption
               40  STORE_NAME               NoEncryption
               42  IMPORT_FROM              ParameterFormat
               44  STORE_NAME               ParameterFormat
               46  IMPORT_FROM              PrivateFormat
               48  STORE_NAME               PrivateFormat
               50  IMPORT_FROM              PublicFormat
               52  STORE_NAME               PublicFormat
               54  IMPORT_FROM              load_der_parameters
               56  STORE_NAME               load_der_parameters
               58  IMPORT_FROM              load_der_private_key
               60  STORE_NAME               load_der_private_key
               62  IMPORT_FROM              load_der_public_key
               64  STORE_NAME               load_der_public_key
               66  IMPORT_FROM              load_pem_parameters
               68  STORE_NAME               load_pem_parameters
               70  IMPORT_FROM              load_pem_private_key
               72  STORE_NAME               load_pem_private_key
               74  IMPORT_FROM              load_pem_public_key
               76  STORE_NAME               load_pem_public_key
               78  POP_TOP          

 L.  22        80  LOAD_CONST               0
               82  LOAD_CONST               ('load_ssh_private_key', 'load_ssh_public_key')
               84  IMPORT_NAME_ATTR         cryptography.hazmat.primitives.serialization.ssh
               86  IMPORT_FROM              load_ssh_private_key
               88  STORE_NAME               load_ssh_private_key
               90  IMPORT_FROM              load_ssh_public_key
               92  STORE_NAME               load_ssh_public_key
               94  POP_TOP          

 L.  28        96  BUILD_LIST_0          0 
               98  LOAD_CONST               ('load_der_parameters', 'load_der_private_key', 'load_der_public_key', 'load_pem_parameters', 'load_pem_private_key', 'load_pem_public_key', 'load_ssh_private_key', 'load_ssh_public_key', 'Encoding', 'PrivateFormat', 'PublicFormat', 'ParameterFormat', 'KeySerializationEncryption', 'BestAvailableEncryption', 'NoEncryption')
              100  CALL_FINALLY        103  'to 103'
              102  STORE_NAME               __all__

Parse error at or near `CALL_FINALLY' instruction at offset 100

