
# file test/103869.pyc
# --- This code section failed: ---

 L.   5         0  LOAD_CONST               0
                2  LOAD_CONST               ('absolute_import', 'division', 'print_function')
                4  IMPORT_NAME              __future__
                6  IMPORT_FROM              absolute_import
                8  STORE_NAME               absolute_import
               10  IMPORT_FROM              division
               12  STORE_NAME               division
               14  IMPORT_FROM              print_function
               16  STORE_NAME               print_function
               18  POP_TOP          

 L.   7        20  LOAD_CONST               0
               22  LOAD_CONST               None
               24  IMPORT_NAME              abc
               26  STORE_NAME               abc

 L.   9        28  SETUP_FINALLY        46  'to 46'

 L.  11        30  LOAD_CONST               0
               32  LOAD_CONST               ('gcd',)
               34  IMPORT_NAME              math
               36  IMPORT_FROM              gcd
               38  STORE_NAME               gcd
               40  POP_TOP          
               42  POP_BLOCK        
               44  JUMP_FORWARD         76  'to 76'
             46_0  COME_FROM_FINALLY    28  '28'

 L.  12        46  DUP_TOP          
               48  LOAD_NAME                ImportError
               50  <121>                74  ''
               52  POP_TOP          
               54  POP_TOP          
               56  POP_TOP          

 L.  13        58  LOAD_CONST               0
               60  LOAD_CONST               ('gcd',)
               62  IMPORT_NAME              fractions
               64  IMPORT_FROM              gcd
               66  STORE_NAME               gcd
               68  POP_TOP          
               70  POP_EXCEPT       
               72  JUMP_FORWARD         76  'to 76'
               74  <48>             
             76_0  COME_FROM            72  '72'
             76_1  COME_FROM            44  '44'

 L.  15        76  LOAD_CONST               0
               78  LOAD_CONST               None
               80  IMPORT_NAME              six
               82  STORE_NAME               six

 L.  17        84  LOAD_CONST               0
               86  LOAD_CONST               ('utils',)
               88  IMPORT_NAME              cryptography
               90  IMPORT_FROM              utils
               92  STORE_NAME               utils
               94  POP_TOP          

 L.  18        96  LOAD_CONST               0
               98  LOAD_CONST               ('UnsupportedAlgorithm', '_Reasons')
              100  IMPORT_NAME_ATTR         cryptography.exceptions
              102  IMPORT_FROM              UnsupportedAlgorithm
              104  STORE_NAME               UnsupportedAlgorithm
              106  IMPORT_FROM              _Reasons
              108  STORE_NAME               _Reasons
              110  POP_TOP          

 L.  19       112  LOAD_CONST               0
              114  LOAD_CONST               ('_get_backend',)
              116  IMPORT_NAME_ATTR         cryptography.hazmat.backends
              118  IMPORT_FROM              _get_backend
              120  STORE_NAME               _get_backend
              122  POP_TOP          

 L.  20       124  LOAD_CONST               0
              126  LOAD_CONST               ('RSABackend',)
              128  IMPORT_NAME_ATTR         cryptography.hazmat.backends.interfaces
              130  IMPORT_FROM              RSABackend
              132  STORE_NAME               RSABackend
              134  POP_TOP          

 L.  23       136  LOAD_NAME                six
              138  LOAD_METHOD              add_metaclass
              140  LOAD_NAME                abc
              142  LOAD_ATTR                ABCMeta
              144  CALL_METHOD_1         1  ''

 L.  24       146  LOAD_BUILD_CLASS 
              148  LOAD_CODE                <code_object RSAPrivateKey>
              150  LOAD_STR                 'RSAPrivateKey'
              152  MAKE_FUNCTION_0          'Neither defaults, keyword-only args, annotations, nor closures'
              154  LOAD_STR                 'RSAPrivateKey'
              156  LOAD_NAME                object
              158  CALL_FUNCTION_3       3  ''
              160  CALL_FUNCTION_1       1  ''
              162  STORE_NAME               RSAPrivateKey

 L.  56       164  LOAD_NAME                six
              166  LOAD_METHOD              add_metaclass
              168  LOAD_NAME                abc
              170  LOAD_ATTR                ABCMeta
              172  CALL_METHOD_1         1  ''

 L.  57       174  LOAD_BUILD_CLASS 
              176  LOAD_CODE                <code_object RSAPrivateKeyWithSerialization>
              178  LOAD_STR                 'RSAPrivateKeyWithSerialization'
              180  MAKE_FUNCTION_0          'Neither defaults, keyword-only args, annotations, nor closures'
              182  LOAD_STR                 'RSAPrivateKeyWithSerialization'
              184  LOAD_NAME                RSAPrivateKey
              186  CALL_FUNCTION_3       3  ''
              188  CALL_FUNCTION_1       1  ''
              190  STORE_NAME               RSAPrivateKeyWithSerialization

 L.  71       192  LOAD_NAME                six
              194  LOAD_METHOD              add_metaclass
              196  LOAD_NAME                abc
              198  LOAD_ATTR                ABCMeta
              200  CALL_METHOD_1         1  ''

 L.  72       202  LOAD_BUILD_CLASS 
              204  LOAD_CODE                <code_object RSAPublicKey>
              206  LOAD_STR                 'RSAPublicKey'
              208  MAKE_FUNCTION_0          'Neither defaults, keyword-only args, annotations, nor closures'
              210  LOAD_STR                 'RSAPublicKey'
              212  LOAD_NAME                object
              214  CALL_FUNCTION_3       3  ''
              216  CALL_FUNCTION_1       1  ''
              218  STORE_NAME               RSAPublicKey

 L. 116       220  LOAD_NAME                RSAPublicKey
              222  STORE_NAME               RSAPublicKeyWithSerialization

 L. 119       224  LOAD_CONST               (None,)
              226  LOAD_CODE                <code_object generate_private_key>
              228  LOAD_STR                 'generate_private_key'
              230  MAKE_FUNCTION_1          'default'
              232  STORE_NAME               generate_private_key

 L. 131       234  LOAD_CODE                <code_object _verify_rsa_parameters>
              236  LOAD_STR                 '_verify_rsa_parameters'
              238  MAKE_FUNCTION_0          'Neither defaults, keyword-only args, annotations, nor closures'
              240  STORE_NAME               _verify_rsa_parameters

 L. 142       242  LOAD_CODE                <code_object _check_private_key_components>
              244  LOAD_STR                 '_check_private_key_components'
              246  MAKE_FUNCTION_0          'Neither defaults, keyword-only args, annotations, nor closures'
              248  STORE_NAME               _check_private_key_components

 L. 182       250  LOAD_CODE                <code_object _check_public_key_components>
              252  LOAD_STR                 '_check_public_key_components'
              254  MAKE_FUNCTION_0          'Neither defaults, keyword-only args, annotations, nor closures'
              256  STORE_NAME               _check_public_key_components

 L. 193       258  LOAD_CODE                <code_object _modinv>
              260  LOAD_STR                 '_modinv'
              262  MAKE_FUNCTION_0          'Neither defaults, keyword-only args, annotations, nor closures'
              264  STORE_NAME               _modinv

 L. 206       266  LOAD_CODE                <code_object rsa_crt_iqmp>
              268  LOAD_STR                 'rsa_crt_iqmp'
              270  MAKE_FUNCTION_0          'Neither defaults, keyword-only args, annotations, nor closures'
              272  STORE_NAME               rsa_crt_iqmp

 L. 213       274  LOAD_CODE                <code_object rsa_crt_dmp1>
              276  LOAD_STR                 'rsa_crt_dmp1'
              278  MAKE_FUNCTION_0          'Neither defaults, keyword-only args, annotations, nor closures'
              280  STORE_NAME               rsa_crt_dmp1

 L. 221       282  LOAD_CODE                <code_object rsa_crt_dmq1>
              284  LOAD_STR                 'rsa_crt_dmq1'
              286  MAKE_FUNCTION_0          'Neither defaults, keyword-only args, annotations, nor closures'
              288  STORE_NAME               rsa_crt_dmq1

 L. 232       290  LOAD_CONST               1000
              292  STORE_NAME               _MAX_RECOVERY_ATTEMPTS

 L. 235       294  LOAD_CODE                <code_object rsa_recover_prime_factors>
              296  LOAD_STR                 'rsa_recover_prime_factors'
              298  MAKE_FUNCTION_0          'Neither defaults, keyword-only args, annotations, nor closures'
              300  STORE_NAME               rsa_recover_prime_factors

 L. 278       302  LOAD_BUILD_CLASS 
              304  LOAD_CODE                <code_object RSAPrivateNumbers>
              306  LOAD_STR                 'RSAPrivateNumbers'
              308  MAKE_FUNCTION_0          'Neither defaults, keyword-only args, annotations, nor closures'
              310  LOAD_STR                 'RSAPrivateNumbers'
              312  LOAD_NAME                object
              314  CALL_FUNCTION_3       3  ''
              316  STORE_NAME               RSAPrivateNumbers

 L. 350       318  LOAD_BUILD_CLASS 
              320  LOAD_CODE                <code_object RSAPublicNumbers>
              322  LOAD_STR                 'RSAPublicNumbers'
              324  MAKE_FUNCTION_0          'Neither defaults, keyword-only args, annotations, nor closures'
              326  LOAD_STR                 'RSAPublicNumbers'
              328  LOAD_NAME                object
              330  CALL_FUNCTION_3       3  ''
              332  STORE_NAME               RSAPublicNumbers

Parse error at or near `<121>' instruction at offset 50

Instruction context:
   
 L.  12        46  DUP_TOP          
                  48  LOAD_NAME                ImportError
->                50  <121>                74  ''
                  52  POP_TOP          
                  54  POP_TOP          
                  56  POP_TOP          

test/103869.pyc -- 
# decompile failed
