
# file test/107641.pyc
# --- This code section failed: ---

 L.   1         0  LOAD_STR                 'Utility functions, node construction macros, etc.'
                2  STORE_NAME               __doc__

 L.   5         4  LOAD_CONST               1
                6  LOAD_CONST               ('token',)
                8  IMPORT_NAME              pgen2
               10  IMPORT_FROM              token
               12  STORE_NAME               token
               14  POP_TOP          

 L.   6        16  LOAD_CONST               1
               18  LOAD_CONST               ('Leaf', 'Node')
               20  IMPORT_NAME              pytree
               22  IMPORT_FROM              Leaf
               24  STORE_NAME               Leaf
               26  IMPORT_FROM              Node
               28  STORE_NAME               Node
               30  POP_TOP          

 L.   7        32  LOAD_CONST               1
               34  LOAD_CONST               ('python_symbols',)
               36  IMPORT_NAME              pygram
               38  IMPORT_FROM              python_symbols
               40  STORE_NAME               syms
               42  POP_TOP          

 L.   8        44  LOAD_CONST               1
               46  LOAD_CONST               ('patcomp',)
               48  IMPORT_NAME              
               50  IMPORT_FROM              patcomp
               52  STORE_NAME               patcomp
               54  POP_TOP          

 L.  15        56  LOAD_CODE                <code_object KeywordArg>
               58  LOAD_STR                 'KeywordArg'
               60  MAKE_FUNCTION_0          'Neither defaults, keyword-only args, annotations, nor closures'
               62  STORE_NAME               KeywordArg

 L.  19        64  LOAD_CODE                <code_object LParen>
               66  LOAD_STR                 'LParen'
               68  MAKE_FUNCTION_0          'Neither defaults, keyword-only args, annotations, nor closures'
               70  STORE_NAME               LParen

 L.  22        72  LOAD_CODE                <code_object RParen>
               74  LOAD_STR                 'RParen'
               76  MAKE_FUNCTION_0          'Neither defaults, keyword-only args, annotations, nor closures'
               78  STORE_NAME               RParen

 L.  25        80  LOAD_CODE                <code_object Assign>
               82  LOAD_STR                 'Assign'
               84  MAKE_FUNCTION_0          'Neither defaults, keyword-only args, annotations, nor closures'
               86  STORE_NAME               Assign

 L.  36        88  LOAD_CONST               (None,)
               90  LOAD_CODE                <code_object Name>
               92  LOAD_STR                 'Name'
               94  MAKE_FUNCTION_1          'default'
               96  STORE_NAME               Name

 L.  40        98  LOAD_CODE                <code_object Attr>
              100  LOAD_STR                 'Attr'
              102  MAKE_FUNCTION_0          'Neither defaults, keyword-only args, annotations, nor closures'
              104  STORE_NAME               Attr

 L.  44       106  LOAD_CODE                <code_object Comma>
              108  LOAD_STR                 'Comma'
              110  MAKE_FUNCTION_0          'Neither defaults, keyword-only args, annotations, nor closures'
              112  STORE_NAME               Comma

 L.  48       114  LOAD_CODE                <code_object Dot>
              116  LOAD_STR                 'Dot'
              118  MAKE_FUNCTION_0          'Neither defaults, keyword-only args, annotations, nor closures'
              120  STORE_NAME               Dot

 L.  52       122  LOAD_NAME                LParen
              124  CALL_FUNCTION_0       0  ''
              126  LOAD_NAME                RParen
              128  CALL_FUNCTION_0       0  ''
              130  BUILD_TUPLE_2         2 
              132  LOAD_CODE                <code_object ArgList>
              134  LOAD_STR                 'ArgList'
              136  MAKE_FUNCTION_1          'default'
              138  STORE_NAME               ArgList

 L.  59       140  LOAD_CONST               (None, None)
              142  LOAD_CODE                <code_object Call>
              144  LOAD_STR                 'Call'
              146  MAKE_FUNCTION_1          'default'
              148  STORE_NAME               Call

 L.  66       150  LOAD_CODE                <code_object Newline>
              152  LOAD_STR                 'Newline'
              154  MAKE_FUNCTION_0          'Neither defaults, keyword-only args, annotations, nor closures'
              156  STORE_NAME               Newline

 L.  70       158  LOAD_CODE                <code_object BlankLine>
              160  LOAD_STR                 'BlankLine'
              162  MAKE_FUNCTION_0          'Neither defaults, keyword-only args, annotations, nor closures'
              164  STORE_NAME               BlankLine

 L.  74       166  LOAD_CONST               (None,)
              168  LOAD_CODE                <code_object Number>
              170  LOAD_STR                 'Number'
              172  MAKE_FUNCTION_1          'default'
              174  STORE_NAME               Number

 L.  77       176  LOAD_CODE                <code_object Subscript>
              178  LOAD_STR                 'Subscript'
              180  MAKE_FUNCTION_0          'Neither defaults, keyword-only args, annotations, nor closures'
              182  STORE_NAME               Subscript

 L.  83       184  LOAD_CONST               (None,)
              186  LOAD_CODE                <code_object String>
              188  LOAD_STR                 'String'
              190  MAKE_FUNCTION_1          'default'
              192  STORE_NAME               String

 L.  87       194  LOAD_CONST               (None,)
              196  LOAD_CODE                <code_object ListComp>
              198  LOAD_STR                 'ListComp'
              200  MAKE_FUNCTION_1          'default'
              202  STORE_NAME               ListComp

 L. 111       204  LOAD_CODE                <code_object FromImport>
              206  LOAD_STR                 'FromImport'
              208  MAKE_FUNCTION_0          'Neither defaults, keyword-only args, annotations, nor closures'
              210  STORE_NAME               FromImport

 L. 130       212  LOAD_CODE                <code_object ImportAndCall>
              214  LOAD_STR                 'ImportAndCall'
              216  MAKE_FUNCTION_0          'Neither defaults, keyword-only args, annotations, nor closures'
              218  STORE_NAME               ImportAndCall

 L. 158       220  LOAD_CODE                <code_object is_tuple>
              222  LOAD_STR                 'is_tuple'
              224  MAKE_FUNCTION_0          'Neither defaults, keyword-only args, annotations, nor closures'
              226  STORE_NAME               is_tuple

 L. 170       228  LOAD_CODE                <code_object is_list>
              230  LOAD_STR                 'is_list'
              232  MAKE_FUNCTION_0          'Neither defaults, keyword-only args, annotations, nor closures'
              234  STORE_NAME               is_list

 L. 184       236  LOAD_CODE                <code_object parenthesize>
              238  LOAD_STR                 'parenthesize'
              240  MAKE_FUNCTION_0          'Neither defaults, keyword-only args, annotations, nor closures'
              242  STORE_NAME               parenthesize

 L. 188       244  BUILD_SET_0           0 
              246  LOAD_CONST               frozenset({'max', 'sum', 'any', 'list', 'enumerate', 'min', 'sorted', 'set', 'tuple', 'all'})
              248  POP_FINALLY           1  ''
              250  STORE_NAME               consuming_calls

 L. 191       252  LOAD_CODE                <code_object attr_chain>
              254  LOAD_STR                 'attr_chain'
              256  MAKE_FUNCTION_0          'Neither defaults, keyword-only args, annotations, nor closures'
              258  STORE_NAME               attr_chain

 L. 210       260  LOAD_STR                 "for_stmt< 'for' any 'in' node=any ':' any* >\n        | comp_for< 'for' any 'in' node=any any* >\n     "
              262  STORE_GLOBAL             p0

 L. 213       264  LOAD_STR                 "\npower<\n    ( 'iter' | 'list' | 'tuple' | 'sorted' | 'set' | 'sum' |\n      'any' | 'all' | 'enumerate' | (any* trailer< '.' 'join' >) )\n    trailer< '(' node=any ')' >\n    any*\n>\n"
              266  STORE_GLOBAL             p1

 L. 221       268  LOAD_STR                 "\npower<\n    ( 'sorted' | 'enumerate' )\n    trailer< '(' arglist<node=any any*> ')' >\n    any*\n>\n"
              270  STORE_GLOBAL             p2

 L. 228       272  LOAD_CONST               False
              274  STORE_GLOBAL             pats_built

 L. 229       276  LOAD_CODE                <code_object in_special_context>
              278  LOAD_STR                 'in_special_context'
              280  MAKE_FUNCTION_0          'Neither defaults, keyword-only args, annotations, nor closures'
              282  STORE_NAME               in_special_context

 L. 248       284  LOAD_CODE                <code_object is_probably_builtin>
              286  LOAD_STR                 'is_probably_builtin'
              288  MAKE_FUNCTION_0          'Neither defaults, keyword-only args, annotations, nor closures'
              290  STORE_NAME               is_probably_builtin

 L. 271       292  LOAD_CODE                <code_object find_indentation>
              294  LOAD_STR                 'find_indentation'
              296  MAKE_FUNCTION_0          'Neither defaults, keyword-only args, annotations, nor closures'
              298  STORE_NAME               find_indentation

 L. 285       300  LOAD_CODE                <code_object make_suite>
              302  LOAD_STR                 'make_suite'
              304  MAKE_FUNCTION_0          'Neither defaults, keyword-only args, annotations, nor closures'
              306  STORE_NAME               make_suite

 L. 294       308  LOAD_CODE                <code_object find_root>
              310  LOAD_STR                 'find_root'
              312  MAKE_FUNCTION_0          'Neither defaults, keyword-only args, annotations, nor closures'
              314  STORE_NAME               find_root

 L. 303       316  LOAD_CODE                <code_object does_tree_import>
              318  LOAD_STR                 'does_tree_import'
              320  MAKE_FUNCTION_0          'Neither defaults, keyword-only args, annotations, nor closures'
              322  STORE_NAME               does_tree_import

 L. 311       324  LOAD_CODE                <code_object is_import>
              326  LOAD_STR                 'is_import'
              328  MAKE_FUNCTION_0          'Neither defaults, keyword-only args, annotations, nor closures'
              330  STORE_NAME               is_import

 L. 315       332  LOAD_CODE                <code_object touch_import>
              334  LOAD_STR                 'touch_import'
              336  MAKE_FUNCTION_0          'Neither defaults, keyword-only args, annotations, nor closures'
              338  STORE_NAME               touch_import

 L. 360       340  LOAD_NAME                syms
              342  LOAD_ATTR                classdef
              344  LOAD_NAME                syms
              346  LOAD_ATTR                funcdef
              348  BUILD_SET_2           2 
              350  STORE_NAME               _def_syms

 L. 361       352  LOAD_CONST               (None,)
              354  LOAD_CODE                <code_object find_binding>
              356  LOAD_STR                 'find_binding'
              358  MAKE_FUNCTION_1          'default'
              360  STORE_NAME               find_binding

 L. 403       362  LOAD_NAME                syms
              364  LOAD_ATTR                funcdef
              366  LOAD_NAME                syms
              368  LOAD_ATTR                classdef
              370  LOAD_NAME                syms
              372  LOAD_ATTR                trailer
              374  BUILD_SET_3           3 
              376  STORE_NAME               _block_syms

 L. 404       378  LOAD_CODE                <code_object _find>
              380  LOAD_STR                 '_find'
              382  MAKE_FUNCTION_0          'Neither defaults, keyword-only args, annotations, nor closures'
              384  STORE_NAME               _find

 L. 414       386  LOAD_CONST               (None,)
              388  LOAD_CODE                <code_object _is_import_binding>
              390  LOAD_STR                 '_is_import_binding'
              392  MAKE_FUNCTION_1          'default'
              394  STORE_NAME               _is_import_binding

Parse error at or near `POP_FINALLY' instruction at offset 248

Instruction context:
   
 L. 188       244  BUILD_SET_0           0 
                 246  LOAD_CONST               frozenset({'max', 'sum', 'any', 'list', 'enumerate', 'min', 'sorted', 'set', 'tuple', 'all'})
->               248  POP_FINALLY           1  ''
                 250  STORE_NAME               consuming_calls

test/107641.pyc -- 
# decompile failed
