
# file test/112032.pyc
# --- This code section failed: ---

 L.   4         0  LOAD_CONST               0
                2  LOAD_CONST               ('absolute_import', 'division', 'print_function')
                4  IMPORT_NAME              __future__
                6  IMPORT_FROM              absolute_import
                8  STORE_NAME               absolute_import
               10  IMPORT_FROM              division
               12  STORE_NAME               division
               14  IMPORT_FROM              print_function
               16  STORE_NAME               print_function
               18  POP_TOP          

 L.   6        20  LOAD_CONST               0
               22  LOAD_CONST               None
               24  IMPORT_NAME              operator
               26  STORE_NAME               operator

 L.   7        28  LOAD_CONST               0
               30  LOAD_CONST               None
               32  IMPORT_NAME              os
               34  STORE_NAME               os

 L.   8        36  LOAD_CONST               0
               38  LOAD_CONST               None
               40  IMPORT_NAME              platform
               42  STORE_NAME               platform

 L.   9        44  LOAD_CONST               0
               46  LOAD_CONST               None
               48  IMPORT_NAME              sys
               50  STORE_NAME               sys

 L.  11        52  LOAD_CONST               0
               54  LOAD_CONST               ('ParseException', 'ParseResults', 'stringStart', 'stringEnd')
               56  IMPORT_NAME_ATTR         setuptools.extern.pyparsing
               58  IMPORT_FROM              ParseException
               60  STORE_NAME               ParseException
               62  IMPORT_FROM              ParseResults
               64  STORE_NAME               ParseResults
               66  IMPORT_FROM              stringStart
               68  STORE_NAME               stringStart
               70  IMPORT_FROM              stringEnd
               72  STORE_NAME               stringEnd
               74  POP_TOP          

 L.  12        76  LOAD_CONST               0
               78  LOAD_CONST               ('ZeroOrMore', 'Group', 'Forward', 'QuotedString')
               80  IMPORT_NAME_ATTR         setuptools.extern.pyparsing
               82  IMPORT_FROM              ZeroOrMore
               84  STORE_NAME               ZeroOrMore
               86  IMPORT_FROM              Group
               88  STORE_NAME               Group
               90  IMPORT_FROM              Forward
               92  STORE_NAME               Forward
               94  IMPORT_FROM              QuotedString
               96  STORE_NAME               QuotedString
               98  POP_TOP          

 L.  13       100  LOAD_CONST               0
              102  LOAD_CONST               ('Literal',)
              104  IMPORT_NAME_ATTR         setuptools.extern.pyparsing
              106  IMPORT_FROM              Literal
              108  STORE_NAME               L
              110  POP_TOP          

 L.  15       112  LOAD_CONST               1
              114  LOAD_CONST               ('string_types',)
              116  IMPORT_NAME              _compat
              118  IMPORT_FROM              string_types
              120  STORE_NAME               string_types
              122  POP_TOP          

 L.  16       124  LOAD_CONST               1
              126  LOAD_CONST               ('TYPE_CHECKING',)
              128  IMPORT_NAME              _typing
              130  IMPORT_FROM              TYPE_CHECKING
              132  STORE_NAME               TYPE_CHECKING
              134  POP_TOP          

 L.  17       136  LOAD_CONST               1
              138  LOAD_CONST               ('Specifier', 'InvalidSpecifier')
              140  IMPORT_NAME              specifiers
              142  IMPORT_FROM              Specifier
              144  STORE_NAME               Specifier
              146  IMPORT_FROM              InvalidSpecifier
              148  STORE_NAME               InvalidSpecifier
              150  POP_TOP          

 L.  19       152  LOAD_NAME                TYPE_CHECKING
              154  POP_JUMP_IF_FALSE   208  'to 208'

 L.  20       156  LOAD_CONST               0
              158  LOAD_CONST               ('Any', 'Callable', 'Dict', 'List', 'Optional', 'Tuple', 'Union')
              160  IMPORT_NAME              typing
              162  IMPORT_FROM              Any
              164  STORE_NAME               Any
              166  IMPORT_FROM              Callable
              168  STORE_NAME               Callable
              170  IMPORT_FROM              Dict
              172  STORE_NAME               Dict
              174  IMPORT_FROM              List
              176  STORE_NAME               List
              178  IMPORT_FROM              Optional
              180  STORE_NAME               Optional
              182  IMPORT_FROM              Tuple
              184  STORE_NAME               Tuple
              186  IMPORT_FROM              Union
              188  STORE_NAME               Union
              190  POP_TOP          

 L.  22       192  LOAD_NAME                Callable
              194  LOAD_NAME                str
              196  LOAD_NAME                str
              198  BUILD_LIST_2          2 
              200  LOAD_NAME                bool
              202  BUILD_TUPLE_2         2 
              204  BINARY_SUBSCR    
              206  STORE_NAME               Operator
            208_0  COME_FROM           154  '154'

 L.  25       208  BUILD_LIST_0          0 
              210  LOAD_CONST               ('InvalidMarker', 'UndefinedComparison', 'UndefinedEnvironmentName', 'Marker', 'default_environment')
              212  CALL_FINALLY        215  'to 215'
              214  STORE_NAME               __all__

 L.  34       216  LOAD_BUILD_CLASS 
              218  LOAD_CODE                <code_object InvalidMarker>
              220  LOAD_STR                 'InvalidMarker'
              222  MAKE_FUNCTION_0          'Neither defaults, keyword-only args, annotations, nor closures'
              224  LOAD_STR                 'InvalidMarker'
              226  LOAD_NAME                ValueError
              228  CALL_FUNCTION_3       3  ''
              230  STORE_NAME               InvalidMarker

 L.  40       232  LOAD_BUILD_CLASS 
              234  LOAD_CODE                <code_object UndefinedComparison>
              236  LOAD_STR                 'UndefinedComparison'
              238  MAKE_FUNCTION_0          'Neither defaults, keyword-only args, annotations, nor closures'
              240  LOAD_STR                 'UndefinedComparison'
              242  LOAD_NAME                ValueError
              244  CALL_FUNCTION_3       3  ''
              246  STORE_NAME               UndefinedComparison

 L.  46       248  LOAD_BUILD_CLASS 
              250  LOAD_CODE                <code_object UndefinedEnvironmentName>
              252  LOAD_STR                 'UndefinedEnvironmentName'
              254  MAKE_FUNCTION_0          'Neither defaults, keyword-only args, annotations, nor closures'
              256  LOAD_STR                 'UndefinedEnvironmentName'
              258  LOAD_NAME                ValueError
              260  CALL_FUNCTION_3       3  ''
              262  STORE_NAME               UndefinedEnvironmentName

 L.  53       264  LOAD_BUILD_CLASS 
              266  LOAD_CODE                <code_object Node>
              268  LOAD_STR                 'Node'
              270  MAKE_FUNCTION_0          'Neither defaults, keyword-only args, annotations, nor closures'
              272  LOAD_STR                 'Node'
              274  LOAD_NAME                object
              276  CALL_FUNCTION_3       3  ''
              278  STORE_NAME               Node

 L.  71       280  LOAD_BUILD_CLASS 
              282  LOAD_CODE                <code_object Variable>
              284  LOAD_STR                 'Variable'
              286  MAKE_FUNCTION_0          'Neither defaults, keyword-only args, annotations, nor closures'
              288  LOAD_STR                 'Variable'
              290  LOAD_NAME                Node
              292  CALL_FUNCTION_3       3  ''
              294  STORE_NAME               Variable

 L.  77       296  LOAD_BUILD_CLASS 
              298  LOAD_CODE                <code_object Value>
              300  LOAD_STR                 'Value'
              302  MAKE_FUNCTION_0          'Neither defaults, keyword-only args, annotations, nor closures'
              304  LOAD_STR                 'Value'
              306  LOAD_NAME                Node
              308  CALL_FUNCTION_3       3  ''
              310  STORE_NAME               Value

 L.  83       312  LOAD_BUILD_CLASS 
              314  LOAD_CODE                <code_object Op>
              316  LOAD_STR                 'Op'
              318  MAKE_FUNCTION_0          'Neither defaults, keyword-only args, annotations, nor closures'
              320  LOAD_STR                 'Op'
              322  LOAD_NAME                Node
              324  CALL_FUNCTION_3       3  ''
              326  STORE_NAME               Op

 L.  90       328  LOAD_NAME                L
              330  LOAD_STR                 'implementation_version'
              332  CALL_FUNCTION_1       1  ''

 L.  91       334  LOAD_NAME                L
              336  LOAD_STR                 'platform_python_implementation'
              338  CALL_FUNCTION_1       1  ''

 L.  90       340  BINARY_OR        

 L.  92       342  LOAD_NAME                L
              344  LOAD_STR                 'implementation_name'
              346  CALL_FUNCTION_1       1  ''

 L.  90       348  BINARY_OR        

 L.  93       350  LOAD_NAME                L
              352  LOAD_STR                 'python_full_version'
              354  CALL_FUNCTION_1       1  ''

 L.  90       356  BINARY_OR        

 L.  94       358  LOAD_NAME                L
              360  LOAD_STR                 'platform_release'
              362  CALL_FUNCTION_1       1  ''

 L.  90       364  BINARY_OR        

 L.  95       366  LOAD_NAME                L
              368  LOAD_STR                 'platform_version'
              370  CALL_FUNCTION_1       1  ''

 L.  90       372  BINARY_OR        

 L.  96       374  LOAD_NAME                L
              376  LOAD_STR                 'platform_machine'
              378  CALL_FUNCTION_1       1  ''

 L.  90       380  BINARY_OR        

 L.  97       382  LOAD_NAME                L
              384  LOAD_STR                 'platform_system'
              386  CALL_FUNCTION_1       1  ''

 L.  90       388  BINARY_OR        

 L.  98       390  LOAD_NAME                L
              392  LOAD_STR                 'python_version'
              394  CALL_FUNCTION_1       1  ''

 L.  90       396  BINARY_OR        

 L.  99       398  LOAD_NAME                L
              400  LOAD_STR                 'sys_platform'
              402  CALL_FUNCTION_1       1  ''

 L.  90       404  BINARY_OR        

 L. 100       406  LOAD_NAME                L
              408  LOAD_STR                 'os_name'
              410  CALL_FUNCTION_1       1  ''

 L.  90       412  BINARY_OR        

 L. 101       414  LOAD_NAME                L
              416  LOAD_STR                 'os.name'
              418  CALL_FUNCTION_1       1  ''

 L.  90       420  BINARY_OR        

 L. 102       422  LOAD_NAME                L
              424  LOAD_STR                 'sys.platform'
              426  CALL_FUNCTION_1       1  ''

 L.  90       428  BINARY_OR        

 L. 103       430  LOAD_NAME                L
              432  LOAD_STR                 'platform.version'
              434  CALL_FUNCTION_1       1  ''

 L.  90       436  BINARY_OR        

 L. 104       438  LOAD_NAME                L
              440  LOAD_STR                 'platform.machine'
              442  CALL_FUNCTION_1       1  ''

 L.  90       444  BINARY_OR        

 L. 105       446  LOAD_NAME                L
              448  LOAD_STR                 'platform.python_implementation'
              450  CALL_FUNCTION_1       1  ''

 L.  90       452  BINARY_OR        

 L. 106       454  LOAD_NAME                L
              456  LOAD_STR                 'python_implementation'
              458  CALL_FUNCTION_1       1  ''

 L.  90       460  BINARY_OR        

 L. 107       462  LOAD_NAME                L
              464  LOAD_STR                 'extra'
              466  CALL_FUNCTION_1       1  ''

 L.  90       468  BINARY_OR        

 L.  89       470  STORE_NAME               VARIABLE

 L. 110       472  LOAD_STR                 'os_name'

 L. 111       474  LOAD_STR                 'sys_platform'

 L. 112       476  LOAD_STR                 'platform_version'

 L. 113       478  LOAD_STR                 'platform_machine'

 L. 114       480  LOAD_STR                 'platform_python_implementation'

 L. 115       482  LOAD_STR                 'platform_python_implementation'

 L. 109       484  LOAD_CONST               ('os.name', 'sys.platform', 'platform.version', 'platform.machine', 'platform.python_implementation', 'python_implementation')
              486  BUILD_CONST_KEY_MAP_6     6 
              488  STORE_NAME               ALIASES

 L. 117       490  LOAD_NAME                VARIABLE
              492  LOAD_METHOD              setParseAction
              494  LOAD_LAMBDA              '<code_object <lambda>>'
              496  LOAD_STR                 '<lambda>'
              498  MAKE_FUNCTION_0          'Neither defaults, keyword-only args, annotations, nor closures'
              500  CALL_METHOD_1         1  ''
              502  POP_TOP          

 L. 120       504  LOAD_NAME                L
              506  LOAD_STR                 '==='
              508  CALL_FUNCTION_1       1  ''
              510  LOAD_NAME                L
              512  LOAD_STR                 '=='
              514  CALL_FUNCTION_1       1  ''
              516  BINARY_OR        
              518  LOAD_NAME                L
              520  LOAD_STR                 '>='
              522  CALL_FUNCTION_1       1  ''
              524  BINARY_OR        
              526  LOAD_NAME                L
              528  LOAD_STR                 '<='
              530  CALL_FUNCTION_1       1  ''
              532  BINARY_OR        
              534  LOAD_NAME                L
              536  LOAD_STR                 '!='
              538  CALL_FUNCTION_1       1  ''
              540  BINARY_OR        
              542  LOAD_NAME                L
              544  LOAD_STR                 '~='
              546  CALL_FUNCTION_1       1  ''
              548  BINARY_OR        
              550  LOAD_NAME                L
              552  LOAD_STR                 '>'
              554  CALL_FUNCTION_1       1  ''
              556  BINARY_OR        
              558  LOAD_NAME                L
              560  LOAD_STR                 '<'
              562  CALL_FUNCTION_1       1  ''
              564  BINARY_OR        

 L. 119       566  STORE_NAME               VERSION_CMP

 L. 123       568  LOAD_NAME                VERSION_CMP
              570  LOAD_NAME                L
              572  LOAD_STR                 'not in'
              574  CALL_FUNCTION_1       1  ''
              576  BINARY_OR        
              578  LOAD_NAME                L
              580  LOAD_STR                 'in'
              582  CALL_FUNCTION_1       1  ''
              584  BINARY_OR        
              586  STORE_NAME               MARKER_OP

 L. 124       588  LOAD_NAME                MARKER_OP
              590  LOAD_METHOD              setParseAction
              592  LOAD_LAMBDA              '<code_object <lambda>>'
              594  LOAD_STR                 '<lambda>'
              596  MAKE_FUNCTION_0          'Neither defaults, keyword-only args, annotations, nor closures'
              598  CALL_METHOD_1         1  ''
              600  POP_TOP          

 L. 126       602  LOAD_NAME                QuotedString
              604  LOAD_STR                 "'"
              606  CALL_FUNCTION_1       1  ''
              608  LOAD_NAME                QuotedString
              610  LOAD_STR                 '"'
              612  CALL_FUNCTION_1       1  ''
              614  BINARY_OR        
              616  STORE_NAME               MARKER_VALUE

 L. 127       618  LOAD_NAME                MARKER_VALUE
              620  LOAD_METHOD              setParseAction
              622  LOAD_LAMBDA              '<code_object <lambda>>'
              624  LOAD_STR                 '<lambda>'
              626  MAKE_FUNCTION_0          'Neither defaults, keyword-only args, annotations, nor closures'
              628  CALL_METHOD_1         1  ''
              630  POP_TOP          

 L. 129       632  LOAD_NAME                L
              634  LOAD_STR                 'and'
              636  CALL_FUNCTION_1       1  ''
              638  LOAD_NAME                L
              640  LOAD_STR                 'or'
              642  CALL_FUNCTION_1       1  ''
              644  BINARY_OR        
              646  STORE_NAME               BOOLOP

 L. 131       648  LOAD_NAME                VARIABLE
              650  LOAD_NAME                MARKER_VALUE
              652  BINARY_OR        
              654  STORE_NAME               MARKER_VAR

 L. 133       656  LOAD_NAME                Group
              658  LOAD_NAME                MARKER_VAR
              660  LOAD_NAME                MARKER_OP
              662  BINARY_ADD       
              664  LOAD_NAME                MARKER_VAR
              666  BINARY_ADD       
              668  CALL_FUNCTION_1       1  ''
              670  STORE_NAME               MARKER_ITEM

 L. 134       672  LOAD_NAME                MARKER_ITEM
              674  LOAD_METHOD              setParseAction
              676  LOAD_LAMBDA              '<code_object <lambda>>'
              678  LOAD_STR                 '<lambda>'
              680  MAKE_FUNCTION_0          'Neither defaults, keyword-only args, annotations, nor closures'
              682  CALL_METHOD_1         1  ''
              684  POP_TOP          

 L. 136       686  LOAD_NAME                L
              688  LOAD_STR                 '('
              690  CALL_FUNCTION_1       1  ''
              692  LOAD_METHOD              suppress
              694  CALL_METHOD_0         0  ''
              696  STORE_NAME               LPAREN

 L. 137       698  LOAD_NAME                L
              700  LOAD_STR                 ')'
              702  CALL_FUNCTION_1       1  ''
              704  LOAD_METHOD              suppress
              706  CALL_METHOD_0         0  ''
              708  STORE_NAME               RPAREN

 L. 139       710  LOAD_NAME                Forward
              712  CALL_FUNCTION_0       0  ''
              714  STORE_NAME               MARKER_EXPR

 L. 140       716  LOAD_NAME                MARKER_ITEM
              718  LOAD_NAME                Group
              720  LOAD_NAME                LPAREN
              722  LOAD_NAME                MARKER_EXPR
              724  BINARY_ADD       
              726  LOAD_NAME                RPAREN
              728  BINARY_ADD       
              730  CALL_FUNCTION_1       1  ''
              732  BINARY_OR        
              734  STORE_NAME               MARKER_ATOM

 L. 141       736  LOAD_NAME                MARKER_EXPR
              738  LOAD_NAME                MARKER_ATOM
              740  LOAD_NAME                ZeroOrMore
              742  LOAD_NAME                BOOLOP
              744  LOAD_NAME                MARKER_EXPR
              746  BINARY_ADD       
              748  CALL_FUNCTION_1       1  ''
              750  BINARY_ADD       
              752  BINARY_LSHIFT    
              754  POP_TOP          

 L. 143       756  LOAD_NAME                stringStart
              758  LOAD_NAME                MARKER_EXPR
              760  BINARY_ADD       
              762  LOAD_NAME                stringEnd
              764  BINARY_ADD       
              766  STORE_NAME               MARKER

 L. 146       768  LOAD_CODE                <code_object _coerce_parse_result>
              770  LOAD_STR                 '_coerce_parse_result'
              772  MAKE_FUNCTION_0          'Neither defaults, keyword-only args, annotations, nor closures'
              774  STORE_NAME               _coerce_parse_result

 L. 154       776  LOAD_CONST               (True,)
              778  LOAD_CODE                <code_object _format_marker>
              780  LOAD_STR                 '_format_marker'
              782  MAKE_FUNCTION_1          'default'
              784  STORE_NAME               _format_marker

 L. 183       786  LOAD_LAMBDA              '<code_object <lambda>>'
              788  LOAD_STR                 '<lambda>'
              790  MAKE_FUNCTION_0          'Neither defaults, keyword-only args, annotations, nor closures'

 L. 184       792  LOAD_LAMBDA              '<code_object <lambda>>'
              794  LOAD_STR                 '<lambda>'
              796  MAKE_FUNCTION_0          'Neither defaults, keyword-only args, annotations, nor closures'

 L. 185       798  LOAD_NAME                operator
              800  LOAD_ATTR                lt

 L. 186       802  LOAD_NAME                operator
              804  LOAD_ATTR                le

 L. 187       806  LOAD_NAME                operator
              808  LOAD_ATTR                eq

 L. 188       810  LOAD_NAME                operator
              812  LOAD_ATTR                ne

 L. 189       814  LOAD_NAME                operator
              816  LOAD_ATTR                ge

 L. 190       818  LOAD_NAME                operator
              820  LOAD_ATTR                gt

 L. 182       822  LOAD_CONST               ('in', 'not in', '<', '<=', '==', '!=', '>=', '>')
              824  BUILD_CONST_KEY_MAP_8     8 
              826  STORE_NAME               _operators

 L. 194       828  LOAD_CODE                <code_object _eval_op>
              830  LOAD_STR                 '_eval_op'
              832  MAKE_FUNCTION_0          'Neither defaults, keyword-only args, annotations, nor closures'
              834  STORE_NAME               _eval_op

 L. 212       836  LOAD_BUILD_CLASS 
              838  LOAD_CODE                <code_object Undefined>
              840  LOAD_STR                 'Undefined'
              842  MAKE_FUNCTION_0          'Neither defaults, keyword-only args, annotations, nor closures'
              844  LOAD_STR                 'Undefined'
              846  LOAD_NAME                object
              848  CALL_FUNCTION_3       3  ''
              850  STORE_NAME               Undefined

 L. 216       852  LOAD_NAME                Undefined
              854  CALL_FUNCTION_0       0  ''
              856  STORE_NAME               _undefined

 L. 219       858  LOAD_CODE                <code_object _get_env>
              860  LOAD_STR                 '_get_env'
              862  MAKE_FUNCTION_0          'Neither defaults, keyword-only args, annotations, nor closures'
              864  STORE_NAME               _get_env

 L. 231       866  LOAD_CODE                <code_object _evaluate_markers>
              868  LOAD_STR                 '_evaluate_markers'
              870  MAKE_FUNCTION_0          'Neither defaults, keyword-only args, annotations, nor closures'
              872  STORE_NAME               _evaluate_markers

 L. 259       874  LOAD_CODE                <code_object format_full_version>
              876  LOAD_STR                 'format_full_version'
              878  MAKE_FUNCTION_0          'Neither defaults, keyword-only args, annotations, nor closures'
              880  STORE_NAME               format_full_version

 L. 268       882  LOAD_CODE                <code_object default_environment>
              884  LOAD_STR                 'default_environment'
              886  MAKE_FUNCTION_0          'Neither defaults, keyword-only args, annotations, nor closures'
              888  STORE_NAME               default_environment

 L. 295       890  LOAD_BUILD_CLASS 
              892  LOAD_CODE                <code_object Marker>
              894  LOAD_STR                 'Marker'
              896  MAKE_FUNCTION_0          'Neither defaults, keyword-only args, annotations, nor closures'
              898  LOAD_STR                 'Marker'
              900  LOAD_NAME                object
              902  CALL_FUNCTION_3       3  ''
              904  STORE_NAME               Marker

Parse error at or near `CALL_FINALLY' instruction at offset 212

Instruction context:
   
 L.  25       208  BUILD_LIST_0          0 
                 210  LOAD_CONST               ('InvalidMarker', 'UndefinedComparison', 'UndefinedEnvironmentName', 'Marker', 'default_environment')
->               212  CALL_FINALLY        215  'to 215'
                 214  STORE_NAME               __all__

test/112032.pyc -- 
# decompile failed
