
# file test/115966.pyc
# --- This code section failed: ---

 L.   1         0  LOAD_STR                 'Wrapper functions for Tcl/Tk.\n\nTkinter provides classes which allow the display, positioning and\ncontrol of widgets. Toplevel widgets are Tk and Toplevel. Other\nwidgets are Frame, Label, Entry, Text, Canvas, Button, Radiobutton,\nCheckbutton, Scale, Listbox, Scrollbar, OptionMenu, Spinbox\nLabelFrame and PanedWindow.\n\nProperties of the widgets are specified with keyword arguments.\nKeyword arguments have the same name as the corresponding resource\nunder Tk.\n\nWidgets are positioned with one of the geometry managers Place, Pack\nor Grid. These managers can be called with methods place, pack, grid\navailable in every Widget.\n\nActions are bound to events by resources (e.g. keyword argument\ncommand) or with the method bind.\n\nExample (Hello, World):\nimport tkinter\nfrom tkinter.constants import *\ntk = tkinter.Tk()\nframe = tkinter.Frame(tk, relief=RIDGE, borderwidth=2)\nframe.pack(fill=BOTH,expand=1)\nlabel = tkinter.Label(frame, text="Hello, World")\nlabel.pack(fill=X, expand=1)\nbutton = tkinter.Button(frame,text="Exit",command=tk.destroy)\nbutton.pack(side=BOTTOM)\ntk.mainloop()\n'
                2  STORE_NAME               __doc__

 L.  33         4  LOAD_CONST               0
                6  LOAD_CONST               None
                8  IMPORT_NAME              enum
               10  STORE_NAME               enum

 L.  34        12  LOAD_CONST               0
               14  LOAD_CONST               None
               16  IMPORT_NAME              sys
               18  STORE_NAME               sys

 L.  35        20  LOAD_CONST               0
               22  LOAD_CONST               None
               24  IMPORT_NAME              types
               26  STORE_NAME               types

 L.  37        28  LOAD_CONST               0
               30  LOAD_CONST               None
               32  IMPORT_NAME              _tkinter
               34  STORE_NAME               _tkinter

 L.  38        36  LOAD_NAME                _tkinter
               38  LOAD_ATTR                TclError
               40  STORE_NAME               TclError

 L.  39        42  LOAD_CONST               0
               44  LOAD_CONST               ('*',)
               46  IMPORT_NAME_ATTR         tkinter.constants
               48  IMPORT_STAR      

 L.  40        50  LOAD_CONST               0
               52  LOAD_CONST               None
               54  IMPORT_NAME              re
               56  STORE_NAME               re

 L.  42        58  LOAD_CONST               1
               60  STORE_NAME               wantobjects

 L.  44        62  LOAD_NAME                float
               64  LOAD_NAME                _tkinter
               66  LOAD_ATTR                TK_VERSION
               68  CALL_FUNCTION_1       1  ''
               70  STORE_NAME               TkVersion

 L.  45        72  LOAD_NAME                float
               74  LOAD_NAME                _tkinter
               76  LOAD_ATTR                TCL_VERSION
               78  CALL_FUNCTION_1       1  ''
               80  STORE_NAME               TclVersion

 L.  47        82  LOAD_NAME                _tkinter
               84  LOAD_ATTR                READABLE
               86  STORE_NAME               READABLE

 L.  48        88  LOAD_NAME                _tkinter
               90  LOAD_ATTR                WRITABLE
               92  STORE_NAME               WRITABLE

 L.  49        94  LOAD_NAME                _tkinter
               96  LOAD_ATTR                EXCEPTION
               98  STORE_NAME               EXCEPTION

 L.  52       100  LOAD_NAME                re
              102  LOAD_METHOD              compile
              104  LOAD_STR                 '([\\\\{}])'
              106  CALL_METHOD_1         1  ''
              108  STORE_NAME               _magic_re

 L.  53       110  LOAD_NAME                re
              112  LOAD_METHOD              compile
              114  LOAD_STR                 '([\\s])'
              116  LOAD_NAME                re
              118  LOAD_ATTR                ASCII
              120  CALL_METHOD_2         2  ''
              122  STORE_NAME               _space_re

 L.  56       124  LOAD_CODE                <code_object _join>
              126  LOAD_STR                 '_join'
              128  MAKE_FUNCTION_0          'Neither defaults, keyword-only args, annotations, nor closures'
              130  STORE_NAME               _join

 L.  61       132  LOAD_CODE                <code_object _stringify>
              134  LOAD_STR                 '_stringify'
              136  MAKE_FUNCTION_0          'Neither defaults, keyword-only args, annotations, nor closures'
              138  STORE_NAME               _stringify

 L.  86       140  LOAD_CODE                <code_object _flatten>
              142  LOAD_STR                 '_flatten'
              144  MAKE_FUNCTION_0          'Neither defaults, keyword-only args, annotations, nor closures'
              146  STORE_NAME               _flatten

 L.  97       148  SETUP_FINALLY       160  'to 160'
              150  LOAD_NAME                _tkinter
              152  LOAD_ATTR                _flatten
              154  STORE_NAME               _flatten
              156  POP_BLOCK        
              158  JUMP_FORWARD        178  'to 178'
            160_0  COME_FROM_FINALLY   148  '148'

 L.  98       160  DUP_TOP          
              162  LOAD_NAME                AttributeError
              164  <121>               176  ''
              166  POP_TOP          
              168  POP_TOP          
              170  POP_TOP          
              172  POP_EXCEPT       
              174  JUMP_FORWARD        178  'to 178'
              176  <48>             
            178_0  COME_FROM           174  '174'
            178_1  COME_FROM           158  '158'

 L. 101       178  LOAD_CODE                <code_object _cnfmerge>
              180  LOAD_STR                 '_cnfmerge'
              182  MAKE_FUNCTION_0          'Neither defaults, keyword-only args, annotations, nor closures'
              184  STORE_NAME               _cnfmerge

 L. 119       186  SETUP_FINALLY       198  'to 198'
              188  LOAD_NAME                _tkinter
              190  LOAD_ATTR                _cnfmerge
              192  STORE_NAME               _cnfmerge
              194  POP_BLOCK        
              196  JUMP_FORWARD        216  'to 216'
            198_0  COME_FROM_FINALLY   186  '186'

 L. 120       198  DUP_TOP          
              200  LOAD_NAME                AttributeError
              202  <121>               214  ''
              204  POP_TOP          
              206  POP_TOP          
              208  POP_TOP          
              210  POP_EXCEPT       
              212  JUMP_FORWARD        216  'to 216'
              214  <48>             
            216_0  COME_FROM           212  '212'
            216_1  COME_FROM           196  '196'

 L. 123       216  LOAD_CONST               (True, None)
              218  LOAD_CODE                <code_object _splitdict>
              220  LOAD_STR                 '_splitdict'
              222  MAKE_FUNCTION_1          'default'
              224  STORE_NAME               _splitdict

 L. 147       226  LOAD_BUILD_CLASS 
              228  LOAD_CODE                <code_object EventType>
              230  LOAD_STR                 'EventType'
              232  MAKE_FUNCTION_0          'Neither defaults, keyword-only args, annotations, nor closures'
              234  LOAD_STR                 'EventType'
              236  LOAD_NAME                str
              238  LOAD_NAME                enum
              240  LOAD_ATTR                Enum
              242  CALL_FUNCTION_4       4  ''
              244  STORE_NAME               EventType

 L. 191       246  LOAD_BUILD_CLASS 
              248  LOAD_CODE                <code_object Event>
              250  LOAD_STR                 'Event'
              252  MAKE_FUNCTION_0          'Neither defaults, keyword-only args, annotations, nor closures'
              254  LOAD_STR                 'Event'
              256  CALL_FUNCTION_2       2  ''
              258  STORE_NAME               Event

 L. 273       260  LOAD_CONST               True
              262  STORE_GLOBAL             _support_default_root

 L. 274       264  LOAD_CONST               None
              266  STORE_GLOBAL             _default_root

 L. 277       268  LOAD_CODE                <code_object NoDefaultRoot>
              270  LOAD_STR                 'NoDefaultRoot'
              272  MAKE_FUNCTION_0          'Neither defaults, keyword-only args, annotations, nor closures'
              274  STORE_NAME               NoDefaultRoot

 L. 291       276  LOAD_CONST               (None,)
              278  LOAD_CODE                <code_object _get_default_root>
              280  LOAD_STR                 '_get_default_root'
              282  MAKE_FUNCTION_1          'default'
              284  STORE_NAME               _get_default_root

 L. 303       286  LOAD_CODE                <code_object _tkerror>
              288  LOAD_STR                 '_tkerror'
              290  MAKE_FUNCTION_0          'Neither defaults, keyword-only args, annotations, nor closures'
              292  STORE_NAME               _tkerror

 L. 308       294  LOAD_CONST               (0,)
              296  LOAD_CODE                <code_object _exit>
              298  LOAD_STR                 '_exit'
              300  MAKE_FUNCTION_1          'default'
              302  STORE_NAME               _exit

 L. 317       304  LOAD_CONST               0
              306  STORE_GLOBAL             _varnum

 L. 320       308  LOAD_BUILD_CLASS 
              310  LOAD_CODE                <code_object Variable>
              312  LOAD_STR                 'Variable'
              314  MAKE_FUNCTION_0          'Neither defaults, keyword-only args, annotations, nor closures'
              316  LOAD_STR                 'Variable'
              318  CALL_FUNCTION_2       2  ''
              320  STORE_NAME               Variable

 L. 501       322  LOAD_BUILD_CLASS 
              324  LOAD_CODE                <code_object StringVar>
              326  LOAD_STR                 'StringVar'
              328  MAKE_FUNCTION_0          'Neither defaults, keyword-only args, annotations, nor closures'
              330  LOAD_STR                 'StringVar'
              332  LOAD_NAME                Variable
              334  CALL_FUNCTION_3       3  ''
              336  STORE_NAME               StringVar

 L. 525       338  LOAD_BUILD_CLASS 
              340  LOAD_CODE                <code_object IntVar>
              342  LOAD_STR                 'IntVar'
              344  MAKE_FUNCTION_0          'Neither defaults, keyword-only args, annotations, nor closures'
              346  LOAD_STR                 'IntVar'
              348  LOAD_NAME                Variable
              350  CALL_FUNCTION_3       3  ''
              352  STORE_NAME               IntVar

 L. 550       354  LOAD_BUILD_CLASS 
              356  LOAD_CODE                <code_object DoubleVar>
              358  LOAD_STR                 'DoubleVar'
              360  MAKE_FUNCTION_0          'Neither defaults, keyword-only args, annotations, nor closures'
              362  LOAD_STR                 'DoubleVar'
              364  LOAD_NAME                Variable
              366  CALL_FUNCTION_3       3  ''
              368  STORE_NAME               DoubleVar

 L. 571       370  LOAD_BUILD_CLASS 
              372  LOAD_CODE                <code_object BooleanVar>
              374  LOAD_STR                 'BooleanVar'
              376  MAKE_FUNCTION_0          'Neither defaults, keyword-only args, annotations, nor closures'
              378  LOAD_STR                 'BooleanVar'
              380  LOAD_NAME                Variable
              382  CALL_FUNCTION_3       3  ''
              384  STORE_NAME               BooleanVar

 L. 601       386  LOAD_CONST               (0,)
              388  LOAD_CODE                <code_object mainloop>
              390  LOAD_STR                 'mainloop'
              392  MAKE_FUNCTION_1          'default'
              394  STORE_NAME               mainloop

 L. 606       396  LOAD_NAME                int
              398  STORE_NAME               getint

 L. 608       400  LOAD_NAME                float
              402  STORE_NAME               getdouble

 L. 611       404  LOAD_CODE                <code_object getboolean>
              406  LOAD_STR                 'getboolean'
              408  MAKE_FUNCTION_0          'Neither defaults, keyword-only args, annotations, nor closures'
              410  STORE_NAME               getboolean

 L. 621       412  LOAD_BUILD_CLASS 
              414  LOAD_CODE                <code_object Misc>
              416  LOAD_STR                 'Misc'
              418  MAKE_FUNCTION_0          'Neither defaults, keyword-only args, annotations, nor closures'
              420  LOAD_STR                 'Misc'
              422  CALL_FUNCTION_2       2  ''
              424  STORE_NAME               Misc

 L.1877       426  LOAD_BUILD_CLASS 
              428  LOAD_CODE                <code_object CallWrapper>
              430  LOAD_STR                 'CallWrapper'
              432  MAKE_FUNCTION_0          'Neither defaults, keyword-only args, annotations, nor closures'
              434  LOAD_STR                 'CallWrapper'
              436  CALL_FUNCTION_2       2  ''
              438  STORE_NAME               CallWrapper

 L.1899       440  LOAD_BUILD_CLASS 
              442  LOAD_CODE                <code_object XView>
              444  LOAD_STR                 'XView'
              446  MAKE_FUNCTION_0          'Neither defaults, keyword-only args, annotations, nor closures'
              448  LOAD_STR                 'XView'
              450  CALL_FUNCTION_2       2  ''
              452  STORE_NAME               XView

 L.1920       454  LOAD_BUILD_CLASS 
              456  LOAD_CODE                <code_object YView>
              458  LOAD_STR                 'YView'
              460  MAKE_FUNCTION_0          'Neither defaults, keyword-only args, annotations, nor closures'
              462  LOAD_STR                 'YView'
              464  CALL_FUNCTION_2       2  ''
              466  STORE_NAME               YView

 L.1941       468  LOAD_BUILD_CLASS 
              470  LOAD_CODE                <code_object Wm>
              472  LOAD_STR                 'Wm'
              474  MAKE_FUNCTION_0          'Neither defaults, keyword-only args, annotations, nor closures'
              476  LOAD_STR                 'Wm'
              478  CALL_FUNCTION_2       2  ''
              480  STORE_NAME               Wm

 L.2245       482  LOAD_BUILD_CLASS 
              484  LOAD_CODE                <code_object Tk>
              486  LOAD_STR                 'Tk'
              488  MAKE_FUNCTION_0          'Neither defaults, keyword-only args, annotations, nor closures'
              490  LOAD_STR                 'Tk'
              492  LOAD_NAME                Misc
              494  LOAD_NAME                Wm
              496  CALL_FUNCTION_4       4  ''
              498  STORE_NAME               Tk

 L.2371       500  LOAD_CONST               (None, None, 'Tk', False)
              502  LOAD_CODE                <code_object Tcl>
              504  LOAD_STR                 'Tcl'
              506  MAKE_FUNCTION_1          'default'
              508  STORE_NAME               Tcl

 L.2375       510  LOAD_BUILD_CLASS 
              512  LOAD_CODE                <code_object Pack>
              514  LOAD_STR                 'Pack'
              516  MAKE_FUNCTION_0          'Neither defaults, keyword-only args, annotations, nor closures'
              518  LOAD_STR                 'Pack'
              520  CALL_FUNCTION_2       2  ''
              522  STORE_NAME               Pack

 L.2421       524  LOAD_BUILD_CLASS 
              526  LOAD_CODE                <code_object Place>
              528  LOAD_STR                 'Place'
              530  MAKE_FUNCTION_0          'Neither defaults, keyword-only args, annotations, nor closures'
              532  LOAD_STR                 'Place'
              534  CALL_FUNCTION_2       2  ''
              536  STORE_NAME               Place

 L.2472       538  LOAD_BUILD_CLASS 
              540  LOAD_CODE                <code_object Grid>
              542  LOAD_STR                 'Grid'
              544  MAKE_FUNCTION_0          'Neither defaults, keyword-only args, annotations, nor closures'
              546  LOAD_STR                 'Grid'
              548  CALL_FUNCTION_2       2  ''
              550  STORE_NAME               Grid

 L.2527       552  LOAD_BUILD_CLASS 
              554  LOAD_CODE                <code_object BaseWidget>
              556  LOAD_STR                 'BaseWidget'
              558  MAKE_FUNCTION_0          'Neither defaults, keyword-only args, annotations, nor closures'
              560  LOAD_STR                 'BaseWidget'
              562  LOAD_NAME                Misc
              564  CALL_FUNCTION_3       3  ''
              566  STORE_NAME               BaseWidget

 L.2590       568  LOAD_BUILD_CLASS 
              570  LOAD_CODE                <code_object Widget>
              572  LOAD_STR                 'Widget'
              574  MAKE_FUNCTION_0          'Neither defaults, keyword-only args, annotations, nor closures'
              576  LOAD_STR                 'Widget'
              578  LOAD_NAME                BaseWidget
              580  LOAD_NAME                Pack
              582  LOAD_NAME                Place
              584  LOAD_NAME                Grid
              586  CALL_FUNCTION_6       6  ''
              588  STORE_NAME               Widget

 L.2598       590  LOAD_BUILD_CLASS 
              592  LOAD_CODE                <code_object Toplevel>
              594  LOAD_STR                 'Toplevel'
              596  MAKE_FUNCTION_0          'Neither defaults, keyword-only args, annotations, nor closures'
              598  LOAD_STR                 'Toplevel'
              600  LOAD_NAME                BaseWidget
              602  LOAD_NAME                Wm
              604  CALL_FUNCTION_4       4  ''
              606  STORE_NAME               Toplevel

 L.2628       608  LOAD_BUILD_CLASS 
              610  LOAD_CODE                <code_object Button>
              612  LOAD_STR                 'Button'
              614  MAKE_FUNCTION_0          'Neither defaults, keyword-only args, annotations, nor closures'
              616  LOAD_STR                 'Button'
              618  LOAD_NAME                Widget
              620  CALL_FUNCTION_3       3  ''
              622  STORE_NAME               Button

 L.2675       624  LOAD_BUILD_CLASS 
              626  LOAD_CODE                <code_object Canvas>
              628  LOAD_STR                 'Canvas'
              630  MAKE_FUNCTION_0          'Neither defaults, keyword-only args, annotations, nor closures'
              632  LOAD_STR                 'Canvas'
              634  LOAD_NAME                Widget
              636  LOAD_NAME                XView
              638  LOAD_NAME                YView
              640  CALL_FUNCTION_5       5  ''
              642  STORE_NAME               Canvas

 L.2985       644  LOAD_BUILD_CLASS 
              646  LOAD_CODE                <code_object Checkbutton>
              648  LOAD_STR                 'Checkbutton'
              650  MAKE_FUNCTION_0          'Neither defaults, keyword-only args, annotations, nor closures'
              652  LOAD_STR                 'Checkbutton'
              654  LOAD_NAME                Widget
              656  CALL_FUNCTION_3       3  ''
              658  STORE_NAME               Checkbutton

 L.3021       660  LOAD_BUILD_CLASS 
              662  LOAD_CODE                <code_object Entry>
              664  LOAD_STR                 'Entry'
              666  MAKE_FUNCTION_0          'Neither defaults, keyword-only args, annotations, nor closures'
              668  LOAD_STR                 'Entry'
              670  LOAD_NAME                Widget
              672  LOAD_NAME                XView
              674  CALL_FUNCTION_4       4  ''
              676  STORE_NAME               Entry

 L.3107       678  LOAD_BUILD_CLASS 
              680  LOAD_CODE                <code_object Frame>
              682  LOAD_STR                 'Frame'
              684  MAKE_FUNCTION_0          'Neither defaults, keyword-only args, annotations, nor closures'
              686  LOAD_STR                 'Frame'
              688  LOAD_NAME                Widget
              690  CALL_FUNCTION_3       3  ''
              692  STORE_NAME               Frame

 L.3127       694  LOAD_BUILD_CLASS 
              696  LOAD_CODE                <code_object Label>
              698  LOAD_STR                 'Label'
              700  MAKE_FUNCTION_0          'Neither defaults, keyword-only args, annotations, nor closures'
              702  LOAD_STR                 'Label'
              704  LOAD_NAME                Widget
              706  CALL_FUNCTION_3       3  ''
              708  STORE_NAME               Label

 L.3151       710  LOAD_BUILD_CLASS 
              712  LOAD_CODE                <code_object Listbox>
              714  LOAD_STR                 'Listbox'
              716  MAKE_FUNCTION_0          'Neither defaults, keyword-only args, annotations, nor closures'
              718  LOAD_STR                 'Listbox'
              720  LOAD_NAME                Widget
              722  LOAD_NAME                XView
              724  LOAD_NAME                YView
              726  CALL_FUNCTION_5       5  ''
              728  STORE_NAME               Listbox

 L.3267       730  LOAD_BUILD_CLASS 
              732  LOAD_CODE                <code_object Menu>
              734  LOAD_STR                 'Menu'
              736  MAKE_FUNCTION_0          'Neither defaults, keyword-only args, annotations, nor closures'
              738  LOAD_STR                 'Menu'
              740  LOAD_NAME                Widget
              742  CALL_FUNCTION_3       3  ''
              744  STORE_NAME               Menu

 L.3397       746  LOAD_BUILD_CLASS 
              748  LOAD_CODE                <code_object Menubutton>
              750  LOAD_STR                 'Menubutton'
              752  MAKE_FUNCTION_0          'Neither defaults, keyword-only args, annotations, nor closures'
              754  LOAD_STR                 'Menubutton'
              756  LOAD_NAME                Widget
              758  CALL_FUNCTION_3       3  ''
              760  STORE_NAME               Menubutton

 L.3404       762  LOAD_BUILD_CLASS 
              764  LOAD_CODE                <code_object Message>
              766  LOAD_STR                 'Message'
              768  MAKE_FUNCTION_0          'Neither defaults, keyword-only args, annotations, nor closures'
              770  LOAD_STR                 'Message'
              772  LOAD_NAME                Widget
              774  CALL_FUNCTION_3       3  ''
              776  STORE_NAME               Message

 L.3411       778  LOAD_BUILD_CLASS 
              780  LOAD_CODE                <code_object Radiobutton>
              782  LOAD_STR                 'Radiobutton'
              784  MAKE_FUNCTION_0          'Neither defaults, keyword-only args, annotations, nor closures'
              786  LOAD_STR                 'Radiobutton'
              788  LOAD_NAME                Widget
              790  CALL_FUNCTION_3       3  ''
              792  STORE_NAME               Radiobutton

 L.3444       794  LOAD_BUILD_CLASS 
              796  LOAD_CODE                <code_object Scale>
              798  LOAD_STR                 'Scale'
              800  MAKE_FUNCTION_0          'Neither defaults, keyword-only args, annotations, nor closures'
              802  LOAD_STR                 'Scale'
              804  LOAD_NAME                Widget
              806  CALL_FUNCTION_3       3  ''
              808  STORE_NAME               Scale

 L.3483       810  LOAD_BUILD_CLASS 
              812  LOAD_CODE                <code_object Scrollbar>
              814  LOAD_STR                 'Scrollbar'
              816  MAKE_FUNCTION_0          'Neither defaults, keyword-only args, annotations, nor closures'
              818  LOAD_STR                 'Scrollbar'
              820  LOAD_NAME                Widget
              822  CALL_FUNCTION_3       3  ''
              824  STORE_NAME               Scrollbar

 L.3533       826  LOAD_BUILD_CLASS 
              828  LOAD_CODE                <code_object Text>
              830  LOAD_STR                 'Text'
              832  MAKE_FUNCTION_0          'Neither defaults, keyword-only args, annotations, nor closures'
              834  LOAD_STR                 'Text'
              836  LOAD_NAME                Widget
              838  LOAD_NAME                XView
              840  LOAD_NAME                YView
              842  CALL_FUNCTION_5       5  ''
              844  STORE_NAME               Text

 L.3937       846  LOAD_BUILD_CLASS 
              848  LOAD_CODE                <code_object _setit>
              850  LOAD_STR                 '_setit'
              852  MAKE_FUNCTION_0          'Neither defaults, keyword-only args, annotations, nor closures'
              854  LOAD_STR                 '_setit'
              856  CALL_FUNCTION_2       2  ''
              858  STORE_NAME               _setit

 L.3951       860  LOAD_BUILD_CLASS 
              862  LOAD_CODE                <code_object OptionMenu>
              864  LOAD_STR                 'OptionMenu'
              866  MAKE_FUNCTION_0          'Neither defaults, keyword-only args, annotations, nor closures'
              868  LOAD_STR                 'OptionMenu'
              870  LOAD_NAME                Menubutton
              872  CALL_FUNCTION_3       3  ''
              874  STORE_NAME               OptionMenu

 L.3990       876  LOAD_BUILD_CLASS 
              878  LOAD_CODE                <code_object Image>
              880  LOAD_STR                 'Image'
              882  MAKE_FUNCTION_0          'Neither defaults, keyword-only args, annotations, nor closures'
              884  LOAD_STR                 'Image'
              886  CALL_FUNCTION_2       2  ''
              888  STORE_NAME               Image

 L.4056       890  LOAD_BUILD_CLASS 
              892  LOAD_CODE                <code_object PhotoImage>
              894  LOAD_STR                 'PhotoImage'
              896  MAKE_FUNCTION_0          'Neither defaults, keyword-only args, annotations, nor closures'
              898  LOAD_STR                 'PhotoImage'
              900  LOAD_NAME                Image
              902  CALL_FUNCTION_3       3  ''
              904  STORE_NAME               PhotoImage

 L.4140       906  LOAD_BUILD_CLASS 
              908  LOAD_CODE                <code_object BitmapImage>
              910  LOAD_STR                 'BitmapImage'
              912  MAKE_FUNCTION_0          'Neither defaults, keyword-only args, annotations, nor closures'
              914  LOAD_STR                 'BitmapImage'
              916  LOAD_NAME                Image
              918  CALL_FUNCTION_3       3  ''
              920  STORE_NAME               BitmapImage

 L.4150       922  LOAD_CODE                <code_object image_names>
              924  LOAD_STR                 'image_names'
              926  MAKE_FUNCTION_0          'Neither defaults, keyword-only args, annotations, nor closures'
              928  STORE_NAME               image_names

 L.4155       930  LOAD_CODE                <code_object image_types>
              932  LOAD_STR                 'image_types'
              934  MAKE_FUNCTION_0          'Neither defaults, keyword-only args, annotations, nor closures'
              936  STORE_NAME               image_types

 L.4160       938  LOAD_BUILD_CLASS 
              940  LOAD_CODE                <code_object Spinbox>
              942  LOAD_STR                 'Spinbox'
              944  MAKE_FUNCTION_0          'Neither defaults, keyword-only args, annotations, nor closures'
              946  LOAD_STR                 'Spinbox'
              948  LOAD_NAME                Widget
              950  LOAD_NAME                XView
              952  CALL_FUNCTION_4       4  ''
              954  STORE_NAME               Spinbox

 L.4338       956  LOAD_BUILD_CLASS 
              958  LOAD_CODE                <code_object LabelFrame>
              960  LOAD_STR                 'LabelFrame'
              962  MAKE_FUNCTION_0          'Neither defaults, keyword-only args, annotations, nor closures'
              964  LOAD_STR                 'LabelFrame'
              966  LOAD_NAME                Widget
              968  CALL_FUNCTION_3       3  ''
              970  STORE_NAME               LabelFrame

 L.4362       972  LOAD_BUILD_CLASS 
              974  LOAD_CODE                <code_object PanedWindow>
              976  LOAD_STR                 'PanedWindow'
              978  MAKE_FUNCTION_0          'Neither defaults, keyword-only args, annotations, nor closures'
              980  LOAD_STR                 'PanedWindow'
              982  LOAD_NAME                Widget
              984  CALL_FUNCTION_3       3  ''
              986  STORE_NAME               PanedWindow

 L.4556       988  LOAD_CODE                <code_object _test>
              990  LOAD_STR                 '_test'
              992  MAKE_FUNCTION_0          'Neither defaults, keyword-only args, annotations, nor closures'
              994  STORE_NAME               _test

 L.4577       996  LOAD_LISTCOMP            '<code_object <listcomp>>'
              998  LOAD_STR                 '<listcomp>'
             1000  MAKE_FUNCTION_0          'Neither defaults, keyword-only args, annotations, nor closures'
             1002  LOAD_NAME                globals
             1004  CALL_FUNCTION_0       0  ''
             1006  LOAD_METHOD              items
             1008  CALL_METHOD_0         0  ''
             1010  GET_ITER         
             1012  CALL_FUNCTION_1       1  ''
             1014  STORE_NAME               __all__

 L.4581      1016  LOAD_NAME                __name__
             1018  LOAD_STR                 '__main__'
             1020  COMPARE_OP               ==
         1022_1024  POP_JUMP_IF_FALSE  1032  'to 1032'

 L.4582      1026  LOAD_NAME                _test
             1028  CALL_FUNCTION_0       0  ''
             1030  POP_TOP          
           1032_0  COME_FROM          1022  '1022'

Parse error at or near `<121>' instruction at offset 164

Instruction context:
   
 L.  98       160  DUP_TOP          
                 162  LOAD_NAME                AttributeError
->               164  <121>               176  ''
                 166  POP_TOP          
                 168  POP_TOP          
                 170  POP_TOP          
                 172  POP_EXCEPT       
                 174  JUMP_FORWARD        178  'to 178'
                 176  <48>             
               178_0  COME_FROM           174  '174'
               178_1  COME_FROM           158  '158'

test/115966.pyc -- 
# decompile failed
