
# file test/129344.pyc
# --- This code section failed: ---

 L.   1         0  LOAD_CONST               0
                2  LOAD_CONST               ('FormatError', 'POINTER', 'Structure', 'WINFUNCTYPE', 'byref', 'c_long', 'c_void_p', 'oledll', 'pointer', 'windll')
                4  IMPORT_NAME              ctypes
                6  IMPORT_FROM              FormatError
                8  STORE_NAME               FormatError
               10  IMPORT_FROM              POINTER
               12  STORE_NAME               POINTER
               14  IMPORT_FROM              Structure
               16  STORE_NAME               Structure
               18  IMPORT_FROM              WINFUNCTYPE
               20  STORE_NAME               WINFUNCTYPE
               22  IMPORT_FROM              byref
               24  STORE_NAME               byref
               26  IMPORT_FROM              c_long
               28  STORE_NAME               c_long
               30  IMPORT_FROM              c_void_p
               32  STORE_NAME               c_void_p
               34  IMPORT_FROM              oledll
               36  STORE_NAME               oledll
               38  IMPORT_FROM              pointer
               40  STORE_NAME               pointer
               42  IMPORT_FROM              windll
               44  STORE_NAME               windll
               46  POP_TOP          

 L.   5        48  LOAD_CONST               0
               50  LOAD_CONST               ('CopyComPointer',)
               52  IMPORT_NAME              _ctypes
               54  IMPORT_FROM              CopyComPointer
               56  STORE_NAME               CopyComPointer
               58  POP_TOP          

 L.   6        60  LOAD_CONST               0
               62  LOAD_CONST               None
               64  IMPORT_NAME              logging
               66  STORE_NAME               logging

 L.   7        68  LOAD_CONST               0
               70  LOAD_CONST               None
               72  IMPORT_NAME              os
               74  STORE_NAME               os

 L.   9        76  LOAD_CONST               0
               78  LOAD_CONST               ('COMError', 'ReturnHRESULT', 'instancemethod', '_encode_idl')
               80  IMPORT_NAME              comtypes
               82  IMPORT_FROM              COMError
               84  STORE_NAME               COMError
               86  IMPORT_FROM              ReturnHRESULT
               88  STORE_NAME               ReturnHRESULT
               90  IMPORT_FROM              instancemethod
               92  STORE_NAME               instancemethod
               94  IMPORT_FROM              _encode_idl
               96  STORE_NAME               _encode_idl
               98  POP_TOP          

 L.  10       100  LOAD_CONST               0
              102  LOAD_CONST               ('ISupportErrorInfo', 'ReportException', 'ReportError')
              104  IMPORT_NAME_ATTR         comtypes.errorinfo
              106  IMPORT_FROM              ISupportErrorInfo
              108  STORE_NAME               ISupportErrorInfo
              110  IMPORT_FROM              ReportException
              112  STORE_NAME               ReportException
              114  IMPORT_FROM              ReportError
              116  STORE_NAME               ReportError
              118  POP_TOP          

 L.  11       120  LOAD_CONST               0
              122  LOAD_CONST               ('IPersist',)
              124  IMPORT_NAME              comtypes
              126  IMPORT_FROM              IPersist
              128  STORE_NAME               IPersist
              130  POP_TOP          

 L.  12       132  LOAD_CONST               0
              134  LOAD_CONST               ('DISP_E_BADINDEX', 'DISP_E_MEMBERNOTFOUND', 'E_FAIL', 'E_NOINTERFACE', 'E_INVALIDARG', 'E_NOTIMPL', 'RPC_E_CHANGED_MODE', 'S_FALSE', 'S_OK')
              136  IMPORT_NAME_ATTR         comtypes.hresult
              138  IMPORT_FROM              DISP_E_BADINDEX
              140  STORE_NAME               DISP_E_BADINDEX
              142  IMPORT_FROM              DISP_E_MEMBERNOTFOUND
              144  STORE_NAME               DISP_E_MEMBERNOTFOUND
              146  IMPORT_FROM              E_FAIL
              148  STORE_NAME               E_FAIL
              150  IMPORT_FROM              E_NOINTERFACE
              152  STORE_NAME               E_NOINTERFACE
              154  IMPORT_FROM              E_INVALIDARG
              156  STORE_NAME               E_INVALIDARG
              158  IMPORT_FROM              E_NOTIMPL
              160  STORE_NAME               E_NOTIMPL
              162  IMPORT_FROM              RPC_E_CHANGED_MODE
              164  STORE_NAME               RPC_E_CHANGED_MODE
              166  IMPORT_FROM              S_FALSE
              168  STORE_NAME               S_FALSE
              170  IMPORT_FROM              S_OK
              172  STORE_NAME               S_OK
              174  POP_TOP          

 L.  16       176  LOAD_CONST               0
              178  LOAD_CONST               ('IProvideClassInfo', 'IProvideClassInfo2')
              180  IMPORT_NAME_ATTR         comtypes.typeinfo
              182  IMPORT_FROM              IProvideClassInfo
              184  STORE_NAME               IProvideClassInfo
              186  IMPORT_FROM              IProvideClassInfo2
              188  STORE_NAME               IProvideClassInfo2
              190  POP_TOP          

 L.  19       192  LOAD_NAME                logging
              194  LOAD_METHOD              getLogger
              196  LOAD_NAME                __name__
              198  CALL_METHOD_1         1  ''
              200  STORE_NAME               logger

 L.  20       202  LOAD_NAME                logger
              204  LOAD_ATTR                debug
              206  STORE_NAME               _debug

 L.  21       208  LOAD_NAME                logger
              210  LOAD_ATTR                warning
              212  STORE_NAME               _warning

 L.  22       214  LOAD_NAME                logger
              216  LOAD_ATTR                error
              218  STORE_NAME               _error

 L.  28       220  LOAD_CONST               1
              222  STORE_NAME               DISPATCH_METHOD

 L.  29       224  LOAD_CONST               2
              226  STORE_NAME               DISPATCH_PROPERTYGET

 L.  30       228  LOAD_CONST               4
              230  STORE_NAME               DISPATCH_PROPERTYPUT

 L.  31       232  LOAD_CONST               8
              234  STORE_NAME               DISPATCH_PROPERTYPUTREF

 L.  34       236  LOAD_BUILD_CLASS 
              238  LOAD_CODE                <code_object E_NotImplemented>
              240  LOAD_STR                 'E_NotImplemented'
              242  MAKE_FUNCTION_0          'Neither defaults, keyword-only args, annotations, nor closures'
              244  LOAD_STR                 'E_NotImplemented'
              246  LOAD_NAME                Exception
              248  CALL_FUNCTION_3       3  ''
              250  STORE_NAME               E_NotImplemented

 L.  38       252  LOAD_CODE                <code_object HRESULT_FROM_WIN32>
              254  LOAD_STR                 'HRESULT_FROM_WIN32'
              256  MAKE_FUNCTION_0          'Neither defaults, keyword-only args, annotations, nor closures'
              258  STORE_NAME               HRESULT_FROM_WIN32

 L.  47       260  LOAD_CODE                <code_object winerror>
              262  LOAD_STR                 'winerror'
              264  MAKE_FUNCTION_0          'Neither defaults, keyword-only args, annotations, nor closures'
              266  STORE_NAME               winerror

 L.  63       268  LOAD_CODE                <code_object _do_implement>
              270  LOAD_STR                 '_do_implement'
              272  MAKE_FUNCTION_0          'Neither defaults, keyword-only args, annotations, nor closures'
              274  STORE_NAME               _do_implement

 L.  72       276  LOAD_CODE                <code_object catch_errors>
              278  LOAD_STR                 'catch_errors'
              280  MAKE_FUNCTION_0          'Neither defaults, keyword-only args, annotations, nor closures'
              282  STORE_NAME               catch_errors

 L. 108       284  LOAD_CODE                <code_object hack>
              286  LOAD_STR                 'hack'
              288  MAKE_FUNCTION_0          'Neither defaults, keyword-only args, annotations, nor closures'
              290  STORE_NAME               hack

 L. 193       292  LOAD_BUILD_CLASS 
              294  LOAD_CODE                <code_object _MethodFinder>
              296  LOAD_STR                 '_MethodFinder'
              298  MAKE_FUNCTION_0          'Neither defaults, keyword-only args, annotations, nor closures'
              300  LOAD_STR                 '_MethodFinder'
              302  LOAD_NAME                object
              304  CALL_FUNCTION_3       3  ''
              306  STORE_NAME               _MethodFinder

 L. 262       308  LOAD_CODE                <code_object _create_vtbl_type>
              310  LOAD_STR                 '_create_vtbl_type'
              312  MAKE_FUNCTION_0          'Neither defaults, keyword-only args, annotations, nor closures'
              314  STORE_NAME               _create_vtbl_type

 L. 273       316  BUILD_MAP_0           0 
              318  STORE_NAME               _vtbl_types

 L. 277       320  SETUP_FINALLY       342  'to 342'

 L. 278       322  LOAD_NAME                windll
              324  LOAD_ATTR                kernel32
              326  LOAD_ATTR                InterlockedIncrement
              328  STORE_NAME               _InterlockedIncrement

 L. 279       330  LOAD_NAME                windll
              332  LOAD_ATTR                kernel32
              334  LOAD_ATTR                InterlockedDecrement
              336  STORE_NAME               _InterlockedDecrement
              338  POP_BLOCK        
              340  JUMP_FORWARD        406  'to 406'
            342_0  COME_FROM_FINALLY   320  '320'

 L. 280       342  DUP_TOP          
              344  LOAD_NAME                AttributeError
          346_348  <121>               404  ''
              350  POP_TOP          
              352  POP_TOP          
              354  POP_TOP          

 L. 281       356  LOAD_CONST               0
              358  LOAD_CONST               None
              360  IMPORT_NAME              threading
              362  STORE_NAME               threading

 L. 282       364  LOAD_NAME                threading
              366  LOAD_METHOD              Lock
              368  CALL_METHOD_0         0  ''
              370  STORE_NAME               _lock

 L. 283       372  LOAD_NAME                _lock
              374  LOAD_ATTR                acquire
              376  STORE_NAME               _acquire

 L. 284       378  LOAD_NAME                _lock
              380  LOAD_ATTR                release
              382  STORE_NAME               _release

 L. 287       384  LOAD_CODE                <code_object _InterlockedIncrement>
              386  LOAD_STR                 '_InterlockedIncrement'
              388  MAKE_FUNCTION_0          'Neither defaults, keyword-only args, annotations, nor closures'
              390  STORE_NAME               _InterlockedIncrement

 L. 294       392  LOAD_CODE                <code_object _InterlockedDecrement>
              394  LOAD_STR                 '_InterlockedDecrement'
              396  MAKE_FUNCTION_0          'Neither defaults, keyword-only args, annotations, nor closures'
              398  STORE_NAME               _InterlockedDecrement
              400  POP_EXCEPT       
              402  JUMP_FORWARD        442  'to 442'
              404  <48>             
            406_0  COME_FROM           340  '340'

 L. 301       406  LOAD_NAME                POINTER
              408  LOAD_NAME                c_long
              410  CALL_FUNCTION_1       1  ''
              412  BUILD_LIST_1          1 
              414  LOAD_NAME                _InterlockedIncrement
              416  STORE_ATTR               argtypes

 L. 302       418  LOAD_NAME                POINTER
              420  LOAD_NAME                c_long
              422  CALL_FUNCTION_1       1  ''
              424  BUILD_LIST_1          1 
              426  LOAD_NAME                _InterlockedDecrement
              428  STORE_ATTR               argtypes

 L. 303       430  LOAD_NAME                c_long
              432  LOAD_NAME                _InterlockedIncrement
              434  STORE_ATTR               restype

 L. 304       436  LOAD_NAME                c_long
              438  LOAD_NAME                _InterlockedDecrement
              440  STORE_ATTR               restype
            442_0  COME_FROM           402  '402'

 L. 307       442  LOAD_BUILD_CLASS 
              444  LOAD_CODE                <code_object LocalServer>
              446  LOAD_STR                 'LocalServer'
              448  MAKE_FUNCTION_0          'Neither defaults, keyword-only args, annotations, nor closures'
              450  LOAD_STR                 'LocalServer'
              452  LOAD_NAME                object
              454  CALL_FUNCTION_3       3  ''
              456  STORE_NAME               LocalServer

 L. 352       458  LOAD_BUILD_CLASS 
              460  LOAD_CODE                <code_object InprocServer>
              462  LOAD_STR                 'InprocServer'
              464  MAKE_FUNCTION_0          'Neither defaults, keyword-only args, annotations, nor closures'
              466  LOAD_STR                 'InprocServer'
              468  LOAD_NAME                object
              470  CALL_FUNCTION_3       3  ''
              472  STORE_NAME               InprocServer

 L. 371       474  LOAD_BUILD_CLASS 
              476  LOAD_CODE                <code_object COMObject>
              478  LOAD_STR                 'COMObject'
              480  MAKE_FUNCTION_0          'Neither defaults, keyword-only args, annotations, nor closures'
              482  LOAD_STR                 'COMObject'
              484  LOAD_NAME                object
              486  CALL_FUNCTION_3       3  ''
              488  STORE_NAME               COMObject

 L. 771       490  LOAD_STR                 'COMObject'
              492  BUILD_LIST_1          1 
              494  STORE_NAME               __all__

Parse error at or near `<121>' instruction at offset 346_348

Instruction context:
   
 L. 280       342  DUP_TOP          
                 344  LOAD_NAME                AttributeError
->           346_348  <121>               404  ''
                 350  POP_TOP          
                 352  POP_TOP          
                 354  POP_TOP          

test/129344.pyc -- 
# decompile failed
