
# file test/129788.pyc
# --- This code section failed: ---

 L.   1         0  LOAD_STR                 'setuptools.command.bdist_egg\n\nBuild .egg distributions'
                2  STORE_NAME               __doc__

 L.   5         4  LOAD_CONST               0
                6  LOAD_CONST               ('DistutilsSetupError',)
                8  IMPORT_NAME_ATTR         distutils.errors
               10  IMPORT_FROM              DistutilsSetupError
               12  STORE_NAME               DistutilsSetupError
               14  POP_TOP          

 L.   6        16  LOAD_CONST               0
               18  LOAD_CONST               ('remove_tree', 'mkpath')
               20  IMPORT_NAME_ATTR         distutils.dir_util
               22  IMPORT_FROM              remove_tree
               24  STORE_NAME               remove_tree
               26  IMPORT_FROM              mkpath
               28  STORE_NAME               mkpath
               30  POP_TOP          

 L.   7        32  LOAD_CONST               0
               34  LOAD_CONST               ('log',)
               36  IMPORT_NAME              distutils
               38  IMPORT_FROM              log
               40  STORE_NAME               log
               42  POP_TOP          

 L.   8        44  LOAD_CONST               0
               46  LOAD_CONST               ('CodeType',)
               48  IMPORT_NAME              types
               50  IMPORT_FROM              CodeType
               52  STORE_NAME               CodeType
               54  POP_TOP          

 L.   9        56  LOAD_CONST               0
               58  LOAD_CONST               None
               60  IMPORT_NAME              sys
               62  STORE_NAME               sys

 L.  10        64  LOAD_CONST               0
               66  LOAD_CONST               None
               68  IMPORT_NAME              os
               70  STORE_NAME               os

 L.  11        72  LOAD_CONST               0
               74  LOAD_CONST               None
               76  IMPORT_NAME              re
               78  STORE_NAME               re

 L.  12        80  LOAD_CONST               0
               82  LOAD_CONST               None
               84  IMPORT_NAME              textwrap
               86  STORE_NAME               textwrap

 L.  13        88  LOAD_CONST               0
               90  LOAD_CONST               None
               92  IMPORT_NAME              marshal
               94  STORE_NAME               marshal

 L.  14        96  LOAD_CONST               0
               98  LOAD_CONST               None
              100  IMPORT_NAME              warnings
              102  STORE_NAME               warnings

 L.  16       104  LOAD_CONST               0
              106  LOAD_CONST               ('six',)
              108  IMPORT_NAME_ATTR         setuptools.extern
              110  IMPORT_FROM              six
              112  STORE_NAME               six
              114  POP_TOP          

 L.  18       116  LOAD_CONST               0
              118  LOAD_CONST               ('get_build_platform', 'Distribution', 'ensure_directory')
              120  IMPORT_NAME              pkg_resources
              122  IMPORT_FROM              get_build_platform
              124  STORE_NAME               get_build_platform
              126  IMPORT_FROM              Distribution
              128  STORE_NAME               Distribution
              130  IMPORT_FROM              ensure_directory
              132  STORE_NAME               ensure_directory
              134  POP_TOP          

 L.  19       136  LOAD_CONST               0
              138  LOAD_CONST               ('EntryPoint',)
              140  IMPORT_NAME              pkg_resources
              142  IMPORT_FROM              EntryPoint
              144  STORE_NAME               EntryPoint
              146  POP_TOP          

 L.  20       148  LOAD_CONST               0
              150  LOAD_CONST               ('Library',)
              152  IMPORT_NAME_ATTR         setuptools.extension
              154  IMPORT_FROM              Library
              156  STORE_NAME               Library
              158  POP_TOP          

 L.  21       160  LOAD_CONST               0
              162  LOAD_CONST               ('Command', 'SetuptoolsDeprecationWarning')
              164  IMPORT_NAME              setuptools
              166  IMPORT_FROM              Command
              168  STORE_NAME               Command
              170  IMPORT_FROM              SetuptoolsDeprecationWarning
              172  STORE_NAME               SetuptoolsDeprecationWarning
              174  POP_TOP          

 L.  23       176  SETUP_FINALLY       206  'to 206'

 L.  25       178  LOAD_CONST               0
              180  LOAD_CONST               ('get_path', 'get_python_version')
              182  IMPORT_NAME              sysconfig
              184  IMPORT_FROM              get_path
              186  STORE_NAME               get_path
              188  IMPORT_FROM              get_python_version
              190  STORE_NAME               get_python_version
              192  POP_TOP          

 L.  27       194  LOAD_CODE                <code_object _get_purelib>
              196  LOAD_STR                 '_get_purelib'
              198  MAKE_FUNCTION_0          'Neither defaults, keyword-only args, annotations, nor closures'
              200  STORE_NAME               _get_purelib
              202  POP_BLOCK        
              204  JUMP_FORWARD        248  'to 248'
            206_0  COME_FROM_FINALLY   176  '176'

 L.  29       206  DUP_TOP          
              208  LOAD_NAME                ImportError
              210  <121>               246  ''
              212  POP_TOP          
              214  POP_TOP          
              216  POP_TOP          

 L.  30       218  LOAD_CONST               0
              220  LOAD_CONST               ('get_python_lib', 'get_python_version')
              222  IMPORT_NAME_ATTR         distutils.sysconfig
              224  IMPORT_FROM              get_python_lib
              226  STORE_NAME               get_python_lib
              228  IMPORT_FROM              get_python_version
              230  STORE_NAME               get_python_version
              232  POP_TOP          

 L.  32       234  LOAD_CODE                <code_object _get_purelib>
              236  LOAD_STR                 '_get_purelib'
              238  MAKE_FUNCTION_0          'Neither defaults, keyword-only args, annotations, nor closures'
              240  STORE_NAME               _get_purelib
              242  POP_EXCEPT       
              244  JUMP_FORWARD        248  'to 248'
              246  <48>             
            248_0  COME_FROM           244  '244'
            248_1  COME_FROM           204  '204'

 L.  36       248  LOAD_CODE                <code_object strip_module>
              250  LOAD_STR                 'strip_module'
              252  MAKE_FUNCTION_0          'Neither defaults, keyword-only args, annotations, nor closures'
              254  STORE_NAME               strip_module

 L.  44       256  LOAD_CODE                <code_object sorted_walk>
              258  LOAD_STR                 'sorted_walk'
              260  MAKE_FUNCTION_0          'Neither defaults, keyword-only args, annotations, nor closures'
              262  STORE_NAME               sorted_walk

 L.  54       264  LOAD_CODE                <code_object write_stub>
              266  LOAD_STR                 'write_stub'
              268  MAKE_FUNCTION_0          'Neither defaults, keyword-only args, annotations, nor closures'
              270  STORE_NAME               write_stub

 L.  69       272  LOAD_BUILD_CLASS 
              274  LOAD_CODE                <code_object bdist_egg>
              276  LOAD_STR                 'bdist_egg'
              278  MAKE_FUNCTION_0          'Neither defaults, keyword-only args, annotations, nor closures'
              280  LOAD_STR                 'bdist_egg'
              282  LOAD_NAME                Command
              284  CALL_FUNCTION_3       3  ''
              286  STORE_NAME               bdist_egg

 L. 363       288  LOAD_NAME                dict
              290  LOAD_METHOD              fromkeys
              292  LOAD_STR                 '.dll .so .dylib .pyd'
              294  LOAD_METHOD              split
              296  CALL_METHOD_0         0  ''
              298  CALL_METHOD_1         1  ''
              300  STORE_NAME               NATIVE_EXTENSIONS

 L. 366       302  LOAD_CODE                <code_object walk_egg>
              304  LOAD_STR                 'walk_egg'
              306  MAKE_FUNCTION_0          'Neither defaults, keyword-only args, annotations, nor closures'
              308  STORE_NAME               walk_egg

 L. 377       310  LOAD_CODE                <code_object analyze_egg>
              312  LOAD_STR                 'analyze_egg'
              314  MAKE_FUNCTION_0          'Neither defaults, keyword-only args, annotations, nor closures'
              316  STORE_NAME               analyze_egg

 L. 395       318  LOAD_CODE                <code_object write_safety_flag>
              320  LOAD_STR                 'write_safety_flag'
              322  MAKE_FUNCTION_0          'Neither defaults, keyword-only args, annotations, nor closures'
              324  STORE_NAME               write_safety_flag

 L. 409       326  LOAD_STR                 'zip-safe'

 L. 410       328  LOAD_STR                 'not-zip-safe'

 L. 408       330  LOAD_CONST               (True, False)
              332  BUILD_CONST_KEY_MAP_2     2 
              334  STORE_NAME               safety_flags

 L. 414       336  LOAD_CODE                <code_object scan_module>
              338  LOAD_STR                 'scan_module'
              340  MAKE_FUNCTION_0          'Neither defaults, keyword-only args, annotations, nor closures'
              342  STORE_NAME               scan_module

 L. 450       344  LOAD_CODE                <code_object iter_symbols>
              346  LOAD_STR                 'iter_symbols'
              348  MAKE_FUNCTION_0          'Neither defaults, keyword-only args, annotations, nor closures'
              350  STORE_NAME               iter_symbols

 L. 462       352  LOAD_CODE                <code_object can_scan>
              354  LOAD_STR                 'can_scan'
              356  MAKE_FUNCTION_0          'Neither defaults, keyword-only args, annotations, nor closures'
              358  STORE_NAME               can_scan

 L. 474       360  BUILD_LIST_0          0 
              362  LOAD_CONST               ('install_lib', 'install_dir', 'install_data', 'install_base')
              364  CALL_FINALLY        367  'to 367'
              366  STORE_NAME               INSTALL_DIRECTORY_ATTRS

 L. 479       368  LOAD_CONST               (0, 0, True, 'w')
              370  LOAD_CODE                <code_object make_zipfile>
              372  LOAD_STR                 'make_zipfile'
              374  MAKE_FUNCTION_1          'default'
              376  STORE_NAME               make_zipfile

Parse error at or near `<121>' instruction at offset 210

Instruction context:
   
 L.  29       206  DUP_TOP          
                 208  LOAD_NAME                ImportError
->               210  <121>               246  ''
                 212  POP_TOP          
                 214  POP_TOP          
                 216  POP_TOP          

test/129788.pyc -- 
# decompile failed
