
# file test/134358.pyc
# --- This code section failed: ---

 L.   1         0  SETUP_ANNOTATIONS
                2  LOAD_STR                 '3.7.4.post0'
                4  STORE_NAME               __version__

 L.   3         6  LOAD_CONST               0
                8  LOAD_CONST               ('Tuple',)
               10  IMPORT_NAME              typing
               12  IMPORT_FROM              Tuple
               14  STORE_NAME               Tuple
               16  POP_TOP          

 L.   5        18  LOAD_CONST               1
               20  LOAD_CONST               ('hdrs',)
               22  IMPORT_NAME              
               24  IMPORT_FROM              hdrs
               26  STORE_NAME               hdrs
               28  POP_TOP          

 L.   6        30  LOAD_CONST               1
               32  LOAD_CONST               ('BaseConnector', 'ClientConnectionError', 'ClientConnectorCertificateError', 'ClientConnectorError', 'ClientConnectorSSLError', 'ClientError', 'ClientHttpProxyError', 'ClientOSError', 'ClientPayloadError', 'ClientProxyConnectionError', 'ClientRequest', 'ClientResponse', 'ClientResponseError', 'ClientSession', 'ClientSSLError', 'ClientTimeout', 'ClientWebSocketResponse', 'ContentTypeError', 'Fingerprint', 'InvalidURL', 'NamedPipeConnector', 'RequestInfo', 'ServerConnectionError', 'ServerDisconnectedError', 'ServerFingerprintMismatch', 'ServerTimeoutError', 'TCPConnector', 'TooManyRedirects', 'UnixConnector', 'WSServerHandshakeError', 'request')
               34  IMPORT_NAME              client
               36  IMPORT_FROM              BaseConnector
               38  STORE_NAME               BaseConnector
               40  IMPORT_FROM              ClientConnectionError
               42  STORE_NAME               ClientConnectionError
               44  IMPORT_FROM              ClientConnectorCertificateError
               46  STORE_NAME               ClientConnectorCertificateError
               48  IMPORT_FROM              ClientConnectorError
               50  STORE_NAME               ClientConnectorError
               52  IMPORT_FROM              ClientConnectorSSLError
               54  STORE_NAME               ClientConnectorSSLError
               56  IMPORT_FROM              ClientError
               58  STORE_NAME               ClientError
               60  IMPORT_FROM              ClientHttpProxyError
               62  STORE_NAME               ClientHttpProxyError
               64  IMPORT_FROM              ClientOSError
               66  STORE_NAME               ClientOSError
               68  IMPORT_FROM              ClientPayloadError
               70  STORE_NAME               ClientPayloadError
               72  IMPORT_FROM              ClientProxyConnectionError
               74  STORE_NAME               ClientProxyConnectionError
               76  IMPORT_FROM              ClientRequest
               78  STORE_NAME               ClientRequest
               80  IMPORT_FROM              ClientResponse
               82  STORE_NAME               ClientResponse
               84  IMPORT_FROM              ClientResponseError
               86  STORE_NAME               ClientResponseError
               88  IMPORT_FROM              ClientSession
               90  STORE_NAME               ClientSession
               92  IMPORT_FROM              ClientSSLError
               94  STORE_NAME               ClientSSLError
               96  IMPORT_FROM              ClientTimeout
               98  STORE_NAME               ClientTimeout
              100  IMPORT_FROM              ClientWebSocketResponse
              102  STORE_NAME               ClientWebSocketResponse
              104  IMPORT_FROM              ContentTypeError
              106  STORE_NAME               ContentTypeError
              108  IMPORT_FROM              Fingerprint
              110  STORE_NAME               Fingerprint
              112  IMPORT_FROM              InvalidURL
              114  STORE_NAME               InvalidURL
              116  IMPORT_FROM              NamedPipeConnector
              118  STORE_NAME               NamedPipeConnector
              120  IMPORT_FROM              RequestInfo
              122  STORE_NAME               RequestInfo
              124  IMPORT_FROM              ServerConnectionError
              126  STORE_NAME               ServerConnectionError
              128  IMPORT_FROM              ServerDisconnectedError
              130  STORE_NAME               ServerDisconnectedError
              132  IMPORT_FROM              ServerFingerprintMismatch
              134  STORE_NAME               ServerFingerprintMismatch
              136  IMPORT_FROM              ServerTimeoutError
              138  STORE_NAME               ServerTimeoutError
              140  IMPORT_FROM              TCPConnector
              142  STORE_NAME               TCPConnector
              144  IMPORT_FROM              TooManyRedirects
              146  STORE_NAME               TooManyRedirects
              148  IMPORT_FROM              UnixConnector
              150  STORE_NAME               UnixConnector
              152  IMPORT_FROM              WSServerHandshakeError
              154  STORE_NAME               WSServerHandshakeError
              156  IMPORT_FROM              request
              158  STORE_NAME               request
              160  POP_TOP          

 L.  39       162  LOAD_CONST               1
              164  LOAD_CONST               ('CookieJar', 'DummyCookieJar')
              166  IMPORT_NAME              cookiejar
              168  IMPORT_FROM              CookieJar
              170  STORE_NAME               CookieJar
              172  IMPORT_FROM              DummyCookieJar
              174  STORE_NAME               DummyCookieJar
              176  POP_TOP          

 L.  40       178  LOAD_CONST               1
              180  LOAD_CONST               ('FormData',)
              182  IMPORT_NAME              formdata
              184  IMPORT_FROM              FormData
              186  STORE_NAME               FormData
              188  POP_TOP          

 L.  41       190  LOAD_CONST               1
              192  LOAD_CONST               ('BasicAuth', 'ChainMapProxy')
              194  IMPORT_NAME              helpers
              196  IMPORT_FROM              BasicAuth
              198  STORE_NAME               BasicAuth
              200  IMPORT_FROM              ChainMapProxy
              202  STORE_NAME               ChainMapProxy
              204  POP_TOP          

 L.  42       206  LOAD_CONST               1
              208  LOAD_CONST               ('HttpVersion', 'HttpVersion10', 'HttpVersion11', 'WebSocketError', 'WSCloseCode', 'WSMessage', 'WSMsgType')
              210  IMPORT_NAME              http
              212  IMPORT_FROM              HttpVersion
              214  STORE_NAME               HttpVersion
              216  IMPORT_FROM              HttpVersion10
              218  STORE_NAME               HttpVersion10
              220  IMPORT_FROM              HttpVersion11
              222  STORE_NAME               HttpVersion11
              224  IMPORT_FROM              WebSocketError
              226  STORE_NAME               WebSocketError
              228  IMPORT_FROM              WSCloseCode
              230  STORE_NAME               WSCloseCode
              232  IMPORT_FROM              WSMessage
              234  STORE_NAME               WSMessage
              236  IMPORT_FROM              WSMsgType
              238  STORE_NAME               WSMsgType
              240  POP_TOP          

 L.  51       242  LOAD_CONST               1
              244  LOAD_CONST               ('BadContentDispositionHeader', 'BadContentDispositionParam', 'BodyPartReader', 'MultipartReader', 'MultipartWriter', 'content_disposition_filename', 'parse_content_disposition')
              246  IMPORT_NAME              multipart
              248  IMPORT_FROM              BadContentDispositionHeader
              250  STORE_NAME               BadContentDispositionHeader
              252  IMPORT_FROM              BadContentDispositionParam
              254  STORE_NAME               BadContentDispositionParam
              256  IMPORT_FROM              BodyPartReader
              258  STORE_NAME               BodyPartReader
              260  IMPORT_FROM              MultipartReader
              262  STORE_NAME               MultipartReader
              264  IMPORT_FROM              MultipartWriter
              266  STORE_NAME               MultipartWriter
              268  IMPORT_FROM              content_disposition_filename
              270  STORE_NAME               content_disposition_filename
              272  IMPORT_FROM              parse_content_disposition
              274  STORE_NAME               parse_content_disposition
              276  POP_TOP          

 L.  60       278  LOAD_CONST               1
              280  LOAD_CONST               ('PAYLOAD_REGISTRY', 'AsyncIterablePayload', 'BufferedReaderPayload', 'BytesIOPayload', 'BytesPayload', 'IOBasePayload', 'JsonPayload', 'Payload', 'StringIOPayload', 'StringPayload', 'TextIOPayload', 'get_payload', 'payload_type')
              282  IMPORT_NAME              payload
              284  IMPORT_FROM              PAYLOAD_REGISTRY
              286  STORE_NAME               PAYLOAD_REGISTRY
              288  IMPORT_FROM              AsyncIterablePayload
              290  STORE_NAME               AsyncIterablePayload
              292  IMPORT_FROM              BufferedReaderPayload
              294  STORE_NAME               BufferedReaderPayload
              296  IMPORT_FROM              BytesIOPayload
              298  STORE_NAME               BytesIOPayload
              300  IMPORT_FROM              BytesPayload
              302  STORE_NAME               BytesPayload
              304  IMPORT_FROM              IOBasePayload
              306  STORE_NAME               IOBasePayload
              308  IMPORT_FROM              JsonPayload
              310  STORE_NAME               JsonPayload
              312  IMPORT_FROM              Payload
              314  STORE_NAME               Payload
              316  IMPORT_FROM              StringIOPayload
              318  STORE_NAME               StringIOPayload
              320  IMPORT_FROM              StringPayload
              322  STORE_NAME               StringPayload
              324  IMPORT_FROM              TextIOPayload
              326  STORE_NAME               TextIOPayload
              328  IMPORT_FROM              get_payload
              330  STORE_NAME               get_payload
              332  IMPORT_FROM              payload_type
              334  STORE_NAME               payload_type
              336  POP_TOP          

 L.  75       338  LOAD_CONST               1
              340  LOAD_CONST               ('streamer',)
              342  IMPORT_NAME              payload_streamer
              344  IMPORT_FROM              streamer
              346  STORE_NAME               streamer
              348  POP_TOP          

 L.  76       350  LOAD_CONST               1
              352  LOAD_CONST               ('AsyncResolver', 'DefaultResolver', 'ThreadedResolver')
              354  IMPORT_NAME              resolver
              356  IMPORT_FROM              AsyncResolver
              358  STORE_NAME               AsyncResolver
              360  IMPORT_FROM              DefaultResolver
              362  STORE_NAME               DefaultResolver
              364  IMPORT_FROM              ThreadedResolver
              366  STORE_NAME               ThreadedResolver
              368  POP_TOP          

 L.  81       370  LOAD_CONST               1
              372  LOAD_CONST               ('Signal',)
              374  IMPORT_NAME              signals
              376  IMPORT_FROM              Signal
              378  STORE_NAME               Signal
              380  POP_TOP          

 L.  82       382  LOAD_CONST               1
              384  LOAD_CONST               ('EMPTY_PAYLOAD', 'DataQueue', 'EofStream', 'FlowControlDataQueue', 'StreamReader')
              386  IMPORT_NAME              streams
              388  IMPORT_FROM              EMPTY_PAYLOAD
              390  STORE_NAME               EMPTY_PAYLOAD
              392  IMPORT_FROM              DataQueue
              394  STORE_NAME               DataQueue
              396  IMPORT_FROM              EofStream
              398  STORE_NAME               EofStream
              400  IMPORT_FROM              FlowControlDataQueue
              402  STORE_NAME               FlowControlDataQueue
              404  IMPORT_FROM              StreamReader
              406  STORE_NAME               StreamReader
              408  POP_TOP          

 L.  89       410  LOAD_CONST               1
              412  LOAD_CONST               ('TraceConfig', 'TraceConnectionCreateEndParams', 'TraceConnectionCreateStartParams', 'TraceConnectionQueuedEndParams', 'TraceConnectionQueuedStartParams', 'TraceConnectionReuseconnParams', 'TraceDnsCacheHitParams', 'TraceDnsCacheMissParams', 'TraceDnsResolveHostEndParams', 'TraceDnsResolveHostStartParams', 'TraceRequestChunkSentParams', 'TraceRequestEndParams', 'TraceRequestExceptionParams', 'TraceRequestRedirectParams', 'TraceRequestStartParams', 'TraceResponseChunkReceivedParams')
              414  IMPORT_NAME              tracing
              416  IMPORT_FROM              TraceConfig
              418  STORE_NAME               TraceConfig
              420  IMPORT_FROM              TraceConnectionCreateEndParams
              422  STORE_NAME               TraceConnectionCreateEndParams
              424  IMPORT_FROM              TraceConnectionCreateStartParams
              426  STORE_NAME               TraceConnectionCreateStartParams
              428  IMPORT_FROM              TraceConnectionQueuedEndParams
              430  STORE_NAME               TraceConnectionQueuedEndParams
              432  IMPORT_FROM              TraceConnectionQueuedStartParams
              434  STORE_NAME               TraceConnectionQueuedStartParams
              436  IMPORT_FROM              TraceConnectionReuseconnParams
              438  STORE_NAME               TraceConnectionReuseconnParams
              440  IMPORT_FROM              TraceDnsCacheHitParams
              442  STORE_NAME               TraceDnsCacheHitParams
              444  IMPORT_FROM              TraceDnsCacheMissParams
              446  STORE_NAME               TraceDnsCacheMissParams
              448  IMPORT_FROM              TraceDnsResolveHostEndParams
              450  STORE_NAME               TraceDnsResolveHostEndParams
              452  IMPORT_FROM              TraceDnsResolveHostStartParams
              454  STORE_NAME               TraceDnsResolveHostStartParams
              456  IMPORT_FROM              TraceRequestChunkSentParams
              458  STORE_NAME               TraceRequestChunkSentParams
              460  IMPORT_FROM              TraceRequestEndParams
              462  STORE_NAME               TraceRequestEndParams
              464  IMPORT_FROM              TraceRequestExceptionParams
              466  STORE_NAME               TraceRequestExceptionParams
              468  IMPORT_FROM              TraceRequestRedirectParams
              470  STORE_NAME               TraceRequestRedirectParams
              472  IMPORT_FROM              TraceRequestStartParams
              474  STORE_NAME               TraceRequestStartParams
              476  IMPORT_FROM              TraceResponseChunkReceivedParams
              478  STORE_NAME               TraceResponseChunkReceivedParams
              480  POP_TOP          

 L. 108       482  LOAD_CONST               ('hdrs', 'BaseConnector', 'ClientConnectionError', 'ClientConnectorCertificateError', 'ClientConnectorError', 'ClientConnectorSSLError', 'ClientError', 'ClientHttpProxyError', 'ClientOSError', 'ClientPayloadError', 'ClientProxyConnectionError', 'ClientResponse', 'ClientRequest', 'ClientResponseError', 'ClientSSLError', 'ClientSession', 'ClientTimeout', 'ClientWebSocketResponse', 'ContentTypeError', 'Fingerprint', 'InvalidURL', 'RequestInfo', 'ServerConnectionError', 'ServerDisconnectedError', 'ServerFingerprintMismatch', 'ServerTimeoutError', 'TCPConnector', 'TooManyRedirects', 'UnixConnector', 'NamedPipeConnector', 'WSServerHandshakeError', 'request', 'CookieJar', 'DummyCookieJar', 'FormData', 'BasicAuth', 'ChainMapProxy', 'HttpVersion', 'HttpVersion10', 'HttpVersion11', 'WSMsgType', 'WSCloseCode', 'WSMessage', 'WebSocketError', 'BadContentDispositionHeader', 'BadContentDispositionParam', 'BodyPartReader', 'MultipartReader', 'MultipartWriter', 'content_disposition_filename', 'parse_content_disposition', 'AsyncIterablePayload', 'BufferedReaderPayload', 'BytesIOPayload', 'BytesPayload', 'IOBasePayload', 'JsonPayload', 'PAYLOAD_REGISTRY', 'Payload', 'StringIOPayload', 'StringPayload', 'TextIOPayload', 'get_payload', 'payload_type', 'streamer', 'AsyncResolver', 'DefaultResolver', 'ThreadedResolver', 'Signal', 'DataQueue', 'EMPTY_PAYLOAD', 'EofStream', 'FlowControlDataQueue', 'StreamReader', 'TraceConfig', 'TraceConnectionCreateEndParams', 'TraceConnectionCreateStartParams', 'TraceConnectionQueuedEndParams', 'TraceConnectionQueuedStartParams', 'TraceConnectionReuseconnParams', 'TraceDnsCacheHitParams', 'TraceDnsCacheMissParams', 'TraceDnsResolveHostEndParams', 'TraceDnsResolveHostStartParams', 'TraceRequestChunkSentParams', 'TraceRequestEndParams', 'TraceRequestExceptionParams', 'TraceRequestRedirectParams', 'TraceRequestStartParams', 'TraceResponseChunkReceivedParams')
              484  STORE_NAME               __all__
              486  LOAD_NAME                Tuple
              488  LOAD_NAME                str
              490  LOAD_CONST               Ellipsis
              492  BUILD_TUPLE_2         2 
              494  BINARY_SUBSCR    
              496  LOAD_ANNOTATION          __annotations__
              498  LOAD_STR                 '__all__'
              500  STORE_SUBSCR     

 L. 212       502  SETUP_FINALLY       532  'to 532'

 L. 213       504  LOAD_CONST               1
              506  LOAD_CONST               ('GunicornUVLoopWebWorker', 'GunicornWebWorker')
              508  IMPORT_NAME              worker
              510  IMPORT_FROM              GunicornUVLoopWebWorker
              512  STORE_NAME               GunicornUVLoopWebWorker
              514  IMPORT_FROM              GunicornWebWorker
              516  STORE_NAME               GunicornWebWorker
              518  POP_TOP          

 L. 215       520  LOAD_NAME                __all__
              522  LOAD_CONST               ('GunicornWebWorker', 'GunicornUVLoopWebWorker')
              524  INPLACE_ADD      
              526  STORE_NAME               __all__
              528  POP_BLOCK        
              530  JUMP_FORWARD        552  'to 552'
            532_0  COME_FROM_FINALLY   502  '502'

 L. 216       532  DUP_TOP          
              534  LOAD_NAME                ImportError
          536_538  <121>               550  ''
              540  POP_TOP          
              542  POP_TOP          
              544  POP_TOP          

 L. 217       546  POP_EXCEPT       
              548  JUMP_FORWARD        552  'to 552'
              550  <48>             
            552_0  COME_FROM           548  '548'
            552_1  COME_FROM           530  '530'

Parse error at or near `<121>' instruction at offset 536_538

Instruction context:
   
 L. 216       532  DUP_TOP          
                 534  LOAD_NAME                ImportError
->           536_538  <121>               550  ''
                 540  POP_TOP          
                 542  POP_TOP          
                 544  POP_TOP          

test/134358.pyc -- 
# decompile failed
