Instruction context:
   
 L. 110        50  LOAD_FAST                'factory'
                  52  LOAD_FAST                'data'
                  54  BUILD_LIST_1          1 
                  56  LOAD_FAST                'args'
->                58  CALL_FINALLY         61  'to 61'
                  60  WITH_CLEANUP_FINISH
                  62  BUILD_MAP_0           0 
                  64  LOAD_FAST                'kwargs'
                  66  <164>                 1  ''
                  68  CALL_FUNCTION_EX_KW     1  'keyword and positional arguments'
                  70  ROT_TWO          
                  72  POP_TOP          
                  74  RETURN_VALUE     
                  76  JUMP_BACK            32  'to 32'
Instruction context:
   
 L. 147        26  LOAD_FAST                'content_type'
                  28  LOAD_GLOBAL              sentinel
->                30  <117>                 1  ''
                  32  POP_JUMP_IF_FALSE    56  'to 56'
                  34  LOAD_FAST                'content_type'
                  36  LOAD_CONST               None
                  38  <117>                 1  ''
                  40  POP_JUMP_IF_FALSE    56  'to 56'
Instruction context:
-> 
 L. 196        14  <164>                 1  ''
                  16  CALL_FUNCTION_EX_KW     1  'keyword and positional arguments'
                  18  LOAD_FAST                'self'
                  20  LOAD_ATTR                _headers
                  22  LOAD_GLOBAL              hdrs
                  24  LOAD_ATTR                CONTENT_DISPOSITION
Instruction context:
   
 L. 215        34  LOAD_STR                 'content_type'
                  36  LOAD_FAST                'kwargs'
->                38  <118>                 1  ''
                  40  POP_JUMP_IF_FALSE    50  'to 50'
Instruction context:
-> 
 L. 299        82  LOAD_FAST                'loop'
                  84  LOAD_METHOD              run_in_executor
                  86  LOAD_CONST               None
                  88  LOAD_FAST                'self'
                  90  LOAD_ATTR                _value
                  92  LOAD_ATTR                close
                  94  CALL_METHOD_2         2  ''
                  96  GET_AWAITABLE    
                  98  LOAD_CONST               None
                 100  YIELD_FROM       
                 102  POP_TOP          
                 104  JUMP_FORWARD        130  'to 130'
               106_0  COME_FROM_FINALLY     8  '8'
                 106  LOAD_FAST                'loop'
                 108  LOAD_METHOD              run_in_executor
                 110  LOAD_CONST               None
                 112  LOAD_FAST                'self'
                 114  LOAD_ATTR                _value
                 116  LOAD_ATTR                close
                 118  CALL_METHOD_2         2  ''
                 120  GET_AWAITABLE    
                 122  LOAD_CONST               None
                 124  YIELD_FROM       
                 126  POP_TOP          
                 128  <48>             
Instruction context:
   
 L. 335        32  DUP_TOP          
                  34  LOAD_GLOBAL              OSError
->                36  <121>                50  ''
                  38  POP_TOP          
                  40  POP_TOP          
                  42  POP_TOP          
Instruction context:
-> 
 L. 346        90  LOAD_FAST                'loop'
                  92  LOAD_METHOD              run_in_executor
                  94  LOAD_CONST               None
                  96  LOAD_FAST                'self'
                  98  LOAD_ATTR                _value
                 100  LOAD_ATTR                close
                 102  CALL_METHOD_2         2  ''
                 104  GET_AWAITABLE    
                 106  LOAD_CONST               None
                 108  YIELD_FROM       
                 110  POP_TOP          
                 112  JUMP_FORWARD        138  'to 138'
               114_0  COME_FROM_FINALLY     8  '8'
                 114  LOAD_FAST                'loop'
                 116  LOAD_METHOD              run_in_executor
                 118  LOAD_CONST               None
                 120  LOAD_FAST                'self'
                 122  LOAD_ATTR                _value
                 124  LOAD_ATTR                close
                 126  CALL_METHOD_2         2  ''
                 128  GET_AWAITABLE    
                 130  LOAD_CONST               None
                 132  YIELD_FROM       
                 134  POP_TOP          
                 136  <48>             
Instruction context:
   
 L. 363        32  DUP_TOP          
                  34  LOAD_GLOBAL              OSError
->                36  <121>                50  ''
                  38  POP_TOP          
                  40  POP_TOP          
                  42  POP_TOP          
Instruction context:
-> 
 L. 380        22  CALL_FINALLY         25  'to 25'
                  24  WITH_CLEANUP_FINISH
Instruction context:
   
 L. 413        28  LOAD_STR                 'content_type'
                  30  LOAD_FAST                'kwargs'
->                32  <118>                 1  ''
                  34  POP_JUMP_IF_FALSE    44  'to 44'
Instruction context:
   
 L. 428        46  DUP_TOP          
                  48  LOAD_GLOBAL              StopAsyncIteration
->                50  <121>                68  ''
                  52  POP_TOP          
                  54  POP_TOP          
                  56  POP_TOP          

test/134335.pyc -- 
# decompile failed

# file test/134335.pyc
# Deparsing stopped due to parse error
