
# file test/134401.pyc
# --- This code section failed: ---

 L.   1         0  LOAD_CONST               0
                2  LOAD_CONST               ('absolute_import', 'division', 'print_function')
                4  IMPORT_NAME              __future__
                6  IMPORT_FROM              absolute_import
                8  STORE_NAME               absolute_import
               10  IMPORT_FROM              division
               12  STORE_NAME               division
               14  IMPORT_FROM              print_function
               16  STORE_NAME               print_function
               18  POP_TOP          

 L.   3        20  LOAD_CONST               0
               22  LOAD_CONST               None
               24  IMPORT_NAME              sys
               26  STORE_NAME               sys

 L.   5        28  LOAD_CONST               0
               30  LOAD_CONST               ('partial',)
               32  IMPORT_NAME              functools
               34  IMPORT_FROM              partial
               36  STORE_NAME               partial
               38  POP_TOP          

 L.   7        40  LOAD_CONST               1
               42  LOAD_CONST               ('converters', 'exceptions', 'filters', 'setters', 'validators')
               44  IMPORT_NAME              
               46  IMPORT_FROM              converters
               48  STORE_NAME               converters
               50  IMPORT_FROM              exceptions
               52  STORE_NAME               exceptions
               54  IMPORT_FROM              filters
               56  STORE_NAME               filters
               58  IMPORT_FROM              setters
               60  STORE_NAME               setters
               62  IMPORT_FROM              validators
               64  STORE_NAME               validators
               66  POP_TOP          

 L.   8        68  LOAD_CONST               1
               70  LOAD_CONST               ('cmp_using',)
               72  IMPORT_NAME              _cmp
               74  IMPORT_FROM              cmp_using
               76  STORE_NAME               cmp_using
               78  POP_TOP          

 L.   9        80  LOAD_CONST               1
               82  LOAD_CONST               ('get_run_validators', 'set_run_validators')
               84  IMPORT_NAME              _config
               86  IMPORT_FROM              get_run_validators
               88  STORE_NAME               get_run_validators
               90  IMPORT_FROM              set_run_validators
               92  STORE_NAME               set_run_validators
               94  POP_TOP          

 L.  10        96  LOAD_CONST               1
               98  LOAD_CONST               ('asdict', 'assoc', 'astuple', 'evolve', 'has', 'resolve_types')
              100  IMPORT_NAME              _funcs
              102  IMPORT_FROM              asdict
              104  STORE_NAME               asdict
              106  IMPORT_FROM              assoc
              108  STORE_NAME               assoc
              110  IMPORT_FROM              astuple
              112  STORE_NAME               astuple
              114  IMPORT_FROM              evolve
              116  STORE_NAME               evolve
              118  IMPORT_FROM              has
              120  STORE_NAME               has
              122  IMPORT_FROM              resolve_types
              124  STORE_NAME               resolve_types
              126  POP_TOP          

 L.  11       128  LOAD_CONST               1
              130  LOAD_CONST               ('NOTHING', 'Attribute', 'Factory', 'attrib', 'attrs', 'fields', 'fields_dict', 'make_class', 'validate')
              132  IMPORT_NAME              _make
              134  IMPORT_FROM              NOTHING
              136  STORE_NAME               NOTHING
              138  IMPORT_FROM              Attribute
              140  STORE_NAME               Attribute
              142  IMPORT_FROM              Factory
              144  STORE_NAME               Factory
              146  IMPORT_FROM              attrib
              148  STORE_NAME               attrib
              150  IMPORT_FROM              attrs
              152  STORE_NAME               attrs
              154  IMPORT_FROM              fields
              156  STORE_NAME               fields
              158  IMPORT_FROM              fields_dict
              160  STORE_NAME               fields_dict
              162  IMPORT_FROM              make_class
              164  STORE_NAME               make_class
              166  IMPORT_FROM              validate
              168  STORE_NAME               validate
              170  POP_TOP          

 L.  22       172  LOAD_CONST               1
              174  LOAD_CONST               ('VersionInfo',)
              176  IMPORT_NAME              _version_info
              178  IMPORT_FROM              VersionInfo
              180  STORE_NAME               VersionInfo
              182  POP_TOP          

 L.  25       184  LOAD_STR                 '21.2.0'
              186  STORE_NAME               __version__

 L.  26       188  LOAD_NAME                VersionInfo
              190  LOAD_METHOD              _from_version_string
              192  LOAD_NAME                __version__
              194  CALL_METHOD_1         1  ''
              196  STORE_NAME               __version_info__

 L.  28       198  LOAD_STR                 'attrs'
              200  STORE_NAME               __title__

 L.  29       202  LOAD_STR                 'Classes Without Boilerplate'
              204  STORE_NAME               __description__

 L.  30       206  LOAD_STR                 'https://www.attrs.org/'
              208  STORE_NAME               __url__

 L.  31       210  LOAD_NAME                __url__
              212  STORE_NAME               __uri__

 L.  32       214  LOAD_NAME                __description__
              216  LOAD_STR                 ' <'
              218  BINARY_ADD       
              220  LOAD_NAME                __uri__
              222  BINARY_ADD       
              224  LOAD_STR                 '>'
              226  BINARY_ADD       
              228  STORE_NAME               __doc__

 L.  34       230  LOAD_STR                 'Hynek Schlawack'
              232  STORE_NAME               __author__

 L.  35       234  LOAD_STR                 'hs@ox.cx'
              236  STORE_NAME               __email__

 L.  37       238  LOAD_STR                 'MIT'
              240  STORE_NAME               __license__

 L.  38       242  LOAD_STR                 'Copyright (c) 2015 Hynek Schlawack'
              244  STORE_NAME               __copyright__

 L.  41       246  LOAD_NAME                attrs
              248  DUP_TOP          
              250  STORE_NAME               s
              252  STORE_NAME               attributes

 L.  42       254  LOAD_NAME                attrib
              256  DUP_TOP          
              258  STORE_NAME               ib
              260  STORE_NAME               attr

 L.  43       262  LOAD_NAME                partial
              264  LOAD_NAME                attrs
              266  LOAD_CONST               True
              268  LOAD_CONST               ('auto_attribs',)
              270  CALL_FUNCTION_KW_2     2  '2 total positional and keyword args'
              272  STORE_NAME               dataclass

 L.  45       274  BUILD_LIST_0          0 
              276  LOAD_CONST               ('Attribute', 'Factory', 'NOTHING', 'asdict', 'assoc', 'astuple', 'attr', 'attrib', 'attributes', 'attrs', 'cmp_using', 'converters', 'evolve', 'exceptions', 'fields', 'fields_dict', 'filters', 'get_run_validators', 'has', 'ib', 'make_class', 'resolve_types', 's', 'set_run_validators', 'setters', 'validate', 'validators')
              278  CALL_FINALLY        281  'to 281'
              280  STORE_NAME               __all__

 L.  75       282  LOAD_NAME                sys
              284  LOAD_ATTR                version_info
              286  LOAD_CONST               None
              288  LOAD_CONST               2
              290  BUILD_SLICE_2         2 
              292  BINARY_SUBSCR    
              294  LOAD_CONST               (3, 6)
              296  COMPARE_OP               >=
          298_300  POP_JUMP_IF_FALSE   344  'to 344'

 L.  76       302  LOAD_CONST               1
              304  LOAD_CONST               ('define', 'field', 'frozen', 'mutable')
              306  IMPORT_NAME              _next_gen
              308  IMPORT_FROM              define
              310  STORE_NAME               define
              312  IMPORT_FROM              field
              314  STORE_NAME               field
              316  IMPORT_FROM              frozen
              318  STORE_NAME               frozen
              320  IMPORT_FROM              mutable
              322  STORE_NAME               mutable
              324  POP_TOP          

 L.  78       326  LOAD_NAME                __all__
              328  LOAD_METHOD              extend
              330  LOAD_NAME                define
              332  LOAD_NAME                field
              334  LOAD_NAME                frozen
              336  LOAD_NAME                mutable
              338  BUILD_TUPLE_4         4 
              340  CALL_METHOD_1         1  ''
              342  POP_TOP          
            344_0  COME_FROM           298  '298'

Parse error at or near `CALL_FINALLY' instruction at offset 278

Instruction context:
   
 L.  45       274  BUILD_LIST_0          0 
                 276  LOAD_CONST               ('Attribute', 'Factory', 'NOTHING', 'asdict', 'assoc', 'astuple', 'attr', 'attrib', 'attributes', 'attrs', 'cmp_using', 'converters', 'evolve', 'exceptions', 'fields', 'fields_dict', 'filters', 'get_run_validators', 'has', 'ib', 'make_class', 'resolve_types', 's', 'set_run_validators', 'setters', 'validate', 'validators')
->               278  CALL_FINALLY        281  'to 281'
                 280  STORE_NAME               __all__

test/134401.pyc -- 
# decompile failed
