
# file test/136268.pyc
# --- This code section failed: ---

 L.  54         0  LOAD_CONST               0
                2  LOAD_CONST               None
                4  IMPORT_NAME              copy
                6  STORE_NAME               copy

 L.  55         8  LOAD_CONST               0
               10  LOAD_CONST               None
               12  IMPORT_NAME              struct
               14  STORE_NAME               struct

 L.  57        16  BUILD_LIST_0          0 
               18  LOAD_CONST               ('AES', 'AESModeOfOperationCTR', 'AESModeOfOperationCBC', 'AESModeOfOperationCFB', 'AESModeOfOperationECB', 'AESModeOfOperationOFB', 'AESModesOfOperation', 'Counter')
               20  CALL_FINALLY         23  'to 23'
               22  STORE_NAME               __all__

 L.  61        24  LOAD_CODE                <code_object _compact_word>
               26  LOAD_STR                 '_compact_word'
               28  MAKE_FUNCTION_0          'Neither defaults, keyword-only args, annotations, nor closures'
               30  STORE_NAME               _compact_word

 L.  64        32  LOAD_CODE                <code_object _string_to_bytes>
               34  LOAD_STR                 '_string_to_bytes'
               36  MAKE_FUNCTION_0          'Neither defaults, keyword-only args, annotations, nor closures'
               38  STORE_NAME               _string_to_bytes

 L.  67        40  LOAD_CODE                <code_object _bytes_to_string>
               42  LOAD_STR                 '_bytes_to_string'
               44  MAKE_FUNCTION_0          'Neither defaults, keyword-only args, annotations, nor closures'
               46  STORE_NAME               _bytes_to_string

 L.  70        48  LOAD_CODE                <code_object _concat_list>
               50  LOAD_STR                 '_concat_list'
               52  MAKE_FUNCTION_0          'Neither defaults, keyword-only args, annotations, nor closures'
               54  STORE_NAME               _concat_list

 L.  75        56  SETUP_FINALLY        66  'to 66'

 L.  76        58  LOAD_NAME                xrange
               60  POP_TOP          
               62  POP_BLOCK        
               64  JUMP_FORWARD        112  'to 112'
             66_0  COME_FROM_FINALLY    56  '56'

 L.  77        66  DUP_TOP          
               68  LOAD_NAME                Exception
               70  <121>               110  ''
               72  POP_TOP          
               74  POP_TOP          
               76  POP_TOP          

 L.  78        78  LOAD_NAME                range
               80  STORE_NAME               xrange

 L.  81        82  LOAD_CODE                <code_object _string_to_bytes>
               84  LOAD_STR                 '_string_to_bytes'
               86  MAKE_FUNCTION_0          'Neither defaults, keyword-only args, annotations, nor closures'
               88  STORE_NAME               _string_to_bytes

 L.  87        90  LOAD_CODE                <code_object _bytes_to_string>
               92  LOAD_STR                 '_bytes_to_string'
               94  MAKE_FUNCTION_0          'Neither defaults, keyword-only args, annotations, nor closures'
               96  STORE_NAME               _bytes_to_string

 L.  91        98  LOAD_CODE                <code_object _concat_list>
              100  LOAD_STR                 '_concat_list'
              102  MAKE_FUNCTION_0          'Neither defaults, keyword-only args, annotations, nor closures'
              104  STORE_NAME               _concat_list
              106  POP_EXCEPT       
              108  JUMP_FORWARD        112  'to 112'
              110  <48>             
            112_0  COME_FROM           108  '108'
            112_1  COME_FROM            64  '64'

 L.  97       112  LOAD_BUILD_CLASS 
              114  LOAD_CODE                <code_object AES>
              116  LOAD_STR                 'AES'
              118  MAKE_FUNCTION_0          'Neither defaults, keyword-only args, annotations, nor closures'
              120  LOAD_STR                 'AES'
              122  LOAD_NAME                object
              124  CALL_FUNCTION_3       3  ''
              126  STORE_NAME               AES

 L. 272       128  LOAD_BUILD_CLASS 
              130  LOAD_CODE                <code_object Counter>
              132  LOAD_STR                 'Counter'
              134  MAKE_FUNCTION_0          'Neither defaults, keyword-only args, annotations, nor closures'
              136  LOAD_STR                 'Counter'
              138  LOAD_NAME                object
              140  CALL_FUNCTION_3       3  ''
              142  STORE_NAME               Counter

 L. 301       144  LOAD_BUILD_CLASS 
              146  LOAD_CODE                <code_object AESBlockModeOfOperation>
              148  LOAD_STR                 'AESBlockModeOfOperation'
              150  MAKE_FUNCTION_0          'Neither defaults, keyword-only args, annotations, nor closures'
              152  LOAD_STR                 'AESBlockModeOfOperation'
              154  LOAD_NAME                object
              156  CALL_FUNCTION_3       3  ''
              158  STORE_NAME               AESBlockModeOfOperation

 L. 313       160  LOAD_BUILD_CLASS 
              162  LOAD_CODE                <code_object AESStreamModeOfOperation>
              164  LOAD_STR                 'AESStreamModeOfOperation'
              166  MAKE_FUNCTION_0          'Neither defaults, keyword-only args, annotations, nor closures'
              168  LOAD_STR                 'AESStreamModeOfOperation'
              170  LOAD_NAME                AESBlockModeOfOperation
              172  CALL_FUNCTION_3       3  ''
              174  STORE_NAME               AESStreamModeOfOperation

 L. 316       176  LOAD_BUILD_CLASS 
              178  LOAD_CODE                <code_object AESSegmentModeOfOperation>
              180  LOAD_STR                 'AESSegmentModeOfOperation'
              182  MAKE_FUNCTION_0          'Neither defaults, keyword-only args, annotations, nor closures'
              184  LOAD_STR                 'AESSegmentModeOfOperation'
              186  LOAD_NAME                AESStreamModeOfOperation
              188  CALL_FUNCTION_3       3  ''
              190  STORE_NAME               AESSegmentModeOfOperation

 L. 323       192  LOAD_BUILD_CLASS 
              194  LOAD_CODE                <code_object AESModeOfOperationECB>
              196  LOAD_STR                 'AESModeOfOperationECB'
              198  MAKE_FUNCTION_0          'Neither defaults, keyword-only args, annotations, nor closures'
              200  LOAD_STR                 'AESModeOfOperationECB'
              202  LOAD_NAME                AESBlockModeOfOperation
              204  CALL_FUNCTION_3       3  ''
              206  STORE_NAME               AESModeOfOperationECB

 L. 356       208  LOAD_BUILD_CLASS 
              210  LOAD_CODE                <code_object AESModeOfOperationCBC>
              212  LOAD_STR                 'AESModeOfOperationCBC'
              214  MAKE_FUNCTION_0          'Neither defaults, keyword-only args, annotations, nor closures'
              216  LOAD_STR                 'AESModeOfOperationCBC'
              218  LOAD_NAME                AESBlockModeOfOperation
              220  CALL_FUNCTION_3       3  ''
              222  STORE_NAME               AESModeOfOperationCBC

 L. 409       224  LOAD_BUILD_CLASS 
              226  LOAD_CODE                <code_object AESModeOfOperationCFB>
              228  LOAD_STR                 'AESModeOfOperationCFB'
              230  MAKE_FUNCTION_0          'Neither defaults, keyword-only args, annotations, nor closures'
              232  LOAD_STR                 'AESModeOfOperationCFB'
              234  LOAD_NAME                AESSegmentModeOfOperation
              236  CALL_FUNCTION_3       3  ''
              238  STORE_NAME               AESModeOfOperationCFB

 L. 480       240  LOAD_BUILD_CLASS 
              242  LOAD_CODE                <code_object AESModeOfOperationOFB>
              244  LOAD_STR                 'AESModeOfOperationOFB'
              246  MAKE_FUNCTION_0          'Neither defaults, keyword-only args, annotations, nor closures'
              248  LOAD_STR                 'AESModeOfOperationOFB'
              250  LOAD_NAME                AESStreamModeOfOperation
              252  CALL_FUNCTION_3       3  ''
              254  STORE_NAME               AESModeOfOperationOFB

 L. 527       256  LOAD_BUILD_CLASS 
              258  LOAD_CODE                <code_object AESModeOfOperationCTR>
              260  LOAD_STR                 'AESModeOfOperationCTR'
              262  MAKE_FUNCTION_0          'Neither defaults, keyword-only args, annotations, nor closures'
              264  LOAD_STR                 'AESModeOfOperationCTR'
              266  LOAD_NAME                AESStreamModeOfOperation
              268  CALL_FUNCTION_3       3  ''
              270  STORE_NAME               AESModeOfOperationCTR

 L. 583       272  LOAD_NAME                dict

 L. 584       274  LOAD_NAME                AESModeOfOperationCTR

 L. 585       276  LOAD_NAME                AESModeOfOperationCBC

 L. 586       278  LOAD_NAME                AESModeOfOperationCFB

 L. 587       280  LOAD_NAME                AESModeOfOperationECB

 L. 588       282  LOAD_NAME                AESModeOfOperationOFB

 L. 583       284  LOAD_CONST               ('ctr', 'cbc', 'cfb', 'ecb', 'ofb')
              286  CALL_FUNCTION_KW_5     5  '5 total positional and keyword args'
              288  STORE_NAME               AESModesOfOperation

Parse error at or near `CALL_FINALLY' instruction at offset 20

Instruction context:
   
 L.  57        16  BUILD_LIST_0          0 
                  18  LOAD_CONST               ('AES', 'AESModeOfOperationCTR', 'AESModeOfOperationCBC', 'AESModeOfOperationCFB', 'AESModeOfOperationECB', 'AESModeOfOperationOFB', 'AESModesOfOperation', 'Counter')
->                20  CALL_FINALLY         23  'to 23'
                  22  STORE_NAME               __all__

test/136268.pyc -- 
# decompile failed
