
# file test/162657.pyc
# --- This code section failed: ---

 L.   1         0  LOAD_STR                 'Lite version of scipy.linalg.\n\nNotes\n-----\nThis module is a lite version of the linalg.py module in SciPy which\ncontains high-level Python interface to the LAPACK library.  The lite\nversion only accesses the following LAPACK functions: dgesv, zgesv,\ndgeev, zgeev, dgesdd, zgesdd, dgelsd, zgelsd, dsyevd, zheevd, dgetrf,\nzgetrf, dpotrf, zpotrf, dgeqrf, zgeqrf, zungqr, dorgqr.\n'
                2  STORE_NAME               __doc__

 L.  12         4  BUILD_LIST_0          0 
                6  LOAD_CONST               ('matrix_power', 'solve', 'tensorsolve', 'tensorinv', 'inv', 'cholesky', 'eigvals', 'eigvalsh', 'pinv', 'slogdet', 'det', 'svd', 'eig', 'eigh', 'lstsq', 'norm', 'qr', 'cond', 'matrix_rank', 'LinAlgError', 'multi_dot')
                8  CALL_FINALLY         11  'to 11'
               10  STORE_NAME               __all__

 L.  17        12  LOAD_CONST               0
               14  LOAD_CONST               None
               16  IMPORT_NAME              functools
               18  STORE_NAME               functools

 L.  18        20  LOAD_CONST               0
               22  LOAD_CONST               None
               24  IMPORT_NAME              operator
               26  STORE_NAME               operator

 L.  19        28  LOAD_CONST               0
               30  LOAD_CONST               None
               32  IMPORT_NAME              warnings
               34  STORE_NAME               warnings

 L.  21        36  LOAD_CONST               0
               38  LOAD_CONST               ('array', 'asarray', 'zeros', 'empty', 'empty_like', 'intc', 'single', 'double', 'csingle', 'cdouble', 'inexact', 'complexfloating', 'newaxis', 'all', 'Inf', 'dot', 'add', 'multiply', 'sqrt', 'fastCopyAndTranspose', 'sum', 'isfinite', 'finfo', 'errstate', 'geterrobj', 'moveaxis', 'amin', 'amax', 'product', 'abs', 'atleast_2d', 'intp', 'asanyarray', 'object_', 'matmul', 'swapaxes', 'divide', 'count_nonzero', 'isnan', 'sign', 'argsort', 'sort')
               40  IMPORT_NAME_ATTR         numpy.core
               42  IMPORT_FROM              array
               44  STORE_NAME               array
               46  IMPORT_FROM              asarray
               48  STORE_NAME               asarray
               50  IMPORT_FROM              zeros
               52  STORE_NAME               zeros
               54  IMPORT_FROM              empty
               56  STORE_NAME               empty
               58  IMPORT_FROM              empty_like
               60  STORE_NAME               empty_like
               62  IMPORT_FROM              intc
               64  STORE_NAME               intc
               66  IMPORT_FROM              single
               68  STORE_NAME               single
               70  IMPORT_FROM              double
               72  STORE_NAME               double
               74  IMPORT_FROM              csingle
               76  STORE_NAME               csingle
               78  IMPORT_FROM              cdouble
               80  STORE_NAME               cdouble
               82  IMPORT_FROM              inexact
               84  STORE_NAME               inexact
               86  IMPORT_FROM              complexfloating
               88  STORE_NAME               complexfloating
               90  IMPORT_FROM              newaxis
               92  STORE_NAME               newaxis
               94  IMPORT_FROM              all
               96  STORE_NAME               all
               98  IMPORT_FROM              Inf
              100  STORE_NAME               Inf
              102  IMPORT_FROM              dot
              104  STORE_NAME               dot
              106  IMPORT_FROM              add
              108  STORE_NAME               add
              110  IMPORT_FROM              multiply
              112  STORE_NAME               multiply
              114  IMPORT_FROM              sqrt
              116  STORE_NAME               sqrt
              118  IMPORT_FROM              fastCopyAndTranspose
              120  STORE_NAME               fastCopyAndTranspose
              122  IMPORT_FROM              sum
              124  STORE_NAME               sum
              126  IMPORT_FROM              isfinite
              128  STORE_NAME               isfinite
              130  IMPORT_FROM              finfo
              132  STORE_NAME               finfo
              134  IMPORT_FROM              errstate
              136  STORE_NAME               errstate
              138  IMPORT_FROM              geterrobj
              140  STORE_NAME               geterrobj
              142  IMPORT_FROM              moveaxis
              144  STORE_NAME               moveaxis
              146  IMPORT_FROM              amin
              148  STORE_NAME               amin
              150  IMPORT_FROM              amax
              152  STORE_NAME               amax
              154  IMPORT_FROM              product
              156  STORE_NAME               product
              158  IMPORT_FROM              abs
              160  STORE_NAME               abs
              162  IMPORT_FROM              atleast_2d
              164  STORE_NAME               atleast_2d
              166  IMPORT_FROM              intp
              168  STORE_NAME               intp
              170  IMPORT_FROM              asanyarray
              172  STORE_NAME               asanyarray
              174  IMPORT_FROM              object_
              176  STORE_NAME               object_
              178  IMPORT_FROM              matmul
              180  STORE_NAME               matmul
              182  IMPORT_FROM              swapaxes
              184  STORE_NAME               swapaxes
              186  IMPORT_FROM              divide
              188  STORE_NAME               divide
              190  IMPORT_FROM              count_nonzero
              192  STORE_NAME               count_nonzero
              194  IMPORT_FROM              isnan
              196  STORE_NAME               isnan
              198  IMPORT_FROM              sign
              200  STORE_NAME               sign
              202  IMPORT_FROM              argsort
              204  STORE_NAME               argsort
              206  IMPORT_FROM              sort
              208  STORE_NAME               sort
              210  POP_TOP          

 L.  29       212  LOAD_CONST               0
              214  LOAD_CONST               ('normalize_axis_index',)
              216  IMPORT_NAME_ATTR         numpy.core.multiarray
              218  IMPORT_FROM              normalize_axis_index
              220  STORE_NAME               normalize_axis_index
              222  POP_TOP          

 L.  30       224  LOAD_CONST               0
              226  LOAD_CONST               ('set_module',)
              228  IMPORT_NAME_ATTR         numpy.core.overrides
              230  IMPORT_FROM              set_module
              232  STORE_NAME               set_module
              234  POP_TOP          

 L.  31       236  LOAD_CONST               0
              238  LOAD_CONST               ('overrides',)
              240  IMPORT_NAME_ATTR         numpy.core
              242  IMPORT_FROM              overrides
              244  STORE_NAME               overrides
              246  POP_TOP          

 L.  32       248  LOAD_CONST               0
              250  LOAD_CONST               ('triu', 'eye')
              252  IMPORT_NAME_ATTR         numpy.lib.twodim_base
              254  IMPORT_FROM              triu
              256  STORE_NAME               triu
              258  IMPORT_FROM              eye
              260  STORE_NAME               eye
              262  POP_TOP          

 L.  33       264  LOAD_CONST               0
              266  LOAD_CONST               ('lapack_lite', '_umath_linalg')
              268  IMPORT_NAME_ATTR         numpy.linalg
              270  IMPORT_FROM              lapack_lite
              272  STORE_NAME               lapack_lite
              274  IMPORT_FROM              _umath_linalg
              276  STORE_NAME               _umath_linalg
              278  POP_TOP          

 L.  36       280  LOAD_NAME                functools
              282  LOAD_ATTR                partial

 L.  37       284  LOAD_NAME                overrides
              286  LOAD_ATTR                array_function_dispatch
              288  LOAD_STR                 'numpy.linalg'

 L.  36       290  LOAD_CONST               ('module',)
              292  CALL_FUNCTION_KW_2     2  '2 total positional and keyword args'
              294  STORE_NAME               array_function_dispatch

 L.  40       296  LOAD_NAME                intc
              298  STORE_NAME               fortran_int

 L.  43       300  LOAD_NAME                set_module
              302  LOAD_STR                 'numpy.linalg'
              304  CALL_FUNCTION_1       1  ''

 L.  44       306  LOAD_BUILD_CLASS 
              308  LOAD_CODE                <code_object LinAlgError>
              310  LOAD_STR                 'LinAlgError'
              312  MAKE_FUNCTION_0          'Neither defaults, keyword-only args, annotations, nor closures'
              314  LOAD_STR                 'LinAlgError'
              316  LOAD_NAME                Exception
              318  CALL_FUNCTION_3       3  ''
              320  CALL_FUNCTION_1       1  ''
              322  STORE_NAME               LinAlgError

 L.  73       324  LOAD_CODE                <code_object _determine_error_states>
              326  LOAD_STR                 '_determine_error_states'
              328  MAKE_FUNCTION_0          'Neither defaults, keyword-only args, annotations, nor closures'
              330  STORE_NAME               _determine_error_states

 L.  84       332  LOAD_NAME                _determine_error_states
              334  CALL_FUNCTION_0       0  ''
              336  STORE_NAME               _linalg_error_extobj

 L.  85       338  DELETE_NAME              _determine_error_states

 L.  87       340  LOAD_CODE                <code_object _raise_linalgerror_singular>
              342  LOAD_STR                 '_raise_linalgerror_singular'
              344  MAKE_FUNCTION_0          'Neither defaults, keyword-only args, annotations, nor closures'
              346  STORE_NAME               _raise_linalgerror_singular

 L.  90       348  LOAD_CODE                <code_object _raise_linalgerror_nonposdef>
              350  LOAD_STR                 '_raise_linalgerror_nonposdef'
              352  MAKE_FUNCTION_0          'Neither defaults, keyword-only args, annotations, nor closures'
              354  STORE_NAME               _raise_linalgerror_nonposdef

 L.  93       356  LOAD_CODE                <code_object _raise_linalgerror_eigenvalues_nonconvergence>
              358  LOAD_STR                 '_raise_linalgerror_eigenvalues_nonconvergence'
              360  MAKE_FUNCTION_0          'Neither defaults, keyword-only args, annotations, nor closures'
              362  STORE_NAME               _raise_linalgerror_eigenvalues_nonconvergence

 L.  96       364  LOAD_CODE                <code_object _raise_linalgerror_svd_nonconvergence>
              366  LOAD_STR                 '_raise_linalgerror_svd_nonconvergence'
              368  MAKE_FUNCTION_0          'Neither defaults, keyword-only args, annotations, nor closures'
              370  STORE_NAME               _raise_linalgerror_svd_nonconvergence

 L.  99       372  LOAD_CODE                <code_object _raise_linalgerror_lstsq>
              374  LOAD_STR                 '_raise_linalgerror_lstsq'
              376  MAKE_FUNCTION_0          'Neither defaults, keyword-only args, annotations, nor closures'
              378  STORE_NAME               _raise_linalgerror_lstsq

 L. 102       380  LOAD_CODE                <code_object get_linalg_error_extobj>
              382  LOAD_STR                 'get_linalg_error_extobj'
              384  MAKE_FUNCTION_0          'Neither defaults, keyword-only args, annotations, nor closures'
              386  STORE_NAME               get_linalg_error_extobj

 L. 107       388  LOAD_CODE                <code_object _makearray>
              390  LOAD_STR                 '_makearray'
              392  MAKE_FUNCTION_0          'Neither defaults, keyword-only args, annotations, nor closures'
              394  STORE_NAME               _makearray

 L. 112       396  LOAD_CODE                <code_object isComplexType>
              398  LOAD_STR                 'isComplexType'
              400  MAKE_FUNCTION_0          'Neither defaults, keyword-only args, annotations, nor closures'
              402  STORE_NAME               isComplexType

 L. 115       404  LOAD_NAME                single
              406  LOAD_NAME                single

 L. 116       408  LOAD_NAME                double
              410  LOAD_NAME                double

 L. 117       412  LOAD_NAME                csingle
              414  LOAD_NAME                single

 L. 118       416  LOAD_NAME                cdouble
              418  LOAD_NAME                double

 L. 115       420  BUILD_MAP_4           4 
              422  STORE_NAME               _real_types_map

 L. 120       424  LOAD_NAME                single
              426  LOAD_NAME                csingle

 L. 121       428  LOAD_NAME                double
              430  LOAD_NAME                cdouble

 L. 122       432  LOAD_NAME                csingle
              434  LOAD_NAME                csingle

 L. 123       436  LOAD_NAME                cdouble
              438  LOAD_NAME                cdouble

 L. 120       440  BUILD_MAP_4           4 
              442  STORE_NAME               _complex_types_map

 L. 125       444  LOAD_NAME                double
              446  BUILD_TUPLE_1         1 
              448  LOAD_CODE                <code_object _realType>
              450  LOAD_STR                 '_realType'
              452  MAKE_FUNCTION_1          'default'
              454  STORE_NAME               _realType

 L. 128       456  LOAD_NAME                cdouble
              458  BUILD_TUPLE_1         1 
              460  LOAD_CODE                <code_object _complexType>
              462  LOAD_STR                 '_complexType'
              464  MAKE_FUNCTION_1          'default'
              466  STORE_NAME               _complexType

 L. 131       468  LOAD_CODE                <code_object _linalgRealType>
              470  LOAD_STR                 '_linalgRealType'
              472  MAKE_FUNCTION_0          'Neither defaults, keyword-only args, annotations, nor closures'
              474  STORE_NAME               _linalgRealType

 L. 135       476  LOAD_CODE                <code_object _commonType>
              478  LOAD_STR                 '_commonType'
              480  MAKE_FUNCTION_0          'Neither defaults, keyword-only args, annotations, nor closures'
              482  STORE_NAME               _commonType

 L. 162       484  LOAD_NAME                fastCopyAndTranspose
              486  STORE_NAME               _fastCT

 L. 164       488  LOAD_CODE                <code_object _to_native_byte_order>
              490  LOAD_STR                 '_to_native_byte_order'
              492  MAKE_FUNCTION_0          'Neither defaults, keyword-only args, annotations, nor closures'
              494  STORE_NAME               _to_native_byte_order

 L. 176       496  LOAD_CODE                <code_object _fastCopyAndTranspose>
              498  LOAD_STR                 '_fastCopyAndTranspose'
              500  MAKE_FUNCTION_0          'Neither defaults, keyword-only args, annotations, nor closures'
              502  STORE_NAME               _fastCopyAndTranspose

 L. 187       504  LOAD_CODE                <code_object _assert_2d>
              506  LOAD_STR                 '_assert_2d'
              508  MAKE_FUNCTION_0          'Neither defaults, keyword-only args, annotations, nor closures'
              510  STORE_NAME               _assert_2d

 L. 193       512  LOAD_CODE                <code_object _assert_stacked_2d>
              514  LOAD_STR                 '_assert_stacked_2d'
              516  MAKE_FUNCTION_0          'Neither defaults, keyword-only args, annotations, nor closures'
              518  STORE_NAME               _assert_stacked_2d

 L. 199       520  LOAD_CODE                <code_object _assert_stacked_square>
              522  LOAD_STR                 '_assert_stacked_square'
              524  MAKE_FUNCTION_0          'Neither defaults, keyword-only args, annotations, nor closures'
              526  STORE_NAME               _assert_stacked_square

 L. 205       528  LOAD_CODE                <code_object _assert_finite>
              530  LOAD_STR                 '_assert_finite'
              532  MAKE_FUNCTION_0          'Neither defaults, keyword-only args, annotations, nor closures'
              534  STORE_NAME               _assert_finite

 L. 210       536  LOAD_CODE                <code_object _is_empty_2d>
              538  LOAD_STR                 '_is_empty_2d'
              540  MAKE_FUNCTION_0          'Neither defaults, keyword-only args, annotations, nor closures'
              542  STORE_NAME               _is_empty_2d

 L. 215       544  LOAD_CODE                <code_object transpose>
              546  LOAD_STR                 'transpose'
              548  MAKE_FUNCTION_0          'Neither defaults, keyword-only args, annotations, nor closures'
              550  STORE_NAME               transpose

 L. 234       552  LOAD_CONST               (None,)
              554  LOAD_CODE                <code_object _tensorsolve_dispatcher>
              556  LOAD_STR                 '_tensorsolve_dispatcher'
              558  MAKE_FUNCTION_1          'default'
              560  STORE_NAME               _tensorsolve_dispatcher

 L. 238       562  LOAD_NAME                array_function_dispatch
              564  LOAD_NAME                _tensorsolve_dispatcher
              566  CALL_FUNCTION_1       1  ''

 L. 239       568  LOAD_CONST               (None,)
              570  LOAD_CODE                <code_object tensorsolve>
              572  LOAD_STR                 'tensorsolve'
              574  MAKE_FUNCTION_1          'default'
              576  CALL_FUNCTION_1       1  ''
              578  STORE_NAME               tensorsolve

 L. 309       580  LOAD_CODE                <code_object _solve_dispatcher>
              582  LOAD_STR                 '_solve_dispatcher'
              584  MAKE_FUNCTION_0          'Neither defaults, keyword-only args, annotations, nor closures'
              586  STORE_NAME               _solve_dispatcher

 L. 313       588  LOAD_NAME                array_function_dispatch
              590  LOAD_NAME                _solve_dispatcher
              592  CALL_FUNCTION_1       1  ''

 L. 314       594  LOAD_CODE                <code_object solve>
              596  LOAD_STR                 'solve'
              598  MAKE_FUNCTION_0          'Neither defaults, keyword-only args, annotations, nor closures'
              600  CALL_FUNCTION_1       1  ''
              602  STORE_NAME               solve

 L. 398       604  LOAD_CONST               (None,)
              606  LOAD_CODE                <code_object _tensorinv_dispatcher>
              608  LOAD_STR                 '_tensorinv_dispatcher'
              610  MAKE_FUNCTION_1          'default'
              612  STORE_NAME               _tensorinv_dispatcher

 L. 402       614  LOAD_NAME                array_function_dispatch
              616  LOAD_NAME                _tensorinv_dispatcher
              618  CALL_FUNCTION_1       1  ''

 L. 403       620  LOAD_CONST               (2,)
              622  LOAD_CODE                <code_object tensorinv>
              624  LOAD_STR                 'tensorinv'
              626  MAKE_FUNCTION_1          'default'
              628  CALL_FUNCTION_1       1  ''
              630  STORE_NAME               tensorinv

 L. 472       632  LOAD_CODE                <code_object _unary_dispatcher>
              634  LOAD_STR                 '_unary_dispatcher'
              636  MAKE_FUNCTION_0          'Neither defaults, keyword-only args, annotations, nor closures'
              638  STORE_NAME               _unary_dispatcher

 L. 476       640  LOAD_NAME                array_function_dispatch
              642  LOAD_NAME                _unary_dispatcher
              644  CALL_FUNCTION_1       1  ''

 L. 477       646  LOAD_CODE                <code_object inv>
              648  LOAD_STR                 'inv'
              650  MAKE_FUNCTION_0          'Neither defaults, keyword-only args, annotations, nor closures'
              652  CALL_FUNCTION_1       1  ''
              654  STORE_NAME               inv

 L. 549       656  LOAD_CODE                <code_object _matrix_power_dispatcher>
              658  LOAD_STR                 '_matrix_power_dispatcher'
              660  MAKE_FUNCTION_0          'Neither defaults, keyword-only args, annotations, nor closures'
              662  STORE_NAME               _matrix_power_dispatcher

 L. 553       664  LOAD_NAME                array_function_dispatch
              666  LOAD_NAME                _matrix_power_dispatcher
              668  CALL_FUNCTION_1       1  ''

 L. 554       670  LOAD_CODE                <code_object matrix_power>
              672  LOAD_STR                 'matrix_power'
              674  MAKE_FUNCTION_0          'Neither defaults, keyword-only args, annotations, nor closures'
              676  CALL_FUNCTION_1       1  ''
              678  STORE_NAME               matrix_power

 L. 672       680  LOAD_NAME                array_function_dispatch
              682  LOAD_NAME                _unary_dispatcher
              684  CALL_FUNCTION_1       1  ''

 L. 673       686  LOAD_CODE                <code_object cholesky>
              688  LOAD_STR                 'cholesky'
              690  MAKE_FUNCTION_0          'Neither defaults, keyword-only args, annotations, nor closures'
              692  CALL_FUNCTION_1       1  ''
              694  STORE_NAME               cholesky

 L. 769       696  LOAD_CONST               (None,)
              698  LOAD_CODE                <code_object _qr_dispatcher>
              700  LOAD_STR                 '_qr_dispatcher'
              702  MAKE_FUNCTION_1          'default'
              704  STORE_NAME               _qr_dispatcher

 L. 773       706  LOAD_NAME                array_function_dispatch
              708  LOAD_NAME                _qr_dispatcher
              710  CALL_FUNCTION_1       1  ''

 L. 774       712  LOAD_CONST               ('reduced',)
              714  LOAD_CODE                <code_object qr>
              716  LOAD_STR                 'qr'
              718  MAKE_FUNCTION_1          'default'
              720  CALL_FUNCTION_1       1  ''
              722  STORE_NAME               qr

 L. 988       724  LOAD_NAME                array_function_dispatch
              726  LOAD_NAME                _unary_dispatcher
              728  CALL_FUNCTION_1       1  ''

 L. 989       730  LOAD_CODE                <code_object eigvals>
              732  LOAD_STR                 'eigvals'
              734  MAKE_FUNCTION_0          'Neither defaults, keyword-only args, annotations, nor closures'
              736  CALL_FUNCTION_1       1  ''
              738  STORE_NAME               eigvals

 L.1080       740  LOAD_CONST               (None,)
              742  LOAD_CODE                <code_object _eigvalsh_dispatcher>
              744  LOAD_STR                 '_eigvalsh_dispatcher'
              746  MAKE_FUNCTION_1          'default'
              748  STORE_NAME               _eigvalsh_dispatcher

 L.1084       750  LOAD_NAME                array_function_dispatch
              752  LOAD_NAME                _eigvalsh_dispatcher
              754  CALL_FUNCTION_1       1  ''

 L.1085       756  LOAD_CONST               ('L',)
              758  LOAD_CODE                <code_object eigvalsh>
              760  LOAD_STR                 'eigvalsh'
              762  MAKE_FUNCTION_1          'default'
              764  CALL_FUNCTION_1       1  ''
              766  STORE_NAME               eigvalsh

 L.1178       768  LOAD_CODE                <code_object _convertarray>
              770  LOAD_STR                 '_convertarray'
              772  MAKE_FUNCTION_0          'Neither defaults, keyword-only args, annotations, nor closures'
              774  STORE_NAME               _convertarray

 L.1187       776  LOAD_NAME                array_function_dispatch
              778  LOAD_NAME                _unary_dispatcher
              780  CALL_FUNCTION_1       1  ''

 L.1188       782  LOAD_CODE                <code_object eig>
              784  LOAD_STR                 'eig'
              786  MAKE_FUNCTION_0          'Neither defaults, keyword-only args, annotations, nor closures'
              788  CALL_FUNCTION_1       1  ''
              790  STORE_NAME               eig

 L.1336       792  LOAD_NAME                array_function_dispatch
              794  LOAD_NAME                _eigvalsh_dispatcher
              796  CALL_FUNCTION_1       1  ''

 L.1337       798  LOAD_CONST               ('L',)
              800  LOAD_CODE                <code_object eigh>
              802  LOAD_STR                 'eigh'
              804  MAKE_FUNCTION_1          'default'
              806  CALL_FUNCTION_1       1  ''
              808  STORE_NAME               eigh

 L.1478       810  LOAD_CONST               (None, None, None)
              812  LOAD_CODE                <code_object _svd_dispatcher>
              814  LOAD_STR                 '_svd_dispatcher'
              816  MAKE_FUNCTION_1          'default'
              818  STORE_NAME               _svd_dispatcher

 L.1482       820  LOAD_NAME                array_function_dispatch
              822  LOAD_NAME                _svd_dispatcher
              824  CALL_FUNCTION_1       1  ''

 L.1483       826  LOAD_CONST               (True, True, False)
              828  LOAD_CODE                <code_object svd>
              830  LOAD_STR                 'svd'
              832  MAKE_FUNCTION_1          'default'
              834  CALL_FUNCTION_1       1  ''
              836  STORE_NAME               svd

 L.1677       838  LOAD_CONST               (None,)
              840  LOAD_CODE                <code_object _cond_dispatcher>
              842  LOAD_STR                 '_cond_dispatcher'
              844  MAKE_FUNCTION_1          'default'
              846  STORE_NAME               _cond_dispatcher

 L.1681       848  LOAD_NAME                array_function_dispatch
              850  LOAD_NAME                _cond_dispatcher
              852  CALL_FUNCTION_1       1  ''

 L.1682       854  LOAD_CONST               (None,)
              856  LOAD_CODE                <code_object cond>
              858  LOAD_STR                 'cond'
              860  MAKE_FUNCTION_1          'default'
              862  CALL_FUNCTION_1       1  ''
              864  STORE_NAME               cond

 L.1800       866  LOAD_CONST               (None, None)
              868  LOAD_CODE                <code_object _matrix_rank_dispatcher>
              870  LOAD_STR                 '_matrix_rank_dispatcher'
              872  MAKE_FUNCTION_1          'default'
              874  STORE_NAME               _matrix_rank_dispatcher

 L.1804       876  LOAD_NAME                array_function_dispatch
              878  LOAD_NAME                _matrix_rank_dispatcher
              880  CALL_FUNCTION_1       1  ''

 L.1805       882  LOAD_CONST               (None, False)
              884  LOAD_CODE                <code_object matrix_rank>
              886  LOAD_STR                 'matrix_rank'
              888  MAKE_FUNCTION_1          'default'
              890  CALL_FUNCTION_1       1  ''
              892  STORE_NAME               matrix_rank

 L.1911       894  LOAD_CONST               (None, None)
              896  LOAD_CODE                <code_object _pinv_dispatcher>
              898  LOAD_STR                 '_pinv_dispatcher'
              900  MAKE_FUNCTION_1          'default'
              902  STORE_NAME               _pinv_dispatcher

 L.1915       904  LOAD_NAME                array_function_dispatch
              906  LOAD_NAME                _pinv_dispatcher
              908  CALL_FUNCTION_1       1  ''

 L.1916       910  LOAD_CONST               (1e-15, False)
              912  LOAD_CODE                <code_object pinv>
              914  LOAD_STR                 'pinv'
              916  MAKE_FUNCTION_1          'default'
              918  CALL_FUNCTION_1       1  ''
              920  STORE_NAME               pinv

 L.2017       922  LOAD_NAME                array_function_dispatch
              924  LOAD_NAME                _unary_dispatcher
              926  CALL_FUNCTION_1       1  ''

 L.2018       928  LOAD_CODE                <code_object slogdet>
              930  LOAD_STR                 'slogdet'
              932  MAKE_FUNCTION_0          'Neither defaults, keyword-only args, annotations, nor closures'
              934  CALL_FUNCTION_1       1  ''
              936  STORE_NAME               slogdet

 L.2104       938  LOAD_NAME                array_function_dispatch
              940  LOAD_NAME                _unary_dispatcher
              942  CALL_FUNCTION_1       1  ''

 L.2105       944  LOAD_CODE                <code_object det>
              946  LOAD_STR                 'det'
              948  MAKE_FUNCTION_0          'Neither defaults, keyword-only args, annotations, nor closures'
              950  CALL_FUNCTION_1       1  ''
              952  STORE_NAME               det

 L.2165       954  LOAD_CONST               (None,)
              956  LOAD_CODE                <code_object _lstsq_dispatcher>
              958  LOAD_STR                 '_lstsq_dispatcher'
              960  MAKE_FUNCTION_1          'default'
              962  STORE_NAME               _lstsq_dispatcher

 L.2169       964  LOAD_NAME                array_function_dispatch
              966  LOAD_NAME                _lstsq_dispatcher
              968  CALL_FUNCTION_1       1  ''

 L.2170       970  LOAD_CONST               ('warn',)
              972  LOAD_CODE                <code_object lstsq>
              974  LOAD_STR                 'lstsq'
              976  MAKE_FUNCTION_1          'default'
              978  CALL_FUNCTION_1       1  ''
              980  STORE_NAME               lstsq

 L.2331       982  LOAD_CODE                <code_object _multi_svd_norm>
              984  LOAD_STR                 '_multi_svd_norm'
              986  MAKE_FUNCTION_0          'Neither defaults, keyword-only args, annotations, nor closures'
              988  STORE_NAME               _multi_svd_norm

 L.2359       990  LOAD_CONST               (None, None, None)
              992  LOAD_CODE                <code_object _norm_dispatcher>
              994  LOAD_STR                 '_norm_dispatcher'
              996  MAKE_FUNCTION_1          'default'
              998  STORE_NAME               _norm_dispatcher

 L.2363      1000  LOAD_NAME                array_function_dispatch
             1002  LOAD_NAME                _norm_dispatcher
             1004  CALL_FUNCTION_1       1  ''

 L.2364      1006  LOAD_CONST               (None, None, False)
             1008  LOAD_CODE                <code_object norm>
             1010  LOAD_STR                 'norm'
             1012  MAKE_FUNCTION_1          'default'
             1014  CALL_FUNCTION_1       1  ''
             1016  STORE_NAME               norm

 L.2616      1018  LOAD_CONST               None
             1020  LOAD_CONST               ('out',)
             1022  BUILD_CONST_KEY_MAP_1     1 
             1024  LOAD_CODE                <code_object _multidot_dispatcher>
             1026  LOAD_STR                 '_multidot_dispatcher'
             1028  MAKE_FUNCTION_2          'keyword-only'
             1030  STORE_NAME               _multidot_dispatcher

 L.2621      1032  LOAD_NAME                array_function_dispatch
             1034  LOAD_NAME                _multidot_dispatcher
             1036  CALL_FUNCTION_1       1  ''

 L.2622      1038  LOAD_CONST               None
             1040  LOAD_CONST               ('out',)
             1042  BUILD_CONST_KEY_MAP_1     1 
             1044  LOAD_CODE                <code_object multi_dot>
             1046  LOAD_STR                 'multi_dot'
             1048  MAKE_FUNCTION_2          'keyword-only'
             1050  CALL_FUNCTION_1       1  ''
             1052  STORE_NAME               multi_dot

 L.2742      1054  LOAD_CONST               (None,)
             1056  LOAD_CODE                <code_object _multi_dot_three>
             1058  LOAD_STR                 '_multi_dot_three'
             1060  MAKE_FUNCTION_1          'default'
             1062  STORE_NAME               _multi_dot_three

 L.2763      1064  LOAD_CONST               (False,)
             1066  LOAD_CODE                <code_object _multi_dot_matrix_chain_order>
             1068  LOAD_STR                 '_multi_dot_matrix_chain_order'
             1070  MAKE_FUNCTION_1          'default'
             1072  STORE_NAME               _multi_dot_matrix_chain_order

 L.2804      1074  LOAD_CONST               (None,)
             1076  LOAD_CODE                <code_object _multi_dot>
             1078  LOAD_STR                 '_multi_dot'
             1080  MAKE_FUNCTION_1          'default'
             1082  STORE_NAME               _multi_dot

Parse error at or near `CALL_FINALLY' instruction at offset 8

Instruction context:
   
 L.  12         4  BUILD_LIST_0          0 
                   6  LOAD_CONST               ('matrix_power', 'solve', 'tensorsolve', 'tensorinv', 'inv', 'cholesky', 'eigvals', 'eigvalsh', 'pinv', 'slogdet', 'det', 'svd', 'eig', 'eigh', 'lstsq', 'norm', 'qr', 'cond', 'matrix_rank', 'LinAlgError', 'multi_dot')
->                 8  CALL_FINALLY         11  'to 11'
                  10  STORE_NAME               __all__

test/162657.pyc -- 
# decompile failed
