
# file test/162681.pyc
# --- This code section failed: ---

 L.   1         0  LOAD_STR                 '\nUtility function to facilitate testing.\n\n'
                2  STORE_NAME               __doc__

 L.   5         4  LOAD_CONST               0
                6  LOAD_CONST               None
                8  IMPORT_NAME              os
               10  STORE_NAME               os

 L.   6        12  LOAD_CONST               0
               14  LOAD_CONST               None
               16  IMPORT_NAME              sys
               18  STORE_NAME               sys

 L.   7        20  LOAD_CONST               0
               22  LOAD_CONST               None
               24  IMPORT_NAME              platform
               26  STORE_NAME               platform

 L.   8        28  LOAD_CONST               0
               30  LOAD_CONST               None
               32  IMPORT_NAME              re
               34  STORE_NAME               re

 L.   9        36  LOAD_CONST               0
               38  LOAD_CONST               None
               40  IMPORT_NAME              gc
               42  STORE_NAME               gc

 L.  10        44  LOAD_CONST               0
               46  LOAD_CONST               None
               48  IMPORT_NAME              operator
               50  STORE_NAME               operator

 L.  11        52  LOAD_CONST               0
               54  LOAD_CONST               None
               56  IMPORT_NAME              warnings
               58  STORE_NAME               warnings

 L.  12        60  LOAD_CONST               0
               62  LOAD_CONST               ('partial', 'wraps')
               64  IMPORT_NAME              functools
               66  IMPORT_FROM              partial
               68  STORE_NAME               partial
               70  IMPORT_FROM              wraps
               72  STORE_NAME               wraps
               74  POP_TOP          

 L.  13        76  LOAD_CONST               0
               78  LOAD_CONST               None
               80  IMPORT_NAME              shutil
               82  STORE_NAME               shutil

 L.  14        84  LOAD_CONST               0
               86  LOAD_CONST               None
               88  IMPORT_NAME              contextlib
               90  STORE_NAME               contextlib

 L.  15        92  LOAD_CONST               0
               94  LOAD_CONST               ('mkdtemp', 'mkstemp')
               96  IMPORT_NAME              tempfile
               98  IMPORT_FROM              mkdtemp
              100  STORE_NAME               mkdtemp
              102  IMPORT_FROM              mkstemp
              104  STORE_NAME               mkstemp
              106  POP_TOP          

 L.  16       108  LOAD_CONST               0
              110  LOAD_CONST               ('SkipTest',)
              112  IMPORT_NAME_ATTR         unittest.case
              114  IMPORT_FROM              SkipTest
              116  STORE_NAME               SkipTest
              118  POP_TOP          

 L.  17       120  LOAD_CONST               0
              122  LOAD_CONST               ('WarningMessage',)
              124  IMPORT_NAME              warnings
              126  IMPORT_FROM              WarningMessage
              128  STORE_NAME               WarningMessage
              130  POP_TOP          

 L.  18       132  LOAD_CONST               0
              134  LOAD_CONST               None
              136  IMPORT_NAME              pprint
              138  STORE_NAME               pprint

 L.  20       140  LOAD_CONST               0
              142  LOAD_CONST               None
              144  IMPORT_NAME              numpy
              146  STORE_NAME               np

 L.  21       148  LOAD_CONST               0
              150  LOAD_CONST               ('intp', 'float32', 'empty', 'arange', 'array_repr', 'ndarray', 'isnat', 'array')
              152  IMPORT_NAME_ATTR         numpy.core
              154  IMPORT_FROM              intp
              156  STORE_NAME               intp
              158  IMPORT_FROM              float32
              160  STORE_NAME               float32
              162  IMPORT_FROM              empty
              164  STORE_NAME               empty
              166  IMPORT_FROM              arange
              168  STORE_NAME               arange
              170  IMPORT_FROM              array_repr
              172  STORE_NAME               array_repr
              174  IMPORT_FROM              ndarray
              176  STORE_NAME               ndarray
              178  IMPORT_FROM              isnat
              180  STORE_NAME               isnat
              182  IMPORT_FROM              array
              184  STORE_NAME               array
              186  POP_TOP          

 L.  23       188  LOAD_CONST               0
              190  LOAD_CONST               None
              192  IMPORT_NAME_ATTR         numpy.linalg.lapack_lite
              194  STORE_NAME               numpy

 L.  25       196  LOAD_CONST               0
              198  LOAD_CONST               ('StringIO',)
              200  IMPORT_NAME              io
              202  IMPORT_FROM              StringIO
              204  STORE_NAME               StringIO
              206  POP_TOP          

 L.  27       208  BUILD_LIST_0          0 
              210  LOAD_CONST               ('assert_equal', 'assert_almost_equal', 'assert_approx_equal', 'assert_array_equal', 'assert_array_less', 'assert_string_equal', 'assert_array_almost_equal', 'assert_raises', 'build_err_msg', 'decorate_methods', 'jiffies', 'memusage', 'print_assert_equal', 'raises', 'rundocs', 'runstring', 'verbose', 'measure', 'assert_', 'assert_array_almost_equal_nulp', 'assert_raises_regex', 'assert_array_max_ulp', 'assert_warns', 'assert_no_warnings', 'assert_allclose', 'IgnoreException', 'clear_and_catch_warnings', 'SkipTest', 'KnownFailureException', 'temppath', 'tempdir', 'IS_PYPY', 'HAS_REFCOUNT', 'suppress_warnings', 'assert_array_compare', '_assert_valid_refcount', '_gen_alignment_data', 'assert_no_gc_cycles', 'break_cycles', 'HAS_LAPACK64')
              212  CALL_FINALLY        215  'to 215'
              214  STORE_NAME               __all__

 L.  43       216  LOAD_BUILD_CLASS 
              218  LOAD_CODE                <code_object KnownFailureException>
              220  LOAD_STR                 'KnownFailureException'
              222  MAKE_FUNCTION_0          'Neither defaults, keyword-only args, annotations, nor closures'
              224  LOAD_STR                 'KnownFailureException'
              226  LOAD_NAME                Exception
              228  CALL_FUNCTION_3       3  ''
              230  STORE_NAME               KnownFailureException

 L.  48       232  LOAD_NAME                KnownFailureException
              234  STORE_NAME               KnownFailureTest

 L.  49       236  LOAD_CONST               0
              238  STORE_NAME               verbose

 L.  51       240  LOAD_NAME                platform
              242  LOAD_METHOD              python_implementation
              244  CALL_METHOD_0         0  ''
              246  LOAD_STR                 'PyPy'
              248  COMPARE_OP               ==
              250  STORE_NAME               IS_PYPY

 L.  52       252  LOAD_NAME                getattr
              254  LOAD_NAME                sys
              256  LOAD_STR                 'getrefcount'
              258  LOAD_CONST               None
              260  CALL_FUNCTION_3       3  ''
              262  LOAD_CONST               None
              264  <117>                 1  ''
              266  STORE_NAME               HAS_REFCOUNT

 L.  53       268  LOAD_NAME                numpy
              270  LOAD_ATTR                linalg
              272  LOAD_ATTR                lapack_lite
              274  LOAD_ATTR                _ilp64
              276  STORE_NAME               HAS_LAPACK64

 L.  56       278  LOAD_CODE                <code_object import_nose>
              280  LOAD_STR                 'import_nose'
              282  MAKE_FUNCTION_0          'Neither defaults, keyword-only args, annotations, nor closures'
              284  STORE_NAME               import_nose

 L.  78       286  LOAD_CONST               ('',)
              288  LOAD_CODE                <code_object assert_>
              290  LOAD_STR                 'assert_'
              292  MAKE_FUNCTION_1          'default'
              294  STORE_NAME               assert_

 L.  98       296  LOAD_CODE                <code_object gisnan>
              298  LOAD_STR                 'gisnan'
              300  MAKE_FUNCTION_0          'Neither defaults, keyword-only args, annotations, nor closures'
              302  STORE_NAME               gisnan

 L. 116       304  LOAD_CODE                <code_object gisfinite>
              306  LOAD_STR                 'gisfinite'
              308  MAKE_FUNCTION_0          'Neither defaults, keyword-only args, annotations, nor closures'
              310  STORE_NAME               gisfinite

 L. 135       312  LOAD_CODE                <code_object gisinf>
              314  LOAD_STR                 'gisinf'
              316  MAKE_FUNCTION_0          'Neither defaults, keyword-only args, annotations, nor closures'
              318  STORE_NAME               gisinf

 L. 154       320  LOAD_NAME                os
              322  LOAD_ATTR                name
              324  LOAD_STR                 'nt'
              326  COMPARE_OP               ==
          328_330  POP_JUMP_IF_FALSE   354  'to 354'

 L. 156       332  LOAD_CONST               (None, -1, None, None)
              334  LOAD_CODE                <code_object GetPerformanceAttributes>
              336  LOAD_STR                 'GetPerformanceAttributes'
              338  MAKE_FUNCTION_1          'default'
              340  STORE_NAME               GetPerformanceAttributes

 L. 183       342  LOAD_CONST               ('python', 0)
              344  LOAD_CODE                <code_object memusage>
              346  LOAD_STR                 'memusage'
              348  MAKE_FUNCTION_1          'default'
              350  STORE_NAME               memusage
              352  JUMP_FORWARD        408  'to 408'
            354_0  COME_FROM           328  '328'

 L. 189       354  LOAD_NAME                sys
              356  LOAD_ATTR                platform
              358  LOAD_CONST               None
              360  LOAD_CONST               5
              362  BUILD_SLICE_2         2 
              364  BINARY_SUBSCR    
              366  LOAD_STR                 'linux'
              368  COMPARE_OP               ==
          370_372  POP_JUMP_IF_FALSE   400  'to 400'

 L. 191       374  LOAD_STR                 '/proc/'
              376  LOAD_NAME                os
              378  LOAD_METHOD              getpid
              380  CALL_METHOD_0         0  ''
              382  FORMAT_VALUE          0  ''
              384  LOAD_STR                 '/stat'
              386  BUILD_STRING_3        3 
              388  BUILD_TUPLE_1         1 
              390  LOAD_CODE                <code_object memusage>
              392  LOAD_STR                 'memusage'
              394  MAKE_FUNCTION_1          'default'
              396  STORE_NAME               memusage
              398  JUMP_FORWARD        408  'to 408'
            400_0  COME_FROM           370  '370'

 L. 203       400  LOAD_CODE                <code_object memusage>
              402  LOAD_STR                 'memusage'
              404  MAKE_FUNCTION_0          'Neither defaults, keyword-only args, annotations, nor closures'
              406  STORE_NAME               memusage
            408_0  COME_FROM           398  '398'
            408_1  COME_FROM           352  '352'

 L. 211       408  LOAD_NAME                sys
              410  LOAD_ATTR                platform
              412  LOAD_CONST               None
              414  LOAD_CONST               5
              416  BUILD_SLICE_2         2 
              418  BINARY_SUBSCR    
              420  LOAD_STR                 'linux'
              422  COMPARE_OP               ==
          424_426  POP_JUMP_IF_FALSE   456  'to 456'

 L. 212       428  LOAD_STR                 '/proc/'
              430  LOAD_NAME                os
              432  LOAD_METHOD              getpid
              434  CALL_METHOD_0         0  ''
              436  FORMAT_VALUE          0  ''
              438  LOAD_STR                 '/stat'
              440  BUILD_STRING_3        3 
              442  BUILD_LIST_0          0 
              444  BUILD_TUPLE_2         2 
              446  LOAD_CODE                <code_object jiffies>
              448  LOAD_STR                 'jiffies'
              450  MAKE_FUNCTION_1          'default'
              452  STORE_NAME               jiffies
              454  JUMP_FORWARD        468  'to 468'
            456_0  COME_FROM           424  '424'

 L. 233       456  BUILD_LIST_0          0 
              458  BUILD_TUPLE_1         1 
              460  LOAD_CODE                <code_object jiffies>
              462  LOAD_STR                 'jiffies'
              464  MAKE_FUNCTION_1          'default'
              466  STORE_NAME               jiffies
            468_0  COME_FROM           454  '454'

 L. 247       468  LOAD_CONST               ('Items are not equal:', True, ('ACTUAL', 'DESIRED'), 8)
              470  LOAD_CODE                <code_object build_err_msg>
              472  LOAD_STR                 'build_err_msg'
              474  MAKE_FUNCTION_1          'default'
              476  STORE_NAME               build_err_msg

 L. 275       478  LOAD_CONST               ('', True)
              480  LOAD_CODE                <code_object assert_equal>
              482  LOAD_STR                 'assert_equal'
              484  MAKE_FUNCTION_1          'default'
              486  STORE_NAME               assert_equal

 L. 435       488  LOAD_CODE                <code_object print_assert_equal>
              490  LOAD_STR                 'print_assert_equal'
              492  MAKE_FUNCTION_0          'Neither defaults, keyword-only args, annotations, nor closures'
              494  STORE_NAME               print_assert_equal

 L. 476       496  LOAD_CONST               (7, '', True)
              498  LOAD_CODE                <code_object assert_almost_equal>
              500  LOAD_STR                 'assert_almost_equal'
              502  MAKE_FUNCTION_1          'default'
              504  STORE_NAME               assert_almost_equal

 L. 602       506  LOAD_CONST               (7, '', True)
              508  LOAD_CODE                <code_object assert_approx_equal>
              510  LOAD_STR                 'assert_approx_equal'
              512  MAKE_FUNCTION_1          'default'
              514  STORE_NAME               assert_approx_equal

 L. 701       516  LOAD_CONST               ('', True, '', 6, True, True)
              518  LOAD_CODE                <code_object assert_array_compare>
              520  LOAD_STR                 'assert_array_compare'
              522  MAKE_FUNCTION_1          'default'
              524  STORE_NAME               assert_array_compare

 L. 855       526  LOAD_CONST               ('', True)
              528  LOAD_CODE                <code_object assert_array_equal>
              530  LOAD_STR                 'assert_array_equal'
              532  MAKE_FUNCTION_1          'default'
              534  STORE_NAME               assert_array_equal

 L. 938       536  LOAD_CONST               (6, '', True)
              538  LOAD_CODE                <code_object assert_array_almost_equal>
              540  LOAD_STR                 'assert_array_almost_equal'
              542  MAKE_FUNCTION_1          'default'
              544  STORE_NAME               assert_array_almost_equal

 L.1051       546  LOAD_CONST               ('', True)
              548  LOAD_CODE                <code_object assert_array_less>
              550  LOAD_STR                 'assert_array_less'
              552  MAKE_FUNCTION_1          'default'
              554  STORE_NAME               assert_array_less

 L.1134       556  LOAD_CODE                <code_object runstring>
              558  LOAD_STR                 'runstring'
              560  MAKE_FUNCTION_0          'Neither defaults, keyword-only args, annotations, nor closures'
              562  STORE_NAME               runstring

 L.1138       564  LOAD_CODE                <code_object assert_string_equal>
              566  LOAD_STR                 'assert_string_equal'
              568  MAKE_FUNCTION_0          'Neither defaults, keyword-only args, annotations, nor closures'
              570  STORE_NAME               assert_string_equal

 L.1209       572  LOAD_CONST               (None, True)
              574  LOAD_CODE                <code_object rundocs>
              576  LOAD_STR                 'rundocs'
              578  MAKE_FUNCTION_1          'default'
              580  STORE_NAME               rundocs

 L.1255       582  LOAD_CODE                <code_object raises>
              584  LOAD_STR                 'raises'
              586  MAKE_FUNCTION_0          'Neither defaults, keyword-only args, annotations, nor closures'
              588  STORE_NAME               raises

 L.1295       590  LOAD_CONST               0
              592  LOAD_CONST               None
              594  IMPORT_NAME              unittest
              596  STORE_NAME               unittest

 L.1298       598  LOAD_BUILD_CLASS 
              600  LOAD_CODE                <code_object _Dummy>
              602  LOAD_STR                 '_Dummy'
              604  MAKE_FUNCTION_0          'Neither defaults, keyword-only args, annotations, nor closures'
              606  LOAD_STR                 '_Dummy'
              608  LOAD_NAME                unittest
              610  LOAD_ATTR                TestCase
              612  CALL_FUNCTION_3       3  ''
              614  STORE_NAME               _Dummy

 L.1302       616  LOAD_NAME                _Dummy
              618  LOAD_STR                 'nop'
              620  CALL_FUNCTION_1       1  ''
              622  STORE_NAME               _d

 L.1304       624  LOAD_CODE                <code_object assert_raises>
              626  LOAD_STR                 'assert_raises'
              628  MAKE_FUNCTION_0          'Neither defaults, keyword-only args, annotations, nor closures'
              630  STORE_NAME               assert_raises

 L.1333       632  LOAD_CODE                <code_object assert_raises_regex>
              634  LOAD_STR                 'assert_raises_regex'
              636  MAKE_FUNCTION_0          'Neither defaults, keyword-only args, annotations, nor closures'
              638  STORE_NAME               assert_raises_regex

 L.1357       640  LOAD_CONST               (None,)
              642  LOAD_CODE                <code_object decorate_methods>
              644  LOAD_STR                 'decorate_methods'
              646  MAKE_FUNCTION_1          'default'
              648  STORE_NAME               decorate_methods

 L.1404       650  LOAD_CONST               (1, None)
              652  LOAD_CODE                <code_object measure>
              654  LOAD_STR                 'measure'
              656  MAKE_FUNCTION_1          'default'
              658  STORE_NAME               measure

 L.1450       660  LOAD_CODE                <code_object _assert_valid_refcount>
              662  LOAD_STR                 '_assert_valid_refcount'
              664  MAKE_FUNCTION_0          'Neither defaults, keyword-only args, annotations, nor closures'
              666  STORE_NAME               _assert_valid_refcount

 L.1476       668  LOAD_CONST               (1e-07, 0, True, '', True)
              670  LOAD_CODE                <code_object assert_allclose>
              672  LOAD_STR                 'assert_allclose'
              674  MAKE_FUNCTION_1          'default'
              676  STORE_NAME               assert_allclose

 L.1534       678  LOAD_CONST               (1,)
              680  LOAD_CODE                <code_object assert_array_almost_equal_nulp>
              682  LOAD_STR                 'assert_array_almost_equal_nulp'
              684  MAKE_FUNCTION_1          'default'
              686  STORE_NAME               assert_array_almost_equal_nulp

 L.1597       688  LOAD_CONST               (1, None)
              690  LOAD_CODE                <code_object assert_array_max_ulp>
              692  LOAD_STR                 'assert_array_max_ulp'
              694  MAKE_FUNCTION_1          'default'
              696  STORE_NAME               assert_array_max_ulp

 L.1649       698  LOAD_CONST               (None,)
              700  LOAD_CODE                <code_object nulp_diff>
              702  LOAD_STR                 'nulp_diff'
              704  MAKE_FUNCTION_1          'default'
              706  STORE_NAME               nulp_diff

 L.1712       708  LOAD_CODE                <code_object _integer_repr>
              710  LOAD_STR                 '_integer_repr'
              712  MAKE_FUNCTION_0          'Neither defaults, keyword-only args, annotations, nor closures'
              714  STORE_NAME               _integer_repr

 L.1727       716  LOAD_CODE                <code_object integer_repr>
              718  LOAD_STR                 'integer_repr'
              720  MAKE_FUNCTION_0          'Neither defaults, keyword-only args, annotations, nor closures'
              722  STORE_NAME               integer_repr

 L.1741       724  LOAD_NAME                contextlib
              726  LOAD_ATTR                contextmanager

 L.1742       728  LOAD_CONST               (None,)
              730  LOAD_CODE                <code_object _assert_warns_context>
              732  LOAD_STR                 '_assert_warns_context'
              734  MAKE_FUNCTION_1          'default'
              736  CALL_FUNCTION_1       1  ''
              738  STORE_NAME               _assert_warns_context

 L.1752       740  LOAD_CODE                <code_object assert_warns>
              742  LOAD_STR                 'assert_warns'
              744  MAKE_FUNCTION_0          'Neither defaults, keyword-only args, annotations, nor closures'
              746  STORE_NAME               assert_warns

 L.1806       748  LOAD_NAME                contextlib
              750  LOAD_ATTR                contextmanager

 L.1807       752  LOAD_CONST               (None,)
              754  LOAD_CODE                <code_object _assert_no_warnings_context>
              756  LOAD_STR                 '_assert_no_warnings_context'
              758  MAKE_FUNCTION_1          'default'
              760  CALL_FUNCTION_1       1  ''
              762  STORE_NAME               _assert_no_warnings_context

 L.1817       764  LOAD_CODE                <code_object assert_no_warnings>
              766  LOAD_STR                 'assert_no_warnings'
              768  MAKE_FUNCTION_0          'Neither defaults, keyword-only args, annotations, nor closures'
              770  STORE_NAME               assert_no_warnings

 L.1853       772  LOAD_NAME                float32
              774  LOAD_STR                 'binary'
              776  LOAD_CONST               24
              778  BUILD_TUPLE_3         3 
              780  LOAD_CODE                <code_object _gen_alignment_data>
              782  LOAD_STR                 '_gen_alignment_data'
              784  MAKE_FUNCTION_1          'default'
              786  STORE_NAME               _gen_alignment_data

 L.1922       788  LOAD_BUILD_CLASS 
              790  LOAD_CODE                <code_object IgnoreException>
              792  LOAD_STR                 'IgnoreException'
              794  MAKE_FUNCTION_0          'Neither defaults, keyword-only args, annotations, nor closures'
              796  LOAD_STR                 'IgnoreException'
              798  LOAD_NAME                Exception
              800  CALL_FUNCTION_3       3  ''
              802  STORE_NAME               IgnoreException

 L.1927       804  LOAD_NAME                contextlib
              806  LOAD_ATTR                contextmanager

 L.1928       808  LOAD_CODE                <code_object tempdir>
              810  LOAD_STR                 'tempdir'
              812  MAKE_FUNCTION_0          'Neither defaults, keyword-only args, annotations, nor closures'
              814  CALL_FUNCTION_1       1  ''
              816  STORE_NAME               tempdir

 L.1942       818  LOAD_NAME                contextlib
              820  LOAD_ATTR                contextmanager

 L.1943       822  LOAD_CODE                <code_object temppath>
              824  LOAD_STR                 'temppath'
              826  MAKE_FUNCTION_0          'Neither defaults, keyword-only args, annotations, nor closures'
              828  CALL_FUNCTION_1       1  ''
              830  STORE_NAME               temppath

 L.1964       832  LOAD_BUILD_CLASS 
              834  LOAD_CODE                <code_object clear_and_catch_warnings>
              836  LOAD_STR                 'clear_and_catch_warnings'
              838  MAKE_FUNCTION_0          'Neither defaults, keyword-only args, annotations, nor closures'
              840  LOAD_STR                 'clear_and_catch_warnings'
              842  LOAD_NAME                warnings
              844  LOAD_ATTR                catch_warnings
              846  CALL_FUNCTION_3       3  ''
              848  STORE_NAME               clear_and_catch_warnings

 L.2030       850  LOAD_BUILD_CLASS 
              852  LOAD_CODE                <code_object suppress_warnings>
              854  LOAD_STR                 'suppress_warnings'
              856  MAKE_FUNCTION_0          'Neither defaults, keyword-only args, annotations, nor closures'
              858  LOAD_STR                 'suppress_warnings'
              860  CALL_FUNCTION_2       2  ''
              862  STORE_NAME               suppress_warnings

 L.2308       864  LOAD_NAME                contextlib
              866  LOAD_ATTR                contextmanager

 L.2309       868  LOAD_CONST               (None,)
              870  LOAD_CODE                <code_object _assert_no_gc_cycles_context>
              872  LOAD_STR                 '_assert_no_gc_cycles_context'
              874  MAKE_FUNCTION_1          'default'
              876  CALL_FUNCTION_1       1  ''
              878  STORE_NAME               _assert_no_gc_cycles_context

 L.2360       880  LOAD_CODE                <code_object assert_no_gc_cycles>
              882  LOAD_STR                 'assert_no_gc_cycles'
              884  MAKE_FUNCTION_0          'Neither defaults, keyword-only args, annotations, nor closures'
              886  STORE_NAME               assert_no_gc_cycles

 L.2394       888  LOAD_CODE                <code_object break_cycles>
              890  LOAD_STR                 'break_cycles'
              892  MAKE_FUNCTION_0          'Neither defaults, keyword-only args, annotations, nor closures'
              894  STORE_NAME               break_cycles

 L.2412       896  LOAD_CODE                <code_object requires_memory>
              898  LOAD_STR                 'requires_memory'
              900  MAKE_FUNCTION_0          'Neither defaults, keyword-only args, annotations, nor closures'
              902  STORE_NAME               requires_memory

 L.2434       904  LOAD_CODE                <code_object check_free_memory>
              906  LOAD_STR                 'check_free_memory'
              908  MAKE_FUNCTION_0          'Neither defaults, keyword-only args, annotations, nor closures'
              910  STORE_NAME               check_free_memory

 L.2463       912  LOAD_CODE                <code_object _parse_size>
              914  LOAD_STR                 '_parse_size'
              916  MAKE_FUNCTION_0          'Neither defaults, keyword-only args, annotations, nor closures'
              918  STORE_NAME               _parse_size

 L.2479       920  LOAD_CODE                <code_object _get_mem_available>
              922  LOAD_STR                 '_get_mem_available'
              924  MAKE_FUNCTION_0          'Neither defaults, keyword-only args, annotations, nor closures'
              926  STORE_NAME               _get_mem_available

 L.2503       928  LOAD_CODE                <code_object _no_tracing>
              930  LOAD_STR                 '_no_tracing'
              932  MAKE_FUNCTION_0          'Neither defaults, keyword-only args, annotations, nor closures'
              934  STORE_NAME               _no_tracing

Parse error at or near `CALL_FINALLY' instruction at offset 212

Instruction context:
   
 L.  27       208  BUILD_LIST_0          0 
                 210  LOAD_CONST               ('assert_equal', 'assert_almost_equal', 'assert_approx_equal', 'assert_array_equal', 'assert_array_less', 'assert_string_equal', 'assert_array_almost_equal', 'assert_raises', 'build_err_msg', 'decorate_methods', 'jiffies', 'memusage', 'print_assert_equal', 'raises', 'rundocs', 'runstring', 'verbose', 'measure', 'assert_', 'assert_array_almost_equal_nulp', 'assert_raises_regex', 'assert_array_max_ulp', 'assert_warns', 'assert_no_warnings', 'assert_allclose', 'IgnoreException', 'clear_and_catch_warnings', 'SkipTest', 'KnownFailureException', 'temppath', 'tempdir', 'IS_PYPY', 'HAS_REFCOUNT', 'suppress_warnings', 'assert_array_compare', '_assert_valid_refcount', '_gen_alignment_data', 'assert_no_gc_cycles', 'break_cycles', 'HAS_LAPACK64')
->               212  CALL_FINALLY        215  'to 215'
                 214  STORE_NAME               __all__

test/162681.pyc -- 
# decompile failed
