
# file test/162605.pyc
# --- This code section failed: ---

 L.   1         0  LOAD_STR                 'Array printing function\n\n$Id: arrayprint.py,v 1.9 2005/09/13 13:58:44 teoliphant Exp $\n\n'
                2  STORE_NAME               __doc__

 L.   6         4  BUILD_LIST_0          0 
                6  LOAD_CONST               ('array2string', 'array_str', 'array_repr', 'set_string_function', 'set_printoptions', 'get_printoptions', 'printoptions', 'format_float_positional', 'format_float_scientific')
                8  CALL_FINALLY         11  'to 11'
               10  STORE_NAME               __all__

 L.   9        12  LOAD_STR                 'restructuredtext'
               14  STORE_NAME               __docformat__

 L.  25        16  LOAD_CONST               0
               18  LOAD_CONST               None
               20  IMPORT_NAME              functools
               22  STORE_NAME               functools

 L.  26        24  LOAD_CONST               0
               26  LOAD_CONST               None
               28  IMPORT_NAME              numbers
               30  STORE_NAME               numbers

 L.  27        32  SETUP_FINALLY        50  'to 50'

 L.  28        34  LOAD_CONST               0
               36  LOAD_CONST               ('get_ident',)
               38  IMPORT_NAME              _thread
               40  IMPORT_FROM              get_ident
               42  STORE_NAME               get_ident
               44  POP_TOP          
               46  POP_BLOCK        
               48  JUMP_FORWARD         80  'to 80'
             50_0  COME_FROM_FINALLY    32  '32'

 L.  29        50  DUP_TOP          
               52  LOAD_NAME                ImportError
               54  <121>                78  ''
               56  POP_TOP          
               58  POP_TOP          
               60  POP_TOP          

 L.  30        62  LOAD_CONST               0
               64  LOAD_CONST               ('get_ident',)
               66  IMPORT_NAME              _dummy_thread
               68  IMPORT_FROM              get_ident
               70  STORE_NAME               get_ident
               72  POP_TOP          
               74  POP_EXCEPT       
               76  JUMP_FORWARD         80  'to 80'
               78  <48>             
             80_0  COME_FROM            76  '76'
             80_1  COME_FROM            48  '48'

 L.  32        80  LOAD_CONST               0
               82  LOAD_CONST               None
               84  IMPORT_NAME              numpy
               86  STORE_NAME               np

 L.  33        88  LOAD_CONST               1
               90  LOAD_CONST               ('numerictypes',)
               92  IMPORT_NAME              
               94  IMPORT_FROM              numerictypes
               96  STORE_NAME               _nt
               98  POP_TOP          

 L.  34       100  LOAD_CONST               1
              102  LOAD_CONST               ('absolute', 'isinf', 'isfinite', 'isnat')
              104  IMPORT_NAME              umath
              106  IMPORT_FROM              absolute
              108  STORE_NAME               absolute
              110  IMPORT_FROM              isinf
              112  STORE_NAME               isinf
              114  IMPORT_FROM              isfinite
              116  STORE_NAME               isfinite
              118  IMPORT_FROM              isnat
              120  STORE_NAME               isnat
              122  POP_TOP          

 L.  35       124  LOAD_CONST               1
              126  LOAD_CONST               ('multiarray',)
              128  IMPORT_NAME              
              130  IMPORT_FROM              multiarray
              132  STORE_NAME               multiarray
              134  POP_TOP          

 L.  36       136  LOAD_CONST               1
              138  LOAD_CONST               ('array', 'dragon4_positional', 'dragon4_scientific', 'datetime_as_string', 'datetime_data', 'ndarray', 'set_legacy_print_mode')
              140  IMPORT_NAME              multiarray
              142  IMPORT_FROM              array
              144  STORE_NAME               array
              146  IMPORT_FROM              dragon4_positional
              148  STORE_NAME               dragon4_positional
              150  IMPORT_FROM              dragon4_scientific
              152  STORE_NAME               dragon4_scientific
              154  IMPORT_FROM              datetime_as_string
              156  STORE_NAME               datetime_as_string
              158  IMPORT_FROM              datetime_data
              160  STORE_NAME               datetime_data
              162  IMPORT_FROM              ndarray
              164  STORE_NAME               ndarray
              166  IMPORT_FROM              set_legacy_print_mode
              168  STORE_NAME               set_legacy_print_mode
              170  POP_TOP          

 L.  39       172  LOAD_CONST               1
              174  LOAD_CONST               ('any',)
              176  IMPORT_NAME              fromnumeric
              178  IMPORT_FROM              any
              180  STORE_NAME               any
              182  POP_TOP          

 L.  40       184  LOAD_CONST               1
              186  LOAD_CONST               ('concatenate', 'asarray', 'errstate')
              188  IMPORT_NAME              numeric
              190  IMPORT_FROM              concatenate
              192  STORE_NAME               concatenate
              194  IMPORT_FROM              asarray
              196  STORE_NAME               asarray
              198  IMPORT_FROM              errstate
              200  STORE_NAME               errstate
              202  POP_TOP          

 L.  41       204  LOAD_CONST               1
              206  LOAD_CONST               ('longlong', 'intc', 'int_', 'float_', 'complex_', 'bool_', 'flexible')
              208  IMPORT_NAME              numerictypes
              210  IMPORT_FROM              longlong
              212  STORE_NAME               longlong
              214  IMPORT_FROM              intc
              216  STORE_NAME               intc
              218  IMPORT_FROM              int_
              220  STORE_NAME               int_
              222  IMPORT_FROM              float_
              224  STORE_NAME               float_
              226  IMPORT_FROM              complex_
              228  STORE_NAME               complex_
              230  IMPORT_FROM              bool_
              232  STORE_NAME               bool_
              234  IMPORT_FROM              flexible
              236  STORE_NAME               flexible
              238  POP_TOP          

 L.  43       240  LOAD_CONST               1
              242  LOAD_CONST               ('array_function_dispatch', 'set_module')
              244  IMPORT_NAME              overrides
              246  IMPORT_FROM              array_function_dispatch
              248  STORE_NAME               array_function_dispatch
              250  IMPORT_FROM              set_module
              252  STORE_NAME               set_module
              254  POP_TOP          

 L.  44       256  LOAD_CONST               0
              258  LOAD_CONST               None
              260  IMPORT_NAME              operator
              262  STORE_NAME               operator

 L.  45       264  LOAD_CONST               0
              266  LOAD_CONST               None
              268  IMPORT_NAME              warnings
              270  STORE_NAME               warnings

 L.  46       272  LOAD_CONST               0
              274  LOAD_CONST               None
              276  IMPORT_NAME              contextlib
              278  STORE_NAME               contextlib

 L.  49       280  LOAD_CONST               3

 L.  50       282  LOAD_CONST               1000

 L.  51       284  LOAD_STR                 'maxprec'

 L.  52       286  LOAD_CONST               8

 L.  53       288  LOAD_CONST               False

 L.  54       290  LOAD_CONST               75

 L.  55       292  LOAD_STR                 'nan'

 L.  56       294  LOAD_STR                 'inf'

 L.  57       296  LOAD_STR                 '-'

 L.  58       298  LOAD_CONST               None

 L.  59       300  LOAD_CONST               False

 L.  48       302  LOAD_CONST               ('edgeitems', 'threshold', 'floatmode', 'precision', 'suppress', 'linewidth', 'nanstr', 'infstr', 'sign', 'formatter', 'legacy')
              304  BUILD_CONST_KEY_MAP_11    11 
              306  STORE_NAME               _format_options

 L.  61       308  LOAD_CONST               (None, None, None, None, None, None, None, None, None, None, None)
              310  LOAD_CODE                <code_object _make_options_dict>
              312  LOAD_STR                 '_make_options_dict'
              314  MAKE_FUNCTION_1          'default'
              316  STORE_NAME               _make_options_dict

 L. 101       318  LOAD_NAME                set_module
              320  LOAD_STR                 'numpy'
              322  CALL_FUNCTION_1       1  ''

 L. 102       324  LOAD_CONST               (None, None, None, None, None, None, None, None, None, None)

 L. 104       326  LOAD_CONST               None

 L. 102       328  LOAD_CONST               ('legacy',)
              330  BUILD_CONST_KEY_MAP_1     1 
              332  LOAD_CODE                <code_object set_printoptions>
              334  LOAD_STR                 'set_printoptions'
              336  MAKE_FUNCTION_3          'default, keyword-only'
              338  CALL_FUNCTION_1       1  ''
              340  STORE_NAME               set_printoptions

 L. 268       342  LOAD_NAME                set_module
              344  LOAD_STR                 'numpy'
              346  CALL_FUNCTION_1       1  ''

 L. 269       348  LOAD_CODE                <code_object get_printoptions>
              350  LOAD_STR                 'get_printoptions'
              352  MAKE_FUNCTION_0          'Neither defaults, keyword-only args, annotations, nor closures'
              354  CALL_FUNCTION_1       1  ''
              356  STORE_NAME               get_printoptions

 L. 298       358  LOAD_NAME                set_module
              360  LOAD_STR                 'numpy'
              362  CALL_FUNCTION_1       1  ''

 L. 299       364  LOAD_NAME                contextlib
              366  LOAD_ATTR                contextmanager

 L. 300       368  LOAD_CODE                <code_object printoptions>
              370  LOAD_STR                 'printoptions'
              372  MAKE_FUNCTION_0          'Neither defaults, keyword-only args, annotations, nor closures'
              374  CALL_FUNCTION_1       1  ''
              376  CALL_FUNCTION_1       1  ''
              378  STORE_NAME               printoptions

 L. 333       380  LOAD_CONST               ((),)
              382  LOAD_CODE                <code_object _leading_trailing>
              384  LOAD_STR                 '_leading_trailing'
              386  MAKE_FUNCTION_1          'default'
              388  STORE_NAME               _leading_trailing

 L. 353       390  LOAD_CODE                <code_object _object_format>
              392  LOAD_STR                 '_object_format'
              394  MAKE_FUNCTION_0          'Neither defaults, keyword-only args, annotations, nor closures'
              396  STORE_NAME               _object_format

 L. 361       398  LOAD_CODE                <code_object repr_format>
              400  LOAD_STR                 'repr_format'
              402  MAKE_FUNCTION_0          'Neither defaults, keyword-only args, annotations, nor closures'
              404  STORE_NAME               repr_format

 L. 364       406  LOAD_CODE                <code_object str_format>
              408  LOAD_STR                 'str_format'
              410  MAKE_FUNCTION_0          'Neither defaults, keyword-only args, annotations, nor closures'
              412  STORE_NAME               str_format

 L. 367       414  LOAD_CODE                <code_object _get_formatdict>
              416  LOAD_STR                 '_get_formatdict'
              418  MAKE_FUNCTION_0          'Neither defaults, keyword-only args, annotations, nor closures'
              420  STORE_NAME               _get_formatdict

 L. 416       422  LOAD_CODE                <code_object _get_format_function>
              424  LOAD_STR                 '_get_format_function'
              426  MAKE_FUNCTION_0          'Neither defaults, keyword-only args, annotations, nor closures'
              428  STORE_NAME               _get_format_function

 L. 455       430  LOAD_CONST               ('...',)
              432  LOAD_CODE                <code_object _recursive_guard>
              434  LOAD_STR                 '_recursive_guard'
              436  MAKE_FUNCTION_1          'default'
              438  STORE_NAME               _recursive_guard

 L. 485       440  LOAD_NAME                _recursive_guard
              442  CALL_FUNCTION_0       0  ''

 L. 486       444  LOAD_CONST               (' ', '')
              446  LOAD_CODE                <code_object _array2string>
              448  LOAD_STR                 '_array2string'
              450  MAKE_FUNCTION_1          'default'
              452  CALL_FUNCTION_1       1  ''
              454  STORE_NAME               _array2string

 L. 514       456  LOAD_CONST               (None, None, None, None, None, None, None, None, None, None, None, None)

 L. 519       458  LOAD_CONST               None

 L. 514       460  LOAD_CONST               ('legacy',)
              462  BUILD_CONST_KEY_MAP_1     1 
              464  LOAD_CODE                <code_object _array2string_dispatcher>
              466  LOAD_STR                 '_array2string_dispatcher'
              468  MAKE_FUNCTION_3          'default, keyword-only'
              470  STORE_NAME               _array2string_dispatcher

 L. 523       472  LOAD_NAME                array_function_dispatch
              474  LOAD_NAME                _array2string_dispatcher
              476  LOAD_STR                 'numpy'
              478  LOAD_CONST               ('module',)
              480  CALL_FUNCTION_KW_2     2  '2 total positional and keyword args'

 L. 524       482  LOAD_CONST               None
              484  LOAD_CONST               None

 L. 525       486  LOAD_CONST               None
              488  LOAD_STR                 ' '
              490  LOAD_STR                 ''

 L. 526       492  LOAD_NAME                np
              494  LOAD_ATTR                _NoValue
              496  LOAD_CONST               None
              498  LOAD_CONST               None

 L. 527       500  LOAD_CONST               None
              502  LOAD_CONST               None
              504  LOAD_CONST               None
              506  LOAD_STR                 ''

 L. 524       508  BUILD_TUPLE_12       12 

 L. 528       510  LOAD_CONST               None

 L. 524       512  LOAD_CONST               ('legacy',)
              514  BUILD_CONST_KEY_MAP_1     1 
              516  LOAD_CODE                <code_object array2string>
              518  LOAD_STR                 'array2string'
              520  MAKE_FUNCTION_3          'default, keyword-only'
              522  CALL_FUNCTION_1       1  ''
              524  STORE_NAME               array2string

 L. 701       526  LOAD_CODE                <code_object _extendLine>
              528  LOAD_STR                 '_extendLine'
              530  MAKE_FUNCTION_0          'Neither defaults, keyword-only args, annotations, nor closures'
              532  STORE_NAME               _extendLine

 L. 715       534  LOAD_CODE                <code_object _extendLine_pretty>
              536  LOAD_STR                 '_extendLine_pretty'
              538  MAKE_FUNCTION_0          'Neither defaults, keyword-only args, annotations, nor closures'
              540  STORE_NAME               _extendLine_pretty

 L. 742       542  LOAD_CODE                <code_object _formatArray>
              544  LOAD_STR                 '_formatArray'
              546  MAKE_FUNCTION_0          'Neither defaults, keyword-only args, annotations, nor closures'
              548  STORE_NAME               _formatArray

 L. 860       550  LOAD_CODE                <code_object _none_or_positive_arg>
              552  LOAD_STR                 '_none_or_positive_arg'
              554  MAKE_FUNCTION_0          'Neither defaults, keyword-only args, annotations, nor closures'
              556  STORE_NAME               _none_or_positive_arg

 L. 867       558  LOAD_BUILD_CLASS 
              560  LOAD_CODE                <code_object FloatingFormat>
              562  LOAD_STR                 'FloatingFormat'
              564  MAKE_FUNCTION_0          'Neither defaults, keyword-only args, annotations, nor closures'
              566  LOAD_STR                 'FloatingFormat'
              568  CALL_FUNCTION_2       2  ''
              570  STORE_NAME               FloatingFormat

 L.1012       572  LOAD_NAME                set_module
              574  LOAD_STR                 'numpy'
              576  CALL_FUNCTION_1       1  ''

 L.1013       578  LOAD_CONST               (None, True, 'k', False, None, None, None)
              580  LOAD_CODE                <code_object format_float_scientific>
              582  LOAD_STR                 'format_float_scientific'
              584  MAKE_FUNCTION_1          'default'
              586  CALL_FUNCTION_1       1  ''
              588  STORE_NAME               format_float_scientific

 L.1092       590  LOAD_NAME                set_module
              592  LOAD_STR                 'numpy'
              594  CALL_FUNCTION_1       1  ''

 L.1093       596  LOAD_CONST               (None, True, True, 'k', False, None, None, None)
              598  LOAD_CODE                <code_object format_float_positional>
              600  LOAD_STR                 'format_float_positional'
              602  MAKE_FUNCTION_1          'default'
              604  CALL_FUNCTION_1       1  ''
              606  STORE_NAME               format_float_positional

 L.1184       608  LOAD_BUILD_CLASS 
              610  LOAD_CODE                <code_object IntegerFormat>
              612  LOAD_STR                 'IntegerFormat'
              614  MAKE_FUNCTION_0          'Neither defaults, keyword-only args, annotations, nor closures'
              616  LOAD_STR                 'IntegerFormat'
              618  CALL_FUNCTION_2       2  ''
              620  STORE_NAME               IntegerFormat

 L.1197       622  LOAD_BUILD_CLASS 
              624  LOAD_CODE                <code_object BoolFormat>
              626  LOAD_STR                 'BoolFormat'
              628  MAKE_FUNCTION_0          'Neither defaults, keyword-only args, annotations, nor closures'
              630  LOAD_STR                 'BoolFormat'
              632  CALL_FUNCTION_2       2  ''
              634  STORE_NAME               BoolFormat

 L.1207       636  LOAD_BUILD_CLASS 
              638  LOAD_CODE                <code_object ComplexFloatingFormat>
              640  LOAD_STR                 'ComplexFloatingFormat'
              642  MAKE_FUNCTION_0          'Neither defaults, keyword-only args, annotations, nor closures'
              644  LOAD_STR                 'ComplexFloatingFormat'
              646  CALL_FUNCTION_2       2  ''
              648  STORE_NAME               ComplexFloatingFormat

 L.1240       650  LOAD_BUILD_CLASS 
              652  LOAD_CODE                <code_object _TimelikeFormat>
              654  LOAD_STR                 '_TimelikeFormat'
              656  MAKE_FUNCTION_0          'Neither defaults, keyword-only args, annotations, nor closures'
              658  LOAD_STR                 '_TimelikeFormat'
              660  CALL_FUNCTION_2       2  ''
              662  STORE_NAME               _TimelikeFormat

 L.1266       664  LOAD_BUILD_CLASS 
              666  LOAD_CODE                <code_object DatetimeFormat>
              668  LOAD_STR                 'DatetimeFormat'
              670  MAKE_FUNCTION_0          'Neither defaults, keyword-only args, annotations, nor closures'
              672  LOAD_STR                 'DatetimeFormat'
              674  LOAD_NAME                _TimelikeFormat
              676  CALL_FUNCTION_3       3  ''
              678  STORE_NAME               DatetimeFormat

 L.1298       680  LOAD_BUILD_CLASS 
              682  LOAD_CODE                <code_object TimedeltaFormat>
              684  LOAD_STR                 'TimedeltaFormat'
              686  MAKE_FUNCTION_0          'Neither defaults, keyword-only args, annotations, nor closures'
              688  LOAD_STR                 'TimedeltaFormat'
              690  LOAD_NAME                _TimelikeFormat
              692  CALL_FUNCTION_3       3  ''
              694  STORE_NAME               TimedeltaFormat

 L.1303       696  LOAD_BUILD_CLASS 
              698  LOAD_CODE                <code_object SubArrayFormat>
              700  LOAD_STR                 'SubArrayFormat'
              702  MAKE_FUNCTION_0          'Neither defaults, keyword-only args, annotations, nor closures'
              704  LOAD_STR                 'SubArrayFormat'
              706  CALL_FUNCTION_2       2  ''
              708  STORE_NAME               SubArrayFormat

 L.1313       710  LOAD_BUILD_CLASS 
              712  LOAD_CODE                <code_object StructuredVoidFormat>
              714  LOAD_STR                 'StructuredVoidFormat'
              716  MAKE_FUNCTION_0          'Neither defaults, keyword-only args, annotations, nor closures'
              718  LOAD_STR                 'StructuredVoidFormat'
              720  CALL_FUNCTION_2       2  ''
              722  STORE_NAME               StructuredVoidFormat

 L.1349       724  LOAD_CODE                <code_object _void_scalar_repr>
              726  LOAD_STR                 '_void_scalar_repr'
              728  MAKE_FUNCTION_0          'Neither defaults, keyword-only args, annotations, nor closures'
              730  STORE_NAME               _void_scalar_repr

 L.1358       732  LOAD_NAME                int_
              734  LOAD_NAME                float_
              736  LOAD_NAME                complex_
              738  LOAD_NAME                bool_
              740  BUILD_LIST_4          4 
              742  STORE_NAME               _typelessdata

 L.1359       744  LOAD_NAME                issubclass
              746  LOAD_NAME                intc
              748  LOAD_NAME                int
              750  CALL_FUNCTION_2       2  ''
          752_754  POP_JUMP_IF_FALSE   766  'to 766'

 L.1360       756  LOAD_NAME                _typelessdata
              758  LOAD_METHOD              append
              760  LOAD_NAME                intc
              762  CALL_METHOD_1         1  ''
              764  POP_TOP          
            766_0  COME_FROM           752  '752'

 L.1361       766  LOAD_NAME                issubclass
              768  LOAD_NAME                longlong
              770  LOAD_NAME                int
              772  CALL_FUNCTION_2       2  ''
          774_776  POP_JUMP_IF_FALSE   788  'to 788'

 L.1362       778  LOAD_NAME                _typelessdata
              780  LOAD_METHOD              append
              782  LOAD_NAME                longlong
              784  CALL_METHOD_1         1  ''
              786  POP_TOP          
            788_0  COME_FROM           774  '774'

 L.1365       788  LOAD_CODE                <code_object dtype_is_implied>
              790  LOAD_STR                 'dtype_is_implied'
              792  MAKE_FUNCTION_0          'Neither defaults, keyword-only args, annotations, nor closures'
              794  STORE_NAME               dtype_is_implied

 L.1401       796  LOAD_CODE                <code_object dtype_short_repr>
              798  LOAD_STR                 'dtype_short_repr'
              800  MAKE_FUNCTION_0          'Neither defaults, keyword-only args, annotations, nor closures'
              802  STORE_NAME               dtype_short_repr

 L.1427       804  LOAD_CONST               None
              806  LOAD_CONST               None
              808  LOAD_CONST               None

 L.1428       810  LOAD_NAME                array2string

 L.1426       812  BUILD_TUPLE_4         4 
              814  LOAD_CODE                <code_object _array_repr_implementation>
              816  LOAD_STR                 '_array_repr_implementation'
              818  MAKE_FUNCTION_1          'default'
              820  STORE_NAME               _array_repr_implementation

 L.1473       822  LOAD_CONST               (None, None, None)
              824  LOAD_CODE                <code_object _array_repr_dispatcher>
              826  LOAD_STR                 '_array_repr_dispatcher'
              828  MAKE_FUNCTION_1          'default'
              830  STORE_NAME               _array_repr_dispatcher

 L.1478       832  LOAD_NAME                array_function_dispatch
              834  LOAD_NAME                _array_repr_dispatcher
              836  LOAD_STR                 'numpy'
              838  LOAD_CONST               ('module',)
              840  CALL_FUNCTION_KW_2     2  '2 total positional and keyword args'

 L.1479       842  LOAD_CONST               (None, None, None)
              844  LOAD_CODE                <code_object array_repr>
              846  LOAD_STR                 'array_repr'
              848  MAKE_FUNCTION_1          'default'
              850  CALL_FUNCTION_1       1  ''
              852  STORE_NAME               array_repr

 L.1527       854  LOAD_NAME                _recursive_guard
              856  CALL_FUNCTION_0       0  ''

 L.1528       858  LOAD_CODE                <code_object _guarded_repr_or_str>
              860  LOAD_STR                 '_guarded_repr_or_str'
              862  MAKE_FUNCTION_0          'Neither defaults, keyword-only args, annotations, nor closures'
              864  CALL_FUNCTION_1       1  ''
              866  STORE_NAME               _guarded_repr_or_str

 L.1535       868  LOAD_CONST               None
              870  LOAD_CONST               None
              872  LOAD_CONST               None

 L.1536       874  LOAD_NAME                array2string

 L.1534       876  BUILD_TUPLE_4         4 
              878  LOAD_CODE                <code_object _array_str_implementation>
              880  LOAD_STR                 '_array_str_implementation'
              882  MAKE_FUNCTION_1          'default'
              884  STORE_NAME               _array_str_implementation

 L.1554       886  LOAD_CONST               (None, None, None)
              888  LOAD_CODE                <code_object _array_str_dispatcher>
              890  LOAD_STR                 '_array_str_dispatcher'
              892  MAKE_FUNCTION_1          'default'
              894  STORE_NAME               _array_str_dispatcher

 L.1559       896  LOAD_NAME                array_function_dispatch
              898  LOAD_NAME                _array_str_dispatcher
              900  LOAD_STR                 'numpy'
              902  LOAD_CONST               ('module',)
              904  CALL_FUNCTION_KW_2     2  '2 total positional and keyword args'

 L.1560       906  LOAD_CONST               (None, None, None)
              908  LOAD_CODE                <code_object array_str>
              910  LOAD_STR                 'array_str'
              912  MAKE_FUNCTION_1          'default'
              914  CALL_FUNCTION_1       1  ''
              916  STORE_NAME               array_str

 L.1600       918  LOAD_NAME                getattr
              920  LOAD_NAME                array2string
              922  LOAD_STR                 '__wrapped__'
              924  LOAD_NAME                array2string
              926  CALL_FUNCTION_3       3  ''
              928  STORE_NAME               _array2string_impl

 L.1601       930  LOAD_NAME                functools
              932  LOAD_ATTR                partial
              934  LOAD_NAME                _array_str_implementation

 L.1602       936  LOAD_NAME                _array2string_impl

 L.1601       938  LOAD_CONST               ('array2string',)
              940  CALL_FUNCTION_KW_2     2  '2 total positional and keyword args'
              942  STORE_NAME               _default_array_str

 L.1603       944  LOAD_NAME                functools
              946  LOAD_ATTR                partial
              948  LOAD_NAME                _array_repr_implementation

 L.1604       950  LOAD_NAME                _array2string_impl

 L.1603       952  LOAD_CONST               ('array2string',)
              954  CALL_FUNCTION_KW_2     2  '2 total positional and keyword args'
              956  STORE_NAME               _default_array_repr

 L.1607       958  LOAD_CONST               (True,)
              960  LOAD_CODE                <code_object set_string_function>
              962  LOAD_STR                 'set_string_function'
              964  MAKE_FUNCTION_1          'default'
              966  STORE_NAME               set_string_function

Parse error at or near `CALL_FINALLY' instruction at offset 8

Instruction context:
   
 L.   6         4  BUILD_LIST_0          0 
                   6  LOAD_CONST               ('array2string', 'array_str', 'array_repr', 'set_string_function', 'set_printoptions', 'get_printoptions', 'printoptions', 'format_float_positional', 'format_float_scientific')
->                 8  CALL_FINALLY         11  'to 11'
                  10  STORE_NAME               __all__

test/162605.pyc -- 
# decompile failed
