
# file test/164597.pyc
# --- This code section failed: ---

 L.   1         0  LOAD_CONST               0
                2  LOAD_CONST               None
                4  IMPORT_NAME              functools
                6  STORE_NAME               functools

 L.   2         8  LOAD_CONST               0
               10  LOAD_CONST               None
               12  IMPORT_NAME              sys
               14  STORE_NAME               sys

 L.   3        16  LOAD_CONST               0
               18  LOAD_CONST               None
               20  IMPORT_NAME              math
               22  STORE_NAME               math

 L.   4        24  LOAD_CONST               0
               26  LOAD_CONST               None
               28  IMPORT_NAME              warnings
               30  STORE_NAME               warnings

 L.   6        32  LOAD_CONST               0
               34  LOAD_CONST               None
               36  IMPORT_NAME_ATTR         numpy.core.numeric
               38  IMPORT_FROM              core
               40  ROT_TWO          
               42  POP_TOP          
               44  IMPORT_FROM              numeric
               46  STORE_NAME               _nx
               48  POP_TOP          

 L.   7        50  LOAD_CONST               0
               52  LOAD_CONST               ('asarray', 'ScalarType', 'array', 'alltrue', 'cumprod', 'arange', 'ndim')
               54  IMPORT_NAME_ATTR         numpy.core.numeric
               56  IMPORT_FROM              asarray
               58  STORE_NAME               asarray
               60  IMPORT_FROM              ScalarType
               62  STORE_NAME               ScalarType
               64  IMPORT_FROM              array
               66  STORE_NAME               array
               68  IMPORT_FROM              alltrue
               70  STORE_NAME               alltrue
               72  IMPORT_FROM              cumprod
               74  STORE_NAME               cumprod
               76  IMPORT_FROM              arange
               78  STORE_NAME               arange
               80  IMPORT_FROM              ndim
               82  STORE_NAME               ndim
               84  POP_TOP          

 L.  10        86  LOAD_CONST               0
               88  LOAD_CONST               ('find_common_type', 'issubdtype')
               90  IMPORT_NAME_ATTR         numpy.core.numerictypes
               92  IMPORT_FROM              find_common_type
               94  STORE_NAME               find_common_type
               96  IMPORT_FROM              issubdtype
               98  STORE_NAME               issubdtype
              100  POP_TOP          

 L.  12       102  LOAD_CONST               0
              104  LOAD_CONST               None
              106  IMPORT_NAME_ATTR         numpy.matrixlib
              108  IMPORT_FROM              matrixlib
              110  STORE_NAME               matrixlib
              112  POP_TOP          

 L.  13       114  LOAD_CONST               1
              116  LOAD_CONST               ('diff',)
              118  IMPORT_NAME              function_base
              120  IMPORT_FROM              diff
              122  STORE_NAME               diff
              124  POP_TOP          

 L.  14       126  LOAD_CONST               0
              128  LOAD_CONST               ('ravel_multi_index', 'unravel_index')
              130  IMPORT_NAME_ATTR         numpy.core.multiarray
              132  IMPORT_FROM              ravel_multi_index
              134  STORE_NAME               ravel_multi_index
              136  IMPORT_FROM              unravel_index
              138  STORE_NAME               unravel_index
              140  POP_TOP          

 L.  15       142  LOAD_CONST               0
              144  LOAD_CONST               ('set_module',)
              146  IMPORT_NAME_ATTR         numpy.core.overrides
              148  IMPORT_FROM              set_module
              150  STORE_NAME               set_module
              152  POP_TOP          

 L.  16       154  LOAD_CONST               0
              156  LOAD_CONST               ('overrides', 'linspace')
              158  IMPORT_NAME_ATTR         numpy.core
              160  IMPORT_FROM              overrides
              162  STORE_NAME               overrides
              164  IMPORT_FROM              linspace
              166  STORE_NAME               linspace
              168  POP_TOP          

 L.  17       170  LOAD_CONST               0
              172  LOAD_CONST               ('as_strided',)
              174  IMPORT_NAME_ATTR         numpy.lib.stride_tricks
              176  IMPORT_FROM              as_strided
              178  STORE_NAME               as_strided
              180  POP_TOP          

 L.  20       182  LOAD_NAME                functools
              184  LOAD_ATTR                partial

 L.  21       186  LOAD_NAME                overrides
              188  LOAD_ATTR                array_function_dispatch
              190  LOAD_STR                 'numpy'

 L.  20       192  LOAD_CONST               ('module',)
              194  CALL_FUNCTION_KW_2     2  '2 total positional and keyword args'
              196  STORE_NAME               array_function_dispatch

 L.  24       198  BUILD_LIST_0          0 
              200  LOAD_CONST               ('ravel_multi_index', 'unravel_index', 'mgrid', 'ogrid', 'r_', 'c_', 's_', 'index_exp', 'ix_', 'ndenumerate', 'ndindex', 'fill_diagonal', 'diag_indices', 'diag_indices_from')
              202  CALL_FINALLY        205  'to 205'
              204  STORE_NAME               __all__

 L.  31       206  LOAD_CODE                <code_object _ix__dispatcher>
              208  LOAD_STR                 '_ix__dispatcher'
              210  MAKE_FUNCTION_0          'Neither defaults, keyword-only args, annotations, nor closures'
              212  STORE_NAME               _ix__dispatcher

 L.  35       214  LOAD_NAME                array_function_dispatch
              216  LOAD_NAME                _ix__dispatcher
              218  CALL_FUNCTION_1       1  ''

 L.  36       220  LOAD_CODE                <code_object ix_>
              222  LOAD_STR                 'ix_'
              224  MAKE_FUNCTION_0          'Neither defaults, keyword-only args, annotations, nor closures'
              226  CALL_FUNCTION_1       1  ''
              228  STORE_NAME               ix_

 L. 109       230  LOAD_BUILD_CLASS 
              232  LOAD_CODE                <code_object nd_grid>
              234  LOAD_STR                 'nd_grid'
              236  MAKE_FUNCTION_0          'Neither defaults, keyword-only args, annotations, nor closures'
              238  LOAD_STR                 'nd_grid'
              240  CALL_FUNCTION_2       2  ''
              242  STORE_NAME               nd_grid

 L. 209       244  LOAD_BUILD_CLASS 
              246  LOAD_CODE                <code_object MGridClass>
              248  LOAD_STR                 'MGridClass'
              250  MAKE_FUNCTION_0          'Neither defaults, keyword-only args, annotations, nor closures'
              252  LOAD_STR                 'MGridClass'
              254  LOAD_NAME                nd_grid
              256  CALL_FUNCTION_3       3  ''
              258  STORE_NAME               MGridClass

 L. 254       260  LOAD_NAME                MGridClass
              262  CALL_FUNCTION_0       0  ''
              264  STORE_NAME               mgrid

 L. 256       266  LOAD_BUILD_CLASS 
              268  LOAD_CODE                <code_object OGridClass>
              270  LOAD_STR                 'OGridClass'
              272  MAKE_FUNCTION_0          'Neither defaults, keyword-only args, annotations, nor closures'
              274  LOAD_STR                 'OGridClass'
              276  LOAD_NAME                nd_grid
              278  CALL_FUNCTION_3       3  ''
              280  STORE_NAME               OGridClass

 L. 298       282  LOAD_NAME                OGridClass
              284  CALL_FUNCTION_0       0  ''
              286  STORE_NAME               ogrid

 L. 301       288  LOAD_BUILD_CLASS 
              290  LOAD_CODE                <code_object AxisConcatenator>
              292  LOAD_STR                 'AxisConcatenator'
              294  MAKE_FUNCTION_0          'Neither defaults, keyword-only args, annotations, nor closures'
              296  LOAD_STR                 'AxisConcatenator'
              298  CALL_FUNCTION_2       2  ''
              300  STORE_NAME               AxisConcatenator

 L. 423       302  LOAD_BUILD_CLASS 
              304  LOAD_CODE                <code_object RClass>
              306  LOAD_STR                 'RClass'
              308  MAKE_FUNCTION_0          'Neither defaults, keyword-only args, annotations, nor closures'
              310  LOAD_STR                 'RClass'
              312  LOAD_NAME                AxisConcatenator
              314  CALL_FUNCTION_3       3  ''
              316  STORE_NAME               RClass

 L. 521       318  LOAD_NAME                RClass
              320  CALL_FUNCTION_0       0  ''
              322  STORE_NAME               r_

 L. 523       324  LOAD_BUILD_CLASS 
              326  LOAD_CODE                <code_object CClass>
              328  LOAD_STR                 'CClass'
              330  MAKE_FUNCTION_0          'Neither defaults, keyword-only args, annotations, nor closures'
              332  LOAD_STR                 'CClass'
              334  LOAD_NAME                AxisConcatenator
              336  CALL_FUNCTION_3       3  ''
              338  STORE_NAME               CClass

 L. 552       340  LOAD_NAME                CClass
              342  CALL_FUNCTION_0       0  ''
              344  STORE_NAME               c_

 L. 555       346  LOAD_NAME                set_module
              348  LOAD_STR                 'numpy'
              350  CALL_FUNCTION_1       1  ''

 L. 556       352  LOAD_BUILD_CLASS 
              354  LOAD_CODE                <code_object ndenumerate>
              356  LOAD_STR                 'ndenumerate'
              358  MAKE_FUNCTION_0          'Neither defaults, keyword-only args, annotations, nor closures'
              360  LOAD_STR                 'ndenumerate'
              362  CALL_FUNCTION_2       2  ''
              364  CALL_FUNCTION_1       1  ''
              366  STORE_NAME               ndenumerate

 L. 604       368  LOAD_NAME                set_module
              370  LOAD_STR                 'numpy'
              372  CALL_FUNCTION_1       1  ''

 L. 605       374  LOAD_BUILD_CLASS 
              376  LOAD_CODE                <code_object ndindex>
              378  LOAD_STR                 'ndindex'
              380  MAKE_FUNCTION_0          'Neither defaults, keyword-only args, annotations, nor closures'
              382  LOAD_STR                 'ndindex'
              384  CALL_FUNCTION_2       2  ''
              386  CALL_FUNCTION_1       1  ''
              388  STORE_NAME               ndindex

 L. 701       390  LOAD_BUILD_CLASS 
              392  LOAD_CODE                <code_object IndexExpression>
              394  LOAD_STR                 'IndexExpression'
              396  MAKE_FUNCTION_0          'Neither defaults, keyword-only args, annotations, nor closures'
              398  LOAD_STR                 'IndexExpression'
              400  CALL_FUNCTION_2       2  ''
              402  STORE_NAME               IndexExpression

 L. 754       404  LOAD_NAME                IndexExpression
              406  LOAD_CONST               True
              408  LOAD_CONST               ('maketuple',)
              410  CALL_FUNCTION_KW_1     1  '1 total positional and keyword args'
              412  STORE_NAME               index_exp

 L. 755       414  LOAD_NAME                IndexExpression
              416  LOAD_CONST               False
              418  LOAD_CONST               ('maketuple',)
              420  CALL_FUNCTION_KW_1     1  '1 total positional and keyword args'
              422  STORE_NAME               s_

 L. 764       424  LOAD_CONST               (None,)
              426  LOAD_CODE                <code_object _fill_diagonal_dispatcher>
              428  LOAD_STR                 '_fill_diagonal_dispatcher'
              430  MAKE_FUNCTION_1          'default'
              432  STORE_NAME               _fill_diagonal_dispatcher

 L. 768       434  LOAD_NAME                array_function_dispatch
              436  LOAD_NAME                _fill_diagonal_dispatcher
              438  CALL_FUNCTION_1       1  ''

 L. 769       440  LOAD_CONST               (False,)
              442  LOAD_CODE                <code_object fill_diagonal>
              444  LOAD_STR                 'fill_diagonal'
              446  MAKE_FUNCTION_1          'default'
              448  CALL_FUNCTION_1       1  ''
              450  STORE_NAME               fill_diagonal

 L. 902       452  LOAD_NAME                set_module
              454  LOAD_STR                 'numpy'
              456  CALL_FUNCTION_1       1  ''

 L. 903       458  LOAD_CONST               (2,)
              460  LOAD_CODE                <code_object diag_indices>
              462  LOAD_STR                 'diag_indices'
              464  MAKE_FUNCTION_1          'default'
              466  CALL_FUNCTION_1       1  ''
              468  STORE_NAME               diag_indices

 L. 971       470  LOAD_CODE                <code_object _diag_indices_from>
              472  LOAD_STR                 '_diag_indices_from'
              474  MAKE_FUNCTION_0          'Neither defaults, keyword-only args, annotations, nor closures'
              476  STORE_NAME               _diag_indices_from

 L. 975       478  LOAD_NAME                array_function_dispatch
              480  LOAD_NAME                _diag_indices_from
              482  CALL_FUNCTION_1       1  ''

 L. 976       484  LOAD_CODE                <code_object diag_indices_from>
              486  LOAD_STR                 'diag_indices_from'
              488  MAKE_FUNCTION_0          'Neither defaults, keyword-only args, annotations, nor closures'
              490  CALL_FUNCTION_1       1  ''
              492  STORE_NAME               diag_indices_from

Parse error at or near `CALL_FINALLY' instruction at offset 202

Instruction context:
   
 L.  24       198  BUILD_LIST_0          0 
                 200  LOAD_CONST               ('ravel_multi_index', 'unravel_index', 'mgrid', 'ogrid', 'r_', 'c_', 's_', 'index_exp', 'ix_', 'ndenumerate', 'ndindex', 'fill_diagonal', 'diag_indices', 'diag_indices_from')
->               202  CALL_FINALLY        205  'to 205'
                 204  STORE_NAME               __all__

test/164597.pyc -- 
# decompile failed
