
# file test/164882.pyc
# --- This code section failed: ---

 L.   1         0  LOAD_STR                 '\nSSL with SNI_-support for Python 2. Follow these instructions if you would\nlike to verify SSL certificates in Python 2. Note, the default libraries do\n*not* do certificate checking; you need to do additional work to validate\ncertificates yourself.\n\nThis needs the following packages installed:\n\n* pyOpenSSL (tested with 16.0.0)\n* cryptography (minimum 1.3.4, from pyopenssl)\n* idna (minimum 2.0, from cryptography)\n\nHowever, pyopenssl depends on cryptography, which depends on idna, so while we\nuse all three directly here we end up having relatively few packages required.\n\nYou can install them with the following command:\n\n    pip install pyopenssl cryptography idna\n\nTo activate certificate checking, call\n:func:`~urllib3.contrib.pyopenssl.inject_into_urllib3` from your Python code\nbefore you begin making HTTP requests. This can be done in a ``sitecustomize``\nmodule, or at any other time before your application begins using ``urllib3``,\nlike this::\n\n    try:\n        import urllib3.contrib.pyopenssl\n        urllib3.contrib.pyopenssl.inject_into_urllib3()\n    except ImportError:\n        pass\n\nNow you can use :mod:`urllib3` as you normally would, and it will support SNI\nwhen the required modules are installed.\n\nActivating this module also has the positive side effect of disabling SSL/TLS\ncompression in Python 2 (see `CRIME attack`_).\n\nIf you want to configure the default list of supported cipher suites, you can\nset the ``urllib3.contrib.pyopenssl.DEFAULT_SSL_CIPHER_LIST`` variable.\n\n.. _sni: https://en.wikipedia.org/wiki/Server_Name_Indication\n.. _crime attack: https://en.wikipedia.org/wiki/CRIME_(security_exploit)\n'
                2  STORE_NAME               __doc__

 L.  44         4  LOAD_CONST               0
                6  LOAD_CONST               ('absolute_import',)
                8  IMPORT_NAME              __future__
               10  IMPORT_FROM              absolute_import
               12  STORE_NAME               absolute_import
               14  POP_TOP          

 L.  46        16  LOAD_CONST               0
               18  LOAD_CONST               None
               20  IMPORT_NAME_ATTR         OpenSSL.SSL
               22  STORE_NAME               OpenSSL

 L.  47        24  LOAD_CONST               0
               26  LOAD_CONST               ('x509',)
               28  IMPORT_NAME              cryptography
               30  IMPORT_FROM              x509
               32  STORE_NAME               x509
               34  POP_TOP          

 L.  48        36  LOAD_CONST               0
               38  LOAD_CONST               ('backend',)
               40  IMPORT_NAME_ATTR         cryptography.hazmat.backends.openssl
               42  IMPORT_FROM              backend
               44  STORE_NAME               openssl_backend
               46  POP_TOP          

 L.  49        48  LOAD_CONST               0
               50  LOAD_CONST               ('_Certificate',)
               52  IMPORT_NAME_ATTR         cryptography.hazmat.backends.openssl.x509
               54  IMPORT_FROM              _Certificate
               56  STORE_NAME               _Certificate
               58  POP_TOP          

 L.  51        60  SETUP_FINALLY        78  'to 78'

 L.  52        62  LOAD_CONST               0
               64  LOAD_CONST               ('UnsupportedExtension',)
               66  IMPORT_NAME_ATTR         cryptography.x509
               68  IMPORT_FROM              UnsupportedExtension
               70  STORE_NAME               UnsupportedExtension
               72  POP_TOP          
               74  POP_BLOCK        
               76  JUMP_FORWARD        112  'to 112'
             78_0  COME_FROM_FINALLY    60  '60'

 L.  53        78  DUP_TOP          
               80  LOAD_NAME                ImportError
               82  <121>               110  ''
               84  POP_TOP          
               86  POP_TOP          
               88  POP_TOP          

 L.  55        90  LOAD_BUILD_CLASS 
               92  LOAD_CODE                <code_object UnsupportedExtension>
               94  LOAD_STR                 'UnsupportedExtension'
               96  MAKE_FUNCTION_0          'Neither defaults, keyword-only args, annotations, nor closures'
               98  LOAD_STR                 'UnsupportedExtension'
              100  LOAD_NAME                Exception
              102  CALL_FUNCTION_3       3  ''
              104  STORE_NAME               UnsupportedExtension
              106  POP_EXCEPT       
              108  JUMP_FORWARD        112  'to 112'
              110  <48>             
            112_0  COME_FROM           108  '108'
            112_1  COME_FROM            76  '76'

 L.  59       112  LOAD_CONST               0
              114  LOAD_CONST               ('timeout', 'error')
              116  IMPORT_NAME              socket
              118  IMPORT_FROM              timeout
              120  STORE_NAME               timeout
              122  IMPORT_FROM              error
              124  STORE_NAME               SocketError
              126  POP_TOP          

 L.  60       128  LOAD_CONST               0
              130  LOAD_CONST               ('BytesIO',)
              132  IMPORT_NAME              io
              134  IMPORT_FROM              BytesIO
              136  STORE_NAME               BytesIO
              138  POP_TOP          

 L.  62       140  SETUP_FINALLY       158  'to 158'

 L.  63       142  LOAD_CONST               0
              144  LOAD_CONST               ('_fileobject',)
              146  IMPORT_NAME              socket
              148  IMPORT_FROM              _fileobject
              150  STORE_NAME               _fileobject
              152  POP_TOP          
              154  POP_BLOCK        
              156  JUMP_FORWARD        192  'to 192'
            158_0  COME_FROM_FINALLY   140  '140'

 L.  64       158  DUP_TOP          
              160  LOAD_NAME                ImportError
              162  <121>               190  ''
              164  POP_TOP          
              166  POP_TOP          
              168  POP_TOP          

 L.  65       170  LOAD_CONST               None
              172  STORE_NAME               _fileobject

 L.  66       174  LOAD_CONST               2
              176  LOAD_CONST               ('backport_makefile',)
              178  IMPORT_NAME_ATTR         packages.backports.makefile
              180  IMPORT_FROM              backport_makefile
              182  STORE_NAME               backport_makefile
              184  POP_TOP          
              186  POP_EXCEPT       
              188  JUMP_FORWARD        192  'to 192'
              190  <48>             
            192_0  COME_FROM           188  '188'
            192_1  COME_FROM           156  '156'

 L.  68       192  LOAD_CONST               0
              194  LOAD_CONST               None
              196  IMPORT_NAME              logging
              198  STORE_NAME               logging

 L.  69       200  LOAD_CONST               0
              202  LOAD_CONST               None
              204  IMPORT_NAME              ssl
              206  STORE_NAME               ssl

 L.  70       208  LOAD_CONST               2
              210  LOAD_CONST               ('six',)
              212  IMPORT_NAME              packages
              214  IMPORT_FROM              six
              216  STORE_NAME               six
              218  POP_TOP          

 L.  71       220  LOAD_CONST               0
              222  LOAD_CONST               None
              224  IMPORT_NAME              sys
              226  STORE_NAME               sys

 L.  73       228  LOAD_CONST               2
              230  LOAD_CONST               ('util',)
              232  IMPORT_NAME              
              234  IMPORT_FROM              util
              236  STORE_NAME               util
              238  POP_TOP          

 L.  76       240  LOAD_STR                 'inject_into_urllib3'
              242  LOAD_STR                 'extract_from_urllib3'
              244  BUILD_LIST_2          2 
              246  STORE_NAME               __all__

 L.  79       248  LOAD_CONST               True
              250  STORE_NAME               HAS_SNI

 L.  83       252  LOAD_NAME                util
              254  LOAD_ATTR                PROTOCOL_TLS
              256  LOAD_NAME                OpenSSL
              258  LOAD_ATTR                SSL
              260  LOAD_ATTR                SSLv23_METHOD

 L.  84       262  LOAD_NAME                ssl
              264  LOAD_ATTR                PROTOCOL_TLSv1
              266  LOAD_NAME                OpenSSL
              268  LOAD_ATTR                SSL
              270  LOAD_ATTR                TLSv1_METHOD

 L.  82       272  BUILD_MAP_2           2 
              274  STORE_NAME               _openssl_versions

 L.  87       276  LOAD_NAME                hasattr
              278  LOAD_NAME                ssl
              280  LOAD_STR                 'PROTOCOL_SSLv3'
              282  CALL_FUNCTION_2       2  ''
          284_286  POP_JUMP_IF_FALSE   316  'to 316'
              288  LOAD_NAME                hasattr
              290  LOAD_NAME                OpenSSL
              292  LOAD_ATTR                SSL
              294  LOAD_STR                 'SSLv3_METHOD'
              296  CALL_FUNCTION_2       2  ''
          298_300  POP_JUMP_IF_FALSE   316  'to 316'

 L.  88       302  LOAD_NAME                OpenSSL
              304  LOAD_ATTR                SSL
              306  LOAD_ATTR                SSLv3_METHOD
              308  LOAD_NAME                _openssl_versions
              310  LOAD_NAME                ssl
              312  LOAD_ATTR                PROTOCOL_SSLv3
              314  STORE_SUBSCR     
            316_0  COME_FROM           298  '298'
            316_1  COME_FROM           284  '284'

 L.  90       316  LOAD_NAME                hasattr
              318  LOAD_NAME                ssl
              320  LOAD_STR                 'PROTOCOL_TLSv1_1'
              322  CALL_FUNCTION_2       2  ''
          324_326  POP_JUMP_IF_FALSE   356  'to 356'
              328  LOAD_NAME                hasattr
              330  LOAD_NAME                OpenSSL
              332  LOAD_ATTR                SSL
              334  LOAD_STR                 'TLSv1_1_METHOD'
              336  CALL_FUNCTION_2       2  ''
          338_340  POP_JUMP_IF_FALSE   356  'to 356'

 L.  91       342  LOAD_NAME                OpenSSL
              344  LOAD_ATTR                SSL
              346  LOAD_ATTR                TLSv1_1_METHOD
              348  LOAD_NAME                _openssl_versions
              350  LOAD_NAME                ssl
              352  LOAD_ATTR                PROTOCOL_TLSv1_1
              354  STORE_SUBSCR     
            356_0  COME_FROM           338  '338'
            356_1  COME_FROM           324  '324'

 L.  93       356  LOAD_NAME                hasattr
              358  LOAD_NAME                ssl
              360  LOAD_STR                 'PROTOCOL_TLSv1_2'
              362  CALL_FUNCTION_2       2  ''
          364_366  POP_JUMP_IF_FALSE   396  'to 396'
              368  LOAD_NAME                hasattr
              370  LOAD_NAME                OpenSSL
              372  LOAD_ATTR                SSL
              374  LOAD_STR                 'TLSv1_2_METHOD'
              376  CALL_FUNCTION_2       2  ''
          378_380  POP_JUMP_IF_FALSE   396  'to 396'

 L.  94       382  LOAD_NAME                OpenSSL
              384  LOAD_ATTR                SSL
              386  LOAD_ATTR                TLSv1_2_METHOD
              388  LOAD_NAME                _openssl_versions
              390  LOAD_NAME                ssl
              392  LOAD_ATTR                PROTOCOL_TLSv1_2
              394  STORE_SUBSCR     
            396_0  COME_FROM           378  '378'
            396_1  COME_FROM           364  '364'

 L.  98       396  LOAD_NAME                ssl
              398  LOAD_ATTR                CERT_NONE
              400  LOAD_NAME                OpenSSL
              402  LOAD_ATTR                SSL
              404  LOAD_ATTR                VERIFY_NONE

 L.  99       406  LOAD_NAME                ssl
              408  LOAD_ATTR                CERT_OPTIONAL
              410  LOAD_NAME                OpenSSL
              412  LOAD_ATTR                SSL
              414  LOAD_ATTR                VERIFY_PEER

 L. 100       416  LOAD_NAME                ssl
              418  LOAD_ATTR                CERT_REQUIRED
              420  LOAD_NAME                OpenSSL
              422  LOAD_ATTR                SSL
              424  LOAD_ATTR                VERIFY_PEER

 L. 101       426  LOAD_NAME                OpenSSL
              428  LOAD_ATTR                SSL
              430  LOAD_ATTR                VERIFY_FAIL_IF_NO_PEER_CERT

 L. 100       432  BINARY_ADD       

 L.  97       434  BUILD_MAP_3           3 
              436  STORE_NAME               _stdlib_to_openssl_verify

 L. 103       438  LOAD_NAME                dict
              440  LOAD_GENEXPR             '<code_object <genexpr>>'
              442  LOAD_STR                 '<genexpr>'
              444  MAKE_FUNCTION_0          'Neither defaults, keyword-only args, annotations, nor closures'
              446  LOAD_NAME                _stdlib_to_openssl_verify
              448  LOAD_METHOD              items
              450  CALL_METHOD_0         0  ''
              452  GET_ITER         
              454  CALL_FUNCTION_1       1  ''
              456  CALL_FUNCTION_1       1  ''
              458  STORE_NAME               _openssl_to_stdlib_verify

 L. 106       460  LOAD_CONST               16384
              462  STORE_NAME               SSL_WRITE_BLOCKSIZE

 L. 108       464  LOAD_NAME                util
              466  LOAD_ATTR                HAS_SNI
              468  STORE_NAME               orig_util_HAS_SNI

 L. 109       470  LOAD_NAME                util
              472  LOAD_ATTR                ssl_
              474  LOAD_ATTR                SSLContext
              476  STORE_NAME               orig_util_SSLContext

 L. 112       478  LOAD_NAME                logging
              480  LOAD_METHOD              getLogger
              482  LOAD_NAME                __name__
              484  CALL_METHOD_1         1  ''
              486  STORE_NAME               log

 L. 115       488  LOAD_CODE                <code_object inject_into_urllib3>
              490  LOAD_STR                 'inject_into_urllib3'
              492  MAKE_FUNCTION_0          'Neither defaults, keyword-only args, annotations, nor closures'
              494  STORE_NAME               inject_into_urllib3

 L. 128       496  LOAD_CODE                <code_object extract_from_urllib3>
              498  LOAD_STR                 'extract_from_urllib3'
              500  MAKE_FUNCTION_0          'Neither defaults, keyword-only args, annotations, nor closures'
              502  STORE_NAME               extract_from_urllib3

 L. 139       504  LOAD_CODE                <code_object _validate_dependencies_met>
              506  LOAD_STR                 '_validate_dependencies_met'
              508  MAKE_FUNCTION_0          'Neither defaults, keyword-only args, annotations, nor closures'
              510  STORE_NAME               _validate_dependencies_met

 L. 165       512  LOAD_CODE                <code_object _dnsname_to_stdlib>
              514  LOAD_STR                 '_dnsname_to_stdlib'
              516  MAKE_FUNCTION_0          'Neither defaults, keyword-only args, annotations, nor closures'
              518  STORE_NAME               _dnsname_to_stdlib

 L. 208       520  LOAD_CODE                <code_object get_subj_alt_name>
              522  LOAD_STR                 'get_subj_alt_name'
              524  MAKE_FUNCTION_0          'Neither defaults, keyword-only args, annotations, nor closures'
              526  STORE_NAME               get_subj_alt_name

 L. 262       528  LOAD_BUILD_CLASS 
              530  LOAD_CODE                <code_object WrappedSocket>
              532  LOAD_STR                 'WrappedSocket'
              534  MAKE_FUNCTION_0          'Neither defaults, keyword-only args, annotations, nor closures'
              536  LOAD_STR                 'WrappedSocket'
              538  LOAD_NAME                object
              540  CALL_FUNCTION_3       3  ''
              542  STORE_NAME               WrappedSocket

 L. 397       544  LOAD_NAME                _fileobject
          546_548  POP_JUMP_IF_FALSE   562  'to 562'

 L. 399       550  LOAD_CONST               (-1,)
              552  LOAD_CODE                <code_object makefile>
              554  LOAD_STR                 'makefile'
              556  MAKE_FUNCTION_1          'default'
              558  STORE_NAME               makefile
              560  JUMP_FORWARD        566  'to 566'
            562_0  COME_FROM           546  '546'

 L. 405       562  LOAD_NAME                backport_makefile
              564  STORE_NAME               makefile
            566_0  COME_FROM           560  '560'

 L. 407       566  LOAD_NAME                makefile
              568  LOAD_NAME                WrappedSocket
              570  STORE_ATTR               makefile

 L. 410       572  LOAD_BUILD_CLASS 
              574  LOAD_CODE                <code_object PyOpenSSLContext>
              576  LOAD_STR                 'PyOpenSSLContext'
              578  MAKE_FUNCTION_0          'Neither defaults, keyword-only args, annotations, nor closures'
              580  LOAD_STR                 'PyOpenSSLContext'
              582  LOAD_NAME                object
              584  CALL_FUNCTION_3       3  ''
              586  STORE_NAME               PyOpenSSLContext

 L. 500       588  LOAD_CODE                <code_object _verify_callback>
              590  LOAD_STR                 '_verify_callback'
              592  MAKE_FUNCTION_0          'Neither defaults, keyword-only args, annotations, nor closures'
              594  STORE_NAME               _verify_callback

Parse error at or near `<121>' instruction at offset 82

Instruction context:
   
 L.  53        78  DUP_TOP          
                  80  LOAD_NAME                ImportError
->                82  <121>               110  ''
                  84  POP_TOP          
                  86  POP_TOP          
                  88  POP_TOP          

test/164882.pyc -- 
# decompile failed
