
# file test/164878.pyc
# --- This code section failed: ---

 L.   1         0  LOAD_CONST               0
                2  LOAD_CONST               ('absolute_import',)
                4  IMPORT_NAME              __future__
                6  IMPORT_FROM              absolute_import
                8  STORE_NAME               absolute_import
               10  POP_TOP          

 L.   2        12  LOAD_CONST               0
               14  LOAD_CONST               ('contextmanager',)
               16  IMPORT_NAME              contextlib
               18  IMPORT_FROM              contextmanager
               20  STORE_NAME               contextmanager
               22  POP_TOP          

 L.   3        24  LOAD_CONST               0
               26  LOAD_CONST               None
               28  IMPORT_NAME              zlib
               30  STORE_NAME               zlib

 L.   4        32  LOAD_CONST               0
               34  LOAD_CONST               None
               36  IMPORT_NAME              io
               38  STORE_NAME               io

 L.   5        40  LOAD_CONST               0
               42  LOAD_CONST               None
               44  IMPORT_NAME              logging
               46  STORE_NAME               logging

 L.   6        48  LOAD_CONST               0
               50  LOAD_CONST               ('timeout',)
               52  IMPORT_NAME              socket
               54  IMPORT_FROM              timeout
               56  STORE_NAME               SocketTimeout
               58  POP_TOP          

 L.   7        60  LOAD_CONST               0
               62  LOAD_CONST               ('error',)
               64  IMPORT_NAME              socket
               66  IMPORT_FROM              error
               68  STORE_NAME               SocketError
               70  POP_TOP          

 L.   9        72  SETUP_FINALLY        86  'to 86'

 L.  10        74  LOAD_CONST               0
               76  LOAD_CONST               None
               78  IMPORT_NAME              brotli
               80  STORE_NAME               brotli
               82  POP_BLOCK        
               84  JUMP_FORWARD        108  'to 108'
             86_0  COME_FROM_FINALLY    72  '72'

 L.  11        86  DUP_TOP          
               88  LOAD_NAME                ImportError
               90  <121>               106  ''
               92  POP_TOP          
               94  POP_TOP          
               96  POP_TOP          

 L.  12        98  LOAD_CONST               None
              100  STORE_NAME               brotli
              102  POP_EXCEPT       
              104  JUMP_FORWARD        108  'to 108'
              106  <48>             
            108_0  COME_FROM           104  '104'
            108_1  COME_FROM            84  '84'

 L.  14       108  LOAD_CONST               1
              110  LOAD_CONST               ('HTTPHeaderDict',)
              112  IMPORT_NAME              _collections
              114  IMPORT_FROM              HTTPHeaderDict
              116  STORE_NAME               HTTPHeaderDict
              118  POP_TOP          

 L.  15       120  LOAD_CONST               1
              122  LOAD_CONST               ('BodyNotHttplibCompatible', 'ProtocolError', 'DecodeError', 'ReadTimeoutError', 'ResponseNotChunked', 'IncompleteRead', 'InvalidHeader', 'HTTPError')
              124  IMPORT_NAME              exceptions
              126  IMPORT_FROM              BodyNotHttplibCompatible
              128  STORE_NAME               BodyNotHttplibCompatible
              130  IMPORT_FROM              ProtocolError
              132  STORE_NAME               ProtocolError
              134  IMPORT_FROM              DecodeError
              136  STORE_NAME               DecodeError
              138  IMPORT_FROM              ReadTimeoutError
              140  STORE_NAME               ReadTimeoutError
              142  IMPORT_FROM              ResponseNotChunked
              144  STORE_NAME               ResponseNotChunked
              146  IMPORT_FROM              IncompleteRead
              148  STORE_NAME               IncompleteRead
              150  IMPORT_FROM              InvalidHeader
              152  STORE_NAME               InvalidHeader
              154  IMPORT_FROM              HTTPError
              156  STORE_NAME               HTTPError
              158  POP_TOP          

 L.  25       160  LOAD_CONST               1
              162  LOAD_CONST               ('string_types', 'PY3')
              164  IMPORT_NAME_ATTR         packages.six
              166  IMPORT_FROM              string_types
              168  STORE_NAME               basestring
              170  IMPORT_FROM              PY3
              172  STORE_NAME               PY3
              174  POP_TOP          

 L.  26       176  LOAD_CONST               1
              178  LOAD_CONST               ('http_client',)
              180  IMPORT_NAME_ATTR         packages.six.moves
              182  IMPORT_FROM              http_client
              184  STORE_NAME               httplib
              186  POP_TOP          

 L.  27       188  LOAD_CONST               1
              190  LOAD_CONST               ('HTTPException', 'BaseSSLError')
              192  IMPORT_NAME              connection
              194  IMPORT_FROM              HTTPException
              196  STORE_NAME               HTTPException
              198  IMPORT_FROM              BaseSSLError
              200  STORE_NAME               BaseSSLError
              202  POP_TOP          

 L.  28       204  LOAD_CONST               1
              206  LOAD_CONST               ('is_fp_closed', 'is_response_to_head')
              208  IMPORT_NAME_ATTR         util.response
              210  IMPORT_FROM              is_fp_closed
              212  STORE_NAME               is_fp_closed
              214  IMPORT_FROM              is_response_to_head
              216  STORE_NAME               is_response_to_head
              218  POP_TOP          

 L.  30       220  LOAD_NAME                logging
              222  LOAD_METHOD              getLogger
              224  LOAD_NAME                __name__
              226  CALL_METHOD_1         1  ''
              228  STORE_NAME               log

 L.  33       230  LOAD_BUILD_CLASS 
              232  LOAD_CODE                <code_object DeflateDecoder>
              234  LOAD_STR                 'DeflateDecoder'
              236  MAKE_FUNCTION_0          'Neither defaults, keyword-only args, annotations, nor closures'
              238  LOAD_STR                 'DeflateDecoder'
              240  LOAD_NAME                object
              242  CALL_FUNCTION_3       3  ''
              244  STORE_NAME               DeflateDecoder

 L.  65       246  LOAD_BUILD_CLASS 
              248  LOAD_CODE                <code_object GzipDecoderState>
              250  LOAD_STR                 'GzipDecoderState'
              252  MAKE_FUNCTION_0          'Neither defaults, keyword-only args, annotations, nor closures'
              254  LOAD_STR                 'GzipDecoderState'
              256  LOAD_NAME                object
              258  CALL_FUNCTION_3       3  ''
              260  STORE_NAME               GzipDecoderState

 L.  72       262  LOAD_BUILD_CLASS 
              264  LOAD_CODE                <code_object GzipDecoder>
              266  LOAD_STR                 'GzipDecoder'
              268  MAKE_FUNCTION_0          'Neither defaults, keyword-only args, annotations, nor closures'
              270  LOAD_STR                 'GzipDecoder'
              272  LOAD_NAME                object
              274  CALL_FUNCTION_3       3  ''
              276  STORE_NAME               GzipDecoder

 L. 102       278  LOAD_NAME                brotli
              280  LOAD_CONST               None
              282  <117>                 1  ''
          284_286  POP_JUMP_IF_FALSE   304  'to 304'

 L. 104       288  LOAD_BUILD_CLASS 
              290  LOAD_CODE                <code_object BrotliDecoder>
              292  LOAD_STR                 'BrotliDecoder'
              294  MAKE_FUNCTION_0          'Neither defaults, keyword-only args, annotations, nor closures'
              296  LOAD_STR                 'BrotliDecoder'
              298  LOAD_NAME                object
              300  CALL_FUNCTION_3       3  ''
              302  STORE_NAME               BrotliDecoder
            304_0  COME_FROM           284  '284'

 L. 121       304  LOAD_BUILD_CLASS 
              306  LOAD_CODE                <code_object MultiDecoder>
              308  LOAD_STR                 'MultiDecoder'
              310  MAKE_FUNCTION_0          'Neither defaults, keyword-only args, annotations, nor closures'
              312  LOAD_STR                 'MultiDecoder'
              314  LOAD_NAME                object
              316  CALL_FUNCTION_3       3  ''
              318  STORE_NAME               MultiDecoder

 L. 142       320  LOAD_CODE                <code_object _get_decoder>
              322  LOAD_STR                 '_get_decoder'
              324  MAKE_FUNCTION_0          'Neither defaults, keyword-only args, annotations, nor closures'
              326  STORE_NAME               _get_decoder

 L. 155       328  LOAD_BUILD_CLASS 
              330  LOAD_CODE                <code_object HTTPResponse>
              332  LOAD_STR                 'HTTPResponse'
              334  MAKE_FUNCTION_0          'Neither defaults, keyword-only args, annotations, nor closures'
              336  LOAD_STR                 'HTTPResponse'
              338  LOAD_NAME                io
              340  LOAD_ATTR                IOBase
              342  CALL_FUNCTION_3       3  ''
              344  STORE_NAME               HTTPResponse

Parse error at or near `<121>' instruction at offset 90

Instruction context:
   
 L.  11        86  DUP_TOP          
                  88  LOAD_NAME                ImportError
->                90  <121>               106  ''
                  92  POP_TOP          
                  94  POP_TOP          
                  96  POP_TOP          

test/164878.pyc -- 
# decompile failed
