
# file test/2019.pyc
# --- This code section failed: ---

 L.   1         0  LOAD_STR                 "\n**Note:** almost all functions in the ``numpy.lib`` namespace\nare also present in the main ``numpy`` namespace.  Please use the\nfunctions as ``np.<funcname>`` where possible.\n\n``numpy.lib`` is mostly a space for implementing functions that don't\nbelong in core or in another NumPy submodule with a clear purpose\n(e.g. ``random``, ``fft``, ``linalg``, ``ma``).\n\nMost contains basic functions that are used by several submodules and are\nuseful to have in the main name-space.\n\n"
                2  STORE_NAME               __doc__

 L.  14         4  LOAD_CONST               0
                6  LOAD_CONST               None
                8  IMPORT_NAME              math
               10  STORE_NAME               math

 L.  16        12  LOAD_CONST               0
               14  LOAD_CONST               ('version',)
               16  IMPORT_NAME_ATTR         numpy.version
               18  IMPORT_FROM              version
               20  STORE_NAME               __version__
               22  POP_TOP          

 L.  20        24  LOAD_CONST               1
               26  LOAD_CONST               ('mixins',)
               28  IMPORT_NAME              
               30  IMPORT_FROM              mixins
               32  STORE_NAME               mixins
               34  POP_TOP          

 L.  21        36  LOAD_CONST               1
               38  LOAD_CONST               ('scimath',)
               40  IMPORT_NAME              
               42  IMPORT_FROM              scimath
               44  STORE_NAME               emath
               46  POP_TOP          

 L.  24        48  LOAD_CONST               1
               50  LOAD_CONST               ('*',)
               52  IMPORT_NAME              type_check
               54  IMPORT_STAR      

 L.  25        56  LOAD_CONST               1
               58  LOAD_CONST               ('*',)
               60  IMPORT_NAME              index_tricks
               62  IMPORT_STAR      

 L.  26        64  LOAD_CONST               1
               66  LOAD_CONST               ('*',)
               68  IMPORT_NAME              function_base
               70  IMPORT_STAR      

 L.  27        72  LOAD_CONST               1
               74  LOAD_CONST               ('*',)
               76  IMPORT_NAME              nanfunctions
               78  IMPORT_STAR      

 L.  28        80  LOAD_CONST               1
               82  LOAD_CONST               ('*',)
               84  IMPORT_NAME              shape_base
               86  IMPORT_STAR      

 L.  29        88  LOAD_CONST               1
               90  LOAD_CONST               ('*',)
               92  IMPORT_NAME              stride_tricks
               94  IMPORT_STAR      

 L.  30        96  LOAD_CONST               1
               98  LOAD_CONST               ('*',)
              100  IMPORT_NAME              twodim_base
              102  IMPORT_STAR      

 L.  31       104  LOAD_CONST               1
              106  LOAD_CONST               ('*',)
              108  IMPORT_NAME              ufunclike
              110  IMPORT_STAR      

 L.  32       112  LOAD_CONST               1
              114  LOAD_CONST               ('*',)
              116  IMPORT_NAME              histograms
              118  IMPORT_STAR      

 L.  34       120  LOAD_CONST               1
              122  LOAD_CONST               ('*',)
              124  IMPORT_NAME              polynomial
              126  IMPORT_STAR      

 L.  35       128  LOAD_CONST               1
              130  LOAD_CONST               ('*',)
              132  IMPORT_NAME              utils
              134  IMPORT_STAR      

 L.  36       136  LOAD_CONST               1
              138  LOAD_CONST               ('*',)
              140  IMPORT_NAME              arraysetops
              142  IMPORT_STAR      

 L.  37       144  LOAD_CONST               1
              146  LOAD_CONST               ('*',)
              148  IMPORT_NAME              npyio
              150  IMPORT_STAR      

 L.  38       152  LOAD_CONST               1
              154  LOAD_CONST               ('*',)
              156  IMPORT_NAME              financial
              158  IMPORT_STAR      

 L.  39       160  LOAD_CONST               1
              162  LOAD_CONST               ('Arrayterator',)
              164  IMPORT_NAME              arrayterator
              166  IMPORT_FROM              Arrayterator
              168  STORE_NAME               Arrayterator
              170  POP_TOP          

 L.  40       172  LOAD_CONST               1
              174  LOAD_CONST               ('*',)
              176  IMPORT_NAME              arraypad
              178  IMPORT_STAR      

 L.  41       180  LOAD_CONST               1
              182  LOAD_CONST               ('*',)
              184  IMPORT_NAME              _version
              186  IMPORT_STAR      

 L.  42       188  LOAD_CONST               0
              190  LOAD_CONST               ('tracemalloc_domain',)
              192  IMPORT_NAME_ATTR         numpy.core._multiarray_umath
              194  IMPORT_FROM              tracemalloc_domain
              196  STORE_NAME               tracemalloc_domain
              198  POP_TOP          

 L.  44       200  BUILD_LIST_0          0 
              202  LOAD_CONST               ('emath', 'math', 'tracemalloc_domain', 'Arrayterator')
              204  CALL_FINALLY        207  'to 207'
              206  STORE_NAME               __all__

 L.  45       208  LOAD_NAME                __all__
              210  LOAD_NAME                type_check
              212  LOAD_ATTR                __all__
              214  INPLACE_ADD      
              216  STORE_NAME               __all__

 L.  46       218  LOAD_NAME                __all__
              220  LOAD_NAME                index_tricks
              222  LOAD_ATTR                __all__
              224  INPLACE_ADD      
              226  STORE_NAME               __all__

 L.  47       228  LOAD_NAME                __all__
              230  LOAD_NAME                function_base
              232  LOAD_ATTR                __all__
              234  INPLACE_ADD      
              236  STORE_NAME               __all__

 L.  48       238  LOAD_NAME                __all__
              240  LOAD_NAME                shape_base
              242  LOAD_ATTR                __all__
              244  INPLACE_ADD      
              246  STORE_NAME               __all__

 L.  49       248  LOAD_NAME                __all__
              250  LOAD_NAME                stride_tricks
              252  LOAD_ATTR                __all__
              254  INPLACE_ADD      
              256  STORE_NAME               __all__

 L.  50       258  LOAD_NAME                __all__
              260  LOAD_NAME                twodim_base
              262  LOAD_ATTR                __all__
              264  INPLACE_ADD      
              266  STORE_NAME               __all__

 L.  51       268  LOAD_NAME                __all__
              270  LOAD_NAME                ufunclike
              272  LOAD_ATTR                __all__
              274  INPLACE_ADD      
              276  STORE_NAME               __all__

 L.  52       278  LOAD_NAME                __all__
              280  LOAD_NAME                arraypad
              282  LOAD_ATTR                __all__
              284  INPLACE_ADD      
              286  STORE_NAME               __all__

 L.  53       288  LOAD_NAME                __all__
              290  LOAD_NAME                polynomial
              292  LOAD_ATTR                __all__
              294  INPLACE_ADD      
              296  STORE_NAME               __all__

 L.  54       298  LOAD_NAME                __all__
              300  LOAD_NAME                utils
              302  LOAD_ATTR                __all__
              304  INPLACE_ADD      
              306  STORE_NAME               __all__

 L.  55       308  LOAD_NAME                __all__
              310  LOAD_NAME                arraysetops
              312  LOAD_ATTR                __all__
              314  INPLACE_ADD      
              316  STORE_NAME               __all__

 L.  56       318  LOAD_NAME                __all__
              320  LOAD_NAME                npyio
              322  LOAD_ATTR                __all__
              324  INPLACE_ADD      
              326  STORE_NAME               __all__

 L.  57       328  LOAD_NAME                __all__
              330  LOAD_NAME                financial
              332  LOAD_ATTR                __all__
              334  INPLACE_ADD      
              336  STORE_NAME               __all__

 L.  58       338  LOAD_NAME                __all__
              340  LOAD_NAME                nanfunctions
              342  LOAD_ATTR                __all__
              344  INPLACE_ADD      
              346  STORE_NAME               __all__

 L.  59       348  LOAD_NAME                __all__
              350  LOAD_NAME                histograms
              352  LOAD_ATTR                __all__
              354  INPLACE_ADD      
              356  STORE_NAME               __all__

 L.  61       358  LOAD_CONST               0
              360  LOAD_CONST               ('PytestTester',)
              362  IMPORT_NAME_ATTR         numpy._pytesttester
              364  IMPORT_FROM              PytestTester
              366  STORE_NAME               PytestTester
              368  POP_TOP          

 L.  62       370  LOAD_NAME                PytestTester
              372  LOAD_NAME                __name__
              374  CALL_FUNCTION_1       1  ''
              376  STORE_NAME               test

 L.  63       378  DELETE_NAME              PytestTester

Parse error at or near `CALL_FINALLY' instruction at offset 204

Instruction context:
   
 L.  44       200  BUILD_LIST_0          0 
                 202  LOAD_CONST               ('emath', 'math', 'tracemalloc_domain', 'Arrayterator')
->               204  CALL_FINALLY        207  'to 207'
                 206  STORE_NAME               __all__

test/2019.pyc -- 
# decompile failed
