
# file test/31725.pyc
# --- This code section failed: ---

 L.   9         0  LOAD_CONST               0
                2  LOAD_CONST               None
                4  IMPORT_NAME              sys
                6  STORE_NAME               sys

 L.  11         8  LOAD_CONST               0
               10  LOAD_CONST               ('error',)
               12  IMPORT_NAME_ATTR         pyasn1.type
               14  IMPORT_FROM              error
               16  STORE_NAME               error
               18  POP_TOP          

 L.  13        20  BUILD_LIST_0          0 
               22  LOAD_CONST               ('SingleValueConstraint', 'ContainedSubtypeConstraint', 'ValueRangeConstraint', 'ValueSizeConstraint', 'PermittedAlphabetConstraint', 'InnerTypeConstraint', 'ConstraintsExclusion', 'ConstraintsIntersection', 'ConstraintsUnion')
               24  CALL_FINALLY         27  'to 27'
               26  STORE_NAME               __all__

 L.  20        28  LOAD_BUILD_CLASS 
               30  LOAD_CODE                <code_object AbstractConstraint>
               32  LOAD_STR                 'AbstractConstraint'
               34  MAKE_FUNCTION_0          'Neither defaults, keyword-only args, annotations, nor closures'
               36  LOAD_STR                 'AbstractConstraint'
               38  LOAD_NAME                object
               40  CALL_FUNCTION_3       3  ''
               42  STORE_NAME               AbstractConstraint

 L. 100        44  LOAD_BUILD_CLASS 
               46  LOAD_CODE                <code_object SingleValueConstraint>
               48  LOAD_STR                 'SingleValueConstraint'
               50  MAKE_FUNCTION_0          'Neither defaults, keyword-only args, annotations, nor closures'
               52  LOAD_STR                 'SingleValueConstraint'
               54  LOAD_NAME                AbstractConstraint
               56  CALL_FUNCTION_3       3  ''
               58  STORE_NAME               SingleValueConstraint

 L. 163        60  LOAD_BUILD_CLASS 
               62  LOAD_CODE                <code_object ContainedSubtypeConstraint>
               64  LOAD_STR                 'ContainedSubtypeConstraint'
               66  MAKE_FUNCTION_0          'Neither defaults, keyword-only args, annotations, nor closures'
               68  LOAD_STR                 'ContainedSubtypeConstraint'
               70  LOAD_NAME                AbstractConstraint
               72  CALL_FUNCTION_3       3  ''
               74  STORE_NAME               ContainedSubtypeConstraint

 L. 207        76  LOAD_BUILD_CLASS 
               78  LOAD_CODE                <code_object ValueRangeConstraint>
               80  LOAD_STR                 'ValueRangeConstraint'
               82  MAKE_FUNCTION_0          'Neither defaults, keyword-only args, annotations, nor closures'
               84  LOAD_STR                 'ValueRangeConstraint'
               86  LOAD_NAME                AbstractConstraint
               88  CALL_FUNCTION_3       3  ''
               90  STORE_NAME               ValueRangeConstraint

 L. 263        92  LOAD_BUILD_CLASS 
               94  LOAD_CODE                <code_object ValueSizeConstraint>
               96  LOAD_STR                 'ValueSizeConstraint'
               98  MAKE_FUNCTION_0          'Neither defaults, keyword-only args, annotations, nor closures'
              100  LOAD_STR                 'ValueSizeConstraint'
              102  LOAD_NAME                ValueRangeConstraint
              104  CALL_FUNCTION_3       3  ''
              106  STORE_NAME               ValueSizeConstraint

 L. 323       108  LOAD_BUILD_CLASS 
              110  LOAD_CODE                <code_object PermittedAlphabetConstraint>
              112  LOAD_STR                 'PermittedAlphabetConstraint'
              114  MAKE_FUNCTION_0          'Neither defaults, keyword-only args, annotations, nor closures'
              116  LOAD_STR                 'PermittedAlphabetConstraint'
              118  LOAD_NAME                SingleValueConstraint
              120  CALL_FUNCTION_3       3  ''
              122  STORE_NAME               PermittedAlphabetConstraint

 L. 407       124  LOAD_BUILD_CLASS 
              126  LOAD_CODE                <code_object ComponentPresentConstraint>
              128  LOAD_STR                 'ComponentPresentConstraint'
              130  MAKE_FUNCTION_0          'Neither defaults, keyword-only args, annotations, nor closures'
              132  LOAD_STR                 'ComponentPresentConstraint'
              134  LOAD_NAME                AbstractConstraint
              136  CALL_FUNCTION_3       3  ''
              138  STORE_NAME               ComponentPresentConstraint

 L. 440       140  LOAD_BUILD_CLASS 
              142  LOAD_CODE                <code_object ComponentAbsentConstraint>
              144  LOAD_STR                 'ComponentAbsentConstraint'
              146  MAKE_FUNCTION_0          'Neither defaults, keyword-only args, annotations, nor closures'
              148  LOAD_STR                 'ComponentAbsentConstraint'
              150  LOAD_NAME                AbstractConstraint
              152  CALL_FUNCTION_3       3  ''
              154  STORE_NAME               ComponentAbsentConstraint

 L. 473       156  LOAD_BUILD_CLASS 
              158  LOAD_CODE                <code_object WithComponentsConstraint>
              160  LOAD_STR                 'WithComponentsConstraint'
              162  MAKE_FUNCTION_0          'Neither defaults, keyword-only args, annotations, nor closures'
              164  LOAD_STR                 'WithComponentsConstraint'
              166  LOAD_NAME                AbstractConstraint
              168  CALL_FUNCTION_3       3  ''
              170  STORE_NAME               WithComponentsConstraint

 L. 553       172  LOAD_BUILD_CLASS 
              174  LOAD_CODE                <code_object InnerTypeConstraint>
              176  LOAD_STR                 'InnerTypeConstraint'
              178  MAKE_FUNCTION_0          'Neither defaults, keyword-only args, annotations, nor closures'
              180  LOAD_STR                 'InnerTypeConstraint'
              182  LOAD_NAME                AbstractConstraint
              184  CALL_FUNCTION_3       3  ''
              186  STORE_NAME               InnerTypeConstraint

 L. 580       188  LOAD_BUILD_CLASS 
              190  LOAD_CODE                <code_object ConstraintsExclusion>
              192  LOAD_STR                 'ConstraintsExclusion'
              194  MAKE_FUNCTION_0          'Neither defaults, keyword-only args, annotations, nor closures'
              196  LOAD_STR                 'ConstraintsExclusion'
              198  LOAD_NAME                AbstractConstraint
              200  CALL_FUNCTION_3       3  ''
              202  STORE_NAME               ConstraintsExclusion

 L. 629       204  LOAD_BUILD_CLASS 
              206  LOAD_CODE                <code_object AbstractConstraintSet>
              208  LOAD_STR                 'AbstractConstraintSet'
              210  MAKE_FUNCTION_0          'Neither defaults, keyword-only args, annotations, nor closures'
              212  LOAD_STR                 'AbstractConstraintSet'
              214  LOAD_NAME                AbstractConstraint
              216  CALL_FUNCTION_3       3  ''
              218  STORE_NAME               AbstractConstraintSet

 L. 656       220  LOAD_BUILD_CLASS 
              222  LOAD_CODE                <code_object ConstraintsIntersection>
              224  LOAD_STR                 'ConstraintsIntersection'
              226  MAKE_FUNCTION_0          'Neither defaults, keyword-only args, annotations, nor closures'
              228  LOAD_STR                 'ConstraintsIntersection'
              230  LOAD_NAME                AbstractConstraintSet
              232  CALL_FUNCTION_3       3  ''
              234  STORE_NAME               ConstraintsIntersection

 L. 700       236  LOAD_BUILD_CLASS 
              238  LOAD_CODE                <code_object ConstraintsUnion>
              240  LOAD_STR                 'ConstraintsUnion'
              242  MAKE_FUNCTION_0          'Neither defaults, keyword-only args, annotations, nor closures'
              244  LOAD_STR                 'ConstraintsUnion'
              246  LOAD_NAME                AbstractConstraintSet
              248  CALL_FUNCTION_3       3  ''
              250  STORE_NAME               ConstraintsUnion

Parse error at or near `CALL_FINALLY' instruction at offset 24

Instruction context:
   
 L.  13        20  BUILD_LIST_0          0 
                  22  LOAD_CONST               ('SingleValueConstraint', 'ContainedSubtypeConstraint', 'ValueRangeConstraint', 'ValueSizeConstraint', 'PermittedAlphabetConstraint', 'InnerTypeConstraint', 'ConstraintsExclusion', 'ConstraintsIntersection', 'ConstraintsUnion')
->                24  CALL_FINALLY         27  'to 27'
                  26  STORE_NAME               __all__

test/31725.pyc -- 
# decompile failed
