Instruction context:
   
 L.  16        80  BUILD_LIST_0          0 
                  82  LOAD_CONST               ('ObjectDescriptor', 'GeneralizedTime', 'UTCTime')
->                84  CALL_FINALLY         87  'to 87'
                  86  STORE_NAME               __all__

test/31732.pyc -- 
# decompile failed

# file test/31732.pyc
# --- This code section failed: ---

 L.   7         0  LOAD_CONST               0
                2  LOAD_CONST               None
                4  IMPORT_NAME              datetime
                6  STORE_NAME               datetime

 L.   9         8  LOAD_CONST               0
               10  LOAD_CONST               ('error',)
               12  IMPORT_NAME              pyasn1
               14  IMPORT_FROM              error
               16  STORE_NAME               error
               18  POP_TOP          

 L.  10        20  LOAD_CONST               0
               22  LOAD_CONST               ('dateandtime',)
               24  IMPORT_NAME_ATTR         pyasn1.compat
               26  IMPORT_FROM              dateandtime
               28  STORE_NAME               dateandtime
               30  POP_TOP          

 L.  11        32  LOAD_CONST               0
               34  LOAD_CONST               ('string',)
               36  IMPORT_NAME_ATTR         pyasn1.compat
               38  IMPORT_FROM              string
               40  STORE_NAME               string
               42  POP_TOP          

 L.  12        44  LOAD_CONST               0
               46  LOAD_CONST               ('char',)
               48  IMPORT_NAME_ATTR         pyasn1.type
               50  IMPORT_FROM              char
               52  STORE_NAME               char
               54  POP_TOP          

 L.  13        56  LOAD_CONST               0
               58  LOAD_CONST               ('tag',)
               60  IMPORT_NAME_ATTR         pyasn1.type
               62  IMPORT_FROM              tag
               64  STORE_NAME               tag
               66  POP_TOP          

 L.  14        68  LOAD_CONST               0
               70  LOAD_CONST               ('univ',)
               72  IMPORT_NAME_ATTR         pyasn1.type
               74  IMPORT_FROM              univ
               76  STORE_NAME               univ
               78  POP_TOP          

 L.  16        80  BUILD_LIST_0          0 
               82  LOAD_CONST               ('ObjectDescriptor', 'GeneralizedTime', 'UTCTime')
               84  CALL_FINALLY         87  'to 87'
               86  STORE_NAME               __all__

 L.  18        88  LOAD_NAME                univ
               90  LOAD_ATTR                NoValue
               92  STORE_NAME               NoValue

 L.  19        94  LOAD_NAME                univ
               96  LOAD_ATTR                noValue
               98  STORE_NAME               noValue

 L.  22       100  LOAD_BUILD_CLASS 
              102  LOAD_CODE                <code_object ObjectDescriptor>
              104  LOAD_STR                 'ObjectDescriptor'
              106  MAKE_FUNCTION_0          'Neither defaults, keyword-only args, annotations, nor closures'
              108  LOAD_STR                 'ObjectDescriptor'
              110  LOAD_NAME                char
              112  LOAD_ATTR                GraphicString
              114  CALL_FUNCTION_3       3  ''
              116  STORE_NAME               ObjectDescriptor

 L.  34       118  LOAD_BUILD_CLASS 
              120  LOAD_CODE                <code_object TimeMixIn>
              122  LOAD_STR                 'TimeMixIn'
              124  MAKE_FUNCTION_0          'Neither defaults, keyword-only args, annotations, nor closures'
              126  LOAD_STR                 'TimeMixIn'
              128  LOAD_NAME                object
              130  CALL_FUNCTION_3       3  ''
              132  STORE_NAME               TimeMixIn

 L. 160       134  LOAD_BUILD_CLASS 
              136  LOAD_CODE                <code_object GeneralizedTime>
              138  LOAD_STR                 'GeneralizedTime'
              140  MAKE_FUNCTION_0          'Neither defaults, keyword-only args, annotations, nor closures'
              142  LOAD_STR                 'GeneralizedTime'
              144  LOAD_NAME                char
              146  LOAD_ATTR                VisibleString
              148  LOAD_NAME                TimeMixIn
              150  CALL_FUNCTION_4       4  ''
              152  STORE_NAME               GeneralizedTime

 L. 177       154  LOAD_BUILD_CLASS 
              156  LOAD_CODE                <code_object UTCTime>
              158  LOAD_STR                 'UTCTime'
              160  MAKE_FUNCTION_0          'Neither defaults, keyword-only args, annotations, nor closures'
              162  LOAD_STR                 'UTCTime'
              164  LOAD_NAME                char
              166  LOAD_ATTR                VisibleString
              168  LOAD_NAME                TimeMixIn
              170  CALL_FUNCTION_4       4  ''
              172  STORE_NAME               UTCTime

Parse error at or near `CALL_FINALLY' instruction at offset 84

