
# file test/31795.pyc
# --- This code section failed: ---

 L.   1         0  LOAD_STR                 '\nEasy Install\n------------\n\nA tool for doing automatic download/extract/build of distutils-based Python\npackages.  For detailed documentation, see the accompanying EasyInstall.txt\nfile, or visit the `EasyInstall home page`__.\n\n__ https://setuptools.readthedocs.io/en/latest/easy_install.html\n\n'
                2  STORE_NAME               __doc__

 L.  13         4  LOAD_CONST               0
                6  LOAD_CONST               ('glob',)
                8  IMPORT_NAME              glob
               10  IMPORT_FROM              glob
               12  STORE_NAME               glob
               14  POP_TOP          

 L.  14        16  LOAD_CONST               0
               18  LOAD_CONST               ('get_platform',)
               20  IMPORT_NAME_ATTR         distutils.util
               22  IMPORT_FROM              get_platform
               24  STORE_NAME               get_platform
               26  POP_TOP          

 L.  15        28  LOAD_CONST               0
               30  LOAD_CONST               ('convert_path', 'subst_vars')
               32  IMPORT_NAME_ATTR         distutils.util
               34  IMPORT_FROM              convert_path
               36  STORE_NAME               convert_path
               38  IMPORT_FROM              subst_vars
               40  STORE_NAME               subst_vars
               42  POP_TOP          

 L.  16        44  LOAD_CONST               0
               46  LOAD_CONST               ('DistutilsArgError', 'DistutilsOptionError', 'DistutilsError', 'DistutilsPlatformError')
               48  IMPORT_NAME_ATTR         distutils.errors
               50  IMPORT_FROM              DistutilsArgError
               52  STORE_NAME               DistutilsArgError
               54  IMPORT_FROM              DistutilsOptionError
               56  STORE_NAME               DistutilsOptionError
               58  IMPORT_FROM              DistutilsError
               60  STORE_NAME               DistutilsError
               62  IMPORT_FROM              DistutilsPlatformError
               64  STORE_NAME               DistutilsPlatformError
               66  POP_TOP          

 L.  20        68  LOAD_CONST               0
               70  LOAD_CONST               ('INSTALL_SCHEMES', 'SCHEME_KEYS')
               72  IMPORT_NAME_ATTR         distutils.command.install
               74  IMPORT_FROM              INSTALL_SCHEMES
               76  STORE_NAME               INSTALL_SCHEMES
               78  IMPORT_FROM              SCHEME_KEYS
               80  STORE_NAME               SCHEME_KEYS
               82  POP_TOP          

 L.  21        84  LOAD_CONST               0
               86  LOAD_CONST               ('log', 'dir_util')
               88  IMPORT_NAME              distutils
               90  IMPORT_FROM              log
               92  STORE_NAME               log
               94  IMPORT_FROM              dir_util
               96  STORE_NAME               dir_util
               98  POP_TOP          

 L.  22       100  LOAD_CONST               0
              102  LOAD_CONST               ('first_line_re',)
              104  IMPORT_NAME_ATTR         distutils.command.build_scripts
              106  IMPORT_FROM              first_line_re
              108  STORE_NAME               first_line_re
              110  POP_TOP          

 L.  23       112  LOAD_CONST               0
              114  LOAD_CONST               ('find_executable',)
              116  IMPORT_NAME_ATTR         distutils.spawn
              118  IMPORT_FROM              find_executable
              120  STORE_NAME               find_executable
              122  POP_TOP          

 L.  24       124  LOAD_CONST               0
              126  LOAD_CONST               None
              128  IMPORT_NAME              sys
              130  STORE_NAME               sys

 L.  25       132  LOAD_CONST               0
              134  LOAD_CONST               None
              136  IMPORT_NAME              os
              138  STORE_NAME               os

 L.  26       140  LOAD_CONST               0
              142  LOAD_CONST               None
              144  IMPORT_NAME              zipimport
              146  STORE_NAME               zipimport

 L.  27       148  LOAD_CONST               0
              150  LOAD_CONST               None
              152  IMPORT_NAME              shutil
              154  STORE_NAME               shutil

 L.  28       156  LOAD_CONST               0
              158  LOAD_CONST               None
              160  IMPORT_NAME              tempfile
              162  STORE_NAME               tempfile

 L.  29       164  LOAD_CONST               0
              166  LOAD_CONST               None
              168  IMPORT_NAME              zipfile
              170  STORE_NAME               zipfile

 L.  30       172  LOAD_CONST               0
              174  LOAD_CONST               None
              176  IMPORT_NAME              re
              178  STORE_NAME               re

 L.  31       180  LOAD_CONST               0
              182  LOAD_CONST               None
              184  IMPORT_NAME              stat
              186  STORE_NAME               stat

 L.  32       188  LOAD_CONST               0
              190  LOAD_CONST               None
              192  IMPORT_NAME              random
              194  STORE_NAME               random

 L.  33       196  LOAD_CONST               0
              198  LOAD_CONST               None
              200  IMPORT_NAME              textwrap
              202  STORE_NAME               textwrap

 L.  34       204  LOAD_CONST               0
              206  LOAD_CONST               None
              208  IMPORT_NAME              warnings
              210  STORE_NAME               warnings

 L.  35       212  LOAD_CONST               0
              214  LOAD_CONST               None
              216  IMPORT_NAME              site
              218  STORE_NAME               site

 L.  36       220  LOAD_CONST               0
              222  LOAD_CONST               None
              224  IMPORT_NAME              struct
              226  STORE_NAME               struct

 L.  37       228  LOAD_CONST               0
              230  LOAD_CONST               None
              232  IMPORT_NAME              contextlib
              234  STORE_NAME               contextlib

 L.  38       236  LOAD_CONST               0
              238  LOAD_CONST               None
              240  IMPORT_NAME              subprocess
              242  STORE_NAME               subprocess

 L.  39       244  LOAD_CONST               0
              246  LOAD_CONST               None
              248  IMPORT_NAME              shlex
              250  STORE_NAME               shlex

 L.  40       252  LOAD_CONST               0
              254  LOAD_CONST               None
              256  IMPORT_NAME              io
              258  STORE_NAME               io

 L.  43       260  LOAD_CONST               0
              262  LOAD_CONST               ('get_config_vars', 'get_path')
              264  IMPORT_NAME              sysconfig
              266  IMPORT_FROM              get_config_vars
              268  STORE_NAME               get_config_vars
              270  IMPORT_FROM              get_path
              272  STORE_NAME               get_path
              274  POP_TOP          

 L.  45       276  LOAD_CONST               0
              278  LOAD_CONST               ('SetuptoolsDeprecationWarning',)
              280  IMPORT_NAME              setuptools
              282  IMPORT_FROM              SetuptoolsDeprecationWarning
              284  STORE_NAME               SetuptoolsDeprecationWarning
              286  POP_TOP          

 L.  47       288  LOAD_CONST               0
              290  LOAD_CONST               ('six',)
              292  IMPORT_NAME_ATTR         setuptools.extern
              294  IMPORT_FROM              six
              296  STORE_NAME               six
              298  POP_TOP          

 L.  48       300  LOAD_CONST               0
              302  LOAD_CONST               ('configparser', 'map')
              304  IMPORT_NAME_ATTR         setuptools.extern.six.moves
              306  IMPORT_FROM              configparser
              308  STORE_NAME               configparser
              310  IMPORT_FROM              map
              312  STORE_NAME               map
              314  POP_TOP          

 L.  50       316  LOAD_CONST               0
              318  LOAD_CONST               ('Command',)
              320  IMPORT_NAME              setuptools
              322  IMPORT_FROM              Command
              324  STORE_NAME               Command
              326  POP_TOP          

 L.  51       328  LOAD_CONST               0
              330  LOAD_CONST               ('run_setup',)
              332  IMPORT_NAME_ATTR         setuptools.sandbox
              334  IMPORT_FROM              run_setup
              336  STORE_NAME               run_setup
              338  POP_TOP          

 L.  52       340  LOAD_CONST               0
              342  LOAD_CONST               ('rmtree_safe',)
              344  IMPORT_NAME_ATTR         setuptools.py27compat
              346  IMPORT_FROM              rmtree_safe
              348  STORE_NAME               rmtree_safe
              350  POP_TOP          

 L.  53       352  LOAD_CONST               0
              354  LOAD_CONST               ('setopt',)
              356  IMPORT_NAME_ATTR         setuptools.command
              358  IMPORT_FROM              setopt
              360  STORE_NAME               setopt
              362  POP_TOP          

 L.  54       364  LOAD_CONST               0
              366  LOAD_CONST               ('unpack_archive',)
              368  IMPORT_NAME_ATTR         setuptools.archive_util
              370  IMPORT_FROM              unpack_archive
              372  STORE_NAME               unpack_archive
              374  POP_TOP          

 L.  55       376  LOAD_CONST               0
              378  LOAD_CONST               ('PackageIndex', 'parse_requirement_arg', 'URL_SCHEME')
              380  IMPORT_NAME_ATTR         setuptools.package_index
              382  IMPORT_FROM              PackageIndex
              384  STORE_NAME               PackageIndex
              386  IMPORT_FROM              parse_requirement_arg
              388  STORE_NAME               parse_requirement_arg
              390  IMPORT_FROM              URL_SCHEME
              392  STORE_NAME               URL_SCHEME
              394  POP_TOP          

 L.  58       396  LOAD_CONST               0
              398  LOAD_CONST               ('bdist_egg', 'egg_info')
              400  IMPORT_NAME_ATTR         setuptools.command
              402  IMPORT_FROM              bdist_egg
              404  STORE_NAME               bdist_egg
              406  IMPORT_FROM              egg_info
              408  STORE_NAME               egg_info
              410  POP_TOP          

 L.  59       412  LOAD_CONST               0
              414  LOAD_CONST               ('Wheel',)
              416  IMPORT_NAME_ATTR         setuptools.wheel
              418  IMPORT_FROM              Wheel
              420  STORE_NAME               Wheel
              422  POP_TOP          

 L.  60       424  LOAD_CONST               0
              426  LOAD_CONST               ('yield_lines', 'normalize_path', 'resource_string', 'ensure_directory', 'get_distribution', 'find_distributions', 'Environment', 'Requirement', 'Distribution', 'PathMetadata', 'EggMetadata', 'WorkingSet', 'DistributionNotFound', 'VersionConflict', 'DEVELOP_DIST')
              428  IMPORT_NAME              pkg_resources
              430  IMPORT_FROM              yield_lines
              432  STORE_NAME               yield_lines
              434  IMPORT_FROM              normalize_path
              436  STORE_NAME               normalize_path
              438  IMPORT_FROM              resource_string
              440  STORE_NAME               resource_string
              442  IMPORT_FROM              ensure_directory
              444  STORE_NAME               ensure_directory
              446  IMPORT_FROM              get_distribution
              448  STORE_NAME               get_distribution
              450  IMPORT_FROM              find_distributions
              452  STORE_NAME               find_distributions
              454  IMPORT_FROM              Environment
              456  STORE_NAME               Environment
              458  IMPORT_FROM              Requirement
              460  STORE_NAME               Requirement
              462  IMPORT_FROM              Distribution
              464  STORE_NAME               Distribution
              466  IMPORT_FROM              PathMetadata
              468  STORE_NAME               PathMetadata
              470  IMPORT_FROM              EggMetadata
              472  STORE_NAME               EggMetadata
              474  IMPORT_FROM              WorkingSet
              476  STORE_NAME               WorkingSet
              478  IMPORT_FROM              DistributionNotFound
              480  STORE_NAME               DistributionNotFound
              482  IMPORT_FROM              VersionConflict
              484  STORE_NAME               VersionConflict
              486  IMPORT_FROM              DEVELOP_DIST
              488  STORE_NAME               DEVELOP_DIST
              490  POP_TOP          

 L.  66       492  LOAD_CONST               0
              494  LOAD_CONST               None
              496  IMPORT_NAME              pkg_resources
              498  STORE_NAME               pkg_resources

 L.  68       500  LOAD_NAME                type
              502  STORE_NAME               __metaclass__

 L.  71       504  LOAD_NAME                warnings
              506  LOAD_ATTR                filterwarnings
              508  LOAD_STR                 'default'
              510  LOAD_NAME                pkg_resources
              512  LOAD_ATTR                PEP440Warning
              514  LOAD_CONST               ('category',)
              516  CALL_FUNCTION_KW_2     2  '2 total positional and keyword args'
              518  POP_TOP          

 L.  73       520  BUILD_LIST_0          0 
              522  LOAD_CONST               ('samefile', 'easy_install', 'PthDistributions', 'extract_wininst_cfg', 'main', 'get_exe_prefixes')
              524  CALL_FINALLY        527  'to 527'
              526  STORE_NAME               __all__

 L.  79       528  LOAD_CODE                <code_object is_64bit>
              530  LOAD_STR                 'is_64bit'
              532  MAKE_FUNCTION_0          'Neither defaults, keyword-only args, annotations, nor closures'
              534  STORE_NAME               is_64bit

 L.  83       536  LOAD_CODE                <code_object samefile>
              538  LOAD_STR                 'samefile'
              540  MAKE_FUNCTION_0          'Neither defaults, keyword-only args, annotations, nor closures'
              542  STORE_NAME               samefile

 L.  99       544  LOAD_NAME                six
              546  LOAD_ATTR                PY2
          548_550  POP_JUMP_IF_FALSE   570  'to 570'

 L. 101       552  LOAD_CODE                <code_object _to_bytes>
              554  LOAD_STR                 '_to_bytes'
              556  MAKE_FUNCTION_0          'Neither defaults, keyword-only args, annotations, nor closures'
              558  STORE_NAME               _to_bytes

 L. 104       560  LOAD_CODE                <code_object isascii>
              562  LOAD_STR                 'isascii'
              564  MAKE_FUNCTION_0          'Neither defaults, keyword-only args, annotations, nor closures'
              566  STORE_NAME               isascii
              568  JUMP_FORWARD        586  'to 586'
            570_0  COME_FROM           548  '548'

 L. 112       570  LOAD_CODE                <code_object _to_bytes>
              572  LOAD_STR                 '_to_bytes'
              574  MAKE_FUNCTION_0          'Neither defaults, keyword-only args, annotations, nor closures'
              576  STORE_NAME               _to_bytes

 L. 115       578  LOAD_CODE                <code_object isascii>
              580  LOAD_STR                 'isascii'
              582  MAKE_FUNCTION_0          'Neither defaults, keyword-only args, annotations, nor closures'
              584  STORE_NAME               isascii
            586_0  COME_FROM           568  '568'

 L. 123       586  LOAD_CODE                <code_object _one_liner>
              588  LOAD_STR                 '_one_liner'
              590  MAKE_FUNCTION_0          'Neither defaults, keyword-only args, annotations, nor closures'
              592  STORE_NAME               _one_liner

 L. 127       594  LOAD_BUILD_CLASS 
              596  LOAD_CODE                <code_object easy_install>
              598  LOAD_STR                 'easy_install'
              600  MAKE_FUNCTION_0          'Neither defaults, keyword-only args, annotations, nor closures'
              602  LOAD_STR                 'easy_install'
              604  LOAD_NAME                Command
              606  CALL_FUNCTION_3       3  ''
              608  STORE_NAME               easy_install

 L.1361       610  LOAD_CODE                <code_object _pythonpath>
              612  LOAD_STR                 '_pythonpath'
              614  MAKE_FUNCTION_0          'Neither defaults, keyword-only args, annotations, nor closures'
              616  STORE_NAME               _pythonpath

 L.1366       618  LOAD_CODE                <code_object get_site_dirs>
              620  LOAD_STR                 'get_site_dirs'
              622  MAKE_FUNCTION_0          'Neither defaults, keyword-only args, annotations, nor closures'
              624  STORE_NAME               get_site_dirs

 L.1431       626  LOAD_CODE                <code_object expand_paths>
              628  LOAD_STR                 'expand_paths'
              630  MAKE_FUNCTION_0          'Neither defaults, keyword-only args, annotations, nor closures'
              632  STORE_NAME               expand_paths

 L.1472       634  LOAD_CODE                <code_object extract_wininst_cfg>
              636  LOAD_STR                 'extract_wininst_cfg'
              638  MAKE_FUNCTION_0          'Neither defaults, keyword-only args, annotations, nor closures'
              640  STORE_NAME               extract_wininst_cfg

 L.1513       642  LOAD_CODE                <code_object get_exe_prefixes>
              644  LOAD_STR                 'get_exe_prefixes'
              646  MAKE_FUNCTION_0          'Neither defaults, keyword-only args, annotations, nor closures'
              648  STORE_NAME               get_exe_prefixes

 L.1552       650  LOAD_BUILD_CLASS 
              652  LOAD_CODE                <code_object PthDistributions>
              654  LOAD_STR                 'PthDistributions'
              656  MAKE_FUNCTION_0          'Neither defaults, keyword-only args, annotations, nor closures'
              658  LOAD_STR                 'PthDistributions'
              660  LOAD_NAME                Environment
              662  CALL_FUNCTION_3       3  ''
              664  STORE_NAME               PthDistributions

 L.1660       666  LOAD_BUILD_CLASS 
              668  LOAD_CODE                <code_object RewritePthDistributions>
              670  LOAD_STR                 'RewritePthDistributions'
              672  MAKE_FUNCTION_0          'Neither defaults, keyword-only args, annotations, nor closures'
              674  LOAD_STR                 'RewritePthDistributions'
              676  LOAD_NAME                PthDistributions
              678  CALL_FUNCTION_3       3  ''
              680  STORE_NAME               RewritePthDistributions

 L.1682       682  LOAD_NAME                os
              684  LOAD_ATTR                environ
              686  LOAD_METHOD              get
              688  LOAD_STR                 'SETUPTOOLS_SYS_PATH_TECHNIQUE'
              690  LOAD_STR                 'raw'
              692  CALL_METHOD_2         2  ''
              694  LOAD_STR                 'rewrite'
              696  COMPARE_OP               ==
          698_700  POP_JUMP_IF_FALSE   706  'to 706'

 L.1683       702  LOAD_NAME                RewritePthDistributions
              704  STORE_NAME               PthDistributions
            706_0  COME_FROM           698  '698'

 L.1686       706  LOAD_CODE                <code_object _first_line_re>
              708  LOAD_STR                 '_first_line_re'
              710  MAKE_FUNCTION_0          'Neither defaults, keyword-only args, annotations, nor closures'
              712  STORE_NAME               _first_line_re

 L.1698       714  LOAD_CODE                <code_object auto_chmod>
              716  LOAD_STR                 'auto_chmod'
              718  MAKE_FUNCTION_0          'Neither defaults, keyword-only args, annotations, nor closures'
              720  STORE_NAME               auto_chmod

 L.1706       722  LOAD_CODE                <code_object update_dist_caches>
              724  LOAD_STR                 'update_dist_caches'
              726  MAKE_FUNCTION_0          'Neither defaults, keyword-only args, annotations, nor closures'
              728  STORE_NAME               update_dist_caches

 L.1788       730  LOAD_CODE                <code_object _collect_zipimporter_cache_entries>
              732  LOAD_STR                 '_collect_zipimporter_cache_entries'
              734  MAKE_FUNCTION_0          'Neither defaults, keyword-only args, annotations, nor closures'
              736  STORE_NAME               _collect_zipimporter_cache_entries

 L.1808       738  LOAD_CONST               (None,)
              740  LOAD_CODE                <code_object _update_zipimporter_cache>
              742  LOAD_STR                 '_update_zipimporter_cache'
              744  MAKE_FUNCTION_1          'default'
              746  STORE_NAME               _update_zipimporter_cache

 L.1840       748  LOAD_CODE                <code_object _uncache>
              750  LOAD_STR                 '_uncache'
              752  MAKE_FUNCTION_0          'Neither defaults, keyword-only args, annotations, nor closures'
              754  STORE_NAME               _uncache

 L.1844       756  LOAD_CODE                <code_object _remove_and_clear_zip_directory_cache_data>
              758  LOAD_STR                 '_remove_and_clear_zip_directory_cache_data'
              760  MAKE_FUNCTION_0          'Neither defaults, keyword-only args, annotations, nor closures'
              762  STORE_NAME               _remove_and_clear_zip_directory_cache_data

 L.1861       764  LOAD_STR                 '__pypy__'
              766  LOAD_NAME                sys
              768  LOAD_ATTR                builtin_module_names
              770  <118>                 0  ''
          772_774  POP_JUMP_IF_FALSE   782  'to 782'

 L.1863       776  LOAD_NAME                _remove_and_clear_zip_directory_cache_data

 L.1862       778  STORE_NAME               _replace_zip_directory_cache_data
              780  JUMP_FORWARD        790  'to 790'
            782_0  COME_FROM           772  '772'

 L.1866       782  LOAD_CODE                <code_object _replace_zip_directory_cache_data>
              784  LOAD_STR                 '_replace_zip_directory_cache_data'
              786  MAKE_FUNCTION_0          'Neither defaults, keyword-only args, annotations, nor closures'
              788  STORE_NAME               _replace_zip_directory_cache_data
            790_0  COME_FROM           780  '780'

 L.1885       790  LOAD_CONST               ('<string>',)
              792  LOAD_CODE                <code_object is_python>
              794  LOAD_STR                 'is_python'
              796  MAKE_FUNCTION_1          'default'
              798  STORE_NAME               is_python

 L.1895       800  LOAD_CODE                <code_object is_sh>
              802  LOAD_STR                 'is_sh'
              804  MAKE_FUNCTION_0          'Neither defaults, keyword-only args, annotations, nor closures'
              806  STORE_NAME               is_sh

 L.1905       808  LOAD_CODE                <code_object nt_quote_arg>
              810  LOAD_STR                 'nt_quote_arg'
              812  MAKE_FUNCTION_0          'Neither defaults, keyword-only args, annotations, nor closures'
              814  STORE_NAME               nt_quote_arg

 L.1910       816  LOAD_CODE                <code_object is_python_script>
              818  LOAD_STR                 'is_python_script'
              820  MAKE_FUNCTION_0          'Neither defaults, keyword-only args, annotations, nor closures'
              822  STORE_NAME               is_python_script

 L.1924       824  SETUP_FINALLY       842  'to 842'

 L.1925       826  LOAD_CONST               0
              828  LOAD_CONST               ('chmod',)
              830  IMPORT_NAME              os
              832  IMPORT_FROM              chmod
              834  STORE_NAME               _chmod
              836  POP_TOP          
              838  POP_BLOCK        
              840  JUMP_FORWARD        870  'to 870'
            842_0  COME_FROM_FINALLY   824  '824'

 L.1926       842  DUP_TOP          
              844  LOAD_NAME                ImportError
          846_848  <121>               868  ''
              850  POP_TOP          
              852  POP_TOP          
              854  POP_TOP          

 L.1928       856  LOAD_CODE                <code_object _chmod>
              858  LOAD_STR                 '_chmod'
              860  MAKE_FUNCTION_0          'Neither defaults, keyword-only args, annotations, nor closures'
              862  STORE_NAME               _chmod
              864  POP_EXCEPT       
              866  JUMP_FORWARD        870  'to 870'
              868  <48>             
            870_0  COME_FROM           866  '866'
            870_1  COME_FROM           840  '840'

 L.1932       870  LOAD_CODE                <code_object chmod>
              872  LOAD_STR                 'chmod'
              874  MAKE_FUNCTION_0          'Neither defaults, keyword-only args, annotations, nor closures'
              876  STORE_NAME               chmod

 L.1940       878  LOAD_BUILD_CLASS 
              880  LOAD_CODE                <code_object CommandSpec>
              882  LOAD_STR                 'CommandSpec'
              884  MAKE_FUNCTION_0          'Neither defaults, keyword-only args, annotations, nor closures'
              886  LOAD_STR                 'CommandSpec'
              888  LOAD_NAME                list
              890  CALL_FUNCTION_3       3  ''
              892  STORE_NAME               CommandSpec

 L.2024       894  LOAD_NAME                CommandSpec
              896  LOAD_METHOD              _sys_executable
              898  CALL_METHOD_0         0  ''
              900  STORE_NAME               sys_executable

 L.2027       902  LOAD_BUILD_CLASS 
              904  LOAD_CODE                <code_object WindowsCommandSpec>
              906  LOAD_STR                 'WindowsCommandSpec'
              908  MAKE_FUNCTION_0          'Neither defaults, keyword-only args, annotations, nor closures'
              910  LOAD_STR                 'WindowsCommandSpec'
              912  LOAD_NAME                CommandSpec
              914  CALL_FUNCTION_3       3  ''
              916  STORE_NAME               WindowsCommandSpec

 L.2031       918  LOAD_BUILD_CLASS 
              920  LOAD_CODE                <code_object ScriptWriter>
              922  LOAD_STR                 'ScriptWriter'
              924  MAKE_FUNCTION_0          'Neither defaults, keyword-only args, annotations, nor closures'
              926  LOAD_STR                 'ScriptWriter'
              928  CALL_FUNCTION_2       2  ''
              930  STORE_NAME               ScriptWriter

 L.2147       932  LOAD_BUILD_CLASS 
              934  LOAD_CODE                <code_object WindowsScriptWriter>
              936  LOAD_STR                 'WindowsScriptWriter'
              938  MAKE_FUNCTION_0          'Neither defaults, keyword-only args, annotations, nor closures'
              940  LOAD_STR                 'WindowsScriptWriter'
              942  LOAD_NAME                ScriptWriter
              944  CALL_FUNCTION_3       3  ''
              946  STORE_NAME               WindowsScriptWriter

 L.2212       948  LOAD_BUILD_CLASS 
              950  LOAD_CODE                <code_object WindowsExecutableLauncherWriter>
              952  LOAD_STR                 'WindowsExecutableLauncherWriter'
              954  MAKE_FUNCTION_0          'Neither defaults, keyword-only args, annotations, nor closures'
              956  LOAD_STR                 'WindowsExecutableLauncherWriter'
              958  LOAD_NAME                WindowsScriptWriter
              960  CALL_FUNCTION_3       3  ''
              962  STORE_NAME               WindowsExecutableLauncherWriter

 L.2244       964  LOAD_NAME                ScriptWriter
              966  LOAD_ATTR                get_script_args
              968  STORE_NAME               get_script_args

 L.2245       970  LOAD_NAME                ScriptWriter
              972  LOAD_ATTR                get_script_header
              974  STORE_NAME               get_script_header

 L.2248       976  LOAD_CODE                <code_object get_win_launcher>
              978  LOAD_STR                 'get_win_launcher'
              980  MAKE_FUNCTION_0          'Neither defaults, keyword-only args, annotations, nor closures'
              982  STORE_NAME               get_win_launcher

 L.2264       984  LOAD_CODE                <code_object load_launcher_manifest>
              986  LOAD_STR                 'load_launcher_manifest'
              988  MAKE_FUNCTION_0          'Neither defaults, keyword-only args, annotations, nor closures'
              990  STORE_NAME               load_launcher_manifest

 L.2272       992  LOAD_CONST               False
              994  LOAD_NAME                auto_chmod
              996  BUILD_TUPLE_2         2 
              998  LOAD_CODE                <code_object rmtree>
             1000  LOAD_STR                 'rmtree'
             1002  MAKE_FUNCTION_1          'default'
             1004  STORE_NAME               rmtree

 L.2276      1006  LOAD_CODE                <code_object current_umask>
             1008  LOAD_STR                 'current_umask'
             1010  MAKE_FUNCTION_0          'Neither defaults, keyword-only args, annotations, nor closures'
             1012  STORE_NAME               current_umask

 L.2282      1014  LOAD_CODE                <code_object bootstrap>
             1016  LOAD_STR                 'bootstrap'
             1018  MAKE_FUNCTION_0          'Neither defaults, keyword-only args, annotations, nor closures'
             1020  STORE_NAME               bootstrap

 L.2292      1022  LOAD_CONST               (None,)
             1024  LOAD_CODE                <code_object main>
             1026  LOAD_STR                 'main'
             1028  MAKE_FUNCTION_1          'default'
             1030  STORE_NAME               main

 L.2315      1032  LOAD_NAME                contextlib
             1034  LOAD_ATTR                contextmanager

 L.2316      1036  LOAD_CODE                <code_object _patch_usage>
             1038  LOAD_STR                 '_patch_usage'
             1040  MAKE_FUNCTION_0          'Neither defaults, keyword-only args, annotations, nor closures'
             1042  CALL_FUNCTION_1       1  ''
             1044  STORE_NAME               _patch_usage

 L.2336      1046  LOAD_BUILD_CLASS 
             1048  LOAD_CODE                <code_object EasyInstallDeprecationWarning>
             1050  LOAD_STR                 'EasyInstallDeprecationWarning'
             1052  MAKE_FUNCTION_0          'Neither defaults, keyword-only args, annotations, nor closures'
             1054  LOAD_STR                 'EasyInstallDeprecationWarning'
             1056  LOAD_NAME                SetuptoolsDeprecationWarning
             1058  CALL_FUNCTION_3       3  ''
             1060  STORE_NAME               EasyInstallDeprecationWarning

Parse error at or near `CALL_FINALLY' instruction at offset 524

Instruction context:
   
 L.  73       520  BUILD_LIST_0          0 
                 522  LOAD_CONST               ('samefile', 'easy_install', 'PthDistributions', 'extract_wininst_cfg', 'main', 'get_exe_prefixes')
->               524  CALL_FINALLY        527  'to 527'
                 526  STORE_NAME               __all__

test/31795.pyc -- 
# decompile failed
