
# file test/31832.pyc
# --- This code section failed: ---

 L.   7         0  LOAD_CONST               ('Mock', 'MagicMock', 'patch', 'sentinel', 'DEFAULT', 'ANY', 'call', 'create_autospec', 'AsyncMock', 'FILTER_DIR', 'NonCallableMock', 'NonCallableMagicMock', 'mock_open', 'PropertyMock', 'seal')
                2  STORE_NAME               __all__

 L.  26         4  LOAD_CONST               0
                6  LOAD_CONST               None
                8  IMPORT_NAME              asyncio
               10  STORE_NAME               asyncio

 L.  27        12  LOAD_CONST               0
               14  LOAD_CONST               None
               16  IMPORT_NAME              contextlib
               18  STORE_NAME               contextlib

 L.  28        20  LOAD_CONST               0
               22  LOAD_CONST               None
               24  IMPORT_NAME              io
               26  STORE_NAME               io

 L.  29        28  LOAD_CONST               0
               30  LOAD_CONST               None
               32  IMPORT_NAME              inspect
               34  STORE_NAME               inspect

 L.  30        36  LOAD_CONST               0
               38  LOAD_CONST               None
               40  IMPORT_NAME              pprint
               42  STORE_NAME               pprint

 L.  31        44  LOAD_CONST               0
               46  LOAD_CONST               None
               48  IMPORT_NAME              sys
               50  STORE_NAME               sys

 L.  32        52  LOAD_CONST               0
               54  LOAD_CONST               None
               56  IMPORT_NAME              builtins
               58  STORE_NAME               builtins

 L.  33        60  LOAD_CONST               0
               62  LOAD_CONST               ('iscoroutinefunction',)
               64  IMPORT_NAME              asyncio
               66  IMPORT_FROM              iscoroutinefunction
               68  STORE_NAME               iscoroutinefunction
               70  POP_TOP          

 L.  34        72  LOAD_CONST               0
               74  LOAD_CONST               ('CodeType', 'ModuleType', 'MethodType')
               76  IMPORT_NAME              types
               78  IMPORT_FROM              CodeType
               80  STORE_NAME               CodeType
               82  IMPORT_FROM              ModuleType
               84  STORE_NAME               ModuleType
               86  IMPORT_FROM              MethodType
               88  STORE_NAME               MethodType
               90  POP_TOP          

 L.  35        92  LOAD_CONST               0
               94  LOAD_CONST               ('safe_repr',)
               96  IMPORT_NAME_ATTR         unittest.util
               98  IMPORT_FROM              safe_repr
              100  STORE_NAME               safe_repr
              102  POP_TOP          

 L.  36       104  LOAD_CONST               0
              106  LOAD_CONST               ('wraps', 'partial')
              108  IMPORT_NAME              functools
              110  IMPORT_FROM              wraps
              112  STORE_NAME               wraps
              114  IMPORT_FROM              partial
              116  STORE_NAME               partial
              118  POP_TOP          

 L.  39       120  LOAD_SETCOMP             '<code_object <setcomp>>'
              122  LOAD_STR                 '<setcomp>'
              124  MAKE_FUNCTION_0          'Neither defaults, keyword-only args, annotations, nor closures'
              126  LOAD_NAME                dir
              128  LOAD_NAME                builtins
              130  CALL_FUNCTION_1       1  ''
              132  GET_ITER         
              134  CALL_FUNCTION_1       1  ''
              136  STORE_NAME               _builtins

 L.  41       138  LOAD_CONST               True
              140  STORE_NAME               FILTER_DIR

 L.  45       142  LOAD_NAME                super
              144  STORE_NAME               _safe_super

 L.  47       146  LOAD_CODE                <code_object _is_async_obj>
              148  LOAD_STR                 '_is_async_obj'
              150  MAKE_FUNCTION_0          'Neither defaults, keyword-only args, annotations, nor closures'
              152  STORE_NAME               _is_async_obj

 L.  55       154  LOAD_CODE                <code_object _is_async_func>
              156  LOAD_STR                 '_is_async_func'
              158  MAKE_FUNCTION_0          'Neither defaults, keyword-only args, annotations, nor closures'
              160  STORE_NAME               _is_async_func

 L.  62       162  LOAD_CODE                <code_object _is_instance_mock>
              164  LOAD_STR                 '_is_instance_mock'
              166  MAKE_FUNCTION_0          'Neither defaults, keyword-only args, annotations, nor closures'
              168  STORE_NAME               _is_instance_mock

 L.  68       170  LOAD_CODE                <code_object _is_exception>
              172  LOAD_STR                 '_is_exception'
              174  MAKE_FUNCTION_0          'Neither defaults, keyword-only args, annotations, nor closures'
              176  STORE_NAME               _is_exception

 L.  75       178  LOAD_CODE                <code_object _extract_mock>
              180  LOAD_STR                 '_extract_mock'
              182  MAKE_FUNCTION_0          'Neither defaults, keyword-only args, annotations, nor closures'
              184  STORE_NAME               _extract_mock

 L.  84       186  LOAD_CODE                <code_object _get_signature_object>
              188  LOAD_STR                 '_get_signature_object'
              190  MAKE_FUNCTION_0          'Neither defaults, keyword-only args, annotations, nor closures'
              192  STORE_NAME               _get_signature_object

 L. 113       194  LOAD_CONST               (False,)
              196  LOAD_CODE                <code_object _check_signature>
              198  LOAD_STR                 '_check_signature'
              200  MAKE_FUNCTION_1          'default'
              202  STORE_NAME               _check_signature

 L. 125       204  LOAD_CODE                <code_object _copy_func_details>
              206  LOAD_STR                 '_copy_func_details'
              208  MAKE_FUNCTION_0          'Neither defaults, keyword-only args, annotations, nor closures'
              210  STORE_NAME               _copy_func_details

 L. 138       212  LOAD_CODE                <code_object _callable>
              214  LOAD_STR                 '_callable'
              216  MAKE_FUNCTION_0          'Neither defaults, keyword-only args, annotations, nor closures'
              218  STORE_NAME               _callable

 L. 148       220  LOAD_CODE                <code_object _is_list>
              222  LOAD_STR                 '_is_list'
              224  MAKE_FUNCTION_0          'Neither defaults, keyword-only args, annotations, nor closures'
              226  STORE_NAME               _is_list

 L. 154       228  LOAD_CODE                <code_object _instance_callable>
              230  LOAD_STR                 '_instance_callable'
              232  MAKE_FUNCTION_0          'Neither defaults, keyword-only args, annotations, nor closures'
              234  STORE_NAME               _instance_callable

 L. 169       236  LOAD_CONST               (False,)
              238  LOAD_CODE                <code_object _set_signature>
              240  LOAD_STR                 '_set_signature'
              242  MAKE_FUNCTION_1          'default'
              244  STORE_NAME               _set_signature

 L. 196       246  LOAD_CODE                <code_object _setup_func>
              248  LOAD_STR                 '_setup_func'
              250  MAKE_FUNCTION_0          'Neither defaults, keyword-only args, annotations, nor closures'
              252  STORE_NAME               _setup_func

 L. 245       254  LOAD_CODE                <code_object _setup_async_mock>
              256  LOAD_STR                 '_setup_async_mock'
              258  MAKE_FUNCTION_0          'Neither defaults, keyword-only args, annotations, nor closures'
              260  STORE_NAME               _setup_async_mock

 L. 272       262  LOAD_CODE                <code_object _is_magic>
              264  LOAD_STR                 '_is_magic'
              266  MAKE_FUNCTION_0          'Neither defaults, keyword-only args, annotations, nor closures'
              268  STORE_NAME               _is_magic

 L. 276       270  LOAD_BUILD_CLASS 
              272  LOAD_CODE                <code_object _SentinelObject>
              274  LOAD_STR                 '_SentinelObject'
              276  MAKE_FUNCTION_0          'Neither defaults, keyword-only args, annotations, nor closures'
              278  LOAD_STR                 '_SentinelObject'
              280  LOAD_NAME                object
              282  CALL_FUNCTION_3       3  ''
              284  STORE_NAME               _SentinelObject

 L. 288       286  LOAD_BUILD_CLASS 
              288  LOAD_CODE                <code_object _Sentinel>
              290  LOAD_STR                 '_Sentinel'
              292  MAKE_FUNCTION_0          'Neither defaults, keyword-only args, annotations, nor closures'
              294  LOAD_STR                 '_Sentinel'
              296  LOAD_NAME                object
              298  CALL_FUNCTION_3       3  ''
              300  STORE_NAME               _Sentinel

 L. 303       302  LOAD_NAME                _Sentinel
              304  CALL_FUNCTION_0       0  ''
              306  STORE_NAME               sentinel

 L. 305       308  LOAD_NAME                sentinel
              310  LOAD_ATTR                DEFAULT
              312  STORE_NAME               DEFAULT

 L. 306       314  LOAD_NAME                sentinel
              316  LOAD_ATTR                MISSING
              318  STORE_NAME               _missing

 L. 307       320  LOAD_NAME                sentinel
              322  LOAD_ATTR                DELETED
              324  STORE_NAME               _deleted

 L. 310       326  BUILD_SET_0           0 
              328  LOAD_CONST               frozenset({'return_value', '_mock_side_effect', '_mock_parent', '_mock_return_value', '_mock_new_parent', '_mock_name', '_mock_new_name', 'side_effect'})
              330  POP_FINALLY           1  ''
              332  STORE_NAME               _allowed_names

 L. 317       334  LOAD_CODE                <code_object _delegating_property>
              336  LOAD_STR                 '_delegating_property'
              338  MAKE_FUNCTION_0          'Neither defaults, keyword-only args, annotations, nor closures'
              340  STORE_NAME               _delegating_property

 L. 336       342  LOAD_BUILD_CLASS 
              344  LOAD_CODE                <code_object _CallList>
              346  LOAD_STR                 '_CallList'
              348  MAKE_FUNCTION_0          'Neither defaults, keyword-only args, annotations, nor closures'
              350  LOAD_STR                 '_CallList'
              352  LOAD_NAME                list
              354  CALL_FUNCTION_3       3  ''
              356  STORE_NAME               _CallList

 L. 356       358  LOAD_CODE                <code_object _check_and_set_parent>
              360  LOAD_STR                 '_check_and_set_parent'
              362  MAKE_FUNCTION_0          'Neither defaults, keyword-only args, annotations, nor closures'
              364  STORE_NAME               _check_and_set_parent

 L. 383       366  LOAD_BUILD_CLASS 
              368  LOAD_CODE                <code_object _MockIter>
              370  LOAD_STR                 '_MockIter'
              372  MAKE_FUNCTION_0          'Neither defaults, keyword-only args, annotations, nor closures'
              374  LOAD_STR                 '_MockIter'
              376  LOAD_NAME                object
              378  CALL_FUNCTION_3       3  ''
              380  STORE_NAME               _MockIter

 L. 389       382  LOAD_BUILD_CLASS 
              384  LOAD_CODE                <code_object Base>
              386  LOAD_STR                 'Base'
              388  MAKE_FUNCTION_0          'Neither defaults, keyword-only args, annotations, nor closures'
              390  LOAD_STR                 'Base'
              392  LOAD_NAME                object
              394  CALL_FUNCTION_3       3  ''
              396  STORE_NAME               Base

 L. 397       398  LOAD_BUILD_CLASS 
              400  LOAD_CODE                <code_object NonCallableMock>
              402  LOAD_STR                 'NonCallableMock'
              404  MAKE_FUNCTION_0          'Neither defaults, keyword-only args, annotations, nor closures'
              406  LOAD_STR                 'NonCallableMock'
              408  LOAD_NAME                Base
              410  CALL_FUNCTION_3       3  ''
              412  STORE_NAME               NonCallableMock

 L.1035       414  LOAD_NAME                inspect
              416  LOAD_METHOD              signature
              418  LOAD_NAME                NonCallableMock
              420  LOAD_ATTR                __init__
              422  CALL_METHOD_1         1  ''
              424  STORE_NAME               _MOCK_SIG

 L.1038       426  LOAD_BUILD_CLASS 
              428  LOAD_CODE                <code_object _AnyComparer>
              430  LOAD_STR                 '_AnyComparer'
              432  MAKE_FUNCTION_0          'Neither defaults, keyword-only args, annotations, nor closures'
              434  LOAD_STR                 '_AnyComparer'
              436  LOAD_NAME                list
              438  CALL_FUNCTION_3       3  ''
              440  STORE_NAME               _AnyComparer

 L.1054       442  LOAD_CODE                <code_object _try_iter>
              444  LOAD_STR                 '_try_iter'
              446  MAKE_FUNCTION_0          'Neither defaults, keyword-only args, annotations, nor closures'
              448  STORE_NAME               _try_iter

 L.1069       450  LOAD_BUILD_CLASS 
              452  LOAD_CODE                <code_object CallableMixin>
              454  LOAD_STR                 'CallableMixin'
              456  MAKE_FUNCTION_0          'Neither defaults, keyword-only args, annotations, nor closures'
              458  LOAD_STR                 'CallableMixin'
              460  LOAD_NAME                Base
              462  CALL_FUNCTION_3       3  ''
              464  STORE_NAME               CallableMixin

 L.1173       466  LOAD_BUILD_CLASS 
              468  LOAD_CODE                <code_object Mock>
              470  LOAD_STR                 'Mock'
              472  MAKE_FUNCTION_0          'Neither defaults, keyword-only args, annotations, nor closures'
              474  LOAD_STR                 'Mock'
              476  LOAD_NAME                CallableMixin
              478  LOAD_NAME                NonCallableMock
              480  CALL_FUNCTION_4       4  ''
              482  STORE_NAME               Mock

 L.1225       484  LOAD_CODE                <code_object _dot_lookup>
              486  LOAD_STR                 '_dot_lookup'
              488  MAKE_FUNCTION_0          'Neither defaults, keyword-only args, annotations, nor closures'
              490  STORE_NAME               _dot_lookup

 L.1233       492  LOAD_CODE                <code_object _importer>
              494  LOAD_STR                 '_importer'
              496  MAKE_FUNCTION_0          'Neither defaults, keyword-only args, annotations, nor closures'
              498  STORE_NAME               _importer

 L.1244       500  LOAD_BUILD_CLASS 
              502  LOAD_CODE                <code_object _patch>
              504  LOAD_STR                 '_patch'
              506  MAKE_FUNCTION_0          'Neither defaults, keyword-only args, annotations, nor closures'
              508  LOAD_STR                 '_patch'
              510  LOAD_NAME                object
              512  CALL_FUNCTION_3       3  ''
              514  STORE_NAME               _patch

 L.1558       516  LOAD_CODE                <code_object _get_target>
              518  LOAD_STR                 '_get_target'
              520  MAKE_FUNCTION_0          'Neither defaults, keyword-only args, annotations, nor closures'
              522  STORE_NAME               _get_target

 L.1569       524  LOAD_NAME                DEFAULT
              526  LOAD_CONST               None

 L.1570       528  LOAD_CONST               False
              530  LOAD_CONST               None
              532  LOAD_CONST               None

 L.1571       534  LOAD_CONST               None

 L.1568       536  BUILD_TUPLE_6         6 
              538  LOAD_CODE                <code_object _patch_object>
              540  LOAD_STR                 '_patch_object'
              542  MAKE_FUNCTION_1          'default'
              544  STORE_NAME               _patch_object

 L.1597       546  LOAD_CONST               (None, False, None, None, None)
              548  LOAD_CODE                <code_object _patch_multiple>
              550  LOAD_STR                 '_patch_multiple'
              552  MAKE_FUNCTION_1          'default'
              554  STORE_NAME               _patch_multiple

 L.1647       556  LOAD_NAME                DEFAULT
              558  LOAD_CONST               None
              560  LOAD_CONST               False

 L.1648       562  LOAD_CONST               None
              564  LOAD_CONST               None
              566  LOAD_CONST               None

 L.1646       568  BUILD_TUPLE_6         6 
              570  LOAD_CODE                <code_object patch>
              572  LOAD_STR                 'patch'
              574  MAKE_FUNCTION_1          'default'
              576  STORE_NAME               patch

 L.1724       578  LOAD_BUILD_CLASS 
              580  LOAD_CODE                <code_object _patch_dict>
              582  LOAD_STR                 '_patch_dict'
              584  MAKE_FUNCTION_0          'Neither defaults, keyword-only args, annotations, nor closures'
              586  LOAD_STR                 '_patch_dict'
              588  LOAD_NAME                object
              590  CALL_FUNCTION_3       3  ''
              592  STORE_NAME               _patch_dict

 L.1859       594  LOAD_CODE                <code_object _clear_dict>
              596  LOAD_STR                 '_clear_dict'
              598  MAKE_FUNCTION_0          'Neither defaults, keyword-only args, annotations, nor closures'
              600  STORE_NAME               _clear_dict

 L.1868       602  LOAD_CODE                <code_object _patch_stopall>
              604  LOAD_STR                 '_patch_stopall'
              606  MAKE_FUNCTION_0          'Neither defaults, keyword-only args, annotations, nor closures'
              608  STORE_NAME               _patch_stopall

 L.1874       610  LOAD_NAME                _patch_object
              612  LOAD_NAME                patch
              614  STORE_ATTR               object

 L.1875       616  LOAD_NAME                _patch_dict
              618  LOAD_NAME                patch
              620  STORE_ATTR               dict

 L.1876       622  LOAD_NAME                _patch_multiple
              624  LOAD_NAME                patch
              626  STORE_ATTR               multiple

 L.1877       628  LOAD_NAME                _patch_stopall
              630  LOAD_NAME                patch
              632  STORE_ATTR               stopall

 L.1878       634  LOAD_STR                 'test'
              636  LOAD_NAME                patch
              638  STORE_ATTR               TEST_PREFIX

 L.1881       640  LOAD_STR                 'lt le gt ge eq ne getitem setitem delitem len contains iter hash str sizeof enter exit divmod rdivmod neg pos abs invert complex int float index round trunc floor ceil bool next fspath aiter '

 L.1880       642  STORE_NAME               magic_methods

 L.1897       644  LOAD_STR                 'add sub mul matmul div floordiv mod lshift rshift and xor or pow truediv'

 L.1896       646  STORE_NAME               numerics

 L.1899       648  LOAD_STR                 ' '
              650  LOAD_METHOD              join
              652  LOAD_GENEXPR             '<code_object <genexpr>>'
              654  LOAD_STR                 '<genexpr>'
              656  MAKE_FUNCTION_0          'Neither defaults, keyword-only args, annotations, nor closures'
              658  LOAD_NAME                numerics
              660  LOAD_METHOD              split
              662  CALL_METHOD_0         0  ''
              664  GET_ITER         
              666  CALL_FUNCTION_1       1  ''
              668  CALL_METHOD_1         1  ''
              670  STORE_NAME               inplace

 L.1900       672  LOAD_STR                 ' '
              674  LOAD_METHOD              join
              676  LOAD_GENEXPR             '<code_object <genexpr>>'
              678  LOAD_STR                 '<genexpr>'
              680  MAKE_FUNCTION_0          'Neither defaults, keyword-only args, annotations, nor closures'
              682  LOAD_NAME                numerics
              684  LOAD_METHOD              split
              686  CALL_METHOD_0         0  ''
              688  GET_ITER         
              690  CALL_FUNCTION_1       1  ''
              692  CALL_METHOD_1         1  ''
              694  STORE_NAME               right

 L.1906       696  BUILD_SET_0           0 
              698  LOAD_CONST               frozenset({'__reduce_ex__', '__delete__', '__getformat__', '__missing__', '__dir__', '__getnewargs_ex__', '__getnewargs__', '__repr__', '__subclasses__', '__setformat__', '__set__', '__format__', '__setstate__', '__getstate__', '__getinitargs__', '__get__', '__reduce__', '__reversed__'})
              700  POP_FINALLY           1  ''
              702  STORE_NAME               _non_defaults

 L.1915       704  LOAD_CODE                <code_object _get_method>
              706  LOAD_STR                 '_get_method'
              708  MAKE_FUNCTION_0          'Neither defaults, keyword-only args, annotations, nor closures'
              710  STORE_NAME               _get_method

 L.1923       712  LOAD_SETCOMP             '<code_object <setcomp>>'
              714  LOAD_STR                 '<setcomp>'
              716  MAKE_FUNCTION_0          'Neither defaults, keyword-only args, annotations, nor closures'

 L.1925       718  LOAD_STR                 ' '
              720  LOAD_METHOD              join
              722  LOAD_NAME                magic_methods
              724  LOAD_NAME                numerics
              726  LOAD_NAME                inplace
              728  LOAD_NAME                right
              730  BUILD_LIST_4          4 
              732  CALL_METHOD_1         1  ''
              734  LOAD_METHOD              split
              736  CALL_METHOD_0         0  ''

 L.1923       738  GET_ITER         
              740  CALL_FUNCTION_1       1  ''
              742  STORE_NAME               _magics

 L.1929       744  BUILD_SET_0           0 
              746  LOAD_CONST               frozenset({'__aexit__', '__anext__', '__aenter__'})
              748  POP_FINALLY           1  ''
              750  STORE_NAME               _async_method_magics

 L.1931       752  LOAD_STR                 '__aiter__'
              754  BUILD_SET_1           1 
              756  STORE_NAME               _sync_async_magics

 L.1932       758  LOAD_NAME                _async_method_magics
              760  LOAD_NAME                _sync_async_magics
              762  BINARY_OR        
              764  STORE_NAME               _async_magics

 L.1934       766  LOAD_NAME                _magics
              768  LOAD_NAME                _non_defaults
              770  BINARY_OR        
              772  STORE_NAME               _all_sync_magics

 L.1935       774  LOAD_NAME                _all_sync_magics
              776  LOAD_NAME                _async_magics
              778  BINARY_OR        
              780  STORE_NAME               _all_magics

 L.1937       782  BUILD_SET_0           0 
              784  LOAD_CONST               frozenset({'__del__', '__init__', '__instancecheck__', '__subclasscheck__', '__new__', '__setattr__', '__getattr__', '__prepare__'})
              786  POP_FINALLY           1  ''
              788  STORE_NAME               _unsupported_magics

 L.1945       790  LOAD_LAMBDA              '<code_object <lambda>>'
              792  LOAD_STR                 '<lambda>'
              794  MAKE_FUNCTION_0          'Neither defaults, keyword-only args, annotations, nor closures'

 L.1946       796  LOAD_LAMBDA              '<code_object <lambda>>'
              798  LOAD_STR                 '<lambda>'
              800  MAKE_FUNCTION_0          'Neither defaults, keyword-only args, annotations, nor closures'

 L.1947       802  LOAD_LAMBDA              '<code_object <lambda>>'
              804  LOAD_STR                 '<lambda>'
              806  MAKE_FUNCTION_0          'Neither defaults, keyword-only args, annotations, nor closures'

 L.1948       808  LOAD_LAMBDA              '<code_object <lambda>>'
              810  LOAD_STR                 '<lambda>'
              812  MAKE_FUNCTION_0          'Neither defaults, keyword-only args, annotations, nor closures'

 L.1944       814  LOAD_CONST               ('__hash__', '__str__', '__sizeof__', '__fspath__')
              816  BUILD_CONST_KEY_MAP_4     4 
              818  STORE_NAME               _calculate_return_value

 L.1952       820  LOAD_NAME                NotImplemented

 L.1953       822  LOAD_NAME                NotImplemented

 L.1954       824  LOAD_NAME                NotImplemented

 L.1955       826  LOAD_NAME                NotImplemented

 L.1956       828  LOAD_CONST               1

 L.1957       830  LOAD_CONST               False

 L.1958       832  LOAD_CONST               0

 L.1959       834  LOAD_CONST               False

 L.1960       836  LOAD_CONST               1j

 L.1961       838  LOAD_CONST               1.0

 L.1962       840  LOAD_CONST               True

 L.1963       842  LOAD_CONST               1

 L.1964       844  LOAD_CONST               False

 L.1951       846  LOAD_CONST               ('__lt__', '__gt__', '__le__', '__ge__', '__int__', '__contains__', '__len__', '__exit__', '__complex__', '__float__', '__bool__', '__index__', '__aexit__')
              848  BUILD_CONST_KEY_MAP_13    13 
              850  STORE_NAME               _return_values

 L.1968       852  LOAD_CODE                <code_object _get_eq>
              854  LOAD_STR                 '_get_eq'
              856  MAKE_FUNCTION_0          'Neither defaults, keyword-only args, annotations, nor closures'
              858  STORE_NAME               _get_eq

 L.1978       860  LOAD_CODE                <code_object _get_ne>
              862  LOAD_STR                 '_get_ne'
              864  MAKE_FUNCTION_0          'Neither defaults, keyword-only args, annotations, nor closures'
              866  STORE_NAME               _get_ne

 L.1987       868  LOAD_CODE                <code_object _get_iter>
              870  LOAD_STR                 '_get_iter'
              872  MAKE_FUNCTION_0          'Neither defaults, keyword-only args, annotations, nor closures'
              874  STORE_NAME               _get_iter

 L.1997       876  LOAD_CODE                <code_object _get_async_iter>
              878  LOAD_STR                 '_get_async_iter'
              880  MAKE_FUNCTION_0          'Neither defaults, keyword-only args, annotations, nor closures'
              882  STORE_NAME               _get_async_iter

 L.2006       884  LOAD_NAME                _get_eq

 L.2007       886  LOAD_NAME                _get_ne

 L.2008       888  LOAD_NAME                _get_iter

 L.2009       890  LOAD_NAME                _get_async_iter

 L.2005       892  LOAD_CONST               ('__eq__', '__ne__', '__iter__', '__aiter__')
              894  BUILD_CONST_KEY_MAP_4     4 
              896  STORE_NAME               _side_effect_methods

 L.2014       898  LOAD_CODE                <code_object _set_return_value>
              900  LOAD_STR                 '_set_return_value'
              902  MAKE_FUNCTION_0          'Neither defaults, keyword-only args, annotations, nor closures'
              904  STORE_NAME               _set_return_value

 L.2032       906  LOAD_BUILD_CLASS 
              908  LOAD_CODE                <code_object MagicMixin>
              910  LOAD_STR                 'MagicMixin'
              912  MAKE_FUNCTION_0          'Neither defaults, keyword-only args, annotations, nor closures'
              914  LOAD_STR                 'MagicMixin'
              916  LOAD_NAME                Base
              918  CALL_FUNCTION_3       3  ''
              920  STORE_NAME               MagicMixin

 L.2063       922  LOAD_BUILD_CLASS 
              924  LOAD_CODE                <code_object NonCallableMagicMock>
              926  LOAD_STR                 'NonCallableMagicMock'
              928  MAKE_FUNCTION_0          'Neither defaults, keyword-only args, annotations, nor closures'
              930  LOAD_STR                 'NonCallableMagicMock'
              932  LOAD_NAME                MagicMixin
              934  LOAD_NAME                NonCallableMock
              936  CALL_FUNCTION_4       4  ''
              938  STORE_NAME               NonCallableMagicMock

 L.2075       940  LOAD_BUILD_CLASS 
              942  LOAD_CODE                <code_object AsyncMagicMixin>
              944  LOAD_STR                 'AsyncMagicMixin'
              946  MAKE_FUNCTION_0          'Neither defaults, keyword-only args, annotations, nor closures'
              948  LOAD_STR                 'AsyncMagicMixin'
              950  LOAD_NAME                MagicMixin
              952  CALL_FUNCTION_3       3  ''
              954  STORE_NAME               AsyncMagicMixin

 L.2081       956  LOAD_BUILD_CLASS 
              958  LOAD_CODE                <code_object MagicMock>
              960  LOAD_STR                 'MagicMock'
              962  MAKE_FUNCTION_0          'Neither defaults, keyword-only args, annotations, nor closures'
              964  LOAD_STR                 'MagicMock'
              966  LOAD_NAME                MagicMixin
              968  LOAD_NAME                Mock
              970  CALL_FUNCTION_4       4  ''
              972  STORE_NAME               MagicMock

 L.2103       974  LOAD_BUILD_CLASS 
              976  LOAD_CODE                <code_object MagicProxy>
              978  LOAD_STR                 'MagicProxy'
              980  MAKE_FUNCTION_0          'Neither defaults, keyword-only args, annotations, nor closures'
              982  LOAD_STR                 'MagicProxy'
              984  LOAD_NAME                Base
              986  CALL_FUNCTION_3       3  ''
              988  STORE_NAME               MagicProxy

 L.2121       990  LOAD_BUILD_CLASS 
              992  LOAD_CODE                <code_object AsyncMockMixin>
              994  LOAD_STR                 'AsyncMockMixin'
              996  MAKE_FUNCTION_0          'Neither defaults, keyword-only args, annotations, nor closures'
              998  LOAD_STR                 'AsyncMockMixin'
             1000  LOAD_NAME                Base
             1002  CALL_FUNCTION_3       3  ''
             1004  STORE_NAME               AsyncMockMixin

 L.2304      1006  LOAD_BUILD_CLASS 
             1008  LOAD_CODE                <code_object AsyncMock>
             1010  LOAD_STR                 'AsyncMock'
             1012  MAKE_FUNCTION_0          'Neither defaults, keyword-only args, annotations, nor closures'
             1014  LOAD_STR                 'AsyncMock'
             1016  LOAD_NAME                AsyncMockMixin
             1018  LOAD_NAME                AsyncMagicMixin
             1020  LOAD_NAME                Mock
             1022  CALL_FUNCTION_5       5  ''
             1024  STORE_NAME               AsyncMock

 L.2347      1026  LOAD_BUILD_CLASS 
             1028  LOAD_CODE                <code_object _ANY>
             1030  LOAD_STR                 '_ANY'
             1032  MAKE_FUNCTION_0          'Neither defaults, keyword-only args, annotations, nor closures'
             1034  LOAD_STR                 '_ANY'
             1036  LOAD_NAME                object
             1038  CALL_FUNCTION_3       3  ''
             1040  STORE_NAME               _ANY

 L.2359      1042  LOAD_NAME                _ANY
             1044  CALL_FUNCTION_0       0  ''
             1046  STORE_NAME               ANY

 L.2363      1048  LOAD_CODE                <code_object _format_call_signature>
             1050  LOAD_STR                 '_format_call_signature'
             1052  MAKE_FUNCTION_0          'Neither defaults, keyword-only args, annotations, nor closures'
             1054  STORE_NAME               _format_call_signature

 L.2381      1056  LOAD_BUILD_CLASS 
             1058  LOAD_CODE                <code_object _Call>
             1060  LOAD_STR                 '_Call'
             1062  MAKE_FUNCTION_0          'Neither defaults, keyword-only args, annotations, nor closures'
             1064  LOAD_STR                 '_Call'
             1066  LOAD_NAME                tuple
             1068  CALL_FUNCTION_3       3  ''
             1070  STORE_NAME               _Call

 L.2566      1072  LOAD_NAME                _Call
             1074  LOAD_CONST               False
             1076  LOAD_CONST               ('from_kall',)
             1078  CALL_FUNCTION_KW_1     1  '1 total positional and keyword args'
             1080  STORE_NAME               call

 L.2569      1082  LOAD_CONST               (False, False, None, None)
             1084  LOAD_CODE                <code_object create_autospec>
             1086  LOAD_STR                 'create_autospec'
             1088  MAKE_FUNCTION_1          'default'
             1090  STORE_NAME               create_autospec

 L.2700      1092  LOAD_CODE                <code_object _must_skip>
             1094  LOAD_STR                 '_must_skip'
             1096  MAKE_FUNCTION_0          'Neither defaults, keyword-only args, annotations, nor closures'
             1098  STORE_NAME               _must_skip

 L.2728      1100  LOAD_BUILD_CLASS 
             1102  LOAD_CODE                <code_object _SpecState>
             1104  LOAD_STR                 '_SpecState'
             1106  MAKE_FUNCTION_0          'Neither defaults, keyword-only args, annotations, nor closures'
             1108  LOAD_STR                 '_SpecState'
             1110  LOAD_NAME                object
             1112  CALL_FUNCTION_3       3  ''
             1114  STORE_NAME               _SpecState

 L.2742      1116  LOAD_NAME                type
             1118  LOAD_NAME                create_autospec
             1120  CALL_FUNCTION_1       1  ''

 L.2744      1122  LOAD_NAME                type
             1124  LOAD_NAME                ANY
             1126  LOAD_ATTR                __eq__
             1128  CALL_FUNCTION_1       1  ''

 L.2740      1130  BUILD_TUPLE_2         2 
             1132  STORE_NAME               FunctionTypes

 L.2748      1134  LOAD_CONST               None
             1136  STORE_GLOBAL             file_spec

 L.2751      1138  LOAD_CODE                <code_object _to_stream>
             1140  LOAD_STR                 '_to_stream'
             1142  MAKE_FUNCTION_0          'Neither defaults, keyword-only args, annotations, nor closures'
             1144  STORE_NAME               _to_stream

 L.2758      1146  LOAD_CONST               (None, '')
             1148  LOAD_CODE                <code_object mock_open>
             1150  LOAD_STR                 'mock_open'
             1152  MAKE_FUNCTION_1          'default'
             1154  STORE_NAME               mock_open

 L.2836      1156  LOAD_BUILD_CLASS 
             1158  LOAD_CODE                <code_object PropertyMock>
             1160  LOAD_STR                 'PropertyMock'
             1162  MAKE_FUNCTION_0          'Neither defaults, keyword-only args, annotations, nor closures'
             1164  LOAD_STR                 'PropertyMock'
             1166  LOAD_NAME                Mock
             1168  CALL_FUNCTION_3       3  ''
             1170  STORE_NAME               PropertyMock

 L.2854      1172  LOAD_CODE                <code_object seal>
             1174  LOAD_STR                 'seal'
             1176  MAKE_FUNCTION_0          'Neither defaults, keyword-only args, annotations, nor closures'
             1178  STORE_NAME               seal

 L.2876      1180  LOAD_BUILD_CLASS 
             1182  LOAD_CODE                <code_object _AsyncIterator>
             1184  LOAD_STR                 '_AsyncIterator'
             1186  MAKE_FUNCTION_0          'Neither defaults, keyword-only args, annotations, nor closures'
             1188  LOAD_STR                 '_AsyncIterator'
             1190  CALL_FUNCTION_2       2  ''
             1192  STORE_NAME               _AsyncIterator

Parse error at or near `POP_FINALLY' instruction at offset 330

Instruction context:
   
 L. 310       326  BUILD_SET_0           0 
                 328  LOAD_CONST               frozenset({'return_value', '_mock_side_effect', '_mock_parent', '_mock_return_value', '_mock_new_parent', '_mock_name', '_mock_new_name', 'side_effect'})
->               330  POP_FINALLY           1  ''
                 332  STORE_NAME               _allowed_names

test/31832.pyc -- 
# decompile failed
