Instruction context:
   
 L.  45        12  DUP_TOP          
                  14  LOAD_GLOBAL              AddressValueError
                  16  LOAD_GLOBAL              NetmaskValueError
                  18  BUILD_TUPLE_2         2 
->                20  <121>                32  ''
                  22  POP_TOP          
                  24  POP_TOP          
                  26  POP_TOP          
Instruction context:
   
 L.  75        14  DUP_TOP          
                  16  LOAD_GLOBAL              AddressValueError
                  18  LOAD_GLOBAL              NetmaskValueError
                  20  BUILD_TUPLE_2         2 
->                22  <121>                34  ''
                  24  POP_TOP          
                  26  POP_TOP          
                  28  POP_TOP          
Instruction context:
   
 L. 110        12  DUP_TOP          
                  14  LOAD_GLOBAL              AddressValueError
                  16  LOAD_GLOBAL              NetmaskValueError
                  18  BUILD_TUPLE_2         2 
->                20  <121>                32  ''
                  22  POP_TOP          
                  24  POP_TOP          
                  26  POP_TOP          
Instruction context:
   
 L. 138        16  DUP_TOP          
                  18  LOAD_GLOBAL              OverflowError
->                20  <121>                40  ''
                  22  POP_TOP          
                  24  POP_TOP          
                  26  POP_TOP          
Instruction context:
   
 L. 154        16  DUP_TOP          
                  18  LOAD_GLOBAL              OverflowError
->                20  <121>                40  ''
                  22  POP_TOP          
                  24  POP_TOP          
                  26  POP_TOP          
Instruction context:
   
 L. 288        42  LOAD_FAST                'existing'
                  44  LOAD_CONST               None
->                46  <117>                 0  ''
                  48  POP_JUMP_IF_FALSE    60  'to 60'
Instruction context:
   
 L. 341       152  DUP_TOP          
                 154  LOAD_GLOBAL              AttributeError
->               156  <121>               180  ''
                 158  POP_TOP          
                 160  POP_TOP          
                 162  POP_TOP          
Instruction context:
   
 L. 495        40  DUP_TOP          
                  42  LOAD_GLOBAL              ValueError
->                44  <121>                66  ''
                  46  POP_TOP          
                  48  POP_TOP          
                  50  POP_TOP          
Instruction context:
   
 L. 517        16  DUP_TOP          
                  18  LOAD_GLOBAL              AddressValueError
->                20  <121>                42  ''
                  22  POP_TOP          
                  24  POP_TOP          
                  26  POP_TOP          
Instruction context:
   
 L. 583        28  DUP_TOP          
                  30  LOAD_GLOBAL              AttributeError
->                32  <121>                48  ''
                  34  POP_TOP          
                  36  POP_TOP          
                  38  POP_TOP          
Instruction context:
   
 L. 642        30  LOAD_GLOBAL              _address_fmt_re
                  32  LOAD_CONST               None
->                34  <117>                 0  ''
                  36  POP_JUMP_IF_FALSE    56  'to 56'
Instruction context:
   
 L. 735        48  DUP_TOP          
                  50  LOAD_GLOBAL              AttributeError
->                52  <121>                68  ''
                  54  POP_TOP          
                  56  POP_TOP          
                  58  POP_TOP          
Instruction context:
   
 L. 961        22  LOAD_FAST                'new_prefix'
                  24  LOAD_CONST               None
->                26  <117>                 1  ''
                  28  POP_JUMP_IF_FALSE    74  'to 74'
Instruction context:
   
 L.1008        14  LOAD_FAST                'new_prefix'
                  16  LOAD_CONST               None
->                18  <117>                 1  ''
                  20  POP_JUMP_IF_FALSE    66  'to 66'
Instruction context:
   
 L.1045        60  DUP_TOP          
                  62  LOAD_GLOBAL              AttributeError
->                64  <121>                96  ''
                  66  POP_TOP          
                  68  POP_TOP          
                  70  POP_TOP          
Instruction context:
   
 L.1198        70  DUP_TOP          
                  72  LOAD_GLOBAL              ValueError
->                74  <121>               122  ''
                  76  POP_TOP          
                  78  STORE_FAST               'exc'
                  80  POP_TOP          
                  82  SETUP_FINALLY       114  'to 114'
Instruction context:
   
 L.1305        78  LOAD_STR                 '/'
                  80  LOAD_FAST                'addr_str'
->                82  <118>                 0  ''
                  84  POP_JUMP_IF_FALSE    98  'to 98'

test/39407.pyc -- 
# decompile failed

# file test/39407.pyc
# --- This code section failed: ---

 L.1335         0  LOAD_FAST                '.0'
                2  FOR_ITER             18  'to 18'
                4  STORE_FAST               'net'
                6  LOAD_DEREF               'self'
                8  LOAD_FAST                'net'
               10  <118>                 0  ''
               12  YIELD_VALUE      
               14  POP_TOP          
               16  JUMP_BACK             2  'to 2'

Parse error at or near `None' instruction at offset -1

