
# file test/39420.pyc
# --- This code section failed: ---

 L.   1         0  LOAD_STR                 'Utilities to support packages.'
                2  STORE_NAME               __doc__

 L.   3         4  LOAD_CONST               0
                6  LOAD_CONST               ('namedtuple',)
                8  IMPORT_NAME              collections
               10  IMPORT_FROM              namedtuple
               12  STORE_NAME               namedtuple
               14  POP_TOP          

 L.   4        16  LOAD_CONST               0
               18  LOAD_CONST               ('singledispatch',)
               20  IMPORT_NAME              functools
               22  IMPORT_FROM              singledispatch
               24  STORE_NAME               simplegeneric
               26  POP_TOP          

 L.   5        28  LOAD_CONST               0
               30  LOAD_CONST               None
               32  IMPORT_NAME              importlib
               34  STORE_NAME               importlib

 L.   6        36  LOAD_CONST               0
               38  LOAD_CONST               None
               40  IMPORT_NAME_ATTR         importlib.util
               42  STORE_NAME               importlib

 L.   7        44  LOAD_CONST               0
               46  LOAD_CONST               None
               48  IMPORT_NAME_ATTR         importlib.machinery
               50  STORE_NAME               importlib

 L.   8        52  LOAD_CONST               0
               54  LOAD_CONST               None
               56  IMPORT_NAME              os
               58  STORE_NAME               os

 L.   9        60  LOAD_CONST               0
               62  LOAD_CONST               None
               64  IMPORT_NAME_ATTR         os.path
               66  STORE_NAME               os

 L.  10        68  LOAD_CONST               0
               70  LOAD_CONST               None
               72  IMPORT_NAME              re
               74  STORE_NAME               re

 L.  11        76  LOAD_CONST               0
               78  LOAD_CONST               None
               80  IMPORT_NAME              sys
               82  STORE_NAME               sys

 L.  12        84  LOAD_CONST               0
               86  LOAD_CONST               ('ModuleType',)
               88  IMPORT_NAME              types
               90  IMPORT_FROM              ModuleType
               92  STORE_NAME               ModuleType
               94  POP_TOP          

 L.  13        96  LOAD_CONST               0
               98  LOAD_CONST               None
              100  IMPORT_NAME              warnings
              102  STORE_NAME               warnings

 L.  15       104  BUILD_LIST_0          0 
              106  LOAD_CONST               ('get_importer', 'iter_importers', 'get_loader', 'find_loader', 'walk_packages', 'iter_modules', 'get_data', 'ImpImporter', 'ImpLoader', 'read_code', 'extend_path', 'ModuleInfo')
              108  CALL_FINALLY        111  'to 111'
              110  STORE_NAME               __all__

 L.  23       112  LOAD_NAME                namedtuple
              114  LOAD_STR                 'ModuleInfo'
              116  LOAD_STR                 'module_finder name ispkg'
              118  CALL_FUNCTION_2       2  ''
              120  STORE_NAME               ModuleInfo

 L.  24       122  LOAD_STR                 'A namedtuple with minimal info about a module.'
              124  LOAD_NAME                ModuleInfo
              126  STORE_ATTR               __doc__

 L.  27       128  LOAD_CODE                <code_object _get_spec>
              130  LOAD_STR                 '_get_spec'
              132  MAKE_FUNCTION_0          'Neither defaults, keyword-only args, annotations, nor closures'
              134  STORE_NAME               _get_spec

 L.  41       136  LOAD_CODE                <code_object read_code>
              138  LOAD_STR                 'read_code'
              140  MAKE_FUNCTION_0          'Neither defaults, keyword-only args, annotations, nor closures'
              142  STORE_NAME               read_code

 L.  54       144  LOAD_CONST               (None, '', None)
              146  LOAD_CODE                <code_object walk_packages>
              148  LOAD_STR                 'walk_packages'
              150  MAKE_FUNCTION_1          'default'
              152  STORE_NAME               walk_packages

 L. 111       154  LOAD_CONST               (None, '')
              156  LOAD_CODE                <code_object iter_modules>
              158  LOAD_STR                 'iter_modules'
              160  MAKE_FUNCTION_1          'default'
              162  STORE_NAME               iter_modules

 L. 137       164  LOAD_NAME                simplegeneric

 L. 138       166  LOAD_CONST               ('',)
              168  LOAD_CODE                <code_object iter_importer_modules>
              170  LOAD_STR                 'iter_importer_modules'
              172  MAKE_FUNCTION_1          'default'
              174  CALL_FUNCTION_1       1  ''
              176  STORE_NAME               iter_importer_modules

 L. 145       178  LOAD_CONST               ('',)
              180  LOAD_CODE                <code_object _iter_file_finder_modules>
              182  LOAD_STR                 '_iter_file_finder_modules'
              184  MAKE_FUNCTION_1          'default'
              186  STORE_NAME               _iter_file_finder_modules

 L. 185       188  LOAD_NAME                iter_importer_modules
              190  LOAD_METHOD              register

 L. 186       192  LOAD_NAME                importlib
              194  LOAD_ATTR                machinery
              196  LOAD_ATTR                FileFinder
              198  LOAD_NAME                _iter_file_finder_modules

 L. 185       200  CALL_METHOD_2         2  ''
              202  POP_TOP          

 L. 189       204  LOAD_CODE                <code_object _import_imp>
              206  LOAD_STR                 '_import_imp'
              208  MAKE_FUNCTION_0          'Neither defaults, keyword-only args, annotations, nor closures'
              210  STORE_NAME               _import_imp

 L. 195       212  LOAD_BUILD_CLASS 
              214  LOAD_CODE                <code_object ImpImporter>
              216  LOAD_STR                 'ImpImporter'
              218  MAKE_FUNCTION_0          'Neither defaults, keyword-only args, annotations, nor closures'
              220  LOAD_STR                 'ImpImporter'
              222  CALL_FUNCTION_2       2  ''
              224  STORE_NAME               ImpImporter

 L. 269       226  LOAD_BUILD_CLASS 
              228  LOAD_CODE                <code_object ImpLoader>
              230  LOAD_STR                 'ImpLoader'
              232  MAKE_FUNCTION_0          'Neither defaults, keyword-only args, annotations, nor closures'
              234  LOAD_STR                 'ImpLoader'
              236  CALL_FUNCTION_2       2  ''
              238  STORE_NAME               ImpLoader

 L. 368       240  SETUP_FINALLY       288  'to 288'

 L. 369       242  LOAD_CONST               0
              244  LOAD_CONST               None
              246  IMPORT_NAME              zipimport
              248  STORE_NAME               zipimport

 L. 370       250  LOAD_CONST               0
              252  LOAD_CONST               ('zipimporter',)
              254  IMPORT_NAME              zipimport
              256  IMPORT_FROM              zipimporter
              258  STORE_NAME               zipimporter
              260  POP_TOP          

 L. 372       262  LOAD_CONST               ('',)
              264  LOAD_CODE                <code_object iter_zipimport_modules>
              266  LOAD_STR                 'iter_zipimport_modules'
              268  MAKE_FUNCTION_1          'default'
              270  STORE_NAME               iter_zipimport_modules

 L. 400       272  LOAD_NAME                iter_importer_modules
              274  LOAD_METHOD              register
              276  LOAD_NAME                zipimporter
              278  LOAD_NAME                iter_zipimport_modules
              280  CALL_METHOD_2         2  ''
              282  POP_TOP          
              284  POP_BLOCK        
              286  JUMP_FORWARD        308  'to 308'
            288_0  COME_FROM_FINALLY   240  '240'

 L. 402       288  DUP_TOP          
              290  LOAD_NAME                ImportError
          292_294  <121>               306  ''
              296  POP_TOP          
              298  POP_TOP          
              300  POP_TOP          

 L. 403       302  POP_EXCEPT       
              304  JUMP_FORWARD        308  'to 308'
              306  <48>             
            308_0  COME_FROM           304  '304'
            308_1  COME_FROM           286  '286'

 L. 406       308  LOAD_CODE                <code_object get_importer>
              310  LOAD_STR                 'get_importer'
              312  MAKE_FUNCTION_0          'Neither defaults, keyword-only args, annotations, nor closures'
              314  STORE_NAME               get_importer

 L. 431       316  LOAD_CONST               ('',)
              318  LOAD_CODE                <code_object iter_importers>
              320  LOAD_STR                 'iter_importers'
              322  MAKE_FUNCTION_1          'default'
              324  STORE_NAME               iter_importers

 L. 460       326  LOAD_CODE                <code_object get_loader>
              328  LOAD_STR                 'get_loader'
              330  MAKE_FUNCTION_0          'Neither defaults, keyword-only args, annotations, nor closures'
              332  STORE_NAME               get_loader

 L. 484       334  LOAD_CODE                <code_object find_loader>
              336  LOAD_STR                 'find_loader'
              338  MAKE_FUNCTION_0          'Neither defaults, keyword-only args, annotations, nor closures'
              340  STORE_NAME               find_loader

 L. 505       342  LOAD_CODE                <code_object extend_path>
              344  LOAD_STR                 'extend_path'
              346  MAKE_FUNCTION_0          'Neither defaults, keyword-only args, annotations, nor closures'
              348  STORE_NAME               extend_path

 L. 599       350  LOAD_CODE                <code_object get_data>
              352  LOAD_STR                 'get_data'
              354  MAKE_FUNCTION_0          'Neither defaults, keyword-only args, annotations, nor closures'
              356  STORE_NAME               get_data

 L. 642       358  LOAD_STR                 '(?!\\d)(\\w+)(\\.(?!\\d)(\\w+))*'
              360  STORE_NAME               _DOTTED_WORDS

 L. 643       362  LOAD_NAME                re
              364  LOAD_METHOD              compile
              366  LOAD_STR                 '^(?P<pkg>'
              368  LOAD_NAME                _DOTTED_WORDS
              370  FORMAT_VALUE          0  ''
              372  LOAD_STR                 ')(?P<cln>:(?P<obj>'
              374  LOAD_NAME                _DOTTED_WORDS
              376  FORMAT_VALUE          0  ''
              378  LOAD_STR                 ')?)?$'
              380  BUILD_STRING_5        5 
              382  LOAD_NAME                re
              384  LOAD_ATTR                U
              386  CALL_METHOD_2         2  ''
              388  STORE_NAME               _NAME_PATTERN

 L. 644       390  DELETE_NAME              _DOTTED_WORDS

 L. 646       392  LOAD_CODE                <code_object resolve_name>
              394  LOAD_STR                 'resolve_name'
              396  MAKE_FUNCTION_0          'Neither defaults, keyword-only args, annotations, nor closures'
              398  STORE_NAME               resolve_name

Parse error at or near `CALL_FINALLY' instruction at offset 108

Instruction context:
   
 L.  15       104  BUILD_LIST_0          0 
                 106  LOAD_CONST               ('get_importer', 'iter_importers', 'get_loader', 'find_loader', 'walk_packages', 'iter_modules', 'get_data', 'ImpImporter', 'ImpLoader', 'read_code', 'extend_path', 'ModuleInfo')
->               108  CALL_FINALLY        111  'to 111'
                 110  STORE_NAME               __all__

test/39420.pyc -- 
# decompile failed
