
# file test/39475.pyc
# --- This code section failed: ---

 L.   1         0  LOAD_CONST               0
                2  LOAD_CONST               None
                4  IMPORT_NAME              asyncio
                6  STORE_NAME               asyncio

 L.   2         8  LOAD_CONST               0
               10  LOAD_CONST               None
               12  IMPORT_NAME              codecs
               14  STORE_NAME               codecs

 L.   3        16  LOAD_CONST               0
               18  LOAD_CONST               None
               20  IMPORT_NAME              functools
               22  STORE_NAME               functools

 L.   4        24  LOAD_CONST               0
               26  LOAD_CONST               None
               28  IMPORT_NAME              io
               30  STORE_NAME               io

 L.   5        32  LOAD_CONST               0
               34  LOAD_CONST               None
               36  IMPORT_NAME              re
               38  STORE_NAME               re

 L.   6        40  LOAD_CONST               0
               42  LOAD_CONST               None
               44  IMPORT_NAME              sys
               46  STORE_NAME               sys

 L.   7        48  LOAD_CONST               0
               50  LOAD_CONST               None
               52  IMPORT_NAME              traceback
               54  STORE_NAME               traceback

 L.   8        56  LOAD_CONST               0
               58  LOAD_CONST               None
               60  IMPORT_NAME              warnings
               62  STORE_NAME               warnings

 L.   9        64  LOAD_CONST               0
               66  LOAD_CONST               ('md5', 'sha1', 'sha256')
               68  IMPORT_NAME              hashlib
               70  IMPORT_FROM              md5
               72  STORE_NAME               md5
               74  IMPORT_FROM              sha1
               76  STORE_NAME               sha1
               78  IMPORT_FROM              sha256
               80  STORE_NAME               sha256
               82  POP_TOP          

 L.  10        84  LOAD_CONST               0
               86  LOAD_CONST               ('CookieError', 'Morsel', 'SimpleCookie')
               88  IMPORT_NAME_ATTR         http.cookies
               90  IMPORT_FROM              CookieError
               92  STORE_NAME               CookieError
               94  IMPORT_FROM              Morsel
               96  STORE_NAME               Morsel
               98  IMPORT_FROM              SimpleCookie
              100  STORE_NAME               SimpleCookie
              102  POP_TOP          

 L.  11       104  LOAD_CONST               0
              106  LOAD_CONST               ('MappingProxyType', 'TracebackType')
              108  IMPORT_NAME              types
              110  IMPORT_FROM              MappingProxyType
              112  STORE_NAME               MappingProxyType
              114  IMPORT_FROM              TracebackType
              116  STORE_NAME               TracebackType
              118  POP_TOP          

 L.  12       120  LOAD_CONST               0
              122  LOAD_CONST               ('TYPE_CHECKING', 'Any', 'Dict', 'Iterable', 'List', 'Mapping', 'Optional', 'Tuple', 'Type', 'Union', 'cast')
              124  IMPORT_NAME              typing
              126  IMPORT_FROM              TYPE_CHECKING
              128  STORE_NAME               TYPE_CHECKING
              130  IMPORT_FROM              Any
              132  STORE_NAME               Any
              134  IMPORT_FROM              Dict
              136  STORE_NAME               Dict
              138  IMPORT_FROM              Iterable
              140  STORE_NAME               Iterable
              142  IMPORT_FROM              List
              144  STORE_NAME               List
              146  IMPORT_FROM              Mapping
              148  STORE_NAME               Mapping
              150  IMPORT_FROM              Optional
              152  STORE_NAME               Optional
              154  IMPORT_FROM              Tuple
              156  STORE_NAME               Tuple
              158  IMPORT_FROM              Type
              160  STORE_NAME               Type
              162  IMPORT_FROM              Union
              164  STORE_NAME               Union
              166  IMPORT_FROM              cast
              168  STORE_NAME               cast
              170  POP_TOP          

 L.  26       172  LOAD_CONST               0
              174  LOAD_CONST               None
              176  IMPORT_NAME              attr
              178  STORE_NAME               attr

 L.  27       180  LOAD_CONST               0
              182  LOAD_CONST               ('CIMultiDict', 'CIMultiDictProxy', 'MultiDict', 'MultiDictProxy')
              184  IMPORT_NAME              multidict
              186  IMPORT_FROM              CIMultiDict
              188  STORE_NAME               CIMultiDict
              190  IMPORT_FROM              CIMultiDictProxy
              192  STORE_NAME               CIMultiDictProxy
              194  IMPORT_FROM              MultiDict
              196  STORE_NAME               MultiDict
              198  IMPORT_FROM              MultiDictProxy
              200  STORE_NAME               MultiDictProxy
              202  POP_TOP          

 L.  28       204  LOAD_CONST               0
              206  LOAD_CONST               ('URL',)
              208  IMPORT_NAME              yarl
              210  IMPORT_FROM              URL
              212  STORE_NAME               URL
              214  POP_TOP          

 L.  30       216  LOAD_CONST               1
              218  LOAD_CONST               ('hdrs', 'helpers', 'http', 'multipart', 'payload')
              220  IMPORT_NAME              
              222  IMPORT_FROM              hdrs
              224  STORE_NAME               hdrs
              226  IMPORT_FROM              helpers
              228  STORE_NAME               helpers
              230  IMPORT_FROM              http
              232  STORE_NAME               http
              234  IMPORT_FROM              multipart
              236  STORE_NAME               multipart
              238  IMPORT_FROM              payload
              240  STORE_NAME               payload
              242  POP_TOP          

 L.  31       244  LOAD_CONST               1
              246  LOAD_CONST               ('AbstractStreamWriter',)
              248  IMPORT_NAME              abc
              250  IMPORT_FROM              AbstractStreamWriter
              252  STORE_NAME               AbstractStreamWriter
              254  POP_TOP          

 L.  32       256  LOAD_CONST               1
              258  LOAD_CONST               ('ClientConnectionError', 'ClientOSError', 'ClientResponseError', 'ContentTypeError', 'InvalidURL', 'ServerFingerprintMismatch')
              260  IMPORT_NAME              client_exceptions
              262  IMPORT_FROM              ClientConnectionError
              264  STORE_NAME               ClientConnectionError
              266  IMPORT_FROM              ClientOSError
              268  STORE_NAME               ClientOSError
              270  IMPORT_FROM              ClientResponseError
              272  STORE_NAME               ClientResponseError
              274  IMPORT_FROM              ContentTypeError
              276  STORE_NAME               ContentTypeError
              278  IMPORT_FROM              InvalidURL
              280  STORE_NAME               InvalidURL
              282  IMPORT_FROM              ServerFingerprintMismatch
              284  STORE_NAME               ServerFingerprintMismatch
              286  POP_TOP          

 L.  40       288  LOAD_CONST               1
              290  LOAD_CONST               ('FormData',)
              292  IMPORT_NAME              formdata
              294  IMPORT_FROM              FormData
              296  STORE_NAME               FormData
              298  POP_TOP          

 L.  41       300  LOAD_CONST               1
              302  LOAD_CONST               ('PY_36', 'BaseTimerContext', 'BasicAuth', 'HeadersMixin', 'TimerNoop', 'noop', 'reify', 'set_result')
              304  IMPORT_NAME              helpers
              306  IMPORT_FROM              PY_36
              308  STORE_NAME               PY_36
              310  IMPORT_FROM              BaseTimerContext
              312  STORE_NAME               BaseTimerContext
              314  IMPORT_FROM              BasicAuth
              316  STORE_NAME               BasicAuth
              318  IMPORT_FROM              HeadersMixin
              320  STORE_NAME               HeadersMixin
              322  IMPORT_FROM              TimerNoop
              324  STORE_NAME               TimerNoop
              326  IMPORT_FROM              noop
              328  STORE_NAME               noop
              330  IMPORT_FROM              reify
              332  STORE_NAME               reify
              334  IMPORT_FROM              set_result
              336  STORE_NAME               set_result
              338  POP_TOP          

 L.  51       340  LOAD_CONST               1
              342  LOAD_CONST               ('SERVER_SOFTWARE', 'HttpVersion10', 'HttpVersion11', 'StreamWriter')
              344  IMPORT_NAME              http
              346  IMPORT_FROM              SERVER_SOFTWARE
              348  STORE_NAME               SERVER_SOFTWARE
              350  IMPORT_FROM              HttpVersion10
              352  STORE_NAME               HttpVersion10
              354  IMPORT_FROM              HttpVersion11
              356  STORE_NAME               HttpVersion11
              358  IMPORT_FROM              StreamWriter
              360  STORE_NAME               StreamWriter
              362  POP_TOP          

 L.  52       364  LOAD_CONST               1
              366  LOAD_CONST               ('client_logger',)
              368  IMPORT_NAME              log
              370  IMPORT_FROM              client_logger
              372  STORE_NAME               client_logger
              374  POP_TOP          

 L.  53       376  LOAD_CONST               1
              378  LOAD_CONST               ('StreamReader',)
              380  IMPORT_NAME              streams
              382  IMPORT_FROM              StreamReader
              384  STORE_NAME               StreamReader
              386  POP_TOP          

 L.  54       388  LOAD_CONST               1
              390  LOAD_CONST               ('DEFAULT_JSON_DECODER', 'JSONDecoder', 'LooseCookies', 'LooseHeaders', 'RawHeaders')
              392  IMPORT_NAME              typedefs
              394  IMPORT_FROM              DEFAULT_JSON_DECODER
              396  STORE_NAME               DEFAULT_JSON_DECODER
              398  IMPORT_FROM              JSONDecoder
              400  STORE_NAME               JSONDecoder
              402  IMPORT_FROM              LooseCookies
              404  STORE_NAME               LooseCookies
              406  IMPORT_FROM              LooseHeaders
              408  STORE_NAME               LooseHeaders
              410  IMPORT_FROM              RawHeaders
              412  STORE_NAME               RawHeaders
              414  POP_TOP          

 L.  62       416  SETUP_FINALLY       442  'to 442'

 L.  63       418  LOAD_CONST               0
              420  LOAD_CONST               None
              422  IMPORT_NAME              ssl
              424  STORE_NAME               ssl

 L.  64       426  LOAD_CONST               0
              428  LOAD_CONST               ('SSLContext',)
              430  IMPORT_NAME              ssl
              432  IMPORT_FROM              SSLContext
              434  STORE_NAME               SSLContext
              436  POP_TOP          
              438  POP_BLOCK        
              440  JUMP_FORWARD        470  'to 470'
            442_0  COME_FROM_FINALLY   416  '416'

 L.  65       442  DUP_TOP          
              444  LOAD_NAME                ImportError
          446_448  <121>               468  ''
              450  POP_TOP          
              452  POP_TOP          
              454  POP_TOP          

 L.  66       456  LOAD_CONST               None
              458  STORE_NAME               ssl

 L.  67       460  LOAD_NAME                object
              462  STORE_NAME               SSLContext
              464  POP_EXCEPT       
              466  JUMP_FORWARD        470  'to 470'
              468  <48>             
            470_0  COME_FROM           466  '466'
            470_1  COME_FROM           440  '440'

 L.  69       470  SETUP_FINALLY       484  'to 484'

 L.  70       472  LOAD_CONST               0
              474  LOAD_CONST               None
              476  IMPORT_NAME              cchardet
              478  STORE_NAME               chardet
              480  POP_BLOCK        
              482  JUMP_FORWARD        512  'to 512'
            484_0  COME_FROM_FINALLY   470  '470'

 L.  71       484  DUP_TOP          
              486  LOAD_NAME                ImportError
          488_490  <121>               510  ''
              492  POP_TOP          
              494  POP_TOP          
              496  POP_TOP          

 L.  72       498  LOAD_CONST               0
              500  LOAD_CONST               None
              502  IMPORT_NAME              chardet
              504  STORE_NAME               chardet
              506  POP_EXCEPT       
              508  JUMP_FORWARD        512  'to 512'
              510  <48>             
            512_0  COME_FROM           508  '508'
            512_1  COME_FROM           482  '482'

 L.  75       512  LOAD_CONST               ('ClientRequest', 'ClientResponse', 'RequestInfo', 'Fingerprint')
              514  STORE_NAME               __all__

 L.  78       516  LOAD_NAME                TYPE_CHECKING
          518_520  POP_JUMP_IF_FALSE   558  'to 558'

 L.  79       522  LOAD_CONST               1
              524  LOAD_CONST               ('ClientSession',)
              526  IMPORT_NAME              client
              528  IMPORT_FROM              ClientSession
              530  STORE_NAME               ClientSession
              532  POP_TOP          

 L.  80       534  LOAD_CONST               1
              536  LOAD_CONST               ('Connection',)
              538  IMPORT_NAME              connector
              540  IMPORT_FROM              Connection
              542  STORE_NAME               Connection
              544  POP_TOP          

 L.  81       546  LOAD_CONST               1
              548  LOAD_CONST               ('Trace',)
              550  IMPORT_NAME              tracing
              552  IMPORT_FROM              Trace
              554  STORE_NAME               Trace
              556  POP_TOP          
            558_0  COME_FROM           518  '518'

 L.  84       558  LOAD_NAME                re
              560  LOAD_METHOD              compile
              562  LOAD_STR                 '^application/(?:[\\w.+-]+?\\+)?json'
              564  CALL_METHOD_1         1  ''
              566  STORE_NAME               json_re

 L.  87       568  LOAD_NAME                attr
              570  LOAD_ATTR                s
              572  LOAD_CONST               True
              574  LOAD_CONST               True
              576  LOAD_CONST               True
              578  LOAD_CONST               ('auto_attribs', 'frozen', 'slots')
              580  CALL_FUNCTION_KW_3     3  '3 total positional and keyword args'

 L.  88       582  LOAD_BUILD_CLASS 
              584  LOAD_CODE                <code_object ContentDisposition>
              586  LOAD_STR                 'ContentDisposition'
              588  MAKE_FUNCTION_0          'Neither defaults, keyword-only args, annotations, nor closures'
              590  LOAD_STR                 'ContentDisposition'
              592  CALL_FUNCTION_2       2  ''
              594  CALL_FUNCTION_1       1  ''
              596  STORE_NAME               ContentDisposition

 L.  94       598  LOAD_NAME                attr
              600  LOAD_ATTR                s
              602  LOAD_CONST               True
              604  LOAD_CONST               True
              606  LOAD_CONST               True
              608  LOAD_CONST               ('auto_attribs', 'frozen', 'slots')
              610  CALL_FUNCTION_KW_3     3  '3 total positional and keyword args'

 L.  95       612  LOAD_BUILD_CLASS 
              614  LOAD_CODE                <code_object RequestInfo>
              616  LOAD_STR                 'RequestInfo'
              618  MAKE_FUNCTION_0          'Neither defaults, keyword-only args, annotations, nor closures'
              620  LOAD_STR                 'RequestInfo'
              622  CALL_FUNCTION_2       2  ''
              624  CALL_FUNCTION_1       1  ''
              626  STORE_NAME               RequestInfo

 L. 106       628  LOAD_BUILD_CLASS 
              630  LOAD_CODE                <code_object Fingerprint>
              632  LOAD_STR                 'Fingerprint'
              634  MAKE_FUNCTION_0          'Neither defaults, keyword-only args, annotations, nor closures'
              636  LOAD_STR                 'Fingerprint'
              638  CALL_FUNCTION_2       2  ''
              640  STORE_NAME               Fingerprint

 L. 140       642  LOAD_NAME                ssl
              644  LOAD_CONST               None
              646  <117>                 1  ''
          648_650  POP_JUMP_IF_FALSE   672  'to 672'

 L. 141       652  LOAD_NAME                ssl
              654  LOAD_ATTR                SSLContext
              656  LOAD_NAME                bool
              658  LOAD_NAME                Fingerprint
              660  LOAD_NAME                type
              662  LOAD_CONST               None
              664  CALL_FUNCTION_1       1  ''
              666  BUILD_TUPLE_4         4 
              668  STORE_NAME               SSL_ALLOWED_TYPES
              670  JUMP_FORWARD        680  'to 680'
            672_0  COME_FROM           648  '648'

 L. 143       672  LOAD_NAME                type
              674  LOAD_CONST               None
              676  CALL_FUNCTION_1       1  ''
              678  STORE_NAME               SSL_ALLOWED_TYPES
            680_0  COME_FROM           670  '670'

 L. 147       680  LOAD_NAME                Union
              682  LOAD_STR                 'SSLContext'
              684  LOAD_NAME                bool
              686  LOAD_NAME                Fingerprint
              688  LOAD_CONST               None
              690  BUILD_TUPLE_4         4 
              692  BINARY_SUBSCR    

 L. 148       694  LOAD_NAME                Optional
              696  LOAD_NAME                bool
              698  BINARY_SUBSCR    

 L. 149       700  LOAD_NAME                Optional
              702  LOAD_STR                 'SSLContext'
              704  BINARY_SUBSCR    

 L. 150       706  LOAD_NAME                Optional
              708  LOAD_NAME                bytes
              710  BINARY_SUBSCR    

 L. 151       712  LOAD_NAME                Union
              714  LOAD_STR                 'SSLContext'
              716  LOAD_NAME                bool
              718  LOAD_NAME                Fingerprint
              720  LOAD_CONST               None
              722  BUILD_TUPLE_4         4 
              724  BINARY_SUBSCR    

 L. 146       726  LOAD_CONST               ('ssl', 'verify_ssl', 'ssl_context', 'fingerprint', 'return')
              728  BUILD_CONST_KEY_MAP_5     5 
              730  LOAD_CODE                <code_object _merge_ssl_params>
              732  LOAD_STR                 '_merge_ssl_params'
              734  MAKE_FUNCTION_4          'annotation'
              736  STORE_NAME               _merge_ssl_params

 L. 199       738  LOAD_NAME                attr
              740  LOAD_ATTR                s
              742  LOAD_CONST               True
              744  LOAD_CONST               True
              746  LOAD_CONST               True
              748  LOAD_CONST               ('auto_attribs', 'slots', 'frozen')
              750  CALL_FUNCTION_KW_3     3  '3 total positional and keyword args'

 L. 200       752  LOAD_BUILD_CLASS 
              754  LOAD_CODE                <code_object ConnectionKey>
              756  LOAD_STR                 'ConnectionKey'
              758  MAKE_FUNCTION_0          'Neither defaults, keyword-only args, annotations, nor closures'
              760  LOAD_STR                 'ConnectionKey'
              762  CALL_FUNCTION_2       2  ''
              764  CALL_FUNCTION_1       1  ''
              766  STORE_NAME               ConnectionKey

 L. 213       768  LOAD_NAME                str
              770  LOAD_NAME                str

 L. 214       772  LOAD_NAME                bool

 L. 212       774  LOAD_CONST               ('response_content_type', 'expected_content_type', 'return')
              776  BUILD_CONST_KEY_MAP_3     3 
              778  LOAD_CODE                <code_object _is_expected_content_type>
              780  LOAD_STR                 '_is_expected_content_type'
              782  MAKE_FUNCTION_4          'annotation'
              784  STORE_NAME               _is_expected_content_type

 L. 220       786  LOAD_BUILD_CLASS 
              788  LOAD_CODE                <code_object ClientRequest>
              790  LOAD_STR                 'ClientRequest'
              792  MAKE_FUNCTION_0          'Neither defaults, keyword-only args, annotations, nor closures'
              794  LOAD_STR                 'ClientRequest'
              796  CALL_FUNCTION_2       2  ''
              798  STORE_NAME               ClientRequest

 L. 705       800  LOAD_BUILD_CLASS 
              802  LOAD_CODE                <code_object ClientResponse>
              804  LOAD_STR                 'ClientResponse'
              806  MAKE_FUNCTION_0          'Neither defaults, keyword-only args, annotations, nor closures'
              808  LOAD_STR                 'ClientResponse'
              810  LOAD_NAME                HeadersMixin
              812  CALL_FUNCTION_3       3  ''
              814  STORE_NAME               ClientResponse

Parse error at or near `<121>' instruction at offset 446_448

Instruction context:
   
 L.  65       442  DUP_TOP          
                 444  LOAD_NAME                ImportError
->           446_448  <121>               468  ''
                 450  POP_TOP          
                 452  POP_TOP          
                 454  POP_TOP          

test/39475.pyc -- 
# decompile failed
