
# file test/39549.pyc
# --- This code section failed: ---

 L.   1         0  LOAD_STR                 '\nCommonly useful validators.\n'
                2  STORE_NAME               __doc__

 L.   5         4  LOAD_CONST               0
                6  LOAD_CONST               ('absolute_import', 'division', 'print_function')
                8  IMPORT_NAME              __future__
               10  IMPORT_FROM              absolute_import
               12  STORE_NAME               absolute_import
               14  IMPORT_FROM              division
               16  STORE_NAME               division
               18  IMPORT_FROM              print_function
               20  STORE_NAME               print_function
               22  POP_TOP          

 L.   7        24  LOAD_CONST               0
               26  LOAD_CONST               None
               28  IMPORT_NAME              re
               30  STORE_NAME               re

 L.   9        32  LOAD_CONST               1
               34  LOAD_CONST               ('_AndValidator', 'and_', 'attrib', 'attrs')
               36  IMPORT_NAME              _make
               38  IMPORT_FROM              _AndValidator
               40  STORE_NAME               _AndValidator
               42  IMPORT_FROM              and_
               44  STORE_NAME               and_
               46  IMPORT_FROM              attrib
               48  STORE_NAME               attrib
               50  IMPORT_FROM              attrs
               52  STORE_NAME               attrs
               54  POP_TOP          

 L.  10        56  LOAD_CONST               1
               58  LOAD_CONST               ('NotCallableError',)
               60  IMPORT_NAME              exceptions
               62  IMPORT_FROM              NotCallableError
               64  STORE_NAME               NotCallableError
               66  POP_TOP          

 L.  13        68  BUILD_LIST_0          0 
               70  LOAD_CONST               ('and_', 'deep_iterable', 'deep_mapping', 'in_', 'instance_of', 'is_callable', 'matches_re', 'optional', 'provides')
               72  CALL_FINALLY         75  'to 75'
               74  STORE_NAME               __all__

 L.  26        76  LOAD_NAME                attrs
               78  LOAD_CONST               False
               80  LOAD_CONST               True
               82  LOAD_CONST               True
               84  LOAD_CONST               ('repr', 'slots', 'hash')
               86  CALL_FUNCTION_KW_3     3  '3 total positional and keyword args'

 L.  27        88  LOAD_BUILD_CLASS 
               90  LOAD_CODE                <code_object _InstanceOfValidator>
               92  LOAD_STR                 '_InstanceOfValidator'
               94  MAKE_FUNCTION_0          'Neither defaults, keyword-only args, annotations, nor closures'
               96  LOAD_STR                 '_InstanceOfValidator'
               98  LOAD_NAME                object
              100  CALL_FUNCTION_3       3  ''
              102  CALL_FUNCTION_1       1  ''
              104  STORE_NAME               _InstanceOfValidator

 L.  54       106  LOAD_CODE                <code_object instance_of>
              108  LOAD_STR                 'instance_of'
              110  MAKE_FUNCTION_0          'Neither defaults, keyword-only args, annotations, nor closures'
              112  STORE_NAME               instance_of

 L.  70       114  LOAD_NAME                attrs
              116  LOAD_CONST               False
              118  LOAD_CONST               True
              120  LOAD_CONST               True
              122  LOAD_CONST               ('repr', 'frozen', 'slots')
              124  CALL_FUNCTION_KW_3     3  '3 total positional and keyword args'

 L.  71       126  LOAD_BUILD_CLASS 
              128  LOAD_CODE                <code_object _MatchesReValidator>
              130  LOAD_STR                 '_MatchesReValidator'
              132  MAKE_FUNCTION_0          'Neither defaults, keyword-only args, annotations, nor closures'
              134  LOAD_STR                 '_MatchesReValidator'
              136  LOAD_NAME                object
              138  CALL_FUNCTION_3       3  ''
              140  CALL_FUNCTION_1       1  ''
              142  STORE_NAME               _MatchesReValidator

 L.  97       144  LOAD_CONST               (0, None)
              146  LOAD_CODE                <code_object matches_re>
              148  LOAD_STR                 'matches_re'
              150  MAKE_FUNCTION_1          'default'
              152  STORE_NAME               matches_re

 L. 142       154  LOAD_NAME                attrs
              156  LOAD_CONST               False
              158  LOAD_CONST               True
              160  LOAD_CONST               True
              162  LOAD_CONST               ('repr', 'slots', 'hash')
              164  CALL_FUNCTION_KW_3     3  '3 total positional and keyword args'

 L. 143       166  LOAD_BUILD_CLASS 
              168  LOAD_CODE                <code_object _ProvidesValidator>
              170  LOAD_STR                 '_ProvidesValidator'
              172  MAKE_FUNCTION_0          'Neither defaults, keyword-only args, annotations, nor closures'
              174  LOAD_STR                 '_ProvidesValidator'
              176  LOAD_NAME                object
              178  CALL_FUNCTION_3       3  ''
              180  CALL_FUNCTION_1       1  ''
              182  STORE_NAME               _ProvidesValidator

 L. 167       184  LOAD_CODE                <code_object provides>
              186  LOAD_STR                 'provides'
              188  MAKE_FUNCTION_0          'Neither defaults, keyword-only args, annotations, nor closures'
              190  STORE_NAME               provides

 L. 184       192  LOAD_NAME                attrs
              194  LOAD_CONST               False
              196  LOAD_CONST               True
              198  LOAD_CONST               True
              200  LOAD_CONST               ('repr', 'slots', 'hash')
              202  CALL_FUNCTION_KW_3     3  '3 total positional and keyword args'

 L. 185       204  LOAD_BUILD_CLASS 
              206  LOAD_CODE                <code_object _OptionalValidator>
              208  LOAD_STR                 '_OptionalValidator'
              210  MAKE_FUNCTION_0          'Neither defaults, keyword-only args, annotations, nor closures'
              212  LOAD_STR                 '_OptionalValidator'
              214  LOAD_NAME                object
              216  CALL_FUNCTION_3       3  ''
              218  CALL_FUNCTION_1       1  ''
              220  STORE_NAME               _OptionalValidator

 L. 200       222  LOAD_CODE                <code_object optional>
              224  LOAD_STR                 'optional'
              226  MAKE_FUNCTION_0          'Neither defaults, keyword-only args, annotations, nor closures'
              228  STORE_NAME               optional

 L. 218       230  LOAD_NAME                attrs
              232  LOAD_CONST               False
              234  LOAD_CONST               True
              236  LOAD_CONST               True
              238  LOAD_CONST               ('repr', 'slots', 'hash')
              240  CALL_FUNCTION_KW_3     3  '3 total positional and keyword args'

 L. 219       242  LOAD_BUILD_CLASS 
              244  LOAD_CODE                <code_object _InValidator>
              246  LOAD_STR                 '_InValidator'
              248  MAKE_FUNCTION_0          'Neither defaults, keyword-only args, annotations, nor closures'
              250  LOAD_STR                 '_InValidator'
              252  LOAD_NAME                object
              254  CALL_FUNCTION_3       3  ''
              256  CALL_FUNCTION_1       1  ''
              258  STORE_NAME               _InValidator

 L. 241       260  LOAD_CODE                <code_object in_>
              262  LOAD_STR                 'in_'
              264  MAKE_FUNCTION_0          'Neither defaults, keyword-only args, annotations, nor closures'
              266  STORE_NAME               in_

 L. 259       268  LOAD_NAME                attrs
              270  LOAD_CONST               False
              272  LOAD_CONST               False
              274  LOAD_CONST               True
              276  LOAD_CONST               ('repr', 'slots', 'hash')
              278  CALL_FUNCTION_KW_3     3  '3 total positional and keyword args'

 L. 260       280  LOAD_BUILD_CLASS 
              282  LOAD_CODE                <code_object _IsCallableValidator>
              284  LOAD_STR                 '_IsCallableValidator'
              286  MAKE_FUNCTION_0          'Neither defaults, keyword-only args, annotations, nor closures'
              288  LOAD_STR                 '_IsCallableValidator'
              290  LOAD_NAME                object
              292  CALL_FUNCTION_3       3  ''
              294  CALL_FUNCTION_1       1  ''
              296  STORE_NAME               _IsCallableValidator

 L. 281       298  LOAD_CODE                <code_object is_callable>
              300  LOAD_STR                 'is_callable'
              302  MAKE_FUNCTION_0          'Neither defaults, keyword-only args, annotations, nor closures'
              304  STORE_NAME               is_callable

 L. 296       306  LOAD_NAME                attrs
              308  LOAD_CONST               False
              310  LOAD_CONST               True
              312  LOAD_CONST               True
              314  LOAD_CONST               ('repr', 'slots', 'hash')
              316  CALL_FUNCTION_KW_3     3  '3 total positional and keyword args'

 L. 297       318  LOAD_BUILD_CLASS 
              320  LOAD_CODE                <code_object _DeepIterable>
              322  LOAD_STR                 '_DeepIterable'
              324  MAKE_FUNCTION_0          'Neither defaults, keyword-only args, annotations, nor closures'
              326  LOAD_STR                 '_DeepIterable'
              328  LOAD_NAME                object
              330  CALL_FUNCTION_3       3  ''
              332  CALL_FUNCTION_1       1  ''
              334  STORE_NAME               _DeepIterable

 L. 328       336  LOAD_CONST               (None,)
              338  LOAD_CODE                <code_object deep_iterable>
              340  LOAD_STR                 'deep_iterable'
              342  MAKE_FUNCTION_1          'default'
              344  STORE_NAME               deep_iterable

 L. 343       346  LOAD_NAME                attrs
              348  LOAD_CONST               False
              350  LOAD_CONST               True
              352  LOAD_CONST               True
              354  LOAD_CONST               ('repr', 'slots', 'hash')
              356  CALL_FUNCTION_KW_3     3  '3 total positional and keyword args'

 L. 344       358  LOAD_BUILD_CLASS 
              360  LOAD_CODE                <code_object _DeepMapping>
              362  LOAD_STR                 '_DeepMapping'
              364  MAKE_FUNCTION_0          'Neither defaults, keyword-only args, annotations, nor closures'
              366  LOAD_STR                 '_DeepMapping'
              368  LOAD_NAME                object
              370  CALL_FUNCTION_3       3  ''
              372  CALL_FUNCTION_1       1  ''
              374  STORE_NAME               _DeepMapping

 L. 366       376  LOAD_CONST               (None,)
              378  LOAD_CODE                <code_object deep_mapping>
              380  LOAD_STR                 'deep_mapping'
              382  MAKE_FUNCTION_1          'default'
              384  STORE_NAME               deep_mapping

Parse error at or near `CALL_FINALLY' instruction at offset 72

Instruction context:
   
 L.  13        68  BUILD_LIST_0          0 
                  70  LOAD_CONST               ('and_', 'deep_iterable', 'deep_mapping', 'in_', 'instance_of', 'is_callable', 'matches_re', 'optional', 'provides')
->                72  CALL_FINALLY         75  'to 75'
                  74  STORE_NAME               __all__

test/39549.pyc -- 
# decompile failed
