
# file test/39603.pyc
# --- This code section failed: ---

 L.   1         0  SETUP_FINALLY        14  'to 14'

 L.   2         2  LOAD_CONST               0
                4  LOAD_CONST               None
                6  IMPORT_NAME              unicodedata2
                8  STORE_NAME               unicodedata
               10  POP_BLOCK        
               12  JUMP_FORWARD         40  'to 40'
             14_0  COME_FROM_FINALLY     0  '0'

 L.   3        14  DUP_TOP          
               16  LOAD_NAME                ImportError
               18  <121>                38  ''
               20  POP_TOP          
               22  POP_TOP          
               24  POP_TOP          

 L.   4        26  LOAD_CONST               0
               28  LOAD_CONST               None
               30  IMPORT_NAME              unicodedata
               32  STORE_NAME               unicodedata
               34  POP_EXCEPT       
               36  JUMP_FORWARD         40  'to 40'
               38  <48>             
             40_0  COME_FROM            36  '36'
             40_1  COME_FROM            12  '12'

 L.   6        40  LOAD_CONST               0
               42  LOAD_CONST               ('IncrementalDecoder',)
               44  IMPORT_NAME              codecs
               46  IMPORT_FROM              IncrementalDecoder
               48  STORE_NAME               IncrementalDecoder
               50  POP_TOP          

 L.   7        52  LOAD_CONST               0
               54  LOAD_CONST               ('findall',)
               56  IMPORT_NAME              re
               58  IMPORT_FROM              findall
               60  STORE_NAME               findall
               62  POP_TOP          

 L.   8        64  LOAD_CONST               0
               66  LOAD_CONST               ('Optional', 'Tuple', 'Union', 'List', 'Set')
               68  IMPORT_NAME              typing
               70  IMPORT_FROM              Optional
               72  STORE_NAME               Optional
               74  IMPORT_FROM              Tuple
               76  STORE_NAME               Tuple
               78  IMPORT_FROM              Union
               80  STORE_NAME               Union
               82  IMPORT_FROM              List
               84  STORE_NAME               List
               86  IMPORT_FROM              Set
               88  STORE_NAME               Set
               90  POP_TOP          

 L.   9        92  LOAD_CONST               0
               94  LOAD_CONST               None
               96  IMPORT_NAME              importlib
               98  STORE_NAME               importlib

 L.  10       100  LOAD_CONST               0
              102  LOAD_CONST               ('MultibyteIncrementalDecoder',)
              104  IMPORT_NAME              _multibytecodec
              106  IMPORT_FROM              MultibyteIncrementalDecoder
              108  STORE_NAME               MultibyteIncrementalDecoder
              110  POP_TOP          

 L.  12       112  LOAD_CONST               0
              114  LOAD_CONST               ('aliases',)
              116  IMPORT_NAME_ATTR         encodings.aliases
              118  IMPORT_FROM              aliases
              120  STORE_NAME               aliases
              122  POP_TOP          

 L.  13       124  LOAD_CONST               0
              126  LOAD_CONST               ('lru_cache',)
              128  IMPORT_NAME              functools
              130  IMPORT_FROM              lru_cache
              132  STORE_NAME               lru_cache
              134  POP_TOP          

 L.  15       136  LOAD_CONST               0
              138  LOAD_CONST               ('UNICODE_RANGES_COMBINED', 'UNICODE_SECONDARY_RANGE_KEYWORD', 'RE_POSSIBLE_ENCODING_INDICATION', 'ENCODING_MARKS', 'UTF8_MAXIMAL_ALLOCATION', 'IANA_SUPPORTED_SIMILAR')
              140  IMPORT_NAME_ATTR         charset_normalizer.constant
              142  IMPORT_FROM              UNICODE_RANGES_COMBINED
              144  STORE_NAME               UNICODE_RANGES_COMBINED
              146  IMPORT_FROM              UNICODE_SECONDARY_RANGE_KEYWORD
              148  STORE_NAME               UNICODE_SECONDARY_RANGE_KEYWORD
              150  IMPORT_FROM              RE_POSSIBLE_ENCODING_INDICATION
              152  STORE_NAME               RE_POSSIBLE_ENCODING_INDICATION
              154  IMPORT_FROM              ENCODING_MARKS
              156  STORE_NAME               ENCODING_MARKS
              158  IMPORT_FROM              UTF8_MAXIMAL_ALLOCATION
              160  STORE_NAME               UTF8_MAXIMAL_ALLOCATION
              162  IMPORT_FROM              IANA_SUPPORTED_SIMILAR
              164  STORE_NAME               IANA_SUPPORTED_SIMILAR
              166  POP_TOP          

 L.  19       168  LOAD_NAME                lru_cache
              170  LOAD_NAME                UTF8_MAXIMAL_ALLOCATION
              172  LOAD_CONST               ('maxsize',)
              174  CALL_FUNCTION_KW_1     1  '1 total positional and keyword args'

 L.  20       176  LOAD_NAME                str
              178  LOAD_NAME                bool
              180  LOAD_CONST               ('character', 'return')
              182  BUILD_CONST_KEY_MAP_2     2 
              184  LOAD_CODE                <code_object is_accentuated>
              186  LOAD_STR                 'is_accentuated'
              188  MAKE_FUNCTION_4          'annotation'
              190  CALL_FUNCTION_1       1  ''
              192  STORE_NAME               is_accentuated

 L.  28       194  LOAD_NAME                lru_cache
              196  LOAD_NAME                UTF8_MAXIMAL_ALLOCATION
              198  LOAD_CONST               ('maxsize',)
              200  CALL_FUNCTION_KW_1     1  '1 total positional and keyword args'

 L.  29       202  LOAD_NAME                str
              204  LOAD_NAME                str
              206  LOAD_CONST               ('character', 'return')
              208  BUILD_CONST_KEY_MAP_2     2 
              210  LOAD_CODE                <code_object remove_accent>
              212  LOAD_STR                 'remove_accent'
              214  MAKE_FUNCTION_4          'annotation'
              216  CALL_FUNCTION_1       1  ''
              218  STORE_NAME               remove_accent

 L.  44       220  LOAD_NAME                lru_cache
              222  LOAD_NAME                UTF8_MAXIMAL_ALLOCATION
              224  LOAD_CONST               ('maxsize',)
              226  CALL_FUNCTION_KW_1     1  '1 total positional and keyword args'

 L.  45       228  LOAD_NAME                str
              230  LOAD_NAME                Optional
              232  LOAD_NAME                str
              234  BINARY_SUBSCR    
              236  LOAD_CONST               ('character', 'return')
              238  BUILD_CONST_KEY_MAP_2     2 
              240  LOAD_CODE                <code_object unicode_range>
              242  LOAD_STR                 'unicode_range'
              244  MAKE_FUNCTION_4          'annotation'
              246  CALL_FUNCTION_1       1  ''
              248  STORE_NAME               unicode_range

 L.  58       250  LOAD_NAME                lru_cache
              252  LOAD_NAME                UTF8_MAXIMAL_ALLOCATION
              254  LOAD_CONST               ('maxsize',)
              256  CALL_FUNCTION_KW_1     1  '1 total positional and keyword args'

 L.  59       258  LOAD_NAME                str
              260  LOAD_NAME                bool
              262  LOAD_CONST               ('character', 'return')
              264  BUILD_CONST_KEY_MAP_2     2 
              266  LOAD_CODE                <code_object is_latin>
              268  LOAD_STR                 'is_latin'
              270  MAKE_FUNCTION_4          'annotation'
              272  CALL_FUNCTION_1       1  ''
              274  STORE_NAME               is_latin

 L.  67       276  LOAD_NAME                lru_cache
              278  LOAD_NAME                UTF8_MAXIMAL_ALLOCATION
              280  LOAD_CONST               ('maxsize',)
              282  CALL_FUNCTION_KW_1     1  '1 total positional and keyword args'

 L.  68       284  LOAD_NAME                str
              286  LOAD_NAME                bool
              288  LOAD_CONST               ('character', 'return')
              290  BUILD_CONST_KEY_MAP_2     2 
              292  LOAD_CODE                <code_object is_punctuation>
              294  LOAD_STR                 'is_punctuation'
              296  MAKE_FUNCTION_4          'annotation'
              298  CALL_FUNCTION_1       1  ''
              300  STORE_NAME               is_punctuation

 L.  82       302  LOAD_NAME                lru_cache
              304  LOAD_NAME                UTF8_MAXIMAL_ALLOCATION
              306  LOAD_CONST               ('maxsize',)
              308  CALL_FUNCTION_KW_1     1  '1 total positional and keyword args'

 L.  83       310  LOAD_NAME                str
              312  LOAD_NAME                bool
              314  LOAD_CONST               ('character', 'return')
              316  BUILD_CONST_KEY_MAP_2     2 
              318  LOAD_CODE                <code_object is_symbol>
              320  LOAD_STR                 'is_symbol'
              322  MAKE_FUNCTION_4          'annotation'
              324  CALL_FUNCTION_1       1  ''
              326  STORE_NAME               is_symbol

 L.  97       328  LOAD_NAME                lru_cache
              330  LOAD_NAME                UTF8_MAXIMAL_ALLOCATION
              332  LOAD_CONST               ('maxsize',)
              334  CALL_FUNCTION_KW_1     1  '1 total positional and keyword args'

 L.  98       336  LOAD_NAME                str
              338  LOAD_NAME                bool
              340  LOAD_CONST               ('character', 'return')
              342  BUILD_CONST_KEY_MAP_2     2 
              344  LOAD_CODE                <code_object is_separator>
              346  LOAD_STR                 'is_separator'
              348  MAKE_FUNCTION_4          'annotation'
              350  CALL_FUNCTION_1       1  ''
              352  STORE_NAME               is_separator

 L. 107       354  LOAD_NAME                str
              356  LOAD_NAME                bool
              358  LOAD_CONST               ('character', 'return')
              360  BUILD_CONST_KEY_MAP_2     2 
              362  LOAD_CODE                <code_object is_private_use_only>
              364  LOAD_STR                 'is_private_use_only'
              366  MAKE_FUNCTION_4          'annotation'
              368  STORE_NAME               is_private_use_only

 L. 113       370  LOAD_NAME                str
              372  LOAD_NAME                bool
              374  LOAD_CONST               ('character', 'return')
              376  BUILD_CONST_KEY_MAP_2     2 
              378  LOAD_CODE                <code_object is_cjk>
              380  LOAD_STR                 'is_cjk'
              382  MAKE_FUNCTION_4          'annotation'
              384  STORE_NAME               is_cjk

 L. 122       386  LOAD_NAME                lru_cache
              388  LOAD_NAME                len
              390  LOAD_NAME                UNICODE_RANGES_COMBINED
              392  CALL_FUNCTION_1       1  ''
              394  LOAD_CONST               ('maxsize',)
              396  CALL_FUNCTION_KW_1     1  '1 total positional and keyword args'

 L. 123       398  LOAD_NAME                str
              400  LOAD_NAME                bool
              402  LOAD_CONST               ('range_name', 'return')
              404  BUILD_CONST_KEY_MAP_2     2 
              406  LOAD_CODE                <code_object is_unicode_range_secondary>
              408  LOAD_STR                 'is_unicode_range_secondary'
              410  MAKE_FUNCTION_4          'annotation'
              412  CALL_FUNCTION_1       1  ''
              414  STORE_NAME               is_unicode_range_secondary

 L. 131       416  LOAD_CONST               (4096,)
              418  LOAD_NAME                bytes
              420  LOAD_NAME                int
              422  LOAD_NAME                Optional
              424  LOAD_NAME                str
              426  BINARY_SUBSCR    
              428  LOAD_CONST               ('sequence', 'search_zone', 'return')
              430  BUILD_CONST_KEY_MAP_3     3 
              432  LOAD_CODE                <code_object any_specified_encoding>
              434  LOAD_STR                 'any_specified_encoding'
              436  MAKE_FUNCTION_5          'default, annotation'
              438  STORE_NAME               any_specified_encoding

 L. 160       440  LOAD_NAME                lru_cache
              442  LOAD_CONST               128
              444  LOAD_CONST               ('maxsize',)
              446  CALL_FUNCTION_KW_1     1  '1 total positional and keyword args'

 L. 161       448  LOAD_NAME                str
              450  LOAD_NAME                bool
              452  LOAD_CONST               ('name', 'return')
              454  BUILD_CONST_KEY_MAP_2     2 
              456  LOAD_CODE                <code_object is_multi_byte_encoding>
              458  LOAD_STR                 'is_multi_byte_encoding'
              460  MAKE_FUNCTION_4          'annotation'
              462  CALL_FUNCTION_1       1  ''
              464  STORE_NAME               is_multi_byte_encoding

 L. 171       466  LOAD_NAME                bytes
              468  LOAD_NAME                Tuple
              470  LOAD_NAME                Optional
              472  LOAD_NAME                str
              474  BINARY_SUBSCR    
              476  LOAD_NAME                bytes
              478  BUILD_TUPLE_2         2 
              480  BINARY_SUBSCR    
              482  LOAD_CONST               ('sequence', 'return')
              484  BUILD_CONST_KEY_MAP_2     2 
              486  LOAD_CODE                <code_object identify_sig_or_bom>
              488  LOAD_STR                 'identify_sig_or_bom'
              490  MAKE_FUNCTION_4          'annotation'
              492  STORE_NAME               identify_sig_or_bom

 L. 189       494  LOAD_NAME                str
              496  LOAD_NAME                bool
              498  LOAD_CONST               ('iana_encoding', 'return')
              500  BUILD_CONST_KEY_MAP_2     2 
              502  LOAD_CODE                <code_object should_strip_sig_or_bom>
              504  LOAD_STR                 'should_strip_sig_or_bom'
              506  MAKE_FUNCTION_4          'annotation'
              508  STORE_NAME               should_strip_sig_or_bom

 L. 193       510  LOAD_CONST               (True,)
              512  LOAD_NAME                str
              514  LOAD_NAME                bool
              516  LOAD_NAME                str
              518  LOAD_CONST               ('cp_name', 'strict', 'return')
              520  BUILD_CONST_KEY_MAP_3     3 
              522  LOAD_CODE                <code_object iana_name>
              524  LOAD_STR                 'iana_name'
              526  MAKE_FUNCTION_5          'default, annotation'
              528  STORE_NAME               iana_name

 L. 206       530  LOAD_NAME                str
              532  LOAD_NAME                List
              534  LOAD_NAME                str
              536  BINARY_SUBSCR    
              538  LOAD_CONST               ('decoded_sequence', 'return')
              540  BUILD_CONST_KEY_MAP_2     2 
              542  LOAD_CODE                <code_object range_scan>
              544  LOAD_STR                 'range_scan'
              546  MAKE_FUNCTION_4          'annotation'
              548  STORE_NAME               range_scan

 L. 222       550  LOAD_NAME                str
              552  LOAD_NAME                str
              554  LOAD_NAME                float
              556  LOAD_CONST               ('iana_name_a', 'iana_name_b', 'return')
              558  BUILD_CONST_KEY_MAP_3     3 
              560  LOAD_CODE                <code_object cp_similarity>
              562  LOAD_STR                 'cp_similarity'
              564  MAKE_FUNCTION_4          'annotation'
              566  STORE_NAME               cp_similarity

 L. 243       568  LOAD_NAME                str
              570  LOAD_NAME                str
              572  LOAD_NAME                bool
              574  LOAD_CONST               ('iana_name_a', 'iana_name_b', 'return')
              576  BUILD_CONST_KEY_MAP_3     3 
              578  LOAD_CODE                <code_object is_cp_similar>
              580  LOAD_STR                 'is_cp_similar'
              582  MAKE_FUNCTION_4          'annotation'
              584  STORE_NAME               is_cp_similar

Parse error at or near `<121>' instruction at offset 18

Instruction context:
   
 L.   3        14  DUP_TOP          
                  16  LOAD_NAME                ImportError
->                18  <121>                38  ''
                  20  POP_TOP          
                  22  POP_TOP          
                  24  POP_TOP          

test/39603.pyc -- 
# decompile failed
