
# file test/39662.pyc
# --- This code section failed: ---

 L.   1         0  LOAD_STR                 'HTTP/1.1 client library\n\n<intro stuff goes here>\n<other stuff, too>\n\nHTTPConnection goes through a number of "states", which define when a client\nmay legally make another request or fetch the response for a particular\nrequest. This diagram details these state transitions:\n\n    (null)\n      |\n      | HTTPConnection()\n      v\n    Idle\n      |\n      | putrequest()\n      v\n    Request-started\n      |\n      | ( putheader() )*  endheaders()\n      v\n    Request-sent\n      |\\_____________________________\n      |                              | getresponse() raises\n      | response = getresponse()     | ConnectionError\n      v                              v\n    Unread-response                Idle\n    [Response-headers-read]\n      |\\____________________\n      |                     |\n      | response.read()     | putrequest()\n      v                     v\n    Idle                  Req-started-unread-response\n                     ______/|\n                   /        |\n   response.read() |        | ( putheader() )*  endheaders()\n                   v        v\n       Request-started    Req-sent-unread-response\n                            |\n                            | response.read()\n                            v\n                          Request-sent\n\nThis diagram presents the following rules:\n  -- a second request may not be started until {response-headers-read}\n  -- a response [object] cannot be retrieved until {request-sent}\n  -- there is no differentiation between an unread response body and a\n     partially read response body\n\nNote: this enforcement is applied by the HTTPConnection class. The\n      HTTPResponse class does not enforce this state machine, which\n      implies sophisticated clients may accelerate the request/response\n      pipeline. Caution should be taken, though: accelerating the states\n      beyond the above pattern may imply knowledge of the server\'s\n      connection-close behavior for certain requests. For example, it\n      is impossible to tell whether the server will close the connection\n      UNTIL the response headers have been read; this means that further\n      requests cannot be placed into the pipeline until it is known that\n      the server will NOT be closing the connection.\n\nLogical State                  __state            __response\n-------------                  -------            ----------\nIdle                           _CS_IDLE           None\nRequest-started                _CS_REQ_STARTED    None\nRequest-sent                   _CS_REQ_SENT       None\nUnread-response                _CS_IDLE           <response_class>\nReq-started-unread-response    _CS_REQ_STARTED    <response_class>\nReq-sent-unread-response       _CS_REQ_SENT       <response_class>\n'
                2  STORE_NAME               __doc__

 L.  71         4  LOAD_CONST               0
                6  LOAD_CONST               None
                8  IMPORT_NAME_ATTR         email.parser
               10  STORE_NAME               email

 L.  72        12  LOAD_CONST               0
               14  LOAD_CONST               None
               16  IMPORT_NAME_ATTR         email.message
               18  STORE_NAME               email

 L.  73        20  LOAD_CONST               0
               22  LOAD_CONST               None
               24  IMPORT_NAME              http
               26  STORE_NAME               http

 L.  74        28  LOAD_CONST               0
               30  LOAD_CONST               None
               32  IMPORT_NAME              io
               34  STORE_NAME               io

 L.  75        36  LOAD_CONST               0
               38  LOAD_CONST               None
               40  IMPORT_NAME              re
               42  STORE_NAME               re

 L.  76        44  LOAD_CONST               0
               46  LOAD_CONST               None
               48  IMPORT_NAME              socket
               50  STORE_NAME               socket

 L.  77        52  LOAD_CONST               0
               54  LOAD_CONST               None
               56  IMPORT_NAME_ATTR         collections.abc
               58  STORE_NAME               collections

 L.  78        60  LOAD_CONST               0
               62  LOAD_CONST               ('urlsplit',)
               64  IMPORT_NAME_ATTR         urllib.parse
               66  IMPORT_FROM              urlsplit
               68  STORE_NAME               urlsplit
               70  POP_TOP          

 L.  82        72  BUILD_LIST_0          0 
               74  LOAD_CONST               ('HTTPResponse', 'HTTPConnection', 'HTTPException', 'NotConnected', 'UnknownProtocol', 'UnknownTransferEncoding', 'UnimplementedFileMode', 'IncompleteRead', 'InvalidURL', 'ImproperConnectionState', 'CannotSendRequest', 'CannotSendHeader', 'ResponseNotReady', 'BadStatusLine', 'LineTooLong', 'RemoteDisconnected', 'error', 'responses')
               76  CALL_FINALLY         79  'to 79'
               78  STORE_NAME               __all__

 L.  90        80  LOAD_CONST               80
               82  STORE_NAME               HTTP_PORT

 L.  91        84  LOAD_CONST               443
               86  STORE_NAME               HTTPS_PORT

 L.  93        88  LOAD_STR                 'UNKNOWN'
               90  STORE_NAME               _UNKNOWN

 L.  96        92  LOAD_STR                 'Idle'
               94  STORE_NAME               _CS_IDLE

 L.  97        96  LOAD_STR                 'Request-started'
               98  STORE_NAME               _CS_REQ_STARTED

 L.  98       100  LOAD_STR                 'Request-sent'
              102  STORE_NAME               _CS_REQ_SENT

 L. 102       104  LOAD_NAME                globals
              106  CALL_FUNCTION_0       0  ''
              108  LOAD_METHOD              update
              110  LOAD_NAME                http
              112  LOAD_ATTR                HTTPStatus
              114  LOAD_ATTR                __members__
              116  CALL_METHOD_1         1  ''
              118  POP_TOP          

 L. 106       120  LOAD_DICTCOMP            '<code_object <dictcomp>>'
              122  LOAD_STR                 '<dictcomp>'
              124  MAKE_FUNCTION_0          'Neither defaults, keyword-only args, annotations, nor closures'
              126  LOAD_NAME                http
              128  LOAD_ATTR                HTTPStatus
              130  LOAD_ATTR                __members__
              132  LOAD_METHOD              values
              134  CALL_METHOD_0         0  ''
              136  GET_ITER         
              138  CALL_FUNCTION_1       1  ''
              140  STORE_NAME               responses

 L. 109       142  LOAD_CONST               65536
              144  STORE_NAME               _MAXLINE

 L. 110       146  LOAD_CONST               100
              148  STORE_NAME               _MAXHEADERS

 L. 137       150  LOAD_NAME                re
              152  LOAD_METHOD              compile
              154  LOAD_CONST               b'[^:\\s][^:\\r\\n]*'
              156  CALL_METHOD_1         1  ''
              158  LOAD_ATTR                fullmatch
              160  STORE_NAME               _is_legal_header_name

 L. 138       162  LOAD_NAME                re
              164  LOAD_METHOD              compile
              166  LOAD_CONST               b'\\n(?![ \\t])|\\r(?![ \\t\\n])'
              168  CALL_METHOD_1         1  ''
              170  LOAD_ATTR                search
              172  STORE_NAME               _is_illegal_header_value

 L. 145       174  LOAD_NAME                re
              176  LOAD_METHOD              compile
              178  LOAD_STR                 '[\x00- \x7f]'
              180  CALL_METHOD_1         1  ''
              182  STORE_NAME               _contains_disallowed_url_pchar_re

 L. 152       184  LOAD_NAME                re
              186  LOAD_METHOD              compile
              188  LOAD_STR                 '[\x00-\x1f]'
              190  CALL_METHOD_1         1  ''
              192  STORE_NAME               _contains_disallowed_method_pchar_re

 L. 156       194  BUILD_SET_0           0 
              196  LOAD_CONST               frozenset({'POST', 'PUT', 'PATCH'})
              198  POP_FINALLY           1  ''
              200  STORE_NAME               _METHODS_EXPECTING_BODY

 L. 159       202  LOAD_CONST               ('data',)
              204  LOAD_CODE                <code_object _encode>
              206  LOAD_STR                 '_encode'
              208  MAKE_FUNCTION_1          'default'
              210  STORE_NAME               _encode

 L. 174       212  LOAD_BUILD_CLASS 
              214  LOAD_CODE                <code_object HTTPMessage>
              216  LOAD_STR                 'HTTPMessage'
              218  MAKE_FUNCTION_0          'Neither defaults, keyword-only args, annotations, nor closures'
              220  LOAD_STR                 'HTTPMessage'
              222  LOAD_NAME                email
              224  LOAD_ATTR                message
              226  LOAD_ATTR                Message
              228  CALL_FUNCTION_3       3  ''
              230  STORE_NAME               HTTPMessage

 L. 204       232  LOAD_CODE                <code_object _read_headers>
              234  LOAD_STR                 '_read_headers'
              236  MAKE_FUNCTION_0          'Neither defaults, keyword-only args, annotations, nor closures'
              238  STORE_NAME               _read_headers

 L. 222       240  LOAD_NAME                HTTPMessage
              242  BUILD_TUPLE_1         1 
              244  LOAD_CODE                <code_object parse_headers>
              246  LOAD_STR                 'parse_headers'
              248  MAKE_FUNCTION_1          'default'
              250  STORE_NAME               parse_headers

 L. 237       252  LOAD_BUILD_CLASS 
              254  LOAD_CODE                <code_object HTTPResponse>
              256  LOAD_STR                 'HTTPResponse'
              258  MAKE_FUNCTION_0          'Neither defaults, keyword-only args, annotations, nor closures'
              260  LOAD_STR                 'HTTPResponse'
              262  LOAD_NAME                io
              264  LOAD_ATTR                BufferedIOBase
              266  CALL_FUNCTION_3       3  ''
              268  STORE_NAME               HTTPResponse

 L. 772       270  LOAD_BUILD_CLASS 
              272  LOAD_CODE                <code_object HTTPConnection>
              274  LOAD_STR                 'HTTPConnection'
              276  MAKE_FUNCTION_0          'Neither defaults, keyword-only args, annotations, nor closures'
              278  LOAD_STR                 'HTTPConnection'
              280  CALL_FUNCTION_2       2  ''
              282  STORE_NAME               HTTPConnection

 L.1368       284  SETUP_FINALLY       298  'to 298'

 L.1369       286  LOAD_CONST               0
              288  LOAD_CONST               None
              290  IMPORT_NAME              ssl
              292  STORE_NAME               ssl
              294  POP_BLOCK        
              296  JUMP_FORWARD        318  'to 318'
            298_0  COME_FROM_FINALLY   284  '284'

 L.1370       298  DUP_TOP          
              300  LOAD_NAME                ImportError
          302_304  <121>               316  ''
              306  POP_TOP          
              308  POP_TOP          
              310  POP_TOP          

 L.1371       312  POP_EXCEPT       
              314  JUMP_FORWARD        344  'to 344'
              316  <48>             
            318_0  COME_FROM           296  '296'

 L.1373       318  LOAD_BUILD_CLASS 
              320  LOAD_CODE                <code_object HTTPSConnection>
              322  LOAD_STR                 'HTTPSConnection'
              324  MAKE_FUNCTION_0          'Neither defaults, keyword-only args, annotations, nor closures'
              326  LOAD_STR                 'HTTPSConnection'
              328  LOAD_NAME                HTTPConnection
              330  CALL_FUNCTION_3       3  ''
              332  STORE_NAME               HTTPSConnection

 L.1429       334  LOAD_NAME                __all__
              336  LOAD_METHOD              append
              338  LOAD_STR                 'HTTPSConnection'
              340  CALL_METHOD_1         1  ''
              342  POP_TOP          
            344_0  COME_FROM           314  '314'

 L.1431       344  LOAD_BUILD_CLASS 
              346  LOAD_CODE                <code_object HTTPException>
              348  LOAD_STR                 'HTTPException'
              350  MAKE_FUNCTION_0          'Neither defaults, keyword-only args, annotations, nor closures'
              352  LOAD_STR                 'HTTPException'
              354  LOAD_NAME                Exception
              356  CALL_FUNCTION_3       3  ''
              358  STORE_NAME               HTTPException

 L.1436       360  LOAD_BUILD_CLASS 
              362  LOAD_CODE                <code_object NotConnected>
              364  LOAD_STR                 'NotConnected'
              366  MAKE_FUNCTION_0          'Neither defaults, keyword-only args, annotations, nor closures'
              368  LOAD_STR                 'NotConnected'
              370  LOAD_NAME                HTTPException
              372  CALL_FUNCTION_3       3  ''
              374  STORE_NAME               NotConnected

 L.1439       376  LOAD_BUILD_CLASS 
              378  LOAD_CODE                <code_object InvalidURL>
              380  LOAD_STR                 'InvalidURL'
              382  MAKE_FUNCTION_0          'Neither defaults, keyword-only args, annotations, nor closures'
              384  LOAD_STR                 'InvalidURL'
              386  LOAD_NAME                HTTPException
              388  CALL_FUNCTION_3       3  ''
              390  STORE_NAME               InvalidURL

 L.1442       392  LOAD_BUILD_CLASS 
              394  LOAD_CODE                <code_object UnknownProtocol>
              396  LOAD_STR                 'UnknownProtocol'
              398  MAKE_FUNCTION_0          'Neither defaults, keyword-only args, annotations, nor closures'
              400  LOAD_STR                 'UnknownProtocol'
              402  LOAD_NAME                HTTPException
              404  CALL_FUNCTION_3       3  ''
              406  STORE_NAME               UnknownProtocol

 L.1447       408  LOAD_BUILD_CLASS 
              410  LOAD_CODE                <code_object UnknownTransferEncoding>
              412  LOAD_STR                 'UnknownTransferEncoding'
              414  MAKE_FUNCTION_0          'Neither defaults, keyword-only args, annotations, nor closures'
              416  LOAD_STR                 'UnknownTransferEncoding'
              418  LOAD_NAME                HTTPException
              420  CALL_FUNCTION_3       3  ''
              422  STORE_NAME               UnknownTransferEncoding

 L.1450       424  LOAD_BUILD_CLASS 
              426  LOAD_CODE                <code_object UnimplementedFileMode>
              428  LOAD_STR                 'UnimplementedFileMode'
              430  MAKE_FUNCTION_0          'Neither defaults, keyword-only args, annotations, nor closures'
              432  LOAD_STR                 'UnimplementedFileMode'
              434  LOAD_NAME                HTTPException
              436  CALL_FUNCTION_3       3  ''
              438  STORE_NAME               UnimplementedFileMode

 L.1453       440  LOAD_BUILD_CLASS 
              442  LOAD_CODE                <code_object IncompleteRead>
              444  LOAD_STR                 'IncompleteRead'
              446  MAKE_FUNCTION_0          'Neither defaults, keyword-only args, annotations, nor closures'
              448  LOAD_STR                 'IncompleteRead'
              450  LOAD_NAME                HTTPException
              452  CALL_FUNCTION_3       3  ''
              454  STORE_NAME               IncompleteRead

 L.1467       456  LOAD_BUILD_CLASS 
              458  LOAD_CODE                <code_object ImproperConnectionState>
              460  LOAD_STR                 'ImproperConnectionState'
              462  MAKE_FUNCTION_0          'Neither defaults, keyword-only args, annotations, nor closures'
              464  LOAD_STR                 'ImproperConnectionState'
              466  LOAD_NAME                HTTPException
              468  CALL_FUNCTION_3       3  ''
              470  STORE_NAME               ImproperConnectionState

 L.1470       472  LOAD_BUILD_CLASS 
              474  LOAD_CODE                <code_object CannotSendRequest>
              476  LOAD_STR                 'CannotSendRequest'
              478  MAKE_FUNCTION_0          'Neither defaults, keyword-only args, annotations, nor closures'
              480  LOAD_STR                 'CannotSendRequest'
              482  LOAD_NAME                ImproperConnectionState
              484  CALL_FUNCTION_3       3  ''
              486  STORE_NAME               CannotSendRequest

 L.1473       488  LOAD_BUILD_CLASS 
              490  LOAD_CODE                <code_object CannotSendHeader>
              492  LOAD_STR                 'CannotSendHeader'
              494  MAKE_FUNCTION_0          'Neither defaults, keyword-only args, annotations, nor closures'
              496  LOAD_STR                 'CannotSendHeader'
              498  LOAD_NAME                ImproperConnectionState
              500  CALL_FUNCTION_3       3  ''
              502  STORE_NAME               CannotSendHeader

 L.1476       504  LOAD_BUILD_CLASS 
              506  LOAD_CODE                <code_object ResponseNotReady>
              508  LOAD_STR                 'ResponseNotReady'
              510  MAKE_FUNCTION_0          'Neither defaults, keyword-only args, annotations, nor closures'
              512  LOAD_STR                 'ResponseNotReady'
              514  LOAD_NAME                ImproperConnectionState
              516  CALL_FUNCTION_3       3  ''
              518  STORE_NAME               ResponseNotReady

 L.1479       520  LOAD_BUILD_CLASS 
              522  LOAD_CODE                <code_object BadStatusLine>
              524  LOAD_STR                 'BadStatusLine'
              526  MAKE_FUNCTION_0          'Neither defaults, keyword-only args, annotations, nor closures'
              528  LOAD_STR                 'BadStatusLine'
              530  LOAD_NAME                HTTPException
              532  CALL_FUNCTION_3       3  ''
              534  STORE_NAME               BadStatusLine

 L.1486       536  LOAD_BUILD_CLASS 
              538  LOAD_CODE                <code_object LineTooLong>
              540  LOAD_STR                 'LineTooLong'
              542  MAKE_FUNCTION_0          'Neither defaults, keyword-only args, annotations, nor closures'
              544  LOAD_STR                 'LineTooLong'
              546  LOAD_NAME                HTTPException
              548  CALL_FUNCTION_3       3  ''
              550  STORE_NAME               LineTooLong

 L.1491       552  LOAD_BUILD_CLASS 
              554  LOAD_CODE                <code_object RemoteDisconnected>
              556  LOAD_STR                 'RemoteDisconnected'
              558  MAKE_FUNCTION_0          'Neither defaults, keyword-only args, annotations, nor closures'
              560  LOAD_STR                 'RemoteDisconnected'
              562  LOAD_NAME                ConnectionResetError
              564  LOAD_NAME                BadStatusLine
              566  CALL_FUNCTION_4       4  ''
              568  STORE_NAME               RemoteDisconnected

 L.1497       570  LOAD_NAME                HTTPException
              572  STORE_NAME               error

Parse error at or near `CALL_FINALLY' instruction at offset 76

Instruction context:
   
 L.  82        72  BUILD_LIST_0          0 
                  74  LOAD_CONST               ('HTTPResponse', 'HTTPConnection', 'HTTPException', 'NotConnected', 'UnknownProtocol', 'UnknownTransferEncoding', 'UnimplementedFileMode', 'IncompleteRead', 'InvalidURL', 'ImproperConnectionState', 'CannotSendRequest', 'CannotSendHeader', 'ResponseNotReady', 'BadStatusLine', 'LineTooLong', 'RemoteDisconnected', 'error', 'responses')
->                76  CALL_FINALLY         79  'to 79'
                  78  STORE_NAME               __all__

test/39662.pyc -- 
# decompile failed
